Workbook
Name Actual_month: General!$B$3

Sheet Distribution Dashboard
A1: NAIVAWASS DISTRIBUTION DASHBOARD - NON-REVENUE WATER & ZONAL PERFORMANCE
B2: =INDEX('KPI 100'!E$18:P$18,Actual_month) -> 46054
D3: Monthly | J3: Cumulative | R3: 0.9
C4: Unit | G4: Target | H4: Actual | I4: % real. | M4: Target | N4: Actual | O4: % real.
A5: GLOBAL PERFORMNCE
B6: REGIONAL NRW | Q6: month | R6: cum
A7: 100 | B7: WATER AVAILABLE FOR SALES- REGIONS | C7: m3 | D7: l | E7: l | F7: l | G7: =IFERROR(INDEX('KPI 100'!E$19:P$19,Actual_month),0) -> 230597.54 | H7: =IFERROR(INDEX('KPI 100'!E$20:P$20,Actual_month),0) -> 222543 | I7: =IFERROR(H7/G7,"") -> 0.96507099 | J7: l | K7: l | L7: l | M7: =IFERROR(INDEX('KPI 100'!E$26:P$26,Actual_month),0) -> 1776711.4 | N7: =IFERROR(INDEX('KPI 100'!E$27:P$27,Actual_month),0) -> 1717654 | O7: =IFERROR(N7/M7,"") -> 0.96676025 | P7: details | Q7: =G7*$R$3 -> 207537.79 | R7: =M7*$R$3 -> 1599040.3 | S7: H | U7: V
A8: 128a | B8: VOLUME WATER BILLED(CUSTOMERS-M3) | C8: m3 | D8: l | E8: l | F8: l | G8: =IFERROR(INDEX('KPI 128a'!E$19:P$19,Actual_month),0) -> 183888.91 | H8: =IFERROR(INDEX('KPI 128a'!E$20:P$20,Actual_month),0) -> 172266 | I8: =IFERROR(H8/G8,"") -> 0.93679384 | J8: l | K8: l | L8: l | M8: =IFERROR(INDEX('KPI 128a'!E$26:P$26,Actual_month),0) -> 1382493.7 | N8: =IFERROR(INDEX('KPI 128a'!E$27:P$27,Actual_month),0) -> 1275843 | O8: =IFERROR(N8/M8,"") -> 0.92285629 | P8: details | Q8: =G8*$R$3 -> 165500.02 | R8: =M8*$R$3 -> 1244244.3 | S8: H | U8: V
A9: 128 | B9: GLOBAL NRW | C9: % | D9: l | E9: l | F9: l | G9: =IFERROR(INDEX('KPI 128'!E$19:P$19,Actual_month),0) -> 0.20255476 | H9: =IFERROR(INDEX('KPI 128'!E$20:P$20,Actual_month),0) -> 0.22592038 | I9: =IFERROR(G9/H9,"") -> 0.89657587 | J9: l | K9: l | L9: l | M9: =IFERROR(INDEX('KPI 128'!E$26:P$26,Actual_month),0) -> 0.22188057 | N9: =IFERROR(INDEX('KPI 128'!E$27:P$27,Actual_month),0) -> 0.25721769 | O9: =IFERROR(M9/N9,"") -> 0.86261784 | P9: details | Q9: =G9/$R$3 -> 0.22506085 | R9: =M9/$R$3 -> 0.24653397 | S9: L | U9: V
B10: Number of Active water Connections | C10: NO. | D10: l | E10: l | F10: l | G10: =IFERROR(INDEX(#REF!,Actual_month),0) -> 0 | H10: =IFERROR(INDEX(#REF!,Actual_month),0) -> 0 | I10: =IFERROR(H10/G10,"") | J10: l | K10: l | L10: l | M10: =IFERROR(INDEX(#REF!,Actual_month),0) -> 0 | N10: =IFERROR(INDEX(#REF!,Actual_month),0) -> 0 | O10: =IFERROR(N10/M10,"") | P10: details | Q10: =G10*$R$3 -> 0 | R10: =M10*$R$3 -> 0 | S10: H | U10: V
B11: Number of Active sewer Connections | C11: NO. | D11: l | E11: l | F11: l | G11: =IFERROR(INDEX(#REF!,Actual_month),0) -> 0 | H11: =IFERROR(INDEX(#REF!,Actual_month),0) -> 0 | I11: =IFERROR(H11/G11,"") | J11: l | K11: l | L11: l | M11: =IFERROR(INDEX(#REF!,Actual_month),0) -> 0 | N11: =IFERROR(INDEX(#REF!,Actual_month),0) -> 0 | O11: =IFERROR(N11/M11,"") | P11: details | Q11: =G11*$R$3 -> 0 | R11: =M11*$R$3 -> 0 | S11: H | U11: V
B12: Number of In-active Sewer Connections | C12: NO. | D12: l | E12: l | F12: l | G12: =IFERROR(INDEX(#REF!,Actual_month),0) -> 0 | H12: =IFERROR(INDEX(#REF!,Actual_month),0) -> 0 | I12: =IFERROR(H12/G12,"") | J12: l | K12: l | L12: l | M12: =IFERROR(INDEX(#REF!,Actual_month),0) -> 0 | N12: =IFERROR(INDEX(#REF!,Actual_month),0) -> 0 | O12: =IFERROR(N12/M12,"") | P12: details | Q12: =G12/$R$3 -> 0 | R12: =M12/$R$3 -> 0 | S12: L | U12: V
B13: Number of In-active Water Connections | C13: NO. | D13: l | E13: l | F13: l | G13: =IFERROR(INDEX(#REF!,Actual_month),0) -> 0 | H13: =IFERROR(INDEX(#REF!,Actual_month),0) -> 0 | I13: =IFERROR(H13/G13,"") | J13: l | K13: l | L13: l | M13: =IFERROR(INDEX(#REF!,Actual_month),0) -> 0 | N13: =IFERROR(INDEX(#REF!,Actual_month),0) -> 0 | O13: =IFERROR(N13/M13,"") | P13: details | Q13: =G13/$R$3 -> 0 | R13: =M13/$R$3 -> 0 | S13: L | U13: V
B14: Number of Connections | C14: NO. | D14: l | E14: l | F14: l | G14: =IFERROR(INDEX(#REF!,Actual_month),0) -> 0 | H14: =IFERROR(INDEX(#REF!,Actual_month),0) -> 0 | I14: =IFERROR(H14/G14,"") | J14: l | K14: l | L14: l | M14: =IFERROR(INDEX(#REF!,Actual_month),0) -> 0 | N14: =IFERROR(INDEX(#REF!,Actual_month),0) -> 0 | O14: =IFERROR(N14/M14,"") | P14: details | Q14: =G14*$R$3 -> 0 | R14: =M14*$R$3 -> 0 | S14: H | U14: V
B15: Maintenance, repair and operational cost | C15: KES | D15: l | E15: l | F15: l | G15: =IFERROR(INDEX(#REF!,Actual_month),0) -> 0 | H15: =IFERROR(INDEX(#REF!,Actual_month),0) -> 0 | I15: =IFERROR(G15/H15,"") | J15: l | K15: l | L15: l | M15: =IFERROR(INDEX(#REF!,Actual_month),0) -> 0 | N15: =IFERROR(INDEX(#REF!,Actual_month),0) -> 0 | O15: =IFERROR(M15/N15,"") | P15: details | Q15: =G15/$R$3 -> 0 | R15: =M15/$R$3 -> 0 | S15: L | U15: V
B16: CENTRAL REGION: CBD,CCCR,KABATI,SITE,KIHOTO,LAKEVIEW | Q16: month | R16: cum
A17: RA | B17: Volume Water Supplied | C17: m3 | D17: l | E17: l | F17: l | G17: =IFERROR(INDEX('KPI RA'!E$19:P$19,Actual_month),0) -> 103813.31 | H17: =IFERROR(INDEX('KPI RA'!E$20:P$20,Actual_month),0) -> 101836 | I17: =IFERROR(H17/G17,"") -> 0.98095318 | J17: l | K17: l | L17: l | M17: =IFERROR(INDEX('KPI RA'!E$26:P$26,Actual_month),0) -> 836353.87 | N17: =IFERROR(INDEX('KPI RA'!E$27:P$27,Actual_month),0) -> 820288 | O17: =IFERROR(N17/M17,"") -> 0.98079058 | P17: details | Q17: =G17*$R$3 -> 93431.982 | R17: =M17*$R$3 -> 752718.48 | S17: H | U17: V
A18: RA2 | B18: Volume Water Sold | C18: m3 | D18: l | E18: l | F18: l | G18: =IFERROR(INDEX('KPI RA2'!E$19:P$19,Actual_month),0) -> 87853.153 | H18: =IFERROR(INDEX('KPI RA2'!E$20:P$20,Actual_month),0) -> 83599 | I18: =IFERROR(H18/G18,"") -> 0.95157655 | J18: l | K18: l | L18: l | M18: =IFERROR(INDEX('KPI RA2'!E$26:P$26,Actual_month),0) -> 689333.08 | N18: =IFERROR(INDEX('KPI RA2'!E$27:P$27,Actual_month),0) -> 647518 | O18: =IFERROR(N18/M18,"") -> 0.9393398 | P18: details | Q18: =G18*$R$3 -> 79067.838 | R18: =M18*$R$3 -> 620399.77 | S18: H | U18: V
A19: RA3 | B19: NRW | C19: m3 | D19: l | E19: l | F19: l | G19: =IFERROR(INDEX('KPI RA3'!E$19:P$19,Actual_month),0) -> 15960.161 | H19: =IFERROR(INDEX('KPI RA3'!E$20:P$20,Actual_month),0) -> 18237 | I19: =IFERROR(G19/H19,"") -> 0.87515274 | J19: l | K19: l | L19: l | M19: =IFERROR(INDEX('KPI RA3'!E$26:P$26,Actual_month),0) -> 147020.79 | N19: =IFERROR(INDEX('KPI RA3'!E$27:P$27,Actual_month),0) -> 172770 | O19: =IFERROR(M19/N19,"") -> 0.8509625 | P19: details | Q19: =G19/$R$3 -> 17733.512 | R19: =M19/$R$3 -> 163356.43 | S19: L | U19: V
A20: RA4 | B20: NRW | C20: % | D20: l | E20: l | F20: l | G20: =IFERROR(INDEX('KPI RA4'!E$19:P$19,Actual_month),0) -> 0.15373905 | H20: =IFERROR(INDEX('KPI RA4'!E$20:P$20,Actual_month),0) -> 0.17908205 | I20: =IFERROR(G20/H20,"") -> 0.85848386 | J20: l | K20: l | L20: l | M20: =IFERROR(INDEX('KPI RA4'!E$26:P$26,Actual_month),0) -> 0.17578778 | N20: =IFERROR(INDEX('KPI RA4'!E$27:P$27,Actual_month),0) -> 0.21062115 | O20: =IFERROR(M20/N20,"") -> 0.834616 | P20: details | Q20: =G20/$R$3 -> 0.17082117 | R20: =M20/$R$3 -> 0.19531976 | S20: L | U20: V
B21: Amount Billed Water | C21: KES | D21: l | E21: l | F21: l | G21: =IFERROR(INDEX(#REF!,Actual_month),0) -> 0 | H21: =IFERROR(INDEX(#REF!,Actual_month),0) -> 0 | I21: =IFERROR(H21/G21,"") | J21: l | K21: l | L21: l | M21: =IFERROR(INDEX(#REF!,Actual_month),0) -> 0 | N21: =IFERROR(INDEX(#REF!,Actual_month),0) -> 0 | O21: =IFERROR(N21/M21,"") | P21: details | Q21: =G21*$R$3 -> 0 | R21: =M21*$R$3 -> 0 | S21: H | U21: V
B22: Amount Billed Sewer | C22: KES | D22: l | E22: l | F22: l | G22: =IFERROR(INDEX(#REF!,Actual_month),0) -> 0 | H22: =IFERROR(INDEX(#REF!,Actual_month),0) -> 0 | I22: =IFERROR(H22/G22,"") | J22: l | K22: l | L22: l | M22: =IFERROR(INDEX(#REF!,Actual_month),0) -> 0 | N22: =IFERROR(INDEX(#REF!,Actual_month),0) -> 0 | O22: =IFERROR(N22/M22,"") | P22: details | Q22: =G22*$R$3 -> 0 | R22: =M22*$R$3 -> 0 | S22: H | U22: V
B23: Number of Active water Connections | C23: KES | D23: l | E23: l | F23: l | G23: =IFERROR(INDEX(#REF!,Actual_month),0) -> 0 | H23: =IFERROR(INDEX(#REF!,Actual_month),0) -> 0 | I23: =IFERROR(H23/G23,"") | J23: l | K23: l | L23: l | M23: =IFERROR(INDEX(#REF!,Actual_month),0) -> 0 | N23: =IFERROR(INDEX(#REF!,Actual_month),0) -> 0 | O23: =IFERROR(N23/M23,"") | P23: details | Q23: =G23*$R$3 -> 0 | R23: =M23*$R$3 -> 0 | S23: H | U23: V
B24: Number of Active sewer Connections | C24: KES | D24: l | E24: l | F24: l | G24: =IFERROR(INDEX(#REF!,Actual_month),0) -> 0 | H24: =IFERROR(INDEX(#REF!,Actual_month),0) -> 0 | I24: =IFERROR(H24/G24,"") | J24: l | K24: l | L24: l | M24: =IFERROR(INDEX(#REF!,Actual_month),0) -> 0 | N24: =IFERROR(INDEX(#REF!,Actual_month),0) -> 0 | O24: =IFERROR(N24/M24,"") | P24: details | Q24: =G24*$R$3 -> 0 | R24: =M24*$R$3 -> 0 | S24: H | U24: V
B25: SOUTHERN REGION: MAI MAHIU,KAMERE,HELLSGATE | Q25: month | R25: cum
A26: RA6 (B) | B26: Volume Water Supplied | C26: m3 | D26: l | E26: l | F26: l | G26: =IFERROR(INDEX('KPI RA6 (B)'!E$19:P$19,Actual_month),0) -> 89353.394 | H26: =IFERROR(INDEX('KPI RA6 (B)'!E$20:P$20,Actual_month),0) -> 77635 | I26: =IFERROR(H26/G26,"") -> 0.86885339 | J26: l | K26: l | L26: l | M26: =IFERROR(INDEX('KPI RA6 (B)'!E$26:P$26,Actual_month),0) -> 649012.41 | N26: =IFERROR(INDEX('KPI RA6 (B)'!E$27:P$27,Actual_month),0) -> 576686 | O26: =IFERROR(N26/M26,"") -> 0.88855928 | P26: details | Q26: =G26*$R$3 -> 80418.055 | R26: =M26*$R$3 -> 584111.17 | S26: H | U26: V
A27: RB2 | B27: Volume Water Sold | C27: m3 | D27: l | E27: l | F27: l | G27: =IFERROR(INDEX('KPI RB2'!E$19:P$19,Actual_month),0) -> 64564.498 | H27: =IFERROR(INDEX('KPI RB2'!E$20:P$20,Actual_month),0) -> 55022 | I27: =IFERROR(H27/G27,"") -> 0.85220208 | J27: l | K27: l | L27: l | M27: =IFERROR(INDEX('KPI RB2'!E$26:P$26,Actual_month),0) -> 452009.1 | N27: =IFERROR(INDEX('KPI RB2'!E$27:P$27,Actual_month),0) -> 395248 | O27: =IFERROR(N27/M27,"") -> 0.87442488 | P27: details | Q27: =G27*$R$3 -> 58108.049 | R27: =M27*$R$3 -> 406808.19 | S27: H | U27: V
A28: RB3 (2) | B28: NRW | C28: m3 | D28: l | E28: l | F28: l | G28: =IFERROR(INDEX('KPI RB3 (2)'!E$19:P$19,Actual_month),0) -> 24788.896 | H28: =IFERROR(INDEX('KPI RB3 (2)'!E$20:P$20,Actual_month),0) -> 22613 | I28: =IFERROR(G28/H28,"") -> 1.0962232 | J28: l | K28: l | L28: l | M28: =IFERROR(INDEX('KPI RB3 (2)'!E$26:P$26,Actual_month),0) -> 197003.31 | N28: =IFERROR(INDEX('KPI RB3 (2)'!E$27:P$27,Actual_month),0) -> 181438 | O28: =IFERROR(M28/N28,"") -> 1.0857886 | P28: details | Q28: =G28/$R$3 -> 27543.218 | R28: =M28/$R$3 -> 218892.57 | S28: L | U28: V
A29: RB4 | B29: NRW | C29: % | D29: l | E29: l | F29: l | G29: =IFERROR(INDEX('KPI RB4'!E$19:P$19,Actual_month),0) -> 0.27742534 | H29: =IFERROR(INDEX('KPI RB4'!E$20:P$20,Actual_month),0) -> 0.29127327 | I29: =IFERROR(G29/H29,"") -> 0.95245728 | J29: l | K29: l | L29: l | M29: =IFERROR(INDEX('KPI RB4'!E$26:P$26,Actual_month),0) -> 0.3046841 | N29: =IFERROR(INDEX('KPI RB4'!E$27:P$27,Actual_month),0) -> 0.31392199 | O29: =IFERROR(M29/N29,"") -> 0.97057265 | P29: details | Q29: =G29/$R$3 -> 0.30825038 | R29: =M29/$R$3 -> 0.33853789 | S29: L | U29: V
B30: EASTERN REGION: KAYOLE,GONDI, KINUNGI,NJONJORO | Q30: month | R30: cum
A31: RA6 (B) (2) | B31: Volume Water Supplied | C31: m3 | D31: l | E31: l | F31: l | G31: =IFERROR(INDEX('KPI RA6 (B) (2)'!E$19:P$19,Actual_month),0) -> 37430.836 | H31: =IFERROR(INDEX('KPI RA6 (B) (2)'!E$20:P$20,Actual_month),0) -> 43072 | I31: =IFERROR(H31/G31,"") -> 1.150709 | J31: l | K31: l | L31: l | M31: =IFERROR(INDEX('KPI RA6 (B) (2)'!E$26:P$26,Actual_month),0) -> 291345.17 | N31: =IFERROR(INDEX('KPI RA6 (B) (2)'!E$27:P$27,Actual_month),0) -> 320680 | O31: =IFERROR(N31/M31,"") -> 1.1006876 | P31: details | Q31: =G31*$R$3 -> 33687.752 | R31: =M31*$R$3 -> 262210.65 | S31: H | U31: V
A32: RB2 (3) | B32: Volume Water Sold | C32: m3 | D32: l | E32: l | F32: l | G32: =IFERROR(INDEX('KPI RB2 (3)'!E$19:P$19,Actual_month),0) -> 31471.261 | H32: =IFERROR(INDEX('KPI RB2 (3)'!E$20:P$20,Actual_month),0) -> 33645 | I32: =IFERROR(H32/G32,"") -> 1.0690706 | J32: l | K32: l | L32: l | M32: =IFERROR(INDEX('KPI RB2 (3)'!E$26:P$26,Actual_month),0) -> 241151.52 | N32: =IFERROR(INDEX('KPI RB2 (3)'!E$27:P$27,Actual_month),0) -> 233077 | O32: =IFERROR(N32/M32,"") -> 0.96651682 | P32: details | Q32: =G32*$R$3 -> 28324.135 | R32: =M32*$R$3 -> 217036.37 | S32: H | U32: V
A33: RB3 (3) | B33: NRW | C33: m3 | D33: l | E33: l | F33: l | G33: =IFERROR(INDEX('KPI RB3 (3)'!E$19:P$19,Actual_month),0) -> 5959.5747 | H33: =IFERROR(INDEX('KPI RB3 (3)'!E$20:P$20,Actual_month),0) -> 9427 | I33: =IFERROR(G33/H33,"") -> 0.63218147 | J33: l | K33: l | L33: l | M33: =IFERROR(INDEX('KPI RB3 (3)'!E$26:P$26,Actual_month),0) -> 50193.646 | N33: =IFERROR(INDEX('KPI RB3 (3)'!E$27:P$27,Actual_month),0) -> 87603 | O33: =IFERROR(M33/N33,"") -> 0.5729672 | P33: details | Q33: =G33/$R$3 -> 6621.7497 | R33: =M33/$R$3 -> 55770.718 | S33: L | U33: V
A34: RB4 (2) | B34: NRW | C34: % | D34: l | E34: l | F34: l | G34: =IFERROR(INDEX('KPI RB4 (2)'!E$19:P$19,Actual_month),0) -> 0.15921565 | H34: =IFERROR(INDEX('KPI RB4 (2)'!E$20:P$20,Actual_month),0) -> 0.21886608 | I34: =IFERROR(G34/H34,"") -> 0.72745691 | J34: l | K34: l | L34: l | M34: =IFERROR(INDEX('KPI RB4 (2)'!E$26:P$26,Actual_month),0) -> 0.172438 | N34: =IFERROR(INDEX('KPI RB4 (2)'!E$27:P$27,Actual_month),0) -> 0.26963776 | O34: =IFERROR(M34/N34,"") -> 0.63951727 | P34: details | Q34: =G34/$R$3 -> 0.17690627 | R34: =M34/$R$3 -> 0.19159778 | S34: L | U34: V
B35: ZONE - CBD | Q35: month | R35: cum
A36: 101 | B36: Volume Water Supplied | C36: m3 | D36: l | E36: l | F36: l | G36: =IFERROR(INDEX('KPI 101'!E$19:P$19,Actual_month),0) -> 20399.04 | H36: =IFERROR(INDEX('KPI 101'!E$20:P$20,Actual_month),0) -> 19812 | I36: =IFERROR(H36/G36,"") -> 0.97122218 | J36: l | K36: l | L36: l | M36: =IFERROR(INDEX('KPI 101'!E$26:P$26,Actual_month),0) -> 165895.34 | N36: =IFERROR(INDEX('KPI 101'!E$27:P$27,Actual_month),0) -> 167638 | O36: =IFERROR(N36/M36,"") -> 1.0105046 | P36: details | Q36: =G36*$R$3 -> 18359.136 | R36: =M36*$R$3 -> 149305.81 | S36: H | U36: V
A37: 108 | B37: Volume Water Sold | C37: m3 | D37: l | E37: l | F37: l | G37: =IFERROR(INDEX('KPI 108'!E$19:P$19,Actual_month),0) -> 16218.625 | H37: =IFERROR(INDEX('KPI 108'!E$20:P$20,Actual_month),0) -> 15811 | I37: =IFERROR(H37/G37,"") -> 0.97486686 | J37: l | K37: l | L37: l | M37: =IFERROR(INDEX('KPI 108'!E$26:P$26,Actual_month),0) -> 129411.98 | N37: =IFERROR(INDEX('KPI 108'!E$27:P$27,Actual_month),0) -> 125957 | O37: =IFERROR(N37/M37,"") -> 0.97330248 | P37: details | Q37: =G37*$R$3 -> 14596.762 | R37: =M37*$R$3 -> 116470.78 | S37: H | U37: V
A38: 122 | B38: NRW | C38: % | D38: l | E38: l | F38: l | G38: =IFERROR(INDEX('KPI 122'!E$19:P$19,Actual_month),0) -> 0.20493195 | H38: =IFERROR(INDEX('KPI 122'!E$20:P$20,Actual_month),0) -> 0.20194831 | I38: =IFERROR(G38/H38,"") -> 1.0147742 | J38: l | K38: l | L38: l | M38: =IFERROR(INDEX('KPI 122'!E$26:P$26,Actual_month),0) -> 0.21991795 | N38: =IFERROR(INDEX('KPI 122'!E$27:P$27,Actual_month),0) -> 0.24863694 | O38: =IFERROR(M38/N38,"") -> 0.88449426 | P38: details | Q38: =G38/$R$3 -> 0.22770217 | R38: =M38/$R$3 -> 0.24435328 | S38: L | U38: V
B39: Amount Billed Water | C39: KES | D39: l | E39: l | F39: l | G39: =IFERROR(INDEX(#REF!,Actual_month),0) -> 0 | H39: =IFERROR(INDEX(#REF!,Actual_month),0) -> 0 | I39: =IFERROR(H39/G39,"") | J39: l | K39: l | L39: l | M39: =IFERROR(INDEX(#REF!,Actual_month),0) -> 0 | N39: =IFERROR(INDEX(#REF!,Actual_month),0) -> 0 | O39: =IFERROR(N39/M39,"") | P39: details | Q39: =G39*$R$3 -> 0 | R39: =M39*$R$3 -> 0 | S39: H | U39: V
B40: Amount Billed Sewer | C40: KES | D40: l | E40: l | F40: l | G40: =IFERROR(INDEX(#REF!,Actual_month),0) -> 0 | H40: =IFERROR(INDEX(#REF!,Actual_month),0) -> 0 | I40: =IFERROR(H40/G40,"") | J40: l | K40: l | L40: l | M40: =IFERROR(INDEX(#REF!,Actual_month),0) -> 0 | N40: =IFERROR(SUM(#REF!:INDEX(#REF!,Actual_month)),0) -> 0 | O40: =IFERROR(N40/M40,"") | P40: details | Q40: =G40*$R$3 -> 0 | R40: =M40*$R$3 -> 0 | S40: H | U40: V
B41: ZONE - CCCR | Q41: month | R41: cum
A42: 102 | B42: Volume Water Supplied | C42: m3 | D42: l | E42: l | F42: l | G42: =IFERROR(INDEX('KPI 102'!E$19:P$19,Actual_month),0) -> 19601.74 | H42: =IFERROR(INDEX('KPI 102'!E$20:P$20,Actual_month),0) -> 20893 | I42: =IFERROR(H42/G42,"") -> 1.0658748 | J42: l | K42: l | L42: l | M42: =IFERROR(INDEX('KPI 102'!E$26:P$26,Actual_month),0) -> 154600.02 | N42: =IFERROR(INDEX('KPI 102'!E$27:P$27,Actual_month),0) -> 158283 | O42: =IFERROR(N42/M42,"") -> 1.0238226 | P42: details | Q42: =G42*$R$3 -> 17641.566 | R42: =M42*$R$3 -> 139140.02 | S42: H | U42: V
A43: 109 | B43: Volume Water Sold | C43: m3 | D43: l | E43: l | F43: l | G43: =IFERROR(INDEX('KPI 109'!E$19:P$19,Actual_month),0) -> 17168.191 | H43: =IFERROR(INDEX('KPI 109'!E$20:P$20,Actual_month),0) -> 17374 | I43: =IFERROR(H43/G43,"") -> 1.0119878 | J43: l | K43: l | L43: l | M43: =IFERROR(INDEX('KPI 109'!E$26:P$26,Actual_month),0) -> 130834.1 | N43: =IFERROR(INDEX('KPI 109'!E$27:P$27,Actual_month),0) -> 127731 | O43: =IFERROR(N43/M43,"") -> 0.97628216 | P43: details | Q43: =G43*$R$3 -> 15451.372 | R43: =M43*$R$3 -> 117750.69 | S43: H | U43: V
A44: 123 | B44: NRW | C44: % | D44: l | E44: l | F44: l | G44: =IFERROR(INDEX('KPI 123'!E$19:P$19,Actual_month),0) -> 0.12414963 | H44: =IFERROR(INDEX('KPI 123'!E$20:P$20,Actual_month),0) -> 0.16842962 | I44: =IFERROR(G44/H44,"") -> 0.73710096 | J44: l | K44: l | L44: l | M44: =IFERROR(INDEX('KPI 123'!E$26:P$26,Actual_month),0) -> 0.15372519 | N44: =IFERROR(INDEX('KPI 123'!E$27:P$27,Actual_month),0) -> 0.19302136 | O44: =IFERROR(M44/N44,"") -> 0.79641545 | P44: details | Q44: =G44/$R$3 -> 0.13794404 | R44: =M44/$R$3 -> 0.17080577 | S44: L | U44: V
B45: Amount Billed Water | C45: KES | D45: l | E45: l | F45: l | G45: =IFERROR(INDEX(#REF!,Actual_month),0) -> 0 | H45: =IFERROR(INDEX(#REF!,Actual_month),0) -> 0 | I45: =IFERROR(H45/G45,"") | J45: l | K45: l | L45: l | M45: =IFERROR(INDEX(#REF!,Actual_month),0) -> 0 | N45: =IFERROR(INDEX(#REF!,Actual_month),0) -> 0 | O45: =IFERROR(N45/M45,"") | P45: details | Q45: =G45*$R$3 -> 0 | R45: =M45*$R$3 -> 0 | S45: H | U45: V
B46: Amount Billed Sewer | C46: KES | D46: l | E46: l | F46: l | G46: =IFERROR(INDEX(#REF!,Actual_month),0) -> 0 | H46: =IFERROR(INDEX(#REF!,Actual_month),0) -> 0 | I46: =IFERROR(H46/G46,"") | J46: l | K46: l | L46: l | M46: =IFERROR(INDEX(#REF!,Actual_month),0) -> 0 | N46: =IFERROR(INDEX(#REF!,Actual_month),0) -> 0 | O46: =IFERROR(N46/M46,"") | P46: details | Q46: =G46*$R$3 -> 0 | R46: =M46*$R$3 -> 0 | S46: H | U46: V
B47: ZONE - LAKEVIEW | Q47: month | R47: cum
A48: 104 | B48: Volume Water Supplied | C48: m3 | D48: l | E48: l | F48: l | G48: =IFERROR(INDEX('KPI 104'!E$19:P$19,Actual_month),0) -> 25784 | H48: =IFERROR(INDEX('KPI 104'!E$20:P$20,Actual_month),0) -> 26597 | I48: =IFERROR(H48/G48,"") -> 1.0315312 | J48: l | K48: l | L48: l | M48: =IFERROR(INDEX('KPI 104'!E$26:P$26,Actual_month),0) -> 209089.35 | N48: =IFERROR(INDEX('KPI 104'!E$27:P$27,Actual_month),0) -> 210015 | O48: =IFERROR(N48/M48,"") -> 1.0044271 | P48: details | Q48: =G48*$R$3 -> 23205.6 | R48: =M48*$R$3 -> 188180.41 | S48: H | U48: V
A49: 111 | B49: Volume Water Sold | C49: m3 | D49: l | E49: l | F49: l | G49: =IFERROR(INDEX('KPI 111'!E$19:P$19,Actual_month),0) -> 21596.293 | H49: =IFERROR(INDEX('KPI 111'!E$20:P$20,Actual_month),0) -> 21183 | I49: =IFERROR(H49/G49,"") -> 0.98086278 | J49: l | K49: l | L49: l | M49: =IFERROR(INDEX('KPI 111'!E$26:P$26,Actual_month),0) -> 170748.56 | N49: =IFERROR(INDEX('KPI 111'!E$27:P$27,Actual_month),0) -> 157584 | O49: =IFERROR(N49/M49,"") -> 0.92290089 | P49: details | Q49: =G49*$R$3 -> 19436.664 | R49: =M49*$R$3 -> 153673.71 | S49: H | U49: V
A50: 125 | B50: NRW | C50: % | D50: l | E50: l | F50: l | G50: =IFERROR(INDEX('KPI 125'!E$19:P$19,Actual_month),0) -> 0.16241494 | H50: =IFERROR(INDEX('KPI 125'!E$20:P$20,Actual_month),0) -> 0.20355679 | I50: =IFERROR(G50/H50,"") -> 0.79788515 | J50: l | K50: l | L50: l | M50: =IFERROR(INDEX('KPI 125'!E$26:P$26,Actual_month),0) -> 0.18337034 | N50: =IFERROR(INDEX('KPI 125'!E$27:P$27,Actual_month),0) -> 0.2496536 | O50: =IFERROR(M50/N50,"") -> 0.7344991 | P50: details | Q50: =G50/$R$3 -> 0.18046105 | R50: =M50/$R$3 -> 0.20374482 | S50: L | U50: V
B51: Amount Billed Water | C51: KES | D51: l | E51: l | F51: l | G51: =IFERROR(INDEX(#REF!,Actual_month),0) -> 0 | H51: =IFERROR(INDEX(#REF!,Actual_month),0) -> 0 | I51: =IFERROR(H51/G51,"") | J51: l | K51: l | L51: l | M51: =IFERROR(INDEX(#REF!,Actual_month),0) -> 0 | N51: =IFERROR(INDEX(#REF!,Actual_month),0) -> 0 | O51: =IFERROR(N51/M51,"") | P51: details | Q51: =G51/$R$3 -> 0 | R51: =M51*$R$3 -> 0 | S51: H | U51: V
B52: Amount Billed Sewer | C52: KES | D52: l | E52: l | F52: l | G52: =IFERROR(INDEX(#REF!,Actual_month),0) -> 0 | H52: =IFERROR(INDEX(#REF!,Actual_month),0) -> 0 | I52: =IFERROR(H52/G52,"") | J52: l | K52: l | L52: l | M52: =IFERROR(INDEX(#REF!,Actual_month),0) -> 0 | N52: =IFERROR(INDEX(#REF!,Actual_month),0) -> 0 | O52: =IFERROR(N52/M52,"") | P52: details | Q52: =G52*$R$3 -> 0 | R52: =M52*$R$3 -> 0 | S52: H | U52: V
B53: ZONE - KABATI | Q53: month | R53: cum
A54: 103 | B54: Volume Water Supplied | C54: m3 | D54: l | E54: l | F54: l | G54: =IFERROR(INDEX('KPI 103'!E$19:P$19,Actual_month),0) -> 16726.453 | H54: =IFERROR(INDEX('KPI 103'!E$20:P$20,Actual_month),0) -> 14546 | I54: =IFERROR(H54/G54,"") -> 0.86964045 | J54: l | K54: l | L54: l | M54: =IFERROR(INDEX('KPI 103'!E$26:P$26,Actual_month),0) -> 133847.96 | N54: =IFERROR(INDEX('KPI 103'!E$27:P$27,Actual_month),0) -> 121581 | O54: =IFERROR(N54/M54,"") -> 0.90835152 | P54: details | Q54: =G54*$R$3 -> 15053.808 | R54: =M54*$R$3 -> 120463.17 | S54: H | U54: V
A55: 110 | B55: Volume Water Sold | C55: m3 | D55: l | E55: l | F55: l | G55: =IFERROR(INDEX('KPI 110'!E$19:P$19,Actual_month),0) -> 14080.943 | H55: =IFERROR(INDEX('KPI 110'!E$20:P$20,Actual_month),0) -> 12061 | I55: =IFERROR(H55/G55,"") -> 0.85654775 | J55: l | K55: l | L55: l | M55: =IFERROR(INDEX('KPI 110'!E$26:P$26,Actual_month),0) -> 110287.71 | N55: =IFERROR(INDEX('KPI 110'!E$27:P$27,Actual_month),0) -> 97037 | O55: =IFERROR(N55/M55,"") -> 0.87985324 | P55: details | Q55: =G55*$R$3 -> 12672.849 | R55: =M55*$R$3 -> 99258.94 | S55: H | U55: V
A56: 124 | B56: NRW | C56: % | D56: l | E56: l | F56: l | G56: =IFERROR(INDEX('KPI 124'!E$19:P$19,Actual_month),0) -> 0.15816324 | H56: =IFERROR(INDEX('KPI 124'!E$20:P$20,Actual_month),0) -> 0.17083734 | I56: =IFERROR(G56/H56,"") -> 0.92581187 | J56: l | K56: l | L56: l | M56: =IFERROR(INDEX('KPI 124'!E$26:P$26,Actual_month),0) -> 0.17602249 | N56: =IFERROR(INDEX('KPI 124'!E$27:P$27,Actual_month),0) -> 0.20187365 | O56: =IFERROR(M56/N56,"") -> 0.87194386 | P56: details | Q56: =G56/$R$3 -> 0.17573693 | R56: =M56/$R$3 -> 0.19558054 | S56: L | U56: V
B57: Amount Billed | C57: KES | D57: l | E57: l | F57: l | G57: =IFERROR(INDEX(#REF!,Actual_month),0) -> 0 | H57: =IFERROR(INDEX(#REF!,Actual_month),0) -> 0 | I57: =IFERROR(H57/G57,"") | J57: l | K57: l | L57: l | M57: =IFERROR(INDEX(#REF!,Actual_month),0) -> 0 | N57: =IFERROR(INDEX(#REF!,Actual_month),0) -> 0 | O57: =IFERROR(N57/M57,"") | P57: details | Q57: =G57*$R$3 -> 0 | R57: =M57*$R$3 -> 0 | S57: H | U57: V
B58: Amount Billed Sewer | C58: KES | D58: l | E58: l | F58: l | G58: =IFERROR(INDEX(#REF!,Actual_month),0) -> 0 | H58: =IFERROR(INDEX(#REF!,Actual_month),0) -> 0 | I58: =IFERROR(H58/G58,"") | J58: l | K58: l | L58: l | M58: =IFERROR(INDEX(#REF!,Actual_month),0) -> 0 | N58: =IFERROR(INDEX(#REF!,Actual_month),0) -> 0 | O58: =IFERROR(N58/M58,"") | P58: details | Q58: =G58*$R$3 -> 0 | R58: =M58*$R$3 -> 0 | S58: H | U58: V
B59: ZONE - SITE AND SERVICES | Q59: month | R59: cum
A60: 105 | B60: Volume Water Supplied | C60: m3 | D60: l | E60: l | F60: l | G60: =IFERROR(INDEX('KPI 105'!E$19:P$19,Actual_month),0) -> 12367.785 | H60: =IFERROR(INDEX('KPI 105'!E$20:P$20,Actual_month),0) -> 11406 | I60: =IFERROR(H60/G60,"") -> 0.92223467 | J60: l | K60: l | L60: l | M60: =IFERROR(INDEX('KPI 105'!E$26:P$26,Actual_month),0) -> 101970.15 | N60: =IFERROR(INDEX('KPI 105'!E$27:P$27,Actual_month),0) -> 96736 | O60: =IFERROR(N60/M60,"") -> 0.94866974 | P60: details | Q60: =G60*$R$3 -> 11131.006 | R60: =M60*$R$3 -> 91773.139 | S60: H | U60: V
A61: 112 | B61: Volume Water Sold | C61: m3 | D61: l | E61: l | F61: l | G61: =IFERROR(INDEX('KPI 112'!E$19:P$19,Actual_month),0) -> 10832.329 | H61: =IFERROR(INDEX('KPI 112'!E$20:P$20,Actual_month),0) -> 10175 | I61: =IFERROR(H61/G61,"") -> 0.93931786 | J61: l | K61: l | L61: l | M61: =IFERROR(INDEX('KPI 112'!E$26:P$26,Actual_month),0) -> 86236.37 | N61: =IFERROR(INDEX('KPI 112'!E$27:P$27,Actual_month),0) -> 82306 | O61: =IFERROR(N61/M61,"") -> 0.95442329 | P61: details | Q61: =G61*$R$3 -> 9749.096 | R61: =M61*$R$3 -> 77612.733 | S61: H | U61: V
A62: 126 | B62: NRW | C62: % | D62: l | E62: l | F62: l | G62: =IFERROR(INDEX('KPI 126'!E$19:P$19,Actual_month),0) -> 0.12414963 | H62: =IFERROR(INDEX('KPI 126'!E$20:P$20,Actual_month),0) -> 0.10792565 | I62: =IFERROR(G62/H62,"") -> 1.1503255 | J62: l | K62: l | L62: l | M62: =IFERROR(INDEX('KPI 126'!E$26:P$26,Actual_month),0) -> 0.15429794 | N62: =IFERROR(INDEX('KPI 126'!E$27:P$27,Actual_month),0) -> 0.14916887 | O62: =IFERROR(M62/N62,"") -> 1.0343843 | P62: details | Q62: =G62/$R$3 -> 0.13794404 | R62: =M62/$R$3 -> 0.17144216 | S62: L | U62: V
B63: Amount Billed Water | C63: KES | D63: l | E63: l | F63: l | G63: =IFERROR(INDEX(#REF!,Actual_month),0) -> 0 | H63: =IFERROR(INDEX(#REF!,Actual_month),0) -> 0 | I63: =IFERROR(H63/G63,"") | J63: l | K63: l | L63: l | M63: =IFERROR(INDEX(#REF!,Actual_month),0) -> 0 | N63: =IFERROR(INDEX(#REF!,Actual_month),0) -> 0 | O63: =IFERROR(N63/M63,"") | P63: details | Q63: =G63*$R$3 -> 0 | R63: =M63*$R$3 -> 0 | S63: H | U63: V
B64: Amount Billed Sewer | C64: KES | D64: l | E64: l | F64: l | G64: =IFERROR(INDEX(#REF!,Actual_month),0) -> 0 | H64: =IFERROR(INDEX(#REF!,Actual_month),0) -> 0 | I64: =IFERROR(H64/G64,"") | J64: l | K64: l | L64: l | M64: =IFERROR(INDEX(#REF!,Actual_month),0) -> 0 | N64: =IFERROR(INDEX(#REF!,Actual_month),0) -> 0 | O64: =IFERROR(N64/M64,"") | P64: details | Q64: =G64*$R$3 -> 0 | R64: =M64*$R$3 -> 0 | S64: H | U64: V
B65: ZONE - HOPEWELL | Q65: month | R65: cum
A66: 105B | B66: Volume Water Supplied | C66: m3 | D66: l | E66: l | F66: l | G66: =IFERROR(INDEX('KPI 105B'!E$19:P$19,Actual_month),0) -> 6851.8599 | H66: =IFERROR(INDEX('KPI 105B'!E$20:P$20,Actual_month),0) -> 6609 | I66: =IFERROR(H66/G66,"") -> 0.96455563 | J66: l | K66: l | L66: l | M66: =IFERROR(INDEX('KPI 105B'!E$26:P$26,Actual_month),0) -> 54323.533 | N66: =IFERROR(INDEX('KPI 105B'!E$27:P$27,Actual_month),0) -> 50295 | O66: =IFERROR(N66/M66,"") -> 0.92584184 | P66: details | Q66: =G66*$R$3 -> 6166.6739 | R66: =M66*$R$3 -> 48891.18 | S66: H | U66: V
A67: 112B | B67: Volume Water Sold | C67: m3 | D67: l | E67: l | F67: l | G67: =IFERROR(INDEX('KPI 112B'!E$19:P$19,Actual_month),0) -> 6088.6002 | H67: =IFERROR(INDEX('KPI 112B'!E$20:P$20,Actual_month),0) -> 5420 | I67: =IFERROR(H67/G67,"") -> 0.8901882 | J67: l | K67: l | L67: l | M67: =IFERROR(INDEX('KPI 112B'!E$26:P$26,Actual_month),0) -> 47144.896 | N67: =IFERROR(INDEX('KPI 112B'!E$27:P$27,Actual_month),0) -> 44878 | O67: =IFERROR(N67/M67,"") -> 0.95191641 | P67: details | Q67: =G67*$R$3 -> 5479.7401 | R67: =M67*$R$3 -> 42430.406 | S67: H | U67: V
A68: 126B | B68: NRW | C68: % | D68: l | E68: l | F68: l | G68: =IFERROR(INDEX('KPI 126B'!E$19:P$19,Actual_month),0) -> 0.11139453 | H68: =IFERROR(INDEX('KPI 126B'!E$20:P$20,Actual_month),0) -> 0.17990619 | I68: =IFERROR(G68/H68,"") -> 0.61918121 | J68: l | K68: l | L68: l | M68: =IFERROR(INDEX('KPI 126B'!E$26:P$26,Actual_month),0) -> 0.132146 | N68: =IFERROR(INDEX('KPI 126B'!E$27:P$27,Actual_month),0) -> 0.10770454 | O68: =IFERROR(M68/N68,"") -> 1.2269306 | P68: details | Q68: =G68/$R$3 -> 0.1237717 | R68: =M68/$R$3 -> 0.14682888 | S68: L | U68: V
B69: ZONE - KAMERE | Q69: month | R69: cum
A70: 106 | B70: Volume Water Supplied | C70: m3 | D70: l | E70: l | F70: l | G70: =IFERROR(INDEX('KPI 106'!E$19:P$19,Actual_month),0) -> 9597.6641 | H70: =IFERROR(INDEX('KPI 106'!E$20:P$20,Actual_month),0) -> 9112 | I70: =IFERROR(H70/G70,"") -> 0.94939768 | J70: l | K70: l | L70: l | M70: =IFERROR(INDEX('KPI 106'!E$26:P$26,Actual_month),0) -> 71834.912 | N70: =IFERROR(INDEX('KPI 106'!E$27:P$27,Actual_month),0) -> 70353 | O70: =IFERROR(N70/M70,"") -> 0.97937059 | P70: details | Q70: =G70*$R$3 -> 8637.8977 | R70: =M70*$R$3 -> 64651.42 | S70: H | U70: V
A71: 113 | B71: Volume Water Sold | C71: m3 | D71: l | E71: l | F71: l | G71: =IFERROR(INDEX('KPI 113'!E$19:P$19,Actual_month),0) -> 8487.7304 | H71: =IFERROR(INDEX('KPI 113'!E$20:P$20,Actual_month),0) -> 7181 | I71: =IFERROR(H71/G71,"") -> 0.84604478 | J71: l | K71: l | L71: l | M71: =IFERROR(INDEX('KPI 113'!E$26:P$26,Actual_month),0) -> 61865.086 | N71: =IFERROR(INDEX('KPI 113'!E$27:P$27,Actual_month),0) -> 50827 | O71: =IFERROR(N71/M71,"") -> 0.8215781 | P71: details | Q71: =G71*$R$3 -> 7638.9574 | R71: =M71*$R$3 -> 55678.578 | S71: H | U71: V
A72: 127 | B72: NRW | C72: % | D72: l | E72: l | F72: l | G72: =IFERROR(INDEX('KPI 127'!E$19:P$19,Actual_month),0) -> 0.11564623 | H72: =IFERROR(INDEX('KPI 127'!E$20:P$20,Actual_month),0) -> 0.21191835 | I72: =IFERROR(G72/H72,"") -> 0.54571127 | J72: l | K72: l | L72: l | M72: =IFERROR(INDEX('KPI 127'!E$26:P$26,Actual_month),0) -> 0.13878802 | N72: =IFERROR(INDEX('KPI 127'!E$27:P$27,Actual_month),0) -> 0.27754325 | O72: =IFERROR(M72/N72,"") -> 0.50005908 | P72: details | Q72: =G72/$R$3 -> 0.12849581 | R72: =M72/$R$3 -> 0.15420891 | S72: L | U72: V
B73: Amount Billed Water | C73: KES | D73: l | E73: l | F73: l | G73: =IFERROR(INDEX(#REF!,Actual_month),0) -> 0 | H73: =IFERROR(INDEX(#REF!,Actual_month),0) -> 0 | I73: =IFERROR(H73/G73,"") | J73: l | K73: l | L73: l | M73: =IFERROR(INDEX(#REF!,Actual_month),0) -> 0 | N73: =IFERROR(INDEX(#REF!,Actual_month),0) -> 0 | O73: =IFERROR(N73/M73,"") | P73: details | Q73: =G73*$R$3 -> 0 | R73: =M73*$R$3 -> 0 | S73: H | U73: V
B74: Amount Billed Sewer | C74: KES | D74: l | E74: l | F74: l | G74: =IFERROR(INDEX(#REF!,Actual_month),0) -> 0 | H74: =IFERROR(INDEX(#REF!,Actual_month),0) -> 0 | I74: =IFERROR(H74/G74,"") | J74: l | K74: l | L74: l | M74: =IFERROR(INDEX(#REF!,Actual_month),0) -> 0 | N74: =IFERROR(INDEX(#REF!,Actual_month),0) -> 0 | O74: =IFERROR(N74/M74,"") | P74: details | Q74: =G74*$R$3 -> 0 | R74: =M74*$R$3 -> 0 | S74: H | U74: V
B75: ZONE - HELLS GATE | Q75: month | R75: cum
A76: 103 (3) | B76: Volume Water Supplied | C76: m3 | D76: l | E76: l | F76: l | G76: =IFERROR(INDEX('KPI 103 (3)'!E$19:P$19,Actual_month),0) -> 41670.497 | H76: =IFERROR(INDEX('KPI 103 (3)'!E$20:P$20,Actual_month),0) -> 37061 | I76: =IFERROR(H76/G76,"") -> 0.88938224 | J76: l | K76: l | L76: l | M76: =IFERROR(INDEX('KPI 103 (3)'!E$26:P$26,Actual_month),0) -> 313078.83 | N76: =IFERROR(INDEX('KPI 103 (3)'!E$27:P$27,Actual_month),0) -> 283207 | O76: =IFERROR(N76/M76,"") -> 0.90458686 | P76: details | Q76: =G76*$R$3 -> 37503.447 | R76: =M76*$R$3 -> 281770.95 | S76: H | U76: V
A77: 110 (3) | B77: Volume Water Sold | C77: m3 | D77: l | E77: l | F77: l | G77: =IFERROR(INDEX('KPI 110 (3)'!E$19:P$19,Actual_month),0) -> 31004.835 | H77: =IFERROR(INDEX('KPI 110 (3)'!E$20:P$20,Actual_month),0) -> 26800 | I77: =IFERROR(H77/G77,"") -> 0.86438131 | J77: l | K77: l | L77: l | M77: =IFERROR(INDEX('KPI 110 (3)'!E$26:P$26,Actual_month),0) -> 228405.73 | N77: =IFERROR(INDEX('KPI 110 (3)'!E$27:P$27,Actual_month),0) -> 200670 | O77: =IFERROR(N77/M77,"") -> 0.87856816 | P77: details | Q77: =G77*$R$3 -> 27904.352 | R77: =M77*$R$3 -> 205565.16 | S77: H | U77: V
A78: 124 (3) | B78: NRW | C78: % | D78: l | E78: l | F78: l | G78: =IFERROR(INDEX('KPI 124 (3)'!E$19:P$19,Actual_month),0) -> 0.25595236 | H78: =IFERROR(INDEX('KPI 124 (3)'!E$20:P$20,Actual_month),0) -> 0.27686787 | I78: =IFERROR(G78/H78,"") -> 0.92445672 | J78: l | K78: l | L78: l | M78: =IFERROR(INDEX('KPI 124 (3)'!E$26:P$26,Actual_month),0) -> 0.27045298 | N78: =IFERROR(INDEX('KPI 124 (3)'!E$27:P$27,Actual_month),0) -> 0.29143701 | O78: =IFERROR(M78/N78,"") -> 0.92799808 | P78: details | Q78: =G78/$R$3 -> 0.28439151 | R78: =M78/$R$3 -> 0.30050331 | S78: L | U78: V
B79: Amount Billed Water | C79: KES | D79: l | E79: l | F79: l | G79: =IFERROR(INDEX(#REF!,Actual_month),0) -> 0 | H79: =IFERROR(INDEX(#REF!,Actual_month),0) -> 0 | I79: =IFERROR(H79/G79,"") | J79: l | K79: l | L79: l | M79: =IFERROR(INDEX(#REF!,Actual_month),0) -> 0 | N79: =IFERROR(INDEX(#REF!,Actual_month),0) -> 0 | O79: =IFERROR(N79/M79,"") | P79: details | Q79: =G79*$R$3 -> 0 | R79: =M79*$R$3 -> 0 | S79: H | U79: V
B80: Amount Billed Sewer | C80: KES | D80: l | E80: l | F80: l | G80: =IFERROR(INDEX(#REF!,Actual_month),0) -> 0 | H80: =IFERROR(INDEX(#REF!,Actual_month),0) -> 0 | I80: =IFERROR(H80/G80,"") | J80: l | K80: l | L80: l | M80: =IFERROR(INDEX(#REF!,Actual_month),0) -> 0 | N80: =IFERROR(INDEX(#REF!,Actual_month),0) -> 0 | O80: =IFERROR(N80/M80,"") | P80: details | Q80: =G80*$R$3 -> 0 | R80: =M80*$R$3 -> 0 | S80: H | U80: V
B81: KIHOTO | Q81: month | R81: cum
A82: 103 (2) | B82: Volume Water Supplied | C82: m3 | D82: l | E82: l | F82: l | G82: =IFERROR(INDEX('KPI 103 (2)'!E$19:P$19,Actual_month),0) -> 2082.4362 | H82: =IFERROR(INDEX('KPI 103 (2)'!E$20:P$20,Actual_month),0) -> 1973 | I82: =IFERROR(H82/G82,"") -> 0.947448 | J82: l | K82: l | L82: l | M82: =IFERROR(INDEX('KPI 103 (2)'!E$26:P$26,Actual_month),0) -> 16627.511 | N82: =IFERROR(INDEX('KPI 103 (2)'!E$27:P$27,Actual_month),0) -> 15740 | O82: =IFERROR(N82/M82,"") -> 0.94662396 | P82: details | Q82: =G82*$R$3 -> 1874.1926 | R82: =M82*$R$3 -> 14964.76 | S82: H | U82: V
A83: 110 (2) | B83: Volume Water Sold | C83: m3 | D83: l | E83: l | F83: l | G83: =IFERROR(INDEX('KPI 110 (2)'!E$19:P$19,Actual_month),0) -> 1868.172 | H83: =IFERROR(INDEX('KPI 110 (2)'!E$20:P$20,Actual_month),0) -> 1575 | I83: =IFERROR(H83/G83,"") -> 0.84307014 | J83: l | K83: l | L83: l | M83: =IFERROR(INDEX('KPI 110 (2)'!E$26:P$26,Actual_month),0) -> 14669.46 | N83: =IFERROR(INDEX('KPI 110 (2)'!E$27:P$27,Actual_month),0) -> 12025 | O83: =IFERROR(N83/M83,"") -> 0.81973024 | P83: details | Q83: =G83*$R$3 -> 1681.3548 | R83: =M83*$R$3 -> 13202.514 | S83: H | U83: V
A84: 124 (2) | B84: NRW | C84: % | D84: l | E84: l | F84: l | G84: =IFERROR(INDEX('KPI 124 (2)'!E$19:P$19,Actual_month),0) -> 0.10289113 | H84: =IFERROR(INDEX('KPI 124 (2)'!E$20:P$20,Actual_month),0) -> 0.20172326 | I84: =IFERROR(G84/H84,"") -> 0.5100608 | J84: l | K84: l | L84: l | M84: =IFERROR(INDEX('KPI 124 (2)'!E$26:P$26,Actual_month),0) -> 0.1177597 | N84: =IFERROR(INDEX('KPI 124 (2)'!E$27:P$27,Actual_month),0) -> 0.23602287 | O84: =IFERROR(M84/N84,"") -> 0.49893342 | P84: details | Q84: =G84/$R$3 -> 0.11432348 | R84: =M84/$R$3 -> 0.13084411 | S84: L | U84: V
B85: Amount Billed Water | C85: KES | D85: l | E85: l | F85: l | G85: =IFERROR(INDEX(#REF!,Actual_month),0) -> 0 | H85: =IFERROR(INDEX(#REF!,Actual_month),0) -> 0 | I85: =IFERROR(H85/G85,"") | J85: l | K85: l | L85: l | M85: =IFERROR(INDEX(#REF!,Actual_month),0) -> 0 | N85: =IFERROR(INDEX(#REF!,Actual_month),0) -> 0 | O85: =IFERROR(N85/M85,"") | P85: details | Q85: =G85*$R$3 -> 0 | R85: =M85*$R$3 -> 0 | S85: H | U85: V
B86: Amount Billed Sewer | C86: KES | D86: l | E86: l | F86: l | G86: =IFERROR(INDEX(#REF!,Actual_month),0) -> 0 | H86: =IFERROR(INDEX(#REF!,Actual_month),0) -> 0 | I86: =IFERROR(H86/G86,"") | J86: l | K86: l | L86: l | M86: =IFERROR(INDEX(#REF!,Actual_month),0) -> 0 | N86: =IFERROR(INDEX(#REF!,Actual_month),0) -> 0 | O86: =IFERROR(N86/M86,"") | P86: details | Q86: =G86*$R$3 -> 0 | R86: =M86*$R$3 -> 0 | S86: H | U86: V
B87: KAYOLE | Q87: month | R87: cum
A88: 103 (4) | B88: Volume Water Supplied | C88: m3 | D88: l | E88: l | F88: l | G88: =IFERROR(INDEX('KPI 103 (4)'!E$19:P$19,Actual_month),0) -> 35485.172 | H88: =IFERROR(INDEX('KPI 103 (4)'!E$20:P$20,Actual_month),0) -> 42601 | I88: =IFERROR(H88/G88,"") -> 1.2005296 | J88: l | K88: l | L88: l | M88: =IFERROR(INDEX('KPI 103 (4)'!E$26:P$26,Actual_month),0) -> 280869.81 | N88: =IFERROR(INDEX('KPI 103 (4)'!E$27:P$27,Actual_month),0) -> 318051 | O88: =IFERROR(N88/M88,"") -> 1.1323787 | P88: details | Q88: =G88*$R$3 -> 31936.655 | R88: =M88*$R$3 -> 252782.83 | S88: H | U88: V
A89: 110 (4) | B89: Volume Water Sold | C89: m3 | D89: l | E89: l | F89: l | G89: =IFERROR(INDEX('KPI 110 (4)'!E$19:P$19,Actual_month),0) -> 30023.595 | H89: =IFERROR(INDEX('KPI 110 (4)'!E$20:P$20,Actual_month),0) -> 33446 | I89: =IFERROR(H89/G89,"") -> 1.1139905 | J89: l | K89: l | L89: l | M89: =IFERROR(INDEX('KPI 110 (4)'!E$26:P$26,Actual_month),0) -> 233476.19 | N89: =IFERROR(INDEX('KPI 110 (4)'!E$27:P$27,Actual_month),0) -> 232119 | O89: =IFERROR(N89/M89,"") -> 0.99418704 | P89: details | Q89: =G89*$R$3 -> 27021.235 | R89: =M89*$R$3 -> 210128.57 | S89: H | U89: V
A90: 124 (4) | B90: NRW | C90: % | D90: l | E90: l | F90: l | G90: =IFERROR(INDEX('KPI 124 (4)'!E$19:P$19,Actual_month),0) -> 0.15391154 | H90: =IFERROR(INDEX('KPI 124 (4)'!E$20:P$20,Actual_month),0) -> 0.21490106 | I90: =IFERROR(G90/H90,"") -> 0.71619721 | J90: l | K90: l | L90: l | M90: =IFERROR(INDEX('KPI 124 (4)'!E$26:P$26,Actual_month),0) -> 0.16873876 | N90: =IFERROR(INDEX('KPI 124 (4)'!E$27:P$27,Actual_month),0) -> 0.27018308 | O90: =IFERROR(M90/N90,"") -> 0.62453488 | P90: details | Q90: =G90/$R$3 -> 0.17101282 | R90: =M90/$R$3 -> 0.18748751 | S90: L | U90: V
B91: Amount Billed Water | C91: KES | D91: l | E91: l | F91: l | G91: =IFERROR(INDEX(#REF!,Actual_month),0) -> 0 | H91: =IFERROR(INDEX(#REF!,Actual_month),0) -> 0 | I91: =IFERROR(H91/G91,"") | J91: l | K91: l | L91: l | M91: =IFERROR(INDEX(#REF!,Actual_month),0) -> 0 | N91: =IFERROR(INDEX(#REF!,Actual_month),0) -> 0 | O91: =IFERROR(N91/M91,"") | P91: details | Q91: =G91*$R$3 -> 0 | R91: =M91*$R$3 -> 0 | S91: H | U91: V
B92: Amount Billed Sewer | C92: KES | D92: l | E92: l | F92: l | G92: =IFERROR(INDEX(#REF!,Actual_month),0) -> 0 | H92: =IFERROR(INDEX(#REF!,Actual_month),0) -> 0 | I92: =IFERROR(H92/G92,"") | J92: l | K92: l | L92: l | M92: =IFERROR(INDEX(#REF!,Actual_month),0) -> 0 | N92: =IFERROR(INDEX(#REF!,Actual_month),0) -> 0 | O92: =IFERROR(N92/M92,"") | P92: details | Q92: =G92*$R$3 -> 0 | R92: =M92*$R$3 -> 0 | S92: H | U92: V
B93: MAI-MAHIU | Q93: month | R93: cum
A94: 103 (5) | B94: Volume Water Supplied | C94: m3 | D94: l | E94: l | F94: l | G94: =IFERROR(INDEX('KPI 103 (5)'!E$19:P$19,Actual_month),0) -> 31130.555 | H94: =IFERROR(INDEX('KPI 103 (5)'!E$20:P$20,Actual_month),0) -> 24972 | I94: =IFERROR(H94/G94,"") -> 0.80217008 | J94: l | K94: l | L94: l | M94: =IFERROR(INDEX('KPI 103 (5)'!E$26:P$26,Actual_month),0) -> 206383.01 | N94: =IFERROR(INDEX('KPI 103 (5)'!E$27:P$27,Actual_month),0) -> 175192 | O94: =IFERROR(N94/M94,"") -> 0.84886833 | P94: details | Q94: =G94*$R$3 -> 28017.5 | R94: =M94*$R$3 -> 185744.71 | S94: H | U94: V
A95: 110 (5) | B95: Volume Water Sold | C95: m3 | D95: l | E95: l | F95: l | G95: =IFERROR(INDEX('KPI 110 (5)'!E$19:P$19,Actual_month),0) -> 19986.029 | H95: =IFERROR(INDEX('KPI 110 (5)'!E$20:P$20,Actual_month),0) -> 15292 | I95: =IFERROR(H95/G95,"") -> 0.76513449 | J95: l | K95: l | L95: l | M95: =IFERROR(INDEX('KPI 110 (5)'!E$26:P$26,Actual_month),0) -> 123022.45 | N95: =IFERROR(INDEX('KPI 110 (5)'!E$27:P$27,Actual_month),0) -> 106366 | O95: =IFERROR(N95/M95,"") -> 0.86460643 | P95: details | Q95: =G95*$R$3 -> 17987.426 | R95: =M95*$R$3 -> 110720.2 | S95: H | U95: V
A96: 124 (5) | B96: NRW | C96: % | D96: l | E96: l | F96: l | G96: =IFERROR(INDEX('KPI 124 (5)'!E$19:P$19,Actual_month),0) -> 0.35799318 | H96: =IFERROR(INDEX('KPI 124 (5)'!E$20:P$20,Actual_month),0) -> 0.38763415 | I96: =IFERROR(G96/H96,"") -> 0.92353364 | J96: l | K96: l | L96: l | M96: =IFERROR(INDEX('KPI 124 (5)'!E$26:P$26,Actual_month),0) -> 0.40391194 | N96: =IFERROR(INDEX('KPI 124 (5)'!E$27:P$27,Actual_month),0) -> 0.3928604 | O96: =IFERROR(M96/N96,"") -> 1.0281309 | P96: details | Q96: =G96/$R$3 -> 0.3977702 | R96: =M96/$R$3 -> 0.44879104 | S96: L | U96: V
B97: Amount Billed Water | C97: KES | D97: l | E97: l | F97: l | G97: =IFERROR(INDEX(#REF!,Actual_month),0) -> 0 | H97: =IFERROR(INDEX(#REF!,Actual_month),0) -> 0 | I97: =IFERROR(H97/G97,"") | J97: l | K97: l | L97: l | M97: =IFERROR(INDEX(#REF!,Actual_month),0) -> 0 | N97: =IFERROR(INDEX(#REF!,Actual_month),0) -> 0 | O97: =IFERROR(N97/M97,"") | P97: details | Q97: =G97*$R$3 -> 0 | R97: =M97*$R$3 -> 0 | S97: H | U97: V
B98: Amount Billed Sewer | C98: KES | D98: l | E98: l | F98: l | G98: =IFERROR(INDEX(#REF!,Actual_month),0) -> 0 | H98: =IFERROR(INDEX(#REF!,Actual_month),0) -> 0 | I98: =IFERROR(H98/G98,"") | J98: l | K98: l | L98: l | M98: =IFERROR(INDEX(#REF!,Actual_month),0) -> 0 | N98: =IFERROR(INDEX(#REF!,Actual_month),0) -> 0 | O98: =IFERROR(N98/M98,"") | P98: details | Q98: =G98*$R$3 -> 0 | R98: =M98*$R$3 -> 0 | S98: H | U98: V
B99: KINUNGI
A100: Y | B100: Volume Water Supplied-kinungi | C100: m3 | D100: l | E100: l | F100: l | G100: =IFERROR(INDEX('KPI Y'!E$19:P$19,Actual_month),0) -> 0 | H100: =IFERROR(INDEX('KPI Y'!E$20:P$20,Actual_month),0) -> 235 | I100: =IFERROR(H100/G100,"") | J100: l | K100: l | L100: l | M100: =IFERROR(INDEX('KPI Y'!E$26:P$26,Actual_month),0) -> 0 | N100: =IFERROR(INDEX('KPI Y'!E$27:P$27,Actual_month),0) -> 1261 | O100: =IFERROR(N100/M100,"") | P100: details | Q100: =G100*$R$3 -> 0 | R100: =M100*$R$3 -> 0 | S100: H | U100: V
...

Sheet Budget2526
A1: ='Distribution Dashboard'!A1 -> NAIVAWASS DISTRIBUTION DASHBOARD - NON-REVENUE WATER & ZONAL PERFORMANCE | B1: ='Distribution Dashboard'!B1 -> 0 | C1: ='Distribution Dashboard'!D1 -> 0
A2: ='Distribution Dashboard'!A2 -> 0 | B2: ='Distribution Dashboard'!B2 -> 46054 | C2: ='Distribution Dashboard'!D2 -> 0
A3: ='Distribution Dashboard'!A3 -> 0 | B3: ='Distribution Dashboard'!B3 -> 0 | C3: ='Distribution Dashboard'!D3 -> Monthly
A4: ='Distribution Dashboard'!A4 -> 0 | B4: ='Distribution Dashboard'!B4 -> 0 | C4: ='Distribution Dashboard'!C4 -> Unit | D4: 45839 | E4: 45870 | F4: 45901 | G4: 45931 | H4: 45962 | I4: 45992 | J4: 46023 | K4: 46054 | L4: 46082 | M4: 46113 | N4: 46143 | O4: 46174
A5: ='Distribution Dashboard'!#REF! -> #REF! | B5: ='Distribution Dashboard'!#REF! -> #REF! | C5: ='Distribution Dashboard'!#REF! -> #REF!
A6: ='Distribution Dashboard'!#REF! -> #REF! | B6: ='Distribution Dashboard'!#REF! -> #REF! | C6: ='Distribution Dashboard'!#REF! -> #REF! | D6: =D11 -> 214810.57 | E6: =E11 -> 215882.84 | F6: =F11 -> 217038.9 | G6: =G11 -> 220378.23 | H6: =H11 -> 223369.43 | I6: =I11 -> 226152.02 | J6: =J11 -> 228481.92 | K6: =K11 -> 230597.54 | ... O6: =O11 -> 235619.07
A7: ='Distribution Dashboard'!#REF! -> #REF! | B7: ='Distribution Dashboard'!#REF! -> #REF! | C7: ='Distribution Dashboard'!#REF! -> #REF! | D7: =D16 -> 162967.74 | E7: =E16 -> 164996.23 | F7: =F16 -> 167133.61 | G7: =G16 -> 170794.25 | H7: =H16 -> 174251.4 | I7: =I16 -> 177638.11 | J7: =J16 -> 180823.44 | K7: =K16 -> 183888.91 | ... O7: =O16 -> 194059.96
A8: ='Distribution Dashboard'!#REF! -> #REF! | B8: ='Distribution Dashboard'!#REF! -> #REF! | C8: ='Distribution Dashboard'!#REF! -> #REF! | D8: =(D6-D7)/D6 -> 0.24134206 | E8: =(E6-E7)/E6 -> 0.23571401 | F8: =(F6-F7)/F6 -> 0.22993705 | G8: =(G6-G7)/G6 -> 0.22499491 | H8: =(H6-H7)/H6 -> 0.21989592 | I8: =(I6-I7)/I6 -> 0.21451902 | J8: =(J6-J7)/J6 -> 0.20858755 | K8: =(K6-K7)/K6 -> 0.20255476 | ... O8: =(O6-O7)/O6 -> 0.17638265
A9: ='Distribution Dashboard'!#REF! -> #REF!
A10: ='Distribution Dashboard'!#REF! -> #REF! | B10: ='Distribution Dashboard'!#REF! -> #REF! | C10: ='Distribution Dashboard'!#REF! -> #REF! | D10: =D6 -> 214810.57 | E10: =E6 -> 215882.84 | F10: =F6 -> 217038.9 | G10: =G6 -> 220378.23 | H10: =H6 -> 223369.43 | I10: =I6 -> 226152.02 | J10: =J6 -> 228481.92 | K10: =K6 -> 230597.54 | ... O10: =O6 -> 235619.07
A11: ='Distribution Dashboard'!#REF! -> #REF! | B11: ='Distribution Dashboard'!#REF! -> #REF! | C11: ='Distribution Dashboard'!#REF! -> #REF! | D11: =D15 -> 214810.57 | E11: =E15 -> 215882.84 | F11: =F15 -> 217038.9 | G11: =G15 -> 220378.23 | H11: =H15 -> 223369.43 | I11: =I15 -> 226152.02 | J11: =J15 -> 228481.92 | K11: =K15 -> 230597.54 | ... O11: =O15 -> 235619.07
A12: ='Distribution Dashboard'!#REF! -> #REF! | B12: ='Distribution Dashboard'!#REF! -> #REF! | C12: ='Distribution Dashboard'!#REF! -> #REF! | D12: =(D10-D11)/D10 -> 0 | E12: =(E10-E11)/E10 -> 0 | F12: =(F10-F11)/F10 -> 0 | G12: =(G10-G11)/G10 -> 0 | H12: =(H10-H11)/H10 -> 0 | I12: =(I10-I11)/I10 -> 0 | J12: =(J10-J11)/J10 -> 0 | K12: =(K10-K11)/K10 -> 0 | ... O12: =(O10-O11)/O10 -> 0
A13: ='Distribution Dashboard'!#REF! -> #REF!
A14: ='Distribution Dashboard'!A6 -> 0 | B14: ='Distribution Dashboard'!B6 -> REGIONAL NRW | C14: ='Distribution Dashboard'!C6 -> 0
A15: ='Distribution Dashboard'!A7 -> 100 | B15: ='Distribution Dashboard'!B7 -> WATER AVAILABLE FOR SALES- REGIONS | C15: ='Distribution Dashboard'!C7 -> m3 | D15: =D26+D35+D40 -> 214810.57 | E15: =E26+E35+E40 -> 215882.84 | F15: =F26+F35+F40 -> 217038.9 | G15: =G26+G35+G40 -> 220378.23 | H15: =H26+H35+H40 -> 223369.43 | I15: =I26+I35+I40 -> 226152.02 | J15: =J26+J35+J40 -> 228481.92 | K15: =K26+K35+K40 -> 230597.54 | ... Q15: =Q26+Q35+Q40 -> 0
A16: ='Distribution Dashboard'!A8 -> 128a | B16: ='Distribution Dashboard'!B8 -> VOLUME WATER BILLED(CUSTOMERS-M3) | C16: ='Distribution Dashboard'!C8 -> m3 | D16: =D27+D36+D41 -> 162967.74 | E16: =E27+E36+E41 -> 164996.23 | F16: =F27+F36+F41 -> 167133.61 | G16: =G27+G36+G41 -> 170794.25 | H16: =H27+H36+H41 -> 174251.4 | I16: =I27+I36+I41 -> 177638.11 | J16: =J27+J36+J41 -> 180823.44 | K16: =K27+K36+K41 -> 183888.91 | ... O16: =O27+O36+O41 -> 194059.96
A17: ='Distribution Dashboard'!A9 -> 128 | B17: ='Distribution Dashboard'!B9 -> GLOBAL NRW | C17: ='Distribution Dashboard'!C9 -> % | D17: =(D15-D16)/D15 -> 0.24134206 | E17: =(E15-E16)/E15 -> 0.23571401 | F17: =(F15-F16)/F15 -> 0.22993705 | G17: =(G15-G16)/G15 -> 0.22499491 | H17: =(H15-H16)/H15 -> 0.21989592 | I17: =(I15-I16)/I15 -> 0.21451902 | J17: =(J15-J16)/J15 -> 0.20858755 | K17: =(K15-K16)/K15 -> 0.20255476 | ... O17: =(O15-O16)/O15 -> 0.17638265
A18: ='Distribution Dashboard'!A10 -> 0 | B18: ='Distribution Dashboard'!B10 -> Number of Active water Connections | C18: ='Distribution Dashboard'!C10 -> NO.
A19: ='Distribution Dashboard'!A11 -> 0 | B19: ='Distribution Dashboard'!B11 -> Number of Active sewer Connections | C19: ='Distribution Dashboard'!C11 -> NO.
A20: ='Distribution Dashboard'!A12 -> 0 | B20: ='Distribution Dashboard'!B12 -> Number of In-active Sewer Connections | C20: ='Distribution Dashboard'!C12 -> NO.
A21: ='Distribution Dashboard'!A13 -> 0 | B21: ='Distribution Dashboard'!B13 -> Number of In-active Water Connections | C21: ='Distribution Dashboard'!C13 -> NO.
A22: ='Distribution Dashboard'!A14 -> 0 | B22: ='Distribution Dashboard'!B14 -> Number of Connections | C22: ='Distribution Dashboard'!C14 -> NO. | D22: =SUM(D18:D21) -> 0 | E22: =SUM(E18:E21) -> 0 | F22: =SUM(F18:F21) -> 0 | G22: =SUM(G18:G21) -> 0 | H22: =SUM(H18:H21) -> 0 | I22: =SUM(I18:I21) -> 0 | J22: =SUM(J18:J21) -> 0 | K22: =SUM(K18:K21) -> 0 | ... O22: =SUM(O18:O21) -> 0
A23: ='Distribution Dashboard'!A15 -> 0 | B23: ='Distribution Dashboard'!B15 -> Maintenance, repair and operational cost | C23: ='Distribution Dashboard'!C15 -> KES
A24: ='Distribution Dashboard'!#REF! -> #REF! | B24: ='Distribution Dashboard'!#REF! -> #REF! | C24: ='Distribution Dashboard'!#REF! -> #REF!
A25: ='Distribution Dashboard'!A16 -> 0 | B25: ='Distribution Dashboard'!B16 -> CENTRAL REGION: CBD,CCCR,KABATI,SITE,KIHOTO,LAKEVIEW | C25: ='Distribution Dashboard'!C16 -> 0
A26: ='Distribution Dashboard'!A17 -> RA | B26: ='Distribution Dashboard'!B17 -> Volume Water Supplied | C26: ='Distribution Dashboard'!C17 -> m3 | D26: =D45+D51+D57+D63+D69+D91+D75 -> 105295.52 | E26: =E45+E51+E57+E63+E69+E91+E75 -> 105074.89 | F26: =F45+F51+F57+F63+F69+F91+F75 -> 104857.33 | G26: =G45+G51+G57+G63+G69+G91+G75 -> 104642.77 | H26: =H45+H51+H57+H63+H69+H91+H75 -> 104431.15 | I26: =I45+I51+I57+I63+I69+I91+I75 -> 104222.41 | J26: =J45+J51+J57+J63+J69+J91+J75 -> 104016.48 | K26: =K45+K51+K57+K63+K69+K91+K75 -> 103813.31 | ... O26: =O45+O51+O57+O63+O69+O91+O75 -> 103027.06
A27: ='Distribution Dashboard'!A18 -> RA2 | B27: ='Distribution Dashboard'!B18 -> Volume Water Sold | C27: ='Distribution Dashboard'!C18 -> m3 | D27: =D46+D52+D58+D64+D70+D92+D76 -> 84480.117 | E27: =E46+E52+E58+E64+E70+E92+E76 -> 84961.98 | F27: =F46+F52+F58+F64+F70+F92+F76 -> 85443.842 | G27: =G46+G52+G58+G64+G70+G92+G76 -> 85925.704 | H27: =H46+H52+H58+H64+H70+H92+H76 -> 86407.566 | I27: =I46+I52+I58+I64+I70+I92+I76 -> 86889.428 | J27: =J46+J52+J58+J64+J70+J92+J76 -> 87371.291 | K27: =K46+K52+K58+K64+K70+K92+K76 -> 87853.153 | ... O27: =O46+O52+O58+O64+O70+O92+O76 -> 89780.602
A28: ='Distribution Dashboard'!A19 -> RA3 | B28: ='Distribution Dashboard'!B19 -> NRW | C28: ='Distribution Dashboard'!C19 -> m3 | D28: =D26-D27 -> 20815.406 | E28: =E26-E27 -> 20112.91 | F28: =F26-F27 -> 19413.486 | G28: =G26-G27 -> 18717.066 | H28: =H26-H27 -> 18023.586 | I28: =I26-I27 -> 17332.982 | J28: =J26-J27 -> 16645.193 | K28: =K26-K27 -> 15960.161 | ... O28: =O26-O27 -> 13246.463
A29: ='Distribution Dashboard'!A20 -> RA4 | B29: ='Distribution Dashboard'!B20 -> NRW | C29: ='Distribution Dashboard'!C20 -> % | D29: =D28/D26 -> 0.19768557 | E29: =E28/E26 -> 0.191415 | F29: =F28/F26 -> 0.18514191 | G29: =G28/G26 -> 0.17886631 | H29: =H28/H26 -> 0.17258821 | I29: =I28/I26 -> 0.16630763 | J29: =J28/J26 -> 0.16002457 | K29: =K28/K26 -> 0.15373905 | ... O29: =O28/O26 -> 0.12857265
A30: ='Distribution Dashboard'!A21 -> 0 | B30: ='Distribution Dashboard'!B21 -> Amount Billed Water | C30: ='Distribution Dashboard'!C21 -> KES
A31: ='Distribution Dashboard'!A22 -> 0 | B31: ='Distribution Dashboard'!B22 -> Amount Billed Sewer | C31: ='Distribution Dashboard'!C22 -> KES
A32: ='Distribution Dashboard'!A23 -> 0 | B32: ='Distribution Dashboard'!B23 -> Number of Active water Connections | C32: ='Distribution Dashboard'!C23 -> KES
A33: ='Distribution Dashboard'!A24 -> 0 | B33: ='Distribution Dashboard'!B24 -> Number of Active sewer Connections | C33: ='Distribution Dashboard'!C24 -> KES
A34: ='Distribution Dashboard'!A25 -> 0 | B34: ='Distribution Dashboard'!B25 -> SOUTHERN REGION: MAI MAHIU,KAMERE,HELLSGATE | C34: ='Distribution Dashboard'!C25 -> 0
A35: ='Distribution Dashboard'!A26 -> RA6 (B) | B35: ='Distribution Dashboard'!B26 -> Volume Water Supplied | C35: ='Distribution Dashboard'!C26 -> m3 | D35: =D79+D85+D103+D121 -> 74168.145 | E35: =E79+E85+E103+E121 -> 75099.246 | F35: =F79+F85+F103+F121 -> 76156.75 | G35: =G79+G85+G103+G121 -> 79439.402 | H35: =H79+H85+H103+H121 -> 82374.058 | I35: =I79+I85+I103+I121 -> 85141.043 | J35: =J79+J85+J103+J121 -> 87280.37 | K35: =K79+K85+K103+K121 -> 89353.394 | ... O35: =O79+O85+O103+O121 -> 94360.159
A36: ='Distribution Dashboard'!A27 -> RB2 | B36: ='Distribution Dashboard'!B27 -> Volume Water Sold | C36: ='Distribution Dashboard'!C27 -> m3 | D36: =D80+D86+D104+D122 -> 49682.108 | E36: =E80+E86+E104+E122 -> 50812.796 | F36: =F80+F86+F104+F122 -> 52082.386 | G36: =G80+G86+G104+G122 -> 54905.225 | H36: =H80+H86+H104+H122 -> 57524.584 | I36: =I80+I86+I104+I122 -> 60103.499 | J36: =J80+J86+J104+J122 -> 62333.999 | K36: =K80+K86+K104+K122 -> 64564.498 | ... O36: =O80+O86+O104+O122 -> 71530.431
A37: ='Distribution Dashboard'!A28 -> RB3 (2) | B37: ='Distribution Dashboard'!B28 -> NRW | C37: ='Distribution Dashboard'!C28 -> m3 | D37: =D35-D36 -> 24486.037 | E37: =E35-E36 -> 24286.45 | F37: =F35-F36 -> 24074.365 | G37: =G35-G36 -> 24534.176 | H37: =H35-H36 -> 24849.474 | I37: =I35-I36 -> 25037.544 | J37: =J35-J36 -> 24946.372 | K37: =K35-K36 -> 24788.896 | ... O37: =O35-O36 -> 22829.728
A38: ='Distribution Dashboard'!A29 -> RB4 | B38: ='Distribution Dashboard'!B29 -> NRW | C38: ='Distribution Dashboard'!C29 -> % | D38: =D37/D35 -> 0.33014223 | E38: =E37/E35 -> 0.32339139 | F38: =F37/F35 -> 0.31611597 | G38: =G37/G35 -> 0.3088414 | H38: =H37/H35 -> 0.30166626 | I38: =I37/I35 -> 0.29407138 | J38: =J37/J35 -> 0.28581881 | K38: =K37/K35 -> 0.27742534 | ... O38: =O37/O35 -> 0.24194245
A39: ='Distribution Dashboard'!A30 -> 0 | B39: ='Distribution Dashboard'!B30 -> EASTERN REGION: KAYOLE,GONDI, KINUNGI,NJONJORO | C39: ='Distribution Dashboard'!C30 -> 0
A40: ='Distribution Dashboard'!A31 -> RA6 (B) (2) | B40: ='Distribution Dashboard'!B31 -> Volume Water Supplied | C40: ='Distribution Dashboard'!C31 -> m3 | D40: =D125+D97 -> 35346.901 | E40: =E125+E97 -> 35708.701 | F40: =F125+F97 -> 36024.819 | G40: =G125+G97 -> 36296.056 | H40: =H125+H97 -> 36564.217 | I40: =I125+I97 -> 36788.567 | J40: =J125+J97 -> 37185.07 | K40: =K125+K97 -> 37430.836 | ... O40: =O125+O97 -> 38231.852
A41: ='Distribution Dashboard'!A32 -> RB2 (3) | B41: ='Distribution Dashboard'!B32 -> Volume Water Sold | C41: ='Distribution Dashboard'!C32 -> m3 | D41: =D98+D126 -> 28805.519 | E41: =E98+E126 -> 29221.452 | F41: =F98+F126 -> 29607.385 | G41: =G98+G126 -> 29963.318 | H41: =H98+H126 -> 30319.251 | I41: =I98+I126 -> 30645.184 | J41: =J98+J126 -> 31118.15 | K41: =K98+K126 -> 31471.261 | ... O41: =O98+O126 -> 32748.926
A42: ='Distribution Dashboard'!A33 -> RB3 (3) | B42: ='Distribution Dashboard'!B33 -> NRW | C42: ='Distribution Dashboard'!C33 -> m3 | D42: =D40-D41 -> 6541.3823 | E42: =E40-E41 -> 6487.2487 | F42: =F40-F41 -> 6417.4338 | G42: =G40-G41 -> 6332.7377 | H42: =H40-H41 -> 6244.9654 | I42: =I40-I41 -> 6143.3829 | J42: =J40-J41 -> 6066.9204 | K42: =K40-K41 -> 5959.5747 | ... O42: =O40-O41 -> 5482.926
A43: ='Distribution Dashboard'!A33 -> RB3 (3) | B43: ='Distribution Dashboard'!B34 -> NRW | C43: ='Distribution Dashboard'!C33 -> m3 | D43: =D42/D40 -> 0.1850624 | E43: =E42/E40 -> 0.18167137 | F43: =F42/F40 -> 0.17813924 | G43: =G42/G40 -> 0.17447454 | H43: =H42/H40 -> 0.17079445 | I43: =I42/I40 -> 0.16699163 | J43: =J42/J40 -> 0.16315474 | K43: =K42/K40 -> 0.15921565 | ... O43: =O42/O40 -> 0.14341252
A44: ='Distribution Dashboard'!A34 -> RB4 (2) | B44: ='Distribution Dashboard'!B35 -> ZONE - CBD | C44: ='Distribution Dashboard'!C34 -> %
A45: ='Distribution Dashboard'!A36 -> 101 | B45: ='Distribution Dashboard'!B36 -> Volume Water Supplied | C45: ='Distribution Dashboard'!C36 -> m3 | D45: 21082.243 | E45: 20981.407 | F45: 20881.679 | G45: 20783.041 | H45: 20685.476 | I45: 20588.965 | J45: 20493.492 | K45: 20399.04 | L45: 20305.593 | M45: 20213.135 | N45: 20121.649 | O45: 20031.122
A46: ='Distribution Dashboard'!A37 -> 108 | B46: ='Distribution Dashboard'!B37 -> Volume Water Sold | C46: ='Distribution Dashboard'!C37 -> m3 | D46: 16134.37 | E46: 16146.406 | F46: 16158.443 | G46: 16170.479 | H46: 16182.516 | I46: 16194.552 | J46: 16206.589 | K46: 16218.625 | L46: 16230.661 | M46: 16242.698 | N46: 16254.734 | O46: 16266.771
A47: ='Distribution Dashboard'!A38 -> 122 | B47: ='Distribution Dashboard'!B38 -> NRW | C47: ='Distribution Dashboard'!C38 -> % | D47: =(D45-D46)/D45 -> 0.23469385 | E47: =(E45-E46)/E45 -> 0.23044215 | F47: =(F45-F46)/F45 -> 0.22619045 | G47: =(G45-G46)/G45 -> 0.22193875 | H47: =(H45-H46)/H45 -> 0.21768705 | I47: =(I45-I46)/I45 -> 0.21343535 | J47: =(J45-J46)/J45 -> 0.20918365 | K47: =(K45-K46)/K45 -> 0.20493195 | ... O47: =(O45-O46)/O45 -> 0.18792515
A48: ='Distribution Dashboard'!A39 -> 0 | B48: ='Distribution Dashboard'!B39 -> Amount Billed Water | C48: ='Distribution Dashboard'!C39 -> KES
A49: ='Distribution Dashboard'!A40 -> 0 | B49: ='Distribution Dashboard'!B40 -> Amount Billed Sewer | C49: ='Distribution Dashboard'!C40 -> KES
A50: ='Distribution Dashboard'!A41 -> 0 | B50: ='Distribution Dashboard'!B41 -> ZONE - CCCR | C50: ='Distribution Dashboard'!C41 -> 0
A51: ='Distribution Dashboard'!A42 -> 102 | B51: ='Distribution Dashboard'!B42 -> Volume Water Supplied | C51: ='Distribution Dashboard'!C42 -> m3 | D51: 19036.909 | E51: 19122.59 | F51: 19206.523 | G51: 19288.76 | H51: 19369.352 | I51: 19448.349 | J51: 19525.796 | K51: 19601.74 | L51: 19676.223 | M51: 19749.287 | N51: 19820.973 | O51: 19891.319
A52: ='Distribution Dashboard'!A43 -> 109 | B52: ='Distribution Dashboard'!B43 -> Volume Water Sold | C52: ='Distribution Dashboard'!C43 -> m3 | D52: 15540.335 | E52: 15772.885 | F52: 16005.436 | G52: 16237.987 | H52: 16470.538 | I52: 16703.089 | J52: 16935.64 | K52: 17168.191 | L52: 17400.742 | M52: 17633.293 | N52: 17865.844 | O52: 18098.395
A53: ='Distribution Dashboard'!A44 -> 123 | B53: ='Distribution Dashboard'!B44 -> NRW | C53: ='Distribution Dashboard'!C44 -> % | D53: =(D51-D52)/D51 -> 0.18367344 | E53: =(E51-E52)/E51 -> 0.17517004 | F53: =(F51-F52)/F51 -> 0.16666664 | G53: =(G51-G52)/G51 -> 0.15816324 | H53: =(H51-H52)/H51 -> 0.14965984 | I53: =(I51-I52)/I51 -> 0.14115644 | J53: =(J51-J52)/J51 -> 0.13265304 | K53: =(K51-K52)/K51 -> 0.12414963 | ... O53: =(O51-O52)/O51 -> 0.090136027
A54: ='Distribution Dashboard'!A45 -> 0 | B54: ='Distribution Dashboard'!B45 -> Amount Billed Water | C54: ='Distribution Dashboard'!C45 -> KES
A55: ='Distribution Dashboard'!A46 -> 0 | B55: ='Distribution Dashboard'!B46 -> Amount Billed Sewer | C55: ='Distribution Dashboard'!C46 -> KES
A56: ='Distribution Dashboard'!A47 -> 0 | B56: ='Distribution Dashboard'!B47 -> ZONE - LAKEVIEW | C56: ='Distribution Dashboard'!C47 -> 0
A57: ='Distribution Dashboard'!A48 -> 104 | B57: ='Distribution Dashboard'!B48 -> Volume Water Supplied | C57: ='Distribution Dashboard'!C48 -> m3 | D57: 26498.756 | E57: 26392.101 | F57: 26287.017 | G57: 26183.47 | H57: 26081.427 | I57: 25980.855 | J57: 25881.723 | K57: 25784 | L57: 25687.656 | M57: 25592.662 | N57: 25498.99 | O57: 25406.613
A58: ='Distribution Dashboard'!A49 -> 111 | B58: ='Distribution Dashboard'!B49 -> Volume Water Sold | C58: ='Distribution Dashboard'!C49 -> m3 | D58: 21090.848 | E58: 21163.054 | F58: 21235.261 | G58: 21307.467 | H58: 21379.674 | I58: 21451.88 | J58: 21524.086 | K58: 21596.293 | L58: 21668.499 | M58: 21740.706 | N58: 21812.912 | O58: 21885.119
A59: ='Distribution Dashboard'!A50 -> 125 | B59: ='Distribution Dashboard'!B50 -> NRW | C59: ='Distribution Dashboard'!C50 -> % | D59: =(D57-D58)/D57 -> 0.20408161 | E59: =(E57-E58)/E57 -> 0.19812923 | F59: =(F57-F58)/F57 -> 0.19217685 | G59: =(G57-G58)/G57 -> 0.18622447 | H59: =(H57-H58)/H57 -> 0.18027208 | I59: =(I57-I58)/I57 -> 0.1743197 | J59: =(J57-J58)/J57 -> 0.16836732 | K59: =(K57-K58)/K57 -> 0.16241494 | ... O59: =(O57-O58)/O57 -> 0.13860542
A60: ='Distribution Dashboard'!A51 -> 0 | B60: ='Distribution Dashboard'!B51 -> Amount Billed Water | C60: ='Distribution Dashboard'!C51 -> KES
A61: ='Distribution Dashboard'!A52 -> 0 | B61: ='Distribution Dashboard'!B52 -> Amount Billed Sewer | C61: ='Distribution Dashboard'!C52 -> KES
A62: ='Distribution Dashboard'!A53 -> 0 | B62: ='Distribution Dashboard'!B53 -> ZONE - KABATI | C62: ='Distribution Dashboard'!C53 -> 0
A63: ='Distribution Dashboard'!A54 -> 103 | B63: ='Distribution Dashboard'!B54 -> Volume Water Supplied | C63: ='Distribution Dashboard'!C54 -> m3 | D63: 16735.652 | E63: 16734.288 | F63: 16732.941 | G63: 16731.611 | H63: 16730.298 | I63: 16729.001 | J63: 16727.719 | K63: 16726.453 | L63: 16725.202 | M63: 16723.966 | N63: 16722.745 | O63: 16721.539
A64: ='Distribution Dashboard'!A55 -> 110 | B64: ='Distribution Dashboard'!B55 -> Volume Water Sold | C64: ='Distribution Dashboard'!C55 -> m3 | D64: 13490.985 | E64: 13575.265 | F64: 13659.544 | G64: 13743.824 | H64: 13828.104 | I64: 13912.384 | J64: 13996.663 | K64: 14080.943 | L64: 14165.223 | M64: 14249.502 | N64: 14333.782 | O64: 14418.062
A65: ='Distribution Dashboard'!A56 -> 124 | B65: ='Distribution Dashboard'!B56 -> NRW | C65: ='Distribution Dashboard'!C56 -> % | D65: =(D63-D64)/D63 -> 0.19387753 | E65: =(E63-E64)/E63 -> 0.18877549 | F65: =(F63-F64)/F63 -> 0.18367344 | G65: =(G63-G64)/G63 -> 0.1785714 | H65: =(H63-H64)/H63 -> 0.17346936 | I65: =(I63-I64)/I63 -> 0.16836732 | J65: =(J63-J64)/J63 -> 0.16326528 | K65: =(K63-K64)/K63 -> 0.15816324 | ... O65: =(O63-O64)/O63 -> 0.13775508
A66: ='Distribution Dashboard'!A57 -> 0 | B66: ='Distribution Dashboard'!B57 -> Amount Billed | C66: ='Distribution Dashboard'!C57 -> KES
A67: ='Distribution Dashboard'!A58 -> 0 | B67: ='Distribution Dashboard'!B58 -> Amount Billed Sewer | C67: ='Distribution Dashboard'!C58 -> KES
A68: ='Distribution Dashboard'!A59 -> 0 | B68: ='Distribution Dashboard'!B59 -> ZONE - SITE AND SERVICES | C68: ='Distribution Dashboard'!C59 -> 0
A69: ='Distribution Dashboard'!A60 -> 105 | B69: ='Distribution Dashboard'!B60 -> Volume Water Supplied | C69: ='Distribution Dashboard'!C60 -> m3 | D69: 13140.285 | E69: 13023.102 | F69: 12908.31 | G69: 12795.837 | H69: 12685.613 | I69: 12577.573 | J69: 12471.65 | K69: 12367.785 | L69: 12265.917 | M69: 12165.989 | N69: 12067.947 | O69: 11971.737
A70: ='Distribution Dashboard'!A61 -> 112 | B70: ='Distribution Dashboard'!B61 -> Volume Water Sold | C70: ='Distribution Dashboard'!C61 -> m3 | D70: 10726.764 | E70: 10741.844 | F70: 10756.925 | G70: 10772.006 | H70: 10787.087 | I70: 10802.167 | J70: 10817.248 | K70: 10832.329 | L70: 10847.41 | M70: 10862.49 | N70: 10877.571 | O70: 10892.652
A71: ='Distribution Dashboard'!A62 -> 126 | B71: ='Distribution Dashboard'!B62 -> NRW | C71: ='Distribution Dashboard'!C62 -> % | D71: =(D69-D70)/D69 -> 0.18367344 | E71: =(E69-E70)/E69 -> 0.17517004 | F71: =(F69-F70)/F69 -> 0.16666664 | G71: =(G69-G70)/G69 -> 0.15816324 | H71: =(H69-H70)/H69 -> 0.14965984 | I71: =(I69-I70)/I69 -> 0.14115644 | J71: =(J69-J70)/J69 -> 0.13265304 | K71: =(K69-K70)/K69 -> 0.12414963 | ... O71: =(O69-O70)/O69 -> 0.090136027
A72: ='Distribution Dashboard'!A63 -> 0 | B72: ='Distribution Dashboard'!B63 -> Amount Billed Water | C72: ='Distribution Dashboard'!C63 -> KES
A73: ='Distribution Dashboard'!A64 -> 0 | B73: ='Distribution Dashboard'!B64 -> Amount Billed Sewer | C73: ='Distribution Dashboard'!C64 -> KES
A74: ='Distribution Dashboard'!A65 -> 0 | B74: ='Distribution Dashboard'!B65 -> ZONE - HOPEWELL | C74: ='Distribution Dashboard'!C65 -> 0
A75: ='Distribution Dashboard'!A66 -> 105B | B75: ='Distribution Dashboard'!B66 -> Volume Water Supplied | C75: ='Distribution Dashboard'!C66 -> m3 | D75: 6727.3147 | E75: 6745.8519 | F75: 6764.1322 | G75: 6782.1608 | H75: 6799.9429 | I75: 6817.4835 | J75: 6834.7876 | K75: 6851.8599 | L75: 6868.7049 | M75: 6885.3273 | N75: 6901.7313 | O75: 6917.9214
A76: ='Distribution Dashboard'!A67 -> 112B | B76: ='Distribution Dashboard'!B67 -> Volume Water Sold | C76: ='Distribution Dashboard'!C67 -> m3 | D76: 5697.6239 | E76: 5753.4776 | F76: 5809.3314 | G76: 5865.1851 | H76: 5921.0389 | I76: 5976.8926 | J76: 6032.7464 | K76: 6088.6002 | L76: 6144.4539 | M76: 6200.3077 | N76: 6256.1614 | O76: 6312.0152
A77: ='Distribution Dashboard'!A68 -> 126B | B77: ='Distribution Dashboard'!B68 -> NRW | C77: ='Distribution Dashboard'!C68 -> % | D77: =(D75-D76)/D75 -> 0.1530612 | E77: =(E75-E76)/E75 -> 0.14710882 | F77: =(F75-F76)/F75 -> 0.14115644 | G77: =(G75-G76)/G75 -> 0.13520406 | H77: =(H75-H76)/H75 -> 0.12925167 | I77: =(I75-I76)/I75 -> 0.12329929 | J77: =(J75-J76)/J75 -> 0.11734691 | K77: =(K75-K76)/K75 -> 0.11139453 | ... O77: =(O75-O76)/O75 -> 0.087585007
A78: ='Distribution Dashboard'!A69 -> 0 | B78: ='Distribution Dashboard'!B69 -> ZONE - KAMERE | C78: ='Distribution Dashboard'!C69 -> 0
A79: ='Distribution Dashboard'!A70 -> 106 | B79: ='Distribution Dashboard'!B70 -> Volume Water Supplied | C79: ='Distribution Dashboard'!C70 -> m3 | D79: 8583.3921 | E79: 8528.5363 | F79: 8474.5581 | G79: 8896.2257 | H79: 9075.7277 | I79: 9252.4249 | J79: 9426.3826 | K79: 9597.6641 | L79: 9766.3306 | M79: 9932.4415 | N79: 10096.055 | O79: 10257.226
A80: ='Distribution Dashboard'!A71 -> 113 | B80: ='Distribution Dashboard'!B71 -> Volume Water Sold | C80: ='Distribution Dashboard'!C71 -> m3 | D80: 7182.0222 | E80: 7194.1397 | F80: 7206.2571 | G80: 7625.3366 | H80: 7840.935 | I80: 8056.5335 | J80: 8272.132 | K80: 8487.7304 | L80: 8703.3289 | M80: 8918.9273 | N80: 9134.5258 | O80: 9350.1243
A81: ='Distribution Dashboard'!A72 -> 127 | B81: ='Distribution Dashboard'!B72 -> NRW | C81: ='Distribution Dashboard'!C72 -> % | D81: =(D79-D80)/D79 -> 0.16326528 | E81: =(E79-E80)/E79 -> 0.15646256 | F81: =(F79-F80)/F79 -> 0.14965984 | G81: =(G79-G80)/G79 -> 0.14285712 | H81: =(H79-H80)/H79 -> 0.1360544 | I81: =(I79-I80)/I79 -> 0.12925167 | J81: =(J79-J80)/J79 -> 0.12244895 | K81: =(K79-K80)/K79 -> 0.11564623 | ... O81: =(O79-O80)/O79 -> 0.088435347
A82: ='Distribution Dashboard'!A73 -> 0 | B82: ='Distribution Dashboard'!B73 -> Amount Billed Water | C82: ='Distribution Dashboard'!C73 -> KES
A83: ='Distribution Dashboard'!A74 -> 0 | B83: ='Distribution Dashboard'!B74 -> Amount Billed Sewer | C83: ='Distribution Dashboard'!C74 -> KES
A84: ='Distribution Dashboard'!A75 -> 0 | B84: ='Distribution Dashboard'!B75 -> ZONE - HELLS GATE | C84: ='Distribution Dashboard'!C75 -> 0
A85: ='Distribution Dashboard'!A76 -> 103 (3) | B85: ='Distribution Dashboard'!B76 -> Volume Water Supplied | C85: ='Distribution Dashboard'!C76 -> m3 | D85: 37441.323 | E85: 37396.341 | F85: 37600.019 | G85: 38478.289 | H85: 39346.347 | I85: 40204.37 | J85: 40941.647 | K85: 41670.497 | L85: 42191.339 | M85: 42597.291 | N85: 42998.682 | O85: 43356.312
A86: ='Distribution Dashboard'!A77 -> 110 (3) | B86: ='Distribution Dashboard'!B77 -> Volume Water Sold | C86: ='Distribution Dashboard'!C77 -> m3 | D86: 26743.803 | E86: 26870.671 | F86: 27176.885 | G86: 27975.288 | H86: 28773.69 | I86: 29572.093 | J86: 30288.464 | K86: 31004.835 | L86: 31571.751 | M86: 32056.636 | N86: 32541.521 | O86: 32996.514
A87: ='Distribution Dashboard'!A78 -> 124 (3) | B87: ='Distribution Dashboard'!B78 -> NRW | C87: ='Distribution Dashboard'!C78 -> % | D87: =(D85-D86)/D85 -> 0.28571426 | E87: =(E85-E86)/E85 -> 0.28146256 | F87: =(F85-F86)/F85 -> 0.27721086 | G87: =(G85-G86)/G85 -> 0.27295916 | H87: =(H85-H86)/H85 -> 0.26870746 | I87: =(I85-I86)/I85 -> 0.26445576 | J87: =(J85-J86)/J85 -> 0.26020406 | K87: =(K85-K86)/K85 -> 0.25595236 | ... O87: =(O85-O86)/O85 -> 0.23894556
A88: ='Distribution Dashboard'!A79 -> 0 | B88: ='Distribution Dashboard'!B79 -> Amount Billed Water | C88: ='Distribution Dashboard'!C79 -> KES
A89: ='Distribution Dashboard'!A80 -> 0 | B89: ='Distribution Dashboard'!B80 -> Amount Billed Sewer | C89: ='Distribution Dashboard'!C80 -> KES
A90: ='Distribution Dashboard'!A81 -> 0 | B90: ='Distribution Dashboard'!B81 -> KIHOTO | C90: ='Distribution Dashboard'!C81 -> 0
A91: ='Distribution Dashboard'!A82 -> 103 (2) | B91: ='Distribution Dashboard'!B82 -> Volume Water Supplied | C91: ='Distribution Dashboard'!C82 -> m3 | D91: 2074.3637 | E91: 2075.5507 | F91: 2076.7261 | G91: 2077.8902 | H91: 2079.0431 | I91: 2080.1849 | J91: 2081.3159 | K91: 2082.4362 | L91: 2083.5459 | M91: 2084.6452 | N91: 2085.7342 | O91: 2086.813
A92: ='Distribution Dashboard'!A83 -> 110 (2) | B92: ='Distribution Dashboard'!B83 -> Volume Water Sold | C92: ='Distribution Dashboard'!C83 -> m3 | D92: 1799.193 | E92: 1809.0472 | F92: 1818.9013 | G92: 1828.7554 | H92: 1838.6096 | I92: 1848.4637 | J92: 1858.3178 | K92: 1868.172 | L92: 1878.0261 | M92: 1887.8802 | N92: 1897.7344 | O92: 1907.5885
A93: ='Distribution Dashboard'!A84 -> 124 (2) | B93: ='Distribution Dashboard'!B84 -> NRW | C93: ='Distribution Dashboard'!C84 -> % | D93: =(D91-D92)/D91 -> 0.13265304 | E93: =(E91-E92)/E91 -> 0.12840133 | F93: =(F91-F92)/F91 -> 0.12414963 | G93: =(G91-G92)/G91 -> 0.11989793 | H93: =(H91-H92)/H91 -> 0.11564623 | I93: =(I91-I92)/I91 -> 0.11139453 | J93: =(J91-J92)/J91 -> 0.10714283 | K93: =(K91-K92)/K91 -> 0.10289113 | ... O93: =(O91-O92)/O91 -> 0.085884326
A94: ='Distribution Dashboard'!A85 -> 0 | B94: ='Distribution Dashboard'!B85 -> Amount Billed Water | C94: ='Distribution Dashboard'!C85 -> KES
A95: ='Distribution Dashboard'!A86 -> 0 | B95: ='Distribution Dashboard'!B86 -> Amount Billed Sewer | C95: ='Distribution Dashboard'!C86 -> KES
A96: ='Distribution Dashboard'!A87 -> 0 | B96: ='Distribution Dashboard'!B87 -> KAYOLE | C96: ='Distribution Dashboard'!C87 -> 0
A97: ='Distribution Dashboard'!A88 -> 103 (4) | B97: ='Distribution Dashboard'!B88 -> Volume Water Supplied | C97: ='Distribution Dashboard'!C88 -> m3 | D97: 34865.768 | E97: 34921.453 | F97: 34976.565 | G97: 35031.111 | H97: 35085.1 | I97: 35138.542 | J97: 35366.1 | K97: 35485.172 | L97: 35603.053 | M97: 35667.19 | N97: 35730.692 | O97: 35793.568
A98: ='Distribution Dashboard'!A89 -> 110 (4) | B98: ='Distribution Dashboard'!B89 -> Volume Water Sold | C98: ='Distribution Dashboard'!C89 -> m3 | D98: 28461.852 | E98: 28655.785 | F98: 28849.718 | G98: 29043.651 | H98: 29237.585 | I98: 29431.518 | J98: 29772.483 | K98: 30023.595 | L98: 30274.706 | M98: 30480.89 | N98: 30687.075 | O98: 30893.259
A99: ='Distribution Dashboard'!A90 -> 124 (4) | B99: ='Distribution Dashboard'!B90 -> NRW | C99: ='Distribution Dashboard'!C90 -> % | D99: =(D97-D98)/D97 -> 0.18367344 | E99: =(E97-E98)/E97 -> 0.17942174 | F99: =(F97-F98)/F97 -> 0.17517004 | G99: =(G97-G98)/G97 -> 0.17091834 | H99: =(H97-H98)/H97 -> 0.16666664 | I99: =(I97-I98)/I97 -> 0.16241494 | J99: =(J97-J98)/J97 -> 0.15816324 | K99: =(K97-K98)/K97 -> 0.15391154 | ... O99: =(O97-O98)/O97 -> 0.13690474
A100: ='Distribution Dashboard'!A91 -> 0 | B100: ='Distribution Dashboard'!B91 -> Amount Billed Water | C100: ='Distribution Dashboard'!C91 -> KES
...

Sheet Actuals2526
A1: ='Distribution Dashboard'!A1 -> NAIVAWASS DISTRIBUTION DASHBOARD - NON-REVENUE WATER & ZONAL PERFORMANCE | B1: ='Distribution Dashboard'!B1 -> 0 | C1: ='Distribution Dashboard'!D1 -> 0
A2: ='Distribution Dashboard'!A2 -> 0 | B2: ='Distribution Dashboard'!B2 -> 46054 | C2: ='Distribution Dashboard'!D2 -> 0
A3: ='Distribution Dashboard'!A3 -> 0 | B3: ='Distribution Dashboard'!B3 -> 0 | C3: ='Distribution Dashboard'!D3 -> Monthly
A4: ='Distribution Dashboard'!A4 -> 0 | C4: ='Distribution Dashboard'!C4 -> Unit | D4: 45839 | E4: 45870 | F4: 45901 | G4: 45931 | H4: 45962 | I4: 45992 | J4: 46023 | K4: 46054 | L4: 46082 | M4: 46113 | N4: 46143 | O4: 46174
A5: ='Distribution Dashboard'!#REF! -> #REF! | B5: ='Distribution Dashboard'!#REF! -> #REF! | C5: ='Distribution Dashboard'!#REF! -> #REF!
A6: ='Distribution Dashboard'!#REF! -> #REF! | B6: ='Distribution Dashboard'!#REF! -> #REF! | C6: ='Distribution Dashboard'!#REF! -> #REF! | D6: =D11 -> 203624 | E6: =E11 -> 229218 | F6: =F11 -> 194924 | G6: =G11 -> 247237 | H6: =H11 -> 181647 | I6: =I11 -> 180291 | J6: =J11 -> 258170 | K6: =K11 -> 222543 | ... O6: =O11 -> 0
A7: ='Distribution Dashboard'!#REF! -> #REF! | B7: ='Distribution Dashboard'!#REF! -> #REF! | C7: ='Distribution Dashboard'!#REF! -> #REF! | D7: =D16 -> 146435 | E7: =E16 -> 173295 | F7: =F16 -> 145984 | G7: =G16 -> 171125 | H7: =H16 -> 135132 | I7: =I16 -> 131036 | J7: =J16 -> 200570 | K7: =K16 -> 172266 | ... O7: =O16 -> 0
A8: ='Distribution Dashboard'!#REF! -> #REF! | B8: ='Distribution Dashboard'!#REF! -> #REF! | C8: ='Distribution Dashboard'!#REF! -> #REF! | D8: =(D6-D7)/D6 -> 0.28085589 | E8: =(E6-E7)/E6 -> 0.24397299 | F8: =(F6-F7)/F6 -> 0.25107221 | G8: =(G6-G7)/G6 -> 0.30785036 | H8: =(H6-H7)/H6 -> 0.25607359 | I8: =(I6-I7)/I6 -> 0.27319722 | J8: =(J6-J7)/J6 -> 0.2231088 | K8: =(K6-K7)/K6 -> 0.22592038 | ... O8: =(O6-O7)/O6 -> #DIV/0!
A9: ='Distribution Dashboard'!#REF! -> #REF!
A10: ='Distribution Dashboard'!#REF! -> #REF! | B10: ='Distribution Dashboard'!#REF! -> #REF! | C10: ='Distribution Dashboard'!#REF! -> #REF! | D10: =D6 -> 203624 | E10: =E6 -> 229218 | F10: =F6 -> 194924 | G10: =G6 -> 247237 | H10: =H6 -> 181647 | I10: =I6 -> 180291 | J10: =J6 -> 258170 | K10: =K6 -> 222543 | ... O10: =O6 -> 0
A11: ='Distribution Dashboard'!#REF! -> #REF! | B11: ='Distribution Dashboard'!#REF! -> #REF! | C11: ='Distribution Dashboard'!#REF! -> #REF! | D11: =D15 -> 203624 | E11: =E15 -> 229218 | F11: =F15 -> 194924 | G11: =G15 -> 247237 | H11: =H15 -> 181647 | I11: =I15 -> 180291 | J11: =J15 -> 258170 | K11: =K15 -> 222543 | ... O11: =O15 -> 0
A12: ='Distribution Dashboard'!#REF! -> #REF! | B12: ='Distribution Dashboard'!#REF! -> #REF! | C12: ='Distribution Dashboard'!#REF! -> #REF! | D12: =(D10-D11)/D10 -> 0 | E12: =(E10-E11)/E10 -> 0 | F12: =(F10-F11)/F10 -> 0 | G12: =(G10-G11)/G10 -> 0 | H12: =(H10-H11)/H10 -> 0 | I12: =(I10-I11)/I10 -> 0 | J12: =(J10-J11)/J10 -> 0 | K12: =(K10-K11)/K10 -> 0 | ... O12: =(O10-O11)/O10 -> #DIV/0!
A13: ='Distribution Dashboard'!#REF! -> #REF! | B13: ='Distribution Dashboard'!#REF! -> #REF! | C13: ='Distribution Dashboard'!#REF! -> #REF! | D13: =D10-D11 -> 0 | E13: =E10-E11 -> 0 | F13: =F10-F11 -> 0 | G13: =G10-G11 -> 0 | H13: =H10-H11 -> 0 | I13: =I10-I11 -> 0 | J13: =J10-J11 -> 0 | K13: =K10-K11 -> 0 | ... O13: =O10-O11 -> 0
A14: ='Distribution Dashboard'!A6 -> 0 | B14: ='Distribution Dashboard'!B6 -> REGIONAL NRW | C14: ='Distribution Dashboard'!C6 -> 0
A15: ='Distribution Dashboard'!A7 -> 100 | B15: ='Distribution Dashboard'!B7 -> WATER AVAILABLE FOR SALES- REGIONS | C15: ='Distribution Dashboard'!C7 -> m3 | D15: =D26+D35+D40 -> 203624 | E15: =E26+E35+E40 -> 229218 | F15: =F26+F35+F40 -> 194924 | G15: =G26+G35+G40 -> 247237 | H15: =H26+H35+H40 -> 181647 | I15: =I26+I35+I40 -> 180291 | J15: =J26+J35+J40 -> 258170 | K15: =K26+K35+K40 -> 222543 | ... O15: =O26+O35+O40 -> 0
A16: ='Distribution Dashboard'!A8 -> 128a | B16: ='Distribution Dashboard'!B8 -> VOLUME WATER BILLED(CUSTOMERS-M3) | C16: ='Distribution Dashboard'!C8 -> m3 | D16: =D27+D41+D36 -> 146435 | E16: =E27+E41+E36 -> 173295 | F16: =F27+F41+F36 -> 145984 | G16: =G27+G41+G36 -> 171125 | H16: =H27+H41+H36 -> 135132 | I16: =I27+I41+I36 -> 131036 | J16: =J27+J41+J36 -> 200570 | K16: =K27+K41+K36 -> 172266 | ... O16: =O27+O41+O36 -> 0
A17: ='Distribution Dashboard'!A9 -> 128 | B17: ='Distribution Dashboard'!B9 -> GLOBAL NRW | C17: ='Distribution Dashboard'!C9 -> % | D17: =(D15-D16)/D15 -> 0.28085589 | E17: =(E15-E16)/E15 -> 0.24397299 | F17: =(F15-F16)/F15 -> 0.25107221 | G17: =(G15-G16)/G15 -> 0.30785036 | H17: =(H15-H16)/H15 -> 0.25607359 | I17: =(I15-I16)/I15 -> 0.27319722 | J17: =(J15-J16)/J15 -> 0.2231088 | K17: =(K15-K16)/K15 -> 0.22592038 | ... O17: =(O15-O16)/O15 -> #DIV/0!
A18: ='Distribution Dashboard'!A10 -> 0 | B18: ='Distribution Dashboard'!B10 -> Number of Active water Connections | C18: ='Distribution Dashboard'!C10 -> NO. | D18: =D41+D32 -> 31567 | E18: =E41+E32 -> 30396 | F18: =F41+F32 -> 26239 | G18: =G41+G32 -> 28789 | H18: =H41+H32 -> 24966 | I18: =I41+I32 -> 26222 | J18: =J41+J32 -> 31253 | K18: =K41+K32 -> 33645 | ... O18: =O41+O32 -> 0
A19: ='Distribution Dashboard'!A11 -> 0 | B19: ='Distribution Dashboard'!B11 -> Number of Active sewer Connections | C19: ='Distribution Dashboard'!C11 -> NO. | D19: =D42+D33 -> 9642 | E19: =E42+E33 -> 9594 | F19: =F42+F33 -> 10486 | G19: =G42+G33 -> 20017 | H19: =H42+H33 -> 8560 | I19: =I42+I33 -> 8907 | J19: =J42+J33 -> 10970 | K19: =K42+K33 -> 9427 | ... O19: =O42+O33 -> 0
A20: ='Distribution Dashboard'!A12 -> 0 | B20: ='Distribution Dashboard'!B12 -> Number of In-active Sewer Connections | C20: ='Distribution Dashboard'!C12 -> NO.
A21: ='Distribution Dashboard'!A13 -> 0 | B21: ='Distribution Dashboard'!B13 -> Number of In-active Water Connections | C21: ='Distribution Dashboard'!C13 -> NO.
A22: ='Distribution Dashboard'!A14 -> 0 | B22: ='Distribution Dashboard'!B14 -> Number of Connections | C22: ='Distribution Dashboard'!C14 -> NO. | D22: =SUM(D18:D21) -> 41209 | E22: =SUM(E18:E21) -> 39990 | F22: =SUM(F18:F21) -> 36725 | G22: =SUM(G18:G21) -> 48806 | H22: =SUM(H18:H21) -> 33526 | I22: =SUM(I18:I21) -> 35129 | J22: =SUM(J18:J21) -> 42223 | K22: =SUM(K18:K21) -> 43072 | ... O22: =SUM(O18:O21) -> 0
A23: ='Distribution Dashboard'!A15 -> 0 | B23: ='Distribution Dashboard'!B15 -> Maintenance, repair and operational cost | C23: ='Distribution Dashboard'!C15 -> KES
A24: ='Distribution Dashboard'!#REF! -> #REF! | B24: ='Distribution Dashboard'!#REF! -> #REF! | C24: ='Distribution Dashboard'!#REF! -> #REF!
A25: ='Distribution Dashboard'!A16 -> 0 | B25: ='Distribution Dashboard'!B16 -> CENTRAL REGION: CBD,CCCR,KABATI,SITE,KIHOTO,LAKEVIEW | C25: ='Distribution Dashboard'!C16 -> 0
A26: ='Distribution Dashboard'!A17 -> RA | B26: ='Distribution Dashboard'!B17 -> Volume Water Supplied | C26: ='Distribution Dashboard'!C17 -> m3 | D26: =D45+D51+D57+D63+D69+D91+D75 -> 99588 | E26: =E45+E51+E57+E63+E69+E91+E75 -> 104217 | F26: =F45+F51+F57+F63+F69+F91+F75 -> 100946 | G26: =G45+G51+G57+G63+G69+G91+G75 -> 110522 | H26: =H45+H51+H57+H63+H69+H91+H75 -> 92662 | I26: =I45+I51+I57+I63+I69+I91+I75 -> 84151 | J26: =J45+J51+J57+J63+J69+J91+J75 -> 126366 | K26: =K45+K51+K57+K63+K69+K91+K75 -> 101836 | ... O26: =O45+O51+O57+O63+O69+O91+O75 -> 0
A27: ='Distribution Dashboard'!A18 -> RA2 | B27: ='Distribution Dashboard'!B18 -> Volume Water Sold | C27: ='Distribution Dashboard'!C18 -> m3 | D27: =D46+D52+D58+D64+D70+D92+D76 -> 72362 | E27: =E46+E52+E58+E64+E70+E92+E76 -> 84589 | F27: =F46+F52+F58+F64+F70+F92+F76 -> 79590 | G27: =G46+G52+G58+G64+G70+G92+G76 -> 86302 | H27: =H46+H52+H58+H64+H70+H92+H76 -> 71945 | I27: =I46+I52+I58+I64+I70+I92+I76 -> 63233 | J27: =J46+J52+J58+J64+J70+J92+J76 -> 105898 | K27: =K46+K52+K58+K64+K70+K92+K76 -> 83599 | ... O27: =O46+O52+O58+O64+O70+O92+O76 -> 0
A28: ='Distribution Dashboard'!A19 -> RA3 | B28: ='Distribution Dashboard'!B19 -> NRW | C28: ='Distribution Dashboard'!C19 -> m3 | D28: =D26-D27 -> 27226 | E28: =E26-E27 -> 19628 | F28: =F26-F27 -> 21356 | G28: =G26-G27 -> 24220 | H28: =H26-H27 -> 20717 | I28: =I26-I27 -> 20918 | J28: =J26-J27 -> 20468 | K28: =K26-K27 -> 18237 | ... O28: =O26-O27 -> 0
A29: ='Distribution Dashboard'!A20 -> RA4 | B29: ='Distribution Dashboard'!B20 -> NRW | C29: ='Distribution Dashboard'!C20 -> % | D29: =D28/D26 -> 0.27338635 | E29: =E28/E26 -> 0.1883378 | F29: =F28/F26 -> 0.21155866 | G29: =G28/G26 -> 0.21914189 | H29: =H28/H26 -> 0.22357601 | I29: =I28/I26 -> 0.24857696 | J29: =J28/J26 -> 0.16197395 | K29: =K28/K26 -> 0.17908205 | ... O29: =O28/O26 -> #DIV/0!
A30: ='Distribution Dashboard'!A21 -> 0 | B30: ='Distribution Dashboard'!B21 -> Amount Billed Water | C30: ='Distribution Dashboard'!C21 -> KES
A31: ='Distribution Dashboard'!A22 -> 0 | B31: ='Distribution Dashboard'!B22 -> Amount Billed Sewer | C31: ='Distribution Dashboard'!C22 -> KES
A32: ='Distribution Dashboard'!A23 -> 0 | B32: ='Distribution Dashboard'!B23 -> Number of Active water Connections | C32: ='Distribution Dashboard'!C23 -> KES
A33: ='Distribution Dashboard'!A24 -> 0 | B33: ='Distribution Dashboard'!B24 -> Number of Active sewer Connections | C33: ='Distribution Dashboard'!C24 -> KES
A34: ='Distribution Dashboard'!A25 -> 0 | B34: ='Distribution Dashboard'!B25 -> SOUTHERN REGION: MAI MAHIU,KAMERE,HELLSGATE | C34: ='Distribution Dashboard'!C25 -> 0
A35: ='Distribution Dashboard'!A26 -> RA6 (B) | B35: ='Distribution Dashboard'!B26 -> Volume Water Supplied | C35: ='Distribution Dashboard'!C26 -> m3 | D35: =D79+D85+D103+D121 -> 62827 | E35: =E79+E85+E103+E121 -> 85011 | F35: =F79+F85+F103+F121 -> 57253 | G35: =G79+G85+G103+G121 -> 87909 | H35: =H79+H85+H103+H121 -> 55459 | I35: =I79+I85+I103+I121 -> 61011 | J35: =J79+J85+J103+J121 -> 89581 | K35: =K79+K85+K103+K121 -> 77635 | ... O35: =O79+O85+O103+O121 -> 0
A36: ='Distribution Dashboard'!A27 -> RB2 | B36: ='Distribution Dashboard'!B27 -> Volume Water Sold | C36: ='Distribution Dashboard'!C27 -> m3 | D36: =D80+D86+D104+D122 -> 42506 | E36: =E80+E86+E104+E122 -> 58310 | F36: =F80+F86+F104+F122 -> 40155 | G36: =G80+G86+G104+G122 -> 56034 | H36: =H80+H86+H104+H122 -> 38221 | I36: =I80+I86+I104+I122 -> 41581 | J36: =J80+J86+J104+J122 -> 63419 | K36: =K80+K86+K104+K122 -> 55022 | ... O36: =O80+O86+O104+O122 -> 0
A37: ='Distribution Dashboard'!A28 -> RB3 (2) | B37: ='Distribution Dashboard'!B28 -> NRW | C37: ='Distribution Dashboard'!C28 -> m3 | D37: =D35-D36 -> 20321 | E37: =E35-E36 -> 26701 | F37: =F35-F36 -> 17098 | G37: =G35-G36 -> 31875 | H37: =H35-H36 -> 17238 | I37: =I35-I36 -> 19430 | J37: =J35-J36 -> 26162 | K37: =K35-K36 -> 22613 | ... O37: =O35-O36 -> 0
A38: ='Distribution Dashboard'!A29 -> RB4 | B38: ='Distribution Dashboard'!B29 -> NRW | C38: ='Distribution Dashboard'!C29 -> % | D38: =D37/D35 -> 0.32344374 | E38: =E37/E35 -> 0.31408876 | F38: =F37/F35 -> 0.29863937 | G38: =G37/G35 -> 0.36259086 | H38: =H37/H35 -> 0.31082421 | I38: =I37/I35 -> 0.31846716 | J38: =J37/J35 -> 0.29204854 | K38: =K37/K35 -> 0.29127327 | ... O38: =O37/O35 -> #DIV/0!
A39: ='Distribution Dashboard'!A30 -> 0 | B39: ='Distribution Dashboard'!B30 -> EASTERN REGION: KAYOLE,GONDI, KINUNGI,NJONJORO | C39: ='Distribution Dashboard'!C30 -> 0
A40: ='Distribution Dashboard'!A31 -> RA6 (B) (2) | B40: ='Distribution Dashboard'!B31 -> Volume Water Supplied | C40: ='Distribution Dashboard'!C31 -> m3 | D40: =D97+D125 -> 41209 | E40: =E97+E125 -> 39990 | F40: =F97+F125 -> 36725 | G40: =G97+G125 -> 48806 | H40: =H97+H125 -> 33526 | I40: =I97+I125 -> 35129 | J40: =J97+J125 -> 42223 | K40: =K97+K125 -> 43072 | ... O40: =O97+O125 -> 0
A41: ='Distribution Dashboard'!A32 -> RB2 (3) | B41: ='Distribution Dashboard'!B32 -> Volume Water Sold | C41: ='Distribution Dashboard'!C32 -> m3 | D41: =D98+D126 -> 31567 | E41: =E98+E126 -> 30396 | F41: =F98+F126 -> 26239 | G41: =G98+G126 -> 28789 | H41: =H98+H126 -> 24966 | I41: =I98+I126 -> 26222 | J41: =J98+J126 -> 31253 | K41: =K98+K126 -> 33645 | ... O41: =O98+O126 -> 0
A42: ='Distribution Dashboard'!A33 -> RB3 (3) | B42: ='Distribution Dashboard'!B33 -> NRW | C42: ='Distribution Dashboard'!C33 -> m3 | D42: =D40-D41 -> 9642 | E42: =E40-E41 -> 9594 | F42: =F40-F41 -> 10486 | G42: =G40-G41 -> 20017 | H42: =H40-H41 -> 8560 | I42: =I40-I41 -> 8907 | J42: =J40-J41 -> 10970 | K42: =K40-K41 -> 9427 | ... O42: =O40-O41 -> 0
A43: ='Distribution Dashboard'!A33 -> RB3 (3) | B43: ='Distribution Dashboard'!B34 -> NRW | C43: ='Distribution Dashboard'!C33 -> m3 | D43: =D42/D40 -> 0.23397801 | E43: =E42/E40 -> 0.23990998 | F43: =F42/F40 -> 0.28552757 | G43: =G42/G40 -> 0.410134 | H43: =H42/H40 -> 0.25532423 | I43: =I42/I40 -> 0.2535512 | J43: =J42/J40 -> 0.259811 | K43: =K42/K40 -> 0.21886608 | ... O43: =O42/O40 -> #DIV/0!
A44: ='Distribution Dashboard'!A34 -> RB4 (2) | B44: ='Distribution Dashboard'!B35 -> ZONE - CBD | C44: ='Distribution Dashboard'!C34 -> %
A45: ='Distribution Dashboard'!A36 -> 101 | B45: ='Distribution Dashboard'!B36 -> Volume Water Supplied | C45: ='Distribution Dashboard'!C36 -> m3 | D45: 18634 | E45: 23756 | F45: 22318 | G45: 21615 | H45: 20535 | I45: 17778 | J45: 23190 | K45: 19812
A46: ='Distribution Dashboard'!A37 -> 108 | B46: ='Distribution Dashboard'!B37 -> Volume Water Sold | C46: ='Distribution Dashboard'!C37 -> m3 | D46: 12992 | E46: 17788 | F46: 16452 | G46: 16186 | H46: 13605 | I46: 12217 | J46: 20906 | K46: 15811
A47: ='Distribution Dashboard'!A38 -> 122 | B47: ='Distribution Dashboard'!B38 -> NRW | C47: ='Distribution Dashboard'!C38 -> % | D47: =(D45-D46)/D45 -> 0.30277986 | E47: =(E45-E46)/E45 -> 0.25122074 | F47: =(F45-F46)/F45 -> 0.26283717 | G47: =(G45-G46)/G45 -> 0.25116817 | H47: =(H45-H46)/H45 -> 0.33747261 | I47: =(I45-I46)/I45 -> 0.31280234 | J47: =(J45-J46)/J45 -> 0.098490729 | K47: =(K45-K46)/K45 -> 0.20194831 | ... O47: =(O45-O46)/O45 -> #DIV/0!
A48: ='Distribution Dashboard'!A39 -> 0 | B48: ='Distribution Dashboard'!B39 -> Amount Billed Water | C48: ='Distribution Dashboard'!C39 -> KES
A49: ='Distribution Dashboard'!A40 -> 0 | B49: ='Distribution Dashboard'!B40 -> Amount Billed Sewer | C49: ='Distribution Dashboard'!C40 -> KES
A50: ='Distribution Dashboard'!A41 -> 0 | B50: ='Distribution Dashboard'!B41 -> ZONE - CCCR | C50: ='Distribution Dashboard'!C41 -> 0
A51: ='Distribution Dashboard'!A42 -> 102 | B51: ='Distribution Dashboard'!B42 -> Volume Water Supplied | C51: ='Distribution Dashboard'!C42 -> m3 | D51: 21082 | E51: 19289 | F51: 17841 | G51: =21868-320 -> 21548 | H51: 18790 | I51: 15397 | J51: 23443 | K51: 20893
A52: ='Distribution Dashboard'!A43 -> 109 | B52: ='Distribution Dashboard'!B43 -> Volume Water Sold | C52: ='Distribution Dashboard'!C43 -> m3 | D52: 15991 | E52: 15410 | F52: 13572 | G52: 16565 | H52: 15215 | I52: 12683 | J52: 20921 | K52: 17374
A53: ='Distribution Dashboard'!A44 -> 123 | B53: ='Distribution Dashboard'!B44 -> NRW | C53: ='Distribution Dashboard'!C44 -> % | D53: =(D51-D52)/D51 -> 0.24148563 | E53: =(E51-E52)/E51 -> 0.20109907 | F53: =(F51-F52)/F51 -> 0.23928031 | G53: =(G51-G52)/G51 -> 0.23125116 | H53: =(H51-H52)/H51 -> 0.19026078 | I53: =(I51-I52)/I51 -> 0.1762681 | J53: =(J51-J52)/J51 -> 0.10758009 | K53: =(K51-K52)/K51 -> 0.16842962 | ... O53: =(O51-O52)/O51 -> #DIV/0!
A54: ='Distribution Dashboard'!A45 -> 0 | B54: ='Distribution Dashboard'!B45 -> Amount Billed Water | C54: ='Distribution Dashboard'!C45 -> KES
A55: ='Distribution Dashboard'!A46 -> 0 | B55: ='Distribution Dashboard'!B46 -> Amount Billed Sewer | C55: ='Distribution Dashboard'!C46 -> KES
A56: ='Distribution Dashboard'!A47 -> 0 | B56: ='Distribution Dashboard'!B47 -> ZONE - LAKEVIEW | C56: ='Distribution Dashboard'!C47 -> 0
A57: ='Distribution Dashboard'!A48 -> 104 | B57: ='Distribution Dashboard'!B48 -> Volume Water Supplied | C57: ='Distribution Dashboard'!C48 -> m3 | D57: 26384 | E57: 25573 | F57: 25446 | G57: 30068 | H57: 20903 | I57: 22989 | J57: 32055 | K57: 26597
A58: ='Distribution Dashboard'!A49 -> 111 | B58: ='Distribution Dashboard'!B49 -> Volume Water Sold | C58: ='Distribution Dashboard'!C49 -> m3 | D58: 16861 | E58: 20788 | F58: 19143 | G58: 21669 | H58: 16926 | I58: 14915 | J58: 26099 | K58: 21183
A59: ='Distribution Dashboard'!A50 -> 125 | B59: ='Distribution Dashboard'!B50 -> NRW | C59: ='Distribution Dashboard'!C50 -> % | D59: =(D57-D58)/D57 -> 0.36093845 | E59: =(E57-E58)/E57 -> 0.18711141 | F59: =(F57-F58)/F57 -> 0.24770101 | G59: =(G57-G58)/G57 -> 0.27933351 | H59: =(H57-H58)/H57 -> 0.19025977 | I59: =(I57-I58)/I57 -> 0.35121145 | J59: =(J57-J58)/J57 -> 0.18580565 | K59: =(K57-K58)/K57 -> 0.20355679 | ... O59: =(O57-O58)/O57 -> #DIV/0!
A60: ='Distribution Dashboard'!A51 -> 0 | B60: ='Distribution Dashboard'!B51 -> Amount Billed Water | C60: ='Distribution Dashboard'!C51 -> KES
A61: ='Distribution Dashboard'!A52 -> 0 | B61: ='Distribution Dashboard'!B52 -> Amount Billed Sewer | C61: ='Distribution Dashboard'!C52 -> KES
A62: ='Distribution Dashboard'!A53 -> 0 | B62: ='Distribution Dashboard'!B53 -> ZONE - KABATI | C62: ='Distribution Dashboard'!C53 -> 0
A63: ='Distribution Dashboard'!A54 -> 103 | B63: ='Distribution Dashboard'!B54 -> Volume Water Supplied | C63: ='Distribution Dashboard'!C54 -> m3 | D63: 15271 | E63: 14365 | F63: 14499 | G63: 15769 | H63: 13590 | I63: 11896 | J63: 21645 | K63: 14546
A64: ='Distribution Dashboard'!A55 -> 110 | B64: ='Distribution Dashboard'!B55 -> Volume Water Sold | C64: ='Distribution Dashboard'!C55 -> m3 | D64: 10344 | E64: 12199 | F64: 12554 | G64: 12843 | H64: 10930 | I64: 9805 | J64: 16301 | K64: 12061
A65: ='Distribution Dashboard'!A56 -> 124 | B65: ='Distribution Dashboard'!B56 -> NRW | C65: ='Distribution Dashboard'!C56 -> % | D65: =(D63-D64)/D63 -> 0.32263768 | E65: =(E63-E64)/E63 -> 0.15078315 | F65: =(F63-F64)/F63 -> 0.13414718 | G65: =(G63-G64)/G63 -> 0.18555393 | H65: =(H63-H64)/H63 -> 0.19573216 | I65: =(I63-I64)/I63 -> 0.17577337 | J65: =(J63-J64)/J63 -> 0.24689305 | K65: =(K63-K64)/K63 -> 0.17083734 | ... O65: =(O63-O64)/O63 -> #DIV/0!
A66: ='Distribution Dashboard'!A57 -> 0 | B66: ='Distribution Dashboard'!B57 -> Amount Billed | C66: ='Distribution Dashboard'!C57 -> KES
A67: ='Distribution Dashboard'!A58 -> 0 | B67: ='Distribution Dashboard'!B58 -> Amount Billed Sewer | C67: ='Distribution Dashboard'!C58 -> KES
A68: ='Distribution Dashboard'!A59 -> 0 | B68: ='Distribution Dashboard'!B59 -> ZONE - SITE AND SERVICES | C68: ='Distribution Dashboard'!C59 -> 0
A69: ='Distribution Dashboard'!A60 -> 105 | B69: ='Distribution Dashboard'!B60 -> Volume Water Supplied | C69: ='Distribution Dashboard'!C60 -> m3 | D69: 10138 | E69: 13039 | F69: 12762 | G69: =13905-2000 -> 11905 | H69: 12460 | I69: 9387 | J69: 15639 | K69: 11406
A70: ='Distribution Dashboard'!A61 -> 112 | B70: ='Distribution Dashboard'!B61 -> Volume Water Sold | C70: ='Distribution Dashboard'!C61 -> m3 | D70: 9053 | E70: 10669 | F70: 10732 | G70: 11020 | H70: 9629 | I70: 7701 | J70: 13327 | K70: 10175
A71: ='Distribution Dashboard'!A62 -> 126 | B71: ='Distribution Dashboard'!B62 -> NRW | C71: ='Distribution Dashboard'!C62 -> % | D71: =(D69-D70)/D69 -> 0.10702308 | E71: =(E69-E70)/E69 -> 0.18176241 | F71: =(F69-F70)/F69 -> 0.15906598 | G71: =(G69-G70)/G69 -> 0.074338513 | H71: =(H69-H70)/H69 -> 0.22720706 | I71: =(I69-I70)/I69 -> 0.1796101 | J71: =(J69-J70)/J69 -> 0.14783554 | K71: =(K69-K70)/K69 -> 0.10792565 | ... O71: =(O69-O70)/O69 -> #DIV/0!
A72: ='Distribution Dashboard'!A63 -> 0 | B72: ='Distribution Dashboard'!B63 -> Amount Billed Water | C72: ='Distribution Dashboard'!C63 -> KES
A73: ='Distribution Dashboard'!A64 -> 0 | B73: ='Distribution Dashboard'!B64 -> Amount Billed Sewer | C73: ='Distribution Dashboard'!C64 -> KES
A74: ='Distribution Dashboard'!A65 -> 0 | B74: ='Distribution Dashboard'!B65 -> ZONE - HOPEWELL | C74: ='Distribution Dashboard'!C65 -> 0
A75: ='Distribution Dashboard'!A66 -> 105B | B75: ='Distribution Dashboard'!B66 -> Volume Water Supplied | C75: ='Distribution Dashboard'!C66 -> m3 | D75: 5972 | E75: 6247 | F75: 6155 | G75: 7067 | H75: 5512 | I75: 5035 | J75: 7698 | K75: 6609
A76: ='Distribution Dashboard'!A67 -> 112B | B76: ='Distribution Dashboard'!B67 -> Volume Water Sold | C76: ='Distribution Dashboard'!C67 -> m3 | D76: 5299 | E76: 6062 | F76: 5511 | G76: 6280 | H76: 4988 | I76: 4740 | J76: 6578 | K76: 5420
A77: ='Distribution Dashboard'!A68 -> 126B | B77: ='Distribution Dashboard'!B68 -> NRW | C77: ='Distribution Dashboard'!C68 -> % | D77: =(D75-D76)/D75 -> 0.11269257 | E77: =(E75-E76)/E75 -> 0.029614215 | F77: =(F75-F76)/F75 -> 0.10463038 | G77: =(G75-G76)/G75 -> 0.11136267 | H77: =(H75-H76)/H75 -> 0.095065312 | I77: =(I75-I76)/I75 -> 0.058589871 | J77: =(J75-J76)/J75 -> 0.14549234 | K77: =(K75-K76)/K75 -> 0.17990619 | ... O77: =(O75-O76)/O75 -> #DIV/0!
A78: ='Distribution Dashboard'!A69 -> 0 | B78: ='Distribution Dashboard'!B69 -> ZONE - KAMERE | C78: ='Distribution Dashboard'!C69 -> 0
A79: ='Distribution Dashboard'!A70 -> 106 | B79: ='Distribution Dashboard'!B70 -> Volume Water Supplied | C79: ='Distribution Dashboard'!C70 -> m3 | D79: =7517+510 -> 8027 | E79: =9152+765 -> 9917 | F79: =5575+512 -> 6087 | G79: 9083 | H79: =6774+708 -> 7482 | I79: =7771+1100 -> 8871 | J79: =10423+1351 -> 11774 | K79: 9112
A80: ='Distribution Dashboard'!A71 -> 113 | B80: ='Distribution Dashboard'!B71 -> Volume Water Sold | C80: ='Distribution Dashboard'!C71 -> m3 | D80: 5788 | E80: 6705 | F80: 4755 | G80: 6241 | H80: 5183 | I80: 6161 | J80: 8813 | K80: 7181
A81: ='Distribution Dashboard'!A72 -> 127 | B81: ='Distribution Dashboard'!B72 -> NRW | C81: ='Distribution Dashboard'!C72 -> % | D81: =(D79-D80)/D79 -> 0.2789336 | E81: =(E79-E80)/E79 -> 0.32388827 | F81: =(F79-F80)/F79 -> 0.21882701 | G81: =(G79-G80)/G79 -> 0.31289222 | H81: =(H79-H80)/H79 -> 0.30727078 | I81: =(I79-I80)/I79 -> 0.3054898 | J81: =(J79-J80)/J79 -> 0.25148633 | K81: =(K79-K80)/K79 -> 0.21191835 | ... O81: =(O79-O80)/O79 -> #DIV/0!
A82: ='Distribution Dashboard'!A73 -> 0 | B82: ='Distribution Dashboard'!B73 -> Amount Billed Water | C82: ='Distribution Dashboard'!C73 -> KES
A83: ='Distribution Dashboard'!A74 -> 0 | B83: ='Distribution Dashboard'!B74 -> Amount Billed Sewer | C83: ='Distribution Dashboard'!C74 -> KES
A84: ='Distribution Dashboard'!A75 -> 0 | B84: ='Distribution Dashboard'!B75 -> ZONE - HELLS GATE | C84: ='Distribution Dashboard'!C75 -> 0
A85: ='Distribution Dashboard'!A76 -> 103 (3) | B85: ='Distribution Dashboard'!B76 -> Volume Water Supplied | C85: ='Distribution Dashboard'!C76 -> m3 | D85: 30234 | E85: 40128 | F85: 29291 | G85: 44330 | H85: 27402 | I85: 31274 | J85: 43487 | K85: 37061
A86: ='Distribution Dashboard'!A77 -> 110 (3) | B86: ='Distribution Dashboard'!B77 -> Volume Water Sold | C86: ='Distribution Dashboard'!C77 -> m3 | D86: 21124 | E86: 28413 | F86: 21139 | G86: 27997 | H86: 19635 | I86: 22759 | J86: 32803 | K86: 26800
A87: ='Distribution Dashboard'!A78 -> 124 (3) | B87: ='Distribution Dashboard'!B78 -> NRW | C87: ='Distribution Dashboard'!C78 -> % | D87: =(D85-D86)/D85 -> 0.3013164 | E87: =(E85-E86)/E85 -> 0.29194079 | F87: =(F85-F86)/F85 -> 0.27831074 | G87: =(G85-G86)/G85 -> 0.36844124 | H87: =(H85-H86)/H85 -> 0.28344646 | I87: =(I85-I86)/I85 -> 0.2722709 | J87: =(J85-J86)/J85 -> 0.24568262 | K87: =(K85-K86)/K85 -> 0.27686787 | ... O87: =(O85-O86)/O85 -> #DIV/0!
A88: ='Distribution Dashboard'!A79 -> 0 | B88: ='Distribution Dashboard'!B79 -> Amount Billed Water | C88: ='Distribution Dashboard'!C79 -> KES
A89: ='Distribution Dashboard'!A80 -> 0 | B89: ='Distribution Dashboard'!B80 -> Amount Billed Sewer | C89: ='Distribution Dashboard'!C80 -> KES
A90: ='Distribution Dashboard'!A81 -> 0 | B90: ='Distribution Dashboard'!B81 -> KIHOTO | C90: ='Distribution Dashboard'!C81 -> 0
A91: ='Distribution Dashboard'!A82 -> 103 (2) | B91: ='Distribution Dashboard'!B82 -> Volume Water Supplied | C91: ='Distribution Dashboard'!C82 -> m3 | D91: 2107 | E91: 1948 | F91: 1925 | G91: 2550 | H91: 872 | I91: 1669 | J91: 2696 | K91: 1973
A92: ='Distribution Dashboard'!A83 -> 110 (2) | B92: ='Distribution Dashboard'!B83 -> Volume Water Sold | C92: ='Distribution Dashboard'!C83 -> m3 | D92: 1822 | E92: 1673 | F92: 1626 | G92: 1739 | H92: 652 | I92: 1172 | J92: 1766 | K92: 1575
A93: ='Distribution Dashboard'!A84 -> 124 (2) | B93: ='Distribution Dashboard'!B84 -> NRW | C93: ='Distribution Dashboard'!C84 -> % | D93: =(D91-D92)/D91 -> 0.13526341 | E93: =(E91-E92)/E91 -> 0.14117043 | F93: =(F91-F92)/F91 -> 0.15532468 | G93: =(G91-G92)/G91 -> 0.31803922 | H93: =(H91-H92)/H91 -> 0.25229358 | I93: =(I91-I92)/I91 -> 0.2977831 | J93: =(J91-J92)/J91 -> 0.34495549 | K93: =(K91-K92)/K91 -> 0.20172326 | ... O93: =(O91-O92)/O91 -> #DIV/0!
A94: ='Distribution Dashboard'!A85 -> 0 | B94: ='Distribution Dashboard'!B85 -> Amount Billed Water | C94: ='Distribution Dashboard'!C85 -> KES
A95: ='Distribution Dashboard'!A86 -> 0 | B95: ='Distribution Dashboard'!B86 -> Amount Billed Sewer | C95: ='Distribution Dashboard'!C86 -> KES
A96: ='Distribution Dashboard'!A87 -> 0 | B96: ='Distribution Dashboard'!B87 -> KAYOLE | C96: ='Distribution Dashboard'!C87 -> 0
A97: ='Distribution Dashboard'!A88 -> 103 (4) | B97: ='Distribution Dashboard'!B88 -> Volume Water Supplied | C97: ='Distribution Dashboard'!C88 -> m3 | D97: =304+40436+144 -> 40884 | E97: =464+38522+320 -> 39306 | F97: =328+35671+269 -> 36268 | G97: 48806 | H97: =425+32852+249 -> 33526 | I97: =406+34285+282 -> 34973 | J97: =468+40782+437 -> 41687 | K97: 42601
A98: ='Distribution Dashboard'!A89 -> 110 (4) | B98: ='Distribution Dashboard'!B89 -> Volume Water Sold | C98: ='Distribution Dashboard'!C89 -> m3 | D98: 31495 | E98: 30262 | F98: 26101 | G98: 28789 | H98: 24965 | I98: 26090 | J98: 30971 | K98: 33446
A99: ='Distribution Dashboard'!A90 -> 124 (4) | B99: ='Distribution Dashboard'!B90 -> NRW | C99: ='Distribution Dashboard'!C90 -> % | D99: =(D97-D98)/D97 -> 0.22964974 | E99: =(E97-E98)/E97 -> 0.2300921 | F99: =(F97-F98)/F97 -> 0.28032977 | G99: =(G97-G98)/G97 -> 0.410134 | H99: =(H97-H98)/H97 -> 0.25535405 | I99: =(I97-I98)/I97 -> 0.25399594 | J99: =(J97-J98)/J97 -> 0.25705856 | K99: =(K97-K98)/K97 -> 0.21490106 | ... O99: =(O97-O98)/O97 -> #DIV/0!
A100: ='Distribution Dashboard'!A91 -> 0 | B100: ='Distribution Dashboard'!B91 -> Amount Billed Water | C100: ='Distribution Dashboard'!C91 -> KES
...

Sheet Actuals2425
A1: ='Distribution Dashboard'!A1 -> NAIVAWASS DISTRIBUTION DASHBOARD - NON-REVENUE WATER & ZONAL PERFORMANCE | B1: ='Distribution Dashboard'!B1 -> 0 | C1: ='Distribution Dashboard'!D1 -> 0
A2: ='Distribution Dashboard'!A2 -> 0 | B2: ='Distribution Dashboard'!B2 -> 46054 | C2: ='Distribution Dashboard'!D2 -> 0
A3: ='Distribution Dashboard'!A3 -> 0 | B3: ='Distribution Dashboard'!B3 -> 0 | C3: ='Distribution Dashboard'!D3 -> Monthly
A4: ='Distribution Dashboard'!A4 -> 0 | C4: ='Distribution Dashboard'!C4 -> Unit | D4: 45474 | E4: 45505 | F4: 45536 | G4: 45566 | H4: 45597 | I4: 45627 | J4: 45658 | K4: 45689 | L4: 45717 | M4: 45748 | N4: 45778 | O4: 45809
A5: ='Distribution Dashboard'!#REF! -> #REF! | B5: ='Distribution Dashboard'!#REF! -> #REF! | C5: ='Distribution Dashboard'!#REF! -> #REF!
A6: ='Distribution Dashboard'!#REF! -> #REF! | B6: ='Distribution Dashboard'!#REF! -> #REF! | C6: ='Distribution Dashboard'!#REF! -> #REF! | D6: 199192.12 | E6: 229211 | F6: 219157 | G6: 226434 | H6: 232327 | I6: 162567 | J6: 280545 | K6: 236218 | L6: 234258 | M6: 176008 | N6: 222024 | O6: 228197
A7: ='Distribution Dashboard'!#REF! -> #REF! | B7: ='Distribution Dashboard'!#REF! -> #REF! | C7: ='Distribution Dashboard'!#REF! -> #REF! | D7: =D16 -> 141416 | E7: =E16 -> 168508 | F7: =F16 -> 163668 | G7: =G16 -> 160893 | H7: =H16 -> 179892 | I7: =I16 -> 116560 | J7: =J16 -> 184451 | K7: =K16 -> 165475 | ... O7: =O16 -> 164911
A8: ='Distribution Dashboard'!#REF! -> #REF! | B8: ='Distribution Dashboard'!#REF! -> #REF! | C8: ='Distribution Dashboard'!#REF! -> #REF! | D8: =(D6-D7)/D6 -> 0.29005224 | E8: =(E6-E7)/E6 -> 0.26483458 | F8: =(F6-F7)/F6 -> 0.25319292 | G8: =(G6-G7)/G6 -> 0.28944858 | H8: =(H6-H7)/H6 -> 0.22569482 | I8: =(I6-I7)/I6 -> 0.28300332 | J8: =(J6-J7)/J6 -> 0.34252615 | K8: =(K6-K7)/K6 -> 0.29948183 | ... O8: =(O6-O7)/O6 -> 0.27733055
A9: ='Distribution Dashboard'!#REF! -> #REF!
A10: ='Distribution Dashboard'!#REF! -> #REF! | B10: ='Distribution Dashboard'!#REF! -> #REF! | C10: ='Distribution Dashboard'!#REF! -> #REF! | D10: =D6 -> 199192.12 | E10: =E6 -> 229211 | F10: =F6 -> 219157 | G10: =G6 -> 226434 | H10: =H6 -> 232327 | I10: =I6 -> 162567 | J10: =J6 -> 280545 | K10: =K6 -> 236218 | ... O10: =O6 -> 228197
A11: ='Distribution Dashboard'!#REF! -> #REF! | B11: ='Distribution Dashboard'!#REF! -> #REF! | C11: ='Distribution Dashboard'!#REF! -> #REF! | D11: =D15 -> 179812 | E11: =E15 -> 218591 | F11: =F15 -> 206801 | G11: =G15 -> 217593 | H11: =H15 -> 230368 | I11: =I15 -> 151401 | J11: =J15 -> 267445 | K11: =K15 -> 216809 | ... O11: =O15 -> 224235
A12: ='Distribution Dashboard'!#REF! -> #REF! | B12: ='Distribution Dashboard'!#REF! -> #REF! | C12: ='Distribution Dashboard'!#REF! -> #REF! | D12: =(D10-D11)/D10 -> 0.097293608 | E12: =(E10-E11)/E10 -> 0.046332855 | F12: =(F10-F11)/F10 -> 0.056379673 | G12: =(G10-G11)/G10 -> 0.03904449 | H12: =(H10-H11)/H10 -> 0.0084320806 | I12: =(I10-I11)/I10 -> 0.068685527 | J12: =(J10-J11)/J10 -> 0.046694826 | K12: =(K10-K11)/K10 -> 0.082165627 | ... O12: =(O10-O11)/O10 -> 0.017362191
A13: ='Distribution Dashboard'!#REF! -> #REF! | B13: ='Distribution Dashboard'!#REF! -> #REF! | C13: ='Distribution Dashboard'!#REF! -> #REF! | D13: =D10-D11 -> 19380.12 | E13: =E10-E11 -> 10620 | F13: =F10-F11 -> 12356 | G13: =G10-G11 -> 8841 | H13: =H10-H11 -> 1959 | I13: =I10-I11 -> 11166 | J13: =J10-J11 -> 13100 | K13: =K10-K11 -> 19409 | ... O13: =O10-O11 -> 3962
A14: ='Distribution Dashboard'!A6 -> 0 | B14: ='Distribution Dashboard'!B6 -> REGIONAL NRW | C14: ='Distribution Dashboard'!C6 -> 0
A15: ='Distribution Dashboard'!A7 -> 100 | B15: ='Distribution Dashboard'!B7 -> WATER AVAILABLE FOR SALES- REGIONS | C15: ='Distribution Dashboard'!C7 -> m3 | D15: =D26+D35+D40 -> 179812 | E15: =E26+E35+E40 -> 218591 | F15: =F26+F35+F40 -> 206801 | G15: =G26+G35+G40 -> 217593 | H15: =H26+H35+H40 -> 230368 | I15: =I26+I35+I40 -> 151401 | J15: =J26+J35+J40 -> 267445 | K15: =K26+K35+K40 -> 216809 | ... Q15: =Q26+Q35+Q40 -> 0
A16: ='Distribution Dashboard'!A8 -> 128a | B16: ='Distribution Dashboard'!B8 -> VOLUME WATER BILLED(CUSTOMERS-M3) | C16: ='Distribution Dashboard'!C8 -> m3 | D16: =D27+D41+D36 -> 141416 | E16: =E27+E41+E36 -> 168508 | F16: =F27+F41+F36 -> 163668 | G16: =G27+G41+G36 -> 160893 | H16: =H27+H41+H36 -> 179892 | I16: =I27+I41+I36 -> 116560 | J16: =J27+J41+J36 -> 184451 | K16: =K27+K41+K36 -> 165475 | ... O16: =O27+O41+O36 -> 164911
A17: ='Distribution Dashboard'!A9 -> 128 | B17: ='Distribution Dashboard'!B9 -> GLOBAL NRW | C17: ='Distribution Dashboard'!C9 -> % | D17: =(D15-D16)/D15 -> 0.21353414 | E17: =(E15-E16)/E15 -> 0.22911739 | F17: =(F15-F16)/F15 -> 0.20857249 | G17: =(G15-G16)/G15 -> 0.26057824 | H17: =(H15-H16)/H15 -> 0.21911029 | I17: =(I15-I16)/I15 -> 0.23012398 | J17: =(J15-J16)/J15 -> 0.31032175 | K17: =(K15-K16)/K15 -> 0.23677061 | ... O17: =(O15-O16)/O15 -> 0.26456173
A18: ='Distribution Dashboard'!A10 -> 0 | B18: ='Distribution Dashboard'!B10 -> Number of Active water Connections | C18: ='Distribution Dashboard'!C10 -> NO. | D18: =D41+D32 -> 26497 | E18: =E41+E32 -> 29718 | F18: =F41+F32 -> 32245 | G18: =G41+G32 -> 30200 | H18: =H41+H32 -> 32349 | I18: =I41+I32 -> 24184 | J18: =J41+J32 -> 29173 | K18: =K41+K32 -> 28120 | ... O18: =O41+O32 -> 30668
A19: ='Distribution Dashboard'!A11 -> 0 | B19: ='Distribution Dashboard'!B11 -> Number of Active sewer Connections | C19: ='Distribution Dashboard'!C11 -> NO. | D19: =D42+D33 -> 6559 | E19: =E42+E33 -> 10191 | F19: =F42+F33 -> 3039 | G19: =G42+G33 -> 7923 | H19: =H42+H33 -> 6667 | I19: =I42+I33 -> 5375 | J19: =J42+J33 -> 10605 | K19: =K42+K33 -> 8769 | ... O19: =O42+O33 -> 16572
A20: ='Distribution Dashboard'!A12 -> 0 | B20: ='Distribution Dashboard'!B12 -> Number of In-active Sewer Connections | C20: ='Distribution Dashboard'!C12 -> NO.
A21: ='Distribution Dashboard'!A13 -> 0 | B21: ='Distribution Dashboard'!B13 -> Number of In-active Water Connections | C21: ='Distribution Dashboard'!C13 -> NO.
A22: ='Distribution Dashboard'!A14 -> 0 | B22: ='Distribution Dashboard'!B14 -> Number of Connections | C22: ='Distribution Dashboard'!C14 -> NO. | D22: =SUM(D18:D21) -> 33056 | E22: =SUM(E18:E21) -> 39909 | F22: =SUM(F18:F21) -> 35284 | G22: =SUM(G18:G21) -> 38123 | H22: =SUM(H18:H21) -> 39016 | I22: =SUM(I18:I21) -> 29559 | J22: =SUM(J18:J21) -> 39778 | K22: =SUM(K18:K21) -> 36889 | ... O22: =SUM(O18:O21) -> 47240
A23: ='Distribution Dashboard'!A15 -> 0 | B23: ='Distribution Dashboard'!B15 -> Maintenance, repair and operational cost | C23: ='Distribution Dashboard'!C15 -> KES
A24: ='Distribution Dashboard'!#REF! -> #REF! | B24: ='Distribution Dashboard'!#REF! -> #REF! | C24: ='Distribution Dashboard'!#REF! -> #REF!
A25: ='Distribution Dashboard'!A16 -> 0 | B25: ='Distribution Dashboard'!B16 -> CENTRAL REGION: CBD,CCCR,KABATI,SITE,KIHOTO,LAKEVIEW | C25: ='Distribution Dashboard'!C16 -> 0
A26: ='Distribution Dashboard'!A17 -> RA | B26: ='Distribution Dashboard'!B17 -> Volume Water Supplied | C26: ='Distribution Dashboard'!C17 -> m3 | D26: =D45+D51+D57+D63+D69+D91+D75 -> 92367 | E26: =E45+E51+E57+E63+E69+E91+E75 -> 114426 | F26: =F45+F51+F57+F63+F69+F91+F75 -> 101553 | G26: =G45+G51+G57+G63+G69+G91+G75 -> 107597 | H26: =H45+H51+H57+H63+H69+H91+H75 -> 106133 | I26: =I45+I51+I57+I63+I69+I91+I75 -> 74176 | J26: =J45+J51+J57+J63+J69+J91+J75 -> 141121 | K26: =K45+K51+K57+K63+K69+K91+K75 -> 105690 | ... O26: =O45+O51+O57+O63+O69+O91+O75 -> 108927
A27: ='Distribution Dashboard'!A18 -> RA2 | B27: ='Distribution Dashboard'!B18 -> Volume Water Sold | C27: ='Distribution Dashboard'!C18 -> m3 | D27: =D46+D52+D58+D64+D70+D92+D76 -> 73301 | E27: =E46+E52+E58+E64+E70+E92+E76 -> 93670 | F27: =F46+F52+F58+F64+F70+F92+F76 -> 81216 | G27: =G46+G52+G58+G64+G70+G92+G76 -> 82720 | H27: =H46+H52+H58+H64+H70+H92+H76 -> 87303 | I27: =I46+I52+I58+I64+I70+I92+I76 -> 59040 | J27: =J46+J52+J58+J64+J70+J92+J76 -> 102175 | K27: =K46+K52+K58+K64+K70+K92+K76 -> 87481 | ... O27: =O46+O52+O58+O64+O70+O92+O76 -> 86204
A28: ='Distribution Dashboard'!A19 -> RA3 | B28: ='Distribution Dashboard'!B19 -> NRW | C28: ='Distribution Dashboard'!C19 -> m3 | D28: =D26-D27 -> 19066 | E28: =E26-E27 -> 20756 | F28: =F26-F27 -> 20337 | G28: =G26-G27 -> 24877 | H28: =H26-H27 -> 18830 | I28: =I26-I27 -> 15136 | J28: =J26-J27 -> 38946 | K28: =K26-K27 -> 18209 | ... O28: =O26-O27 -> 22723
A29: ='Distribution Dashboard'!A20 -> RA4 | B29: ='Distribution Dashboard'!B20 -> NRW | C29: ='Distribution Dashboard'!C20 -> % | D29: =D28/D26 -> 0.20641571 | E29: =E28/E26 -> 0.18139234 | F29: =F28/F26 -> 0.20025996 | G29: =G28/G26 -> 0.23120533 | H29: =H28/H26 -> 0.1774189 | I29: =I28/I26 -> 0.20405522 | J29: =J28/J26 -> 0.27597594 | K29: =K28/K26 -> 0.17228688 | ... O29: =O28/O26 -> 0.2086076
A30: ='Distribution Dashboard'!A21 -> 0 | B30: ='Distribution Dashboard'!B21 -> Amount Billed Water | C30: ='Distribution Dashboard'!C21 -> KES
A31: ='Distribution Dashboard'!A22 -> 0 | B31: ='Distribution Dashboard'!B22 -> Amount Billed Sewer | C31: ='Distribution Dashboard'!C22 -> KES
A32: ='Distribution Dashboard'!A23 -> 0 | B32: ='Distribution Dashboard'!B23 -> Number of Active water Connections | C32: ='Distribution Dashboard'!C23 -> KES
A33: ='Distribution Dashboard'!A24 -> 0 | B33: ='Distribution Dashboard'!B24 -> Number of Active sewer Connections | C33: ='Distribution Dashboard'!C24 -> KES
A34: ='Distribution Dashboard'!A25 -> 0 | B34: ='Distribution Dashboard'!B25 -> SOUTHERN REGION: MAI MAHIU,KAMERE,HELLSGATE | C34: ='Distribution Dashboard'!C25 -> 0
A35: ='Distribution Dashboard'!A26 -> RA6 (B) | B35: ='Distribution Dashboard'!B26 -> Volume Water Supplied | C35: ='Distribution Dashboard'!C26 -> m3 | D35: =D79+D85+D103+D121 -> 54389 | E35: =E79+E85+E103+E121 -> 64256 | F35: =F79+F85+F103+F121 -> 69964 | G35: =G79+G85+G103+G121 -> 71873 | H35: =H79+H85+H103+H121 -> 85219 | I35: =I79+I85+I103+I121 -> 47666 | J35: =J79+J85+J103+J121 -> 86546 | K35: =K79+K85+K103+K121 -> 74230 | ... O35: =O79+O85+O103+O121 -> 68068
A36: ='Distribution Dashboard'!A27 -> RB2 | B36: ='Distribution Dashboard'!B27 -> Volume Water Sold | C36: ='Distribution Dashboard'!C27 -> m3 | D36: =D80+D86+D104+D122 -> 41618 | E36: =E80+E86+E104+E122 -> 45120 | F36: =F80+F86+F104+F122 -> 50207 | G36: =G80+G86+G104+G122 -> 47973 | H36: =H80+H86+H104+H122 -> 60240 | I36: =I80+I86+I104+I122 -> 33336 | J36: =J80+J86+J104+J122 -> 53103 | K36: =K80+K86+K104+K122 -> 49874 | ... O36: =O80+O86+O104+O122 -> 48039
A37: ='Distribution Dashboard'!A28 -> RB3 (2) | B37: ='Distribution Dashboard'!B28 -> NRW | C37: ='Distribution Dashboard'!C28 -> m3 | D37: =D35-D36 -> 12771 | E37: =E35-E36 -> 19136 | F37: =F35-F36 -> 19757 | G37: =G35-G36 -> 23900 | H37: =H35-H36 -> 24979 | I37: =I35-I36 -> 14330 | J37: =J35-J36 -> 33443 | K37: =K35-K36 -> 24356 | ... O37: =O35-O36 -> 20029
A38: ='Distribution Dashboard'!A29 -> RB4 | B38: ='Distribution Dashboard'!B29 -> NRW | C38: ='Distribution Dashboard'!C29 -> % | D38: =D37/D35 -> 0.23480851 | E38: =E37/E35 -> 0.29780876 | F38: =F37/F35 -> 0.28238809 | G38: =G37/G35 -> 0.33253099 | H38: =H37/H35 -> 0.29311539 | I38: =I37/I35 -> 0.30063358 | J38: =J37/J35 -> 0.38641878 | K38: =K37/K35 -> 0.32811532 | ... O38: =O37/O35 -> 0.29424987
A39: ='Distribution Dashboard'!A30 -> 0 | B39: ='Distribution Dashboard'!B30 -> EASTERN REGION: KAYOLE,GONDI, KINUNGI,NJONJORO | C39: ='Distribution Dashboard'!C30 -> 0
A40: ='Distribution Dashboard'!A31 -> RA6 (B) (2) | B40: ='Distribution Dashboard'!B31 -> Volume Water Supplied | C40: ='Distribution Dashboard'!C31 -> m3 | D40: =D97+D125 -> 33056 | E40: =E97+E125 -> 39909 | F40: =F97+F125 -> 35284 | G40: =G97+G125 -> 38123 | H40: =H97+H125 -> 39016 | I40: =I97+I125 -> 29559 | J40: =J97+J125 -> 39778 | K40: =K97+K125 -> 36889 | ... O40: =O97+O125 -> 47240
A41: ='Distribution Dashboard'!A32 -> RB2 (3) | B41: ='Distribution Dashboard'!B32 -> Volume Water Sold | C41: ='Distribution Dashboard'!C32 -> m3 | D41: =D98+D126 -> 26497 | E41: =E98+E126 -> 29718 | F41: =F98+F126 -> 32245 | G41: =G98+G126 -> 30200 | H41: =H98+H126 -> 32349 | I41: =I98+I126 -> 24184 | J41: =J98+J126 -> 29173 | K41: =K98+K126 -> 28120 | ... O41: =O98+O126 -> 30668
A42: ='Distribution Dashboard'!A33 -> RB3 (3) | B42: ='Distribution Dashboard'!B33 -> NRW | C42: ='Distribution Dashboard'!C33 -> m3 | D42: =D40-D41 -> 6559 | E42: =E40-E41 -> 10191 | F42: =F40-F41 -> 3039 | G42: =G40-G41 -> 7923 | H42: =H40-H41 -> 6667 | I42: =I40-I41 -> 5375 | J42: =J40-J41 -> 10605 | K42: =K40-K41 -> 8769 | ... O42: =O40-O41 -> 16572
A43: ='Distribution Dashboard'!A33 -> RB3 (3) | B43: ='Distribution Dashboard'!B34 -> NRW | C43: ='Distribution Dashboard'!C33 -> m3 | D43: =D42/D40 -> 0.19842086 | E43: =E42/E40 -> 0.25535593 | F43: =F42/F40 -> 0.086129691 | G43: =G42/G40 -> 0.2078273 | H43: =H42/H40 -> 0.17087861 | I43: =I42/I40 -> 0.18183971 | J43: =J42/J40 -> 0.26660466 | K43: =K42/K40 -> 0.23771314 | ... O43: =O42/O40 -> 0.3508044
A44: ='Distribution Dashboard'!A34 -> RB4 (2) | B44: ='Distribution Dashboard'!B35 -> ZONE - CBD | C44: ='Distribution Dashboard'!C34 -> %
A45: ='Distribution Dashboard'!A36 -> 101 | B45: ='Distribution Dashboard'!B36 -> Volume Water Supplied | C45: ='Distribution Dashboard'!C36 -> m3 | D45: 19112 | E45: 23869 | F45: 20294 | G45: 23120 | H45: 22054 | I45: 15058 | J45: 30251 | K45: 21435 | L45: 22177 | M45: 21609 | N45: 22267 | O45: 22668
A46: ='Distribution Dashboard'!A37 -> 108 | B46: ='Distribution Dashboard'!B37 -> Volume Water Sold | C46: ='Distribution Dashboard'!C37 -> m3 | D46: 15333 | E46: 18128 | F46: 15348 | G46: 17288 | H46: 16464 | I46: 11402 | J46: 21639 | K46: 16771 | L46: 16898 | M46: 14822 | N46: 15647 | O46: 15127
A47: ='Distribution Dashboard'!A38 -> 122 | B47: ='Distribution Dashboard'!B38 -> NRW | C47: ='Distribution Dashboard'!C38 -> % | D47: =(D45-D46)/D45 -> 0.19772918 | E47: =(E45-E46)/E45 -> 0.24052118 | F47: =(F45-F46)/F45 -> 0.24371735 | G47: =(G45-G46)/G45 -> 0.25224913 | H47: =(H45-H46)/H45 -> 0.25346876 | I47: =(I45-I46)/I45 -> 0.24279453 | J47: =(J45-J46)/J45 -> 0.2846848 | K47: =(K45-K46)/K45 -> 0.21758806 | ... O47: =(O45-O46)/O45 -> 0.33267161
A48: ='Distribution Dashboard'!A39 -> 0 | B48: ='Distribution Dashboard'!B39 -> Amount Billed Water | C48: ='Distribution Dashboard'!C39 -> KES
A49: ='Distribution Dashboard'!A40 -> 0 | B49: ='Distribution Dashboard'!B40 -> Amount Billed Sewer | C49: ='Distribution Dashboard'!C40 -> KES
A50: ='Distribution Dashboard'!A41 -> 0 | B50: ='Distribution Dashboard'!B41 -> ZONE - CCCR | C50: ='Distribution Dashboard'!C41 -> 0
A51: ='Distribution Dashboard'!A42 -> 102 | B51: ='Distribution Dashboard'!B42 -> Volume Water Supplied | C51: ='Distribution Dashboard'!C42 -> m3 | D51: 16236 | E51: 22065 | F51: 17891 | G51: 19851 | H51: 19526 | I51: 14104 | J51: 25367 | K51: 19845 | L51: 19606 | M51: 15629 | N51: 21957 | O51: 21851
A52: ='Distribution Dashboard'!A43 -> 109 | B52: ='Distribution Dashboard'!B43 -> Volume Water Sold | C52: ='Distribution Dashboard'!C43 -> m3 | D52: 13187 | E52: 19014 | F52: 14518 | G52: 15348 | H52: 15020 | I52: 11149 | J52: 18653 | K52: 16512 | L52: 16356 | M52: 14401 | N52: 18218 | O52: 18443
A53: ='Distribution Dashboard'!A44 -> 123 | B53: ='Distribution Dashboard'!B44 -> NRW | C53: ='Distribution Dashboard'!C44 -> % | D53: =(D51-D52)/D51 -> 0.18779256 | E53: =(E51-E52)/E51 -> 0.13827328 | F53: =(F51-F52)/F51 -> 0.18853055 | G53: =(G51-G52)/G51 -> 0.22683996 | H53: =(H51-H52)/H51 -> 0.23076923 | I53: =(I51-I52)/I51 -> 0.20951503 | J53: =(J51-J52)/J51 -> 0.26467458 | K53: =(K51-K52)/K51 -> 0.16795163 | ... O53: =(O51-O52)/O51 -> 0.1559654
A54: ='Distribution Dashboard'!A45 -> 0 | B54: ='Distribution Dashboard'!B45 -> Amount Billed Water | C54: ='Distribution Dashboard'!C45 -> KES
A55: ='Distribution Dashboard'!A46 -> 0 | B55: ='Distribution Dashboard'!B46 -> Amount Billed Sewer | C55: ='Distribution Dashboard'!C46 -> KES
A56: ='Distribution Dashboard'!A47 -> 0 | B56: ='Distribution Dashboard'!B47 -> ZONE - LAKEVIEW | C56: ='Distribution Dashboard'!C47 -> 0
A57: ='Distribution Dashboard'!A48 -> 104 | B57: ='Distribution Dashboard'!B48 -> Volume Water Supplied | C57: ='Distribution Dashboard'!C48 -> m3 | D57: 29682 | E57: 27699 | F57: 25361 | G57: 26173 | H57: 25162 | I57: 17827 | J57: 33666 | K57: 27318 | L57: 31524 | M57: 17420 | N57: 21884 | O57: 27334
A58: ='Distribution Dashboard'!A49 -> 111 | B58: ='Distribution Dashboard'!B49 -> Volume Water Sold | C58: ='Distribution Dashboard'!C49 -> m3 | D58: 22322 | E58: 22874 | F58: 20854 | G58: 19690 | H58: 22452 | I58: 13727 | J58: 22903 | K58: =25437-2716 -> 22721 | L58: 23737 | M58: 14918 | N58: 19396 | O58: 20427
A59: ='Distribution Dashboard'!A50 -> 125 | B59: ='Distribution Dashboard'!B50 -> NRW | C59: ='Distribution Dashboard'!C50 -> % | D59: =(D57-D58)/D57 -> 0.24796173 | E59: =(E57-E58)/E57 -> 0.17419401 | F59: =(F57-F58)/F57 -> 0.17771381 | G59: =(G57-G58)/G57 -> 0.24769801 | H59: =(H57-H58)/H57 -> 0.10770209 | I59: =(I57-I58)/I57 -> 0.22998822 | J59: =(J57-J58)/J57 -> 0.3196994 | K59: =(K57-K58)/K57 -> 0.16827733 | ... O59: =(O57-O58)/O57 -> 0.25268896
A60: ='Distribution Dashboard'!A51 -> 0 | B60: ='Distribution Dashboard'!B51 -> Amount Billed Water | C60: ='Distribution Dashboard'!C51 -> KES
A61: ='Distribution Dashboard'!A52 -> 0 | B61: ='Distribution Dashboard'!B52 -> Amount Billed Sewer | C61: ='Distribution Dashboard'!C52 -> KES
A62: ='Distribution Dashboard'!A53 -> 0 | B62: ='Distribution Dashboard'!B53 -> ZONE - KABATI | C62: ='Distribution Dashboard'!C53 -> 0
A63: ='Distribution Dashboard'!A54 -> 103 | B63: ='Distribution Dashboard'!B54 -> Volume Water Supplied | C63: ='Distribution Dashboard'!C54 -> m3 | D63: 13873 | E63: 18468 | F63: 16003 | G63: 17425 | H63: 16584 | I63: 11489 | J63: 21782 | K63: 14988 | L63: 18296 | M63: 14499 | N63: 14001 | O63: 15536
A64: ='Distribution Dashboard'!A55 -> 110 | B64: ='Distribution Dashboard'!B55 -> Volume Water Sold | C64: ='Distribution Dashboard'!C55 -> m3 | D64: 10925 | E64: 14744 | F64: 12771 | G64: 12933 | H64: 14236 | I64: 9726 | J64: 16508 | K64: 13532 | L64: 15434 | M64: 11461 | N64: 12714 | O64: 13254
A65: ='Distribution Dashboard'!A56 -> 124 | B65: ='Distribution Dashboard'!B56 -> NRW | C65: ='Distribution Dashboard'!C56 -> % | D65: =(D63-D64)/D63 -> 0.2124991 | E65: =(E63-E64)/E63 -> 0.20164609 | F65: =(F63-F64)/F63 -> 0.20196213 | G65: =(G63-G64)/G63 -> 0.25779053 | H65: =(H63-H64)/H63 -> 0.14158225 | I65: =(I63-I64)/I63 -> 0.15345113 | J65: =(J63-J64)/J63 -> 0.24212653 | K65: =(K63-K64)/K63 -> 0.097144382 | ... O65: =(O63-O64)/O63 -> 0.14688465
A66: ='Distribution Dashboard'!A57 -> 0 | B66: ='Distribution Dashboard'!B57 -> Amount Billed | C66: ='Distribution Dashboard'!C57 -> KES
A67: ='Distribution Dashboard'!A58 -> 0 | B67: ='Distribution Dashboard'!B58 -> Amount Billed Sewer | C67: ='Distribution Dashboard'!C58 -> KES
A68: ='Distribution Dashboard'!A59 -> 0 | B68: ='Distribution Dashboard'!B59 -> ZONE - SITE AND SERVICES | C68: ='Distribution Dashboard'!C59 -> 0
A69: ='Distribution Dashboard'!A60 -> 105 | B69: ='Distribution Dashboard'!B60 -> Volume Water Supplied | C69: ='Distribution Dashboard'!C60 -> m3 | D69: 11520 | E69: 12895 | F69: 12355 | G69: 13424 | H69: 13622 | I69: 10061 | J69: 18043 | K69: 13219 | L69: 13964 | M69: 10907 | N69: 11166 | O69: 12006
A70: ='Distribution Dashboard'!A61 -> 112 | B70: ='Distribution Dashboard'!B61 -> Volume Water Sold | C70: ='Distribution Dashboard'!C61 -> m3 | D70: 9865 | E70: 11182 | F70: 9917 | G70: 10893 | H70: 10729 | I70: 7857 | J70: 13498 | K70: 10409 | L70: 12309 | M70: 9620 | N70: 10093 | O70: 10844
A71: ='Distribution Dashboard'!A62 -> 126 | B71: ='Distribution Dashboard'!B62 -> NRW | C71: ='Distribution Dashboard'!C62 -> % | D71: =(D69-D70)/D69 -> 0.14366319 | E71: =(E69-E70)/E69 -> 0.13284219 | F71: =(F69-F70)/F69 -> 0.19732902 | G71: =(G69-G70)/G69 -> 0.18854291 | H71: =(H69-H70)/H69 -> 0.21237704 | I71: =(I69-I70)/I69 -> 0.21906371 | J71: =(J69-J70)/J69 -> 0.25189824 | K71: =(K69-K70)/K69 -> 0.21257281 | ... O71: =(O69-O70)/O69 -> 0.096784941
A72: ='Distribution Dashboard'!A63 -> 0 | B72: ='Distribution Dashboard'!B63 -> Amount Billed Water | C72: ='Distribution Dashboard'!C63 -> KES
A73: ='Distribution Dashboard'!A64 -> 0 | B73: ='Distribution Dashboard'!B64 -> Amount Billed Sewer | C73: ='Distribution Dashboard'!C64 -> KES
A74: ='Distribution Dashboard'!A65 -> 0 | B74: ='Distribution Dashboard'!B65 -> ZONE - HOPEWELL | C74: ='Distribution Dashboard'!C65 -> 0
A75: ='Distribution Dashboard'!A66 -> 105B | B75: ='Distribution Dashboard'!B66 -> Volume Water Supplied | C75: ='Distribution Dashboard'!C66 -> m3 | E75: 6955 | F75: 7549 | G75: 5654 | H75: 7075 | I75: 4427 | J75: 8912 | K75: 6739 | L75: 7383 | M75: 5172 | N75: 5790 | O75: 7204
A76: ='Distribution Dashboard'!A67 -> 112B | B76: ='Distribution Dashboard'!B67 -> Volume Water Sold | C76: ='Distribution Dashboard'!C67 -> m3 | E76: 5621 | F76: 5975 | G76: 4906 | H76: 6607 | I76: 4156 | J76: 6448 | K76: 5728 | L76: 6684 | M76: 4887 | N76: 5510 | O76: 6078
A77: ='Distribution Dashboard'!A68 -> 126B | B77: ='Distribution Dashboard'!B68 -> NRW | C77: ='Distribution Dashboard'!C68 -> % | D77: =(D75-D76)/D75 -> #DIV/0! | E77: =(E75-E76)/E75 -> 0.19180446 | F77: =(F75-F76)/F75 -> 0.20850444 | G77: =(G75-G76)/G75 -> 0.13229572 | H77: =(H75-H76)/H75 -> 0.06614841 | I77: =(I75-I76)/I75 -> 0.06121527 | J77: =(J75-J76)/J75 -> 0.27648115 | K77: =(K75-K76)/K75 -> 0.15002226 | ... O77: =(O75-O76)/O75 -> 0.15630205
A78: ='Distribution Dashboard'!A69 -> 0 | B78: ='Distribution Dashboard'!B69 -> ZONE - KAMERE | C78: ='Distribution Dashboard'!C69 -> 0
A79: ='Distribution Dashboard'!A70 -> 106 | B79: ='Distribution Dashboard'!B70 -> Volume Water Supplied | C79: ='Distribution Dashboard'!C70 -> m3 | D79: 8393 | E79: 7436 | F79: =7621+805 -> 8426 | G79: =7463+746 -> 8209 | H79: =7893+1014 -> 8907 | I79: =5140+604 -> 5744 | J79: =9295+1412 -> 10707 | K79: =8519+1282 -> 9801 | L79: =8645+1212 -> 9857 | M79: =473+7248 -> 7721 | N79: =7983+464 -> 8447 | O79: 8408
A80: ='Distribution Dashboard'!A71 -> 113 | B80: ='Distribution Dashboard'!B71 -> Volume Water Sold | C80: ='Distribution Dashboard'!C71 -> m3 | D80: 6588 | E80: 6870 | F80: 6726 | G80: 6973 | H80: 7456 | I80: 4906 | J80: 7952 | K80: 8379 | L80: 8691 | M80: 6181 | N80: 6833 | O80: 6893
A81: ='Distribution Dashboard'!A72 -> 127 | B81: ='Distribution Dashboard'!B72 -> NRW | C81: ='Distribution Dashboard'!C72 -> % | D81: =(D79-D80)/D79 -> 0.21506017 | E81: =(E79-E80)/E79 -> 0.076116192 | F81: =(F79-F80)/F79 -> 0.20175647 | G81: =(G79-G80)/G79 -> 0.15056645 | H81: =(H79-H80)/H79 -> 0.16290558 | I81: =(I79-I80)/I79 -> 0.14589136 | J81: =(J79-J80)/J79 -> 0.2573083 | K81: =(K79-K80)/K79 -> 0.14508724 | ... O81: =(O79-O80)/O79 -> 0.18018554
A82: ='Distribution Dashboard'!A73 -> 0 | B82: ='Distribution Dashboard'!B73 -> Amount Billed Water | C82: ='Distribution Dashboard'!C73 -> KES
A83: ='Distribution Dashboard'!A74 -> 0 | B83: ='Distribution Dashboard'!B74 -> Amount Billed Sewer | C83: ='Distribution Dashboard'!C74 -> KES
A84: ='Distribution Dashboard'!A75 -> 0 | B84: ='Distribution Dashboard'!B75 -> ZONE - HELLS GATE | C84: ='Distribution Dashboard'!C75 -> 0
A85: ='Distribution Dashboard'!A76 -> 103 (3) | B85: ='Distribution Dashboard'!B76 -> Volume Water Supplied | C85: ='Distribution Dashboard'!C76 -> m3 | D85: 32348 | E85: 31918 | F85: 33901 | G85: 35361 | H85: 40547 | I85: 26277 | J85: 48222 | K85: 39376 | L85: 33139 | M85: 31995 | N85: 35998 | O85: 40515
A86: ='Distribution Dashboard'!A77 -> 110 (3) | B86: ='Distribution Dashboard'!B77 -> Volume Water Sold | C86: ='Distribution Dashboard'!C77 -> m3 | D86: 26728 | E86: 24225 | F86: 27308 | G86: 26535 | H86: 30367 | I86: 18026 | J86: 31140 | K86: 28691 | L86: 26588 | M86: 22538 | N86: 23286 | O86: 28109
A87: ='Distribution Dashboard'!A78 -> 124 (3) | B87: ='Distribution Dashboard'!B78 -> NRW | C87: ='Distribution Dashboard'!C78 -> % | D87: =(D85-D86)/D85 -> 0.17373563 | E87: =(E85-E86)/E85 -> 0.24102387 | F87: =(F85-F86)/F85 -> 0.19447804 | G87: =(G85-G86)/G85 -> 0.24959701 | H87: =(H85-H86)/H85 -> 0.25106666 | I87: =(I85-I86)/I85 -> 0.31400084 | J87: =(J85-J86)/J85 -> 0.35423666 | K87: =(K85-K86)/K85 -> 0.27135819 | ... O87: =(O85-O86)/O85 -> 0.30620758
A88: ='Distribution Dashboard'!A79 -> 0 | B88: ='Distribution Dashboard'!B79 -> Amount Billed Water | C88: ='Distribution Dashboard'!C79 -> KES
A89: ='Distribution Dashboard'!A80 -> 0 | B89: ='Distribution Dashboard'!B80 -> Amount Billed Sewer | C89: ='Distribution Dashboard'!C80 -> KES
A90: ='Distribution Dashboard'!A81 -> 0 | B90: ='Distribution Dashboard'!B81 -> KIHOTO | C90: ='Distribution Dashboard'!C81 -> 0
A91: ='Distribution Dashboard'!A82 -> 103 (2) | B91: ='Distribution Dashboard'!B82 -> Volume Water Supplied | C91: ='Distribution Dashboard'!C82 -> m3 | D91: 1944 | E91: 2475 | F91: 2100 | G91: 1950 | H91: 2110 | I91: 1210 | J91: 3100 | K91: 2146 | L91: 2470 | M91: 1856 | N91: 2483 | O91: 2328
A92: ='Distribution Dashboard'!A83 -> 110 (2) | B92: ='Distribution Dashboard'!B83 -> Volume Water Sold | C92: ='Distribution Dashboard'!C83 -> m3 | D92: 1669 | E92: 2107 | F92: 1833 | G92: 1662 | H92: 1795 | I92: 1023 | J92: 2526 | K92: 1808 | L92: 2118 | M92: 1486 | N92: 1589 | O92: 2031
A93: ='Distribution Dashboard'!A84 -> 124 (2) | B93: ='Distribution Dashboard'!B84 -> NRW | C93: ='Distribution Dashboard'!C84 -> % | D93: =(D91-D92)/D91 -> 0.14146091 | E93: =(E91-E92)/E91 -> 0.14868687 | F93: =(F91-F92)/F91 -> 0.12714286 | G93: =(G91-G92)/G91 -> 0.14769231 | H93: =(H91-H92)/H91 -> 0.1492891 | I93: =(I91-I92)/I91 -> 0.15454545 | J93: =(J91-J92)/J91 -> 0.18516129 | K93: =(K91-K92)/K91 -> 0.15750233 | ... O93: =(O91-O92)/O91 -> 0.12757732
A94: ='Distribution Dashboard'!A85 -> 0 | B94: ='Distribution Dashboard'!B85 -> Amount Billed Water | C94: ='Distribution Dashboard'!C85 -> KES
A95: ='Distribution Dashboard'!A86 -> 0 | B95: ='Distribution Dashboard'!B86 -> Amount Billed Sewer | C95: ='Distribution Dashboard'!C86 -> KES
A96: ='Distribution Dashboard'!A87 -> 0 | B96: ='Distribution Dashboard'!B87 -> KAYOLE | C96: ='Distribution Dashboard'!C87 -> 0
A97: ='Distribution Dashboard'!A88 -> 103 (4) | B97: ='Distribution Dashboard'!B88 -> Volume Water Supplied | C97: ='Distribution Dashboard'!C88 -> m3 | D97: =32530+433 -> 32963 | E97: 39718 | F97: =34176+565+318 -> 35059 | G97: =37172+344+364 -> 37880 | H97: =38183+345+311 -> 38839 | I97: =28933+161+314 -> 29408 | J97: =474+39063+224 -> 39761 | K97: =35916+508+465 -> 36889 | L97: =42961+448+657 -> 44066 | M97: =351+31702+442 -> 32495 | N97: =415+42840+154 -> 43409 | O97: 47163
A98: ='Distribution Dashboard'!A89 -> 110 (4) | B98: ='Distribution Dashboard'!B89 -> Volume Water Sold | C98: ='Distribution Dashboard'!C89 -> m3 | D98: 26406 | E98: 29527 | F98: 32020 | G98: 29957 | H98: 32172 | I98: 24033 | J98: 29156 | K98: 28120 | L98: 29681 | M98: 26294 | N98: 27869 | O98: 30591
A99: ='Distribution Dashboard'!A90 -> 124 (4) | B99: ='Distribution Dashboard'!B90 -> NRW | C99: ='Distribution Dashboard'!C90 -> % | D99: =(D97-D98)/D97 -> 0.19892 | E99: =(E97-E98)/E97 -> 0.25658392 | F99: =(F97-F98)/F97 -> 0.08668245 | G99: =(G97-G98)/G97 -> 0.20916051 | H99: =(H97-H98)/H97 -> 0.17165735 | I99: =(I97-I98)/I97 -> 0.18277339 | J99: =(J97-J98)/J97 -> 0.26671864 | K99: =(K97-K98)/K97 -> 0.23771314 | ... O99: =(O97-O98)/O97 -> 0.35137714
A100: ='Distribution Dashboard'!A91 -> 0 | B100: ='Distribution Dashboard'!B91 -> Amount Billed Water | C100: ='Distribution Dashboard'!C91 -> KES
...

Sheet Actual2223
A1: ='Distribution Dashboard'!A1 -> NAIVAWASS DISTRIBUTION DASHBOARD - NON-REVENUE WATER & ZONAL PERFORMANCE | B1: ='Distribution Dashboard'!B1 -> 0 | C1: ='Distribution Dashboard'!D1 -> 0
A2: ='Distribution Dashboard'!A2 -> 0 | B2: ='Distribution Dashboard'!B2 -> 46054 | C2: ='Distribution Dashboard'!D2 -> 0
A3: ='Distribution Dashboard'!A3 -> 0 | B3: ='Distribution Dashboard'!B3 -> 0 | C3: ='Distribution Dashboard'!D3 -> Monthly
A4: ='Distribution Dashboard'!A4 -> 0 | C4: ='Distribution Dashboard'!C4 -> Unit | D4: 44743 | E4: 44774 | F4: 44805 | G4: 44835 | H4: 44866 | I4: 44896 | J4: 44927 | K4: 44958 | L4: 44986 | M4: 45017 | N4: 45047 | O4: 45078
A5: ='Distribution Dashboard'!A6 -> 0 | B5: ='Distribution Dashboard'!B6 -> REGIONAL NRW | C5: ='Distribution Dashboard'!C6 -> 0
A6: ='Distribution Dashboard'!A7 -> 100 | B6: ='Distribution Dashboard'!B7 -> WATER AVAILABLE FOR SALES- REGIONS | C6: ='Distribution Dashboard'!C7 -> m3 | D6: =D17+D26+D27 -> 202300 | E6: =E17+E26+E27 -> 205466 | F6: =F17+F26+F31 -> 211119 | G6: =G17+G26+G31 -> 159438 | H6: =H17+H26+H31 -> 176489 | I6: =I17+I26+I31 -> 173351 | J6: =J17+J26+J31 -> 187922 | K6: =K17+K26+K31 -> 216999 | L6: =L17+L26+L31 -> 215601 | M6: =M17+M26+M31 -> 200611 | ... O6: =O17+O26+O31 -> 185559
A7: ='Distribution Dashboard'!A8 -> 128a | B7: ='Distribution Dashboard'!B8 -> VOLUME WATER BILLED(CUSTOMERS-M3) | C7: ='Distribution Dashboard'!C8 -> m3 | D7: =D18+D27+D31 -> 152162 | E7: =E18+E27+E31 -> 157614 | F7: =F18+F27+F32 -> 139547 | G7: =G18+G27+G32 -> 120836 | H7: =H18+H27+H32 -> 123996 | I7: =I18+I27+I32 -> 130054 | J7: =J18+J27+J32 -> 138635 | K7: =K18+K27+K32 -> 153470 | L7: =L18+L27+L32 -> 163824 | M7: =M18+M27+M32 -> 145291 | ... O7: =O18+O27+O32 -> 137010
A8: ='Distribution Dashboard'!A9 -> 128 | B8: ='Distribution Dashboard'!B9 -> GLOBAL NRW | C8: ='Distribution Dashboard'!C9 -> % | D8: =(D6-D7)/D6 -> 0.24783984 | E8: =(E6-E7)/E6 -> 0.23289498 | F8: =(F6-F7)/F6 -> 0.33901259 | G8: =(G6-G7)/G6 -> 0.24211292 | H8: =(H6-H7)/H6 -> 0.2974293 | I8: =(I6-I7)/I6 -> 0.24976493 | J8: =(J6-J7)/J6 -> 0.26227371 | K8: =(K6-K7)/K6 -> 0.29276172 | ... O8: =(O6-O7)/O6 -> 0.26163646
A9: ='Distribution Dashboard'!A10 -> 0 | B9: ='Distribution Dashboard'!B10 -> Number of Active water Connections | C9: ='Distribution Dashboard'!C10 -> NO. | D9: =D32+D23 -> 23761 | E9: =E32+E23 -> 27125 | F9: =F32+F23 -> 16098 | G9: =G32+G23 -> 19707 | H9: =H32+H23 -> 21640 | I9: =I32+I23 -> 20144 | J9: =J32+J23 -> 22923 | K9: =K32+K23 -> 24955 | ... O9: =O32+O23 -> 22371
A10: ='Distribution Dashboard'!A11 -> 0 | B10: ='Distribution Dashboard'!B11 -> Number of Active sewer Connections | C10: ='Distribution Dashboard'!C11 -> NO. | D10: =D33+D24 -> 7326 | E10: =E33+E24 -> 5299 | F10: =F33+F24 -> 8296 | G10: =G33+G24 -> 3219 | H10: =H33+H24 -> 8027 | I10: =I33+I24 -> 5516 | J10: =J33+J24 -> 6620 | K10: =K33+K24 -> 8110 | ... O10: =O33+O24 -> 7283
A11: ='Distribution Dashboard'!A12 -> 0 | B11: ='Distribution Dashboard'!B12 -> Number of In-active Sewer Connections | C11: ='Distribution Dashboard'!C12 -> NO.
A12: ='Distribution Dashboard'!A13 -> 0 | B12: ='Distribution Dashboard'!B13 -> Number of In-active Water Connections | C12: ='Distribution Dashboard'!C13 -> NO.
A13: ='Distribution Dashboard'!A14 -> 0 | B13: ='Distribution Dashboard'!B14 -> Number of Connections | C13: ='Distribution Dashboard'!C14 -> NO. | D13: =SUM(D9:D12) -> 31087 | E13: =SUM(E9:E12) -> 32424 | F13: =SUM(F9:F12) -> 24394 | G13: =SUM(G9:G12) -> 22926 | H13: =SUM(H9:H12) -> 29667 | I13: =SUM(I9:I12) -> 25660 | J13: =SUM(J9:J12) -> 29543 | K13: =SUM(K9:K12) -> 33065 | ... O13: =SUM(O9:O12) -> 29654
A14: ='Distribution Dashboard'!A15 -> 0 | B14: ='Distribution Dashboard'!B15 -> Maintenance, repair and operational cost | C14: ='Distribution Dashboard'!C15 -> KES
A15: ='Distribution Dashboard'!#REF! -> #REF! | B15: ='Distribution Dashboard'!#REF! -> #REF! | C15: ='Distribution Dashboard'!#REF! -> #REF!
A16: ='Distribution Dashboard'!A16 -> 0 | B16: ='Distribution Dashboard'!B16 -> CENTRAL REGION: CBD,CCCR,KABATI,SITE,KIHOTO,LAKEVIEW | C16: ='Distribution Dashboard'!C16 -> 0
A17: ='Distribution Dashboard'!A17 -> RA | B17: ='Distribution Dashboard'!B17 -> Volume Water Supplied | C17: ='Distribution Dashboard'!C17 -> m3 | D17: =D36+D42+D48+D54+D60+D78 -> 130641 | E17: =E36+E42+E48+E54+E60+E78 -> 128120 | F17: =F36+F42+F48+F54+F60+F78 -> 139029 | G17: =G36+G42+G48+G54+G60+G78 -> 95119 | H17: =H36+H42+H48+H54+H60+H78 -> 100181 | I17: =I36+I42+I48+I54+I60+I78 -> 108449 | J17: =J36+J42+J48+J54+J60+J78 -> 106481 | K17: =K36+K42+K48+K54+K60+K78 -> 125827 | ... O17: =O36+O42+O48+O54+O60+O78 -> 108257
A18: ='Distribution Dashboard'!A18 -> RA2 | B18: ='Distribution Dashboard'!B18 -> Volume Water Sold | C18: ='Distribution Dashboard'!C18 -> m3 | D18: =D37+D43+D49+D55+D61+D79 -> 90624 | E18: =E37+E43+E49+E55+E61+E79 -> 92447 | F18: =F37+F43+F49+F55+F61+F79 -> 91237 | G18: =G37+G43+G49+G55+G61+G79 -> 70936 | H18: =H37+H43+H49+H55+H61+H79 -> 71901 | I18: =I37+I43+I49+I55+I61+I79 -> 80684 | J18: =J37+J43+J49+J55+J61+J79 -> 82616 | K18: =K37+K43+K49+K55+K61+K79 -> 91234 | ... O18: =O37+O43+O49+O55+O61+O79 -> 81174
A19: ='Distribution Dashboard'!A19 -> RA3 | B19: ='Distribution Dashboard'!B19 -> NRW | C19: ='Distribution Dashboard'!C19 -> m3 | D19: =D17-D18 -> 40017 | E19: =E17-E18 -> 35673 | F19: =F17-F18 -> 47792 | G19: =G17-G18 -> 24183 | H19: =H17-H18 -> 28280 | I19: =I17-I18 -> 27765 | J19: =J17-J18 -> 23865 | K19: =K17-K18 -> 34593 | ... O19: =O17-O18 -> 27083
A20: ='Distribution Dashboard'!A20 -> RA4 | B20: ='Distribution Dashboard'!B20 -> NRW | C20: ='Distribution Dashboard'!C20 -> % | D20: =D19/D17 -> 0.30631272 | E20: =E19/E17 -> 0.27843428 | F20: =F19/F17 -> 0.34375562 | G20: =G19/G17 -> 0.25423943 | H20: =H19/H17 -> 0.28228906 | I20: =I19/I17 -> 0.25601896 | J20: =J19/J17 -> 0.22412449 | K20: =K19/K17 -> 0.2749251 | ... O20: =O19/O17 -> 0.2501732
A21: ='Distribution Dashboard'!A21 -> 0 | B21: ='Distribution Dashboard'!B21 -> Amount Billed Water | C21: ='Distribution Dashboard'!C21 -> KES
A22: ='Distribution Dashboard'!A22 -> 0 | B22: ='Distribution Dashboard'!B22 -> Amount Billed Sewer | C22: ='Distribution Dashboard'!C22 -> KES
A23: ='Distribution Dashboard'!A23 -> 0 | B23: ='Distribution Dashboard'!B23 -> Number of Active water Connections | C23: ='Distribution Dashboard'!C23 -> KES
A24: ='Distribution Dashboard'!A24 -> 0 | B24: ='Distribution Dashboard'!B24 -> Number of Active sewer Connections | C24: ='Distribution Dashboard'!C24 -> KES
A25: ='Distribution Dashboard'!A25 -> 0 | B25: ='Distribution Dashboard'!B25 -> SOUTHERN REGION: MAI MAHIU,KAMERE,HELLSGATE | C25: ='Distribution Dashboard'!C25 -> 0
A26: ='Distribution Dashboard'!A26 -> RA6 (B) | B26: ='Distribution Dashboard'!B26 -> Volume Water Supplied | C26: ='Distribution Dashboard'!C26 -> m3 | D26: =D66+D72+D90 -> 41208 | E26: =E66+E72+E90 -> 44603 | F26: =F66+F72+F90 -> 47696 | G26: =G66+G72+G90 -> 41393 | H26: =H66+H72+H90 -> 46641 | I26: =I66+I72+I90 -> 39242 | J26: =J66+J72+J90 -> 51898 | K26: =K66+K72+K90 -> 58107 | ... O26: =O66+O72+O90 -> 47648
A27: ='Distribution Dashboard'!A27 -> RB2 | B27: ='Distribution Dashboard'!B27 -> Volume Water Sold | C27: ='Distribution Dashboard'!C27 -> m3 | D27: =D67+D73+D91 -> 30451 | E27: =E67+E73+E91 -> 32743 | F27: =F67+F73+F91 -> 32212 | G27: =G67+G73+G91 -> 30193 | H27: =H67+H73+H91 -> 30455 | I27: =I67+I73+I91 -> 29226 | J27: =J67+J73+J91 -> 33096 | K27: =K67+K73+K91 -> 37281 | ... O27: =O67+O73+O91 -> 33465
A28: ='Distribution Dashboard'!A28 -> RB3 (2) | B28: ='Distribution Dashboard'!B28 -> NRW | C28: ='Distribution Dashboard'!C28 -> m3 | D28: =D26-D27 -> 10757 | E28: =E26-E27 -> 11860 | F28: =F26-F27 -> 15484 | G28: =G26-G27 -> 11200 | H28: =H26-H27 -> 16186 | I28: =I26-I27 -> 10016 | J28: =J26-J27 -> 18802 | K28: =K26-K27 -> 20826 | ... O28: =O26-O27 -> 14183
A29: ='Distribution Dashboard'!A29 -> RB4 | B29: ='Distribution Dashboard'!B29 -> NRW | C29: ='Distribution Dashboard'!C29 -> % | D29: =D28/D26 -> 0.26104155 | E29: =E28/E26 -> 0.2659014 | F29: =F28/F26 -> 0.32463938 | G29: =G28/G26 -> 0.27057715 | H29: =H28/H26 -> 0.34703373 | I29: =I28/I26 -> 0.25523674 | J29: =J28/J26 -> 0.36228756 | K29: =K28/K26 -> 0.35840776 | ... O29: =O28/O26 -> 0.29766202
A30: ='Distribution Dashboard'!A30 -> 0 | B30: ='Distribution Dashboard'!B30 -> EASTERN REGION: KAYOLE,GONDI, KINUNGI,NJONJORO | C30: ='Distribution Dashboard'!C30 -> 0
A31: ='Distribution Dashboard'!A31 -> RA6 (B) (2) | B31: ='Distribution Dashboard'!B31 -> Volume Water Supplied | C31: ='Distribution Dashboard'!C31 -> m3 | D31: =D84+D96+D100+D104 -> 31087 | E31: =E84+E96+E100+E104 -> 32424 | F31: =F84+F96+F100+F104 -> 24394 | G31: =G84+G96+G100+G104 -> 22926 | H31: =H84+H96+H100+H104 -> 29667 | I31: =I84+I96+I100+I104 -> 25660 | J31: =J84+J96+J100+J104 -> 29543 | K31: =K84+K96+K100+K104 -> 33065 | ... O31: =O84+O96+O100+O104 -> 29654
A32: ='Distribution Dashboard'!A32 -> RB2 (3) | B32: ='Distribution Dashboard'!B32 -> Volume Water Sold | C32: ='Distribution Dashboard'!C32 -> m3 | D32: =D85+D97+D101+D105 -> 23761 | E32: =E85+E97+E101+E105 -> 27125 | F32: =F85+F97+F101+F105 -> 16098 | G32: =G85+G97+G101+G105 -> 19707 | H32: =H85+H97+H101+H105 -> 21640 | I32: =I85+I97+I101+I105 -> 20144 | J32: =J85+J97+J101+J105 -> 22923 | K32: =K85+K97+K101+K105 -> 24955 | ... O32: =O85+O97+O101+O105 -> 22371
A33: ='Distribution Dashboard'!A33 -> RB3 (3) | B33: ='Distribution Dashboard'!B33 -> NRW | C33: ='Distribution Dashboard'!C33 -> m3 | D33: =D31-D32 -> 7326 | E33: =E31-E32 -> 5299 | F33: =F31-F32 -> 8296 | G33: =G31-G32 -> 3219 | H33: =H31-H32 -> 8027 | I33: =I31-I32 -> 5516 | J33: =J31-J32 -> 6620 | K33: =K31-K32 -> 8110 | ... O33: =O31-O32 -> 7283
A34: ='Distribution Dashboard'!A33 -> RB3 (3) | B34: ='Distribution Dashboard'!B34 -> NRW | C34: ='Distribution Dashboard'!C33 -> m3 | D34: =D33/D31 -> 0.23566121 | E34: =E33/E31 -> 0.16342832 | F34: =F33/F31 -> 0.34008363 | G34: =G33/G31 -> 0.14040827 | H34: =H33/H31 -> 0.27056999 | I34: =I33/I31 -> 0.21496493 | J34: =J33/J31 -> 0.22408015 | K34: =K33/K31 -> 0.24527446 | ... O34: =O33/O31 -> 0.24559924
A35: ='Distribution Dashboard'!A34 -> RB4 (2) | B35: ='Distribution Dashboard'!B35 -> ZONE - CBD | C35: ='Distribution Dashboard'!C34 -> %
A36: ='Distribution Dashboard'!A36 -> 101 | B36: ='Distribution Dashboard'!B36 -> Volume Water Supplied | C36: ='Distribution Dashboard'!C36 -> m3 | D36: 27084 | E36: 29273 | F36: 34236 | G36: 18117 | H36: 23467 | I36: 22590 | J36: 19637 | K36: 27368 | L36: 26236 | M36: 24481 | N36: 25388 | O36: 22257
A37: ='Distribution Dashboard'!A37 -> 108 | B37: ='Distribution Dashboard'!B37 -> Volume Water Sold | C37: ='Distribution Dashboard'!C37 -> m3 | D37: 16276 | E37: 15745 | F37: 14638 | G37: 10926 | H37: 16241 | I37: 14596 | J37: 13738 | K37: 16338 | L37: 16947 | M37: 13863 | N37: 14764 | O37: 15453
A38: ='Distribution Dashboard'!A38 -> 122 | B38: ='Distribution Dashboard'!B38 -> NRW | C38: ='Distribution Dashboard'!C38 -> % | D38: =(D36-D37)/D36 -> 0.39905479 | E38: =(E36-E37)/E36 -> 0.46213234 | F38: =(F36-F37)/F36 -> 0.57243837 | G38: =(G36-G37)/G36 -> 0.39692002 | H38: =(H36-H37)/H36 -> 0.30792176 | I38: =(I36-I37)/I36 -> 0.3538734 | J38: =(J36-J37)/J36 -> 0.3004023 | K38: =(K36-K37)/K36 -> 0.40302543 | ... O38: =(O36-O37)/O36 -> 0.30570158
A39: ='Distribution Dashboard'!A39 -> 0 | B39: ='Distribution Dashboard'!B39 -> Amount Billed Water | C39: ='Distribution Dashboard'!C39 -> KES
A40: ='Distribution Dashboard'!A40 -> 0 | B40: ='Distribution Dashboard'!B40 -> Amount Billed Sewer | C40: ='Distribution Dashboard'!C40 -> KES
A41: ='Distribution Dashboard'!A41 -> 0 | B41: ='Distribution Dashboard'!B41 -> ZONE - CCCR | C41: ='Distribution Dashboard'!C41 -> 0
A42: ='Distribution Dashboard'!A42 -> 102 | B42: ='Distribution Dashboard'!B42 -> Volume Water Supplied | C42: ='Distribution Dashboard'!C42 -> m3 | D42: 38982 | E42: 32157 | F42: 29043 | G42: 19707 | H42: 21588 | I42: 29406 | J42: 27080 | K42: 28569 | L42: 26192 | M42: 29087 | N42: 28761 | O42: 27337
A43: ='Distribution Dashboard'!A43 -> 109 | B43: ='Distribution Dashboard'!B43 -> Volume Water Sold | C43: ='Distribution Dashboard'!C43 -> m3 | D43: 25989 | E43: 25915 | F43: 22961 | G43: 15606 | H43: 18594 | I43: 22016 | J43: 22166 | K43: 22610 | L43: 23154 | M43: 22838 | N43: 21463 | O43: 21858
A44: ='Distribution Dashboard'!A44 -> 123 | B44: ='Distribution Dashboard'!B44 -> NRW | C44: ='Distribution Dashboard'!C44 -> % | D44: =(D42-D43)/D42 -> 0.33330768 | E44: =(E42-E43)/E42 -> 0.19411015 | F44: =(F42-F43)/F42 -> 0.20941363 | G44: =(G42-G43)/G42 -> 0.20809865 | H44: =(H42-H43)/H42 -> 0.13868816 | I44: =(I42-I43)/I42 -> 0.25130926 | J44: =(J42-J43)/J42 -> 0.18146233 | K44: =(K42-K43)/K42 -> 0.20858273 | ... O44: =(O42-O43)/O42 -> 0.20042433
A45: ='Distribution Dashboard'!A45 -> 0 | B45: ='Distribution Dashboard'!B45 -> Amount Billed Water | C45: ='Distribution Dashboard'!C45 -> KES
A46: ='Distribution Dashboard'!A46 -> 0 | B46: ='Distribution Dashboard'!B46 -> Amount Billed Sewer | C46: ='Distribution Dashboard'!C46 -> KES
A47: ='Distribution Dashboard'!A47 -> 0 | B47: ='Distribution Dashboard'!B47 -> ZONE - LAKEVIEW | C47: ='Distribution Dashboard'!C47 -> 0
A48: ='Distribution Dashboard'!A48 -> 104 | B48: ='Distribution Dashboard'!B48 -> Volume Water Supplied | C48: ='Distribution Dashboard'!C48 -> m3 | D48: 33482 | E48: 34676 | F48: 42603 | G48: 27372 | H48: 26658 | I48: 26063 | J48: 30406 | K48: 34515 | L48: 31324 | M48: 26746 | N48: 26536 | O48: 27776
A49: ='Distribution Dashboard'!A49 -> 111 | B49: ='Distribution Dashboard'!B49 -> Volume Water Sold | C49: ='Distribution Dashboard'!C49 -> m3 | D49: 23236 | E49: 25400 | F49: 32739 | G49: 20259 | H49: 19822 | I49: 21110 | J49: 23140 | K49: 25593 | L49: 27005 | M49: 24587 | N49: 16817 | O49: 21299
A50: ='Distribution Dashboard'!A50 -> 125 | B50: ='Distribution Dashboard'!B50 -> NRW | C50: ='Distribution Dashboard'!C50 -> % | D50: =(D48-D49)/D48 -> 0.30601517 | E50: =(E48-E49)/E48 -> 0.2675049 | F50: =(F48-F49)/F48 -> 0.23153299 | G50: =(G48-G49)/G48 -> 0.25986409 | H50: =(H48-H49)/H48 -> 0.25643334 | I50: =(I48-I49)/I48 -> 0.19003952 | J50: =(J48-J49)/J48 -> 0.23896599 | K50: =(K48-K49)/K48 -> 0.25849631 | ... O50: =(O48-O49)/O48 -> 0.23318692
A51: ='Distribution Dashboard'!A51 -> 0 | B51: ='Distribution Dashboard'!B51 -> Amount Billed Water | C51: ='Distribution Dashboard'!C51 -> KES
A52: ='Distribution Dashboard'!A52 -> 0 | B52: ='Distribution Dashboard'!B52 -> Amount Billed Sewer | C52: ='Distribution Dashboard'!C52 -> KES
A53: ='Distribution Dashboard'!A53 -> 0 | B53: ='Distribution Dashboard'!B53 -> ZONE - KABATI | C53: ='Distribution Dashboard'!C53 -> 0
A54: ='Distribution Dashboard'!A54 -> 103 | B54: ='Distribution Dashboard'!B54 -> Volume Water Supplied | C54: ='Distribution Dashboard'!C54 -> m3 | D54: 17591 | E54: 18277 | F54: 19226 | G54: 15721 | H54: 16212 | I54: 16586 | J54: 14323 | K54: 19047 | L54: 19044 | M54: 17801 | N54: 16113 | O54: 15798
A55: ='Distribution Dashboard'!A55 -> 110 | B55: ='Distribution Dashboard'!B55 -> Volume Water Sold | C55: ='Distribution Dashboard'!C55 -> m3 | D55: 12529 | E55: 13190 | F55: 10526 | G55: 13004 | H55: 7682 | I55: 12092 | J55: 10940 | K55: 13438 | L55: 13760 | M55: 11740 | N55: 9964 | O55: 11468
A56: ='Distribution Dashboard'!A56 -> 124 | B56: ='Distribution Dashboard'!B56 -> NRW | C56: ='Distribution Dashboard'!C56 -> % | D56: =(D54-D55)/D54 -> 0.28776079 | E56: =(E54-E55)/E54 -> 0.27832795 | F56: =(F54-F55)/F54 -> 0.45251222 | G56: =(G54-G55)/G54 -> 0.17282616 | H56: =(H54-H55)/H54 -> 0.52615347 | I56: =(I54-I55)/I54 -> 0.2709514 | J56: =(J54-J55)/J54 -> 0.23619353 | K56: =(K54-K55)/K54 -> 0.29448207 | ... O56: =(O54-O55)/O54 -> 0.27408533
A57: ='Distribution Dashboard'!A57 -> 0 | B57: ='Distribution Dashboard'!B57 -> Amount Billed | C57: ='Distribution Dashboard'!C57 -> KES
A58: ='Distribution Dashboard'!A58 -> 0 | B58: ='Distribution Dashboard'!B58 -> Amount Billed Sewer | C58: ='Distribution Dashboard'!C58 -> KES
A59: ='Distribution Dashboard'!A59 -> 0 | B59: ='Distribution Dashboard'!B59 -> ZONE - SITE AND SERVICES | C59: ='Distribution Dashboard'!C59 -> 0
A60: ='Distribution Dashboard'!A60 -> 105 | B60: ='Distribution Dashboard'!B60 -> Volume Water Supplied | C60: ='Distribution Dashboard'!C60 -> m3 | D60: 11927 | E60: 12251 | F60: 12513 | G60: 12532 | H60: 10496 | I60: 11866 | J60: 12158 | K60: 13341 | L60: 12024 | M60: 13105 | N60: 12878 | O60: 12700
A61: ='Distribution Dashboard'!A61 -> 112 | B61: ='Distribution Dashboard'!B61 -> Volume Water Sold | C61: ='Distribution Dashboard'!C61 -> m3 | D61: 10322 | E61: 10117 | F61: 9026 | G61: 10000 | H61: 7869 | I61: 9280 | J61: 10263 | K61: 11014 | L61: 10702 | M61: 10235 | N61: 9134 | O61: 9404
A62: ='Distribution Dashboard'!A62 -> 126 | B62: ='Distribution Dashboard'!B62 -> NRW | C62: ='Distribution Dashboard'!C62 -> % | D62: =(D60-D61)/D60 -> 0.13456863 | E62: =(E60-E61)/E60 -> 0.17418986 | F62: =(F60-F61)/F60 -> 0.27867018 | G62: =(G60-G61)/G60 -> 0.20204277 | H62: =(H60-H61)/H60 -> 0.25028582 | I62: =(I60-I61)/I60 -> 0.21793359 | J62: =(J60-J61)/J60 -> 0.15586445 | K62: =(K60-K61)/K60 -> 0.17442471 | ... O62: =(O60-O61)/O60 -> 0.25952756
A63: ='Distribution Dashboard'!A63 -> 0 | B63: ='Distribution Dashboard'!B63 -> Amount Billed Water | C63: ='Distribution Dashboard'!C63 -> KES
A64: ='Distribution Dashboard'!A64 -> 0 | B64: ='Distribution Dashboard'!B64 -> Amount Billed Sewer | C64: ='Distribution Dashboard'!C64 -> KES
A65: ='Distribution Dashboard'!A69 -> 0 | B65: ='Distribution Dashboard'!B69 -> ZONE - KAMERE | C65: ='Distribution Dashboard'!C69 -> 0
A66: ='Distribution Dashboard'!A70 -> 106 | B66: ='Distribution Dashboard'!B70 -> Volume Water Supplied | C66: ='Distribution Dashboard'!C70 -> m3 | D66: 8218 | E66: 8614 | F66: 8518 | G66: 7756 | H66: 10551 | I66: 7323 | J66: 8005 | K66: 8581 | L66: 7724 | M66: 7180 | N66: 4554 | O66: 7600
A67: ='Distribution Dashboard'!A71 -> 113 | B67: ='Distribution Dashboard'!B71 -> Volume Water Sold | C67: ='Distribution Dashboard'!C71 -> m3 | D67: 6689 | E67: 7168 | F67: 6762 | G67: 6199 | H67: 5794 | I67: 5451 | J67: 5916 | K67: 6958 | L67: 6756 | M67: 6326 | N67: 4365 | O67: 5937
A68: ='Distribution Dashboard'!A72 -> 127 | B68: ='Distribution Dashboard'!B72 -> NRW | C68: ='Distribution Dashboard'!C72 -> % | D68: =(D66-D67)/D66 -> 0.186055 | E68: =(E66-E67)/E66 -> 0.16786626 | F68: =(F66-F67)/F66 -> 0.20615168 | G68: =(G66-G67)/G66 -> 0.20074781 | H68: =(H66-H67)/H66 -> 0.45085774 | I68: =(I66-I67)/I66 -> 0.25563294 | J68: =(J66-J67)/J66 -> 0.2609619 | K68: =(K66-K67)/K66 -> 0.1891388 | ... O68: =(O66-O67)/O66 -> 0.21881579
A69: ='Distribution Dashboard'!A73 -> 0 | B69: ='Distribution Dashboard'!B73 -> Amount Billed Water | C69: ='Distribution Dashboard'!C73 -> KES
A70: ='Distribution Dashboard'!A74 -> 0 | B70: ='Distribution Dashboard'!B74 -> Amount Billed Sewer | C70: ='Distribution Dashboard'!C74 -> KES
A71: ='Distribution Dashboard'!A75 -> 0 | B71: ='Distribution Dashboard'!B75 -> ZONE - HELLS GATE | C71: ='Distribution Dashboard'!C75 -> 0
A72: ='Distribution Dashboard'!A76 -> 103 (3) | B72: ='Distribution Dashboard'!B76 -> Volume Water Supplied | C72: ='Distribution Dashboard'!C76 -> m3 | D72: 28838 | E72: 30652 | F72: 31585 | G72: 25426 | H72: 28565 | I72: 24228 | J72: 30171 | K72: 33537 | L72: 31889 | M72: 30995 | N72: 21791 | O72: 31533
A73: ='Distribution Dashboard'!A77 -> 110 (3) | B73: ='Distribution Dashboard'!B77 -> Volume Water Sold | C73: ='Distribution Dashboard'!C77 -> m3 | D73: 20752 | E73: 21521 | F73: 18968 | G73: 18382 | H73: 19743 | I73: 17301 | J73: 20591 | K73: 22250 | L73: 24784 | M73: 22577 | N73: 14170 | O73: 22076
A74: ='Distribution Dashboard'!A78 -> 124 (3) | B74: ='Distribution Dashboard'!B78 -> NRW | C74: ='Distribution Dashboard'!C78 -> % | D74: =(D72-D73)/D72 -> 0.28039392 | E74: =(E72-E73)/E72 -> 0.29789247 | F74: =(F72-F73)/F72 -> 0.39946177 | G74: =(G72-G73)/G72 -> 0.27703925 | H74: =(H72-H73)/H72 -> 0.30883949 | I74: =(I72-I73)/I72 -> 0.28590887 | J74: =(J72-J73)/J72 -> 0.31752345 | K74: =(K72-K73)/K72 -> 0.33655366 | ... O74: =(O72-O73)/O72 -> 0.29990803
A75: ='Distribution Dashboard'!A79 -> 0 | B75: ='Distribution Dashboard'!B79 -> Amount Billed Water | C75: ='Distribution Dashboard'!C79 -> KES
A76: ='Distribution Dashboard'!A80 -> 0 | B76: ='Distribution Dashboard'!B80 -> Amount Billed Sewer | C76: ='Distribution Dashboard'!C80 -> KES
A77: ='Distribution Dashboard'!A81 -> 0 | B77: ='Distribution Dashboard'!B81 -> KIHOTO | C77: ='Distribution Dashboard'!C81 -> 0
A78: ='Distribution Dashboard'!A82 -> 103 (2) | B78: ='Distribution Dashboard'!B82 -> Volume Water Supplied | C78: ='Distribution Dashboard'!C82 -> m3 | D78: 1575 | E78: 1486 | F78: 1408 | G78: 1670 | H78: 1760 | I78: 1938 | J78: 2877 | K78: 2987 | L78: 2715 | M78: 1898 | N78: 2316 | O78: 2389
A79: ='Distribution Dashboard'!A83 -> 110 (2) | B79: ='Distribution Dashboard'!B83 -> Volume Water Sold | C79: ='Distribution Dashboard'!C83 -> m3 | D79: 2272 | E79: 2080 | F79: 1347 | G79: 1141 | H79: 1693 | I79: 1590 | J79: 2369 | K79: 2241 | L79: 2236 | M79: 1444 | N79: 1437 | O79: 1692
A80: ='Distribution Dashboard'!A84 -> 124 (2) | B80: ='Distribution Dashboard'!B84 -> NRW | C80: ='Distribution Dashboard'!C84 -> % | D80: =(D78-D79)/D78 -> -0.44253968 | E80: =(E78-E79)/E78 -> -0.39973082 | F80: =(F78-F79)/F78 -> 0.043323864 | G80: =(G78-G79)/G78 -> 0.31676647 | H80: =(H78-H79)/H78 -> 0.038068182 | I80: =(I78-I79)/I78 -> 0.17956656 | J80: =(J78-J79)/J78 -> 0.17657282 | K80: =(K78-K79)/K78 -> 0.24974891 | ... O80: =(O78-O79)/O78 -> 0.29175387
A81: ='Distribution Dashboard'!A85 -> 0 | B81: ='Distribution Dashboard'!B85 -> Amount Billed Water | C81: ='Distribution Dashboard'!C85 -> KES
A82: ='Distribution Dashboard'!A86 -> 0 | B82: ='Distribution Dashboard'!B86 -> Amount Billed Sewer | C82: ='Distribution Dashboard'!C86 -> KES
A83: ='Distribution Dashboard'!A87 -> 0 | B83: ='Distribution Dashboard'!B87 -> KAYOLE | C83: ='Distribution Dashboard'!C87 -> 0
A84: ='Distribution Dashboard'!A88 -> 103 (4) | B84: ='Distribution Dashboard'!B88 -> Volume Water Supplied | C84: ='Distribution Dashboard'!C88 -> m3 | D84: 30501 | E84: 32010 | F84: 24149 | G84: 22652 | H84: 28576 | I84: 25660 | J84: 29543 | K84: 32538 | L84: 37911 | M84: 33845 | N84: 24449 | O84: 29654
A85: ='Distribution Dashboard'!A89 -> 110 (4) | B85: ='Distribution Dashboard'!B89 -> Volume Water Sold | C85: ='Distribution Dashboard'!C89 -> m3 | D85: 23539 | E85: 26711 | F85: 15874 | G85: 19300 | H85: 21187 | I85: 19348 | J85: 22923 | K85: 24955 | L85: 28920 | M85: 24631 | N85: 22558 | O85: 22371
A86: ='Distribution Dashboard'!A90 -> 124 (4) | B86: ='Distribution Dashboard'!B90 -> NRW | C86: ='Distribution Dashboard'!C90 -> % | D86: =(D84-D85)/D84 -> 0.22825481 | E86: =(E84-E85)/E84 -> 0.16554202 | F86: =(F84-F85)/F84 -> 0.34266429 | G86: =(G84-G85)/G84 -> 0.1479781 | H86: =(H84-H85)/H84 -> 0.25857363 | I86: =(I84-I85)/I84 -> 0.24598597 | J86: =(J84-J85)/J84 -> 0.22408015 | K86: =(K84-K85)/K84 -> 0.23305059 | ... O86: =(O84-O85)/O84 -> 0.24559924
A87: ='Distribution Dashboard'!A91 -> 0 | B87: ='Distribution Dashboard'!B91 -> Amount Billed Water | C87: ='Distribution Dashboard'!C91 -> KES
A88: ='Distribution Dashboard'!A92 -> 0 | B88: ='Distribution Dashboard'!B92 -> Amount Billed Sewer | C88: ='Distribution Dashboard'!C92 -> KES
A89: ='Distribution Dashboard'!A93 -> 0 | B89: ='Distribution Dashboard'!B93 -> MAI-MAHIU | C89: ='Distribution Dashboard'!C93 -> 0
A90: ='Distribution Dashboard'!A94 -> 103 (5) | B90: ='Distribution Dashboard'!B94 -> Volume Water Supplied | C90: ='Distribution Dashboard'!C94 -> m3 | D90: 4152 | E90: 5337 | F90: 7593 | G90: 8211 | H90: 7525 | I90: 7691 | J90: 13722 | K90: 15989 | L90: 20542 | M90: 15473 | N90: 7152 | O90: 8515
A91: ='Distribution Dashboard'!A95 -> 110 (5) | B91: ='Distribution Dashboard'!B95 -> Volume Water Sold | C91: ='Distribution Dashboard'!C95 -> m3 | D91: 3010 | E91: 4054 | F91: 6482 | G91: 5612 | H91: 4918 | I91: 6474 | J91: 6589 | K91: 8073 | L91: 9560 | M91: 7050 | N91: 3034 | O91: 5452
A92: ='Distribution Dashboard'!A96 -> 124 (5) | B92: ='Distribution Dashboard'!B96 -> NRW | C92: ='Distribution Dashboard'!C96 -> % | D92: =(D90-D91)/D90 -> 0.27504817 | E92: =(E90-E91)/E90 -> 0.24039723 | F92: =(F90-F91)/F90 -> 0.14631898 | G92: =(G90-G91)/G90 -> 0.31652661 | H92: =(H90-H91)/H90 -> 0.34644518 | I92: =(I90-I91)/I90 -> 0.1582369 | J92: =(J90-J91)/J90 -> 0.51982218 | K92: =(K90-K91)/K90 -> 0.49509037 | ... O92: =(O90-O91)/O90 -> 0.35971814
A93: ='Distribution Dashboard'!A97 -> 0 | B93: ='Distribution Dashboard'!B97 -> Amount Billed Water | C93: ='Distribution Dashboard'!C97 -> KES
A94: ='Distribution Dashboard'!A98 -> 0 | B94: ='Distribution Dashboard'!B98 -> Amount Billed Sewer | C94: ='Distribution Dashboard'!C98 -> KES
A95: ='Distribution Dashboard'!A99 -> 0 | B95: ='Distribution Dashboard'!B99 -> KINUNGI | C95: ='Distribution Dashboard'!C99 -> 0
A96: ='Distribution Dashboard'!A100 -> Y | B96: ='Distribution Dashboard'!B100 -> Volume Water Supplied-kinungi | C96: ='Distribution Dashboard'!C100 -> m3 | D96: 331 | E96: 160 | F96: 108 | G96: 137 | H96: 290 | K96: 235
A97: ='Distribution Dashboard'!A101 -> z | B97: ='Distribution Dashboard'!B101 -> Volume Water Sold-kinungi | C97: ='Distribution Dashboard'!C101 -> m3 | D97: 54 | E97: 160 | F97: 87 | G97: 147 | H97: 0 | I97: 373
A98: ='Distribution Dashboard'!A102 -> K | B98: ='Distribution Dashboard'!B102 -> NRW | C98: ='Distribution Dashboard'!C102 -> % | D98: =(D96-D97)/D96 -> 0.83685801 | E98: =(E96-E97)/E96 -> 0 | F98: =(F96-F97)/F96 -> 0.19444444 | G98: =(G96-G97)/G96 -> -0.072992701 | H98: =(H96-H97)/H96 -> 1 | I98: =(I96-I97)/I96 -> #DIV/0! | J98: =(J96-J97)/J96 -> #DIV/0! | K98: =(K96-K97)/K96 -> 1 | ... O98: =(O96-O97)/O96 -> #DIV/0!
A99: ='Distribution Dashboard'!A103 -> 0 | B99: ='Distribution Dashboard'!B103 -> GONDI | C99: ='Distribution Dashboard'!C103 -> 0
A100: ='Distribution Dashboard'!A104 -> Y (2) | B100: ='Distribution Dashboard'!B104 -> Volume Water Supplied-Gondi | C100: ='Distribution Dashboard'!C104 -> m3 | D100: 119 | E100: 105 | F100: 67 | G100: 30 | H100: 551
...

Sheet Actual2122
A1: NAIVAWASS DISTRIBUTION DASHBOARD - NON-REVENUE WATER & ZONAL PERFORMANCE | B1: 0 | C1: 0
A2: 0 | B2: 44713 | C2: 0
A3: 0 | B3: 0 | C3: Monthly
A4: 0 | C4: Unit | D4: jul | E4: aug | F4: sep | G4: oct | H4: nov | I4: dec | J4: jan | K4: feb | L4: mar | M4: apr | N4: may | O4: jun
A5: 0 | B5: DISTRIBUTION SUMMARY | C5: 0
A6: 0 | B6: Volume Water Available For Sale | C6: m3 | D6: 161811 | E6: 162132 | F6: 173274 | G6: 167697 | H6: 169182 | I6: 173312 | J6: 179560 | K6: 183597 | L6: 164840 | M6: 187589 | N6: 162736 | O6: 166867
A7: 0 | B7: Amount Water Billed | C7: m3 | D7: 120266 | E7: 121428 | F7: 122614 | G7: 126272 | H7: 125501 | I7: 122751 | J7: 137132 | K7: 137861 | L7: 122697 | M7: 144656 | N7: 117988 | O7: 116824
A8: 0 | B8: GLOBAL NRW | C8: % | D8: 0.25675016 | E8: 0.2510547 | F8: 0.29236931 | G8: 0.2470229 | H8: 0.25818941 | I8: 0.29173398 | J8: 0.23628871 | K8: 0.24911082 | L8: 0.25566003 | M8: 0.22886736 | N8: 0.27497296 | O8: 0.29989752
A9: 0 | B9: Number of Active water Connections | C9: NO. | D9: 6417 | E9: 6512 | F9: 6581 | G9: 6678 | H9: 6810 | I9: 6908 | J9: 0 | K9: 0 | L9: 0 | M9: 0 | N9: 0 | O9: 0
A10: 0 | B10: Number of Active sewer Connections | C10: NO. | D10: 1503 | E10: 1514 | F10: 1512 | G10: 1525 | H10: 1533 | I10: 1536 | J10: 0 | K10: 0 | L10: 0 | M10: 0 | N10: 0 | O10: 0
A11: 0 | B11: Number of In-active Sewer Connections | C11: NO. | D11: 201 | E11: 197 | F11: 198 | G11: 200 | H11: 205 | I11: 203
A12: 0 | B12: Number of In-active Water Connections | C12: NO. | D12: 1340 | E12: 1355 | F12: 1450 | G12: 1667 | H12: 1723 | I12: 1859
A13: 0 | B13: Number of Connections | C13: NO. | D13: 9461 | E13: 9578 | F13: 9741 | G13: 10070 | H13: 10271 | I13: 10506 | J13: 0 | K13: 0 | L13: 0 | M13: 0 | N13: 0 | O13: 0
A14: 0 | B14: Maintenance, repair and operational cost | C14: KES
A15: REGIONAL PERFORMANCE | B15: 0 | C15: 0
A16: 0 | B16: DTI REGION: CBD,CCCR,KABATI,SITE,KIHOTO | C16: 0
A17: 0 | B17: Volume Water Supplied | C17: m3 | D17: 80561 | E17: 76366 | F17: 86486 | G17: 78872 | H17: 81663 | I17: 80014 | J17: 83536 | K17: 82356 | L17: 71189 | M17: 81107 | N17: 73794 | O17: 74401
A18: 0 | B18: Volume Water Sold | C18: m3 | D18: 59740 | E18: 56625 | F18: 60469 | G18: 59919 | H18: 63505 | I18: 62002 | J18: 64491 | K18: 70882 | L18: 61332 | M18: 64084 | N18: 57552 | O18: 54519
A19: 0 | B19: NRW | C19: m3 | D19: 20821 | E19: 19741 | F19: 26017 | G19: 18953 | H19: 18158 | I19: 18012 | J19: 19045 | K19: 11474 | L19: 9857 | M19: 17023 | N19: 16242 | O19: 19882
A20: 0 | B20: NRW | C20: % | D20: 0.25845012 | E20: 0.25850509 | F20: 0.30082325 | G20: 0.24030074 | H20: 0.22235284 | I20: 0.22511061 | J20: 0.22798554 | K20: 0.13932197 | L20: 0.1384624 | M20: 0.20988324 | N20: 0.2200992 | O20: 0.26722759
A21: 0 | B21: Amount Billed Water | C21: KES | D21: 5302030 | E21: 4887807 | F21: 5455618.3 | G21: 5416695 | H21: 5791785 | I21: 5819845 | J21: 0 | K21: 0 | L21: 0 | M21: 0 | N21: 0 | O21: 0
A22: 0 | B22: Amount Billed Sewer | C22: KES | D22: 3288087.8 | E22: 3201537.7 | F22: 3456698.3 | G22: 3443299.1 | H22: 3601247.1 | I22: 3830623.7 | J22: 0 | K22: 0 | L22: 0 | M22: 0 | N22: 0 | O22: 0
A23: 0 | B23: Number of Active water Connections | C23: KES | D23: 2594 | E23: 2625 | F23: 2639 | G23: 2659 | H23: 2682 | I23: 2696
A24: 0 | B24: Number of Active sewer Connections | C24: KES | D24: 1390 | E24: 1400 | F24: 1398 | G24: 1406 | H24: 1411 | I24: 1413
A25: 0 | B25: KARATI REGION: KAYOLE,KAMERE,HELLSGATE | C25: 0
A26: 0 | B26: Volume Water Supplied | C26: m3 | D26: 81250 | E26: 85766 | F26: 86788 | G26: 88825 | H26: 87519 | I26: 93298 | J26: 96024 | K26: 101241 | L26: 93651 | M26: 106482 | N26: 88942 | O26: 92466
A27: 0 | B27: Volume Water Sold | C27: m3 | D27: 60526 | E27: 64803 | F27: 62145 | G27: 66353 | H27: 61996 | I27: 60749 | J27: 72641 | K27: 66979 | L27: 61365 | M27: 80572 | N27: 60436 | O27: 62305
A28: 0 | B28: NRW | C28: m3 | D28: 20724 | E28: 20963 | F28: 24643 | G28: 22472 | H28: 25523 | I28: 32549 | J28: 23383 | K28: 34262 | L28: 32286 | M28: 25910 | N28: 28506 | O28: 30161
A29: 0 | B29: NRW | C29: % | D29: 0.25506462 | E29: 0.24442087 | F29: 0.28394478 | G29: 0.25299184 | H29: 0.2916281 | I29: 0.34887136 | J29: 0.24351204 | K29: 0.33842021 | L29: 0.34474805 | M29: 0.24332751 | N29: 0.320501 | O29: 0.32618476
A30: 0 | B30: Amount Billed Water | C30: KES | D30: 4538930 | E30: 4741735 | F30: 4534960 | G30: 4906330 | H30: 4642570 | I30: 4437925 | J30: 0 | K30: 0 | L30: 0 | M30: 0 | N30: 0 | O30: 0
A31: 0 | B31: Amount Billed Sewer | C31: KES | D31: 1112109.4 | E31: 1149846 | F31: 1081878.1 | G31: 1101855.1 | H31: 1476121.3 | I31: 517655.25 | J31: 0 | K31: 0 | L31: 0 | M31: 0 | N31: 0 | O31: 0
A32: 0 | B32: Number of Active water Connections | C32: KES | D32: 3823 | E32: 3887 | F32: 3942 | G32: 4019 | H32: 4128 | I32: 4212
A33: 0 | B33: Number of Active sewer Connections | C33: KES | D33: 113 | E33: 114 | F33: 114 | G33: 119 | H33: 122 | I33: 123
A34: 0 | B34: ZONE - CBD | C34: 0
A35: 0 | B35: Volume Water Supplied | C35: m3 | D35: 25464 | E35: 25318 | F35: 29549 | G35: 26589 | H35: 24717 | I35: 23699 | J35: 25215 | K35: 25652 | L35: 23081 | M35: 25654 | N35: 21461 | O35: 27026
A36: 0 | B36: Volume Water Sold | C36: m3 | D36: 14570 | E36: 12703 | F36: 14042 | G36: 14935 | H36: 13880 | I36: 13632 | J36: 12993 | K36: 16261 | L36: 13989 | M36: 15368 | N36: 13743 | O36: 15808
A37: 0 | B37: NRW | C37: % | D37: 0.42781967 | E37: 0.49826211 | F37: 0.52478933 | G37: 0.43830155 | H37: 0.43844318 | I37: 0.42478586 | J37: 0.48471148 | K37: 0.36609231 | L37: 0.39391707 | M37: 0.40095112 | N37: 0.35962909 | O37: 0.41508177
A38: 0 | B38: Amount Billed Water | C38: KES | D38: 1314750 | E38: 1079305 | F38: 1224540 | G38: 1322020 | H38: 1192110 | I38: 1162935
A39: 0 | B39: Amount Billed Sewer | C39: KES | D39: 985045.05 | E39: 1008806.6 | F39: 981659.25 | G39: 989113 | H39: 979101.1 | I39: 952018
A40: 0 | B40: ZONE - CCCR | C40: 0
A41: 0 | B41: Volume Water Supplied | C41: m3 | D41: 23862 | E41: 22279 | F41: 24748 | G41: 24385 | H41: 25884 | I41: 28340 | J41: 30406 | K41: 31153 | L41: 27595 | M41: 27126 | N41: 22554 | O41: 16703
A42: 0 | B42: Volume Water Sold | C42: m3 | D42: 21194 | E42: 20639 | F42: 23153 | G42: 22430 | H42: 26502 | I42: 28276 | J42: 27957 | K42: 30971 | L42: 26244 | M42: 25901 | N42: 21206 | O42: 14455
A43: 0 | B43: NRW | C43: % | D43: 0.11180957 | E43: 0.073611922 | F43: 0.064449652 | G43: 0.080172237 | H43: -0.023875753 | I43: 0.0022582922 | J43: 0.080543314 | K43: 0.005842134 | L43: 0.048958145 | M43: 0.045159625 | N43: 0.059767669 | O43: 0.1345866
A44: 0 | B44: Amount Billed Water | C44: KES | D44: 2294380 | E44: 2205022 | F44: 2591230 | G44: 2498860 | H44: 2990520 | I44: 3255475
A45: 0 | B45: Amount Billed Sewer | C45: KES | D45: 1674527.1 | E45: 1594854.8 | F45: 1881149.4 | G45: 1853744.3 | H45: 2035489.9 | I45: 2328839.6
A46: 0 | B46: ZONE - LAKEVIEW | C46: 0
A47: 0 | B47: Volume Water Supplied | C47: m3 | D47: 31196 | E47: 31516 | F47: 32245 | G47: 30049 | H47: 30407 | I47: 31615 | J47: 33706 | K47: 35148 | L47: 31057 | M47: 33835 | N47: 27524 | O47: 28258
A48: 0 | B48: Volume Water Sold | C48: m3 | D48: 21080 | E48: 23926 | F48: 22037 | G48: 21522 | H48: 19960 | I48: 18923 | J48: 22230 | K48: 21621 | L48: 18992 | M48: 23230 | N48: 18377 | O48: 19259
A49: 0 | B49: NRW | C49: % | D49: 0.32427234 | E49: 0.24083005 | F49: 0.31657621 | G49: 0.28376984 | H49: 0.3435722 | I49: 0.40145501 | J49: 0.34047351 | K49: 0.38485831 | L49: 0.38847925 | M49: 0.31343284 | N49: 0.33232815 | O49: 0.31845849
A50: 0 | B50: Amount Billed Water | C50: KES | D50: 1629340 | E50: 1783915 | F50: 1644820 | G50: 1661950 | H50: 1555545 | I50: 1441085
A51: 0 | B51: Amount Billed Sewer | C51: KES | D51: 1112109.4 | E51: 1149845.6 | F51: 1081878.1 | G51: 1101855.1 | H51: 1473132.6 | I51: 511091.5
A52: 0 | B52: ZONE - KABATI | C52: 0
A53: 0 | B53: Volume Water Supplied | C53: m3 | D53: 16602 | E53: 14522 | F53: 16634 | G53: 16768 | H53: 16744 | I53: 15666 | J53: 16440 | K53: 16501 | L53: 12687 | M53: 16299 | N53: 16975 | O53: 17418
A54: 0 | B54: Volume Water Sold | C54: m3 | D54: 11902 | E54: 11649 | F54: 11670 | G54: 11430 | H54: 11627 | I54: 9817 | J54: 11177 | K54: 11595 | L54: 9134 | M54: 11564 | N54: 11007 | O54: 12306
A55: 0 | B55: NRW | C55: % | D55: 0.28309842 | E55: 0.19783776 | F55: 0.29842491 | G55: 0.31834447 | H55: 0.30560201 | I55: 0.37335631 | J55: 0.32013382 | K55: 0.29731531 | L55: 0.28005045 | M55: 0.29050862 | N55: 0.35157585 | O55: 0.29348949
A56: 0 | B56: Amount Billed | C56: KES | D56: 872970 | E56: 818990 | F56: 826623.3 | G56: 826540 | H56: 813730 | I56: 687405
A57: 0 | B57: Amount Billed Sewer | C57: KES | D57: 293273.2 | E57: 275943.4 | F57: 288160.15 | G57: 300148.85 | H57: 278265.35 | I57: 262541.85
A58: 0 | B58: ZONE - SITE AND SERVICES | C58: 0
A59: 0 | B59: Volume Water Supplied | C59: m3 | D59: 12851 | E59: 12812 | F59: 13598 | G59: 12551 | H59: 12485 | I59: 10672 | J59: 9744 | K59: 7461 | L59: 6621 | M59: 11019 | N59: 11936 | O59: 12065
A60: 0 | B60: Volume Water Sold | C60: m3 | D60: 10380 | E60: 10384 | F60: 9824 | G60: 9575 | H60: 9820 | I60: 8786 | J60: 10516 | K60: 10497 | L60: 10543 | M60: 9624 | N60: 10549 | O60: 10453
A61: 0 | B61: NRW | C61: % | D61: 0.19228076 | E61: 0.18950983 | F61: 0.27754081 | G61: 0.23711258 | H61: 0.21345615 | I61: 0.17672414 | J61: -0.079228243 | K61: -0.40691596 | L61: -0.59235765 | M61: 0.12659951 | N61: 0.11620308 | O61: 0.13360961
A62: 0 | B62: Amount Billed Water | C62: KES | D62: 696955 | E62: 688640 | F62: 678935 | G62: 651830 | H62: 672340 | I62: 603400
A63: 0 | B63: Amount Billed Sewer | C63: KES | D63: 335242.45 | E63: 321932.95 | F63: 305729.5 | G63: 300292.95 | H63: 308390.75 | I63: 287224.2
A64: 0 | B64: ZONE - KAMERE | C64: 0
A65: 0 | B65: Volume Water Supplied | C65: m3 | D65: 7669 | E65: 7071 | F65: 7829 | G65: 7167 | H65: 7534 | I65: 7538 | J65: 7083 | K65: 7404 | L65: 6801 | M65: 8155 | N65: 6378 | O65: 6513
A66: 0 | B66: Volume Water Sold | C66: m3 | D66: 3826 | E66: 5784 | F66: 5973 | G66: 6283 | H66: 6051 | I66: 5901 | J66: 6534 | K66: 6121 | L66: 4679 | M66: 6665 | N66: 5651 | O66: 5352
A67: 0 | B67: NRW | C67: % | D67: 0.50110836 | E67: 0.18201103 | F67: 0.23706731 | G67: 0.1233431 | H67: 0.19684099 | I67: 0.21716636 | J67: 0.07750953 | K67: 0.17328471 | L67: 0.31201294 | M67: 0.18270999 | N67: 0.11398558 | O67: 0.17825887
A68: 0 | B68: Amount Billed Water | C68: KES | D68: 261860 | E68: 419440 | F68: 430630 | G68: 456335 | H68: 441575 | I68: 417925
A69: 0 | B69: Amount Billed Sewer | C69: KES | D69: 0
A70: 0 | B70: ZONE - HELLS GATE | C70: 0
A71: 0 | B71: Volume Water Supplied | C71: m3 | D71: 18217 | E71: 21853 | F71: 22691 | G71: 22445 | H71: 23907 | I71: 25068 | J71: 25169 | K71: 25372 | L71: 24637 | M71: 28867 | N71: 24435 | O71: 27338
A72: 0 | B72: Volume Water Sold | C72: m3 | D72: 15499 | E72: 15491 | F72: 15957 | G72: 17272 | H72: 16979 | I72: 16972 | J72: 20812 | K72: 18533 | L72: 17119 | M72: 23651 | N72: 16398 | O72: 17921
A73: 0 | B73: NRW | C73: % | D73: 0.1492013 | E73: 0.29112708 | F73: 0.29676964 | G73: 0.23047449 | H73: 0.2897896 | I73: 0.32296154 | J73: 0.17310978 | K73: 0.26954911 | L73: 0.30515079 | M73: 0.18069075 | N73: 0.32891344 | O73: 0.34446558
A74: 0 | B74: Amount Billed Water | C74: KES | D74: 1081140 | E74: 1097130 | F74: 1123975 | G74: 1207365 | H74: 1215745 | I74: 1215285
A75: 0 | B75: Amount Billed Sewer | C75: KES | D75: 0
A76: 0 | B76: KIHOTO | C76: 0
A77: 0 | B77: Volume Water Supplied | C77: m3 | D77: 1782 | E77: 1435 | F77: 1957 | G77: 1708 | H77: 1833 | I77: 1637 | J77: 1731 | K77: 1589 | L77: 1205 | M77: 1009 | N77: 868 | O77: 1189
A78: 0 | B78: Volume Water Sold | C78: m3 | D78: 1694 | E78: 1250 | F78: 1780 | G78: 1549 | H78: 1676 | I78: 1491 | J78: 1848 | K78: 1558 | L78: 1422 | M78: 1627 | N78: 1047 | O78: 1497
A79: 0 | B79: NRW | C79: % | D79: 0.049382716 | E79: 0.12891986 | F79: 0.090444558 | G79: 0.093091335 | H79: 0.085651937 | I79: 0.089187538 | J79: -0.067590988 | K79: 0.019509125 | L79: -0.18008299 | M79: -0.61248761 | N79: -0.2062212 | O79: -0.25904121
A80: 0 | B80: Amount Billed Water | C80: KES | D80: 122975 | E80: 95850 | F80: 134290 | G80: 117445 | H80: 123085 | I80: 110630
A81: 0 | B81: Amount Billed Sewer | C81: KES | D81: 0
A82: 0 | B82: KAYOLE | C82: 0
A83: 0 | B83: Volume Water Supplied | C83: m3 | D83: 22745 | E83: 23836 | F83: 20502 | G83: 26353 | H83: 23395 | I83: 26841 | J83: 26869 | K83: 30661 | L83: 28689 | M83: 31224 | N83: 28141 | O83: 27338
A84: 0 | B84: Volume Water Sold | C84: m3 | D84: 19638 | E84: 18845 | F84: 16366 | G84: 20028 | H84: 17507 | I84: 17716 | J84: 20471 | K84: 18921 | L84: 18590 | M84: 23996 | N84: 18450 | O84: 17776
A85: 0 | B85: NRW | C85: % | D85: 0.13660145 | E85: 0.20938916 | F85: 0.20173642 | G85: 0.24001062 | H85: 0.25167771 | I85: 0.33996498 | J85: 0.23811828 | K85: 0.38289684 | L85: 0.35201645 | M85: 0.2314886 | N85: 0.34437298 | O85: 0.34976955
A86: 0 | B86: Amount Billed Water | C86: KES | D86: 1529830 | E86: 1395460 | F86: 1244770 | G86: 1500085 | H86: 1324150 | I86: 1277850
A87: 0 | B87: Amount Billed Sewer | C87: KES | D87: 0 | H87: 2988.75 | I87: 6563.75
A88: 0 | B88: MAI-MAHIU | C88: 0
A89: 0 | B89: Volume Water Supplied | C89: m3 | D89: 1423 | E89: 1490 | F89: 3521 | G89: 2660 | H89: 2276 | I89: 2236 | J89: 3197 | K89: 2656 | L89: 2467 | M89: 4401 | N89: 2464 | O89: 3019
A90: 0 | B90: Volume Water Sold | C90: m3 | D90: 483 | E90: 757 | F90: 1812 | G90: 1248 | H90: 1499 | I90: 1237 | J90: 2594 | K90: 1783 | L90: 1985 | M90: 3030 | N90: 1560 | O90: 1997
A91: 0 | B91: NRW | C91: % | D91: 0.66057625 | E91: 0.49194631 | F91: 0.48537347 | G91: 0.53082707 | H91: 0.3413884 | I91: 0.44677996 | J91: 0.18861433 | K91: 0.32868976 | L91: 0.195379 | M91: 0.31152011 | N91: 0.36688312 | O91: 0.33852269
A92: 0 | B92: Amount Billed Water | C92: KES | D92: 36760 | E92: 45790 | F92: 90765 | G92: 80595 | H92: 105555 | I92: 85780
A93: 0 | B93: Amount Billed Sewer | C93: KES | D93: 0 | E93: 0 | F93: 0
A94: 0 | B94: SOCIAL CONNECTION | C94: 0
A95: 0 | B95: Number of social connections billed | C95: NO. | I95: 3
A96: 0 | B96: Amount billed_social connection | C96: KSH | I96: 16561
A97: 0 | B97: Amount collected_social connection | C97: 0 | I97: 37339
A98: 0 | B98: 0 | C98: 0
A99: 0 | B99: 0 | C99: 0
A100: 0 | B100: 0 | C100: 0
...

Sheet Actual2021
A1: ='Distribution Dashboard'!A1 -> NAIVAWASS DISTRIBUTION DASHBOARD - NON-REVENUE WATER & ZONAL PERFORMANCE | B1: ='Distribution Dashboard'!B1 -> 0 | C1: ='Distribution Dashboard'!D1 -> 0
A2: ='Distribution Dashboard'!A2 -> 0 | B2: ='Distribution Dashboard'!B2 -> 46054 | C2: ='Distribution Dashboard'!D2 -> 0
A3: ='Distribution Dashboard'!A3 -> 0 | B3: ='Distribution Dashboard'!B3 -> 0 | C3: ='Distribution Dashboard'!D3 -> Monthly
A4: ='Distribution Dashboard'!A4 -> 0 | B4: ='Distribution Dashboard'!B4 -> 0 | C4: ='Distribution Dashboard'!C4 -> Unit | D4: jul | E4: aug | F4: sep | G4: oct | H4: nov | I4: dec | J4: jan | K4: feb | L4: mar | M4: apr | N4: may | O4: jun
A5: ='Distribution Dashboard'!A6 -> 0 | B5: ='Distribution Dashboard'!B6 -> REGIONAL NRW | C5: ='Distribution Dashboard'!C6 -> 0
A6: ='Distribution Dashboard'!A7 -> 100 | B6: ='Distribution Dashboard'!B7 -> WATER AVAILABLE FOR SALES- REGIONS | C6: ='Distribution Dashboard'!C7 -> m3 | D6: 154799 | E6: 156773 | F6: 158586 | G6: 169094 | H6: 178584 | I6: 186791 | J6: 189674 | K6: 191956 | L6: 194056 | M6: 195294 | N6: 196008 | O6: 196375
A7: ='Distribution Dashboard'!A8 -> 128a | B7: ='Distribution Dashboard'!B8 -> VOLUME WATER BILLED(CUSTOMERS-M3) | C7: ='Distribution Dashboard'!C8 -> m3 | D7: 105788 | E7: 108793 | F7: 111815 | G7: 115924 | H7: 120033 | I7: 124349 | J7: 128794 | K7: 132694 | L7: 136529 | M7: 139680 | N7: 142505 | O7: 145112
A8: ='Distribution Dashboard'!A9 -> 128 | B8: ='Distribution Dashboard'!B9 -> GLOBAL NRW | C8: ='Distribution Dashboard'!C9 -> %
A9: ='Distribution Dashboard'!A10 -> 0 | B9: ='Distribution Dashboard'!B10 -> Number of Active water Connections | C9: ='Distribution Dashboard'!C10 -> NO.
A10: ='Distribution Dashboard'!A11 -> 0 | B10: ='Distribution Dashboard'!B11 -> Number of Active sewer Connections | C10: ='Distribution Dashboard'!C11 -> NO.
A11: ='Distribution Dashboard'!A12 -> 0 | B11: ='Distribution Dashboard'!B12 -> Number of In-active Sewer Connections | C11: ='Distribution Dashboard'!C12 -> NO.
A12: ='Distribution Dashboard'!A13 -> 0 | B12: ='Distribution Dashboard'!B13 -> Number of In-active Water Connections | C12: ='Distribution Dashboard'!C13 -> NO.
A13: ='Distribution Dashboard'!A14 -> 0 | B13: ='Distribution Dashboard'!B14 -> Number of Connections | C13: ='Distribution Dashboard'!C14 -> NO. | D13: =SUM(D9:D12) -> 0 | E13: =SUM(E9:E12) -> 0 | F13: =SUM(F9:F12) -> 0 | G13: =SUM(G9:G12) -> 0 | H13: =SUM(H9:H12) -> 0 | I13: =SUM(I9:I12) -> 0 | J13: =SUM(J9:J12) -> 0 | K13: =SUM(K9:K12) -> 0 | ... O13: =SUM(O9:O12) -> 0
A14: ='Distribution Dashboard'!A15 -> 0 | B14: ='Distribution Dashboard'!B15 -> Maintenance, repair and operational cost | C14: ='Distribution Dashboard'!C15 -> KES
A15: ='Distribution Dashboard'!#REF! -> #REF! | B15: ='Distribution Dashboard'!#REF! -> #REF! | C15: ='Distribution Dashboard'!#REF! -> #REF!
A16: ='Distribution Dashboard'!A16 -> 0 | B16: ='Distribution Dashboard'!B16 -> CENTRAL REGION: CBD,CCCR,KABATI,SITE,KIHOTO,LAKEVIEW | C16: ='Distribution Dashboard'!C16 -> 0
A17: ='Distribution Dashboard'!A17 -> RA | B17: ='Distribution Dashboard'!B17 -> Volume Water Supplied | C17: ='Distribution Dashboard'!C17 -> m3 | D17: 73720 | E17: 74769 | F17: 75701 | G17: 77457 | H17: 78581 | I17: 79791 | J17: 80865 | K17: 81369 | L17: 81764 | M17: 81446 | N17: 81133 | O17: 80825
A18: ='Distribution Dashboard'!A18 -> RA2 | B18: ='Distribution Dashboard'!B18 -> Volume Water Sold | C18: ='Distribution Dashboard'!C18 -> m3
A19: ='Distribution Dashboard'!A19 -> RA3 | B19: ='Distribution Dashboard'!B19 -> NRW | C19: ='Distribution Dashboard'!C19 -> m3
A20: ='Distribution Dashboard'!A20 -> RA4 | B20: ='Distribution Dashboard'!B20 -> NRW | C20: ='Distribution Dashboard'!C20 -> %
A21: ='Distribution Dashboard'!A21 -> 0 | B21: ='Distribution Dashboard'!B21 -> Amount Billed Water | C21: ='Distribution Dashboard'!C21 -> KES
A22: ='Distribution Dashboard'!A22 -> 0 | B22: ='Distribution Dashboard'!B22 -> Amount Billed Sewer | C22: ='Distribution Dashboard'!C22 -> KES
A23: ='Distribution Dashboard'!A23 -> 0 | B23: ='Distribution Dashboard'!B23 -> Number of Active water Connections | C23: ='Distribution Dashboard'!C23 -> KES
A24: ='Distribution Dashboard'!A24 -> 0 | B24: ='Distribution Dashboard'!B24 -> Number of Active sewer Connections | C24: ='Distribution Dashboard'!C24 -> KES
A25: ='Distribution Dashboard'!A25 -> 0 | B25: ='Distribution Dashboard'!B25 -> SOUTHERN REGION: MAI MAHIU,KAMERE,HELLSGATE | C25: ='Distribution Dashboard'!C25 -> 0
A26: ='Distribution Dashboard'!A26 -> RA6 (B) | B26: ='Distribution Dashboard'!B26 -> Volume Water Supplied | C26: ='Distribution Dashboard'!C26 -> m3
A27: ='Distribution Dashboard'!A27 -> RB2 | B27: ='Distribution Dashboard'!B27 -> Volume Water Sold | C27: ='Distribution Dashboard'!C27 -> m3
A28: ='Distribution Dashboard'!A28 -> RB3 (2) | B28: ='Distribution Dashboard'!B28 -> NRW | C28: ='Distribution Dashboard'!C28 -> m3
A29: ='Distribution Dashboard'!A29 -> RB4 | B29: ='Distribution Dashboard'!B29 -> NRW | C29: ='Distribution Dashboard'!C29 -> %
A30: ='Distribution Dashboard'!#REF! -> #REF! | B30: ='Distribution Dashboard'!#REF! -> #REF! | C30: ='Distribution Dashboard'!#REF! -> #REF!
A31: ='Distribution Dashboard'!#REF! -> #REF! | B31: ='Distribution Dashboard'!#REF! -> #REF! | C31: ='Distribution Dashboard'!#REF! -> #REF!
A32: ='Distribution Dashboard'!#REF! -> #REF! | B32: ='Distribution Dashboard'!#REF! -> #REF! | C32: ='Distribution Dashboard'!#REF! -> #REF!
A33: ='Distribution Dashboard'!#REF! -> #REF! | B33: ='Distribution Dashboard'!#REF! -> #REF! | C33: ='Distribution Dashboard'!#REF! -> #REF!
A34: ='Distribution Dashboard'!A35 -> 0 | B34: ='Distribution Dashboard'!B35 -> ZONE - CBD | C34: ='Distribution Dashboard'!C35 -> 0
A35: ='Distribution Dashboard'!A36 -> 101 | B35: ='Distribution Dashboard'!B36 -> Volume Water Supplied | C35: ='Distribution Dashboard'!C36 -> m3
A36: ='Distribution Dashboard'!A37 -> 108 | B36: ='Distribution Dashboard'!B37 -> Volume Water Sold | C36: ='Distribution Dashboard'!C37 -> m3
A37: ='Distribution Dashboard'!A38 -> 122 | B37: ='Distribution Dashboard'!B38 -> NRW | C37: ='Distribution Dashboard'!C38 -> %
A38: ='Distribution Dashboard'!A39 -> 0 | B38: ='Distribution Dashboard'!B39 -> Amount Billed Water | C38: ='Distribution Dashboard'!C39 -> KES
A39: ='Distribution Dashboard'!A40 -> 0 | B39: ='Distribution Dashboard'!B40 -> Amount Billed Sewer | C39: ='Distribution Dashboard'!C40 -> KES
A40: ='Distribution Dashboard'!A41 -> 0 | B40: ='Distribution Dashboard'!B41 -> ZONE - CCCR | C40: ='Distribution Dashboard'!C41 -> 0
A41: ='Distribution Dashboard'!A42 -> 102 | B41: ='Distribution Dashboard'!B42 -> Volume Water Supplied | C41: ='Distribution Dashboard'!C42 -> m3
A42: ='Distribution Dashboard'!A43 -> 109 | B42: ='Distribution Dashboard'!B43 -> Volume Water Sold | C42: ='Distribution Dashboard'!C43 -> m3
A43: ='Distribution Dashboard'!A44 -> 123 | B43: ='Distribution Dashboard'!B44 -> NRW | C43: ='Distribution Dashboard'!C44 -> %
A44: ='Distribution Dashboard'!A45 -> 0 | B44: ='Distribution Dashboard'!B45 -> Amount Billed Water | C44: ='Distribution Dashboard'!C45 -> KES
A45: ='Distribution Dashboard'!A46 -> 0 | B45: ='Distribution Dashboard'!B46 -> Amount Billed Sewer | C45: ='Distribution Dashboard'!C46 -> KES
... A63: ='Distribution Dashboard'!A64 -> 0 | B63: ='Distribution Dashboard'!B64 -> Amount Billed Sewer | C63: ='Distribution Dashboard'!C64 -> KES
A64: ='Distribution Dashboard'!A69 -> 0 | B64: ='Distribution Dashboard'!B69 -> ZONE - KAMERE | C64: ='Distribution Dashboard'!C69 -> 0
A65: ='Distribution Dashboard'!A70 -> 106 | B65: ='Distribution Dashboard'!B70 -> Volume Water Supplied | C65: ='Distribution Dashboard'!C70 -> m3
A66: ='Distribution Dashboard'!A71 -> 113 | B66: ='Distribution Dashboard'!B71 -> Volume Water Sold | C66: ='Distribution Dashboard'!C71 -> m3
A67: ='Distribution Dashboard'!A72 -> 127 | B67: ='Distribution Dashboard'!B72 -> NRW | C67: ='Distribution Dashboard'!C72 -> %
A68: ='Distribution Dashboard'!A73 -> 0 | B68: ='Distribution Dashboard'!B73 -> Amount Billed Water | C68: ='Distribution Dashboard'!C73 -> KES
A69: ='Distribution Dashboard'!A74 -> 0 | B69: ='Distribution Dashboard'!B74 -> Amount Billed Sewer | C69: ='Distribution Dashboard'!C74 -> KES
A70: ='Distribution Dashboard'!A75 -> 0 | B70: ='Distribution Dashboard'!B75 -> ZONE - HELLS GATE | C70: ='Distribution Dashboard'!C75 -> 0
A71: ='Distribution Dashboard'!A76 -> 103 (3) | B71: ='Distribution Dashboard'!B76 -> Volume Water Supplied | C71: ='Distribution Dashboard'!C76 -> m3
A72: ='Distribution Dashboard'!A77 -> 110 (3) | B72: ='Distribution Dashboard'!B77 -> Volume Water Sold | C72: ='Distribution Dashboard'!C77 -> m3
A73: ='Distribution Dashboard'!A78 -> 124 (3) | B73: ='Distribution Dashboard'!B78 -> NRW | C73: ='Distribution Dashboard'!C78 -> %
A74: ='Distribution Dashboard'!A79 -> 0 | B74: ='Distribution Dashboard'!B79 -> Amount Billed Water | C74: ='Distribution Dashboard'!C79 -> KES
A75: ='Distribution Dashboard'!A80 -> 0 | B75: ='Distribution Dashboard'!B80 -> Amount Billed Sewer | C75: ='Distribution Dashboard'!C80 -> KES
... A94: ='Distribution Dashboard'!A99 -> 0 | B94: ='Distribution Dashboard'!B99 -> KINUNGI | C94: ='Distribution Dashboard'!C99 -> 0
A95: ='Distribution Dashboard'!A116 -> 103 (6) | B95: ='Distribution Dashboard'!#REF! -> #REF! | C95: ='Distribution Dashboard'!#REF! -> #REF!
A96: ='Distribution Dashboard'!A117 -> 110 (6) | B96: ='Distribution Dashboard'!#REF! -> #REF! | C96: ='Distribution Dashboard'!#REF! -> #REF!
A97: ='Distribution Dashboard'!#REF! -> #REF! | B97: ='Distribution Dashboard'!#REF! -> #REF! | C97: ='Distribution Dashboard'!C118 -> %
A98: ='Distribution Dashboard'!A119 -> 0 | B98: ='Distribution Dashboard'!B116 -> Volume Water Supplied | C98: ='Distribution Dashboard'!C119 -> 0
A99: ='Distribution Dashboard'!A120 -> 0 | B99: ='Distribution Dashboard'!B120 -> 0 | C99: ='Distribution Dashboard'!C120 -> 0
A100: ='Distribution Dashboard'!A121 -> 0 | B100: ='Distribution Dashboard'!B121 -> 0 | C100: ='Distribution Dashboard'!C121 -> 0
A101: ='Distribution Dashboard'!A122 -> 0 | B101: ='Distribution Dashboard'!B122 -> 0 | C101: ='Distribution Dashboard'!C122 -> 0
A102: ='Distribution Dashboard'!A123 -> 0 | B102: ='Distribution Dashboard'!B123 -> 0 | C102: ='Distribution Dashboard'!C123 -> 0
A103: ='Distribution Dashboard'!A124 -> 0 | B103: ='Distribution Dashboard'!B124 -> 0 | C103: ='Distribution Dashboard'!C124 -> 0
A104: ='Distribution Dashboard'!A125 -> 0 | B104: ='Distribution Dashboard'!B125 -> 0 | C104: ='Distribution Dashboard'!C125 -> 0
A105: ='Distribution Dashboard'!A126 -> 0 | B105: ='Distribution Dashboard'!B126 -> 0 | C105: ='Distribution Dashboard'!C126 -> 0
A106: ='Distribution Dashboard'!A127 -> 0 | B106: ='Distribution Dashboard'!B127 -> 0 | C106: ='Distribution Dashboard'!C127 -> 0
A107: ='Distribution Dashboard'!A128 -> 0 | B107: ='Distribution Dashboard'!B128 -> 0 | C107: ='Distribution Dashboard'!C128 -> 0
A108: ='Distribution Dashboard'!A129 -> 0 | B108: ='Distribution Dashboard'!B129 -> 0 | C108: ='Distribution Dashboard'!C129 -> 0
A109: ='Distribution Dashboard'!A130 -> 0 | B109: ='Distribution Dashboard'!B130 -> 0 | C109: ='Distribution Dashboard'!C130 -> 0
A110: ='Distribution Dashboard'!A131 -> 0 | B110: ='Distribution Dashboard'!B131 -> 0 | C110: ='Distribution Dashboard'!C131 -> 0
... A158: ='Distribution Dashboard'!A179 -> 0 | B158: ='Distribution Dashboard'!B179 -> 0 | C158: ='Distribution Dashboard'!C179 -> 0

Sheet KPI A(1)
A1: KPI | B1: ='Distribution Dashboard'!#REF! -> #REF! | C1: Volume water available for sale (Production M3) | G1: Actual month: | I1: =INDEX(E18:P18,Actual_month) -> 46054 | L1: Dashboard
A2: Unit | C2: ='Distribution Dashboard'!C36 -> m3
C3: l | J3: Comments
C4: l | R4: actual | S4: =INDEX(E27:P27,Actual_month) -> 1717654
C5: l | R5: target | S5: =INDEX(E26:P26,Actual_month) -> 1776711.4
R6: 0.9 | S6: =+S5*R6 -> 1599040.3
J9: Actions
C18: MONTHLY | E18: 45839 | F18: 45870 | G18: 45901 | H18: 45931 | I18: 45962 | J18: 45992 | K18: 46023 | L18: 46054 | M18: 46082 | N18: 46113 | O18: 46143 | P18: 46174 | Q18: Total
D19: Budget 2025/26 | E19: =Budget2526!D10 -> 214810.57 | F19: =Budget2526!E10 -> 215882.84 | G19: =Budget2526!F10 -> 217038.9 | H19: =Budget2526!G10 -> 220378.23 | I19: =Budget2526!H10 -> 223369.43 | J19: =Budget2526!I10 -> 226152.02 | K19: =Budget2526!J10 -> 228481.92 | L19: =Budget2526!K10 -> 230597.54 | ... P19: =Budget2526!O10 -> 235619.07
D20: Actual 2025/26 | E20: =Actuals2526!D10 -> 203624 | F20: =Actuals2526!E10 -> 229218 | G20: =Actuals2526!F10 -> 194924 | H20: =Actuals2526!G10 -> 247237 | I20: =Actuals2526!H10 -> 181647 | J20: =Actuals2526!I10 -> 180291 | K20: =Actuals2526!J10 -> 258170 | L20: =Actuals2526!K10 -> 222543 | ... P20: =Actuals2526!O10 -> 0
D21: Difference | E21: =IF(E20=0,0,E20-E19) -> -11186.569 | F21: =IF(F20=0,0,F20-F19) -> 13335.163 | G21: =IF(G20=0,0,G20-G19) -> -22114.897 | H21: =IF(H20=0,0,H20-H19) -> 26858.772 | I21: =IF(I20=0,0,I20-I19) -> -41722.427 | J21: =IF(J20=0,0,J20-J19) -> -45861.021 | K21: =IF(K20=0,0,K20-K19) -> 29688.075 | L21: =IF(L20=0,0,L20-L19) -> -8054.5438 | ... P21: =IF(P20=0,0,P20-P19) -> 0
D22: % realisation | E22: =E20/E19 -> 0.94792356 | F22: =F20/F19 -> 1.0617704 | G22: =G20/G19 -> 0.8981063 | H22: =H20/H19 -> 1.1218758 | I22: =I20/I19 -> 0.81321335 | J22: =J20/J19 -> 0.79721154 | K22: =K20/K19 -> 1.1299362 | L22: =L20/L19 -> 0.96507099 | ... P22: =P20/P19 -> 0
D23: Actual 2024/25 | E23: =Actuals2425!D10 -> 199192.12 | F23: =Actuals2425!E10 -> 229211 | G23: =Actuals2425!F10 -> 219157 | H23: =Actuals2425!G10 -> 226434 | I23: =Actuals2425!H10 -> 232327 | J23: =Actuals2425!I10 -> 162567 | K23: =Actuals2425!J10 -> 280545 | L23: =Actuals2425!K10 -> 236218 | ... P23: =Actuals2425!O10 -> 228197
C25: CUMULATIVE | E25: =E18 -> 45839 | F25: =F18 -> 45870 | G25: =G18 -> 45901 | H25: =H18 -> 45931 | I25: =I18 -> 45962 | J25: =J18 -> 45992 | K25: =K18 -> 46023 | L25: =L18 -> 46054 | ... P25: =P18 -> 46174
D26: =D19 -> Budget 2025/26 | E26: =SUM($E19:E19) -> 214810.57 | F26: =SUM($E19:F19) -> 430693.41 | G26: =SUM($E19:G19) -> 647732.3 | H26: =SUM($E19:H19) -> 868110.53 | I26: =SUM($E19:I19) -> 1091480 | J26: =SUM($E19:J19) -> 1317632 | K26: =SUM($E19:K19) -> 1546113.9 | L26: =SUM($E19:L19) -> 1776711.4 | ... P26: =SUM($E19:P19) -> 2712826
D27: =D20 -> Actual 2025/26 | E27: =SUM($E20:E20) -> 203624 | F27: =SUM($E20:F20) -> 432842 | G27: =SUM($E20:G20) -> 627766 | H27: =SUM($E20:H20) -> 875003 | I27: =SUM($E20:I20) -> 1056650 | J27: =SUM($E20:J20) -> 1236941 | K27: =SUM($E20:K20) -> 1495111 | L27: =SUM($E20:L20) -> 1717654 | ... P27: =SUM($E20:P20) -> 1717654
D28: =D21 -> Difference | E28: =IF(E27=0,0,E27-E26) -> -11186.569 | F28: =IF(F27=0,0,F27-F26) -> 2148.5942 | G28: =IF(G27=0,0,G27-G26) -> -19966.303 | H28: =IF(H27=0,0,H27-H26) -> 6892.4694 | I28: =IF(I27=0,0,I27-I26) -> -34829.957 | J28: =IF(J27=0,0,J27-J26) -> -80690.978 | K28: =IF(K27=0,0,K27-K26) -> -51002.903 | L28: =IF(L27=0,0,L27-L26) -> -59057.447 | ... P28: =IF(P27=0,0,P27-P26) -> -995172
D29: =D22 -> % realisation | E29: =E27/E26 -> 0.94792356 | F29: =F27/F26 -> 1.0049887 | G29: =G27/G26 -> 0.96917507 | H29: =H27/H26 -> 1.0079396 | I29: =I27/I26 -> 0.96808924 | J29: =J27/J26 -> 0.93876061 | K29: =K27/K26 -> 0.9670122 | L29: =L27/L26 -> 0.96676025 | ... P29: =P27/P26 -> 0.6331604
D30: =D23 -> Actual 2024/25 | E30: =SUM($E23:E23) -> 199192.12 | F30: =SUM($E23:F23) -> 428403.12 | G30: =SUM($E23:G23) -> 647560.12 | H30: =SUM($E23:H23) -> 873994.12 | I30: =SUM($E23:I23) -> 1106321.1 | J30: =SUM($E23:J23) -> 1268888.1 | K30: =SUM($E23:K23) -> 1549433.1 | L30: =SUM($E23:L23) -> 1785651.1 | ... P30: =SUM($E23:P23) -> 2646138.1

Sheet KPI A
A1: KPI | B1: ='Distribution Dashboard'!#REF! -> #REF! | C1: Volume water available for sale | G1: Actual month: | I1: =INDEX(E18:P18,Actual_month) -> 46054 | L1: Dashboard
A2: Unit | C2: ='Distribution Dashboard'!C36 -> m3
C3: l | J3: Comments
C4: l | R4: actual | S4: =INDEX(E27:P27,Actual_month) -> 1717654
C5: l | R5: target | S5: =INDEX(E26:P26,Actual_month) -> 1776711.4
R6: 0.9 | S6: =+S5*R6 -> 1599040.3
J9: Actions
C18: MONTHLY | E18: 45839 | F18: 45870 | G18: 45901 | H18: 45931 | I18: 45962 | J18: 45992 | K18: 46023 | L18: 46054 | M18: 46082 | N18: 46113 | O18: 46143 | P18: 46174 | Q18: Total
D19: Budget 2025/26 | E19: =Budget2526!D6 -> 214810.57 | F19: =Budget2526!E6 -> 215882.84 | G19: =Budget2526!F6 -> 217038.9 | H19: =Budget2526!G6 -> 220378.23 | I19: =Budget2526!H6 -> 223369.43 | J19: =Budget2526!I6 -> 226152.02 | K19: =Budget2526!J6 -> 228481.92 | L19: =Budget2526!K6 -> 230597.54 | ... P19: =Budget2526!O6 -> 235619.07
D20: Actual 2025/26 | E20: =Actuals2526!D6 -> 203624 | F20: =Actuals2526!E6 -> 229218 | G20: =Actuals2526!F6 -> 194924 | H20: =Actuals2526!G6 -> 247237 | I20: =Actuals2526!H6 -> 181647 | J20: =Actuals2526!I6 -> 180291 | K20: =Actuals2526!J6 -> 258170 | L20: =Actuals2526!K6 -> 222543 | ... P20: =Actuals2526!O6 -> 0
D21: Difference | E21: =IF(E20=0,0,E20-E19) -> -11186.569 | F21: =IF(F20=0,0,F20-F19) -> 13335.163 | G21: =IF(G20=0,0,G20-G19) -> -22114.897 | H21: =IF(H20=0,0,H20-H19) -> 26858.772 | I21: =IF(I20=0,0,I20-I19) -> -41722.427 | J21: =IF(J20=0,0,J20-J19) -> -45861.021 | K21: =IF(K20=0,0,K20-K19) -> 29688.075 | L21: =IF(L20=0,0,L20-L19) -> -8054.5438 | ... P21: =IF(P20=0,0,P20-P19) -> 0
D22: % realisation | E22: =E20/E19 -> 0.94792356 | F22: =F20/F19 -> 1.0617704 | G22: =G20/G19 -> 0.8981063 | H22: =H20/H19 -> 1.1218758 | I22: =I20/I19 -> 0.81321335 | J22: =J20/J19 -> 0.79721154 | K22: =K20/K19 -> 1.1299362 | L22: =L20/L19 -> 0.96507099 | ... P22: =P20/P19 -> 0
D23: Actual 2024/25 | E23: =Actuals2425!D6 -> 199192.12 | F23: =Actuals2425!E6 -> 229211 | G23: =Actuals2425!F6 -> 219157 | H23: =Actuals2425!G6 -> 226434 | I23: =Actuals2425!H6 -> 232327 | J23: =Actuals2425!I6 -> 162567 | K23: =Actuals2425!J6 -> 280545 | L23: =Actuals2425!K6 -> 236218 | ... P23: =Actuals2425!O6 -> 228197
C25: CUMULATIVE | E25: =E18 -> 45839 | F25: =F18 -> 45870 | G25: =G18 -> 45901 | H25: =H18 -> 45931 | I25: =I18 -> 45962 | J25: =J18 -> 45992 | K25: =K18 -> 46023 | L25: =L18 -> 46054 | ... P25: =P18 -> 46174
D26: =D19 -> Budget 2025/26 | E26: =SUM($E19:E19) -> 214810.57 | F26: =SUM($E19:F19) -> 430693.41 | G26: =SUM($E19:G19) -> 647732.3 | H26: =SUM($E19:H19) -> 868110.53 | I26: =SUM($E19:I19) -> 1091480 | J26: =SUM($E19:J19) -> 1317632 | K26: =SUM($E19:K19) -> 1546113.9 | L26: =SUM($E19:L19) -> 1776711.4 | ... P26: =SUM($E19:P19) -> 2712826
D27: =D20 -> Actual 2025/26 | E27: =SUM($E20:E20) -> 203624 | F27: =SUM($E20:F20) -> 432842 | G27: =SUM($E20:G20) -> 627766 | H27: =SUM($E20:H20) -> 875003 | I27: =SUM($E20:I20) -> 1056650 | J27: =SUM($E20:J20) -> 1236941 | K27: =SUM($E20:K20) -> 1495111 | L27: =SUM($E20:L20) -> 1717654 | ... P27: =SUM($E20:P20) -> 1717654
D28: =D21 -> Difference | E28: =IF(E27=0,0,E27-E26) -> -11186.569 | F28: =IF(F27=0,0,F27-F26) -> 2148.5942 | G28: =IF(G27=0,0,G27-G26) -> -19966.303 | H28: =IF(H27=0,0,H27-H26) -> 6892.4694 | I28: =IF(I27=0,0,I27-I26) -> -34829.957 | J28: =IF(J27=0,0,J27-J26) -> -80690.978 | K28: =IF(K27=0,0,K27-K26) -> -51002.903 | L28: =IF(L27=0,0,L27-L26) -> -59057.447 | ... P28: =IF(P27=0,0,P27-P26) -> -995172
D29: =D22 -> % realisation | E29: =E27/E26 -> 0.94792356 | F29: =F27/F26 -> 1.0049887 | G29: =G27/G26 -> 0.96917507 | H29: =H27/H26 -> 1.0079396 | I29: =I27/I26 -> 0.96808924 | J29: =J27/J26 -> 0.93876061 | K29: =K27/K26 -> 0.9670122 | L29: =L27/L26 -> 0.96676025 | ... P29: =P27/P26 -> 0.6331604
D30: =D23 -> Actual 2024/25 | E30: =SUM($E23:E23) -> 199192.12 | F30: =SUM($E23:F23) -> 428403.12 | G30: =SUM($E23:G23) -> 647560.12 | H30: =SUM($E23:H23) -> 873994.12 | I30: =SUM($E23:I23) -> 1106321.1 | J30: =SUM($E23:J23) -> 1268888.1 | K30: =SUM($E23:K23) -> 1549433.1 | L30: =SUM($E23:L23) -> 1785651.1 | ... P30: =SUM($E23:P23) -> 2646138.1

Sheet KPI 100
A1: KPI | B1: 100 | C1: Volume water available for sale | G1: Actual month: | I1: =INDEX(E18:P18,Actual_month) -> 46054 | L1: Dashboard
A2: Unit | C2: ='Distribution Dashboard'!C36 -> m3
C3: l | J3: Comments
C4: l | R4: actual | S4: =INDEX(E27:P27,Actual_month) -> 1717654
C5: l | R5: target | S5: =INDEX(E26:P26,Actual_month) -> 1776711.4
R6: 0.9 | S6: =+S5*R6 -> 1599040.3
J9: Actions
C18: MONTHLY | E18: 45839 | F18: 45870 | G18: 45901 | H18: 45931 | I18: 45962 | J18: 45992 | K18: 46023 | L18: 46054 | M18: 46082 | N18: 46113 | O18: 46143 | P18: 46174 | Q18: Total
D19: Budget 2025/26 | E19: =Budget2526!D15 -> 214810.57 | F19: =Budget2526!E15 -> 215882.84 | G19: =Budget2526!F15 -> 217038.9 | H19: =Budget2526!G15 -> 220378.23 | I19: =Budget2526!H15 -> 223369.43 | J19: =Budget2526!I15 -> 226152.02 | K19: =Budget2526!J15 -> 228481.92 | L19: =Budget2526!K15 -> 230597.54 | ... P19: =Budget2526!O15 -> 235619.07
D20: Actual 2025/26 | E20: =Actuals2526!D15 -> 203624 | F20: =Actuals2526!E15 -> 229218 | G20: =Actuals2526!F15 -> 194924 | H20: =Actuals2526!G15 -> 247237 | I20: =Actuals2526!H15 -> 181647 | J20: =Actuals2526!I15 -> 180291 | K20: =Actuals2526!J15 -> 258170 | L20: =Actuals2526!K15 -> 222543 | ... P20: =Actuals2526!O15 -> 0
D21: Difference | E21: =IF(E20=0,0,E20-E19) -> -11186.569 | F21: =IF(F20=0,0,F20-F19) -> 13335.163 | G21: =IF(G20=0,0,G20-G19) -> -22114.897 | H21: =IF(H20=0,0,H20-H19) -> 26858.772 | I21: =IF(I20=0,0,I20-I19) -> -41722.427 | J21: =IF(J20=0,0,J20-J19) -> -45861.021 | K21: =IF(K20=0,0,K20-K19) -> 29688.075 | L21: =IF(L20=0,0,L20-L19) -> -8054.5438 | ... P21: =IF(P20=0,0,P20-P19) -> 0
D22: % realisation | E22: =E20/E19 -> 0.94792356 | F22: =F20/F19 -> 1.0617704 | G22: =G20/G19 -> 0.8981063 | H22: =H20/H19 -> 1.1218758 | I22: =I20/I19 -> 0.81321335 | J22: =J20/J19 -> 0.79721154 | K22: =K20/K19 -> 1.1299362 | L22: =L20/L19 -> 0.96507099 | ... P22: =P20/P19 -> 0
D23: Actual 2024/25 | E23: =Actuals2425!D15 -> 179812 | F23: =Actuals2425!E15 -> 218591 | G23: =Actuals2425!F15 -> 206801 | H23: =Actuals2425!G15 -> 217593 | I23: =Actuals2425!H15 -> 230368 | J23: =Actuals2425!I15 -> 151401 | K23: =Actuals2425!J15 -> 267445 | L23: =Actuals2425!K15 -> 216809 | ... Q23: =Actuals2425!P15 -> 0
C25: CUMULATIVE | E25: =E18 -> 45839 | F25: =F18 -> 45870 | G25: =G18 -> 45901 | H25: =H18 -> 45931 | I25: =I18 -> 45962 | J25: =J18 -> 45992 | K25: =K18 -> 46023 | L25: =L18 -> 46054 | ... P25: =P18 -> 46174
D26: =D19 -> Budget 2025/26 | E26: =SUM($E19:E19) -> 214810.57 | F26: =SUM($E19:F19) -> 430693.41 | G26: =SUM($E19:G19) -> 647732.3 | H26: =SUM($E19:H19) -> 868110.53 | I26: =SUM($E19:I19) -> 1091480 | J26: =SUM($E19:J19) -> 1317632 | K26: =SUM($E19:K19) -> 1546113.9 | L26: =SUM($E19:L19) -> 1776711.4 | ... P26: =SUM($E19:P19) -> 2712826
D27: =D20 -> Actual 2025/26 | E27: =SUM($E20:E20) -> 203624 | F27: =SUM($E20:F20) -> 432842 | G27: =SUM($E20:G20) -> 627766 | H27: =SUM($E20:H20) -> 875003 | I27: =SUM($E20:I20) -> 1056650 | J27: =SUM($E20:J20) -> 1236941 | K27: =SUM($E20:K20) -> 1495111 | L27: =SUM($E20:L20) -> 1717654 | ... P27: =SUM($E20:P20) -> 1717654
D28: =D21 -> Difference | E28: =IF(E27=0,0,E27-E26) -> -11186.569 | F28: =IF(F27=0,0,F27-F26) -> 2148.5942 | G28: =IF(G27=0,0,G27-G26) -> -19966.303 | H28: =IF(H27=0,0,H27-H26) -> 6892.4694 | I28: =IF(I27=0,0,I27-I26) -> -34829.957 | J28: =IF(J27=0,0,J27-J26) -> -80690.978 | K28: =IF(K27=0,0,K27-K26) -> -51002.903 | L28: =IF(L27=0,0,L27-L26) -> -59057.447 | ... P28: =IF(P27=0,0,P27-P26) -> -995172
D29: =D22 -> % realisation | E29: =E27/E26 -> 0.94792356 | F29: =F27/F26 -> 1.0049887 | G29: =G27/G26 -> 0.96917507 | H29: =H27/H26 -> 1.0079396 | I29: =I27/I26 -> 0.96808924 | J29: =J27/J26 -> 0.93876061 | K29: =K27/K26 -> 0.9670122 | L29: =L27/L26 -> 0.96676025 | ... P29: =P27/P26 -> 0.6331604
D30: =D23 -> Actual 2024/25 | E30: =SUM($E23:E23) -> 179812 | F30: =SUM($E23:F23) -> 398403 | G30: =SUM($E23:G23) -> 605204 | H30: =SUM($E23:H23) -> 822797 | I30: =SUM($E23:I23) -> 1053165 | J30: =SUM($E23:J23) -> 1204566 | K30: =SUM($E23:K23) -> 1472011 | L30: =SUM($E23:L23) -> 1688820 | ... P30: =SUM($E23:P23) -> 2526351

Sheet KPI B(2)
A1: KPI | B1: ='Distribution Dashboard'!#REF! -> #REF! | C1: Water Available for Sale Regions | G1: Actual month: | I1: =INDEX(E$18:P$18,Actual_month) -> 46054 | L1: Dashboard
A2: Unit | C2: m3
C3: l | J3: Comments
C4: l | J4: Actual Billing 86,843. Prisosns over estimation | R4: actual | S4: =INDEX(E27:P27,Actual_month) -> 1717654
C5: l | R5: target | S5: =INDEX(E26:P26,Actual_month) -> 1776711.4
R6: 0.9 | S6: =+S5*R6 -> 1599040.3
J9: Actions
C18: MONTHLY | E18: ='KPI 100'!E18 -> 45839 | F18: ='KPI 100'!F18 -> 45870 | G18: ='KPI 100'!G18 -> 45901 | H18: ='KPI 100'!H18 -> 45931 | I18: ='KPI 100'!I18 -> 45962 | J18: ='KPI 100'!J18 -> 45992 | K18: ='KPI 100'!K18 -> 46023 | L18: ='KPI 100'!L18 -> 46054 | ... P18: ='KPI 100'!P18 -> 46174 | Q18: Total
D19: ='KPI 100'!D19 -> Budget 2025/26 | E19: =Budget2526!D11 -> 214810.57 | F19: =Budget2526!E11 -> 215882.84 | G19: =Budget2526!F11 -> 217038.9 | H19: =Budget2526!G11 -> 220378.23 | I19: =Budget2526!H11 -> 223369.43 | J19: =Budget2526!I11 -> 226152.02 | K19: =Budget2526!J11 -> 228481.92 | L19: =Budget2526!K11 -> 230597.54 | ... P19: =Budget2526!O11 -> 235619.07
D20: ='KPI 100'!D20 -> Actual 2025/26 | E20: =Actuals2526!D11 -> 203624 | F20: =Actuals2526!E11 -> 229218 | G20: =Actuals2526!F11 -> 194924 | H20: =Actuals2526!G11 -> 247237 | I20: =Actuals2526!H11 -> 181647 | J20: =Actuals2526!I11 -> 180291 | K20: =Actuals2526!J11 -> 258170 | L20: =Actuals2526!K11 -> 222543 | ... P20: =Actuals2526!O11 -> 0
D21: ='KPI 100'!D21 -> Difference | E21: =IF(E20=0,0,E20-E19) -> -11186.569 | F21: =IF(F20=0,0,F20-F19) -> 13335.163 | G21: =IF(G20=0,0,G20-G19) -> -22114.897 | H21: =IF(H20=0,0,H20-H19) -> 26858.772 | I21: =IF(I20=0,0,I20-I19) -> -41722.427 | J21: =IF(J20=0,0,J20-J19) -> -45861.021 | K21: =IF(K20=0,0,K20-K19) -> 29688.075 | L21: =IF(L20=0,0,L20-L19) -> -8054.5438 | ... P21: =IF(P20=0,0,P20-P19) -> 0
D22: ='KPI 100'!D22 -> % realisation | E22: =E20/E19 -> 0.94792356 | F22: =F20/F19 -> 1.0617704 | G22: =G20/G19 -> 0.8981063 | H22: =H20/H19 -> 1.1218758 | I22: =I20/I19 -> 0.81321335 | J22: =J20/J19 -> 0.79721154 | K22: =K20/K19 -> 1.1299362 | L22: =L20/L19 -> 0.96507099 | ... P22: =P20/P19 -> 0
D23: ='KPI 100'!D23 -> Actual 2024/25 | E23: =Actuals2425!D11 -> 179812 | F23: =Actuals2425!E11 -> 218591 | G23: =Actuals2425!F11 -> 206801 | H23: =Actuals2425!G11 -> 217593 | I23: =Actuals2425!H11 -> 230368 | J23: =Actuals2425!I11 -> 151401 | K23: =Actuals2425!J11 -> 267445 | L23: =Actuals2425!K11 -> 216809 | ... P23: =Actuals2425!O11 -> 224235
C25: CUMULATIVE | E25: =E18 -> 45839 | F25: =F18 -> 45870 | G25: =G18 -> 45901 | H25: =H18 -> 45931 | I25: =I18 -> 45962 | J25: =J18 -> 45992 | K25: =K18 -> 46023 | L25: =L18 -> 46054 | ... P25: =P18 -> 46174
D26: =D19 -> Budget 2025/26 | E26: =SUM($E19:E19) -> 214810.57 | F26: =SUM($E19:F19) -> 430693.41 | G26: =SUM($E19:G19) -> 647732.3 | H26: =SUM($E19:H19) -> 868110.53 | I26: =SUM($E19:I19) -> 1091480 | J26: =SUM($E19:J19) -> 1317632 | K26: =SUM($E19:K19) -> 1546113.9 | L26: =SUM($E19:L19) -> 1776711.4 | ... P26: =SUM($E19:P19) -> 2712826
D27: =D20 -> Actual 2025/26 | E27: =SUM($E20:E20) -> 203624 | F27: =SUM($E20:F20) -> 432842 | G27: =SUM($E20:G20) -> 627766 | H27: =SUM($E20:H20) -> 875003 | I27: =SUM($E20:I20) -> 1056650 | J27: =SUM($E20:J20) -> 1236941 | K27: =SUM($E20:K20) -> 1495111 | L27: =SUM($E20:L20) -> 1717654 | ... P27: =SUM($E20:P20) -> 1717654
D28: =D21 -> Difference | E28: =IF(E27=0,0,E27-E26) -> -11186.569 | F28: =IF(F27=0,0,F27-F26) -> 2148.5942 | G28: =IF(G27=0,0,G27-G26) -> -19966.303 | H28: =IF(H27=0,0,H27-H26) -> 6892.4694 | I28: =IF(I27=0,0,I27-I26) -> -34829.957 | J28: =IF(J27=0,0,J27-J26) -> -80690.978 | K28: =IF(K27=0,0,K27-K26) -> -51002.903 | L28: =IF(L27=0,0,L27-L26) -> -59057.447 | ... P28: =IF(P27=0,0,P27-P26) -> -995172
D29: =D22 -> % realisation | E29: =E27/E26 -> 0.94792356 | F29: =F27/F26 -> 1.0049887 | G29: =G27/G26 -> 0.96917507 | H29: =H27/H26 -> 1.0079396 | I29: =I27/I26 -> 0.96808924 | J29: =J27/J26 -> 0.93876061 | K29: =K27/K26 -> 0.9670122 | L29: =L27/L26 -> 0.96676025 | ... P29: =P27/P26 -> 0.6331604
D30: =D23 -> Actual 2024/25 | E30: =SUM($E23:E23) -> 179812 | F30: =SUM($E23:F23) -> 398403 | G30: =SUM($E23:G23) -> 605204 | H30: =SUM($E23:H23) -> 822797 | I30: =SUM($E23:I23) -> 1053165 | J30: =SUM($E23:J23) -> 1204566 | K30: =SUM($E23:K23) -> 1472011 | L30: =SUM($E23:L23) -> 1688820 | ... P30: =SUM($E23:P23) -> 2526351

Sheet KPI B
A1: KPI | B1: ='Distribution Dashboard'!#REF! -> #REF! | C1: Volume Water Billed | G1: Actual month: | I1: =INDEX(E$18:P$18,Actual_month) -> 46054 | L1: Dashboard
A2: Unit | C2: m3
C3: l | J3: Comments
C4: l | R4: actual | S4: =INDEX(E27:P27,Actual_month) -> 1275843
C5: l | R5: target | S5: =INDEX(E26:P26,Actual_month) -> 1382493.7
R6: 0.9 | S6: =+S5*R6 -> 1244244.3
J9: Actions
C18: MONTHLY | E18: ='KPI 100'!E18 -> 45839 | F18: ='KPI 100'!F18 -> 45870 | G18: ='KPI 100'!G18 -> 45901 | H18: ='KPI 100'!H18 -> 45931 | I18: ='KPI 100'!I18 -> 45962 | J18: ='KPI 100'!J18 -> 45992 | K18: ='KPI 100'!K18 -> 46023 | L18: ='KPI 100'!L18 -> 46054 | ... P18: ='KPI 100'!P18 -> 46174 | Q18: Total
D19: ='KPI 100'!D19 -> Budget 2025/26 | E19: =Budget2526!D7 -> 162967.74 | F19: =Budget2526!E7 -> 164996.23 | G19: =Budget2526!F7 -> 167133.61 | H19: =Budget2526!G7 -> 170794.25 | I19: =Budget2526!H7 -> 174251.4 | J19: =Budget2526!I7 -> 177638.11 | K19: =Budget2526!J7 -> 180823.44 | L19: =Budget2526!K7 -> 183888.91 | ... P19: =Budget2526!O7 -> 194059.96
D20: ='KPI 100'!D20 -> Actual 2025/26 | E20: =Actuals2526!D7 -> 146435 | F20: =Actuals2526!E7 -> 173295 | G20: =Actuals2526!F7 -> 145984 | H20: =Actuals2526!G7 -> 171125 | I20: =Actuals2526!H7 -> 135132 | J20: =Actuals2526!I7 -> 131036 | K20: =Actuals2526!J7 -> 200570 | L20: =Actuals2526!K7 -> 172266 | ... P20: =Actuals2526!O7 -> 0
D21: ='KPI 100'!D21 -> Difference | E21: =IF(E20=0,0,E20-E19) -> -16532.744 | F21: =IF(F20=0,0,F20-F19) -> 8298.7724 | G21: =IF(G20=0,0,G20-G19) -> -21149.612 | H21: =IF(H20=0,0,H20-H19) -> 330.75245 | I21: =IF(I20=0,0,I20-I19) -> -39119.402 | J21: =IF(J20=0,0,J20-J19) -> -46602.111 | K21: =IF(K20=0,0,K20-K19) -> 19746.561 | L21: =IF(L20=0,0,L20-L19) -> -11622.913 | ... P21: =IF(P20=0,0,P20-P19) -> 0
D22: ='KPI 100'!D22 -> % realisation | E22: =E20/E19 -> 0.89855205 | F22: =F20/F19 -> 1.0502967 | G22: =G20/G19 -> 0.87345686 | H22: =H20/H19 -> 1.0019366 | I22: =I20/I19 -> 0.77550022 | J22: =J20/J19 -> 0.73765702 | K22: =K20/K19 -> 1.1092035 | L22: =L20/L19 -> 0.93679384 | ... P22: =P20/P19 -> 0
D23: ='KPI 100'!D23 -> Actual 2024/25 | E23: =Actuals2425!D7 -> 141416 | F23: =Actuals2425!E7 -> 168508 | G23: =Actuals2425!F7 -> 163668 | H23: =Actuals2425!G7 -> 160893 | I23: =Actuals2425!H7 -> 179892 | J23: =Actuals2425!I7 -> 116560 | K23: =Actuals2425!J7 -> 184451 | L23: =Actuals2425!K7 -> 165475 | ... P23: =Actuals2425!O7 -> 164911
C25: CUMULATIVE | E25: =E18 -> 45839 | F25: =F18 -> 45870 | G25: =G18 -> 45901 | H25: =H18 -> 45931 | I25: =I18 -> 45962 | J25: =J18 -> 45992 | K25: =K18 -> 46023 | L25: =L18 -> 46054 | ... P25: =P18 -> 46174
D26: =D19 -> Budget 2025/26 | E26: =SUM($E19:E19) -> 162967.74 | F26: =SUM($E19:F19) -> 327963.97 | G26: =SUM($E19:G19) -> 495097.58 | H26: =SUM($E19:H19) -> 665891.83 | I26: =SUM($E19:I19) -> 840143.23 | J26: =SUM($E19:J19) -> 1017781.3 | K26: =SUM($E19:K19) -> 1198604.8 | L26: =SUM($E19:L19) -> 1382493.7 | ... P26: =SUM($E19:P19) -> 2144172.5
D27: =D20 -> Actual 2025/26 | E27: =SUM($E20:E20) -> 146435 | F27: =SUM($E20:F20) -> 319730 | G27: =SUM($E20:G20) -> 465714 | H27: =SUM($E20:H20) -> 636839 | I27: =SUM($E20:I20) -> 771971 | J27: =SUM($E20:J20) -> 903007 | K27: =SUM($E20:K20) -> 1103577 | L27: =SUM($E20:L20) -> 1275843 | ... P27: =SUM($E20:P20) -> 1275843
D28: =D21 -> Difference | E28: =IF(E27=0,0,E27-E26) -> -16532.744 | F28: =IF(F27=0,0,F27-F26) -> -8233.9719 | G28: =IF(G27=0,0,G27-G26) -> -29383.584 | H28: =IF(H27=0,0,H27-H26) -> -29052.832 | I28: =IF(I27=0,0,I27-I26) -> -68172.233 | J28: =IF(J27=0,0,J27-J26) -> -114774.34 | K28: =IF(K27=0,0,K27-K26) -> -95027.784 | L28: =IF(L27=0,0,L27-L26) -> -106650.7 | ... P28: =IF(P27=0,0,P27-P26) -> -868329.48
D29: =D22 -> % realisation | E29: =E27/E26 -> 0.89855205 | F29: =F27/F26 -> 0.97489367 | G29: =G27/G26 -> 0.94065092 | H29: =H27/H26 -> 0.95637004 | I29: =I27/I26 -> 0.91885642 | J29: =J27/J26 -> 0.88723084 | K29: =K27/K26 -> 0.920718 | L29: =L27/L26 -> 0.92285629 | ... P29: =P27/P26 -> 0.59502816
D30: =D23 -> Actual 2024/25 | E30: =SUM($E23:E23) -> 141416 | F30: =SUM($E23:F23) -> 309924 | G30: =SUM($E23:G23) -> 473592 | H30: =SUM($E23:H23) -> 634485 | I30: =SUM($E23:I23) -> 814377 | J30: =SUM($E23:J23) -> 930937 | K30: =SUM($E23:K23) -> 1115388 | L30: =SUM($E23:L23) -> 1280863 | ... P30: =SUM($E23:P23) -> 1910955

Sheet KPI 128a
A1: KPI | B1: 128a | C1: Volume Water Billed | G1: Actual month: | I1: =INDEX(E$18:P$18,Actual_month) -> 46054 | L1: Dashboard
A2: Unit | C2: m3
C3: l | J3: Comments
C4: l | J4: Actual Billing 86,843. Prisosns over estimation | R4: actual | S4: =INDEX(E27:P27,Actual_month) -> 1275843
C5: l | R5: target | S5: =INDEX(E26:P26,Actual_month) -> 1382493.7
R6: 0.9 | S6: =+S5*R6 -> 1244244.3
J9: Actions
C18: MONTHLY | E18: ='KPI 100'!E18 -> 45839 | F18: ='KPI 100'!F18 -> 45870 | G18: ='KPI 100'!G18 -> 45901 | H18: ='KPI 100'!H18 -> 45931 | I18: ='KPI 100'!I18 -> 45962 | J18: ='KPI 100'!J18 -> 45992 | K18: ='KPI 100'!K18 -> 46023 | L18: ='KPI 100'!L18 -> 46054 | ... P18: ='KPI 100'!P18 -> 46174 | Q18: Total
D19: ='KPI 100'!D19 -> Budget 2025/26 | E19: =Budget2526!D16 -> 162967.74 | F19: =Budget2526!E16 -> 164996.23 | G19: =Budget2526!F16 -> 167133.61 | H19: =Budget2526!G16 -> 170794.25 | I19: =Budget2526!H16 -> 174251.4 | J19: =Budget2526!I16 -> 177638.11 | K19: =Budget2526!J16 -> 180823.44 | L19: =Budget2526!K16 -> 183888.91 | ... P19: =Budget2526!O16 -> 194059.96
D20: ='KPI 100'!D20 -> Actual 2025/26 | E20: =Actuals2526!D16 -> 146435 | F20: =Actuals2526!E16 -> 173295 | G20: =Actuals2526!F16 -> 145984 | H20: =Actuals2526!G16 -> 171125 | I20: =Actuals2526!H16 -> 135132 | J20: =Actuals2526!I16 -> 131036 | K20: =Actuals2526!J16 -> 200570 | L20: =Actuals2526!K16 -> 172266 | ... P20: =Actuals2526!O16 -> 0
D21: ='KPI 100'!D21 -> Difference | E21: =IF(E20=0,0,E20-E19) -> -16532.744 | F21: =IF(F20=0,0,F20-F19) -> 8298.7724 | G21: =IF(G20=0,0,G20-G19) -> -21149.612 | H21: =IF(H20=0,0,H20-H19) -> 330.75245 | I21: =IF(I20=0,0,I20-I19) -> -39119.402 | J21: =IF(J20=0,0,J20-J19) -> -46602.111 | K21: =IF(K20=0,0,K20-K19) -> 19746.561 | L21: =IF(L20=0,0,L20-L19) -> -11622.913 | ... P21: =IF(P20=0,0,P20-P19) -> 0
D22: ='KPI 100'!D22 -> % realisation | E22: =E20/E19 -> 0.89855205 | F22: =F20/F19 -> 1.0502967 | G22: =G20/G19 -> 0.87345686 | H22: =H20/H19 -> 1.0019366 | I22: =I20/I19 -> 0.77550022 | J22: =J20/J19 -> 0.73765702 | K22: =K20/K19 -> 1.1092035 | L22: =L20/L19 -> 0.93679384 | ... P22: =P20/P19 -> 0
D23: ='KPI 100'!D23 -> Actual 2024/25 | E23: =Actuals2425!D16 -> 141416 | F23: =Actuals2425!E16 -> 168508 | G23: =Actuals2425!F16 -> 163668 | H23: =Actuals2425!G16 -> 160893 | I23: =Actuals2425!H16 -> 179892 | J23: =Actuals2425!I16 -> 116560 | K23: =Actuals2425!J16 -> 184451 | L23: =Actuals2425!K16 -> 165475 | ... P23: =Actuals2425!O16 -> 164911
C25: CUMULATIVE | E25: =E18 -> 45839 | F25: =F18 -> 45870 | G25: =G18 -> 45901 | H25: =H18 -> 45931 | I25: =I18 -> 45962 | J25: =J18 -> 45992 | K25: =K18 -> 46023 | L25: =L18 -> 46054 | ... P25: =P18 -> 46174
D26: =D19 -> Budget 2025/26 | E26: =SUM($E19:E19) -> 162967.74 | F26: =SUM($E19:F19) -> 327963.97 | G26: =SUM($E19:G19) -> 495097.58 | H26: =SUM($E19:H19) -> 665891.83 | I26: =SUM($E19:I19) -> 840143.23 | J26: =SUM($E19:J19) -> 1017781.3 | K26: =SUM($E19:K19) -> 1198604.8 | L26: =SUM($E19:L19) -> 1382493.7 | ... P26: =SUM($E19:P19) -> 2144172.5
