Workbook
Name Actual_month: General!$B$3

Sheet Dashboard
A1: FINANCE DASHBOARD
B2: =INDEX('KPI 1'!$E18:$P18,Actual_month) -> 46082
D3: Monthly | J3: Cumulative | R3: 0.9
C4: Unit | G4: Target | H4: Actual | I4: % real. | M4: Target | N4: Actual | O4: % real.
A5: BILLING DASHBOARD - SUMMARY | Q5: monthly | R5: cumluative
A6: 1 | B6: Total Water Sales (Ksh) | C6: Ksh | D6: l | E6: l | F6: l | G6: =IFERROR(INDEX('KPI 1'!E$19:P$19,Actual_month),) -> 18825128 | H6: =IFERROR(INDEX('KPI 1'!$E$20:$P$20,Actual_month),) -> 18351480 | I6: =IFERROR(H6/G6,"") -> 0.9748396 | J6: l | K6: l | L6: l | M6: =IFERROR(INDEX('KPI 1'!$E$26:$P$26,Actual_month),) -> 161020690 | N6: =IFERROR(INDEX('KPI 1'!$E$27:$P$27,Actual_month),) -> 179809530 | O6: =IFERROR(N6/M6,"") -> 1.1166859 | P6: details | Q6: =G6*$R$3 -> 16942615 | R6: =M6*$R$3 -> 144918621 | S6: H | T6: v
A7: 2 | B7: Total Sewerage Sales (Ksh) | C7: Ksh | D7: l | E7: l | F7: l | G7: =IFERROR(INDEX('KPI 2'!E$19:P$19,Actual_month),) -> 5264966.7 | H7: =IFERROR(INDEX('KPI 2'!$E$20:$P$20,Actual_month),) -> 5950166 | I7: =IFERROR(H7/G7,"") -> 1.1301431 | J7: l | K7: l | L7: l | M7: =IFERROR(INDEX('KPI 2'!$E$26:$P$26,Actual_month),) -> 46508629 | N7: =IFERROR(INDEX('KPI 2'!$E$27:$P$27,Actual_month),) -> 52285082 | O7: =IFERROR(N7/M7,"") -> 1.1242017 | P7: details | Q7: =G7*$R$3 -> 4738470.1 | R7: =M7*$R$3 -> 41857766 | S7: H | T7: v
A8: 3 | B8: Bulk water | C8: Ksh | D8: l | E8: l | F8: l | G8: =IFERROR(INDEX('KPI a'!E$19:P$19,Actual_month),) -> 64130 | H8: =IFERROR(INDEX('KPI a'!$E$20:$P$20,Actual_month),) -> 30290 | I8: =IFERROR(H8/G8,"") -> 0.47232185 | J8: l | K8: l | L8: l | M8: =IFERROR(INDEX('KPI a'!$E$26:$P$26,Actual_month),) -> 577170 | N8: =IFERROR(INDEX('KPI a'!$E$27:$P$27,Actual_month),) -> 1096030 | O8: =IFERROR(N8/M8,"") -> 1.8989726 | P8: details | Q8: =G8*$R$3 -> 57717 | R8: =M8*$R$3 -> 519453 | S8: H | T8: v
A9: 4 | B9: Sanitation | C9: Ksh | D9: l | E9: l | F9: l | G9: =IFERROR(INDEX('KPI b1'!E$19:P$19,Actual_month),) -> 936756.39 | H9: =IFERROR(INDEX('KPI b1'!$E$20:$P$20,Actual_month),) -> 917568.5 | I9: =IFERROR(H9/G9,"") -> 0.97951667 | J9: l | K9: l | L9: l | M9: =IFERROR(INDEX('KPI b1'!$E$26:$P$26,Actual_month),) -> 8010534.5 | N9: =IFERROR(INDEX('KPI b1'!$E$27:$P$27,Actual_month),) -> 8990471 | O9: =IFERROR(N9/M9,"") -> 1.122331 | P9: details | Q9: =G9*$R$3 -> 843080.75 | R9: =M9*$R$3 -> 7209481 | S9: H | T9: v
A10: 5 | B10: new connection fee water | C10: Ksh | D10: l | E10: l | F10: l | G10: =IFERROR(INDEX('KPI c'!E$19:P$19,Actual_month),) -> 475000 | H10: =IFERROR(INDEX('KPI c'!$E$20:$P$20,Actual_month),) -> 147500 | I10: =IFERROR(H10/G10,"") -> 0.31052632 | J10: l | K10: l | L10: l | M10: =IFERROR(INDEX('KPI c'!$E$26:$P$26,Actual_month),) -> 4500000 | N10: =IFERROR(INDEX('KPI c'!$E$27:$P$27,Actual_month),) -> 3002500 | O10: =IFERROR(N10/M10,"") -> 0.66722222 | P10: details | Q10: =G10*$R$3 -> 427500 | R10: =M10*$R$3 -> 4050000 | S10: H | T10: v
A11: 6 | B11: new connection fee sewer | C11: Ksh | D11: l | E11: l | F11: l | G11: =IFERROR(INDEX('KPI e'!E$19:P$19,Actual_month),) -> 75000 | H11: =IFERROR(INDEX('KPI e'!$E$20:$P$20,Actual_month),) -> 0 | I11: =IFERROR(H11/G11,"") -> 0 | J11: l | K11: l | L11: l | M11: =IFERROR(INDEX('KPI e'!$E$26:$P$26,Actual_month),) -> 680000 | N11: =IFERROR(INDEX('KPI e'!$E$27:$P$27,Actual_month),) -> 142500 | O11: =IFERROR(N11/M11,"") -> 0.20955882 | P11: details | Q11: =G11*$R$3 -> 67500 | R11: =M11*$R$3 -> 612000 | S11: H | T11: v
A12: 7 | B12: reconnection fee (water+sewer) | C12: Ksh | D12: l | E12: l | F12: l | G12: =IFERROR(INDEX('KPI k'!E$19:P$19,Actual_month),) -> 582500 | H12: =IFERROR(INDEX('KPI k'!$E$20:$P$20,Actual_month),) -> 157500 | I12: =IFERROR(H12/G12,"") -> 0.27038627 | J12: l | K12: l | L12: l | M12: =IFERROR(INDEX('KPI k'!$E$26:$P$26,Actual_month),) -> 5242500 | N12: =IFERROR(INDEX('KPI k'!$E$27:$P$27,Actual_month),) -> 1335000 | O12: =IFERROR(N12/M12,"") -> 0.2546495 | P12: details | Q12: =G12*$R$3 -> 524250 | R12: =M12*$R$3 -> 4718250 | S12: H | T12: v
A13: 8 | B13: Prepaid kiosk | C13: Ksh | D13: l | E13: l | F13: l | G13: =IFERROR(INDEX('KPI y'!E$19:P$19,Actual_month),) -> 90000 | H13: =IFERROR(INDEX('KPI y'!$E$20:$P$20,Actual_month),) -> 61500 | I13: =IFERROR(H13/G13,"") -> 0.68333333 | J13: l | K13: l | L13: l | M13: =IFERROR(INDEX('KPI y'!$E$26:$P$26,Actual_month),) -> 810000 | N13: =IFERROR(INDEX('KPI y'!$E$27:$P$27,Actual_month),) -> 708200 | O13: =IFERROR(N13/M13,"") -> 0.87432099 | P13: details | Q13: =G13*$R$3 -> 81000 | R13: =M13*$R$3 -> 729000 | S13: H | T13: v
A14: 9 | B14: misc income-printing fee,CA,meter replacement fee,meter testing | C14: Ksh | D14: l | E14: l | F14: l | G14: =IFERROR(INDEX('KPI w'!E$19:P$19,Actual_month),) -> 112050 | H14: =IFERROR(INDEX('KPI w'!$E$20:$P$20,Actual_month),) -> 2454300 | I14: =IFERROR(H14/G14,"") -> 21.903614 | J14: l | K14: l | L14: l | M14: =IFERROR(INDEX('KPI w'!$E$26:$P$26,Actual_month),) -> 1008450 | N14: =IFERROR(INDEX('KPI w'!$E$27:$P$27,Actual_month),) -> 2918450 | O14: =IFERROR(N14/M14,"") -> 2.8939957 | P14: details | Q14: =G14*$R$3 -> 100845 | R14: =M14*$R$3 -> 907605 | S14: H | T14: v
A15: 10 | B15: sewer unblocking fee | C15: Ksh | D15: l | E15: l | F15: l | G15: =IFERROR(INDEX('KPI z'!E$19:P$19,Actual_month),) -> 2500 | H15: =IFERROR(INDEX('KPI z'!$E$20:$P$20,Actual_month),) -> 0 | I15: =IFERROR(H15/G15,"") -> 0 | J15: l | K15: l | L15: l | M15: =IFERROR(INDEX('KPI z'!$E$26:$P$26,Actual_month),) -> 22500 | N15: =IFERROR(INDEX('KPI z'!$E$27:$P$27,Actual_month),) -> 45000 | O15: =IFERROR(N15/M15,"") -> 2 | P15: details | Q15: =G15*$R$3 -> 2250 | R15: =M15*$R$3 -> 20250 | S15: H | T15: v
A16: 11 | B16: penalties (water+sewer) | C16: Ksh | D16: l | E16: l | F16: l | G16: =IFERROR(INDEX('KPI j'!E$19:P$19,Actual_month),) -> 190001 | H16: =IFERROR(INDEX('KPI j'!$E$20:$P$20,Actual_month),) -> 155000 | I16: =IFERROR(H16/G16,"") -> 0.81578518 | J16: l | K16: l | L16: l | M16: =IFERROR(INDEX('KPI j'!$E$26:$P$26,Actual_month),) -> 1710009 | N16: =IFERROR(INDEX('KPI j'!$E$27:$P$27,Actual_month),) -> 865000 | O16: =IFERROR(N16/M16,"") -> 0.50584529 | P16: details | Q16: =G16*$R$3 -> 171000.9 | R16: =M16*$R$3 -> 1539008.1 | S16: H | T16: v
A17: 12 | B17: Company exhauster | C17: Ksh | D17: l | E17: l | F17: l | G17: =IFERROR(INDEX('KPI 4(i)'!E$19:P$19,Actual_month),) -> 0 | H17: =IFERROR(INDEX('KPI 4(i)'!$E$20:$P$20,Actual_month),) -> 0 | I17: =IFERROR(H17/G17,"") | J17: l | K17: l | L17: l | M17: =IFERROR(INDEX('KPI 4(i)'!$E$26:$P$26,Actual_month),) -> 0 | N17: =IFERROR(INDEX('KPI 4(i)'!$E$27:$P$27,Actual_month),) -> 0 | O17: =IFERROR(N17/M17,"") | P17: details | Q17: =G17*$R$3 -> 0 | R17: =M17*$R$3 -> 0 | S17: H | T17: v
A18: 12 | B18: Customer exhauster | C18: Ksh | D18: l | E18: l | F18: l | G18: =IFERROR(INDEX('KPI 4 (ii)'!E$19:P$19,Actual_month),) -> 210000 | H18: =IFERROR(INDEX('KPI 4 (ii)'!$E$20:$P$20,Actual_month),) -> 180000 | I18: =IFERROR(H18/G18,"") -> 0.85714286 | J18: l | K18: l | L18: l | M18: =IFERROR(INDEX('KPI 4 (ii)'!$E$26:$P$26,Actual_month),) -> 1890000 | N18: =IFERROR(INDEX('KPI 4 (ii)'!$E$27:$P$27,Actual_month),) -> 1770000 | O18: =IFERROR(N18/M18,"") -> 0.93650794 | P18: details | Q18: =G18*$R$3 -> 189000 | R18: =M18*$R$3 -> 1701000 | S18: H | T18: v
A19: 13 | B19: Total billed (Ksh) | C19: Ksh | D19: l | E19: l | F19: l | G19: =IFERROR(INDEX('KPI 5'!E$19:P$19,Actual_month),) -> 26673902 | H19: =IFERROR(INDEX('KPI 5'!$E$20:$P$20,Actual_month),) -> 28313514 | I19: =IFERROR(H19/G19,"") -> 1.0614688 | J19: l | K19: l | L19: l | M19: =IFERROR(INDEX('KPI 5'!$E$26:$P$26,Actual_month),) -> 2.3059331e+08 | N19: =IFERROR(INDEX('KPI 5'!$E$27:$P$27,Actual_month),) -> 2.5116353e+08 | O19: =IFERROR(N19/M19,"") -> 1.0892056 | P19: details | Q19: =G19*$R$3 -> 24006512 | R19: =M19*$R$3 -> 2.0753398e+08 | S19: H | T19: v
A21: A | B21: Eastern Region | C21: DATE | D21: l | E21: l | F21: l | G21: =IFERROR(INDEX('KPI g'!E$19:P$19,Actual_month),) -> 0 | H21: =IFERROR(INDEX('KPI g'!$E$20:$P$20,Actual_month),) -> 10TH | I21: =IFERROR(H21/G21,"") | J21: l | K21: l | L21: l | M21: =IFERROR(INDEX('KPI g'!$E$26:$P$26,Actual_month),) -> 0 | N21: =H21 -> 10TH | O21: =IFERROR(N21/M21,"") | P21: details | R21: =M21*$R$3 -> 0 | S21: H | T21: v
A22: B | B22: Southern Region | C22: DATE | D22: l | E22: l | F22: l | G22: =IFERROR(INDEX('KPI x'!E$19:P$19,Actual_month),) -> 0 | H22: =IFERROR(INDEX('KPI x'!$E$20:$P$20,Actual_month),) -> 24TH | I22: =IFERROR(H22/G22,"") | J22: l | K22: l | L22: l | M22: =IFERROR(INDEX('KPI x'!$E$26:$P$26,Actual_month),) -> 0 | N22: =H22 -> 24TH | O22: =IFERROR(N22/M22,"") | P22: details | R22: =M22*$R$3 -> 0 | S22: H | T22: v
A23: C | B23: Central Region | C23: DATE | D23: l | E23: l | F23: l | G23: =IFERROR(INDEX('KPI x (2)'!E$19:P$19,Actual_month),) -> 0 | H23: =IFERROR(INDEX('KPI x (2)'!$E$20:$P$20,Actual_month),) -> 31ST | I23: =IFERROR(H23/G23,"") | J23: l | K23: l | L23: l | M23: =IFERROR(INDEX('KPI x (2)'!$E$26:$P$26,Actual_month),) -> 0 | N23: =H23 -> 31ST | O23: =IFERROR(N23/M23,"") | P23: details | R23: =M23*$R$3 -> 0 | S23: H | T23: v
A24: COLLECTION EFFICIENCY
A25: D | B25: Total accounts disconnected-water | C25: NO | D25: l | E25: l | F25: l | G25: =IFERROR(INDEX('KPI qi'!E$19:P$19,Actual_month),) -> 500 | H25: =IFERROR(INDEX('KPI qi'!$E$20:$P$20,Actual_month),) -> 148 | I25: =IFERROR(H25/G25,"") -> 0.296 | J25: l | K25: l | L25: l | M25: =IFERROR(INDEX('KPI qi'!$E$26:$P$26,Actual_month),) -> 4500 | N25: =IFERROR(INDEX('KPI qi'!$E$27:$P$27,Actual_month),) -> 1158 | O25: =IFERROR(N25/M25,"") -> 0.25733333 | P25: details | Q25: =G25*$R$3 -> 450 | R25: =M25*$R$3 -> 4050 | S25: H | T25: v
A26: E | B26: Total accounts disconnected-sewer | C26: NO | D26: l | E26: l | F26: l | G26: =IFERROR(INDEX('KPI h'!E$19:P$19,Actual_month),) -> 55 | H26: =IFERROR(INDEX('KPI h'!$E$20:$P$20,Actual_month),) -> 1 | I26: =IFERROR(H26/G26,"") -> 0.018181818 | J26: l | K26: l | L26: l | M26: =IFERROR(INDEX('KPI h'!$E$26:$P$26,Actual_month),) -> 495 | N26: =IFERROR(INDEX('KPI h'!$E$27:$P$27,Actual_month),) -> 30 | O26: =IFERROR(N26/M26,"") -> 0.060606061 | P26: details | Q26: =G26*$R$3 -> 49.5 | R26: =M26*$R$3 -> 445.5 | S26: H | T26: v
A27: 14 | B27: Total Collection for the month | C27: Ksh | D27: l | E27: l | F27: l | G27: =IFERROR(INDEX('KPI 6'!E$19:P$19,Actual_month),) -> 27944610 | H27: =IFERROR(INDEX('KPI 6'!$E$20:$P$20,Actual_month),) -> 31993098 | I27: =IFERROR(H27/G27,"") -> 1.1448754 | J27: l | K27: l | L27: l | M27: =IFERROR(INDEX('KPI 6'!$E$26:$P$26,Actual_month),) -> 2.4209576e+08 | N27: =IFERROR(INDEX('KPI 6'!$E$27:$P$27,Actual_month),) -> 2.345866e+08 | O27: =IFERROR(N27/M27,"") -> 0.9689827 | P27: details | Q27: =G27*$R$3 -> 25150149 | R27: =M27*$R$3 -> 2.1788619e+08 | S27: H | T27: v
A28: 7 | B28: Total Collection- Related Sales | C28: Ksh | D28: l | E28: l | F28: l | G28: =IFERROR(INDEX('KPI j'!E$19:P$19,Actual_month),) -> 190001 | H28: =IFERROR(INDEX('KPI j'!$E$20:$P$20,Actual_month),) -> 155000 | I28: =IFERROR(H28/G28,"") -> 0.81578518 | J28: l | K28: l | L28: l | M28: =IFERROR(INDEX('KPI j'!$E$26:$P$26,Actual_month),) -> 1710009 | N28: =IFERROR(INDEX('KPI j'!$E$27:$P$27,Actual_month),) -> 865000 | O28: =IFERROR(N28/M28,"") -> 0.50584529 | P28: details
A29: 15 | B29: Collection Efficiency - in % of billing | C29: % | D29: l | E29: l | F29: l | G29: =IFERROR(INDEX('KPI 9'!E$19:P$19,Actual_month),) -> 1.0476386 | H29: =IFERROR(INDEX('KPI 9'!$E$20:$P$20,Actual_month),) -> 1.0860913 | I29: =IFERROR(H29/G29,"") -> 1.0367041 | J29: l | K29: l | L29: l | M29: =IFERROR(INDEX('KPI 9'!$E$26:$P$26,Actual_month),) -> 1.0476386 | N29: =IFERROR(INDEX('KPI 9'!$E$27:$P$27,Actual_month),) -> 0.94457038 | O29: =IFERROR(N29/M29,"") -> 0.9016185 | P29: details | Q29: =G29*$R$3 -> 0.94287477 | R29: =M29*$R$3 -> 0.94287477 | S29: H | T29: v
A30: REGIONAL PERFORMANCE
A31: CENTRAL REGION: CBD,CCCR,KABATI,SITE,KIHOTO,LAKEVIEW,HOPEWELL
A32: 16a | B32: Amount Billed Water-Central | C32: Ksh. | D32: l | E32: l | F32: l | G32: =IFERROR(INDEX('KPI 10'!E$19:P$19,Actual_month),) -> 9044300 | H32: =IFERROR(INDEX('KPI 10'!$E$20:$P$20,Actual_month),) -> 10195970 | I32: =IFERROR(H32/G32,"") -> 1.1273366 | J32: l | K32: l | L32: l | M32: =IFERROR(INDEX('KPI 10'!$E$26:$P$26,Actual_month),) -> 81187895 | N32: =IFERROR(INDEX('KPI 10'!$E$27:$P$27,Actual_month),) -> 93178050 | O32: =IFERROR(N32/M32,"") -> 1.147684 | P32: details | Q32: =G32*$R$3 -> 8139870 | R32: =M32*$R$3 -> 73069106 | S32: H
A33: 17a | B33: Amount Billed Sewer-Central | C33: Ksh. | D33: l | E33: l | F33: l | G33: =IFERROR(INDEX('KPI 11'!E$19:P$19,Actual_month),) -> 5161165.8 | H33: =IFERROR(INDEX('KPI 11'!$E$20:$P$20,Actual_month),) -> 5821018.5 | I33: =IFERROR(H33/G33,"") -> 1.1278495 | J33: l | K33: l | L33: l | M33: =IFERROR(INDEX('KPI 11'!$E$26:$P$26,Actual_month),) -> 45605872 | N33: =IFERROR(INDEX('KPI 11'!$E$27:$P$27,Actual_month),) -> 51180684 | O33: =IFERROR(N33/M33,"") -> 1.1222389 | P33: details | Q33: =G33*$R$3 -> 4645049.2 | R33: =M33*$R$3 -> 41045285 | S33: H
A34: 18a | B34: othersales | C34: Ksh. | D34: l | E34: l | F34: l | G34: =IFERROR(INDEX('KPI 11a'!E$19:P$19,Actual_month),) -> 0 | H34: =IFERROR(INDEX('KPI 11a'!$E$20:$P$20,Actual_month),) -> 509798.5 | I34: =IFERROR(H34/G34,"") | J34: l | K34: l | L34: l | M34: =IFERROR(INDEX('KPI 11a'!$E$26:$P$26,Actual_month),) -> 0 | N34: =IFERROR(INDEX('KPI 11a'!$E$27:$P$27,Actual_month),) -> 7916502.5 | O34: =IFERROR(N34/M34,"") | P34: details | Q34: =G34*$R$3 -> 0 | R34: =M34*$R$3 -> 0 | S34: H
A35: 19a | B35: Amount Billed Water & Sewer-othersales-Central | C35: Ksh. | D35: l | E35: l | F35: l | G35: =IFERROR(INDEX('KPI 12'!E$19:P$19,Actual_month),) -> 14205466 | H35: =IFERROR(INDEX('KPI 12'!$E$20:$P$20,Actual_month),) -> 16526787 | I35: =IFERROR(H35/G35,"") -> 1.1634104 | J35: l | K35: l | L35: l | M35: =IFERROR(INDEX('KPI 12'!$E$26:$P$26,Actual_month),) -> 1.2679377e+08 | N35: =IFERROR(INDEX('KPI 12'!$E$27:$P$27,Actual_month),) -> 1.5227524e+08 | O35: =IFERROR(N35/M35,"") -> 1.2009678 | P35: details | Q35: =G35*$R$3 -> 12784919 | R35: =M35*$R$3 -> 1.1411439e+08 | S35: H
A36: 14a | B36: Amount Collected-Central | C36: Ksh. | D36: l | E36: l | F36: l | G36: =IFERROR(INDEX('KPI 13'!E$19:P$19,Actual_month),) -> 14915739 | H36: =IFERROR(INDEX('KPI 13'!$E$20:$P$20,Actual_month),) -> 22532132 | I36: =IFERROR(H36/G36,"") -> 1.5106279 | J36: l | K36: l | L36: l | M36: =IFERROR(INDEX('KPI 13'!$E$26:$P$26,Actual_month),) -> 1.3313346e+08 | N36: =IFERROR(INDEX('KPI 13'!$E$27:$P$27,Actual_month),) -> 1.4782438e+08 | O36: =IFERROR(N36/M36,"") -> 1.1103474 | P36: details | Q36: =G36*$R$3 -> 13424165 | R36: =M36*$R$3 -> 1.1982011e+08 | S36: H
A37: 15a | B37: Collection Efficiency-Central | C37: % | D37: l | E37: l | F37: l | G37: =IFERROR(INDEX('KPI 14'!E$19:P$19,Actual_month),) -> 1.05 | H37: =IFERROR(INDEX('KPI 14'!$E$20:$P$20,Actual_month),) -> 1.2996422 | I37: =IFERROR(H37/G37,"") -> 1.2377545 | J37: l | K37: l | L37: l | M37: =IFERROR(INDEX('KPI 14'!$E$26:$P$26,Actual_month),) -> 1.05 | N37: =IFERROR(INDEX('KPI 14'!$E$27:$P$27,Actual_month),) -> 0.97001417 | O37: =IFERROR(N37/M37,"") -> 0.92382302 | P37: details | Q37: =G37*$R$3 -> 0.945 | R37: =M37*$R$3 -> 0.945 | S37: H
A38: SOUTHERN REGION: HELLSGATE,KAMERE, MAI MAHIU,LONGONOT
A39: 16b | B39: Amount Billed Water-Southern | C39: Ksh. | D39: l | E39: l | F39: l | G39: =IFERROR(INDEX('KPI 15'!E$19:P$19,Actual_month),) -> 6650863.9 | H39: =IFERROR(INDEX('KPI 15'!$E$20:$P$20,Actual_month),) -> 4890400 | I39: =IFERROR(H39/G39,"") -> 0.73530298 | J39: l | K39: l | L39: l | M39: =IFERROR(INDEX('KPI 15'!$E$26:$P$26,Actual_month),) -> 52436203 | N39: =IFERROR(INDEX('KPI 15'!$E$27:$P$27,Actual_month),) -> 54746640 | O39: =IFERROR(N39/M39,"") -> 1.0440619 | P39: details | Q39: =G39*$R$3 -> 5985777.5 | R39: =M39*$R$3 -> 47192583 | S39: H
A40: 17b | B40: Amount Billed Sewer-Southern | C40: Ksh. | D40: l | E40: l | F40: l | G40: =IFERROR(INDEX('KPI 16'!E$19:P$19,Actual_month),) -> 0 | H40: =IFERROR(INDEX('KPI 16'!$E$20:$P$20,Actual_month),) -> 0 | I40: =IFERROR(H40/G40,"") | J40: l | K40: l | L40: l | M40: =IFERROR(INDEX('KPI 16'!$E$26:$P$26,Actual_month),) -> 0 | N40: =IFERROR(INDEX('KPI 16'!$E$27:$P$27,Actual_month),) -> 0 | O40: =IFERROR(N40/M40,"") | P40: details | Q40: =G40*$R$3 -> 0 | R40: =M40*$R$3 -> 0 | S40: H
A41: 18b | B41: othersales | C41: Ksh. | D41: l | E41: l | F41: l | G41: =IFERROR(INDEX('KPI 16A'!E$19:P$19,Actual_month),) -> 0 | H41: =IFERROR(INDEX('KPI 16A'!$E$20:$P$20,Actual_month),) -> 244520 | I41: =IFERROR(H41/G41,"") | J41: l | K41: l | L41: l | M41: =IFERROR(INDEX('KPI 16A'!$E$26:$P$26,Actual_month),) -> 0 | N41: =IFERROR(INDEX('KPI 16A'!$E$27:$P$27,Actual_month),) -> 4946482 | O41: =IFERROR(N41/M41,"") | P41: details | Q41: =G41*$R$3 -> 0 | R41: =M41*$R$3 -> 0 | S41: H
A42: 19b | B42: Amount Billed Water & Sewer-OTHER SALES-Southern | C42: Ksh. | D42: l | E42: l | F42: l | G42: =IFERROR(INDEX('KPI 17'!E$19:P$19,Actual_month),) -> 6650863.9 | H42: =IFERROR(INDEX('KPI 17'!$E$20:$P$20,Actual_month),) -> 5134920 | I42: =IFERROR(H42/G42,"") -> 0.77206813 | J42: l | K42: l | L42: l | M42: =IFERROR(INDEX('KPI 17'!$E$26:$P$26,Actual_month),) -> 52436203 | N42: =IFERROR(INDEX('KPI 17'!$E$27:$P$27,Actual_month),) -> 59693122 | O42: =IFERROR(N42/M42,"") -> 1.1383952 | P42: details | Q42: =G42*$R$3 -> 5985777.5 | R42: =M42*$R$3 -> 47192583 | S42: H
A43: 14b | B43: Amount Collected-Southern | C43: Ksh. | D43: l | E43: l | F43: l | G43: =IFERROR(INDEX('KPI 18'!E$19:P$19,Actual_month),) -> 6983407 | H43: =IFERROR(INDEX('KPI 18'!$E$20:$P$20,Actual_month),) -> 5621150.5 | I43: =IFERROR(H43/G43,"") -> 0.80492952 | J43: l | K43: l | L43: l | M43: =IFERROR(INDEX('KPI 18'!$E$26:$P$26,Actual_month),) -> 55058013 | N43: =IFERROR(INDEX('KPI 18'!$E$27:$P$27,Actual_month),) -> 53274698 | O43: =IFERROR(N43/M43,"") -> 0.96761024 | P43: details | Q43: =G43*$R$3 -> 6285066.3 | R43: =M43*$R$3 -> 49552212 | S43: H
A44: 15b | B44: Collection Efficiency-Southern | C44: % | D44: l | E44: l | F44: l | G44: =IFERROR(INDEX('KPI 14 (2)'!E$19:P$19,Actual_month),) -> 1.05 | H44: =IFERROR(INDEX('KPI 14 (2)'!$E$20:$P$20,Actual_month),) -> 0.74787417 | I44: =IFERROR(H44/G44,"") -> 0.71226111 | J44: l | K44: l | L44: l | M44: =IFERROR(INDEX('KPI 14 (2)'!$E$26:$P$26,Actual_month),) -> 1.05 | N44: =IFERROR(INDEX('KPI 14 (2)'!$E$27:$P$27,Actual_month),) -> 0.90876768 | O44: =IFERROR(N44/M44,"") -> 0.86549303 | P44: details | Q44: =G44*$R$3 -> 0.945 | R44: =M44*$R$3 -> 0.945 | S44: H
A45: EASTERN REGION: KAYOLE,GONDI,KINUNGI,NJONJORO,IHINDU
A46: 16c | B46: Amount Billed Water-Eastern | C46: Ksh. | D46: l | E46: l | F46: l | G46: =IFERROR(INDEX('KPI 10 (2)'!E$19:P$19,Actual_month),) -> 3129963.9 | H46: =IFERROR(INDEX('KPI 10 (2)'!$E$20:$P$20,Actual_month),) -> 3265000 | I46: =IFERROR(H46/G46,"") -> 1.043143 | J46: l | K46: l | L46: l | M46: =IFERROR(INDEX('KPI 10 (2)'!$E$26:$P$26,Actual_month),) -> 27396592 | N46: =IFERROR(INDEX('KPI 10 (2)'!$E$27:$P$27,Actual_month),) -> 31884730 | O46: =IFERROR(N46/M46,"") -> 1.163821 | P46: details | Q46: =G46*$R$3 -> 2816967.5 | R46: =M46*$R$3 -> 24656933 | S46: H
A47: 17c | B47: Amount Billed Sewer-Eastern | C47: Ksh. | D47: l | E47: l | F47: l | G47: =IFERROR(INDEX('KPI 11 (2)'!E$19:P$19,Actual_month),) -> 103800.97 | H47: =IFERROR(INDEX('KPI 11 (2)'!$E$20:$P$20,Actual_month),) -> 112697.5 | I47: =IFERROR(H47/G47,"") -> 1.0857076 | J47: l | K47: l | L47: l | M47: =IFERROR(INDEX('KPI 11 (2)'!$E$26:$P$26,Actual_month),) -> 902756.64 | N47: =IFERROR(INDEX('KPI 11 (2)'!$E$27:$P$27,Actual_month),) -> 1087947.5 | O47: =IFERROR(N47/M47,"") -> 1.2051393 | P47: details | Q47: =G47*$R$3 -> 93420.874 | R47: =M47*$R$3 -> 812480.98 | S47: H
A48: 18c | B48: othersales | C48: Ksh. | D48: l | E48: l | F48: l | G48: =IFERROR(INDEX('KPI 11a (2)'!E$19:P$19,Actual_month),) -> 0 | H48: =IFERROR(INDEX('KPI 11a (2)'!$E$20:$P$20,Actual_month),) -> 163250 | I48: =IFERROR(H48/G48,"") | J48: l | K48: l | L48: l | M48: =IFERROR(INDEX('KPI 11a (2)'!$E$26:$P$26,Actual_month),) -> 0 | N48: =IFERROR(INDEX('KPI 11a (2)'!$E$27:$P$27,Actual_month),) -> 3111636.5 | O48: =IFERROR(N48/M48,"") | P48: details | Q48: =G48*$R$3 -> 0 | R48: =M48*$R$3 -> 0 | S48: H
A49: 19b | B49: Amount Billed Water & Sewer-othersales-Eastern | C49: Ksh. | D49: l | E49: l | F49: l | G49: =IFERROR(INDEX('KPI 12 (2)'!E$19:P$19,Actual_month),) -> 3233764.9 | H49: =IFERROR(INDEX('KPI 12 (2)'!$E$20:$P$20,Actual_month),) -> 3540947.5 | I49: =IFERROR(H49/G49,"") -> 1.0949923 | J49: l | K49: l | L49: l | M49: =IFERROR(INDEX('KPI 12 (2)'!$E$26:$P$26,Actual_month),) -> 28299348 | N49: =IFERROR(INDEX('KPI 12 (2)'!$E$27:$P$27,Actual_month),) -> 36084314 | O49: =IFERROR(N49/M49,"") -> 1.2750935 | P49: details | Q49: =G49*$R$3 -> 2910388.4 | R49: =M49*$R$3 -> 25469414 | S49: H
A50: 14c | B50: Amount Collected-Eastern | C50: Ksh. | D50: l | E50: l | F50: l | G50: =IFERROR(INDEX('KPI 13 (2)'!E$19:P$19,Actual_month),) -> 3395453.1 | H50: =IFERROR(INDEX('KPI 13 (2)'!$E$20:$P$20,Actual_month),) -> 3839815 | I50: =IFERROR(H50/G50,"") -> 1.1308697 | J50: l | K50: l | L50: l | M50: =IFERROR(INDEX('KPI 13 (2)'!$E$26:$P$26,Actual_month),) -> 29714316 | N50: =IFERROR(INDEX('KPI 13 (2)'!$E$27:$P$27,Actual_month),) -> 33487523 | O50: =IFERROR(N50/M50,"") -> 1.1269828 | P50: details | Q50: =G50*$R$3 -> 3055907.8 | R50: =M50*$R$3 -> 26742884 | S50: H
A51: 15c | B51: Collection Efficiency-Eastern | C51: % | D51: l | E51: l | F51: l | G51: =IFERROR(INDEX('KPI 14 (3)'!E$19:P$19,Actual_month),) -> 1.05 | H51: =IFERROR(INDEX('KPI 14 (3)'!$E$20:$P$20,Actual_month),) -> 0.83406317 | I51: =IFERROR(H51/G51,"") -> 0.79434588 | J51: l | K51: l | L51: l | M51: =IFERROR(INDEX('KPI 14 (3)'!$E$26:$P$26,Actual_month),) -> 1.05 | N51: =IFERROR(INDEX('KPI 14 (3)'!$E$27:$P$27,Actual_month),) -> 0.91355898 | O51: =IFERROR(N51/M51,"") -> 0.87005617 | P51: details | Q51: =G51*$R$3 -> 0.945 | R51: =M51*$R$3 -> 0.945 | S51: H
A52: 19 | B52: Collection Efficiency- | C52: % | D52: l | E52: l | F52: l | G52: =IFERROR(INDEX('KPI 19'!E$19:P$19,Actual_month),) -> 0 | H52: =IFERROR(INDEX('KPI 19'!$E$20:$P$20,Actual_month),) -> 0 | I52: =IFERROR(H52/G52,"") | J52: l | K52: l | L52: l | M52: =IFERROR(INDEX('KPI 19'!$E$26:$P$26,Actual_month),) -> 0 | N52: =IFERROR(INDEX('KPI 19'!$E$27:$P$27,Actual_month),) -> 0 | O52: =IFERROR(N52/M52,"") | P52: details | Q52: =G52*$R$3 -> 0 | R52: =M52*$R$3 -> 0 | S52: H
B53: AMOUNT RECEIVABLES
A54: 20 | B54: Amount receivables as at close of the month | C54: Ksh. | D54: l | E54: l | F54: l | G54: =IFERROR(INDEX('KPI q'!E$19:P$19,Actual_month),) -> 0 | H54: =IFERROR(INDEX('KPI q'!$E$20:$P$20,Actual_month),) -> 205010129 | I54: =IFERROR(H54/G54,"") | J54: l | K54: l | L54: l | M54: =IFERROR(INDEX('KPI q'!$E$26:$P$26,Actual_month),) -> 0 | N54: =IFERROR(INDEX('KPI q'!$E$27:$P$27,Actual_month),) -> 205010129 | O54: =IFERROR(N54/M54,"") | P54: details | Q54: =G54*$R$3 -> 0 | R54: =M54*$R$3 -> 0 | S54: H
A55: 21 | B55: Adjustment done for the month | C55: Ksh. | D55: l | E55: l | F55: l | G55: =IFERROR(INDEX('KPI v'!E$19:P$19,Actual_month),) -> 0 | H55: =IFERROR(INDEX('KPI v'!$E$20:$P$20,Actual_month),) -> 90000 | I55: =IFERROR(H55/G55,"") | J55: l | K55: l | L55: l | M55: =IFERROR(INDEX('KPI v'!$E$26:$P$26,Actual_month),) -> 0 | N55: =IFERROR(INDEX('KPI v'!$E$27:$P$27,Actual_month),) -> -283993.75 | O55: =IFERROR(N55/M55,"") | P55: details | Q55: =G55*$R$3 -> 0 | R55: =M55*$R$3 -> 0 | S55: H

Sheet BUDGET2526
A1: =Dashboard!A1 -> FINANCE DASHBOARD
B4: MONTH | C4: UNIT | D4: JUL | E4: AUG | F4: SEP | G4: OCT | H4: NOV | I4: DEC | J4: JAN | K4: FEB | L4: MAR | M4: APR | N4: MAY | O4: JUN
A5: =Dashboard!A5 -> BILLING DASHBOARD - SUMMARY
A6: =Dashboard!A6 -> 1 | B6: =Dashboard!B6 -> Total Water Sales (Ksh) | C6: =Dashboard!C6 -> Ksh | D6: 16944468 | E6: 17161528 | F6: 17381828 | G6: 17650728 | H6: 17903428 | I6: 18139928 | J6: 18392628 | K6: 18621028 | L6: 18825128 | M6: 19013028 | N6: 19200928 | O6: 19385588
A7: =Dashboard!A7 -> 2 | B7: =Dashboard!B7 -> Total Sewerage Sales (Ksh) | C7: =Dashboard!C7 -> Ksh | D7: 5070284.1 | E7: 5094619.4 | F7: 5118954.8 | G7: 5143290.1 | H7: 5167625.4 | I7: 5191960.8 | J7: 5216296.1 | K7: 5240631.4 | L7: 5264966.7 | M7: 5289302.1 | N7: 5313637.4 | O7: 5337972.7
A8: =Dashboard!A8 -> 3 | B8: =Dashboard!B8 -> Bulk water | D8: 64130 | E8: 64130 | F8: 64130 | G8: 64130 | H8: 64130 | I8: 64130 | J8: 64130 | K8: 64130 | L8: 64130 | M8: 64130 | N8: 64130 | O8: 64130
A9: =Dashboard!#REF! -> #REF! | B9: =Dashboard!#REF! -> #REF!
A10: =Dashboard!A9 -> 4 | B10: =Dashboard!B9 -> Sanitation | D10: 842723.39 | E10: 853576.39 | F10: 864591.39 | G10: 878036.39 | H10: 890671.39 | I10: 902496.39 | J10: 915131.39 | K10: 926551.39 | L10: 936756.39 | M10: 946151.39 | N10: 955546.39 | O10: 964779.39
A11: =Dashboard!A10 -> 5 | B11: =Dashboard!B10 -> new connection fee water | D11: 455000 | E11: 407500 | F11: 412500 | G11: 587500 | H11: 562500 | I11: 537500 | J11: 550000 | K11: 512500 | L11: 475000 | M11: 425000 | N11: 425000 | O11: 420000
A12: =Dashboard!A11 -> 6 | B12: =Dashboard!B11 -> new connection fee sewer | D12: 80000 | E12: 75000 | F12: 75000 | G12: 75000 | H12: 75000 | I12: 75000 | J12: 75000 | K12: 75000 | L12: 75000 | M12: 75000 | N12: 75000 | O12: 75000
A13: =Dashboard!A12 -> 7 | B13: =Dashboard!B12 -> reconnection fee (water+sewer) | D13: 582500 | E13: 582500 | F13: 582500 | G13: 582500 | H13: 582500 | I13: 582500 | J13: 582500 | K13: 582500 | L13: 582500 | M13: 582500 | N13: 582500 | O13: 582500
A14: =Dashboard!A13 -> 8 | B14: =Dashboard!B13 -> Prepaid kiosk | C14: =Dashboard!C8 -> Ksh | D14: 90000 | E14: 90000 | F14: 90000 | G14: 90000 | H14: 90000 | I14: 90000 | J14: 90000 | K14: 90000 | L14: 90000 | M14: 90000 | N14: 90000 | O14: 90000
A15: =Dashboard!A14 -> 9 | B15: =Dashboard!B14 -> misc income-printing fee,CA,meter replacement fee,meter testing | C15: =Dashboard!C10 -> Ksh | D15: 112050 | E15: 112050 | F15: 112050 | G15: 112050 | H15: 112050 | I15: 112050 | J15: 112050 | K15: 112050 | L15: 112050 | M15: 112050 | N15: 112050 | O15: 112050
A16: =Dashboard!A15 -> 10 | B16: =Dashboard!B15 -> sewer unblocking fee | C16: =Dashboard!C11 -> Ksh | D16: 2500 | E16: 2500 | F16: 2500 | G16: 2500 | H16: 2500 | I16: 2500 | J16: 2500 | K16: 2500 | L16: 2500 | M16: 2500 | N16: 2500 | O16: 2500
A17: =Dashboard!A16 -> 11 | B17: =Dashboard!B16 -> penalties (water+sewer) | C17: =Dashboard!C12 -> Ksh | D17: 110001 | E17: 260001 | F17: 220001 | G17: 150001 | H17: 160001 | I17: 240001 | J17: 190001 | K17: 190001 | L17: 190001 | M17: 160001 | N17: 110001 | O17: 120001
A18: =Dashboard!#REF! -> #REF! | B18: =Dashboard!#REF! -> #REF! | C18: =Dashboard!C13 -> Ksh
A19: =Dashboard!A17 -> 12 | B19: =Dashboard!B17 -> Company exhauster | C19: =Dashboard!C14 -> Ksh | D19: 0 | E19: 0 | F19: 0 | G19: 0 | H19: 0 | I19: 0 | J19: 0 | K19: 0 | L19: 0 | M19: 0 | N19: 0 | O19: 0
A20: =Dashboard!A18 -> 12 | B20: =Dashboard!B18 -> Customer exhauster | C20: =Dashboard!C15 -> Ksh | D20: 210000 | E20: 210000 | F20: 210000 | G20: 210000 | H20: 210000 | I20: 210000 | J20: 210000 | K20: 210000 | L20: 210000 | M20: 210000 | N20: 210000 | O20: 210000
A21: =Dashboard!A19 -> 13 | B21: =Dashboard!B19 -> Total billed (Ksh) | C21: =Dashboard!C17 -> Ksh | D21: =D6+D7+D9+D11+D12+D13+D14+D16+D17+D20+D10+D15-D14 -> 24409526 | E21: =E6+E7+E9+E11+E12+E13+E14+E16+E17+E20+E10+E15-E14 -> 24759275 | F21: =F6+F7+F9+F11+F12+F13+F14+F16+F17+F20+F10+F15-F14 -> 24979925 | G21: =G6+G7+G9+G11+G12+G13+G14+G16+G17+G20+G10+G15-G14 -> 25391605 | H21: =H6+H7+H9+H11+H12+H13+H14+H16+H17+H20+H10+H15-H14 -> 25666276 | I21: =I6+I7+I9+I11+I12+I13+I14+I16+I17+I20+I10+I15-I14 -> 25993936 | J21: =J6+J7+J9+J11+J12+J13+J14+J16+J17+J20+J10+J15-J14 -> 26246106 | K21: =K6+K7+K9+K11+K12+K13+K14+K16+K17+K20+K10+K15-K14 -> 26472762 | ... O21: =O6+O7+O9+O11+O12+O13+O14+O16+O17+O20+O10+O15-O14 -> 27210391
A22: =Dashboard!A20 -> 0 | B22: =Dashboard!B20 -> 0
A23: =Dashboard!A21 -> A | B23: =Dashboard!B21 -> Eastern Region | C23: =Dashboard!C21 -> DATE
A24: =Dashboard!A22 -> B | B24: =Dashboard!B22 -> Southern Region | C24: =Dashboard!C22 -> DATE
A25: =Dashboard!A23 -> C | B25: =Dashboard!B23 -> Central Region | C25: =Dashboard!C23 -> DATE
A26: =Dashboard!A24 -> COLLECTION EFFICIENCY | B26: =Dashboard!B24 -> 0
A27: =Dashboard!A25 -> D | B27: =Dashboard!B25 -> Total accounts disconnected-water | C27: =Dashboard!C25 -> NO | D27: 500 | E27: 500 | F27: 500 | G27: 500 | H27: 500 | I27: 500 | J27: 500 | K27: 500 | L27: 500 | M27: 500 | N27: 500 | O27: 500
A28: =Dashboard!A26 -> E | B28: =Dashboard!B26 -> Total accounts disconnected-sewer | C28: =Dashboard!C26 -> NO | D28: 55 | E28: 55 | F28: 55 | G28: 55 | H28: 55 | I28: 55 | J28: 55 | K28: 55 | L28: 55 | M28: 55 | N28: 55 | O28: 55
A29: =Dashboard!A27 -> 14 | B29: =Dashboard!B27 -> Total Collection for the month | C29: =Dashboard!C27 -> Ksh | D29: =D21*D31 -> 25630003 | E29: =E21*E31 -> 25997238 | F29: =F21*F31 -> 26228921 | G29: =G21*G31 -> 26723339 | H29: =H21*H31 -> 26984968 | I29: =I21*I31 -> 27296721 | J29: =J21*J31 -> 27537000 | K29: =K21*K31 -> 27752961 | ... O29: =O21*O31 -> 28455822
A30: =Dashboard!A28 -> 7 | B30: =Dashboard!B28 -> Total Collection- Related Sales | C30: =Dashboard!C28 -> Ksh | E30: =D21/E29 -> 0.93892766 | F30: =E21/F29 -> 0.94396847 | G30: =F21/G29 -> 0.93476064 | H30: =G21/H29 -> 0.94095368 | I30: =H21/I29 -> 0.94026954 | J30: =I21/J29 -> 0.94396398 | K30: =J21/K29 -> 0.9457047 | L30: =K21/L29 -> 0.94732979 | ... O30: =N21/O29 -> 0.94838809
A31: =Dashboard!A29 -> 15 | B31: =Dashboard!B29 -> Collection Efficiency - in % of billing | C31: =Dashboard!C29 -> % | D31: 1.05 | E31: 1.05 | F31: 1.05 | G31: 1.0524478 | H31: 1.0513784 | I31: 1.0501188 | J31: 1.0491842 | K31: 1.0483591 | L31: 1.0476386 | M31: 1.0471458 | N31: 1.0465479 | O31: 1.0457704
A32: =Dashboard!A31 -> CENTRAL REGION: CBD,CCCR,KABATI,SITE,KIHOTO,LAKEVIEW,HOPEWELL
A33: =Dashboard!A32 -> 16a | B33: =Dashboard!B32 -> Amount Billed Water-Central | C33: =Dashboard!C32 -> Ksh. | D33: 8942465.9 | E33: 8996210.7 | F33: 9045864.1 | G33: 9035851.2 | H33: 9029894.1 | I33: 9020852.3 | J33: 9032887.4 | K33: 9039569.4 | L33: 9044300 | M33: 9063999.3 | N33: 9084168.1 | O33: 9104601.9
A34: =Dashboard!A33 -> 17a | B34: =Dashboard!B33 -> Amount Billed Sewer-Central | C34: =Dashboard!C33 -> Ksh. | D34: 4973474.6 | E34: 4996935.2 | F34: 5020396 | G34: 5043857.1 | H34: 5067318.4 | I34: 5090779.9 | J34: 5114241.6 | K34: 5137703.6 | L34: 5161165.8 | M34: 5184628.2 | N34: 5208090.8 | O34: 5231553.6
A35: =Dashboard!A34 -> 18a | B35: =Dashboard!B34 -> othersales | C35: =Dashboard!C34 -> Ksh.
A36: =Dashboard!A35 -> 19a | B36: =Dashboard!B35 -> Amount Billed Water & Sewer-othersales-Central | C36: =Dashboard!C35 -> Ksh. | D36: =D33+D34+D35 -> 13915941 | E36: =E33+E34+E35 -> 13993146 | F36: =F33+F34+F35 -> 14066260 | G36: =G33+G34+G35 -> 14079708 | H36: =H33+H34+H35 -> 14097212 | I36: =I33+I34+I35 -> 14111632 | J36: =J33+J34+J35 -> 14147129 | K36: =K33+K34+K35 -> 14177273 | ... O36: =O33+O34+O35 -> 14336156
A37: =Dashboard!A36 -> 14a | B37: =Dashboard!B36 -> Amount Collected-Central | C37: =Dashboard!C36 -> Ksh. | D37: =D38*D36 -> 14611738 | E37: =E38*E36 -> 14692803 | F37: =F38*F36 -> 14769573 | G37: =G38*G36 -> 14783694 | H37: =H38*H36 -> 14802073 | I37: =I38*I36 -> 14817214 | J37: =J38*J36 -> 14854486 | K37: =K38*K36 -> 14886137 | ... O37: =O38*O36 -> 15052963
A38: =Dashboard!A37 -> 15a | B38: =Dashboard!B37 -> Collection Efficiency-Central | C38: =Dashboard!C37 -> % | D38: 1.05 | E38: 1.05 | F38: 1.05 | G38: 1.05 | H38: 1.05 | I38: 1.05 | J38: 1.05 | K38: 1.05 | L38: 1.05 | M38: 1.05 | N38: 1.05 | O38: 1.05
A39: =Dashboard!A38 -> SOUTHERN REGION: HELLSGATE,KAMERE, MAI MAHIU,LONGONOT
A40: =Dashboard!A39 -> 16b | B40: =Dashboard!B39 -> Amount Billed Water-Southern | C40: =Dashboard!C39 -> Ksh. | D40: 5065118.2 | E40: 5186854 | F40: 5320133 | G40: 5584553.7 | H40: 5827594.1 | I40: 6061586.4 | J40: 6268878.1 | K40: 6470621.6 | L40: 6650863.9 | M40: 6799132.4 | N40: 6946856.2 | O40: 7091067.9
A41: =Dashboard!A40 -> 17b | B41: =Dashboard!B40 -> Amount Billed Sewer-Southern | C41: =Dashboard!C40 -> Ksh. | D41: 0 | E41: 0 | F41: 0 | G41: 0 | H41: 0 | I41: 0 | J41: 0 | K41: 0 | L41: 0 | M41: 0 | N41: 0 | O41: 0
A42: =Dashboard!A41 -> 18b | B42: =Dashboard!B41 -> othersales | C42: =Dashboard!C41 -> Ksh.
A43: =Dashboard!A42 -> 19b | B43: =Dashboard!B42 -> Amount Billed Water & Sewer-OTHER SALES-Southern | C43: =Dashboard!C42 -> Ksh. | D43: =D40+D41+D42 -> 5065118.2 | E43: =E40+E41+E42 -> 5186854 | F43: =F40+F41+F42 -> 5320133 | G43: =G40+G41+G42 -> 5584553.7 | H43: =H40+H41+H42 -> 5827594.1 | I43: =I40+I41+I42 -> 6061586.4 | J43: =J40+J41+J42 -> 6268878.1 | K43: =K40+K41+K42 -> 6470621.6 | ... O43: =O40+O41+O42 -> 7091067.9
A44: =Dashboard!A43 -> 14b | B44: =Dashboard!B43 -> Amount Collected-Southern | C44: =Dashboard!C43 -> Ksh. | D44: =D43*D45 -> 5318374.2 | E44: =E43*E45 -> 5446196.7 | F44: =F43*F45 -> 5586139.6 | G44: =G43*G45 -> 5863781.4 | H44: =H43*H45 -> 6118973.9 | I44: =I43*I45 -> 6364665.7 | J44: =J43*J45 -> 6582322 | K44: =K43*K45 -> 6794152.6 | ... O44: =O43*O45 -> 7445621.3
A45: =Dashboard!A44 -> 15b | B45: =Dashboard!B44 -> Collection Efficiency-Southern | C45: =Dashboard!C44 -> % | D45: 1.05 | E45: 1.05 | F45: 1.05 | G45: 1.05 | H45: 1.05 | I45: 1.05 | J45: 1.05 | K45: 1.05 | L45: 1.05 | M45: 1.05 | N45: 1.05 | O45: 1.05
A46: =Dashboard!A45 -> EASTERN REGION: KAYOLE,GONDI,KINUNGI,NJONJORO,IHINDU | B46: =Dashboard!B45 -> 0 | C46: =Dashboard!C45 -> 0
A47: =Dashboard!A46 -> 16c | B47: =Dashboard!B46 -> Amount Billed Water-Eastern | C47: =Dashboard!C46 -> Ksh. | D47: 2936883.6 | E47: 2978463.1 | F47: 3015830.7 | G47: 3030322.9 | H47: 3045939.5 | I47: 3057489 | J47: 3090862.3 | K47: 3110836.8 | L47: 3129963.9 | M47: 3149896.1 | N47: 3169903.5 | O47: 3189917.9
A48: =Dashboard!A47 -> 17c | B48: =Dashboard!B47 -> Amount Billed Sewer-Eastern | C48: =Dashboard!C47 -> Ksh. | D48: 96809.506 | E48: 97684.242 | F48: 98558.742 | G48: 99433.009 | H48: 100307.05 | I48: 101180.86 | J48: 102054.45 | K48: 102927.82 | L48: 103800.97 | M48: 104673.91 | N48: 105546.64 | O48: 106419.17
A49: =Dashboard!A48 -> 18c | B49: =Dashboard!B48 -> othersales | C49: =Dashboard!C48 -> Ksh.
A50: =Dashboard!A49 -> 19b | B50: =Dashboard!B49 -> Amount Billed Water & Sewer-othersales-Eastern | C50: =Dashboard!C49 -> Ksh. | D50: =D47+D48 -> 3033693.1 | E50: =E47+E48 -> 3076147.3 | F50: =F47+F48 -> 3114389.4 | G50: =G47+G48 -> 3129755.9 | H50: =H47+H48 -> 3146246.6 | I50: =I47+I48 -> 3158669.9 | J50: =J47+J48 -> 3192916.7 | K50: =K47+K48 -> 3213764.6 | ... O50: =O47+O48 -> 3296337.1
A51: =Dashboard!A50 -> 14c | B51: =Dashboard!B50 -> Amount Collected-Eastern | C51: =Dashboard!C50 -> Ksh. | D51: =D50*D52 -> 3185377.8 | E51: =E50*E52 -> 3229954.7 | F51: =F50*F52 -> 3270108.9 | G51: =G50*G52 -> 3286243.7 | H51: =H50*H52 -> 3303558.9 | I51: =I50*I52 -> 3316603.4 | J51: =J50*J52 -> 3352562.5 | K51: =K50*K52 -> 3374452.9 | ... O51: =O50*O52 -> 3461154
A52: =Dashboard!A51 -> 15c | B52: =Dashboard!B51 -> Collection Efficiency-Eastern | C52: =Dashboard!C51 -> % | D52: 1.05 | E52: 1.05 | F52: 1.05 | G52: 1.05 | H52: 1.05 | I52: 1.05 | J52: 1.05 | K52: 1.05 | L52: 1.05 | M52: 1.05 | N52: 1.05 | O52: 1.05
A53: =Dashboard!A52 -> 19 | B53: =Dashboard!B59 -> 0 | C53: =Dashboard!C59 -> 0
A54: =Dashboard!A53 -> 0 | B54: =Dashboard!B53 -> AMOUNT RECEIVABLES | C54: =Dashboard!C62 -> 0
A55: =Dashboard!A54 -> 20 | B55: =Dashboard!B54 -> Amount receivables as at close of the month | C55: =Dashboard!C63 -> 0
A56: =Dashboard!A55 -> 21 | B56: =Dashboard!B55 -> Adjustment done for the month | C56: =Dashboard!C55 -> Ksh. | D56: =D55*0.95 -> 0 | E56: =E55*0.95 -> 0 | F56: =F55*0.95 -> 0 | G56: =G55*0.95 -> 0 | H56: =H55*0.95 -> 0 | I56: =I55*0.95 -> 0 | J56: =J55*0.95 -> 0 | K56: =K55*0.95 -> 0 | ... O56: =O55*0.95 -> 0
A57: =Dashboard!A56 -> 0 | B57: =Dashboard!B56 -> 0 | C57: =Dashboard!C65 -> 0
A58: =Dashboard!A57 -> 0 | B58: =Dashboard!B57 -> 0 | C58: =Dashboard!C66 -> 0
A59: =Dashboard!A58 -> 0 | B59: =Dashboard!B58 -> 0 | C59: =Dashboard!C67 -> 0
A60: =Dashboard!A59 -> 0 | B60: =Dashboard!B68 -> 0 | C60: =Dashboard!C68 -> 0
A61: =Dashboard!A60 -> 0 | B61: =Dashboard!B69 -> 0 | C61: =Dashboard!C69 -> 0
A62: =Dashboard!A70 -> 0 | B62: =Dashboard!B70 -> 0 | C62: =Dashboard!C70 -> 0
A63: =Dashboard!A71 -> 0 | B63: =Dashboard!B71 -> 0 | C63: =Dashboard!C71 -> 0
A64: =Dashboard!A72 -> 0 | B64: =Dashboard!B72 -> 0 | C64: =Dashboard!C72 -> 0

Sheet ACTUAL 2526
A1: =Dashboard!A1 -> FINANCE DASHBOARD
B4: MONTH | C4: UNIT | E4: JUL | F4: AUG | G4: SEP | H4: OCT | I4: NOV | J4: DEC | K4: JAN | L4: FEB | M4: MAR | N4: APR | O4: MAY | P4: JUN
A5: =Dashboard!A5 -> BILLING DASHBOARD - SUMMARY
A6: =Dashboard!A6 -> 1 | B6: =Dashboard!B6 -> Total Water Sales (Ksh) | C6: =Dashboard!C6 -> Ksh | E6: 18389070 | F6: 22070060 | G6: =18397090+440 -> 18397530 | H6: 21684080 | I6: =17026640+10140 -> 17036780 | J6: 16441310 | K6: 25608070 | L6: 21831150 | M6: 18351480
A7: =Dashboard!A7 -> 2 | B7: =Dashboard!B7 -> Total Sewerage Sales (Ksh) | C7: =Dashboard!C7 -> Ksh | E7: 5703321 | F7: 6046366 | G7: =5665420.8+55465.2-350 -> 5720536 | H7: 5831421 | I7: =5336003.5+7130 -> 5343133.5 | J7: 4905403.8 | K7: 6958143.5 | L7: 5826591 | M7: 5950166
A8: =Dashboard!A8 -> 3 | B8: =Dashboard!B8 -> Bulk water | C8: =Dashboard!C8 -> Ksh | E8: 185510 | F8: 166400 | G8: 165100 | H8: 164840 | I8: 126750 | J8: 122200 | K8: 46020 | L8: 88920 | M8: 30290
C9: =Dashboard!C9 -> Ksh
A10: =Dashboard!A9 -> 4 | B10: =Dashboard!B9 -> Sanitation | C10: =Dashboard!C10 -> Ksh | E10: 919453.5 | F10: 1103503 | G10: =919854.5+22 -> 919876.5 | H10: 1084204 | I10: =851332+507 -> 851839 | J10: 822065.5 | K10: 1280403.5 | L10: 1091557.5 | M10: 917568.5
A11: =Dashboard!A10 -> 5 | B11: =Dashboard!B10 -> new connection fee water | C11: =Dashboard!C11 -> Ksh | E11: 385000 | F11: 455000 | G11: 345000 | H11: 422500 | I11: 255000 | J11: 360000 | K11: 440000 | L11: 192500 | M11: 147500
A12: =Dashboard!A11 -> 6 | B12: =Dashboard!B11 -> new connection fee sewer | C12: =Dashboard!C12 -> Ksh | E12: 0 | F12: 22500 | G12: 22500 | H12: 20000 | I12: 27500 | J12: 0 | K12: 22500 | L12: 27500 | M12: 0
A13: =Dashboard!A12 -> 7 | B13: =Dashboard!B12 -> reconnection fee (water+sewer) | C13: =Dashboard!C13 -> Ksh | E13: 165000 | F13: 261500 | G13: 120500 | H13: 67500 | I13: 114000 | J13: 101000 | K13: 162000 | L13: 186000 | M13: 157500
A14: =Dashboard!A13 -> 8 | B14: =Dashboard!B13 -> Prepaid kiosk | C14: =Dashboard!C8 -> Ksh | E14: 78800 | F14: 82100 | G14: 74600 | H14: 84300 | I14: 67100 | J14: 62600 | K14: 116200 | L14: 81000 | M14: 61500
A15: =Dashboard!A14 -> 9 | B15: =Dashboard!B14 -> misc income-printing fee,CA,meter replacement fee,meter testing | C15: =Dashboard!C10 -> Ksh | E15: 115100 | F15: 30900 | G15: 49000 | H15: 44200 | I15: 68950 | J15: 21500 | K15: =90200-K16 -> 57700 | L15: 76800 | M15: 2454300
A16: =Dashboard!A15 -> 10 | B16: =Dashboard!B15 -> sewer unblocking fee | C16: =Dashboard!C11 -> Ksh | E16: 2500 | F16: 5000 | G16: 5000 | H16: 0 | I16: 0 | J16: 0 | K16: 32500 | L16: 0 | M16: 0
A17: =Dashboard!A16 -> 11 | B17: =Dashboard!B16 -> penalties (water+sewer) | C17: =Dashboard!C12 -> Ksh | E17: 40000 | F17: 0 | G17: 280000 | H17: 90000 | I17: 0 | J17: 0 | K17: 285000 | L17: 15000 | M17: 155000
A18: =Dashboard!#REF! -> #REF! | B18: =Dashboard!#REF! -> #REF! | C18: =Dashboard!C13 -> Ksh
A19: =Dashboard!A17 -> 12 | B19: =Dashboard!B17 -> Company exhauster | C19: =Dashboard!C14 -> Ksh | E19: 0 | F19: 0 | I19: 0 | J19: 0 | K19: 0 | L19: 0 | M19: 0
A20: =Dashboard!A18 -> 12 | B20: =Dashboard!B18 -> Customer exhauster | C20: =Dashboard!C15 -> Ksh | E20: 180000 | F20: 180000 | G20: 210000 | H20: 210000 | I20: 195000 | J20: 195000 | K20: 210000 | L20: 210000 | M20: 180000
A21: =Dashboard!A19 -> 13 | B21: =Dashboard!B19 -> Total billed (Ksh) | C21: =Dashboard!C17 -> Ksh | D21: ='Actual 202425'!P21 -> 28905832 | E21: =SUM(E6:E20)-(E14+E8) -> 25899444 | F21: =SUM(F6:F20)-(F14+F8) -> 30174829 | G21: =SUM(G6:G20)-(G14+G8) -> 26069942 | H21: =SUM(H6:H20)-(H14+H8) -> 29453905 | I21: =SUM(I6:I20)-(I14+I8) -> 23892202 | J21: =SUM(J6:J20)-(J14+J8) -> 22846279 | K21: =SUM(K6:K20)-(K14+K8) -> 35056317 | L21: =SUM(L6:L20)-(L14+L8) -> 29457098 | ... P21: =SUM(P6:P20)-(P14+P8) -> 0
A22: =Dashboard!A20 -> 0 | B22: =Dashboard!B20 -> 0 | C22: =Dashboard!C18 -> Ksh
A23: =Dashboard!A21 -> A | B23: =Dashboard!B21 -> Eastern Region | C23: =Dashboard!C21 -> DATE | E23: 9TH | F23: 12th | G23: 8th | H23: 9TH | I23: 13TH | J23: 12TH | K23: 15TH | L23: 10TH | M23: 10TH
A24: =Dashboard!A22 -> B | B24: =Dashboard!B22 -> Southern Region | C24: =Dashboard!C22 -> DATE | E24: 17TH | F24: 15th | G24: 15th | H24: 22nd | I24: 18TH | J24: 23RD | K24: 30TH | L24: 25TH | M24: 24TH
A25: =Dashboard!A23 -> C | B25: =Dashboard!B23 -> Central Region | C25: =Dashboard!C23 -> DATE | E25: 31ST | F25: 30th | G25: 29th | H25: 31st | I25: 28TH | J25: 23RD | K25: 30TH | L25: 27TH | M25: 31ST
A26: =Dashboard!A24 -> COLLECTION EFFICIENCY | B26: =Dashboard!B24 -> 0 | C26: =Dashboard!C20 -> 0
A27: =Dashboard!A25 -> D | B27: =Dashboard!B25 -> Total accounts disconnected-water | C27: =Dashboard!C25 -> NO | E27: 152 | F27: 229 | G27: 112 | H27: 42 | I27: 99 | J27: 101 | K27: 142 | L27: 133 | M27: 148
A28: =Dashboard!A26 -> E | B28: =Dashboard!B26 -> Total accounts disconnected-sewer | C28: =Dashboard!C26 -> NO | E28: 6 | F28: 3 | G28: 3 | H28: 1 | I28: 2 | J28: 0 | K28: 0 | L28: 14 | M28: 1
A29: =Dashboard!A27 -> 14 | B29: =Dashboard!B27 -> Total Collection for the month | C29: =Dashboard!C27 -> Ksh | E29: 25396691 | F29: 22000368 | G29: 23442340 | H29: 29982819 | I29: 22433751 | J29: 27037162 | K29: 24586578 | L29: 27713797 | M29: 31993098
A30: =Dashboard!A28 -> 7 | B30: =Dashboard!B28 -> Total Collection- Related Sales | C30: =Dashboard!C18 -> Ksh
A31: =Dashboard!A29 -> 15 | B31: =Dashboard!B29 -> Collection Efficiency - in % of billing | E31: =E29/D21 -> 0.87860095 | F31: =F29/E21 -> 0.84945328 | G31: =G29/F21 -> 0.77688392 | H31: =H29/G21 -> 1.1500915 | I31: =I29/H21 -> 0.76165626 | J31: =J29/I21 -> 1.1316312 | K31: =K29/J21 -> 1.0761743 | L31: =L29/K21 -> 0.79055073 | ... P31: =P29/O21 -> #DIV/0!
A32: =Dashboard!A31 -> CENTRAL REGION: CBD,CCCR,KABATI,SITE,KIHOTO,LAKEVIEW,HOPEWELL
A33: =Dashboard!A32 -> 16a | B33: =Dashboard!B32 -> Amount Billed Water-Central | C33: =Dashboard!C32 -> Ksh. | E33: 9210800 | F33: 10871060 | G33: 10150080 | H33: 11059010 | I33: =9178550+10140 -> 9188690 | J33: 8043560 | K33: 13738330 | L33: 10720550 | M33: 10195970
A34: =Dashboard!A33 -> 17a | B34: =Dashboard!B33 -> Amount Billed Sewer-Central | C34: =Dashboard!C33 -> Ksh. | E34: 5560946 | F34: 5918138.5 | G34: =5553915.8+55465.2-350 -> 5609031 | H34: 5721311 | I34: =5236748.5+7130 -> 5243878.5 | J34: 4788131.3 | K34: 6824426 | L34: 5693803.5 | M34: 5821018.5
A35: =Dashboard!A34 -> 18a | B35: =Dashboard!B34 -> othersales | C35: =Dashboard!C34 -> Ksh. | E35: 871940 | F35: 904453 | G35: 904154 | H35: 1010650.5 | I35: =811077.5+507 -> 811584.5 | J35: 696178 | K35: 1284916.5 | L35: 922827.5 | M35: 509798.5
A36: =Dashboard!A35 -> 19a | B36: =Dashboard!B35 -> Amount Billed Water & Sewer-othersales-Central | C36: =Dashboard!C35 -> Ksh. | D36: ='Actual 202425'!P36 -> 18208520 | E36: =E33+E34+E35 -> 15643686 | F36: =F33+F34+F35 -> 17693652 | G36: =G33+G34+G35 -> 16663265 | H36: =H33+H34+H35 -> 17790972 | I36: =I33+I34+I35 -> 15244153 | J36: =J33+J34+J35 -> 13527869 | K36: =K33+K34+K35 -> 21847672 | L36: =L33+L34+L35 -> 17337181 | ... P36: =P33+P34+P35 -> 0
A37: =Dashboard!A36 -> 14a | B37: =Dashboard!B36 -> Amount Collected-Central | C37: =Dashboard!C36 -> Ksh. | E37: 15973822 | F37: 13044625 | G37: 14430304 | H37: =19726476.6+15000 -> 19741477 | I37: 14374630 | J37: 18112068 | K37: 13052148 | L37: 16563178 | M37: 22532132
A38: =Dashboard!A37 -> 15a | B38: =Dashboard!B37 -> Collection Efficiency-Central | C38: =Dashboard!C37 -> % | E38: =E37/D36 -> 0.87727187 | F38: =F37/E36 -> 0.83385878 | G38: =G37/F36 -> 0.81556393 | H38: =H37/G36 -> 1.1847304 | I38: =I37/H36 -> 0.80797333 | J38: =J37/I36 -> 1.1881322 | K38: =K37/J36 -> 0.96483394 | L38: =L37/K36 -> 0.75812092 | ... P38: =P37/O36 -> #DIV/0!
A39: =Dashboard!A38 -> SOUTHERN REGION: HELLSGATE,KAMERE, MAI MAHIU,LONGONOT
A40: =Dashboard!A39 -> 16b | B40: =Dashboard!B39 -> Amount Billed Water-Southern | C40: =Dashboard!C39 -> Ksh. | E40: 5272370 | F40: 7465830 | G40: 5039430 | H40: 7076450 | I40: 4791020 | J40: 5179850 | K40: 8044460 | L40: 6986830 | M40: 4890400
A41: =Dashboard!A40 -> 17b | B41: =Dashboard!B40 -> Amount Billed Sewer-Southern | C41: =Dashboard!C40 -> Ksh. | E41: 0 | F41: 0 | G41: 0 | H41: 0 | I41: 0 | J41: 0 | K41: 0 | L41: 0 | M41: 0
A42: =Dashboard!A41 -> 18b | B42: =Dashboard!B41 -> othersales | C42: =Dashboard!C41 -> Ksh. | E42: 630818.5 | F42: 696791.5 | G42: 547121.5 | H42: 633322.5 | I42: 416851 | J42: 500992.5 | K42: 746723 | L42: 529341.5 | M42: 244520
A43: =Dashboard!A42 -> 19b | B43: =Dashboard!B42 -> Amount Billed Water & Sewer-OTHER SALES-Southern | C43: =Dashboard!C42 -> Ksh. | D43: ='Actual 202425'!P43 -> 6466178 | E43: =E40+E41+E42 -> 5903188.5 | F43: =F40+F41+F42 -> 8162621.5 | G43: =G40+G41+G42 -> 5586551.5 | H43: =H40+H41+H42 -> 7709772.5 | I43: =I40+I41+I42 -> 5207871 | J43: =J40+J41+J42 -> 5680842.5 | K43: =K40+K41+K42 -> 8791183 | L43: =L40+L41+L42 -> 7516171.5 | ... P43: =P40+P41+P42 -> 0
A44: =Dashboard!A43 -> 14b | B44: =Dashboard!B43 -> Amount Collected-Southern | C44: =Dashboard!C43 -> Ksh. | E44: 5499282 | F44: 5319028.5 | G44: 5187417.5 | H44: 6761835 | I44: 4609313.5 | J44: 5790037 | K44: 7645137.5 | L44: 6841496 | M44: 5621150.5
A45: =Dashboard!A44 -> 15b | B45: =Dashboard!B44 -> Collection Efficiency-Southern | C45: =Dashboard!C44 -> % | E45: =E44/D43 -> 0.8504687 | F45: =F44/E43 -> 0.90104331 | G45: =G44/F43 -> 0.63550876 | H45: =H44/G43 -> 1.2103773 | I45: =I44/H43 -> 0.59785337 | J45: =J44/I43 -> 1.1117858 | K45: =K44/J43 -> 1.3457753 | L45: =L44/K43 -> 0.77822245 | ... P45: =P44/O43 -> #DIV/0!
A46: =Dashboard!A45 -> EASTERN REGION: KAYOLE,GONDI,KINUNGI,NJONJORO,IHINDU | B46: =Dashboard!B45 -> 0 | C46: =Dashboard!C45 -> 0
A47: =Dashboard!A46 -> 16c | B47: =Dashboard!B46 -> Amount Billed Water-Eastern | C47: =Dashboard!C46 -> Ksh. | E47: 3905900 | F47: 3733170 | G47: 3207580 | H47: =3548620+440 -> 3549060 | I47: 3057070 | J47: 3217900 | K47: 3825280 | L47: 4123770 | M47: 3265000
A48: =Dashboard!A47 -> 17c | B48: =Dashboard!B47 -> Amount Billed Sewer-Eastern | C48: =Dashboard!C47 -> Ksh. | E48: 142375 | F48: 128227.5 | G48: 111505 | H48: 110110 | I48: 99255 | J48: 117272.5 | K48: 133717.5 | L48: 132787.5 | M48: 112697.5
A49: =Dashboard!A48 -> 18c | B49: =Dashboard!B48 -> othersales | C49: =Dashboard!C48 -> Ksh. | E49: 304295 | F49: 457158.5 | G49: =500579+22 -> 500601 | H49: 294431 | I49: 283853.5 | J49: 302395 | K49: 458464 | L49: 347188.5 | M49: 163250
A50: =Dashboard!A49 -> 19b | B50: =Dashboard!B49 -> Amount Billed Water & Sewer-othersales-Eastern | C50: =Dashboard!C49 -> Ksh. | D50: ='Actual 202425'!P50 -> 4231134 | E50: =E47+E48+E49 -> 4352570 | F50: =F47+F48+F49 -> 4318556 | G50: =G47+G48+G49 -> 3819686 | H50: =H47+H48+H49 -> 3953601 | I50: =I47+I48+I49 -> 3440178.5 | J50: =J47+J48+J49 -> 3637567.5 | K50: =K47+K48+K49 -> 4417461.5 | L50: =L47+L48+L49 -> 4603746 | ... P50: =P47+P48+P49 -> 0
A51: =Dashboard!A50 -> 14c | B51: =Dashboard!B50 -> Amount Collected-Eastern | C51: =Dashboard!C50 -> Ksh. | E51: 3923587 | F51: 3636715 | G51: 3824618 | H51: 3479507 | I51: 3449807 | J51: 3135057 | K51: 3889293.5 | L51: 4309123.5 | M51: 3839815
A52: =Dashboard!A51 -> 15c | B52: =Dashboard!B51 -> Collection Efficiency-Eastern | C52: =Dashboard!C51 -> % | E52: =E51/D50 -> 0.92731334 | F52: =F51/E50 -> 0.8355328 | G52: =G51/F50 -> 0.88562427 | H52: =H51/G50 -> 0.91094059 | I52: =I51/H50 -> 0.87257338 | J52: =J51/I50 -> 0.91130649 | K52: =K51/J50 -> 1.0692017 | L52: =L51/K50 -> 0.97547506 | ... P52: =P51/O50 -> #DIV/0!
A53: =Dashboard!A52 -> 19 | B53: =Dashboard!B59 -> 0 | C53: =Dashboard!C59 -> 0 | E53: =E52/ACTUAL2122!O47 -> #DIV/0! | F53: =F52/E51 -> 2.1295126e-07 | G53: =G52/F51 -> 2.4352314e-07 | H53: =H52/G51 -> 2.3817819e-07 | I53: =I52/H51 -> 2.50775e-07 | J53: =J52/I51 -> 2.6416159e-07 | K53: =K52/J51 -> 3.4104699e-07 | L53: =L52/K51 -> 2.5081035e-07 | M53: =M52/L51 -> 1.935575e-07 | ... P53: =P52/O51 -> #DIV/0!
A54: =Dashboard!A53 -> 0 | B54: =Dashboard!B53 -> AMOUNT RECEIVABLES | C54: =Dashboard!C62 -> 0
A55: =Dashboard!A54 -> 20 | B55: =Dashboard!B54 -> Amount receivables as at close of the month | C55: =Dashboard!C63 -> 0 | E55: 1.8809427e+08 | F55: 1.9657455e+08 | G55: 198769120 | H55: 1.9902173e+08 | I55: 2.0037734e+08 | J55: 196285940 | K55: 2.0665322e+08 | L55: 2.0837078e+08 | M55: 205010129
A56: =Dashboard!A55 -> 21 | B56: =Dashboard!B55 -> Adjustment done for the month | C56: =Dashboard!C55 -> Ksh. | E56: 0 | F56: -11881 | G56: -388037 | H56: 31990.5 | I56: 3831 | J56: 0 | K56: -2061 | L56: -7836.25 | M56: 90000
A57: =Dashboard!A56 -> 0 | B57: =Dashboard!B56 -> 0 | C57: =Dashboard!C65 -> 0
A58: =Dashboard!A57 -> 0 | B58: =Dashboard!B57 -> 0 | C58: =Dashboard!C66 -> 0
A59: =Dashboard!A58 -> 0 | B59: =Dashboard!B58 -> 0 | C59: =Dashboard!C67 -> 0
A60: =Dashboard!A59 -> 0 | B60: =Dashboard!B68 -> 0 | C60: =Dashboard!C68 -> 0
A61: =Dashboard!A69 -> 0 | B61: =Dashboard!B69 -> 0 | C61: =Dashboard!C69 -> 0
A62: =Dashboard!A70 -> 0 | B62: =Dashboard!B70 -> 0 | C62: =Dashboard!C70 -> 0
A63: =Dashboard!A71 -> 0 | B63: =Dashboard!B71 -> 0 | C63: =Dashboard!C71 -> 0
A64: =Dashboard!A72 -> 0 | B64: =Dashboard!B72 -> 0 | C64: =Dashboard!C72 -> 0

Sheet Actual 202425
A1: =Dashboard!A1 -> FINANCE DASHBOARD
B4: MONTH | C4: UNIT | E4: JUL | F4: AUG | G4: SEP | H4: OCT | I4: NOV | J4: DEC | K4: JAN | L4: FEB | M4: MAR | N4: APR | O4: MAY | P4: JUN
A5: =Dashboard!A5 -> BILLING DASHBOARD - SUMMARY
A6: =Dashboard!A6 -> 1 | B6: =Dashboard!B6 -> Total Water Sales (Ksh) | C6: =Dashboard!C6 -> Ksh | E6: 11183420 | F6: 13918957 | G6: 13018249 | H6: 12608519 | I6: 14174994 | J6: 8977679 | K6: 14767948 | L6: 13060906 | M6: 13951180 | N6: 13956857 | O6: 19515330 | P6: 20899160
A7: =Dashboard!A7 -> 2 | B7: =Dashboard!B7 -> Total Sewerage Sales (Ksh) | C7: =Dashboard!C7 -> Ksh | E7: 4109000.4 | F7: 5060354.7 | G7: 4299927.7 | H7: 4437132.7 | I7: 4483043.5 | J7: 3764102.7 | K7: =5424626.2+350 -> 5424976.2 | L7: 4666903.2 | M7: 4963782.5 | N7: 5710578.7 | O7: 6133011 | P7: 6224363.5
A8: =Dashboard!A8 -> 3 | B8: =Dashboard!B8 -> Bulk water | E8: 22320 | F8: 28370 | G8: 64720 | H8: 22800 | I8: 40480 | J8: 25520 | K8: 51520 | L8: 59520 | M8: 104400 | N8: 73540 | O8: 63440 | P8: 165230
A9: =Dashboard!#REF! -> #REF! | B9: =Dashboard!#REF! -> #REF! | E9: 491000 | F9: 494150 | G9: 496750 | H9: 498550 | I9: 498350 | J9: 501650 | K9: =502600+800 -> 503400 | L9: 507750 | M9: 510500 | N9: 281750 | O9: 0 | P9: 0
A10: =Dashboard!A9 -> 4 | B10: =Dashboard!B9 -> Sanitation | N10: 456894.5 | O10: 975766.5 | P10: 1044958
A11: =Dashboard!A10 -> 5 | B11: =Dashboard!B10 -> new connection fee water | E11: 327500 | F11: 172500 | G11: 90000 | H11: 35000 | I11: 102500 | J11: 145000 | K11: 377500 | L11: 225000 | M11: 245000 | N11: 417500 | O11: 187500 | P11: 265000
A12: =Dashboard!A11 -> 6 | B12: =Dashboard!B11 -> new connection fee sewer | E12: 50000 | F12: 30000 | G12: 37500 | H12: 12500 | I12: 0 | J12: 25000 | K12: 10500 | L12: 60000 | M12: 22500 | N12: 17500 | O12: 0 | P12: 20000
A13: =Dashboard!A12 -> 7 | B13: =Dashboard!B12 -> reconnection fee (water+sewer) | E13: 714000 | F13: 279000 | G13: 192500 | H13: 270000 | I13: 176500 | J13: =150500+4500 -> 155000 | K13: 268500 | L13: 165000 | M13: 243500 | N13: 122500 | O13: 151000 | P13: 127000
A14: =Dashboard!A13 -> 8 | B14: =Dashboard!B13 -> Prepaid kiosk | C14: =Dashboard!C8 -> Ksh | E14: 77900 | F14: 100000 | G14: 107100 | H14: 99700 | I14: 100900 | J14: 57800 | K14: 124500 | L14: 96800 | M14: 100800 | N14: 67500 | O14: 86800 | P14: 124600
A15: =Dashboard!A14 -> 9 | B15: =Dashboard!B14 -> misc income-printing fee,CA,meter replacement fee,meter testing | C15: =Dashboard!C10 -> Ksh | E15: 75850 | F15: 51400 | G15: 133100 | H15: 165000 | I15: 46900 | J15: 80800 | K15: 147500 | L15: 100950 | M15: 163400 | N15: 295950 | O15: 143650 | P15: 90350
A16: =Dashboard!A15 -> 10 | B16: =Dashboard!B15 -> sewer unblocking fee | C16: =Dashboard!C11 -> Ksh | J16: 2500 | O16: 2500
A17: =Dashboard!A16 -> 11 | B17: =Dashboard!B16 -> penalties (water+sewer) | C17: =Dashboard!C12 -> Ksh | E17: 87556 | F17: 16152 | G17: 55750 | H17: 51350 | I17: 0 | K17: 39580 | L17: 7592 | M17: 30000 | N17: 285362 | O17: 40000 | P17: 10000
A18: =Dashboard!#REF! -> #REF! | B18: =Dashboard!#REF! -> #REF! | C18: =Dashboard!C13 -> Ksh
A19: =Dashboard!A17 -> 12 | B19: =Dashboard!B17 -> Company exhauster | C19: =Dashboard!C14 -> Ksh | E19: 0 | F19: 0 | G19: 0
A20: =Dashboard!A18 -> 12 | B20: =Dashboard!B18 -> Customer exhauster | C20: =Dashboard!C15 -> Ksh | E20: 135000 | F20: 135000 | G20: 135000 | H20: 135000 | I20: 135000 | J20: 135000 | K20: 135000 | L20: 165000 | M20: 217500 | N20: 195000 | O20: 195000 | P20: 225000
A21: =Dashboard!A19 -> 13 | B21: =Dashboard!B19 -> Total billed (Ksh) | C21: =Dashboard!C17 -> Ksh | D21: 17945234 | E21: =SUM(E6:E20)-(E14+E8) -> 17173326 | F21: =SUM(F6:F20)-(F14+F8) -> 20157514 | G21: =SUM(G6:G20)-(G14+G8) -> 18458777 | H21: =SUM(H6:H20)-(H14+H8) -> 18213052 | I21: =SUM(I6:I20)-(I14+I8) -> 19617288 | J21: =SUM(J6:J20)-(J14+J8) -> 13786732 | K21: =SUM(K6:K20)-(K14+K8) -> 21674904 | L21: =SUM(L6:L20)-(L14+L8) -> 18959101 | ... P21: =SUM(P6:P20)-(P14+P8) -> 28905832
A22: =Dashboard!A20 -> 0 | B22: =Dashboard!B20 -> 0 | C22: =Dashboard!C18 -> Ksh
A23: =Dashboard!A21 -> A | B23: =Dashboard!B21 -> Eastern Region | C23: =Dashboard!#REF! -> #REF! | E23: 12th &15th | F23: 14th | G23: 12th | H23: 7th | I23: 14th | J23: 11th | K23: 6th | L23: 7th | M23: 14th | N23: 14th | O23: 13th | P23: 19th
A24: =Dashboard!A22 -> B | B24: =Dashboard!B22 -> Southern Region | C24: =Dashboard!#REF! -> #REF! | E24: 15th | F24: 16th | G24: 17th | H24: 15th | I24: 15th | J24: 11th | K24: 20th | L24: 17th | M24: 20th | N24: 19th | O24: 16th | P24: 23rd
A25: =Dashboard!A23 -> C | B25: =Dashboard!B23 -> Central Region | C25: =Dashboard!C19 -> Ksh | E25: 31st | F25: 30th | G25: 30th | H25: 31st | I25: 29th | J25: 20th | K25: 29th | L25: 28th | M25: 30th | N25: 30th | O25: 29th | P25: 30th
A26: =Dashboard!A24 -> COLLECTION EFFICIENCY | B26: =Dashboard!B24 -> 0 | C26: =Dashboard!C20 -> 0
A27: =Dashboard!A25 -> D | B27: =Dashboard!B25 -> Total accounts disconnected-water | C27: =Dashboard!C21 -> DATE | E27: 606 | F27: 270 | G27: 119 | H27: 172 | I27: 166 | J27: 149 | K27: 197 | L27: 144 | M27: 227 | N27: 111 | O27: 123 | P27: 111
A28: =Dashboard!A26 -> E | B28: =Dashboard!B26 -> Total accounts disconnected-sewer | C28: =Dashboard!C16 -> Ksh | E28: 72 | F28: 2 | G28: 20 | H28: 44 | I28: 7 | J28: 4 | K28: 13 | L28: 14 | M28: 3 | N28: 5 | O28: 0 | P28: 0
A29: =Dashboard!A27 -> 14 | B29: =Dashboard!B27 -> Total Collection for the month | C29: =Dashboard!C17 -> Ksh | E29: 22802982 | F29: 15064900 | G29: 17788417 | H29: 18047891 | I29: 20883741 | J29: 15030214 | K29: 21271032 | L29: 18078019 | M29: 16601930 | N29: 23335361 | O29: 22039395 | P29: 28927934
A30: =Dashboard!A28 -> 7 | B30: =Dashboard!B28 -> Total Collection- Related Sales | C30: =Dashboard!C18 -> Ksh
A31: =Dashboard!A29 -> 15 | B31: =Dashboard!B29 -> Collection Efficiency - in % of billing | E31: =E29/D21 -> 1.2706985 | F31: =F29/E21 -> 0.87722668 | G31: =G29/F21 -> 0.8824708 | H31: =H29/G21 -> 0.97774036 | I31: =I29/H21 -> 1.146636 | J31: =J29/I21 -> 0.76617189 | K31: =K29/J21 -> 1.5428625 | L31: =L29/K21 -> 0.83405302 | ... P31: =P29/O21 -> 1.0579356
A32: =Dashboard!A31 -> CENTRAL REGION: CBD,CCCR,KABATI,SITE,KIHOTO,LAKEVIEW,HOPEWELL
A33: =Dashboard!A32 -> 16a | B33: =Dashboard!B32 -> Amount Billed Water-Central | C33: =Dashboard!C32 -> Ksh. | E33: 5843053 | F33: 7922759 | G33: 6574586 | H33: 6654857 | I33: 7074189 | J33: 4685457 | K33: 8536944 | L33: 7146065 | M33: 7724897 | N33: 9123070 | O33: 10708050 | P33: 11093770
A34: =Dashboard!A33 -> 17a | B34: =Dashboard!B33 -> Amount Billed Sewer-Central | C34: =Dashboard!C33 -> Ksh. | E34: 4056872.9 | F34: =4997329.65-1417.5 -> 4995912.2 | G34: 4239319.5 | H34: 4378066.2 | I34: 4413150 | J34: 3714209.2 | K34: =5355862.7+350 -> 5356212.7 | L34: 4592749 | M34: 4885077 | N34: 5635043.5 | O34: 6022758.5 | P34: 6114211
A35: =Dashboard!A34 -> 18a | B35: =Dashboard!B34 -> othersales | C35: =Dashboard!C34 -> Ksh. | E35: 794951 | F35: =491850+135000 -> 626850 | G35: 607950 | H35: 713100 | I35: 489600 | J35: 523900 | K35: =703980+800 -> 704780 | L35: 670850 | M35: 755350 | N35: 1189107.5 | O35: 1026152.5 | P35: 1000538.5
A36: =Dashboard!A35 -> 19a | B36: =Dashboard!B35 -> Amount Billed Water & Sewer-othersales-Central | C36: =Dashboard!C35 -> Ksh. | D36: 12356391 | E36: =E33+E34+E35 -> 10694877 | F36: =F33+F34+F35 -> 13545521 | G36: =G33+G34+G35 -> 11421855 | H36: =H33+H34+H35 -> 11746023 | I36: =I33+I34+I35 -> 11976939 | J36: =J33+J34+J35 -> 8923566.2 | K36: =K33+K34+K35 -> 14597937 | L36: =L33+L34+L35 -> 12409664 | ... P36: =P33+P34+P35 -> 18208520
A37: =Dashboard!A36 -> 14a | B37: =Dashboard!B36 -> Amount Collected-Central | C37: =Dashboard!C36 -> Ksh. | E37: 15577991 | F37: 8917003.1 | G37: 11509367 | H37: 11550709 | I37: 15277870 | J37: 9681321.2 | K37: 14304090 | L37: 12007999 | M37: 10866768 | N37: 16977535 | O37: 15080180 | P37: 19747968
A38: =Dashboard!A37 -> 15a | B38: =Dashboard!B37 -> Collection Efficiency-Central | C38: =Dashboard!C37 -> % | E38: =E37/D36 -> 1.2607234 | F38: =F37/E36 -> 0.83376397 | G38: =G37/F36 -> 0.84968065 | H38: =H37/G36 -> 1.0112813 | I38: =I37/H36 -> 1.3006845 | J38: =J37/I36 -> 0.80833018 | K38: =K37/J36 -> 1.6029566 | L38: =L37/K36 -> 0.82258194 | ... P38: =P37/O36 -> 1.1121254
A39: =Dashboard!A38 -> SOUTHERN REGION: HELLSGATE,KAMERE, MAI MAHIU,LONGONOT
A40: =Dashboard!A39 -> 16b | B40: =Dashboard!B39 -> Amount Billed Water-Southern | C40: =Dashboard!C39 -> Ksh. | E40: 3209469 | F40: 3501347 | G40: 3856856 | H40: 3641147 | I40: 4692660 | J40: 2552870 | K40: 4084599 | L40: 3854228 | M40: 4053585 | N40: 2884277 | O40: 5352660 | P40: 5996360
A41: =Dashboard!A40 -> 17b | B41: =Dashboard!B40 -> Amount Billed Sewer-Southern | C41: =Dashboard!C40 -> Ksh. | E41: 0
A42: =Dashboard!A41 -> 18b | B42: =Dashboard!B41 -> othersales | C42: =Dashboard!C41 -> Ksh. | E42: 467850 | F42: 324100 | G42: 254600 | H42: 227600 | I42: 234950 | J42: 338950 | K42: 495150 | L42: 284992 | M42: 370600 | N42: 539558 | O42: 443033 | P42: 469818
A43: =Dashboard!A42 -> 19b | B43: =Dashboard!B42 -> Amount Billed Water & Sewer-OTHER SALES-Southern | C43: =Dashboard!C42 -> Ksh. | D43: 2754668 | E43: =E40+E41+E42 -> 3677319 | F43: =F40+F41+F42 -> 3825447 | G43: =G40+G41+G42 -> 4111456 | H43: =H40+H41+H42 -> 3868747 | I43: =I40+I41+I42 -> 4927610 | J43: =J40+J41+J42 -> 2891820 | K43: =K40+K41+K42 -> 4579749 | L43: =L40+L41+L42 -> 4139220 | ... P43: =P40+P41+P42 -> 6466178
A44: =Dashboard!A43 -> 14b | B44: =Dashboard!B43 -> Amount Collected-Southern | C44: =Dashboard!C43 -> Ksh. | E44: 3822073 | F44: 3616206 | G44: 3523424 | H44: 3774178 | I44: 3221254 | J44: 3119877 | K44: 4367599 | L44: 3868317.2 | M44: 3550532 | N44: 3717078 | O44: 4107749.5 | P44: 5385918
A45: =Dashboard!A44 -> 15b | B45: =Dashboard!B44 -> Collection Efficiency-Southern | C45: =Dashboard!C44 -> % | E45: =E44/D43 -> 1.3874895 | F45: =F44/E43 -> 0.9833811 | G45: =G44/F43 -> 0.92104896 | H45: =H44/G43 -> 0.91796629 | I45: =I44/H43 -> 0.83263496 | J45: =J44/I43 -> 0.63314203 | K45: =K44/J43 -> 1.5103288 | L45: =L44/K43 -> 0.84465704 | ... P45: =P44/O43 -> 0.92929663
A46: =Dashboard!A45 -> EASTERN REGION: KAYOLE,GONDI,KINUNGI,NJONJORO,IHINDU | B46: =Dashboard!B45 -> 0 | C46: =Dashboard!C45 -> 0
A47: =Dashboard!A46 -> 16c | B47: =Dashboard!B46 -> Amount Billed Water-Eastern | C47: =Dashboard!C46 -> Ksh. | E47: 2130898 | F47: 2494851 | G47: 2586807 | H47: 2312515 | I47: 2408145 | J47: 1739352 | K47: 2146405 | L47: 2060613 | M47: 2172698 | N47: 1949510 | O47: 3454620 | P47: 3809030
A48: =Dashboard!A47 -> 17c | B48: =Dashboard!B47 -> Amount Billed Sewer-Eastern | C48: =Dashboard!C47 -> Ksh. | E48: 52477.5 | F48: 64442.5 | G48: 60608.25 | H48: 59066.5 | I48: 69893.5 | J48: 49893.5 | K48: 68763.5 | L48: 74154.25 | M48: 78705.5 | N48: 75535.25 | O48: 110252.5 | P48: 110152.5
A49: =Dashboard!A48 -> 18c | B49: =Dashboard!B48 -> othersales | C49: =Dashboard!C48 -> Ksh. | E49: 603155 | F49: 229252 | G49: 246550 | H49: 226700 | I49: 234700 | J49: 177600 | K49: 282050 | L49: 275450 | M49: =246400+60050 -> 306450 | N49: 343791 | O49: 226231 | P49: 311951.5
A50: =Dashboard!A49 -> 19b | B50: =Dashboard!B49 -> Amount Billed Water & Sewer-othersales-Eastern | C50: =Dashboard!C49 -> Ksh. | D50: 2693115 | E50: =E47+E48+E49 -> 2786530.5 | F50: =F47+F48+F49 -> 2788545.5 | G50: =G47+G48+G49 -> 2893965.2 | H50: =H47+H48+H49 -> 2598281.5 | I50: =I47+I48+I49 -> 2712738.5 | J50: =J47+J48+J49 -> 1966845.5 | K50: =K47+K48+K49 -> 2497218.5 | L50: =L47+L48+L49 -> 2410217.2 | ... P50: =P47+P48+P49 -> 4231134
A51: =Dashboard!A50 -> 14c | B51: =Dashboard!B50 -> Amount Collected-Eastern | C51: =Dashboard!C50 -> Ksh. | E51: 3402918 | F51: 2531691 | G51: 2755626 | H51: 2723004 | I51: 2384617 | J51: 2229016 | K51: 2599343 | L51: 2201703 | M51: 2184630 | N51: 2640748 | O51: 2851466 | P51: 3794048
A52: =Dashboard!A51 -> 15c | B52: =Dashboard!B51 -> Collection Efficiency-Eastern | C52: =Dashboard!C51 -> % | E52: =E51/D50 -> 1.2635621 | F52: =F51/F50 -> 0.90788944 | G52: =G51/F50 -> 0.98819474 | H52: =H51/G50 -> 0.94092491 | I52: =I51/H50 -> 0.91776699 | J52: =J51/I50 -> 0.8216848 | K52: =K51/J50 -> 1.3215797 | L52: =L51/K50 -> 0.88166214 | M52: =M51/L50 -> 0.90640377 | N52: =N51/M50 -> 1.0324078 | ... P52: =P51/O50 -> 1.0007767
A53: =Dashboard!A52 -> 19 | B53: =Dashboard!B59 -> 0 | C53: =Dashboard!C59 -> 0 | E53: =E52/ACTUAL2122!O47 -> #DIV/0! | F53: =F52/E51 -> 2.6679733e-07 | G53: =G52/F51 -> 3.9032992e-07 | H53: =H52/G51 -> 3.4145596e-07 | I53: =I52/H51 -> 3.370421e-07 | J53: =J52/I51 -> 3.4457726e-07 | K53: =K52/J51 -> 5.9289824e-07 | L53: =L52/K51 -> 3.3918653e-07 | M53: =M52/L51 -> 4.1168303e-07 | ... P53: =P52/O51 -> 3.5096918e-07
A54: =Dashboard!A53 -> 0 | B54: =Dashboard!B53 -> AMOUNT RECEIVABLES | C54: =Dashboard!C62 -> 0
A55: =Dashboard!A54 -> 20 | B55: =Dashboard!B54 -> Amount receivables as at close of the month | C55: =Dashboard!C63 -> 0 | E55: 1.7313037e+08 | F55: 1.7813621e+08 | G55: 1.7860796e+08 | H55: 1.7892067e+08 | I55: 1.7882615e+08 | J55: 1.7626048e+08 | K55: 1.7674649e+08 | L55: 1.7665425e+08 | M55: 1.8333659e+08 | N55: 1.7757028e+08 | O55: 1.8703597e+08 | P55: 1.87226e+08
A56: =Dashboard!A55 -> 21 | B56: =Dashboard!B55 -> Adjustment done for the month | C56: =Dashboard!C55 -> Ksh. | E56: -148115 | F56: -141982 | G56: -89777.5 | H56: -123502 | I56: -140220.7 | J56: -348511 | K56: -198423 | L56: -664.5 | M56: -55634.8 | N56: -986702.55 | O56: -25274.5 | P56: -46950
A57: =Dashboard!A56 -> 0 | B57: =Dashboard!B56 -> 0 | C57: =Dashboard!C65 -> 0
A58: =Dashboard!A57 -> 0 | B58: =Dashboard!B57 -> 0 | C58: =Dashboard!C66 -> 0
A59: =Dashboard!A58 -> 0 | B59: =Dashboard!B58 -> 0 | C59: =Dashboard!C67 -> 0
A60: =Dashboard!A59 -> 0 | B60: =Dashboard!B68 -> 0 | C60: =Dashboard!C68 -> 0
A61: =Dashboard!A69 -> 0 | B61: =Dashboard!B69 -> 0 | C61: =Dashboard!C69 -> 0
A62: =Dashboard!A70 -> 0 | B62: =Dashboard!B70 -> 0 | C62: =Dashboard!C70 -> 0
A63: =Dashboard!A71 -> 0 | B63: =Dashboard!B71 -> 0 | C63: =Dashboard!C71 -> 0
A64: =Dashboard!A72 -> 0 | B64: =Dashboard!B72 -> 0 | C64: =Dashboard!C72 -> 0

Sheet Actual2223
A1: =Dashboard!A1 -> FINANCE DASHBOARD
B4: MONTH | C4: UNIT | D4: JUL | E4: AUG | F4: SEP | G4: OCT | H4: NOV | I4: DEC | J4: JAN | K4: FEB | L4: MAR | M4: APR | N4: MAY | O4: JUN
A5: =Dashboard!A5 -> BILLING DASHBOARD - SUMMARY
A6: =Dashboard!A6 -> 1 | B6: =Dashboard!B6 -> Total Water Sales (Ksh) | C6: =Dashboard!C6 -> Ksh | D6: 12199740 | E6: 12735676 | F6: 11968928 | G6: 9537854 | H6: 10102428 | I6: 10986262 | J6: 11599157 | K6: 12676005 | L6: 13715682 | M6: 12172674 | N6: 10015215 | O6: 11728511
A7: =Dashboard!A7 -> 2 | B7: =Dashboard!B7 -> Total Sewerage Sales (Ksh) | C7: =Dashboard!C7 -> Ksh | D7: 5163189.6 | E7: 5115963.4 | F7: 5069596.2 | G7: 5067979.4 | H7: 5605456.5 | I7: 5780301.4 | J7: 5899284.4 | K7: 5160014.7 | L7: 5301013.9 | M7: 5146079.4 | N7: 4942473.3 | O7: 5141457.9
A8: =Dashboard!A8 -> 3 | B8: =Dashboard!B8 -> Bulk water | D8: 24880 | E8: 40130 | F8: 77090 | G8: 22080 | H8: 14000 | I8: 6240 | J8: 16480 | K8: 41840 | L8: 92880 | M8: 37120 | N8: 5040 | O8: 32560
A9: =Dashboard!#REF! -> #REF! | B9: =Dashboard!#REF! -> #REF! | D9: 392600 | E9: 394950 | F9: 409650 | G9: 414850 | H9: 417300 | I9: 422000 | J9: 424700 | K9: 428050 | L9: 434200 | M9: 439000 | N9: 442900 | O9: 445100
A10: =Dashboard!A10 -> 5 | B10: =Dashboard!B10 -> new connection fee water | D10: 130000 | E10: 276000 | F10: 307500 | G10: 199000 | H10: 209000 | I10: 140000 | J10: 207500 | K10: 430000 | L10: 588500 | M10: 305000 | N10: 175000 | O10: 232500
A11: =Dashboard!A11 -> 6 | B11: =Dashboard!B11 -> new connection fee sewer | D11: 0 | E11: 0 | F11: 22500 | G11: 20000 | H11: 30000 | I11: 30000 | J11: 25000 | K11: 5000 | L11: 45000 | M11: 80000 | N11: 27500 | O11: 5000
A12: =Dashboard!A12 -> 7 | B12: =Dashboard!B12 -> reconnection fee (water+sewer) | D12: 385000 | E12: 423000 | F12: 393500 | G12: 328000 | H12: 287500 | I12: 256000 | J12: 374500 | K12: 266500 | L12: 350500 | M12: 183500 | N12: 295800 | O12: 254500
A13: =Dashboard!A13 -> 8 | B13: =Dashboard!B13 -> Prepaid kiosk | C13: =Dashboard!C8 -> Ksh | D13: 86850 | E13: 84450 | F13: 56450 | G13: 97020 | H13: 61350 | I13: 68250 | J13: 83100 | K13: 90450 | L13: 76200 | M13: 61950 | N13: 26000 | O13: 28100
A14: =Dashboard!A14 -> 9 | B14: =Dashboard!B14 -> misc income-printing fee,CA,meter replacement fee,meter testing | C14: =Dashboard!C10 -> Ksh | D14: 4900 | E14: 8300 | F14: 12500 | G14: 19100 | H14: 292967.35 | I14: 7000 | J14: 19300 | K14: 21200 | L14: 136300 | M14: 759310 | N14: 253900 | O14: 99600
A15: =Dashboard!A15 -> 10 | B15: =Dashboard!B15 -> sewer unblocking fee | C15: =Dashboard!C11 -> Ksh | D15: 2500 | E15: 2500 | F15: 0 | G15: 0 | H15: 0 | I15: 0 | J15: 0 | K15: 0 | L15: 2500 | M15: 0 | N15: 0
A16: =Dashboard!A16 -> 11 | B16: =Dashboard!B16 -> penalties (water+sewer) | C16: =Dashboard!C12 -> Ksh | D16: 38033 | E16: 0 | F16: 169318 | G16: 0 | H16: 0 | I16: 0 | J16: 40000 | K16: 69783 | L16: 315642 | M16: 87169 | N16: 0 | O16: 13000
A17: =Dashboard!#REF! -> #REF! | B17: =Dashboard!#REF! -> #REF! | C17: =Dashboard!C13 -> Ksh
A18: =Dashboard!A17 -> 12 | B18: =Dashboard!B17 -> Company exhauster | C18: =Dashboard!C14 -> Ksh | D18: 155500 | E18: 121000 | F18: 115000 | G18: 112500 | H18: 173050 | I18: 140500 | J18: 288000 | K18: 253000 | L18: 78000 | M18: 107500 | N18: 130000 | O18: 148500
A19: =Dashboard!A18 -> 12 | B19: =Dashboard!B18 -> Customer exhauster | C19: =Dashboard!C15 -> Ksh | D19: 165000 | E19: 150000 | F19: 165000 | G19: 165000 | H19: 165000 | I19: 150000 | J19: 150000 | K19: 150000 | L19: 135000 | M19: 135000 | N19: 135000 | O19: 135000
A20: =Dashboard!A19 -> 13 | B20: =Dashboard!B19 -> Total billed (Ksh) | C20: =Dashboard!C17 -> Ksh | D20: =SUM(D6:D19)-(D13+D8) -> 18636463 | E20: =SUM(E6:E19)-(E13+E8) -> 19227389 | F20: =SUM(F6:F19)-(F13+F8) -> 18633492 | G20: =SUM(G6:G19)-(G13+G8) -> 15864283 | H20: =SUM(H6:H19)-(H13+H8) -> 17282702 | I20: =SUM(I6:I19)-(I13+I8) -> 17912063 | J20: =SUM(J6:J19)-(J13+J8) -> 19027441 | K20: =SUM(K6:K19)-(K13+K8) -> 19459553 | ... O20: =SUM(O6:O19)-(O13+O8) -> 18203169
A21: =Dashboard!A20 -> 0 | B21: =Dashboard!B20 -> 0 | C21: =Dashboard!C18 -> Ksh
A22: =Dashboard!A21 -> A | B22: =Dashboard!B21 -> Eastern Region | C22: =Dashboard!#REF! -> #REF! | D22: 17th | E22: 18th | F22: 16th | G22: 14th | H22: 15th | I22: 16th | J22: 14th | K22: 14th | L22: 16th | M22: 14th | N22: 15th | O22: 15th
A23: =Dashboard!A22 -> B | B23: =Dashboard!B22 -> Southern Region | C23: =Dashboard!#REF! -> #REF! | D23: 17th | E23: 18th | F23: 16th | G23: 14th | H23: 15th | I23: 21st | J23: 18th | K23: 14th | L23: 16th | M23: 20th | N23: 15th | O23: 15th
A24: =Dashboard!A23 -> C | B24: =Dashboard!B23 -> Central Region | C24: =Dashboard!C19 -> Ksh | D24: 29th | E24: 31st | F24: 30th | G24: 31st | H24: 30th | I24: 30th | J24: 31st | K24: 28th | L24: 31st | M24: 28th | N24: 31st | O24: 30th
A25: =Dashboard!A24 -> COLLECTION EFFICIENCY | B25: =Dashboard!B24 -> 0 | C25: =Dashboard!C20 -> 0
A26: =Dashboard!A25 -> D | B26: =Dashboard!B25 -> Total accounts disconnected-water | C26: =Dashboard!C21 -> DATE | D26: 364 | E26: 344 | F26: 323 | G26: 240 | H26: 241 | I26: 186 | J26: 305 | K26: 184 | L26: 313 | M26: 149 | N26: 210 | O26: 176
A27: =Dashboard!A26 -> E | B27: =Dashboard!B26 -> Total accounts disconnected-sewer | C27: =Dashboard!C16 -> Ksh | D27: 10 | E27: 54 | F27: 46 | G27: 58 | H27: 31 | I27: 48 | J27: 39 | K27: 47 | L27: 25 | M27: 23 | N27: 55 | O27: 49
A28: =Dashboard!A27 -> 14 | B28: =Dashboard!B27 -> Total Collection for the month | C28: =Dashboard!C17 -> Ksh | D28: 17553946 | E28: 14640444 | F28: 13485525 | G28: 13714992 | H28: 18534525 | I28: 12470759 | J28: 17312881 | K28: 14901865 | L28: 15605609 | M28: 15079990 | N28: 15346663 | O28: 17393617
A29: =Dashboard!A28 -> 7 | B29: =Dashboard!B28 -> Total Collection- Related Sales | C29: =Dashboard!C18 -> Ksh
A30: =Dashboard!A29 -> 15 | B30: =Dashboard!B29 -> Collection Efficiency - in % of billing | D30: =D28/ACTUAL2122!O22 -> 1.1308867 | E30: =E28/D20 -> 0.78558063 | F30: =F28/E20 -> 0.70137058 | G30: =G28/F20 -> 0.7360398 | H30: =H28/G20 -> 1.1683178 | I30: =I28/H20 -> 0.72157462 | J30: =J28/I20 -> 0.96654865 | K30: =K28/J20 -> 0.78317755 | L30: =L28/K20 -> 0.80195107 | ... O30: =O28/N20 -> 1.0594373
A31: =Dashboard!A31 -> CENTRAL REGION: CBD,CCCR,KABATI,SITE,KIHOTO,LAKEVIEW,HOPEWELL
A32: =Dashboard!A32 -> 16a | B32: =Dashboard!B32 -> Amount Billed Water-Central | C32: =Dashboard!C32 -> Ksh. | D32: 7447916 | E32: 8369605 | F32: 8367806 | G32: 5890041 | H32: 6272475 | I32: 7265076 | J32: 7408161 | K32: 8041476 | L32: 8363946 | M32: 7639624 | N32: 6614595 | O32: 7133367
A33: =Dashboard!A33 -> 17a | B33: =Dashboard!B33 -> Amount Billed Sewer-Central | C33: =Dashboard!C33 -> Ksh. | D33: 4699648.6 | E33: 5075106.4 | F33: 4844721.9 | G33: 4846991.4 | H33: 5367743.8 | I33: 5547386.9 | J33: 5661177.4 | K33: 5114256.4 | L33: 5275456.9 | M33: 5122146.4 | N33: 4916428.8 | O33: 5107057.7
A34: =Dashboard!A34 -> 18a | B34: =Dashboard!B34 -> othersales | C34: =Dashboard!C34 -> Ksh. | D34: 600350 | E34: 778951 | F34: 987568 | G34: 779550 | H34: 1085517.4 | I34: 721900 | J34: 987050 | K34: 908200 | L34: 1050852 | M34: 1456946 | N34: 914650 | O34: 784150
A35: =Dashboard!A35 -> 19a | B35: =Dashboard!B35 -> Amount Billed Water & Sewer-othersales-Central | C35: =Dashboard!C35 -> Ksh. | D35: =D32+D33+D34 -> 12747915 | E35: =E32+E33+E34 -> 14223662 | F35: =F32+F33+F34 -> 14200096 | G35: =G32+G33+G34 -> 11516582 | H35: =H32+H33+H34 -> 12725736 | I35: =I32+I33+I34 -> 13534363 | J35: =J32+J33+J34 -> 14056388 | K35: =K32+K33+K34 -> 14063932 | ... O35: =O32+O33+O34 -> 13024575
A36: =Dashboard!A36 -> 14a | B36: =Dashboard!B36 -> Amount Collected-Central | C36: =Dashboard!C36 -> Ksh. | D36: 13369388 | E36: 10007080 | F36: 9399206.2 | G36: 9447431.8 | H36: 14164924 | I36: 8428642 | J36: 12701452 | K36: 10226755 | L36: 10461453 | M36: 10578929 | N36: 10173620 | O36: 13145367
A37: =Dashboard!A37 -> 15a | B37: =Dashboard!B37 -> Collection Efficiency-Central | C37: =Dashboard!C37 -> % | D37: =D36/ACTUAL2122!O33 -> 1.4269497 | E37: =E36/D35 -> 0.78499742 | F37: =F36/E35 -> 0.66081477 | G37: =G36/F35 -> 0.6653076 | H37: =H36/G35 -> 1.229959 | I37: =I36/H35 -> 0.66233041 | J37: =J36/I35 -> 0.93845956 | K37: =K36/J35 -> 0.72755211 | L37: =L36/K35 -> 0.74384976 | ... O37: =O36/N35 -> 1.0562198
A38: =Dashboard!A38 -> SOUTHERN REGION: HELLSGATE,KAMERE, MAI MAHIU,LONGONOT
A39: =Dashboard!A39 -> 16b | B39: =Dashboard!B39 -> Amount Billed Water-Southern | C39: =Dashboard!C39 -> Ksh. | D39: 2236041 | E39: 2367557 | F39: 2476585 | G39: 2221226 | H39: 2275040 | I39: 2238025 | J39: 2440191 | K39: 2770961 | L39: 3105853 | M39: 2709503 | N39: 1569252 | O39: 2754587
A40: =Dashboard!A40 -> 17b | B40: =Dashboard!B40 -> Amount Billed Sewer-Southern | C40: =Dashboard!C40 -> Ksh. | D40: 0 | E40: 0 | F40: 0 | G40: 0 | H40: 0 | I40: 0 | J40: 0 | K40: 0 | L40: 0 | M40: 0 | N40: 0 | O40: 0
A41: =Dashboard!A41 -> 18b | B41: =Dashboard!B41 -> othersales | C41: =Dashboard!C41 -> Ksh. | D41: 207933 | E41: 309550 | F41: 359250 | G41: 260500 | H41: 288650 | I41: 181250 | J41: 243100 | K41: 491183 | L41: 598700 | M41: 368550 | N41: 280550 | O41: 281550
A42: =Dashboard!A42 -> 19b | B42: =Dashboard!B42 -> Amount Billed Water & Sewer-OTHER SALES-Southern | C42: =Dashboard!C42 -> Ksh. | D42: =D39+D40+D41 -> 2443974 | E42: =E39+E40+E41 -> 2677107 | F42: =F39+F40+F41 -> 2835835 | G42: =G39+G40+G41 -> 2481726 | H42: =H39+H40+H41 -> 2563690 | I42: =I39+I40+I41 -> 2419275 | J42: =J39+J40+J41 -> 2683291 | K42: =K39+K40+K41 -> 3262144 | ... O42: =O39+O40+O41 -> 3036137
A43: =Dashboard!A43 -> 14b | B43: =Dashboard!B43 -> Amount Collected-Southern | C43: =Dashboard!C43 -> Ksh. | D43: 2324233 | E43: 2774831 | F43: 2446763 | G43: 2615808 | H43: 2791158.3 | I43: 2222516 | J43: 2666500 | K43: 2766283 | L43: 3120247.2 | M43: 2628094 | N43: 2470200.8 | O43: 2464320.2
A44: =Dashboard!A44 -> 15b | B44: =Dashboard!B44 -> Collection Efficiency-Southern | C44: =Dashboard!C44 -> % | D44: =D43/ACTUAL2122!O40 -> 0.37773505 | E44: =E43/D42 -> 1.1353766 | F44: =F43/E42 -> 0.91395787 | G44: =G43/F42 -> 0.92241192 | H44: =H43/G42 -> 1.1246843 | I44: =I43/H42 -> 0.86692073 | J44: =J43/I42 -> 1.1021897 | K44: =K43/J42 -> 1.0309292 | L44: =L43/K42 -> 0.95650199 | ... O44: =O43/N42 -> 1.3322076
A45: =Dashboard!A45 -> EASTERN REGION: KAYOLE,GONDI,KINUNGI,NJONJORO,IHINDU | B45: =Dashboard!B45 -> 0 | C45: =Dashboard!C45 -> 0
A46: =Dashboard!A46 -> 16c | B46: =Dashboard!B46 -> Amount Billed Water-Eastern | C46: =Dashboard!C46 -> Ksh. | D46: 1753336 | E46: 1998514 | F46: 1124537 | G46: 1426587 | H46: 1554913 | I46: 1483161 | J46: 1750805 | K46: 1863568 | L46: 2245883 | M46: 1823547 | N46: 1831368 | O46: 1840557
A47: =Dashboard!A47 -> 17c | B47: =Dashboard!B47 -> Amount Billed Sewer-Eastern | C47: =Dashboard!C47 -> Ksh. | D47: 54327.75 | E47: 40857 | F47: 224874.25 | G47: 220988 | H47: 237712.75 | I47: 232914.5 | J47: 238107 | K47: 45758.25 | L47: 25557 | M47: 23933 | N47: 26044.5 | O47: 34400.25
A48: =Dashboard!A48 -> 18c | B48: =Dashboard!B48 -> othersales | C48: =Dashboard!C48 -> Ksh. | D48: 203900 | E48: 289750 | F48: 248150 | G48: 218400 | H48: 200650 | I48: 242350 | J48: 298850 | K48: 224150 | L48: 436090 | M48: 270983 | N48: 264900 | O48: 267500
A49: =Dashboard!A49 -> 19b | B49: =Dashboard!B49 -> Amount Billed Water & Sewer-othersales-Eastern | C49: =Dashboard!C49 -> Ksh. | D49: =D46+D47+D48 -> 2011563.8 | E49: =E46+E47+E48 -> 2329121 | F49: =F46+F47+F48 -> 1597561.2 | G49: =G46+G47+G48 -> 1865975 | H49: =H46+H47+H48 -> 1993275.8 | I49: =I46+I47+I48 -> 1958425.5 | J49: =J46+J47+J48 -> 2287762 | K49: =K46+K47+K48 -> 2133476.2 | ... N49: =N46+N47+N48 -> 2122312.5 | O49: 2142457.2
A50: =Dashboard!A50 -> 14c | B50: =Dashboard!B50 -> Amount Collected-Eastern | C50: =Dashboard!C50 -> Ksh. | D50: 1860325 | E50: 2099889 | F50: 1639556 | G50: 1651752 | H50: 1578443 | I50: 1819601 | J50: 1944928.5 | K50: 1908827 | L50: 2023909 | M50: 1872967 | N50: 2702842.5 | O50: 1783930
A51: =Dashboard!A51 -> 15c | B51: =Dashboard!B51 -> Collection Efficiency-Eastern | C51: =Dashboard!C51 -> % | D51: =D50/D49 -> 0.92481533 | E51: =E50/E49 -> 0.90158004 | F51: =F50/E49 -> 0.70393767 | G51: =G50/F49 -> 1.0339209 | H51: =H50/G49 -> 0.8459079 | I51: =I50/H49 -> 0.91286968 | J51: =J50/I49 -> 0.99310824 | K51: =K50/J49 -> 0.83436433 | L51: =L50/K49 -> 0.94864379 | M51: =M50/L49 -> 0.69176223 | ... O51: =O50/N49 -> 0.84055953
A52: =Dashboard!A52 -> 19 | B52: =Dashboard!B59 -> 0 | C52: =Dashboard!C59 -> 0 | D52: =D51/ACTUAL2122!O47 -> #DIV/0! | E52: =E51/D50 -> 4.8463577e-07 | F52: =F51/E50 -> 3.3522613e-07 | G52: =G51/F50 -> 6.3061031e-07 | H52: =H51/G50 -> 5.1212767e-07 | I52: =I51/H50 -> 5.7833554e-07 | J52: =J51/I50 -> 5.4578352e-07 | K52: =K51/J50 -> 4.2899486e-07 | L52: =L51/K50 -> 4.9697735e-07 | ... O52: =O51/N50 -> 3.1099094e-07
A53: =Dashboard!A53 -> 0 | B53: =Dashboard!B53 -> AMOUNT RECEIVABLES | C53: =Dashboard!C62 -> 0
A54: =Dashboard!A54 -> 20 | B54: =Dashboard!B54 -> Amount receivables as at close of the month | C54: =Dashboard!C63 -> 0 | D54: 138749018 | E54: 1.4384853e+08 | F54: 1.4889087e+08 | G54: 1.507848e+08 | H54: 149166788 | I54: 1.5409969e+08 | J54: 1.5609406e+08 | K54: 1.5934826e+08 | L54: 1.6525124e+08 | M54: 1.6997107e+08 | N54: 1.6869709e+08 | O54: 1.6903197e+08
A55: =Dashboard!A55 -> 21 | B55: =Dashboard!B55 -> Adjustment done for the month | C55: =Dashboard!C55 -> Ksh. | D55: -4997 | E55: -5317 | F55: -298109.02 | G55: -218802 | H55: -444757 | I55: -599234 | J55: -142611 | K55: -1460174.9 | L55: -26367 | M55: -217707 | N55: -2385650 | O55: -559424.5
A56: =Dashboard!A56 -> 0 | B56: =Dashboard!B56 -> 0 | C56: =Dashboard!C65 -> 0
A57: =Dashboard!A57 -> 0 | B57: =Dashboard!B57 -> 0 | C57: =Dashboard!C66 -> 0
A58: =Dashboard!A58 -> 0 | B58: =Dashboard!B58 -> 0 | C58: =Dashboard!C67 -> 0
A59: =Dashboard!A59 -> 0 | B59: =Dashboard!B68 -> 0 | C59: =Dashboard!C68 -> 0
A60: =Dashboard!A69 -> 0 | B60: =Dashboard!B69 -> 0 | C60: =Dashboard!C69 -> 0
A61: =Dashboard!A70 -> 0 | B61: =Dashboard!B70 -> 0 | C61: =Dashboard!C70 -> 0
A62: =Dashboard!A71 -> 0 | B62: =Dashboard!B71 -> 0 | C62: =Dashboard!C71 -> 0
A63: =Dashboard!A72 -> 0 | B63: =Dashboard!B72 -> 0 | C63: =Dashboard!C72 -> 0

Sheet ACTUAL2122
A1: =[1]Dashboard!A1 -> FINANCE DASHBOARD
B4: MONTH | C4: UNIT | D4: JUL | E4: AUG | F4: SEP | G4: OCT | H4: NOV | I4: DEC | J4: JAN | K4: FEB | L4: MAR | M4: APR | N4: MAY | O4: JUN
A5: =[1]Dashboard!A5 -> SALES DASHBOARD - SUMMARY
A6: =[1]Dashboard!A6 -> 1 | B6: =[1]Dashboard!B6 -> Total Water Sales (Ksh) | C6: =[1]Dashboard!C6 -> Ksh | D6: 9816920 | E6: 9629542 | F6: 9990578.3 | G6: 10323025 | H6: 10434355 | I6: 10257770 | J6: 11956646 | K6: 12122204 | L6: 10549503 | M6: 12370653 | N6: 9949935 | O6: 9227442
A7: =[1]Dashboard!A7 -> 2 | B7: =[1]Dashboard!B7 -> Total Sewerage Sales (Ksh) | C7: =[1]Dashboard!C7 -> Ksh | D7: 4382887.2 | E7: 4351383.3 | F7: 4538576.5 | G7: 4545154.2 | H7: 5077368.6 | I7: 4348279 | J7: 4560939.5 | K7: 4812019.1 | L7: 4291621 | M7: 4771105.9 | N7: 4515160.5 | O7: 4714692.6
B8: bulk
B9: meter rent | D9: 331100 | E9: 336400 | F9: 340300 | G9: 343400 | H9: 349350 | I9: 355250 | J9: 361150 | K9: 365900 | L9: 369600 | M9: 380850 | N9: 383800 | O9: 387050
B10: new connection fee-water | D10: 120000 | E10: 108000 | F10: 164000 | G10: 334500 | H10: 192000 | I10: 234000 | J10: 128500 | K10: 264500 | L10: 319000 | M10: 202000 | N10: 143500 | O10: 310000
B11: reconnection fee-water | D11: 91500 | E11: 77000 | F11: 68000 | G11: 65500 | H11: 64000 | I11: 66000 | J11: 45500 | K11: 40500 | L11: 279000 | M11: 199000 | N11: 509500 | O11: 457000
B12: OTHER SALES CA,METER TESTING,PRINTING | D12: 7000 | E12: 5800 | F12: 12500 | G12: 5100 | H12: 4800 | I12: 3900 | J12: 7600 | K12: 7200 | L12: 8300 | M12: 22300 | N12: 20200 | O12: 9600
B13: penalties-water | D13: 178060 | E13: 147985 | F13: 169420 | G13: 76210 | H13: 8000 | I13: 17495 | J13: 16000 | K13: 39884 | L13: 233517 | M13: 12000 | N13: 8400
A14: =[1]Dashboard!A8 -> 3 | B14: =[1]Dashboard!B8 -> Total Water Related Sales | C14: =[1]Dashboard!C8 -> Ksh | D14: =SUM(D9:D13) -> 727660 | E14: =SUM(E9:E13) -> 675185 | F14: =SUM(F9:F13) -> 754220 | G14: =SUM(G9:G13) -> 824710 | H14: =SUM(H9:H13) -> 618150 | I14: =SUM(I9:I13) -> 676645 | J14: =SUM(J9:J13) -> 558750 | K14: =SUM(K9:K13) -> 717984 | ... O14: =SUM(O9:O13) -> 1163650
A15: =[1]Dashboard!A9 -> 4(i) | B15: =[1]Dashboard!B9 -> Company exhauster | C15: =[1]Dashboard!C9 -> Ksh | D15: 140000 | E15: 130000 | F15: 150500 | G15: 142500 | H15: 147500 | I15: 114000 | J15: 150000 | K15: 142500 | L15: 15000 | M15: 152500 | N15: 149000 | O15: 193000
A16: =[1]Dashboard!A10 -> 4(ii) | B16: =[1]Dashboard!B10 -> Customer exhauster | C16: =[1]Dashboard!C10 -> Ksh | D16: 180000 | E16: 180000 | F16: 165000 | G16: 150000 | H16: 150000 | I16: 150000 | J16: 165000 | K16: 150000 | L16: 158500 | M16: 150000 | N16: 150000 | O16: 150000
B17: unblockage fee | G17: 0 | H17: 0 | I17: 0 | J17: 0 | L17: 7500 | M17: 2500 | N17: 0 | O17: 5000
B18: new connection-sewer | D18: 27500 | E18: 38000 | F18: 10500 | G18: 19000 | H18: 87500 | I18: 27500 | J18: 28000 | K18: 60000 | L18: 25000 | M18: 15000 | N18: 44500 | O18: 55000
B19: reconnection fee-sewer | D19: =0+D13 -> 178060 | E19: =3000+E13 -> 150985 | F19: =3000+F13 -> 172420 | G19: 9000 | H19: 3000 | I19: 1500 | J19: 13500 | K19: 96000 | L19: 34500 | M19: 9000 | N19: 19500 | O19: 13500
B20: penalties-sewer | D20: 48000 | G20: 0 | H20: 0 | I20: 0 | L20: 35000 | M20: 0 | N20: 0
A21: =[1]Dashboard!A11 -> 4 | B21: =[1]Dashboard!B11 -> Total Sewerage Related Sales | C21: =[1]Dashboard!C11 -> Ksh | D21: =SUM(D15:D20) -> 573560 | E21: =SUM(E15:E20) -> 498985 | F21: =SUM(F15:F20) -> 498420 | G21: =SUM(G15:G20) -> 320500 | H21: =SUM(H15:H20) -> 388000 | I21: =SUM(I15:I20) -> 293000 | J21: =SUM(J15:J20) -> 356500 | K21: =SUM(K15:K20) -> 448500 | ... O21: =SUM(O15:O20) -> 416500
A22: =[1]Dashboard!A12 -> 5 | B22: =[1]Dashboard!B12 -> Total Water/Sewerage and Related Sales (Ksh) | C22: =[1]Dashboard!C12 -> Ksh | D22: =D6+D7+D14+D21 -> 15501027 | E22: =E6+E7+E14+E21 -> 15155095 | F22: =F6+F7+F14+F21 -> 15781795 | G22: =G6+G7+G14+G21 -> 16013389 | H22: =H6+H7+H14+H21 -> 16517874 | I22: =I6+I7+I14+I21 -> 15575694 | J22: =J6+J7+J14+J21 -> 17432835 | K22: =K6+K7+K14+K21 -> 18100707 | ... O22: =O6+O7+O14+O21 -> 15522285
A23: =[1]Dashboard!A13 -> COLLECTION EFFICIENCY
A24: =[1]Dashboard!A14 -> 6 | B24: =[1]Dashboard!B14 -> Total Collection, Water and Sewer Revenues and other sales | C24: =[1]Dashboard!C14 -> Ksh | D24: 15131038 | E24: 12356990 | F24: 12415042 | G24: 13167328 | H24: 18704966 | I24: 11339412 | J24: 19291963 | K24: 11507178 | L24: 13785470 | M24: 11337951 | N24: 19240363 | O24: 14508155
A25: =[1]Dashboard!A15 -> 7 | B25: =[1]Dashboard!B15 -> Total Collection- Related Sales | C25: =[1]Dashboard!C15 -> Ksh | D25: 729278.67 | E25: 957093.79 | F25: 900865.9 | G25: 817252.59 | H25: 852098.27 | I25: 837820.69 | J25: 954038.3 | K25: 808090.65 | L25: 970913.67 | M25: 852667.86 | N25: 1017770.8 | O25: 1299989.5
A26: =[1]Dashboard!A16 -> 8 | B26: =[1]Dashboard!B16 -> Collection Efficiency - in % of budget | C26: =[1]Dashboard!C16 -> % | D26: =D24/[1]BUDGET!D23 -> 1 | E26: =E24/[1]BUDGET!E23 -> 1 | F26: =F24/[1]BUDGET!F23 -> 1 | G26: =G24/[1]BUDGET!G23 -> 1 | H26: =H24/[1]BUDGET!H23 -> 1 | I26: =I24/[1]BUDGET!I23 -> 1 | J26: =J24/[2]BUDGET!J23 -> 0.94795962 | K26: =K24/[1]BUDGET!K23 -> 1 | L26: =L24/[1]BUDGET!L23 -> 1 | M26: =M24/[1]BUDGET!M23 -> 1 | N26: =N24/[1]BUDGET!N23 -> 1 | O26: =O24/[1]BUDGET!O23 -> 1
A27: =[1]Dashboard!A17 -> 9 | B27: =[1]Dashboard!B17 -> Collection Efficiency - in % of billing | C27: =[1]Dashboard!C17 -> % | D27: =(D24+D25)/[1]ACTUAL2021!O21 -> 1.0130564 | E27: =E24/D22 -> 0.79717236 | F27: =F24/E22 -> 0.81919923 | G27: =G24/F22 -> 0.83433653 | H27: =H24/G22 -> 1.1680829 | I27: =I24/H22 -> 0.68649345 | J27: =J24/I22 -> 1.2385941 | K27: =K24/J22 -> 0.66008642 | L27: =L24/K22 -> 0.7615984 | ... O27: =O24/N22 -> 0.91283599
A28: =[1]Dashboard!A18 -> REGIONAL PERFORMANCE
A29: =[1]Dashboard!A19 -> DTI REGION: CBD,CCCR,KABATI,SITE,KIHOTO
A30: =[1]Dashboard!A20 -> 10 | B30: =[1]Dashboard!B20 -> Amount Billed Water-DTI | C30: =[1]Dashboard!C20 -> Ksh. | D30: 5277990 | E30: 4887807 | F30: 5455618.3 | G30: 5416695 | H30: 5791785 | I30: 5819845 | J30: 6294944 | K30: 6986878 | L30: 5892852 | M30: 6078802 | N30: 5301001 | O30: 4569022
A31: =[1]Dashboard!A21 -> 11 | B31: =[1]Dashboard!B21 -> Amount Billed Sewer-DTI | C31: =[1]Dashboard!C21 -> Ksh. | D31: 3270777.8 | E31: 3201537.7 | F31: 3456698.4 | G31: 3443299.1 | H31: 3601247.2 | I31: 3830623.7 | J31: 4098101.7 | K31: 4386863.2 | L31: 3916586.6 | M31: 4089032.2 | N31: 3907537.3 | O31: 4054135.2
A32: =[1]Dashboard!A22 -> 11a | B32: =[1]Dashboard!B22 -> othersales | C32: =[1]Dashboard!C22 -> Ksh. | D32: 682500 | E32: 293235 | F32: 389800 | G32: 585810 | H32: 545200 | I32: 353296 | J32: 540100 | K32: 716700 | L32: 698850 | M32: 599500 | N32: 712900 | O32: 746050
A33: =[1]Dashboard!A23 -> 12 | B33: =[1]Dashboard!B23 -> Amount Billed Water & Sewer-othersales-DTI | C33: =[1]Dashboard!C23 -> Ksh. | D33: =D30+D31+D32 -> 9231267.8 | E33: =E30+E31+E32 -> 8382579.7 | F33: =F30+F31+F32 -> 9302116.7 | G33: =G30+G31+G32 -> 9445804.2 | H33: =H30+H31+H32 -> 9938232.2 | I33: =I30+I31+I32 -> 10003765 | J33: =J30+J31+J32 -> 10933146 | K33: =K30+K31+K32 -> 12090441 | ... O33: =O30+O31+O32 -> 9369207.2
A34: =[1]Dashboard!A24 -> 13 | B34: =[1]Dashboard!B24 -> Amount Collected-DTI | C34: =[1]Dashboard!C24 -> Ksh. | D34: 11065270 | E34: 7201345.5 | F34: 5950234.7 | G34: 5524967.8 | H34: 12019341 | I34: 5948255 | J34: 11407830 | K34: 6542782 | L34: 7447185.8 | M34: 6330920.2 | N34: 12864395 | O34: 7682751.8
A35: =[1]Dashboard!A25 -> 14 | B35: =[1]Dashboard!B25 -> Collection Efficiency-DTI | C35: =[1]Dashboard!C25 -> % | D35: 1.1634412 | E35: 0.78010362 | F35: 0.70983336 | G35: 0.59394738 | H35: 1.2724529 | I35: 0.59852244 | J35: 1.1403537 | K35: 0.59843545 | L35: 0.6159565 | M35: 0.6024692 | N35: 1.1947614 | O35: 0.77435866
A36: =[1]Dashboard!A26 -> KARATI REGION: KAYOLE,HELLSGATE,KAMERE
A37: =[1]Dashboard!A27 -> 15 | B37: =[1]Dashboard!B27 -> Amount Billed Water-KARATE | C37: =[1]Dashboard!C27 -> Ksh. | D37: 4538930 | E37: 4741735 | F37: 4534960 | G37: 4906330 | H37: 4642570 | I37: 4437925 | J37: 5661702 | K37: 5135326 | L37: 4656651 | M37: 6291851 | N37: 4648934 | O37: 4658420
A38: =[1]Dashboard!A28 -> 16 | B38: =[1]Dashboard!B28 -> Amount Billed Sewer-KARATE | C38: =[1]Dashboard!C28 -> Ksh. | D38: 1112109.4 | E38: 1149845.6 | F38: 1081878.1 | G38: 1101855.1 | H38: 1476121.4 | I38: 517655.25 | J38: 462837.75 | K38: 425155.9 | L38: 375034.4 | M38: 682073.65 | N38: 607623.15 | O38: 660557.4
A39: =[1]Dashboard!A29 -> 16A | B39: =[1]Dashboard!B29 -> othersales | C39: =[1]Dashboard!C29 -> Ksh. | D39: 252410 | E39: 216553 | F39: 537220 | G39: 559400 | H39: 460950 | I39: 466350 | J39: 375150 | K39: 449784 | L39: 946067 | M39: 545650 | N39: 700500 | O39: 834100
A40: =[1]Dashboard!A30 -> 17 | B40: =[1]Dashboard!B30 -> Amount Billed Water & Sewer-OTHER SALES-KARATE | C40: =[1]Dashboard!C30 -> Ksh. | D40: 5903449.3 | E40: 6108133.6 | F40: 6154058.1 | G40: 6567585.1 | H40: 6579641.3 | I40: 5421930.2 | J40: 6499689.8 | K40: 6010265.9 | L40: 5977752.4 | M40: 7519574.7 | N40: 5957057.2 | O40: 6153077.4
A41: =[1]Dashboard!A31 -> 18 | B41: =[1]Dashboard!B31 -> Amount Collected-KARATE | C41: =[1]Dashboard!C31 -> Ksh. | D41: 4795147 | E41: 5155645 | F41: 6464807.8 | G41: 7642360 | H41: 6685625 | I41: 5391157 | J41: 7884132.5 | K41: 4964396 | L41: 6338283.8 | M41: 5007031 | N41: 6375968 | O41: 6825403
A42: =[1]Dashboard!A109 -> se | B42: =[1]Dashboard!B109 -> Money in the bank | C42: =[1]Dashboard!C115 -> 0 | D42: 0.88333703 | E42: 0.87332756 | F42: 1.0583933 | G42: 1.2418407 | H42: 1.0179731 | I42: 0.81936943 | J42: 1.4541191 | K42: 0.76378969 | L42: 1.0545763 | M42: 0.83761097 | N42: 0.84791605 | O42: 1.1457676
A43: =[1]Dashboard!A110 -> 0 | B43: =[1]Dashboard!B110 -> 0 | C43: =[1]Dashboard!C116 -> 0
A44: =[1]Dashboard!A111 -> 0 | B44: =[1]Dashboard!B111 -> 0 | C44: =[1]Dashboard!C117 -> 0
A45: =[1]Dashboard!A118 -> 0 | B45: =[1]Dashboard!B112 -> 0 | C45: =[1]Dashboard!C118 -> 0
A46: =[1]Dashboard!A119 -> 0 | B46: =[1]Dashboard!B119 -> 0 | C46: =[1]Dashboard!C119 -> 0
A47: =[1]Dashboard!A120 -> 0 | B47: =[1]Dashboard!B120 -> 0 | C47: =[1]Dashboard!C120 -> 0
A48: =[1]Dashboard!A121 -> 0 | B48: =[1]Dashboard!B121 -> 0 | C48: =[1]Dashboard!C121 -> 0
A49: =[1]Dashboard!A122 -> 0 | B49: =[1]Dashboard!B122 -> 0 | C49: =[1]Dashboard!C122 -> 0
A50: =[1]Dashboard!A123 -> 0 | B50: =[1]Dashboard!B123 -> 0 | C50: =[1]Dashboard!C123 -> 0
A51: =[1]Dashboard!A124 -> 0 | B51: =[1]Dashboard!B124 -> 0 | C51: =[1]Dashboard!C124 -> 0
A52: =[1]Dashboard!A125 -> 0 | B52: =[1]Dashboard!B125 -> 0 | C52: =[1]Dashboard!C125 -> 0
A53: =[1]Dashboard!A126 -> 0 | B53: =[1]Dashboard!B126 -> 0 | C53: =[1]Dashboard!C126 -> 0

Sheet ACTUAL2021
A1: =Dashboard!A1 -> FINANCE DASHBOARD
B4: MONTH | C4: UNIT | D4: JUL | E4: AUG | F4: SEP | G4: OCT | H4: NOV | I4: DEC | J4: JAN | K4: FEB | L4: MAR | M4: APR | N4: MAY | O4: JUN
A5: =Dashboard!A5 -> BILLING DASHBOARD - SUMMARY
A6: =Dashboard!A6 -> 1 | B6: =Dashboard!B6 -> Total Water Sales (Ksh) | C6: =Dashboard!C6 -> Ksh | D6: 8033080 | E6: 10480450 | F6: 10563035 | G6: 8803530 | H6: 8319130 | I6: 8933605 | J6: 10666780 | K6: 9484535 | L6: 9231735 | M6: 10740380 | N6: 8398845 | O6: 10066755
A7: =Dashboard!A7 -> 2 | B7: =Dashboard!B7 -> Total Sewerage Sales (Ksh) | C7: =Dashboard!C7 -> Ksh | D7: 3963417 | E7: 4025381 | F7: 4547362 | G7: 3846273 | H7: 3738059 | I7: 4422040.2 | J7: 4751034.5 | K7: 4819908.3 | L7: 4820424.7 | M7: 4626476 | N7: 4126126 | O7: 4586502.2
B8: meter rent
B9: new connection fee-water
B10: reconnection fee-water
B11: OTHER SALES CA,METER TESTING,PRINTING
B12: penalties-water
A13: =Dashboard!A8 -> 3 | B13: =Dashboard!B8 -> Bulk water | C13: =Dashboard!C8 -> Ksh | D13: 652095 | E13: 1021202 | F13: 994085 | G13: 638710 | H13: 581155 | I13: 584551 | J13: 587991 | K13: 571550 | L13: 833292 | M13: 581900 | N13: 897358.75 | O13: 617650
A14: =Dashboard!A10 -> 5 | B14: =Dashboard!B10 -> new connection fee water | C14: =Dashboard!C10 -> Ksh | D14: 0 | E14: 0 | F14: 0 | G14: 0 | H14: 0 | I14: 0 | J14: 0 | K14: 0 | L14: 0 | M14: 87500 | N14: 88000 | O14: 106000
A15: =Dashboard!A11 -> 6 | B15: =Dashboard!B11 -> new connection fee sewer | C15: =Dashboard!C11 -> Ksh | D15: 0 | E15: 0 | F15: 0 | G15: 0 | H15: 0 | I15: 0 | J15: 0 | K15: 0 | L15: 0 | M15: 180000 | N15: 180000 | O15: 180000
B16: unblockage fee
B17: new connection-sewer
B18: reconnection fee-sewer
B19: penalties-sewer
A20: =Dashboard!A12 -> 7 | B20: =Dashboard!B12 -> reconnection fee (water+sewer) | C20: =Dashboard!C12 -> Ksh | D20: 40871 | E20: 26492 | F20: 30921 | G20: 46637 | H20: 8500 | I20: 388500 | J20: 29000 | K20: 134000 | L20: 74000 | M20: 91500 | N20: 96200 | O20: 99000
A21: =Dashboard!A19 -> 13 | B21: =Dashboard!B19 -> Total billed (Ksh) | C21: =Dashboard!C19 -> Ksh | D21: =D6+D7+D13+D20 -> 12689463 | E21: =E6+E7+E13+E20 -> 15553525 | F21: =F6+F7+F13+F20 -> 16135403 | G21: =G6+G7+G13+G20 -> 13335150 | H21: =H6+H7+H13+H20 -> 12646844 | I21: =I6+I7+I13+I20 -> 14328696 | J21: =J6+J7+J13+J20 -> 16034806 | K21: =K6+K7+K13+K20 -> 15009993 | ... N21: =N6+N7+N13+N20 -> 13518530 | O21: =O6+O7+O13+O20+O14+O15 -> 15655907
A22: =Dashboard!A24 -> COLLECTION EFFICIENCY
A23: =Dashboard!A25 -> D | B23: =Dashboard!B25 -> Total accounts disconnected-water | C23: =Dashboard!C25 -> NO | D23: 18904165 | E23: 8241524 | F23: 11025250 | G23: 15698553 | H23: 8486541 | I23: 11994611 | J23: 10908165 | K23: 16454521 | L23: 13196644 | M23: 12174966 | N23: 15916705 | O23: 11719505
A24: =Dashboard!A26 -> E | B24: =Dashboard!B26 -> Total accounts disconnected-sewer | C24: =Dashboard!C26 -> NO | D24: 595166 | E24: 624092 | F24: 774506 | G24: 570747 | H24: 451705 | I24: 411895.5 | J24: 509050 | K24: 368468 | L24: 459098.05 | M24: 696391.52 | N24: 779005.18 | O24: 558058.41
A25: =Dashboard!#REF! -> #REF! | B25: =Dashboard!#REF! -> #REF! | C25: =Dashboard!#REF! -> #REF!
A26: =Dashboard!A29 -> 15 | B26: =Dashboard!B29 -> Collection Efficiency - in % of billing | C26: =Dashboard!C29 -> %
A27: =Dashboard!A30 -> REGIONAL PERFORMANCE | O27: =[3]SUMMARY!$C$262-O32 -> 326450.05
A28: =Dashboard!A31 -> CENTRAL REGION: CBD,CCCR,KABATI,SITE,KIHOTO,LAKEVIEW,HOPEWELL | O28: 326450.05
A29: =Dashboard!A32 -> 16a | B29: =Dashboard!B32 -> Amount Billed Water-Central | C29: =Dashboard!C32 -> Ksh. | D29: 5721035 | E29: 6734605 | F29: 7621450 | G29: 5605755 | H29: 5415485 | I29: 5122305 | J29: 5499295 | K29: 5141690 | L29: 5494275 | M29: 7399560 | N29: 4902855 | O29: 5571390
A30: =Dashboard!A33 -> 17a | B30: =Dashboard!B33 -> Amount Billed Sewer-Central | C30: =Dashboard!C33 -> Ksh. | D30: 3456061 | E30: 3516948 | F30: 4046923 | G30: 3326350 | H30: 3247600 | I30: 2167577.1 | J30: 3642577.2 | K30: 3510500.4 | L30: 3965142.8 | M30: 4102307.7 | N30: 3237807.9 | O30: 3939421.6
A31: =Dashboard!A34 -> 18a | B31: =Dashboard!B34 -> othersales | C31: =Dashboard!C34 -> Ksh.
A32: =Dashboard!A35 -> 19a | B32: =Dashboard!B35 -> Amount Billed Water & Sewer-othersales-Central | C32: =Dashboard!C35 -> Ksh. | D32: =D29+D30+D31 -> 9177096 | E32: =E29+E30+E31 -> 10251553 | F32: =F29+F30+F31 -> 11668373 | G32: =G29+G30+G31 -> 8932105 | H32: =H29+H30+H31 -> 8663085 | I32: =I29+I30+I31 -> 7289882.1 | J32: =J29+J30+J31 -> 9141872.2 | K32: =K29+K30+K31 -> 8652190.4 | ... O32: =O29+O30+O31 -> 9510811.6
A33: =Dashboard!A36 -> 14a | B33: =Dashboard!B36 -> Amount Collected-Central | C33: =Dashboard!C36 -> Ksh. | D33: 15948729 | E33: 5334326 | F33: 7406833 | G33: 12126115 | H33: 5868908 | I33: 7723477 | J33: 7243732.5 | K33: 12466621 | L33: 8511496.2 | M33: 8775903.5 | N33: 10061637 | O33: 7500516.1
A34: =Dashboard!A37 -> 15a | B34: =Dashboard!B37 -> Collection Efficiency-Central | C34: =Dashboard!C37 -> %
A35: =Dashboard!A38 -> SOUTHERN REGION: HELLSGATE,KAMERE, MAI MAHIU,LONGONOT | O35: 390200
A36: =Dashboard!A39 -> 16b | B36: =Dashboard!B39 -> Amount Billed Water-Southern | C36: =Dashboard!C39 -> Ksh. | D36: 2312045 | E36: 3745845 | F36: 2941585 | G36: 3197775 | H36: 2903645 | I36: 3811300 | J36: 4864585 | K36: 4342845 | L36: 3737460 | M36: 3608320 | N36: 3495990 | O36: 4495365
A37: =Dashboard!A40 -> 17b | B37: =Dashboard!B40 -> Amount Billed Sewer-Southern | C37: =Dashboard!C40 -> Ksh. | D37: 327356 | E37: 328433 | F37: 320439 | G37: 339923 | H37: 310459 | I37: 397209.75 | J37: 1106456.8 | K37: 1024408 | L37: 855281.85 | M37: 256668.25 | N37: 888318.1 | O37: 933080.6
A38: =Dashboard!A41 -> 18b | B38: =Dashboard!B41 -> othersales | C38: =Dashboard!C41 -> Ksh.
A39: =Dashboard!A42 -> 19b | B39: =Dashboard!B42 -> Amount Billed Water & Sewer-OTHER SALES-Southern | C39: =Dashboard!C42 -> Ksh. | D39: =D36+D37+D38 -> 2639401 | E39: =E36+E37+E38 -> 4074278 | F39: =F36+F37+F38 -> 3262024 | G39: =G36+G37+G38 -> 3537698 | H39: =H36+H37+H38 -> 3214104 | I39: =I36+I37+I38 -> 4208509.8 | J39: =J36+J37+J38 -> 5971041.8 | K39: =K36+K37+K38 -> 5367253 | ... O39: =O36+O37+O38 -> 5428445.6
A40: =Dashboard!A43 -> 14b | B40: =Dashboard!B43 -> Amount Collected-Southern | C40: =Dashboard!C43 -> Ksh. | D40: 2790436 | E40: 2736198 | F40: 3393417 | G40: 3422438 | H40: 2467633 | I40: 4421927 | J40: 3513934.5 | K40: 4356367.5 | L40: 5144246 | M40: 4095454 | N40: 6634073 | O40: 4777047
A41: =Dashboard!A52 -> 19 | B41: =Dashboard!B52 -> Collection Efficiency- | C41: =Dashboard!C52 -> %
A42: =Dashboard!#REF! -> #REF!
A43: =Dashboard!#REF! -> #REF! | O43: 195350
A44: =Dashboard!#REF! -> #REF! | B44: =Dashboard!#REF! -> #REF! | C44: =Dashboard!#REF! -> #REF! | D44: 1927795 | E44: 1909110 | F44: 2500535 | G44: 2020305 | H44: 1101790 | I44: 1303930 | J44: 1192160 | K44: 1212390 | L44: 1098935 | M44: 1195365 | N44: 1087650 | O44: 1287320
A45: =Dashboard!#REF! -> #REF! | B45: =Dashboard!#REF! -> #REF! | C45: =Dashboard!#REF! -> #REF! | D45: 1901026 | E45: 1780214 | F45: 2194780 | G45: 1857663 | H45: 1159219 | I45: 719484.9 | J45: 1033578.8 | K45: 1081510.6 | L45: 1228339.3 | M45: 973539 | N45: 945696.3 | O45: 1051931.7
A46: =Dashboard!#REF! -> #REF! | B46: =Dashboard!#REF! -> #REF! | C46: =Dashboard!#REF! -> #REF!
A47: =Dashboard!#REF! -> #REF! | B47: =Dashboard!#REF! -> #REF! | C47: =Dashboard!#REF! -> #REF! | D47: =D44+D45+D46 -> 3828821 | E47: =E44+E45+E46 -> 3689324 | F47: =F44+F45+F46 -> 4695315 | G47: =G44+G45+G46 -> 3877968 | H47: =H44+H45+H46 -> 2261009 | I47: =I44+I45+I46 -> 2023414.9 | J47: =J44+J45+J46 -> 2225738.8 | K47: =K44+K45+K46 -> 2293900.5 | ... O47: =O44+O45+O46 -> 2339251.7 | P47: =SUM(P44:P45) -> 0
A48: =Dashboard!#REF! -> #REF! | B48: =Dashboard!#REF! -> #REF! | C48: =Dashboard!#REF! -> #REF! | D48: 3167304 | E48: 1606664 | F48: 3201888 | G48: 3221111 | H48: 2496835 | I48: 4249840.5 | J48: 2616516 | K48: 1803754.8 | L48: 1989769 | M48: 3535820.5 | N48: 2279673.5 | O48: 3854161.5
A49: =Dashboard!#REF! -> #REF! | B49: =Dashboard!#REF! -> #REF! | C49: =Dashboard!#REF! -> #REF!
A50: =Dashboard!#REF! -> #REF! | O50: 60200.05
A51: =Dashboard!#REF! -> #REF! | B51: =Dashboard!#REF! -> #REF! | C51: =Dashboard!#REF! -> #REF! | D51: 1942595 | E51: 2693160 | F51: 2618030 | G51: 1837240 | H51: 2646735 | I51: 1922675 | J51: 2576655 | K51: 2435365 | L51: 2751275 | M51: 2816575 | N51: 2259705 | O51: 2641260
A52: =Dashboard!#REF! -> #REF! | B52: =Dashboard!#REF! -> #REF! | C52: =Dashboard!#REF! -> #REF! | D52: 933121 | E52: 1072672 | F52: 1114010 | G52: 868108 | H52: 1472915 | I52: 987003.5 | J52: 1970837.1 | K52: 1838167.1 | L52: 2084319 | M52: 2161919.5 | N52: 1706692.8 | O52: 1998094.8
A53: =Dashboard!#REF! -> #REF! | B53: =Dashboard!#REF! -> #REF! | C53: =Dashboard!#REF! -> #REF!
A54: =Dashboard!#REF! -> #REF! | B54: =Dashboard!#REF! -> #REF! | C54: =Dashboard!#REF! -> #REF! | D54: =D51+D52+D53 -> 2875716 | E54: =E51+E52+E53 -> 3765832 | F54: =F51+F52+F53 -> 3732040 | G54: =G51+G52+G53 -> 2705348 | H54: =H51+H52+H53 -> 4119650 | I54: =I51+I52+I53 -> 2909678.5 | J54: =J51+J52+J53 -> 4547492 | K54: =K51+K52+K53 -> 4273532.1 | ... O54: =O51+O52+O53 -> 4639354.8
A55: =Dashboard!#REF! -> #REF! | B55: =Dashboard!#REF! -> #REF! | C55: =Dashboard!#REF! -> #REF! | D55: 10474293 | E55: 1077542 | F55: 1514620 | G55: 5922130 | H55: 1013106 | I55: 1450539.5 | J55: 2593394.2 | K55: 8169148 | L55: 4304949.5 | M55: 2833281 | N55: 7027962 | O55: 1550306.2
A56: =Dashboard!#REF! -> #REF! | B56: =Dashboard!#REF! -> #REF! | C56: =Dashboard!#REF! -> #REF!
A57: =Dashboard!#REF! -> #REF! | O57: 102550
A58: =Dashboard!#REF! -> #REF! | B58: =Dashboard!#REF! -> #REF! | C58: =Dashboard!#REF! -> #REF! | D58: 1143215 | E58: 1253770 | F58: 1496530 | G58: 1098965 | H58: 984155 | I58: 937010 | J58: 918335 | K58: 781850 | L58: 869540 | M58: 791875 | N58: 848455 | O58: 846705
A59: =Dashboard!#REF! -> #REF! | B59: =Dashboard!#REF! -> #REF! | C59: =Dashboard!#REF! -> #REF! | D59: 267455 | E59: 280587 | F59: 317281 | G59: 265132 | H59: 253057 | I59: 185632.45 | J59: 290554.5 | K59: 278593.9 | L59: 293221.65 | M59: 256668.25 | N59: 268655.1 | O59: 273011.35
A60: =Dashboard!#REF! -> #REF! | B60: =Dashboard!#REF! -> #REF! | C60: =Dashboard!#REF! -> #REF!
A61: =Dashboard!#REF! -> #REF! | B61: =Dashboard!#REF! -> #REF! | C61: =Dashboard!#REF! -> #REF! | D61: =D58+D59+D60 -> 1410670 | E61: =E58+E59+E60 -> 1534357 | F61: =F58+F59+F60 -> 1813811 | G61: =G58+G59+G60 -> 1364097 | H61: =H58+H59+H60 -> 1237212 | I61: =I58+I59+I60 -> 1122642.4 | J61: =J58+J59+J60 -> 1208889.5 | K61: =K58+K59+K60 -> 1060443.9 | ... O61: =O58+O59+O60 -> 1119716.4
A62: =Dashboard!#REF! -> #REF! | B62: =Dashboard!#REF! -> #REF! | C62: =Dashboard!#REF! -> #REF! | D62: 1308785 | E62: 1646057 | F62: 1579483 | G62: 1708396 | H62: 1407047 | I62: 1030639 | J62: 1543151 | K62: 1371344.5 | L62: 1046449.7 | M62: 1235437 | N62: 1130466.3 | O62: 1098316
A63: =Dashboard!#REF! -> #REF! | B63: =Dashboard!#REF! -> #REF! | C63: =Dashboard!#REF! -> #REF!
A64: =Dashboard!#REF! -> #REF! | O64: 77800
A65: =Dashboard!#REF! -> #REF! | B65: =Dashboard!#REF! -> #REF! | C65: =Dashboard!#REF! -> #REF! | D65: 567085 | E65: 668235 | F65: 637835 | G65: 744565 | H65: 558960 | I65: 1609145 | J65: 2027975 | K65: 1900400 | L65: 1697570 | M65: 2318820 | N65: 1339470 | O65: 1609685
A66: =Dashboard!#REF! -> #REF! | B66: =Dashboard!#REF! -> #REF! | C66: =Dashboard!#REF! -> #REF! | D66: 327356 | E66: 328433 | F66: 320439 | G66: 339923 | H66: 310459 | I66: 397209.75 | J66: 1106455 | K66: 1024408 | L66: 855281.85 | M66: 897622 | N66: 888318.1 | O66: 933080.6
A67: =Dashboard!#REF! -> #REF! | B67: =Dashboard!#REF! -> #REF! | C67: =Dashboard!#REF! -> #REF!
A68: =Dashboard!#REF! -> #REF! | B68: =Dashboard!#REF! -> #REF! | C68: =Dashboard!#REF! -> #REF! | D68: =D65+D66+D67 -> 894441 | E68: =E65+E66+E67 -> 996668 | F68: =F65+F66+F67 -> 958274 | G68: =G65+G66+G67 -> 1084488 | H68: =H65+H66+H67 -> 869419 | I68: =I65+I66+I67 -> 2006354.8 | J68: =J65+J66+J67 -> 3134430 | K68: =K65+K66+K67 -> 2924808 | ... O68: =O65+O66+O67 -> 2542765.6
A69: =Dashboard!#REF! -> #REF! | B69: =Dashboard!#REF! -> #REF! | C69: =Dashboard!#REF! -> #REF! | D69: 713899 | E69: 1031071 | F69: 943486 | G69: 1175086 | H69: 858500 | I69: 1554633 | J69: 869274 | K69: 1723430.6 | L69: 2515639 | M69: 1882537 | N69: 2697191.2 | O69: 2015225
A70: =Dashboard!#REF! -> #REF! | B70: =Dashboard!#REF! -> #REF! | C70: =Dashboard!#REF! -> #REF!
A71: =Dashboard!#REF! -> #REF! | O71: 63200
A72: =Dashboard!#REF! -> #REF! | B72: =Dashboard!#REF! -> #REF! | C72: =Dashboard!#REF! -> #REF! | D72: 651215 | E72: 781985 | F72: 905435 | G72: 591950 | H72: 606465 | I72: 870985 | J72: 719225 | K72: 624080 | L72: 662235 | M72: 730225 | N72: 626835 | O72: 715135
A73: =Dashboard!#REF! -> #REF! | B73: =Dashboard!#REF! -> #REF! | C73: =Dashboard!#REF! -> #REF! | D73: 354459 | E73: 383475 | F73: 420852 | G73: 335447 | H73: 362409 | I73: 275456.25 | J73: 347604 | K73: 312228.8 | L73: 359262.8 | M73: 336727.25 | N73: 316763.65 | O73: 330383.85
A74: =Dashboard!#REF! -> #REF! | B74: =Dashboard!#REF! -> #REF! | C74: =Dashboard!#REF! -> #REF!
A75: =Dashboard!#REF! -> #REF! | B75: =Dashboard!#REF! -> #REF! | C75: =Dashboard!#REF! -> #REF! | D75: =D72+D73+D74 -> 1005674 | E75: =E72+E73+E74 -> 1165460 | F75: =F72+F73+F74 -> 1326287 | G75: =G72+G73+G74 -> 927397 | H75: =H72+H73+H74 -> 968874 | I75: =I72+I73+I74 -> 1146441.2 | J75: =J72+J73+J74 -> 1066829 | K75: =K72+K73+K74 -> 936308.8 | ... O75: =O72+O73+O74 -> 1045518.8
A76: =Dashboard!#REF! -> #REF! | B76: =Dashboard!#REF! -> #REF! | C76: =Dashboard!#REF! -> #REF! | D76: 1005674 | E76: 1165460 | F76: 1326287 | G76: 927397 | H76: 968874 | I76: 1146441.2 | J76: 1066829 | K76: 936308.8 | L76: 1021497.8 | M76: 1127652.2 | N76: 997398.65
A77: =Dashboard!#REF! -> #REF! | B77: =Dashboard!#REF! -> #REF! | C77: =Dashboard!#REF! -> #REF!
A78: =Dashboard!#REF! -> #REF! | O78: 16800
A79: =Dashboard!#REF! -> #REF! | B79: =Dashboard!#REF! -> #REF! | C79: =Dashboard!#REF! -> #REF! | D79: 315875 | E79: 377705 | F79: 434070 | G79: 445670 | H79: 308425 | I79: 304150 | J79: 374805 | K79: 351090 | L79: 258780 | M79: 468630 | N79: 304285 | O79: 494260
A80: =Dashboard!#REF! -> #REF! | B80: =Dashboard!#REF! -> #REF! | C80: =Dashboard!#REF! -> #REF! | D80: 0 | E80: 0 | F80: 0 | G80: 0 | H80: 0 | I80: 0 | J80: 0 | K80: 0 | L80: 0 | M80: 0 | N80: 0 | O80: 0
A81: =Dashboard!#REF! -> #REF! | B81: =Dashboard!#REF! -> #REF! | C81: =Dashboard!#REF! -> #REF!
A82: =Dashboard!#REF! -> #REF! | B82: =Dashboard!#REF! -> #REF! | C82: =Dashboard!#REF! -> #REF! | D82: =D79+D80+D81 -> 315875 | E82: =E79+E80+E81 -> 377705 | F82: =F79+F80+F81 -> 434070 | G82: =G79+G80+G81 -> 445670 | H82: =H79+H80+H81 -> 308425 | I82: =I79+I80+I81 -> 304150 | J82: =J79+J80+J81 -> 374805 | K82: =K79+K80+K81 -> 351090 | ... O82: =O79+O80+O81 -> 494260
A83: =Dashboard!#REF! -> #REF! | B83: =Dashboard!#REF! -> #REF! | C83: =Dashboard!#REF! -> #REF! | D83: 347640 | E83: 338375 | F83: 459268 | G83: 324140 | H83: 347491 | I83: 389604 | J83: 289506 | K83: 350590 | L83: 347934 | M83: 359088 | N83: 343492 | O83: 367577
A84: =Dashboard!#REF! -> #REF! | B84: =Dashboard!#REF! -> #REF! | C84: =Dashboard!#REF! -> #REF!
A85: =Dashboard!#REF! -> #REF! | O85: 177700
A86: =Dashboard!#REF! -> #REF! | B86: =Dashboard!#REF! -> #REF! | C86: =Dashboard!#REF! -> #REF! | D86: 788220 | E86: 1662000 | F86: 1165465 | G86: 1091740 | H86: 1044620 | I86: 1070700 | J86: 1373265 | K86: 1123855 | L86: 1034830 | M86: 1309955 | N86: 1052065 | O86: 1591310
A87: =Dashboard!#REF! -> #REF! | B87: =Dashboard!#REF! -> #REF! | C87: =Dashboard!#REF! -> #REF! | D87: 0 | E87: 0 | F87: 0 | G87: 0 | H87: 0 | I87: 0 | J87: 0 | K87: 0 | L87: 0 | M87: 0 | N87: 0 | O87: 0
A88: =Dashboard!#REF! -> #REF! | B88: =Dashboard!#REF! -> #REF! | C88: =Dashboard!#REF! -> #REF! | D88: 0 | E88: 0 | F88: 0 | G88: 0 | H88: 0 | I88: 0 | J88: 0 | K88: 0 | L88: 0 | M88: 0 | N88: 0 | O88: 0
A89: =Dashboard!#REF! -> #REF! | B89: =Dashboard!#REF! -> #REF! | C89: =Dashboard!#REF! -> #REF! | D89: =D86+D87+D88 -> 788220 | E89: =E86+E87+E88 -> 1662000 | F89: =F86+F87+F88 -> 1165465 | G89: =G86+G87+G88 -> 1091740 | H89: =H86+H87+H88 -> 1044620 | I89: =I86+I87+I88 -> 1070700 | J89: =J86+J87+J88 -> 1373265 | K89: =K86+K87+K88 -> 1123855 | ... O89: =O86+O87+O88 -> 1591310
A90: =Dashboard!#REF! -> #REF! | B90: =Dashboard!#REF! -> #REF! | C90: =Dashboard!#REF! -> #REF! | D90: 978890 | E90: 543915 | F90: 1248065 | G90: 1297244 | H90: 753106 | I90: 1392742 | J90: 1146903 | K90: 1273541 | L90: 1239975 | M90: 1011325 | N90: 1246374 | O90: 1431933
A91: =Dashboard!#REF! -> #REF! | B91: =Dashboard!#REF! -> #REF! | C91: =Dashboard!#REF! -> #REF!
A92: =Dashboard!#REF! -> #REF! | O92: 89900
A93: =Dashboard!#REF! -> #REF! | B93: =Dashboard!#REF! -> #REF! | C93: =Dashboard!#REF! -> #REF! | D93: 640865 | E93: 1037905 | F93: 704215 | G93: 915800 | H93: 991640 | I93: 827305 | J93: 1088540 | K93: 967500 | L93: 745830 | M93: 1037860 | N93: 800170 | O93: 800110
A94: =Dashboard!#REF! -> #REF! | B94: =Dashboard!#REF! -> #REF! | C94: =Dashboard!#REF! -> #REF! | D94: 0 | E94: 0 | F94: 0 | G94: 0 | H94: 0 | I94: 0 | J94: 0 | K94: 0 | L94: 0 | M94: 0 | N94: 0 | O94: 0
A95: =Dashboard!#REF! -> #REF! | B95: =Dashboard!#REF! -> #REF! | C95: =Dashboard!#REF! -> #REF! | D95: 0 | E95: 0 | F95: 0 | G95: 0 | H95: 0 | I95: 0 | J95: 0 | K95: 0 | L95: 0 | M95: 0 | N95: 0 | O95: 0
A96: =Dashboard!#REF! -> #REF! | B96: =Dashboard!#REF! -> #REF! | C96: =Dashboard!#REF! -> #REF! | D96: =D93+D94+D95 -> 640865 | E96: =E93+E94+E95 -> 1037905 | F96: =F93+F94+F95 -> 704215 | G96: =G93+G94+G95 -> 915800 | H96: =H93+H94+H95 -> 991640 | I96: =I93+I94+I95 -> 827305 | J96: =J93+J94+J95 -> 1088540 | K96: =K93+K94+K95 -> 967500 | ... O96: =O93+O94+O95 -> 800110
A97: =Dashboard!#REF! -> #REF! | B97: =Dashboard!#REF! -> #REF! | C97: =Dashboard!#REF! -> #REF! | D97: 750007 | E97: 822837 | F97: 742598 | G97: 625968 | H97: 508536 | I97: 1084948 | J97: 661424 | K97: 1000176 | L97: 1040698 | M97: 823504 | N97: 797015 | O97: 926782
A98: =Dashboard!#REF! -> #REF! | B98: =Dashboard!#REF! -> #REF! | C98: =Dashboard!#REF! -> #REF!
A99: =Dashboard!#REF! -> #REF! | O99: 11150
A100: =Dashboard!#REF! -> #REF! | B100: =Dashboard!#REF! -> #REF! | C100: =Dashboard!#REF! -> #REF! | D100: 56215 | E100: 96580 | F100: 100920 | G100: 57295 | H100: 76340 | I100: 87705 | J100: 92920 | K100: 88005 | L100: 112290 | M100: 71075 | N100: 80210 | O100: 80970
A101: =Dashboard!#REF! -> #REF! | B101: =Dashboard!#REF! -> #REF! | C101: =Dashboard!#REF! -> #REF! | D101: 0 | E101: 0 | F101: 0 | G101: 0 | H101: 0 | I101: 0 | J101: 0 | K101: 0 | L101: 0 | N101: 0 | O101: 0
A102: =Dashboard!#REF! -> #REF! | B102: =Dashboard!#REF! -> #REF! | C102: =Dashboard!#REF! -> #REF! | D102: 0 | E102: 0 | F102: 0 | G102: 0 | H102: 0 | I102: 0 | J102: 0 | K102: 0 | L102: 0 | N102: 0 | O102: 0
...

Sheet KPI 1
A1: KPI | B1: KPI | C1: =Dashboard!B6 -> Total Water Sales (Ksh) | G1: Actual month: | I1: =INDEX($E$18:$P$18,Actual_month) -> 46082 | L1: Dashboard
A2: Unit | C2: Ksh.
C3: l | J3: Comments
C4: l | R4: actual | S4: =INDEX(E27:P27,Actual_month) -> 179809530
C5: l | R5: target | S5: =INDEX(E26:P26,Actual_month) -> 161020690
R6: 0.9 | S6: =+S5*R6 -> 144918621
J9: Actions
C18: MONTHLY | E18: 45839 | F18: 45870 | G18: 45901 | H18: 45931 | I18: 45962 | J18: 45992 | K18: 46023 | L18: 46054 | M18: 46082 | N18: 46113 | O18: 46143 | P18: 46174 | Q18: Total
D19: budget2025/26 | E19: =BUDGET2526!D6 -> 16944468 | F19: =BUDGET2526!E6 -> 17161528 | G19: =BUDGET2526!F6 -> 17381828 | H19: =BUDGET2526!G6 -> 17650728 | I19: =BUDGET2526!H6 -> 17903428 | J19: =BUDGET2526!I6 -> 18139928 | K19: =BUDGET2526!J6 -> 18392628 | L19: =BUDGET2526!K6 -> 18621028 | ... P19: =BUDGET2526!O6 -> 19385588 | Q19: =SUM(E19:P19) -> 2.1862023e+08
D20: ACTUAL2025/26 | E20: ='ACTUAL 2526'!E6 -> 18389070 | F20: ='ACTUAL 2526'!F6 -> 22070060 | G20: ='ACTUAL 2526'!G6 -> 18397530 | H20: ='ACTUAL 2526'!H6 -> 21684080 | I20: ='ACTUAL 2526'!I6 -> 17036780 | J20: ='ACTUAL 2526'!J6 -> 16441310 | K20: ='ACTUAL 2526'!K6 -> 25608070 | L20: ='ACTUAL 2526'!L6 -> 21831150 | ... P20: ='ACTUAL 2526'!P6 -> 0 | Q20: =SUM(E20:P20) -> 179809530
D21: ACTUAL2024/25 | E21: ='Actual 202425'!E6 -> 11183420 | F21: ='Actual 202425'!F6 -> 13918957 | G21: ='Actual 202425'!G6 -> 13018249 | H21: ='Actual 202425'!H6 -> 12608519 | I21: ='Actual 202425'!I6 -> 14174994 | J21: ='Actual 202425'!J6 -> 8977679 | K21: ='Actual 202425'!K6 -> 14767948 | L21: ='Actual 202425'!L6 -> 13060906 | ... P21: ='Actual 202425'!P6 -> 20899160 | Q21: =SUM(E21:P21) -> 170033199
D22: DIFFERENCE | Q22: =SUM(E22:P22) -> 0
D23: %REALISATION | E23: =E20/E19 -> 1.0852551 | F23: =F20/F19 -> 1.2860195 | G23: =G20/G19 -> 1.0584347 | H23: =H20/H19 -> 1.2285091 | I23: =I20/I19 -> 0.95159319 | J23: =J20/J19 -> 0.90636028 | K23: =K20/K19 -> 1.3923008 | L23: =L20/L19 -> 1.1723923 | ... P23: =P20/P19 -> 0
C25: CUMULATIVE | E25: =E18 -> 45839 | F25: =F18 -> 45870 | G25: =G18 -> 45901 | H25: =H18 -> 45931 | I25: =I18 -> 45962 | J25: =J18 -> 45992 | K25: =K18 -> 46023 | L25: =L18 -> 46054 | ... P25: =P18 -> 46174
D26: =D19 -> budget2025/26 | E26: =SUM($E19:E19) -> 16944468 | F26: =SUM($E19:F19) -> 34105996 | G26: =SUM($E19:G19) -> 51487823 | H26: =SUM($E19:H19) -> 69138551 | I26: =SUM($E19:I19) -> 87041979 | J26: =SUM($E19:J19) -> 1.0518191e+08 | K26: =SUM($E19:K19) -> 1.2357453e+08 | L26: =SUM($E19:L19) -> 1.4219556e+08 | ... P26: =SUM($E19:P19) -> 2.1862023e+08
D27: =D20 -> ACTUAL2025/26 | E27: =SUM($E20:E20) -> 18389070 | F27: =SUM($E20:F20) -> 40459130 | G27: =SUM($E20:G20) -> 58856660 | H27: =SUM($E20:H20) -> 80540740 | I27: =SUM($E20:I20) -> 97577520 | J27: =SUM($E20:J20) -> 114018830 | K27: =SUM($E20:K20) -> 139626900 | L27: =SUM($E20:L20) -> 161458050 | ... P27: =SUM($E20:P20) -> 179809530
D28: =D21 -> ACTUAL2024/25 | E28: =SUM($E21:E21) -> 11183420 | F28: =SUM($E21:F21) -> 25102377 | G28: =SUM($E21:G21) -> 38120626 | H28: =SUM($E21:H21) -> 50729145 | I28: =SUM($E21:I21) -> 64904139 | J28: =SUM($E21:J21) -> 73881818 | K28: =SUM($E21:K21) -> 88649766 | L28: =SUM($E21:L21) -> 101710672 | ... P28: =SUM($E21:P21) -> 170033199
D29: DIFFERENCE | E29: =SUM($E22:E22) -> 0 | F29: =SUM($E22:F22) -> 0 | G29: =SUM($E22:G22) -> 0 | H29: =SUM($E22:H22) -> 0 | I29: =SUM($E22:I22) -> 0 | J29: =SUM($E22:J22) -> 0 | K29: =SUM($E22:K22) -> 0 | L29: =SUM($E22:L22) -> 0 | ... P29: =SUM($E22:P22) -> 0
D30: =D23 -> %REALISATION | E30: =E27/E26 -> 1.0852551 | F30: =F27/F26 -> 1.1862762 | G30: =G27/G26 -> 1.143118 | H30: =H27/H26 -> 1.164918 | I30: =I27/I26 -> 1.1210398 | J30: =J27/J26 -> 1.0840156 | K30: =K27/K26 -> 1.1299003 | L30: =L27/L26 -> 1.1354648 | ... P30: =P27/P26 -> 0.82247433

Sheet KPI 3 (2)
A1: KPI | B1: =Dashboard!A8 -> 3 | C1: =Dashboard!B8 -> Bulk water | G1: Actual month: | I1: =INDEX($E$18:$P$18,Actual_month) -> 46082 | L1: Dashboard
A2: Unit | C2: Ksh.
C3: l | J3: Comments
C4: l | R4: actual | S4: =INDEX(E27:P27,Actual_month) -> 704120
C5: l | R5: target | S5: =INDEX(E26:P26,Actual_month) -> 810000
R6: 0.9 | S6: =+S5*R6 -> 729000
J9: Actions
C18: MONTHLY | E18: ='KPI 1'!E18 -> 45839 | F18: ='KPI 1'!F18 -> 45870 | G18: ='KPI 1'!G18 -> 45901 | H18: ='KPI 1'!H18 -> 45931 | I18: ='KPI 1'!I18 -> 45962 | J18: ='KPI 1'!J18 -> 45992 | K18: ='KPI 1'!K18 -> 46023 | L18: ='KPI 1'!L18 -> 46054 | ... P18: ='KPI 1'!P18 -> 46174 | Q18: Total
D19: ='KPI 1'!D19 -> budget2025/26 | E19: =BUDGET2526!D14 -> 90000 | F19: =BUDGET2526!E14 -> 90000 | G19: =BUDGET2526!F14 -> 90000 | H19: =BUDGET2526!G14 -> 90000 | I19: =BUDGET2526!H14 -> 90000 | J19: =BUDGET2526!I14 -> 90000 | K19: =BUDGET2526!J14 -> 90000 | L19: =BUDGET2526!K14 -> 90000 | ... P19: =BUDGET2526!O14 -> 90000 | Q19: =SUM(E19:P19) -> 1080000
D20: ='KPI 1'!D20 -> ACTUAL2025/26 | E20: =Actual2223!D13 -> 86850 | F20: =Actual2223!E13 -> 84450 | G20: =Actual2223!F13 -> 56450 | H20: =Actual2223!G13 -> 97020 | I20: =Actual2223!H13 -> 61350 | J20: =Actual2223!I13 -> 68250 | K20: =Actual2223!J13 -> 83100 | L20: =Actual2223!K13 -> 90450 | ... P20: =Actual2223!O13 -> 28100 | Q20: =SUM(E20:P20) -> 820170
D21: ='KPI 1'!D21 -> ACTUAL2024/25 | E21: =ACTUAL2122!D14 -> 727660 | F21: =ACTUAL2122!E14 -> 675185 | G21: =ACTUAL2122!F14 -> 754220 | H21: =ACTUAL2122!G14 -> 824710 | I21: =ACTUAL2122!H14 -> 618150 | J21: =ACTUAL2122!I14 -> 676645 | K21: =ACTUAL2122!J14 -> 558750 | L21: =ACTUAL2122!K14 -> 717984 | ... P21: =ACTUAL2122!O14 -> 1163650 | Q21: =SUM(E21:P21) -> 9807921
D22: ='KPI 1'!D22 -> DIFFERENCE | E22: =IF(E20=0,0,E20-E19) -> -3150 | F22: =IF(F20=0,0,F20-F19) -> -5550 | G22: =IF(G20=0,0,G20-G19) -> -33550 | H22: =IF(H20=0,0,H20-H19) -> 7020 | I22: =IF(I20=0,0,I20-I19) -> -28650 | J22: =IF(J20=0,0,J20-J19) -> -21750 | K22: =IF(K20=0,0,K20-K19) -> -6900 | L22: =IF(L20=0,0,L20-L19) -> 450 | ... P22: =IF(P20=0,0,P20-P19) -> -61900 | Q22: =SUM(E22:P22) -> -259830
D23: ='KPI 1'!D23 -> %REALISATION | E23: =E21/E19 -> 8.0851111 | F23: =F20/F19 -> 0.93833333 | G23: =G20/G19 -> 0.62722222 | H23: =H20/H19 -> 1.078 | I23: =I20/I19 -> 0.68166667 | J23: =J20/J19 -> 0.75833333 | K23: =K20/K19 -> 0.92333333 | L23: =L20/L19 -> 1.005 | M23: =M20/M19 -> 0.84666667 | ... P23: =P20/P19 -> 0.31222222
C25: CUMULATIVE | D25: ='KPI 1'!D25 -> 0 | E25: ='KPI 1'!E25 -> 45839 | F25: ='KPI 1'!F25 -> 45870 | G25: ='KPI 1'!G25 -> 45901 | H25: ='KPI 1'!H25 -> 45931 | I25: ='KPI 1'!I25 -> 45962 | J25: ='KPI 1'!J25 -> 45992 | K25: ='KPI 1'!K25 -> 46023 | ... P25: ='KPI 1'!P25 -> 46174
D26: ='KPI 1'!D26 -> budget2025/26 | E26: =SUM($E19:E19) -> 90000 | F26: =SUM($E19:F19) -> 180000 | G26: =SUM($E19:G19) -> 270000 | H26: =SUM($E19:H19) -> 360000 | I26: =SUM($E19:I19) -> 450000 | J26: =SUM($E19:J19) -> 540000 | K26: =SUM($E19:K19) -> 630000 | L26: =SUM($E19:L19) -> 720000 | ... P26: =SUM($E19:P19) -> 1080000
D27: ='KPI 1'!D27 -> ACTUAL2025/26 | E27: =SUM($E20:E20) -> 86850 | F27: =SUM($E20:F20) -> 171300 | G27: =SUM($E20:G20) -> 227750 | H27: =SUM($E20:H20) -> 324770 | I27: =SUM($E20:I20) -> 386120 | J27: =SUM($E20:J20) -> 454370 | K27: =SUM($E20:K20) -> 537470 | L27: =SUM($E20:L20) -> 627920 | ... P27: =SUM($E20:P20) -> 820170
D28: ='KPI 1'!D28 -> ACTUAL2024/25 | E28: =SUM($E21:E21) -> 727660 | F28: =SUM($E21:F21) -> 1402845 | G28: =SUM($E21:G21) -> 2157065 | H28: =SUM($E21:H21) -> 2981775 | I28: =SUM($E21:I21) -> 3599925 | J28: =SUM($E21:J21) -> 4276570 | K28: =SUM($E21:K21) -> 4835320 | L28: =SUM($E21:L21) -> 5553304 | ... P28: =SUM($E21:P21) -> 9807921
D29: ='KPI 1'!D29 -> DIFFERENCE | E29: =SUM($E22:E22) -> -3150 | F29: =SUM($E22:F22) -> -8700 | G29: =SUM($E22:G22) -> -42250 | H29: =SUM($E22:H22) -> -35230 | I29: =SUM($E22:I22) -> -63880 | J29: =SUM($E22:J22) -> -85630 | K29: =SUM($E22:K22) -> -92530 | L29: =SUM($E22:L22) -> -92080 | ... P29: =SUM($E22:P22) -> -259830
D30: ='KPI 1'!D30 -> %REALISATION | E30: =E28/E26 -> 8.0851111 | F30: =F27/F26 -> 0.95166667 | G30: =G27/G26 -> 0.84351852 | H30: =H27/H26 -> 0.90213889 | I30: =I27/I26 -> 0.85804444 | J30: =J27/J26 -> 0.84142593 | K30: =K27/K26 -> 0.85312698 | L30: =L27/L26 -> 0.87211111 | M30: =M27/M26 -> 0.86928395 | ... P30: =P27/P26 -> 0.75941667

Sheet KPI 2
A1: KPI | B1: =Dashboard!A7 -> 2 | C1: =Dashboard!B7 -> Total Sewerage Sales (Ksh) | G1: Actual month: | I1: =INDEX($E$18:$P$18,Actual_month) -> 46082 | L1: Dashboard
A2: Unit | C2: Ksh.
C3: l | J3: Comments
C4: l | R4: actual | S4: =INDEX(E27:P27,Actual_month) -> 52285082
C5: l | R5: target | S5: =INDEX(E26:P26,Actual_month) -> 46508629
R6: 0.9 | S6: =+S5*R6 -> 41857766
J9: Actions
C18: MONTHLY | E18: ='KPI 1'!E18 -> 45839 | F18: ='KPI 1'!F18 -> 45870 | G18: ='KPI 1'!G18 -> 45901 | H18: ='KPI 1'!H18 -> 45931 | I18: ='KPI 1'!I18 -> 45962 | J18: ='KPI 1'!J18 -> 45992 | K18: ='KPI 1'!K18 -> 46023 | L18: ='KPI 1'!L18 -> 46054 | ... P18: ='KPI 1'!P18 -> 46174 | Q18: Total
D19: ='KPI 1'!D19 -> budget2025/26 | E19: =BUDGET2526!D7 -> 5070284.1 | F19: =BUDGET2526!E7 -> 5094619.4 | G19: =BUDGET2526!F7 -> 5118954.8 | H19: =BUDGET2526!G7 -> 5143290.1 | I19: =BUDGET2526!H7 -> 5167625.4 | J19: =BUDGET2526!I7 -> 5191960.8 | K19: =BUDGET2526!J7 -> 5216296.1 | L19: =BUDGET2526!K7 -> 5240631.4 | ... P19: =BUDGET2526!O7 -> 5337972.7 | Q19: =SUM(E19:P19) -> 62449541
D20: ='KPI 1'!D20 -> ACTUAL2025/26 | E20: ='ACTUAL 2526'!E7 -> 5703321 | F20: ='ACTUAL 2526'!F7 -> 6046366 | G20: ='ACTUAL 2526'!G7 -> 5720536 | H20: ='ACTUAL 2526'!H7 -> 5831421 | I20: ='ACTUAL 2526'!I7 -> 5343133.5 | J20: ='ACTUAL 2526'!J7 -> 4905403.8 | K20: ='ACTUAL 2526'!K7 -> 6958143.5 | L20: ='ACTUAL 2526'!L7 -> 5826591 | ... P20: ='ACTUAL 2526'!P7 -> 0 | Q20: =SUM(E20:P20) -> 52285082
D21: ='KPI 1'!D21 -> ACTUAL2024/25 | E21: ='Actual 202425'!E7 -> 4109000.4 | F21: ='Actual 202425'!F7 -> 5060354.7 | G21: ='Actual 202425'!G7 -> 4299927.7 | H21: ='Actual 202425'!H7 -> 4437132.7 | I21: ='Actual 202425'!I7 -> 4483043.5 | J21: ='Actual 202425'!J7 -> 3764102.7 | K21: ='Actual 202425'!K7 -> 5424976.2 | L21: ='Actual 202425'!L7 -> 4666903.2 | ... P21: ='Actual 202425'!P7 -> 6224363.5 | Q21: =SUM(E21:P21) -> 59277177
D22: ='KPI 1'!D22 -> DIFFERENCE | E22: =IF(E20=0,0,E20-E19) -> 633036.91 | F22: =IF(F20=0,0,F20-F19) -> 951746.58 | G22: =IF(G20=0,0,G20-G19) -> 601581.24 | H22: =IF(H20=0,0,H20-H19) -> 688130.91 | I22: =IF(I20=0,0,I20-I19) -> 175508.08 | J22: =IF(J20=0,0,J20-J19) -> -286556.95 | K22: =IF(K20=0,0,K20-K19) -> 1741847.4 | L22: =IF(L20=0,0,L20-L19) -> 585959.58 | ... P22: =IF(P20=0,0,P20-P19) -> 0 | Q22: =SUM(E22:P22) -> 5776453
D23: ='KPI 1'!D23 -> %REALISATION | E23: =E20/E19 -> 1.1248524 | F23: =F20/F19 -> 1.1868141 | G23: =G20/G19 -> 1.1175203 | H23: =H20/H19 -> 1.133792 | I23: =I20/I19 -> 1.033963 | J23: =J20/J19 -> 0.94480757 | K23: =K20/K19 -> 1.3339242 | L23: =L20/L19 -> 1.1118109 | ... P23: =P20/P19 -> 0
C25: CUMULATIVE | D25: ='KPI 1'!D25 -> 0 | E25: ='KPI 1'!E25 -> 45839 | F25: ='KPI 1'!F25 -> 45870 | G25: ='KPI 1'!G25 -> 45901 | H25: ='KPI 1'!H25 -> 45931 | I25: ='KPI 1'!I25 -> 45962 | J25: ='KPI 1'!J25 -> 45992 | K25: ='KPI 1'!K25 -> 46023 | ... P25: ='KPI 1'!P25 -> 46174
D26: ='KPI 1'!D26 -> budget2025/26 | E26: =SUM($E19:E19) -> 5070284.1 | F26: =SUM($E19:F19) -> 10164904 | G26: =SUM($E19:G19) -> 15283858 | H26: =SUM($E19:H19) -> 20427148 | I26: =SUM($E19:I19) -> 25594774 | J26: =SUM($E19:J19) -> 30786735 | K26: =SUM($E19:K19) -> 36003031 | L26: =SUM($E19:L19) -> 41243662 | ... P26: =SUM($E19:P19) -> 62449541
D27: ='KPI 1'!D27 -> ACTUAL2025/26 | E27: =SUM($E20:E20) -> 5703321 | F27: =SUM($E20:F20) -> 11749687 | G27: =SUM($E20:G20) -> 17470223 | H27: =SUM($E20:H20) -> 23301644 | I27: =SUM($E20:I20) -> 28644778 | J27: =SUM($E20:J20) -> 33550181 | K27: =SUM($E20:K20) -> 40508325 | L27: =SUM($E20:L20) -> 46334916 | ... P27: =SUM($E20:P20) -> 52285082
D28: ='KPI 1'!D28 -> ACTUAL2024/25 | E28: =SUM($E21:E21) -> 4109000.4 | F28: =SUM($E21:F21) -> 9169355.1 | G28: =SUM($E21:G21) -> 13469283 | H28: =SUM($E21:H21) -> 17906415 | I28: =SUM($E21:I21) -> 22389459 | J28: =SUM($E21:J21) -> 26153562 | K28: =SUM($E21:K21) -> 31578538 | L28: =SUM($E21:L21) -> 36245441 | ... P28: =SUM($E21:P21) -> 59277177
D29: ='KPI 1'!D29 -> DIFFERENCE | E29: =SUM($E22:E22) -> 633036.91 | F29: =SUM($E22:F22) -> 1584783.5 | G29: =SUM($E22:G22) -> 2186364.7 | H29: =SUM($E22:H22) -> 2874495.6 | I29: =SUM($E22:I22) -> 3050003.7 | J29: =SUM($E22:J22) -> 2763446.8 | K29: =SUM($E22:K22) -> 4505294.2 | L29: =SUM($E22:L22) -> 5091253.8 | ... P29: =SUM($E22:P22) -> 5776453
D30: ='KPI 1'!D30 -> %REALISATION | E30: =E27/E26 -> 1.1248524 | F30: =F27/F26 -> 1.1559074 | G30: =G27/G26 -> 1.1430506 | H30: =H27/H26 -> 1.1407194 | I30: =I27/I26 -> 1.1191651 | J30: =J27/J26 -> 1.089761 | K30: =K27/K26 -> 1.1251365 | L30: =L27/L26 -> 1.1234433 | ... P30: =P27/P26 -> 0.83723725

Sheet KPI a
A1: =Dashboard!A8 -> 3 | B1: =Dashboard!B8 -> Bulk water | C1: =Dashboard!C8 -> Ksh | G1: Actual month: | I1: =INDEX($E$18:$P$18,Actual_month) -> 46082 | L1: Dashboard
A2: Unit | C2: Ksh.
C3: l | J3: Comments
C4: l | R4: actual | S4: =INDEX(E27:P27,Actual_month) -> 1096030
C5: l | R5: target | S5: =INDEX(E26:P26,Actual_month) -> 577170
R6: 0.9 | S6: =+S5*R6 -> 519453
J9: Actions
C18: MONTHLY | E18: ='KPI 1'!E18 -> 45839 | F18: ='KPI 1'!F18 -> 45870 | G18: ='KPI 1'!G18 -> 45901 | H18: ='KPI 1'!H18 -> 45931 | I18: ='KPI 1'!I18 -> 45962 | J18: ='KPI 1'!J18 -> 45992 | K18: ='KPI 1'!K18 -> 46023 | L18: ='KPI 1'!L18 -> 46054 | ... P18: ='KPI 1'!P18 -> 46174 | Q18: Total
D19: ='KPI 1'!D19 -> budget2025/26 | E19: =BUDGET2526!D8 -> 64130 | F19: =BUDGET2526!E8 -> 64130 | G19: =BUDGET2526!F8 -> 64130 | H19: =BUDGET2526!G8 -> 64130 | I19: =BUDGET2526!H8 -> 64130 | J19: =BUDGET2526!I8 -> 64130 | K19: =BUDGET2526!J8 -> 64130 | L19: =BUDGET2526!K8 -> 64130 | ... P19: =BUDGET2526!O8 -> 64130 | Q19: =SUM(E19:P19) -> 769560
D20: ='KPI 1'!D20 -> ACTUAL2025/26 | E20: ='ACTUAL 2526'!E8 -> 185510 | F20: ='ACTUAL 2526'!F8 -> 166400 | G20: ='ACTUAL 2526'!G8 -> 165100 | H20: ='ACTUAL 2526'!H8 -> 164840 | I20: ='ACTUAL 2526'!I8 -> 126750 | J20: ='ACTUAL 2526'!J8 -> 122200 | K20: ='ACTUAL 2526'!K8 -> 46020 | L20: ='ACTUAL 2526'!L8 -> 88920 | ... P20: ='ACTUAL 2526'!P8 -> 0 | Q20: =SUM(E20:P20) -> 1096030
D21: ='KPI 1'!D21 -> ACTUAL2024/25 | E21: ='Actual 202425'!E8 -> 22320 | F21: ='Actual 202425'!F8 -> 28370 | G21: ='Actual 202425'!G8 -> 64720 | H21: ='Actual 202425'!H8 -> 22800 | I21: ='Actual 202425'!I8 -> 40480 | J21: ='Actual 202425'!J8 -> 25520 | K21: ='Actual 202425'!K8 -> 51520 | L21: ='Actual 202425'!L8 -> 59520 | ... P21: ='Actual 202425'!P8 -> 165230 | Q21: =SUM(E21:P21) -> 721860
D22: ='KPI 1'!D22 -> DIFFERENCE | E22: =IF(E20=0,0,E20-E19) -> 121380 | F22: =IF(F20=0,0,F20-F19) -> 102270 | G22: =IF(G20=0,0,G20-G19) -> 100970 | H22: =IF(H20=0,0,H20-H19) -> 100710 | I22: =IF(I20=0,0,I20-I19) -> 62620 | J22: =IF(J20=0,0,J20-J19) -> 58070 | K22: =IF(K20=0,0,K20-K19) -> -18110 | L22: =IF(L20=0,0,L20-L19) -> 24790 | ... P22: =IF(P20=0,0,P20-P19) -> 0 | Q22: =SUM(E22:P22) -> 518860
D23: ='KPI 1'!D23 -> %REALISATION | E23: =E20/E19 -> 2.8927179 | F23: =F20/F19 -> 2.5947295 | G23: =G20/G19 -> 2.5744581 | H23: =H20/H19 -> 2.5704039 | I23: =I20/I19 -> 1.9764541 | J23: =J20/J19 -> 1.9055044 | K23: =K20/K19 -> 0.71760487 | L23: =L20/L19 -> 1.3865586 | ... P23: =P20/P19 -> 0
C25: CUMULATIVE | D25: ='KPI 1'!D25 -> 0 | E25: ='KPI 1'!E25 -> 45839 | F25: ='KPI 1'!F25 -> 45870 | G25: ='KPI 1'!G25 -> 45901 | H25: ='KPI 1'!H25 -> 45931 | I25: ='KPI 1'!I25 -> 45962 | J25: ='KPI 1'!J25 -> 45992 | K25: ='KPI 1'!K25 -> 46023 | ... P25: ='KPI 1'!P25 -> 46174
D26: ='KPI 1'!D26 -> budget2025/26 | E26: =SUM($E19:E19) -> 64130 | F26: =SUM($E19:F19) -> 128260 | G26: =SUM($E19:G19) -> 192390 | H26: =SUM($E19:H19) -> 256520 | I26: =SUM($E19:I19) -> 320650 | J26: =SUM($E19:J19) -> 384780 | K26: =SUM($E19:K19) -> 448910 | L26: =SUM($E19:L19) -> 513040 | ... P26: =SUM($E19:P19) -> 769560
D27: ='KPI 1'!D27 -> ACTUAL2025/26 | E27: =SUM($E20:E20) -> 185510 | F27: =SUM($E20:F20) -> 351910 | G27: =SUM($E20:G20) -> 517010 | H27: =SUM($E20:H20) -> 681850 | I27: =SUM($E20:I20) -> 808600 | J27: =SUM($E20:J20) -> 930800 | K27: =SUM($E20:K20) -> 976820 | L27: =SUM($E20:L20) -> 1065740 | ... P27: =SUM($E20:P20) -> 1096030
D28: ='KPI 1'!D28 -> ACTUAL2024/25 | E28: =SUM($E21:E21) -> 22320 | F28: =SUM($E21:F21) -> 50690 | G28: =SUM($E21:G21) -> 115410 | H28: =SUM($E21:H21) -> 138210 | I28: =SUM($E21:I21) -> 178690 | J28: =SUM($E21:J21) -> 204210 | K28: =SUM($E21:K21) -> 255730 | L28: =SUM($E21:L21) -> 315250 | ... P28: =SUM($E21:P21) -> 721860
D29: ='KPI 1'!D29 -> DIFFERENCE | E29: =SUM($E22:E22) -> 121380 | F29: =SUM($E22:F22) -> 223650 | G29: =SUM($E22:G22) -> 324620 | H29: =SUM($E22:H22) -> 425330 | I29: =SUM($E22:I22) -> 487950 | J29: =SUM($E22:J22) -> 546020 | K29: =SUM($E22:K22) -> 527910 | L29: =SUM($E22:L22) -> 552700 | ... P29: =SUM($E22:P22) -> 518860
D30: ='KPI 1'!D30 -> %REALISATION | E30: =E27/E26 -> 2.8927179 | F30: =F27/F26 -> 2.7437237 | G30: =G27/G26 -> 2.6873018 | H30: =H27/H26 -> 2.6580773 | I30: =I27/I26 -> 2.5217527 | J30: =J27/J26 -> 2.4190446 | K30: =K27/K26 -> 2.1759818 | L30: =L27/L26 -> 2.0773039 | ... P30: =P27/P26 -> 1.4242294

Sheet KPI b1
B1: =Dashboard!A9 -> 4 | C1: =Dashboard!B9 -> Sanitation | G1: Actual month: | I1: =INDEX($E$18:$P$18,Actual_month) -> 46082 | L1: Dashboard
A2: Unit | C2: Ksh.
C3: l | J3: Comments
C4: l | R4: actual | S4: =INDEX(E27:P27,Actual_month) -> 8990471
C5: l | R5: target | S5: =INDEX(E26:P26,Actual_month) -> 8010534.5
R6: 0.9 | S6: =+S5*R6 -> 7209481
J9: Actions
C18: MONTHLY | E18: ='KPI 1'!E18 -> 45839 | F18: ='KPI 1'!F18 -> 45870 | G18: ='KPI 1'!G18 -> 45901 | H18: ='KPI 1'!H18 -> 45931 | I18: ='KPI 1'!I18 -> 45962 | J18: ='KPI 1'!J18 -> 45992 | K18: ='KPI 1'!K18 -> 46023 | L18: ='KPI 1'!L18 -> 46054 | ... P18: ='KPI 1'!P18 -> 46174 | Q18: Total
D19: ='KPI 1'!D19 -> budget2025/26 | E19: =BUDGET2526!D10 -> 842723.39 | F19: =BUDGET2526!E10 -> 853576.39 | G19: =BUDGET2526!F10 -> 864591.39 | H19: =BUDGET2526!G10 -> 878036.39 | I19: =BUDGET2526!H10 -> 890671.39 | J19: =BUDGET2526!I10 -> 902496.39 | K19: =BUDGET2526!J10 -> 915131.39 | L19: =BUDGET2526!K10 -> 926551.39 | ... P19: =BUDGET2526!O10 -> 964779.39 | Q19: =SUM(E19:P19) -> 10877012
D20: ='KPI 1'!D20 -> ACTUAL2025/26 | E20: ='ACTUAL 2526'!E10 -> 919453.5 | F20: ='ACTUAL 2526'!F10 -> 1103503 | G20: ='ACTUAL 2526'!G10 -> 919876.5 | H20: ='ACTUAL 2526'!H10 -> 1084204 | I20: ='ACTUAL 2526'!I10 -> 851839 | J20: ='ACTUAL 2526'!J10 -> 822065.5 | K20: ='ACTUAL 2526'!K10 -> 1280403.5 | L20: ='ACTUAL 2526'!L10 -> 1091557.5 | ... P20: ='ACTUAL 2526'!P10 -> 0 | Q20: =SUM(E20:P20) -> 8990471
D21: ='KPI 1'!D21 -> ACTUAL2024/25 | E21: =Actual2223!D9 -> 392600 | F21: =Actual2223!E9 -> 394950 | G21: =Actual2223!F9 -> 409650 | H21: =Actual2223!G9 -> 414850 | I21: =Actual2223!H9 -> 417300 | J21: =Actual2223!I9 -> 422000 | K21: =Actual2223!J9 -> 424700 | L21: =Actual2223!K9 -> 428050 | ... P21: =Actual2223!O9 -> 445100 | Q21: =SUM(E21:P21) -> 5065300
D22: ='KPI 1'!D22 -> DIFFERENCE | E22: =IF(E20=0,0,E20-E19) -> 76730.111 | F22: =IF(F20=0,0,F20-F19) -> 249926.61 | G22: =IF(G20=0,0,G20-G19) -> 55285.111 | H22: =IF(H20=0,0,H20-H19) -> 206167.61 | I22: =IF(I20=0,0,I20-I19) -> -38832.389 | J22: =IF(J20=0,0,J20-J19) -> -80430.889 | K22: =IF(K20=0,0,K20-K19) -> 365272.11 | L22: =IF(L20=0,0,L20-L19) -> 165006.11 | ... P22: =IF(P20=0,0,P20-P19) -> 0 | Q22: =SUM(E22:P22) -> 979936.5
D23: ='KPI 1'!D23 -> %REALISATION | E23: =E20/E19 -> 1.0910502 | F23: =F20/F19 -> 1.2927993 | G23: =G20/G19 -> 1.0639436 | H23: =H20/H19 -> 1.2348053 | I23: =I20/I19 -> 0.95640099 | J23: =J20/J19 -> 0.91087954 | K23: =K20/K19 -> 1.3991472 | L23: =L20/L19 -> 1.1780863 | ... P23: =P20/P19 -> 0
C25: CUMULATIVE | D25: ='KPI 1'!D25 -> 0 | E25: ='KPI 1'!E25 -> 45839 | F25: ='KPI 1'!F25 -> 45870 | G25: ='KPI 1'!G25 -> 45901 | H25: ='KPI 1'!H25 -> 45931 | I25: ='KPI 1'!I25 -> 45962 | J25: ='KPI 1'!J25 -> 45992 | K25: ='KPI 1'!K25 -> 46023 | ... P25: ='KPI 1'!P25 -> 46174
D26: ='KPI 1'!D26 -> budget2025/26 | E26: =SUM($E19:E19) -> 842723.39 | F26: =SUM($E19:F19) -> 1696299.8 | G26: =SUM($E19:G19) -> 2560891.2 | H26: =SUM($E19:H19) -> 3438927.6 | I26: =SUM($E19:I19) -> 4329598.9 | J26: =SUM($E19:J19) -> 5232095.3 | K26: =SUM($E19:K19) -> 6147226.7 | L26: =SUM($E19:L19) -> 7073778.1 | ... P26: =SUM($E19:P19) -> 10877012
D27: ='KPI 1'!D27 -> ACTUAL2025/26 | E27: =SUM($E20:E20) -> 919453.5 | F27: =SUM($E20:F20) -> 2022956.5 | G27: =SUM($E20:G20) -> 2942833 | H27: =SUM($E20:H20) -> 4027037 | I27: =SUM($E20:I20) -> 4878876 | J27: =SUM($E20:J20) -> 5700941.5 | K27: =SUM($E20:K20) -> 6981345 | L27: =SUM($E20:L20) -> 8072902.5 | ... P27: =SUM($E20:P20) -> 8990471
D28: ='KPI 1'!D28 -> ACTUAL2024/25 | E28: =SUM($E21:E21) -> 392600 | F28: =SUM($E21:F21) -> 787550 | G28: =SUM($E21:G21) -> 1197200 | H28: =SUM($E21:H21) -> 1612050 | I28: =SUM($E21:I21) -> 2029350 | J28: =SUM($E21:J21) -> 2451350 | K28: =SUM($E21:K21) -> 2876050 | L28: =SUM($E21:L21) -> 3304100 | ... P28: =SUM($E21:P21) -> 5065300
D29: ='KPI 1'!D29 -> DIFFERENCE | E29: =SUM($E22:E22) -> 76730.111 | F29: =SUM($E22:F22) -> 326656.72 | G29: =SUM($E22:G22) -> 381941.83 | H29: =SUM($E22:H22) -> 588109.44 | I29: =SUM($E22:I22) -> 549277.06 | J29: =SUM($E22:J22) -> 468846.17 | K29: =SUM($E22:K22) -> 834118.28 | L29: =SUM($E22:L22) -> 999124.39 | ... P29: =SUM($E22:P22) -> 979936.5
D30: ='KPI 1'!D30 -> %REALISATION | E30: =E27/E26 -> 1.0910502 | F30: =F27/F26 -> 1.1925702 | G30: =G27/G26 -> 1.1491441 | H30: =H27/H26 -> 1.1710154 | I30: =I27/I26 -> 1.1268656 | J30: =J27/J26 -> 1.0896096 | K30: =K27/K26 -> 1.1356902 | L30: =L27/L26 -> 1.1412434 | ... P30: =P27/P26 -> 0.82655708

Sheet KPI b
A1: =Dashboard!#REF! -> #REF! | B1: =Dashboard!#REF! -> #REF! | C1: =Dashboard!#REF! -> #REF! | G1: Actual month: | I1: =INDEX($E$18:$P$18,Actual_month) -> 46082 | L1: Dashboard
A2: Unit | C2: Ksh.
C3: l | J3: Comments
C4: l | R4: actual | S4: =INDEX(E27:P27,Actual_month) -> 0
C5: l | R5: target | S5: =INDEX(E26:P26,Actual_month) -> 0
R6: 0.9 | S6: =+S5*R6 -> 0
J9: Actions
C18: MONTHLY | E18: ='KPI 1'!E18 -> 45839 | F18: ='KPI 1'!F18 -> 45870 | G18: ='KPI 1'!G18 -> 45901 | H18: ='KPI 1'!H18 -> 45931 | I18: ='KPI 1'!I18 -> 45962 | J18: ='KPI 1'!J18 -> 45992 | K18: ='KPI 1'!K18 -> 46023 | L18: ='KPI 1'!L18 -> 46054 | ... P18: ='KPI 1'!P18 -> 46174 | Q18: Total
D19: ='KPI 1'!D19 -> budget2025/26 | E19: =BUDGET2526!D9 -> 0 | F19: =BUDGET2526!E9 -> 0 | G19: =BUDGET2526!F9 -> 0 | H19: =BUDGET2526!G9 -> 0 | I19: =BUDGET2526!H9 -> 0 | J19: =BUDGET2526!I9 -> 0 | K19: =BUDGET2526!J9 -> 0 | L19: =BUDGET2526!K9 -> 0 | ... P19: =BUDGET2526!O9 -> 0 | Q19: =SUM(E19:P19) -> 0
D20: ='KPI 1'!D20 -> ACTUAL2025/26 | E20: ='ACTUAL 2526'!E9 -> 0 | F20: ='ACTUAL 2526'!F9 -> 0 | G20: ='ACTUAL 2526'!G9 -> 0 | H20: ='ACTUAL 2526'!H9 -> 0 | I20: ='ACTUAL 2526'!I9 -> 0 | J20: ='ACTUAL 2526'!J9 -> 0 | K20: ='ACTUAL 2526'!K9 -> 0 | L20: ='ACTUAL 2526'!L9 -> 0 | ... P20: ='ACTUAL 2526'!P9 -> 0 | Q20: =SUM(E20:P20) -> 0
D21: ='KPI 1'!D21 -> ACTUAL2024/25 | E21: ='Actual 202425'!E9 -> 491000 | F21: ='Actual 202425'!F9 -> 494150 | G21: ='Actual 202425'!G9 -> 496750 | H21: ='Actual 202425'!H9 -> 498550 | I21: ='Actual 202425'!I9 -> 498350 | J21: ='Actual 202425'!J9 -> 501650 | K21: ='Actual 202425'!K9 -> 503400 | L21: ='Actual 202425'!L9 -> 507750 | ... P21: ='Actual 202425'!P9 -> 0 | Q21: =SUM(E21:P21) -> 4783850
D22: ='KPI 1'!D22 -> DIFFERENCE | E22: =IF(E20=0,0,E20-E19) -> 0 | F22: =IF(F20=0,0,F20-F19) -> 0 | G22: =IF(G20=0,0,G20-G19) -> 0 | H22: =IF(H20=0,0,H20-H19) -> 0 | I22: =IF(I20=0,0,I20-I19) -> 0 | J22: =IF(J20=0,0,J20-J19) -> 0 | K22: =IF(K20=0,0,K20-K19) -> 0 | L22: =IF(L20=0,0,L20-L19) -> 0 | ... P22: =IF(P20=0,0,P20-P19) -> 0 | Q22: =SUM(E22:P22) -> 0
D23: ='KPI 1'!D23 -> %REALISATION | E23: =E21/E19 -> #DIV/0! | F23: =F20/F19 -> #DIV/0! | G23: =G20/G19 -> #DIV/0! | H23: =H20/H19 -> #DIV/0! | I23: =I20/I19 -> #DIV/0! | J23: =J20/J19 -> #DIV/0! | K23: =K20/K19 -> #DIV/0! | L23: =L20/L19 -> #DIV/0! | M23: =M20/M19 -> #DIV/0! | ... P23: =P20/P19 -> #DIV/0!
C25: CUMULATIVE | D25: ='KPI 1'!D25 -> 0 | E25: ='KPI 1'!E25 -> 45839 | F25: ='KPI 1'!F25 -> 45870 | G25: ='KPI 1'!G25 -> 45901 | H25: ='KPI 1'!H25 -> 45931 | I25: ='KPI 1'!I25 -> 45962 | J25: ='KPI 1'!J25 -> 45992 | K25: ='KPI 1'!K25 -> 46023 | ... P25: ='KPI 1'!P25 -> 46174
D26: ='KPI 1'!D26 -> budget2025/26 | E26: =SUM($E19:E19) -> 0 | F26: =SUM($E19:F19) -> 0 | G26: =SUM($E19:G19) -> 0 | H26: =SUM($E19:H19) -> 0 | I26: =SUM($E19:I19) -> 0 | J26: =SUM($E19:J19) -> 0 | K26: =SUM($E19:K19) -> 0 | L26: =SUM($E19:L19) -> 0 | ... P26: =SUM($E19:P19) -> 0
D27: ='KPI 1'!D27 -> ACTUAL2025/26 | E27: =SUM($E20:E20) -> 0 | F27: =SUM($E20:F20) -> 0 | G27: =SUM($E20:G20) -> 0 | H27: =SUM($E20:H20) -> 0 | I27: =SUM($E20:I20) -> 0 | J27: =SUM($E20:J20) -> 0 | K27: =SUM($E20:K20) -> 0 | L27: =SUM($E20:L20) -> 0 | ... P27: =SUM($E20:P20) -> 0
D28: ='KPI 1'!D28 -> ACTUAL2024/25 | E28: =SUM($E21:E21) -> 491000 | F28: =SUM($E21:F21) -> 985150 | G28: =SUM($E21:G21) -> 1481900 | H28: =SUM($E21:H21) -> 1980450 | I28: =SUM($E21:I21) -> 2478800 | J28: =SUM($E21:J21) -> 2980450 | K28: =SUM($E21:K21) -> 3483850 | L28: =SUM($E21:L21) -> 3991600 | ... P28: =SUM($E21:P21) -> 4783850
D29: ='KPI 1'!D29 -> DIFFERENCE | E29: =SUM($E22:E22) -> 0 | F29: =SUM($E22:F22) -> 0 | G29: =SUM($E22:G22) -> 0 | H29: =SUM($E22:H22) -> 0 | I29: =SUM($E22:I22) -> 0 | J29: =SUM($E22:J22) -> 0 | K29: =SUM($E22:K22) -> 0 | L29: =SUM($E22:L22) -> 0 | ... P29: =SUM($E22:P22) -> 0
D30: ='KPI 1'!D30 -> %REALISATION | E30: =E28/E26 -> #DIV/0! | F30: =F27/F26 -> #DIV/0! | G30: =G27/G26 -> #DIV/0! | H30: =H27/H26 -> #DIV/0! | I30: =I27/I26 -> #DIV/0! | J30: =J27/J26 -> #DIV/0! | K30: =K27/K26 -> #DIV/0! | L30: =L27/L26 -> #DIV/0! | M30: =M27/M26 -> #DIV/0! | ... P30: =P27/P26 -> #DIV/0!

Sheet KPI c
A1: KPI | B1: =Dashboard!A10 -> 5 | C1: =Dashboard!B10 -> new connection fee water | G1: Actual month: | I1: =INDEX($E$18:$P$18,Actual_month) -> 46082 | L1: Dashboard
A2: Unit | C2: Ksh.
C3: l | J3: Comments
C4: l | R4: actual | S4: =INDEX(E27:P27,Actual_month) -> 3002500
C5: l | R5: target | S5: =INDEX(E26:P26,Actual_month) -> 4500000
R6: 0.9 | S6: =+S5*R6 -> 4050000
J9: Actions
C18: MONTHLY | E18: ='KPI 1'!E18 -> 45839 | F18: ='KPI 1'!F18 -> 45870 | G18: ='KPI 1'!G18 -> 45901 | H18: ='KPI 1'!H18 -> 45931 | I18: ='KPI 1'!I18 -> 45962 | J18: ='KPI 1'!J18 -> 45992 | K18: ='KPI 1'!K18 -> 46023 | L18: ='KPI 1'!L18 -> 46054 | ... P18: ='KPI 1'!P18 -> 46174 | Q18: Total
D19: ='KPI 1'!D19 -> budget2025/26 | E19: =BUDGET2526!D11 -> 455000 | F19: =BUDGET2526!E11 -> 407500 | G19: =BUDGET2526!F11 -> 412500 | H19: =BUDGET2526!G11 -> 587500 | I19: =BUDGET2526!H11 -> 562500 | J19: =BUDGET2526!I11 -> 537500 | K19: =BUDGET2526!J11 -> 550000 | L19: =BUDGET2526!K11 -> 512500 | ... P19: =BUDGET2526!O11 -> 420000 | Q19: =SUM(E19:P19) -> 5770000
D20: ='KPI 1'!D20 -> ACTUAL2025/26 | E20: ='ACTUAL 2526'!E11 -> 385000 | F20: ='ACTUAL 2526'!F11 -> 455000 | G20: ='ACTUAL 2526'!G11 -> 345000 | H20: ='ACTUAL 2526'!H11 -> 422500 | I20: ='ACTUAL 2526'!I11 -> 255000 | J20: ='ACTUAL 2526'!J11 -> 360000 | K20: ='ACTUAL 2526'!K11 -> 440000 | L20: ='ACTUAL 2526'!L11 -> 192500 | ... P20: ='ACTUAL 2526'!P11 -> 0 | Q20: =SUM(E20:P20) -> 3002500
D21: ='KPI 1'!D21 -> ACTUAL2024/25 | E21: ='Actual 202425'!E11 -> 327500 | F21: ='Actual 202425'!F11 -> 172500 | G21: ='Actual 202425'!G11 -> 90000 | H21: ='Actual 202425'!H11 -> 35000 | I21: ='Actual 202425'!I11 -> 102500 | J21: ='Actual 202425'!J11 -> 145000 | K21: ='Actual 202425'!K11 -> 377500 | L21: ='Actual 202425'!L11 -> 225000 | ... P21: ='Actual 202425'!P11 -> 265000 | Q21: =SUM(E21:P21) -> 2590000
D22: ='KPI 1'!D22 -> DIFFERENCE | E22: =IF(E20=0,0,E20-E19) -> -70000 | F22: =IF(F20=0,0,F20-F19) -> 47500 | G22: =IF(G20=0,0,G20-G19) -> -67500 | H22: =IF(H20=0,0,H20-H19) -> -165000 | I22: =IF(I20=0,0,I20-I19) -> -307500 | J22: =IF(J20=0,0,J20-J19) -> -177500 | K22: =IF(K20=0,0,K20-K19) -> -110000 | L22: =IF(L20=0,0,L20-L19) -> -320000 | ... P22: =IF(P20=0,0,P20-P19) -> 0 | Q22: =SUM(E22:P22) -> -1497500
D23: ='KPI 1'!D23 -> %REALISATION | E23: =E20/E19 -> 0.84615385 | F23: =F20/F19 -> 1.1165644 | G23: =G20/G19 -> 0.83636364 | H23: =H20/H19 -> 0.71914894 | I23: =I20/I19 -> 0.45333333 | J23: =J20/J19 -> 0.66976744 | K23: =K20/K19 -> 0.8 | L23: =L20/L19 -> 0.37560976 | ... P23: =P20/P19 -> 0
C25: CUMULATIVE | D25: ='KPI 1'!D25 -> 0 | E25: ='KPI 1'!E25 -> 45839 | F25: ='KPI 1'!F25 -> 45870 | G25: ='KPI 1'!G25 -> 45901 | H25: ='KPI 1'!H25 -> 45931 | I25: ='KPI 1'!I25 -> 45962 | J25: ='KPI 1'!J25 -> 45992 | K25: ='KPI 1'!K25 -> 46023 | ... P25: ='KPI 1'!P25 -> 46174
D26: ='KPI 1'!D26 -> budget2025/26 | E26: =SUM($E19:E19) -> 455000 | F26: =SUM($E19:F19) -> 862500 | G26: =SUM($E19:G19) -> 1275000 | H26: =SUM($E19:H19) -> 1862500 | I26: =SUM($E19:I19) -> 2425000 | J26: =SUM($E19:J19) -> 2962500 | K26: =SUM($E19:K19) -> 3512500 | L26: =SUM($E19:L19) -> 4025000 | ... P26: =SUM($E19:P19) -> 5770000
D27: ='KPI 1'!D27 -> ACTUAL2025/26 | E27: =SUM($E20:E20) -> 385000 | F27: =SUM($E20:F20) -> 840000 | G27: =SUM($E20:G20) -> 1185000 | H27: =SUM($E20:H20) -> 1607500 | I27: =SUM($E20:I20) -> 1862500 | J27: =SUM($E20:J20) -> 2222500 | K27: =SUM($E20:K20) -> 2662500 | L27: =SUM($E20:L20) -> 2855000 | ... P27: =SUM($E20:P20) -> 3002500
D28: ='KPI 1'!D28 -> ACTUAL2024/25 | E28: =SUM($E21:E21) -> 327500 | F28: =SUM($E21:F21) -> 500000 | G28: =SUM($E21:G21) -> 590000 | H28: =SUM($E21:H21) -> 625000 | I28: =SUM($E21:I21) -> 727500 | J28: =SUM($E21:J21) -> 872500 | K28: =SUM($E21:K21) -> 1250000 | L28: =SUM($E21:L21) -> 1475000 | ... P28: =SUM($E21:P21) -> 2590000
D29: ='KPI 1'!D29 -> DIFFERENCE | E29: =SUM($E22:E22) -> -70000 | F29: =SUM($E22:F22) -> -22500 | G29: =SUM($E22:G22) -> -90000 | H29: =SUM($E22:H22) -> -255000 | I29: =SUM($E22:I22) -> -562500 | J29: =SUM($E22:J22) -> -740000 | K29: =SUM($E22:K22) -> -850000 | L29: =SUM($E22:L22) -> -1170000 | ... P29: =SUM($E22:P22) -> -1497500
D30: ='KPI 1'!D30 -> %REALISATION | E30: =E27/E26 -> 0.84615385 | F30: =F27/F26 -> 0.97391304 | G30: =G27/G26 -> 0.92941176 | H30: =H27/H26 -> 0.86308725 | I30: =I27/I26 -> 0.76804124 | J30: =J27/J26 -> 0.75021097 | K30: =K27/K26 -> 0.75800712 | L30: =L27/L26 -> 0.70931677 | ... P30: =P27/P26 -> 0.52036395

Sheet KPI e
A1: KPI | B1: =Dashboard!A11 -> 6 | C1: =Dashboard!B11 -> new connection fee sewer | G1: Actual month: | I1: =INDEX($E$18:$P$18,Actual_month) -> 46082 | L1: Dashboard
A2: Unit | C2: Ksh.
C3: l | J3: Comments
C4: l | R4: actual | S4: =INDEX(E27:P27,Actual_month) -> 142500
C5: l | R5: target | S5: =INDEX(E26:P26,Actual_month) -> 680000
R6: 0.9 | S6: =+S5*R6 -> 612000
J9: Actions
C18: MONTHLY | E18: ='KPI 1'!E18 -> 45839 | F18: ='KPI 1'!F18 -> 45870 | G18: ='KPI 1'!G18 -> 45901 | H18: ='KPI 1'!H18 -> 45931 | I18: ='KPI 1'!I18 -> 45962 | J18: ='KPI 1'!J18 -> 45992 | K18: ='KPI 1'!K18 -> 46023 | L18: ='KPI 1'!L18 -> 46054 | ... P18: ='KPI 1'!P18 -> 46174 | Q18: Total
D19: ='KPI 1'!D19 -> budget2025/26 | E19: =BUDGET2526!D12 -> 80000 | F19: =BUDGET2526!E12 -> 75000 | G19: =BUDGET2526!F12 -> 75000 | H19: =BUDGET2526!G12 -> 75000 | I19: =BUDGET2526!H12 -> 75000 | J19: =BUDGET2526!I12 -> 75000 | K19: =BUDGET2526!J12 -> 75000 | L19: =BUDGET2526!K12 -> 75000 | ... P19: =BUDGET2526!O12 -> 75000 | Q19: =SUM(E19:P19) -> 905000
D20: ='KPI 1'!D20 -> ACTUAL2025/26 | E20: ='ACTUAL 2526'!E12 -> 0 | F20: ='ACTUAL 2526'!F12 -> 22500 | G20: ='ACTUAL 2526'!G12 -> 22500 | H20: ='ACTUAL 2526'!H12 -> 20000 | I20: ='ACTUAL 2526'!I12 -> 27500 | J20: ='ACTUAL 2526'!J12 -> 0 | K20: ='ACTUAL 2526'!K12 -> 22500 | L20: ='ACTUAL 2526'!L12 -> 27500 | ... P20: ='ACTUAL 2526'!P12 -> 0 | Q20: =SUM(E20:P20) -> 142500
D21: ='KPI 1'!D21 -> ACTUAL2024/25 | E21: ='Actual 202425'!E12 -> 50000 | F21: ='Actual 202425'!F12 -> 30000 | G21: ='Actual 202425'!G12 -> 37500 | H21: ='Actual 202425'!H12 -> 12500 | I21: ='Actual 202425'!I12 -> 0 | J21: ='Actual 202425'!J12 -> 25000 | K21: ='Actual 202425'!K12 -> 10500 | L21: ='Actual 202425'!L12 -> 60000 | ... P21: ='Actual 202425'!P12 -> 20000 | Q21: =ACTUAL2021!P20 -> 0
D22: ='KPI 1'!D22 -> DIFFERENCE | E22: =IF(E20=0,0,E20-E19) -> 0 | F22: =IF(F20=0,0,F20-F19) -> -52500 | G22: =IF(G20=0,0,G20-G19) -> -52500 | H22: =IF(H20=0,0,H20-H19) -> -55000 | I22: =IF(I20=0,0,I20-I19) -> -47500 | J22: =IF(J20=0,0,J20-J19) -> 0 | K22: =IF(K20=0,0,K20-K19) -> -52500 | L22: =IF(L20=0,0,L20-L19) -> -47500 | ... P22: =IF(P20=0,0,P20-P19) -> 0 | Q22: =SUM(E22:P22) -> -307500
D23: ='KPI 1'!D23 -> %REALISATION | E23: =E20/E19 -> 0 | F23: =F20/F19 -> 0.3 | G23: =G20/G19 -> 0.3 | H23: =H20/H19 -> 0.26666667 | I23: =I20/I19 -> 0.36666667 | J23: =J20/J19 -> 0 | K23: =K20/K19 -> 0.3 | L23: =L20/L19 -> 0.36666667 | ... P23: =P20/P19 -> 0
C25: CUMULATIVE | D25: ='KPI 1'!D25 -> 0 | E25: ='KPI 1'!E25 -> 45839 | F25: ='KPI 1'!F25 -> 45870 | G25: ='KPI 1'!G25 -> 45901 | H25: ='KPI 1'!H25 -> 45931 | I25: ='KPI 1'!I25 -> 45962 | J25: ='KPI 1'!J25 -> 45992 | K25: ='KPI 1'!K25 -> 46023 | ... P25: ='KPI 1'!P25 -> 46174
D26: ='KPI 1'!D26 -> budget2025/26 | E26: =SUM($E19:E19) -> 80000 | F26: =SUM($E19:F19) -> 155000 | G26: =SUM($E19:G19) -> 230000 | H26: =SUM($E19:H19) -> 305000 | I26: =SUM($E19:I19) -> 380000 | J26: =SUM($E19:J19) -> 455000 | K26: =SUM($E19:K19) -> 530000 | L26: =SUM($E19:L19) -> 605000 | ... P26: =SUM($E19:P19) -> 905000
D27: ='KPI 1'!D27 -> ACTUAL2025/26 | E27: =SUM($E20:E20) -> 0 | F27: =SUM($E20:F20) -> 22500 | G27: =SUM($E20:G20) -> 45000 | H27: =SUM($E20:H20) -> 65000 | I27: =SUM($E20:I20) -> 92500 | J27: =SUM($E20:J20) -> 92500 | K27: =SUM($E20:K20) -> 115000 | L27: =SUM($E20:L20) -> 142500 | ... P27: =SUM($E20:P20) -> 142500
D28: ='KPI 1'!D28 -> ACTUAL2024/25 | E28: =SUM($E21:E21) -> 50000 | F28: =SUM($E21:F21) -> 80000 | G28: =SUM($E21:G21) -> 117500 | H28: =SUM($E21:H21) -> 130000 | I28: =SUM($E21:I21) -> 130000 | J28: =SUM($E21:J21) -> 155000 | K28: =SUM($E21:K21) -> 165500 | L28: =SUM($E21:L21) -> 225500 | ... P28: =SUM($E21:P21) -> 285500
D29: ='KPI 1'!D29 -> DIFFERENCE | E29: =SUM($E22:E22) -> 0 | F29: =SUM($E22:F22) -> -52500 | G29: =SUM($E22:G22) -> -105000 | H29: =SUM($E22:H22) -> -160000 | I29: =SUM($E22:I22) -> -207500 | J29: =SUM($E22:J22) -> -207500 | K29: =SUM($E22:K22) -> -260000 | L29: =SUM($E22:L22) -> -307500 | ... P29: =SUM($E22:P22) -> -307500
D30: ='KPI 1'!D30 -> %REALISATION | E30: =E27/E26 -> 0 | F30: =F27/F26 -> 0.14516129 | G30: =G27/G26 -> 0.19565217 | H30: =H27/H26 -> 0.21311475 | I30: =I27/I26 -> 0.24342105 | J30: =J27/J26 -> 0.2032967 | K30: =K27/K26 -> 0.21698113 | L30: =L27/L26 -> 0.23553719 | ... P30: =P27/P26 -> 0.15745856

Sheet KPI 3
A1: KPI | B1: =Dashboard!A8 -> 3 | C1: =Dashboard!B8 -> Bulk water | G1: Actual month: | I1: =INDEX($E$18:$P$18,Actual_month) -> 46082 | L1: Dashboard
A2: Unit | C2: Ksh.
C3: l | J3: Comments
C4: l | R4: actual | S4: =INDEX(E27:P27,Actual_month) -> 704120
C5: l | R5: target | S5: =INDEX(E26:P26,Actual_month) -> 810000
R6: 0.9 | S6: =+S5*R6 -> 729000
J9: Actions
C18: MONTHLY | E18: ='KPI 1'!E18 -> 45839 | F18: ='KPI 1'!F18 -> 45870 | G18: ='KPI 1'!G18 -> 45901 | H18: ='KPI 1'!H18 -> 45931 | I18: ='KPI 1'!I18 -> 45962 | J18: ='KPI 1'!J18 -> 45992 | K18: ='KPI 1'!K18 -> 46023 | L18: ='KPI 1'!L18 -> 46054 | ... P18: ='KPI 1'!P18 -> 46174 | Q18: Total
D19: ='KPI 1'!D19 -> budget2025/26 | E19: =BUDGET2526!D14 -> 90000 | F19: =BUDGET2526!E14 -> 90000 | G19: =BUDGET2526!F14 -> 90000 | H19: =BUDGET2526!G14 -> 90000 | I19: =BUDGET2526!H14 -> 90000 | J19: =BUDGET2526!I14 -> 90000 | K19: =BUDGET2526!J14 -> 90000 | L19: =BUDGET2526!K14 -> 90000 | ... P19: =BUDGET2526!O14 -> 90000 | Q19: =SUM(E19:P19) -> 1080000
D20: ='KPI 1'!D20 -> ACTUAL2025/26 | E20: =Actual2223!D13 -> 86850 | F20: =Actual2223!E13 -> 84450 | G20: =Actual2223!F13 -> 56450 | H20: =Actual2223!G13 -> 97020 | I20: =Actual2223!H13 -> 61350 | J20: =Actual2223!I13 -> 68250 | K20: =Actual2223!J13 -> 83100 | L20: =Actual2223!K13 -> 90450 | ... P20: =Actual2223!O13 -> 28100 | Q20: =SUM(E20:P20) -> 820170
D21: ='KPI 1'!D21 -> ACTUAL2024/25 | E21: 0 | F21: 0 | G21: 0 | H21: 0 | I21: 0 | J21: 0 | K21: 0 | L21: 0 | M21: 0 | N21: 0 | O21: 0 | P21: 0 | Q21: =SUM(E21:P21) -> 0
D22: ='KPI 1'!D22 -> DIFFERENCE | E22: =IF(E20=0,0,E20-E19) -> -3150 | F22: =IF(F20=0,0,F20-F19) -> -5550 | G22: =IF(G20=0,0,G20-G19) -> -33550 | H22: =IF(H20=0,0,H20-H19) -> 7020 | I22: =IF(I20=0,0,I20-I19) -> -28650 | J22: =IF(J20=0,0,J20-J19) -> -21750 | K22: =IF(K20=0,0,K20-K19) -> -6900 | L22: =IF(L20=0,0,L20-L19) -> 450 | ... P22: =IF(P20=0,0,P20-P19) -> -61900 | Q22: =SUM(E22:P22) -> -259830
D23: ='KPI 1'!D23 -> %REALISATION | E23: =E21/E19 -> 0 | F23: =F20/F19 -> 0.93833333 | G23: =G20/G19 -> 0.62722222 | H23: =H20/H19 -> 1.078 | I23: =I20/I19 -> 0.68166667 | J23: =J20/J19 -> 0.75833333 | K23: =K20/K19 -> 0.92333333 | L23: =L20/L19 -> 1.005 | M23: =M20/M19 -> 0.84666667 | ... P23: =P20/P19 -> 0.31222222
C25: CUMULATIVE | D25: ='KPI 1'!D25 -> 0 | E25: ='KPI 1'!E25 -> 45839 | F25: ='KPI 1'!F25 -> 45870 | G25: ='KPI 1'!G25 -> 45901 | H25: ='KPI 1'!H25 -> 45931 | I25: ='KPI 1'!I25 -> 45962 | J25: ='KPI 1'!J25 -> 45992 | K25: ='KPI 1'!K25 -> 46023 | ... P25: ='KPI 1'!P25 -> 46174
D26: ='KPI 1'!D26 -> budget2025/26 | E26: =SUM($E19:E19) -> 90000 | F26: =SUM($E19:F19) -> 180000 | G26: =SUM($E19:G19) -> 270000 | H26: =SUM($E19:H19) -> 360000 | I26: =SUM($E19:I19) -> 450000 | J26: =SUM($E19:J19) -> 540000 | K26: =SUM($E19:K19) -> 630000 | L26: =SUM($E19:L19) -> 720000 | ... P26: =SUM($E19:P19) -> 1080000
D27: ='KPI 1'!D27 -> ACTUAL2025/26 | E27: =SUM($E20:E20) -> 86850 | F27: =SUM($E20:F20) -> 171300 | G27: =SUM($E20:G20) -> 227750 | H27: =SUM($E20:H20) -> 324770 | I27: =SUM($E20:I20) -> 386120 | J27: =SUM($E20:J20) -> 454370 | K27: =SUM($E20:K20) -> 537470 | L27: =SUM($E20:L20) -> 627920 | ... P27: =SUM($E20:P20) -> 820170
D28: ='KPI 1'!D28 -> ACTUAL2024/25 | E28: =SUM($E21:E21) -> 0 | F28: =SUM($E21:F21) -> 0 | G28: =SUM($E21:G21) -> 0 | H28: =SUM($E21:H21) -> 0 | I28: =SUM($E21:I21) -> 0 | J28: =SUM($E21:J21) -> 0 | K28: =SUM($E21:K21) -> 0 | L28: =SUM($E21:L21) -> 0 | ... P28: =SUM($E21:P21) -> 0
D29: ='KPI 1'!D29 -> DIFFERENCE | E29: =SUM($E22:E22) -> -3150 | F29: =SUM($E22:F22) -> -8700 | G29: =SUM($E22:G22) -> -42250 | H29: =SUM($E22:H22) -> -35230 | I29: =SUM($E22:I22) -> -63880 | J29: =SUM($E22:J22) -> -85630 | K29: =SUM($E22:K22) -> -92530 | L29: =SUM($E22:L22) -> -92080 | ... P29: =SUM($E22:P22) -> -259830
D30: ='KPI 1'!D30 -> %REALISATION | E30: =E28/E26 -> 0 | F30: =F27/F26 -> 0.95166667 | G30: =G27/G26 -> 0.84351852 | H30: =H27/H26 -> 0.90213889 | I30: =I27/I26 -> 0.85804444 | J30: =J27/J26 -> 0.84142593 | K30: =K27/K26 -> 0.85312698 | L30: =L27/L26 -> 0.87211111 | M30: =M27/M26 -> 0.86928395 | ... P30: =P27/P26 -> 0.75941667

Sheet KPI 3a
A1: KPI | B1: 5a | C1: Meter Rent | G1: Actual month: | I1: =INDEX($E$18:$P$18,Actual_month) -> 46082 | L1: Dashboard
A2: Unit | C2: Ksh.
C3: l | J3: Comments
C4: l | R4: actual | S4: =INDEX(E27:P27,Actual_month) -> 3152450
C5: l | R5: target | S5: =INDEX(E26:P26,Actual_month) -> 577170
R6: 0.9 | S6: =+S5*R6 -> 519453
J9: Actions
C18: MONTHLY | E18: ='KPI 1'!E18 -> 45839 | F18: ='KPI 1'!F18 -> 45870 | G18: ='KPI 1'!G18 -> 45901 | H18: ='KPI 1'!H18 -> 45931 | I18: ='KPI 1'!I18 -> 45962 | J18: ='KPI 1'!J18 -> 45992 | K18: ='KPI 1'!K18 -> 46023 | L18: ='KPI 1'!L18 -> 46054 | ... P18: ='KPI 1'!P18 -> 46174 | Q18: Total
D19: ='KPI 1'!D19 -> budget2025/26 | E19: =BUDGET2526!D8 -> 64130 | F19: =BUDGET2526!E8 -> 64130 | G19: =BUDGET2526!F8 -> 64130 | H19: =BUDGET2526!G8 -> 64130 | I19: =BUDGET2526!H8 -> 64130 | J19: =BUDGET2526!I8 -> 64130 | K19: =BUDGET2526!J8 -> 64130 | L19: =BUDGET2526!K8 -> 64130 | ... P19: =BUDGET2526!O8 -> 64130 | Q19: =SUM(E19:P19) -> 769560
D20: ='KPI 1'!D20 -> ACTUAL2025/26 | E20: =ACTUAL2122!D9 -> 331100 | F20: =ACTUAL2122!E9 -> 336400 | G20: =ACTUAL2122!F9 -> 340300 | H20: =ACTUAL2122!G9 -> 343400 | I20: =ACTUAL2122!H9 -> 349350 | J20: =ACTUAL2122!I9 -> 355250 | K20: =ACTUAL2122!J9 -> 361150 | L20: =ACTUAL2122!K9 -> 365900 | ... P20: =ACTUAL2122!O9 -> 387050 | Q20: =SUM(E20:P20) -> 4304150
D21: ='KPI 1'!D21 -> ACTUAL2024/25 | E21: =ACTUAL2021!D8 -> 0 | F21: =ACTUAL2021!E8 -> 0 | G21: =ACTUAL2021!F8 -> 0 | H21: =ACTUAL2021!G8 -> 0 | I21: =ACTUAL2021!H8 -> 0 | J21: =ACTUAL2021!I8 -> 0 | K21: =ACTUAL2021!J8 -> 0 | L21: =ACTUAL2021!K8 -> 0 | ... P21: =ACTUAL2021!O8 -> 0 | Q21: =SUM(E21:P21) -> 0
D22: ='KPI 1'!D22 -> DIFFERENCE | E22: =IF(E20=0,0,E20-E19) -> 266970 | F22: =IF(F20=0,0,F20-F19) -> 272270 | G22: =IF(G20=0,0,G20-G19) -> 276170 | H22: =IF(H20=0,0,H20-H19) -> 279270 | I22: =IF(I20=0,0,I20-I19) -> 285220 | J22: =IF(J20=0,0,J20-J19) -> 291120 | K22: =IF(K20=0,0,K20-K19) -> 297020 | L22: =IF(L20=0,0,L20-L19) -> 301770 | ... P22: =IF(P20=0,0,P20-P19) -> 322920 | Q22: =SUM(E22:P22) -> 3534590
D23: ='KPI 1'!D23 -> %REALISATION | E23: =E21/E19 -> 0 | F23: =F20/F19 -> 5.2455949 | G23: =G20/G19 -> 5.3064089 | H23: =H20/H19 -> 5.3547482 | I23: =I20/I19 -> 5.4475285 | J23: =J20/J19 -> 5.5395291 | K23: =K20/K19 -> 5.6315297 | L23: =L20/L19 -> 5.705598 | M23: =M20/M19 -> 5.7632933 | ... P23: =P20/P19 -> 6.0353969
E24: =#REF! -> #REF! | F24: =#REF! -> #REF! | G24: =#REF! -> #REF! | H24: =#REF! -> #REF! | I24: =#REF! -> #REF! | J24: =#REF! -> #REF! | K24: =#REF! -> #REF! | L24: =#REF! -> #REF! | ... P24: =#REF! -> #REF!
C25: CUMULATIVE | D25: ='KPI 1'!D25 -> 0 | E25: ='KPI 1'!E25 -> 45839 | F25: ='KPI 1'!F25 -> 45870 | G25: ='KPI 1'!G25 -> 45901 | H25: ='KPI 1'!H25 -> 45931 | I25: ='KPI 1'!I25 -> 45962 | J25: ='KPI 1'!J25 -> 45992 | K25: ='KPI 1'!K25 -> 46023 | ... P25: ='KPI 1'!P25 -> 46174
D26: ='KPI 1'!D26 -> budget2025/26 | E26: =SUM($E19:E19) -> 64130 | F26: =SUM($E19:F19) -> 128260 | G26: =SUM($E19:G19) -> 192390 | H26: =SUM($E19:H19) -> 256520 | I26: =SUM($E19:I19) -> 320650 | J26: =SUM($E19:J19) -> 384780 | K26: =SUM($E19:K19) -> 448910 | L26: =SUM($E19:L19) -> 513040 | ... P26: =SUM($E19:P19) -> 769560
D27: ='KPI 1'!D27 -> ACTUAL2025/26 | E27: =SUM($E20:E20) -> 331100 | F27: =SUM($E20:F20) -> 667500 | G27: =SUM($E20:G20) -> 1007800 | H27: =SUM($E20:H20) -> 1351200 | I27: =SUM($E20:I20) -> 1700550 | J27: =SUM($E20:J20) -> 2055800 | K27: =SUM($E20:K20) -> 2416950 | L27: =SUM($E20:L20) -> 2782850 | ... P27: =SUM($E20:P20) -> 4304150
D28: ='KPI 1'!D28 -> ACTUAL2024/25 | E28: =SUM($E21:E21) -> 0 | F28: =SUM($E21:F21) -> 0 | G28: =SUM($E21:G21) -> 0 | H28: =SUM($E21:H21) -> 0 | I28: =SUM($E21:I21) -> 0 | J28: =SUM($E21:J21) -> 0 | K28: =SUM($E21:K21) -> 0 | L28: =SUM($E21:L21) -> 0 | ... P28: =SUM($E21:P21) -> 0
D29: ='KPI 1'!D29 -> DIFFERENCE | E29: =SUM($E22:E22) -> 266970 | F29: =SUM($E22:F22) -> 539240 | G29: =SUM($E22:G22) -> 815410 | H29: =SUM($E22:H22) -> 1094680 | I29: =SUM($E22:I22) -> 1379900 | J29: =SUM($E22:J22) -> 1671020 | K29: =SUM($E22:K22) -> 1968040 | L29: =SUM($E22:L22) -> 2269810 | ... P29: =SUM($E22:P22) -> 3534590
D30: ='KPI 1'!D30 -> %REALISATION | E30: =E28/E26 -> 0 | F30: =F27/F26 -> 5.2042726 | G30: =G27/G26 -> 5.238318 | H30: =H27/H26 -> 5.2674255 | I30: =I27/I26 -> 5.3034461 | J30: =J27/J26 -> 5.3427933 | K30: =K27/K26 -> 5.3840413 | L30: =L27/L26 -> 5.4242359 | M30: =M27/M26 -> 5.461909 | ... P30: =P27/P26 -> 5.5930012

Sheet KPI 3b
A1: KPI | B1: 5b | C1: New Connection Fee Water | G1: Actual month: | I1: =INDEX($E$18:$P$18,Actual_month) -> 46082 | L1: Dashboard
A2: Unit | C2: Ksh.
C3: l | J3: Comments
C4: l | R4: actual | S4: =INDEX(E27:P27,Actual_month) -> 1864500
C5: l | R5: target | S5: =INDEX(E26:P26,Actual_month) -> 0
R6: 0.9 | S6: =+S5*R6 -> 0
J9: Actions
C18: MONTHLY | E18: ='KPI 1'!E18 -> 45839 | F18: ='KPI 1'!F18 -> 45870 | G18: ='KPI 1'!G18 -> 45901 | H18: ='KPI 1'!H18 -> 45931 | I18: ='KPI 1'!I18 -> 45962 | J18: ='KPI 1'!J18 -> 45992 | K18: ='KPI 1'!K18 -> 46023 | L18: ='KPI 1'!L18 -> 46054 | ... P18: ='KPI 1'!P18 -> 46174 | Q18: Total
D19: ='KPI 1'!D19 -> budget2025/26 | E19: =BUDGET2526!D9 -> 0 | F19: =BUDGET2526!E9 -> 0 | G19: =BUDGET2526!F9 -> 0 | H19: =BUDGET2526!G9 -> 0 | I19: =BUDGET2526!H9 -> 0 | J19: =BUDGET2526!I9 -> 0 | K19: =BUDGET2526!J9 -> 0 | L19: =BUDGET2526!K9 -> 0 | ... P19: =BUDGET2526!O9 -> 0 | Q19: =SUM(E19:P19) -> 0
D20: ='KPI 1'!D20 -> ACTUAL2025/26 | E20: =ACTUAL2122!D10 -> 120000 | F20: =ACTUAL2122!E10 -> 108000 | G20: =ACTUAL2122!F10 -> 164000 | H20: =ACTUAL2122!G10 -> 334500 | I20: =ACTUAL2122!H10 -> 192000 | J20: =ACTUAL2122!I10 -> 234000 | K20: =ACTUAL2122!J10 -> 128500 | L20: =ACTUAL2122!K10 -> 264500 | ... P20: =ACTUAL2122!O10 -> 310000 | Q20: =SUM(E20:P20) -> 2520000
D21: ='KPI 1'!D21 -> ACTUAL2024/25 | E21: =ACTUAL2021!D9 -> 0 | F21: =ACTUAL2021!E9 -> 0 | G21: =ACTUAL2021!F9 -> 0 | H21: =ACTUAL2021!G9 -> 0 | I21: =ACTUAL2021!H9 -> 0 | J21: =ACTUAL2021!I9 -> 0 | K21: =ACTUAL2021!J9 -> 0 | L21: =ACTUAL2021!K9 -> 0 | ... P21: =ACTUAL2021!O9 -> 0 | Q21: =SUM(E21:P21) -> 0
D22: ='KPI 1'!D22 -> DIFFERENCE | E22: =IF(E20=0,0,E20-E19) -> 120000 | F22: =IF(F20=0,0,F20-F19) -> 108000 | G22: =IF(G20=0,0,G20-G19) -> 164000 | H22: =IF(H20=0,0,H20-H19) -> 334500 | I22: =IF(I20=0,0,I20-I19) -> 192000 | J22: =IF(J20=0,0,J20-J19) -> 234000 | K22: =IF(K20=0,0,K20-K19) -> 128500 | L22: =IF(L20=0,0,L20-L19) -> 264500 | ... P22: =IF(P20=0,0,P20-P19) -> 310000 | Q22: =SUM(E22:P22) -> 2520000
D23: ='KPI 1'!D23 -> %REALISATION | E23: =E21/E19 -> #DIV/0! | F23: =F20/F19 -> #DIV/0! | G23: =G20/G19 -> #DIV/0! | H23: =H20/H19 -> #DIV/0! | I23: =I20/I19 -> #DIV/0! | J23: =J20/J19 -> #DIV/0! | K23: =K20/K19 -> #DIV/0! | L23: =L20/L19 -> #DIV/0! | M23: =M20/M19 -> #DIV/0! | ... P23: =P20/P19 -> #DIV/0!
E24: =#REF! -> #REF! | F24: =#REF! -> #REF! | G24: =#REF! -> #REF! | H24: =#REF! -> #REF! | I24: =#REF! -> #REF! | J24: =#REF! -> #REF! | K24: =#REF! -> #REF! | L24: =#REF! -> #REF! | ... P24: =#REF! -> #REF!
C25: CUMULATIVE | D25: ='KPI 1'!D25 -> 0 | E25: ='KPI 1'!E25 -> 45839 | F25: ='KPI 1'!F25 -> 45870 | G25: ='KPI 1'!G25 -> 45901 | H25: ='KPI 1'!H25 -> 45931 | I25: ='KPI 1'!I25 -> 45962 | J25: ='KPI 1'!J25 -> 45992 | K25: ='KPI 1'!K25 -> 46023 | ... P25: ='KPI 1'!P25 -> 46174
D26: ='KPI 1'!D26 -> budget2025/26 | E26: =SUM($E19:E19) -> 0 | F26: =SUM($E19:F19) -> 0 | G26: =SUM($E19:G19) -> 0 | H26: =SUM($E19:H19) -> 0 | I26: =SUM($E19:I19) -> 0 | J26: =SUM($E19:J19) -> 0 | K26: =SUM($E19:K19) -> 0 | L26: =SUM($E19:L19) -> 0 | ... P26: =SUM($E19:P19) -> 0
D27: ='KPI 1'!D27 -> ACTUAL2025/26 | E27: =SUM($E20:E20) -> 120000 | F27: =SUM($E20:F20) -> 228000 | G27: =SUM($E20:G20) -> 392000 | H27: =SUM($E20:H20) -> 726500 | I27: =SUM($E20:I20) -> 918500 | J27: =SUM($E20:J20) -> 1152500 | K27: =SUM($E20:K20) -> 1281000 | L27: =SUM($E20:L20) -> 1545500 | ... P27: =SUM($E20:P20) -> 2520000
D28: ='KPI 1'!D28 -> ACTUAL2024/25 | E28: =SUM($E21:E21) -> 0 | F28: =SUM($E21:F21) -> 0 | G28: =SUM($E21:G21) -> 0 | H28: =SUM($E21:H21) -> 0 | I28: =SUM($E21:I21) -> 0 | J28: =SUM($E21:J21) -> 0 | K28: =SUM($E21:K21) -> 0 | L28: =SUM($E21:L21) -> 0 | ... P28: =SUM($E21:P21) -> 0
D29: ='KPI 1'!D29 -> DIFFERENCE | E29: =SUM($E22:E22) -> 120000 | F29: =SUM($E22:F22) -> 228000 | G29: =SUM($E22:G22) -> 392000 | H29: =SUM($E22:H22) -> 726500 | I29: =SUM($E22:I22) -> 918500 | J29: =SUM($E22:J22) -> 1152500 | K29: =SUM($E22:K22) -> 1281000 | L29: =SUM($E22:L22) -> 1545500 | ... P29: =SUM($E22:P22) -> 2520000
D30: ='KPI 1'!D30 -> %REALISATION | E30: =E28/E26 -> #DIV/0! | F30: =F27/F26 -> #DIV/0! | G30: =G27/G26 -> #DIV/0! | H30: =H27/H26 -> #DIV/0! | I30: =I27/I26 -> #DIV/0! | J30: =J27/J26 -> #DIV/0! | K30: =K27/K26 -> #DIV/0! | L30: =L27/L26 -> #DIV/0! | M30: =M27/M26 -> #DIV/0! | ... P30: =P27/P26 -> #DIV/0!

Sheet KPI 3c
A1: KPI | B1: 5c | C1: Re-connection fee water (RCF) | G1: Actual month: | I1: =INDEX($E$18:$P$18,Actual_month) -> 46082 | L1: Dashboard
A2: Unit | C2: Ksh.
C3: l | J3: Comments
C4: l | R4: actual | S4: =INDEX(E27:P27,Actual_month) -> 797000
C5: l | R5: target | S5: =INDEX(E26:P26,Actual_month) -> 4500000
R6: 0.9 | S6: =+S5*R6 -> 4050000
J9: Actions
C18: MONTHLY | E18: ='KPI 1'!E18 -> 45839 | F18: ='KPI 1'!F18 -> 45870 | G18: ='KPI 1'!G18 -> 45901 | H18: ='KPI 1'!H18 -> 45931 | I18: ='KPI 1'!I18 -> 45962 | J18: ='KPI 1'!J18 -> 45992 | K18: ='KPI 1'!K18 -> 46023 | L18: ='KPI 1'!L18 -> 46054 | ... P18: ='KPI 1'!P18 -> 46174 | Q18: Total
D19: ='KPI 1'!D19 -> budget2025/26 | E19: =BUDGET2526!D11 -> 455000 | F19: =BUDGET2526!E11 -> 407500 | G19: =BUDGET2526!F11 -> 412500 | H19: =BUDGET2526!G11 -> 587500 | I19: =BUDGET2526!H11 -> 562500 | J19: =BUDGET2526!I11 -> 537500 | K19: =BUDGET2526!J11 -> 550000 | L19: =BUDGET2526!K11 -> 512500 | ... P19: =BUDGET2526!O11 -> 420000 | Q19: =SUM(E19:P19) -> 5770000
D20: ='KPI 1'!D20 -> ACTUAL2025/26 | E20: =ACTUAL2122!D11 -> 91500 | F20: =ACTUAL2122!E11 -> 77000 | G20: =ACTUAL2122!F11 -> 68000 | H20: =ACTUAL2122!G11 -> 65500 | I20: =ACTUAL2122!H11 -> 64000 | J20: =ACTUAL2122!I11 -> 66000 | K20: =ACTUAL2122!J11 -> 45500 | L20: =ACTUAL2122!K11 -> 40500 | ... P20: =ACTUAL2122!O11 -> 457000 | Q20: =SUM(E20:P20) -> 1962500
D21: ='KPI 1'!D21 -> ACTUAL2024/25 | E21: =ACTUAL2021!D10 -> 0 | F21: =ACTUAL2021!E10 -> 0 | G21: =ACTUAL2021!F10 -> 0 | H21: =ACTUAL2021!G10 -> 0 | I21: =ACTUAL2021!H10 -> 0 | J21: =ACTUAL2021!I10 -> 0 | K21: =ACTUAL2021!J10 -> 0 | L21: =ACTUAL2021!K10 -> 0 | ... P21: =ACTUAL2021!O10 -> 0 | Q21: =SUM(E21:P21) -> 0
D22: ='KPI 1'!D22 -> DIFFERENCE | E22: =IF(E20=0,0,E20-E19) -> -363500 | F22: =IF(F20=0,0,F20-F19) -> -330500 | G22: =IF(G20=0,0,G20-G19) -> -344500 | H22: =IF(H20=0,0,H20-H19) -> -522000 | I22: =IF(I20=0,0,I20-I19) -> -498500 | J22: =IF(J20=0,0,J20-J19) -> -471500 | K22: =IF(K20=0,0,K20-K19) -> -504500 | L22: =IF(L20=0,0,L20-L19) -> -472000 | ... P22: =IF(P20=0,0,P20-P19) -> 37000 | Q22: =SUM(E22:P22) -> -3807500
D23: ='KPI 1'!D23 -> %REALISATION | E23: =E21/E19 -> 0 | F23: =F20/F19 -> 0.18895706 | G23: =G20/G19 -> 0.16484848 | H23: =H20/H19 -> 0.11148936 | I23: =I20/I19 -> 0.11377778 | J23: =J20/J19 -> 0.1227907 | K23: =K20/K19 -> 0.082727273 | L23: =L20/L19 -> 0.07902439 | M23: =M20/M19 -> 0.58736842 | ... P23: =P20/P19 -> 1.0880952
E24: =#REF! -> #REF! | F24: =#REF! -> #REF! | G24: =#REF! -> #REF! | H24: =#REF! -> #REF! | I24: =#REF! -> #REF! | J24: =#REF! -> #REF! | K24: =#REF! -> #REF! | L24: =#REF! -> #REF! | ... P24: =#REF! -> #REF!
C25: CUMULATIVE | D25: ='KPI 1'!D25 -> 0 | E25: ='KPI 1'!E25 -> 45839 | F25: ='KPI 1'!F25 -> 45870 | G25: ='KPI 1'!G25 -> 45901 | H25: ='KPI 1'!H25 -> 45931 | I25: ='KPI 1'!I25 -> 45962 | J25: ='KPI 1'!J25 -> 45992 | K25: ='KPI 1'!K25 -> 46023 | ... P25: ='KPI 1'!P25 -> 46174
D26: ='KPI 1'!D26 -> budget2025/26 | E26: =SUM($E19:E19) -> 455000 | F26: =SUM($E19:F19) -> 862500 | G26: =SUM($E19:G19) -> 1275000 | H26: =SUM($E19:H19) -> 1862500 | I26: =SUM($E19:I19) -> 2425000 | J26: =SUM($E19:J19) -> 2962500 | K26: =SUM($E19:K19) -> 3512500 | L26: =SUM($E19:L19) -> 4025000 | ... P26: =SUM($E19:P19) -> 5770000
D27: ='KPI 1'!D27 -> ACTUAL2025/26 | E27: =SUM($E20:E20) -> 91500 | F27: =SUM($E20:F20) -> 168500 | G27: =SUM($E20:G20) -> 236500 | H27: =SUM($E20:H20) -> 302000 | I27: =SUM($E20:I20) -> 366000 | J27: =SUM($E20:J20) -> 432000 | K27: =SUM($E20:K20) -> 477500 | L27: =SUM($E20:L20) -> 518000 | ... P27: =SUM($E20:P20) -> 1962500
D28: ='KPI 1'!D28 -> ACTUAL2024/25 | E28: =SUM($E21:E21) -> 0 | F28: =SUM($E21:F21) -> 0 | G28: =SUM($E21:G21) -> 0 | H28: =SUM($E21:H21) -> 0 | I28: =SUM($E21:I21) -> 0 | J28: =SUM($E21:J21) -> 0 | K28: =SUM($E21:K21) -> 0 | L28: =SUM($E21:L21) -> 0 | ... P28: =SUM($E21:P21) -> 0
D29: ='KPI 1'!D29 -> DIFFERENCE | E29: =SUM($E22:E22) -> -363500 | F29: =SUM($E22:F22) -> -694000 | G29: =SUM($E22:G22) -> -1038500 | H29: =SUM($E22:H22) -> -1560500 | I29: =SUM($E22:I22) -> -2059000 | J29: =SUM($E22:J22) -> -2530500 | K29: =SUM($E22:K22) -> -3035000 | L29: =SUM($E22:L22) -> -3507000 | ... P29: =SUM($E22:P22) -> -3807500
D30: ='KPI 1'!D30 -> %REALISATION | E30: =E28/E26 -> 0 | F30: =F27/F26 -> 0.19536232 | G30: =G27/G26 -> 0.1854902 | H30: =H27/H26 -> 0.16214765 | I30: =I27/I26 -> 0.15092784 | J30: =J27/J26 -> 0.14582278 | K30: =K27/K26 -> 0.13594306 | L30: =L27/L26 -> 0.12869565 | M30: =M27/M26 -> 0.17711111 | ... P30: =P27/P26 -> 0.34012132

Sheet KPI 3d
A1: KPI | B1: 5d | C1: Penalties water (ICW, IRW, MB) | G1: Actual month: | I1: =INDEX($E$18:$P$18,Actual_month) -> 46082 | L1: Dashboard
A2: Unit | C2: Ksh.
C3: l | J3: Comments
C4: l | R4: actual | S4: =INDEX(E27:P27,Actual_month) -> 886571
C5: l | R5: target | S5: =INDEX(E26:P26,Actual_month) -> 5242500
R6: 0.9 | S6: =+S5*R6 -> 4718250
J9: Actions
C18: MONTHLY | E18: ='KPI 1'!E18 -> 45839 | F18: ='KPI 1'!F18 -> 45870 | G18: ='KPI 1'!G18 -> 45901 | H18: ='KPI 1'!H18 -> 45931 | I18: ='KPI 1'!I18 -> 45962 | J18: ='KPI 1'!J18 -> 45992 | K18: ='KPI 1'!K18 -> 46023 | L18: ='KPI 1'!L18 -> 46054 | ... P18: ='KPI 1'!P18 -> 46174 | Q18: Total
D19: ='KPI 1'!D19 -> budget2025/26 | E19: =BUDGET2526!D13 -> 582500 | F19: =BUDGET2526!E13 -> 582500 | G19: =BUDGET2526!F13 -> 582500 | H19: =BUDGET2526!G13 -> 582500 | I19: =BUDGET2526!H13 -> 582500 | J19: =BUDGET2526!I13 -> 582500 | K19: =BUDGET2526!J13 -> 582500 | L19: =BUDGET2526!K13 -> 582500 | ... P19: =BUDGET2526!O13 -> 582500 | Q19: =SUM(E19:P19) -> 6990000
D20: ='KPI 1'!D20 -> ACTUAL2025/26 | E20: =ACTUAL2122!D13 -> 178060 | F20: =ACTUAL2122!E13 -> 147985 | G20: =ACTUAL2122!F13 -> 169420 | H20: =ACTUAL2122!G13 -> 76210 | I20: =ACTUAL2122!H13 -> 8000 | J20: =ACTUAL2122!I13 -> 17495 | K20: =ACTUAL2122!J13 -> 16000 | L20: =ACTUAL2122!K13 -> 39884 | ... P20: =ACTUAL2122!O13 -> 0 | Q20: =SUM(E20:P20) -> 906971
D21: ='KPI 1'!D21 -> ACTUAL2024/25 | E21: =ACTUAL2021!D12 -> 0 | F21: =ACTUAL2021!E12 -> 0 | G21: =ACTUAL2021!F12 -> 0 | H21: =ACTUAL2021!G12 -> 0 | I21: =ACTUAL2021!H12 -> 0 | J21: =ACTUAL2021!I12 -> 0 | K21: =ACTUAL2021!J12 -> 0 | L21: =ACTUAL2021!K12 -> 0 | ... P21: =ACTUAL2021!O12 -> 0 | Q21: =SUM(E21:P21) -> 0
D22: ='KPI 1'!D22 -> DIFFERENCE | E22: =IF(E20=0,0,E20-E19) -> -404440 | F22: =IF(F20=0,0,F20-F19) -> -434515 | G22: =IF(G20=0,0,G20-G19) -> -413080 | H22: =IF(H20=0,0,H20-H19) -> -506290 | I22: =IF(I20=0,0,I20-I19) -> -574500 | J22: =IF(J20=0,0,J20-J19) -> -565005 | K22: =IF(K20=0,0,K20-K19) -> -566500 | L22: =IF(L20=0,0,L20-L19) -> -542616 | ... P22: =IF(P20=0,0,P20-P19) -> 0 | Q22: =SUM(E22:P22) -> -5500529
D23: ='KPI 1'!D23 -> %REALISATION | E23: =E21/E19 -> 0 | F23: =F20/F19 -> 0.2540515 | G23: =G20/G19 -> 0.29084979 | H23: =H20/H19 -> 0.13083262 | I23: =I20/I19 -> 0.013733906 | J23: =J20/J19 -> 0.030034335 | K23: =K20/K19 -> 0.027467811 | L23: =L20/L19 -> 0.068470386 | M23: =M20/M19 -> 0.40088755 | ... P23: =P20/P19 -> 0
E24: =#REF! -> #REF! | F24: =#REF! -> #REF! | G24: =#REF! -> #REF! | H24: =#REF! -> #REF! | I24: =#REF! -> #REF! | J24: =#REF! -> #REF! | K24: =#REF! -> #REF! | L24: =#REF! -> #REF! | ... P24: =#REF! -> #REF!
C25: CUMULATIVE | D25: ='KPI 1'!D25 -> 0 | E25: ='KPI 1'!E25 -> 45839 | F25: ='KPI 1'!F25 -> 45870 | G25: ='KPI 1'!G25 -> 45901 | H25: ='KPI 1'!H25 -> 45931 | I25: ='KPI 1'!I25 -> 45962 | J25: ='KPI 1'!J25 -> 45992 | K25: ='KPI 1'!K25 -> 46023 | ... P25: ='KPI 1'!P25 -> 46174
D26: ='KPI 1'!D26 -> budget2025/26 | E26: =SUM($E19:E19) -> 582500 | F26: =SUM($E19:F19) -> 1165000 | G26: =SUM($E19:G19) -> 1747500 | H26: =SUM($E19:H19) -> 2330000 | I26: =SUM($E19:I19) -> 2912500 | J26: =SUM($E19:J19) -> 3495000 | K26: =SUM($E19:K19) -> 4077500 | L26: =SUM($E19:L19) -> 4660000 | ... P26: =SUM($E19:P19) -> 6990000
D27: ='KPI 1'!D27 -> ACTUAL2025/26 | E27: =SUM($E20:E20) -> 178060 | F27: =SUM($E20:F20) -> 326045 | G27: =SUM($E20:G20) -> 495465 | H27: =SUM($E20:H20) -> 571675 | I27: =SUM($E20:I20) -> 579675 | J27: =SUM($E20:J20) -> 597170 | K27: =SUM($E20:K20) -> 613170 | L27: =SUM($E20:L20) -> 653054 | ... P27: =SUM($E20:P20) -> 906971
D28: ='KPI 1'!D28 -> ACTUAL2024/25 | E28: =SUM($E21:E21) -> 0 | F28: =SUM($E21:F21) -> 0 | G28: =SUM($E21:G21) -> 0 | H28: =SUM($E21:H21) -> 0 | I28: =SUM($E21:I21) -> 0 | J28: =SUM($E21:J21) -> 0 | K28: =SUM($E21:K21) -> 0 | L28: =SUM($E21:L21) -> 0 | ... P28: =SUM($E21:P21) -> 0
D29: ='KPI 1'!D29 -> DIFFERENCE | E29: =SUM($E22:E22) -> -404440 | F29: =SUM($E22:F22) -> -838955 | G29: =SUM($E22:G22) -> -1252035 | H29: =SUM($E22:H22) -> -1758325 | I29: =SUM($E22:I22) -> -2332825 | J29: =SUM($E22:J22) -> -2897830 | K29: =SUM($E22:K22) -> -3464330 | L29: =SUM($E22:L22) -> -4006946 | ... P29: =SUM($E22:P22) -> -5500529
D30: ='KPI 1'!D30 -> %REALISATION | E30: =E28/E26 -> 0 | F30: =F27/F26 -> 0.27986695 | G30: =G27/G26 -> 0.2835279 | H30: =H27/H26 -> 0.24535408 | I30: =I27/I26 -> 0.19903004 | J30: =J27/J26 -> 0.17086409 | K30: =K27/K26 -> 0.15037891 | L30: =L27/L26 -> 0.14014034 | M30: =M27/M26 -> 0.16911226 | ... P30: =P27/P26 -> 0.12975265

Sheet KPI k
A1: KPI | B1: =Dashboard!A12 -> 7 | C1: =Dashboard!B12 -> reconnection fee (water+sewer) | G1: Actual month: | I1: =INDEX($E$18:$P$18,Actual_month) -> 46082 | L1: Dashboard
A2: Unit | C2: Ksh.
C3: l | J3: Comments
C4: l | R4: actual | S4: =INDEX(E27:P27,Actual_month) -> 1335000
C5: l | R5: target | S5: =INDEX(E26:P26,Actual_month) -> 5242500
R6: 0.9 | S6: =+S5*R6 -> 4718250
J9: Actions
C18: MONTHLY | E18: ='KPI 1'!E18 -> 45839 | F18: ='KPI 1'!F18 -> 45870 | G18: ='KPI 1'!G18 -> 45901 | H18: ='KPI 1'!H18 -> 45931 | I18: ='KPI 1'!I18 -> 45962 | J18: ='KPI 1'!J18 -> 45992 | K18: ='KPI 1'!K18 -> 46023 | L18: ='KPI 1'!L18 -> 46054 | ... P18: ='KPI 1'!P18 -> 46174 | Q18: Total
D19: ='KPI 1'!D19 -> budget2025/26 | E19: =BUDGET2526!D13 -> 582500 | F19: =BUDGET2526!E13 -> 582500 | G19: =BUDGET2526!F13 -> 582500 | H19: =BUDGET2526!G13 -> 582500 | I19: =BUDGET2526!H13 -> 582500 | J19: =BUDGET2526!I13 -> 582500 | K19: =BUDGET2526!J13 -> 582500 | L19: =BUDGET2526!K13 -> 582500 | ... P19: =BUDGET2526!O13 -> 582500 | Q19: =SUM(E19:P19) -> 6990000
D20: ='KPI 1'!D20 -> ACTUAL2025/26 | E20: ='ACTUAL 2526'!E13 -> 165000 | F20: ='ACTUAL 2526'!F13 -> 261500 | G20: ='ACTUAL 2526'!G13 -> 120500 | H20: ='ACTUAL 2526'!H13 -> 67500 | I20: ='ACTUAL 2526'!I13 -> 114000 | J20: ='ACTUAL 2526'!J13 -> 101000 | K20: ='ACTUAL 2526'!K13 -> 162000 | L20: ='ACTUAL 2526'!L13 -> 186000 | ... P20: ='ACTUAL 2526'!P13 -> 0 | Q20: =SUM(E20:P20) -> 1335000
D21: ='KPI 1'!D21 -> ACTUAL2024/25 | E21: ='Actual 202425'!E13 -> 714000 | F21: ='Actual 202425'!F13 -> 279000 | G21: ='Actual 202425'!G13 -> 192500 | H21: ='Actual 202425'!H13 -> 270000 | I21: ='Actual 202425'!I13 -> 176500 | J21: ='Actual 202425'!J13 -> 155000 | K21: ='Actual 202425'!K13 -> 268500 | L21: ='Actual 202425'!L13 -> 165000 | ... P21: ='Actual 202425'!P13 -> 127000 | Q21: =SUM(E21:P21) -> 2864500
D22: ='KPI 1'!D22 -> DIFFERENCE | E22: =IF(E20=0,0,E20-E19) -> -417500 | F22: =IF(F20=0,0,F20-F19) -> -321000 | G22: =IF(G20=0,0,G20-G19) -> -462000 | H22: =IF(H20=0,0,H20-H19) -> -515000 | I22: =IF(I20=0,0,I20-I19) -> -468500 | J22: =IF(J20=0,0,J20-J19) -> -481500 | K22: =IF(K20=0,0,K20-K19) -> -420500 | L22: =IF(L20=0,0,L20-L19) -> -396500 | ... P22: =IF(P20=0,0,P20-P19) -> 0 | Q22: =SUM(E22:P22) -> -3907500
D23: ='KPI 1'!D23 -> %REALISATION | E23: =E20/E19 -> 0.2832618 | F23: =F20/F19 -> 0.44892704 | G23: =G20/G19 -> 0.20686695 | H23: =H20/H19 -> 0.11587983 | I23: =I20/I19 -> 0.19570815 | J23: =J20/J19 -> 0.17339056 | K23: =K20/K19 -> 0.27811159 | L23: =L20/L19 -> 0.3193133 | ... P23: =P20/P19 -> 0
C25: CUMULATIVE | D25: ='KPI 1'!D25 -> 0 | E25: ='KPI 1'!E25 -> 45839 | F25: ='KPI 1'!F25 -> 45870 | G25: ='KPI 1'!G25 -> 45901 | H25: ='KPI 1'!H25 -> 45931 | I25: ='KPI 1'!I25 -> 45962 | J25: ='KPI 1'!J25 -> 45992 | K25: ='KPI 1'!K25 -> 46023 | ... P25: ='KPI 1'!P25 -> 46174
D26: ='KPI 1'!D26 -> budget2025/26 | E26: =SUM($E19:E19) -> 582500 | F26: =SUM($E19:F19) -> 1165000 | G26: =SUM($E19:G19) -> 1747500 | H26: =SUM($E19:H19) -> 2330000 | I26: =SUM($E19:I19) -> 2912500 | J26: =SUM($E19:J19) -> 3495000 | K26: =SUM($E19:K19) -> 4077500 | L26: =SUM($E19:L19) -> 4660000 | ... P26: =SUM($E19:P19) -> 6990000
D27: ='KPI 1'!D27 -> ACTUAL2025/26 | E27: =SUM($E20:E20) -> 165000 | F27: =SUM($E20:F20) -> 426500 | G27: =SUM($E20:G20) -> 547000 | H27: =SUM($E20:H20) -> 614500 | I27: =SUM($E20:I20) -> 728500 | J27: =SUM($E20:J20) -> 829500 | K27: =SUM($E20:K20) -> 991500 | L27: =SUM($E20:L20) -> 1177500 | ... P27: =SUM($E20:P20) -> 1335000
D28: ='KPI 1'!D28 -> ACTUAL2024/25 | E28: =SUM($E21:E21) -> 714000 | F28: =SUM($E21:F21) -> 993000 | G28: =SUM($E21:G21) -> 1185500 | H28: =SUM($E21:H21) -> 1455500 | I28: =SUM($E21:I21) -> 1632000 | J28: =SUM($E21:J21) -> 1787000 | K28: =SUM($E21:K21) -> 2055500 | L28: =SUM($E21:L21) -> 2220500 | ... P28: =SUM($E21:P21) -> 2864500
D29: ='KPI 1'!D29 -> DIFFERENCE | E29: =SUM($E22:E22) -> -417500 | F29: =SUM($E22:F22) -> -738500 | G29: =SUM($E22:G22) -> -1200500 | H29: =SUM($E22:H22) -> -1715500 | I29: =SUM($E22:I22) -> -2184000 | J29: =SUM($E22:J22) -> -2665500 | K29: =SUM($E22:K22) -> -3086000 | L29: =SUM($E22:L22) -> -3482500 | ... P29: =SUM($E22:P22) -> -3907500
D30: ='KPI 1'!D30 -> %REALISATION | E30: =E27/E26 -> 0.2832618 | F30: =F27/F26 -> 0.36609442 | G30: =G27/G26 -> 0.3130186 | H30: =H27/H26 -> 0.26373391 | I30: =I27/I26 -> 0.25012876 | J30: =J27/J26 -> 0.23733906 | K30: =K27/K26 -> 0.2431637 | L30: =L27/L26 -> 0.2526824 | ... P30: =P27/P26 -> 0.19098712

Sheet KPI 4a
A1: KPI | B1: 5a | C1: Unblockage fee sewer (SWF) | G1: Actual month: | I1: =INDEX($E$18:$P$18,Actual_month) -> 46082 | L1: Dashboard
A2: Unit | C2: Ksh.
C3: l | J3: Comments
C4: l | R4: actual | S4: =INDEX(E27:P27,Actual_month) -> 7500
C5: l | R5: target | S5: =INDEX(E26:P26,Actual_month) -> 1710009
R6: 0.9 | S6: =+S5*R6 -> 1539008.1
J9: Actions
C18: MONTHLY | E18: ='KPI 1'!E18 -> 45839 | F18: ='KPI 1'!F18 -> 45870 | G18: ='KPI 1'!G18 -> 45901 | H18: ='KPI 1'!H18 -> 45931 | I18: ='KPI 1'!I18 -> 45962 | J18: ='KPI 1'!J18 -> 45992 | K18: ='KPI 1'!K18 -> 46023 | L18: ='KPI 1'!L18 -> 46054 | ... P18: ='KPI 1'!P18 -> 46174 | Q18: Total
D19: ='KPI 1'!D19 -> budget2025/26 | E19: =BUDGET2526!D17 -> 110001 | F19: =BUDGET2526!E17 -> 260001 | G19: =BUDGET2526!F17 -> 220001 | H19: =BUDGET2526!G17 -> 150001 | I19: =BUDGET2526!H17 -> 160001 | J19: =BUDGET2526!I17 -> 240001 | K19: =BUDGET2526!J17 -> 190001 | L19: =BUDGET2526!K17 -> 190001 | ... P19: =BUDGET2526!O17 -> 120001 | Q19: =SUM(E19:P19) -> 2100012
D20: ='KPI 1'!D20 -> ACTUAL2025/26 | E20: =ACTUAL2122!D17 -> 0 | F20: =ACTUAL2122!E17 -> 0 | G20: =ACTUAL2122!F17 -> 0 | H20: =ACTUAL2122!G17 -> 0 | I20: =ACTUAL2122!H17 -> 0 | J20: =ACTUAL2122!I17 -> 0 | K20: =ACTUAL2122!J17 -> 0 | L20: =ACTUAL2122!K17 -> 0 | ... P20: =ACTUAL2122!O17 -> 5000 | Q20: =SUM(E20:P20) -> 15000
D21: ='KPI 1'!D21 -> ACTUAL2024/25 | E21: =ACTUAL2021!D16 -> 0 | F21: =ACTUAL2021!E16 -> 0 | G21: =ACTUAL2021!F16 -> 0 | H21: =ACTUAL2021!G16 -> 0 | I21: =ACTUAL2021!H16 -> 0 | J21: =ACTUAL2021!I16 -> 0 | K21: =ACTUAL2021!J16 -> 0 | L21: =ACTUAL2021!K16 -> 0 | ... P21: =ACTUAL2021!O16 -> 0 | Q21: =SUM(E21:P21) -> 0
D22: ='KPI 1'!D22 -> DIFFERENCE | E22: =IF(E20=0,0,E20-E19) -> 0 | F22: =IF(F20=0,0,F20-F19) -> 0 | G22: =IF(G20=0,0,G20-G19) -> 0 | H22: =IF(H20=0,0,H20-H19) -> 0 | I22: =IF(I20=0,0,I20-I19) -> 0 | J22: =IF(J20=0,0,J20-J19) -> 0 | K22: =IF(K20=0,0,K20-K19) -> 0 | L22: =IF(L20=0,0,L20-L19) -> 0 | ... P22: =IF(P20=0,0,P20-P19) -> -115001 | Q22: =SUM(E22:P22) -> -455003
D23: ='KPI 1'!D23 -> %REALISATION | E23: =E21/E19 -> 0 | F23: =F20/F19 -> 0 | G23: =G20/G19 -> 0 | H23: =H20/H19 -> 0 | I23: =I20/I19 -> 0 | J23: =J20/J19 -> 0 | K23: =K20/K19 -> 0 | L23: =L20/L19 -> 0 | M23: =M20/M19 -> 0.039473476 | ... P23: =P20/P19 -> 0.041666319
E24: =#REF! -> #REF! | F24: =#REF! -> #REF! | G24: =#REF! -> #REF! | H24: =#REF! -> #REF! | I24: =#REF! -> #REF! | J24: =#REF! -> #REF! | K24: =#REF! -> #REF! | L24: =#REF! -> #REF! | ... P24: =#REF! -> #REF!
C25: CUMULATIVE | D25: ='KPI 1'!D25 -> 0 | E25: ='KPI 1'!E25 -> 45839 | F25: ='KPI 1'!F25 -> 45870 | G25: ='KPI 1'!G25 -> 45901 | H25: ='KPI 1'!H25 -> 45931 | I25: ='KPI 1'!I25 -> 45962 | J25: ='KPI 1'!J25 -> 45992 | K25: ='KPI 1'!K25 -> 46023 | ... P25: ='KPI 1'!P25 -> 46174
D26: ='KPI 1'!D26 -> budget2025/26 | E26: =SUM($E19:E19) -> 110001 | F26: =SUM($E19:F19) -> 370002 | G26: =SUM($E19:G19) -> 590003 | H26: =SUM($E19:H19) -> 740004 | I26: =SUM($E19:I19) -> 900005 | J26: =SUM($E19:J19) -> 1140006 | K26: =SUM($E19:K19) -> 1330007 | L26: =SUM($E19:L19) -> 1520008 | ... P26: =SUM($E19:P19) -> 2100012
D27: ='KPI 1'!D27 -> ACTUAL2025/26 | E27: =SUM($E20:E20) -> 0 | F27: =SUM($E20:F20) -> 0 | G27: =SUM($E20:G20) -> 0 | H27: =SUM($E20:H20) -> 0 | I27: =SUM($E20:I20) -> 0 | J27: =SUM($E20:J20) -> 0 | K27: =SUM($E20:K20) -> 0 | L27: =SUM($E20:L20) -> 0 | ... P27: =SUM($E20:P20) -> 15000
D28: ='KPI 1'!D28 -> ACTUAL2024/25 | E28: =SUM($E21:E21) -> 0 | F28: =SUM($E21:F21) -> 0 | G28: =SUM($E21:G21) -> 0 | H28: =SUM($E21:H21) -> 0 | I28: =SUM($E21:I21) -> 0 | J28: =SUM($E21:J21) -> 0 | K28: =SUM($E21:K21) -> 0 | L28: =SUM($E21:L21) -> 0 | ... P28: =SUM($E21:P21) -> 0
D29: ='KPI 1'!D29 -> DIFFERENCE | E29: =SUM($E22:E22) -> 0 | F29: =SUM($E22:F22) -> 0 | G29: =SUM($E22:G22) -> 0 | H29: =SUM($E22:H22) -> 0 | I29: =SUM($E22:I22) -> 0 | J29: =SUM($E22:J22) -> 0 | K29: =SUM($E22:K22) -> 0 | L29: =SUM($E22:L22) -> 0 | ... P29: =SUM($E22:P22) -> -455003
D30: ='KPI 1'!D30 -> %REALISATION | E30: =E28/E26 -> 0 | F30: =F27/F26 -> 0 | G30: =G27/G26 -> 0 | H30: =H27/H26 -> 0 | I30: =I27/I26 -> 0 | J30: =J27/J26 -> 0 | K30: =K27/K26 -> 0 | L30: =L27/L26 -> 0 | M30: =M27/M26 -> 0.0043859418 | ... P30: =P27/P26 -> 0.0071428163

Sheet KPI 4b
A1: KPI | B1: 6b | C1: New connection fee sewer (SNC) | G1: Actual month: | I1: =INDEX($E$18:$P$18,Actual_month) -> 46082 | L1: Dashboard
A2: Unit | C2: Ksh.
C3: l | J3: Comments
C4: l | R4: actual | S4: =INDEX(E27:P27,Actual_month) -> 323000
C5: l | R5: target | S5: =INDEX(E26:P26,Actual_month) -> 0
R6: 0.9 | S6: =+S5*R6 -> 0
J9: Actions
C18: MONTHLY | E18: ='KPI 1'!E18 -> 45839 | F18: ='KPI 1'!F18 -> 45870 | G18: ='KPI 1'!G18 -> 45901 | H18: ='KPI 1'!H18 -> 45931 | I18: ='KPI 1'!I18 -> 45962 | J18: ='KPI 1'!J18 -> 45992 | K18: ='KPI 1'!K18 -> 46023 | L18: ='KPI 1'!L18 -> 46054 | ... P18: ='KPI 1'!P18 -> 46174 | Q18: Total
D19: ='KPI 1'!D19 -> budget2025/26 | E19: =BUDGET2526!D18 -> 0 | F19: =BUDGET2526!E18 -> 0 | G19: =BUDGET2526!F18 -> 0 | H19: =BUDGET2526!G18 -> 0 | I19: =BUDGET2526!H18 -> 0 | J19: =BUDGET2526!I18 -> 0 | K19: =BUDGET2526!J18 -> 0 | L19: =BUDGET2526!K18 -> 0 | ... P19: =BUDGET2526!O18 -> 0 | Q19: =SUM(E19:P19) -> 0
D20: ='KPI 1'!D20 -> ACTUAL2025/26 | E20: =ACTUAL2122!D18 -> 27500 | F20: =ACTUAL2122!E18 -> 38000 | G20: =ACTUAL2122!F18 -> 10500 | H20: =ACTUAL2122!G18 -> 19000 | I20: =ACTUAL2122!H18 -> 87500 | J20: =ACTUAL2122!I18 -> 27500 | K20: =ACTUAL2122!J18 -> 28000 | L20: =ACTUAL2122!K18 -> 60000 | ... P20: =ACTUAL2122!O18 -> 55000 | Q20: =SUM(E20:P20) -> 437500
D21: ='KPI 1'!D21 -> ACTUAL2024/25 | E21: =ACTUAL2021!D17 -> 0 | F21: =ACTUAL2021!E17 -> 0 | G21: =ACTUAL2021!F17 -> 0 | H21: =ACTUAL2021!G17 -> 0 | I21: =ACTUAL2021!H17 -> 0 | J21: =ACTUAL2021!I17 -> 0 | K21: =ACTUAL2021!J17 -> 0 | L21: =ACTUAL2021!K17 -> 0 | ... P21: =ACTUAL2021!O17 -> 0 | Q21: =SUM(E21:P21) -> 0
D22: ='KPI 1'!D22 -> DIFFERENCE | E22: =IF(E20=0,0,E20-E19) -> 27500 | F22: =IF(F20=0,0,F20-F19) -> 38000 | G22: =IF(G20=0,0,G20-G19) -> 10500 | H22: =IF(H20=0,0,H20-H19) -> 19000 | I22: =IF(I20=0,0,I20-I19) -> 87500 | J22: =IF(J20=0,0,J20-J19) -> 27500 | K22: =IF(K20=0,0,K20-K19) -> 28000 | L22: =IF(L20=0,0,L20-L19) -> 60000 | ... P22: =IF(P20=0,0,P20-P19) -> 55000 | Q22: =SUM(E22:P22) -> 437500
D23: ='KPI 1'!D23 -> %REALISATION | E23: =E21/E19 -> #DIV/0! | F23: =F20/F19 -> #DIV/0! | G23: =G20/G19 -> #DIV/0! | H23: =H20/H19 -> #DIV/0! | I23: =I20/I19 -> #DIV/0! | J23: =J20/J19 -> #DIV/0! | K23: =K20/K19 -> #DIV/0! | L23: =L20/L19 -> #DIV/0! | M23: =M20/M19 -> #DIV/0! | ... P23: =P20/P19 -> #DIV/0!
E24: =#REF! -> #REF! | F24: =#REF! -> #REF! | G24: =#REF! -> #REF! | H24: =#REF! -> #REF! | I24: =#REF! -> #REF! | J24: =#REF! -> #REF! | K24: =#REF! -> #REF! | L24: =#REF! -> #REF! | ... P24: =#REF! -> #REF!
C25: CUMULATIVE | D25: ='KPI 1'!D25 -> 0 | E25: ='KPI 1'!E25 -> 45839 | F25: ='KPI 1'!F25 -> 45870 | G25: ='KPI 1'!G25 -> 45901 | H25: ='KPI 1'!H25 -> 45931 | I25: ='KPI 1'!I25 -> 45962 | J25: ='KPI 1'!J25 -> 45992 | K25: ='KPI 1'!K25 -> 46023 | ... P25: ='KPI 1'!P25 -> 46174
D26: ='KPI 1'!D26 -> budget2025/26 | E26: =SUM($E19:E19) -> 0 | F26: =SUM($E19:F19) -> 0 | G26: =SUM($E19:G19) -> 0 | H26: =SUM($E19:H19) -> 0 | I26: =SUM($E19:I19) -> 0 | J26: =SUM($E19:J19) -> 0 | K26: =SUM($E19:K19) -> 0 | L26: =SUM($E19:L19) -> 0 | ... P26: =SUM($E19:P19) -> 0
D27: ='KPI 1'!D27 -> ACTUAL2025/26 | E27: =SUM($E20:E20) -> 27500 | F27: =SUM($E20:F20) -> 65500 | G27: =SUM($E20:G20) -> 76000 | H27: =SUM($E20:H20) -> 95000 | I27: =SUM($E20:I20) -> 182500 | J27: =SUM($E20:J20) -> 210000 | K27: =SUM($E20:K20) -> 238000 | L27: =SUM($E20:L20) -> 298000 | ... P27: =SUM($E20:P20) -> 437500
D28: ='KPI 1'!D28 -> ACTUAL2024/25 | E28: =SUM($E21:E21) -> 0 | F28: =SUM($E21:F21) -> 0 | G28: =SUM($E21:G21) -> 0 | H28: =SUM($E21:H21) -> 0 | I28: =SUM($E21:I21) -> 0 | J28: =SUM($E21:J21) -> 0 | K28: =SUM($E21:K21) -> 0 | L28: =SUM($E21:L21) -> 0 | ... P28: =SUM($E21:P21) -> 0
D29: ='KPI 1'!D29 -> DIFFERENCE | E29: =SUM($E22:E22) -> 27500 | F29: =SUM($E22:F22) -> 65500 | G29: =SUM($E22:G22) -> 76000 | H29: =SUM($E22:H22) -> 95000 | I29: =SUM($E22:I22) -> 182500 | J29: =SUM($E22:J22) -> 210000 | K29: =SUM($E22:K22) -> 238000 | L29: =SUM($E22:L22) -> 298000 | ... P29: =SUM($E22:P22) -> 437500
D30: ='KPI 1'!D30 -> %REALISATION | E30: =E28/E26 -> #DIV/0! | F30: =F27/F26 -> #DIV/0! | G30: =G27/G26 -> #DIV/0! | H30: =H27/H26 -> #DIV/0! | I30: =I27/I26 -> #DIV/0! | J30: =J27/J26 -> #DIV/0! | K30: =K27/K26 -> #DIV/0! | L30: =L27/L26 -> #DIV/0! | M30: =M27/M26 -> #DIV/0! | ... P30: =P27/P26 -> #DIV/0!

Sheet KPI 4c
A1: KPI | B1: 6c | C1: Re-connection fee sewer (RCFS) | G1: Actual month: | I1: =INDEX($E$18:$P$18,Actual_month) -> 46082 | L1: Dashboard
A2: Unit | C2: Ksh.
C3: l | J3: Comments
C4: l | R4: actual | S4: =INDEX(E27:P27,Actual_month) -> 658965
C5: l | R5: target | S5: =INDEX(E26:P26,Actual_month) -> 0
R6: 0.9 | S6: =+S5*R6 -> 0
J9: Actions
C18: MONTHLY | E18: ='KPI 1'!E18 -> 45839 | F18: ='KPI 1'!F18 -> 45870 | G18: ='KPI 1'!G18 -> 45901 | H18: ='KPI 1'!H18 -> 45931 | I18: ='KPI 1'!I18 -> 45962 | J18: ='KPI 1'!J18 -> 45992 | K18: ='KPI 1'!K18 -> 46023 | L18: ='KPI 1'!L18 -> 46054 | ... P18: ='KPI 1'!P18 -> 46174 | Q18: Total
D19: ='KPI 1'!D19 -> budget2025/26 | E19: =BUDGET2526!D19 -> 0 | F19: =BUDGET2526!E19 -> 0 | G19: =BUDGET2526!F19 -> 0 | H19: =BUDGET2526!G19 -> 0 | I19: =BUDGET2526!H19 -> 0 | J19: =BUDGET2526!I19 -> 0 | K19: =BUDGET2526!J19 -> 0 | L19: =BUDGET2526!K19 -> 0 | ... P19: =BUDGET2526!O19 -> 0 | Q19: =SUM(E19:P19) -> 0
D20: ='KPI 1'!D20 -> ACTUAL2025/26 | E20: =ACTUAL2122!D19 -> 178060 | F20: =ACTUAL2122!E19 -> 150985 | G20: =ACTUAL2122!F19 -> 172420 | H20: =ACTUAL2122!G19 -> 9000 | I20: =ACTUAL2122!H19 -> 3000 | J20: =ACTUAL2122!I19 -> 1500 | K20: =ACTUAL2122!J19 -> 13500 | L20: =ACTUAL2122!K19 -> 96000 | ... P20: =ACTUAL2122!O19 -> 13500 | Q20: =SUM(E20:P20) -> 700965
D21: ='KPI 1'!D21 -> ACTUAL2024/25 | E21: =ACTUAL2021!D18 -> 0 | F21: =ACTUAL2021!E18 -> 0 | G21: =ACTUAL2021!F18 -> 0 | H21: =ACTUAL2021!G18 -> 0 | I21: =ACTUAL2021!H18 -> 0 | J21: =ACTUAL2021!I18 -> 0 | K21: =ACTUAL2021!J18 -> 0 | L21: =ACTUAL2021!K18 -> 0 | ... P21: =ACTUAL2021!O18 -> 0 | Q21: =SUM(E21:P21) -> 0
D22: ='KPI 1'!D22 -> DIFFERENCE | E22: =IF(E20=0,0,E20-E19) -> 178060 | F22: =IF(F20=0,0,F20-F19) -> 150985 | G22: =IF(G20=0,0,G20-G19) -> 172420 | H22: =IF(H20=0,0,H20-H19) -> 9000 | I22: =IF(I20=0,0,I20-I19) -> 3000 | J22: =IF(J20=0,0,J20-J19) -> 1500 | K22: =IF(K20=0,0,K20-K19) -> 13500 | L22: =IF(L20=0,0,L20-L19) -> 96000 | ... P22: =IF(P20=0,0,P20-P19) -> 13500 | Q22: =SUM(E22:P22) -> 700965
D23: ='KPI 1'!D23 -> %REALISATION | E23: =E21/E19 -> #DIV/0! | F23: =F20/F19 -> #DIV/0! | G23: =G20/G19 -> #DIV/0! | H23: =H20/H19 -> #DIV/0! | I23: =I20/I19 -> #DIV/0! | J23: =J20/J19 -> #DIV/0! | K23: =K20/K19 -> #DIV/0! | L23: =L20/L19 -> #DIV/0! | M23: =M20/M19 -> #DIV/0! | ... P23: =P20/P19 -> #DIV/0!
E24: =#REF! -> #REF! | F24: =#REF! -> #REF! | G24: =#REF! -> #REF! | H24: =#REF! -> #REF! | I24: =#REF! -> #REF! | J24: =#REF! -> #REF! | K24: =#REF! -> #REF! | L24: =#REF! -> #REF! | ... P24: =#REF! -> #REF!
C25: CUMULATIVE | D25: ='KPI 1'!D25 -> 0 | E25: ='KPI 1'!E25 -> 45839 | F25: ='KPI 1'!F25 -> 45870 | G25: ='KPI 1'!G25 -> 45901 | H25: ='KPI 1'!H25 -> 45931 | I25: ='KPI 1'!I25 -> 45962 | J25: ='KPI 1'!J25 -> 45992 | K25: ='KPI 1'!K25 -> 46023 | ... P25: ='KPI 1'!P25 -> 46174
D26: ='KPI 1'!D26 -> budget2025/26 | E26: =SUM($E19:E19) -> 0 | F26: =SUM($E19:F19) -> 0 | G26: =SUM($E19:G19) -> 0 | H26: =SUM($E19:H19) -> 0 | I26: =SUM($E19:I19) -> 0 | J26: =SUM($E19:J19) -> 0 | K26: =SUM($E19:K19) -> 0 | L26: =SUM($E19:L19) -> 0 | ... P26: =SUM($E19:P19) -> 0
D27: ='KPI 1'!D27 -> ACTUAL2025/26 | E27: =SUM($E20:E20) -> 178060 | F27: =SUM($E20:F20) -> 329045 | G27: =SUM($E20:G20) -> 501465 | H27: =SUM($E20:H20) -> 510465 | I27: =SUM($E20:I20) -> 513465 | J27: =SUM($E20:J20) -> 514965 | K27: =SUM($E20:K20) -> 528465 | L27: =SUM($E20:L20) -> 624465 | ... P27: =SUM($E20:P20) -> 700965
D28: ='KPI 1'!D28 -> ACTUAL2024/25 | E28: =SUM($E21:E21) -> 0 | F28: =SUM($E21:F21) -> 0 | G28: =SUM($E21:G21) -> 0 | H28: =SUM($E21:H21) -> 0 | I28: =SUM($E21:I21) -> 0 | J28: =SUM($E21:J21) -> 0 | K28: =SUM($E21:K21) -> 0 | L28: =SUM($E21:L21) -> 0 | ... P28: =SUM($E21:P21) -> 0
D29: ='KPI 1'!D29 -> DIFFERENCE | E29: =SUM($E22:E22) -> 178060 | F29: =SUM($E22:F22) -> 329045 | G29: =SUM($E22:G22) -> 501465 | H29: =SUM($E22:H22) -> 510465 | I29: =SUM($E22:I22) -> 513465 | J29: =SUM($E22:J22) -> 514965 | K29: =SUM($E22:K22) -> 528465 | L29: =SUM($E22:L22) -> 624465 | ... P29: =SUM($E22:P22) -> 700965
D30: ='KPI 1'!D30 -> %REALISATION | E30: =E28/E26 -> #DIV/0! | F30: =F27/F26 -> #DIV/0! | G30: =G27/G26 -> #DIV/0! | H30: =H27/H26 -> #DIV/0! | I30: =I27/I26 -> #DIV/0! | J30: =J27/J26 -> #DIV/0! | K30: =K27/K26 -> #DIV/0! | L30: =L27/L26 -> #DIV/0! | M30: =M27/M26 -> #DIV/0! | ... P30: =P27/P26 -> #DIV/0!

Sheet KPI 4d
A1: KPI | B1: 6d | C1: Penalties sewer (ICS) | G1: Actual month: | I1: =INDEX($E$18:$P$18,Actual_month) -> 46082 | L1: Dashboard
A2: Unit | C2: Ksh.
C3: l | J3: Comments
C4: l | R4: actual | S4: =INDEX(E27:P27,Actual_month) -> 83000
C5: l | R5: target | S5: =INDEX(E26:P26,Actual_month) -> 1890000
R6: 0.9 | S6: =+S5*R6 -> 1701000
J9: Actions
C18: MONTHLY | E18: ='KPI 1'!E18 -> 45839 | F18: ='KPI 1'!F18 -> 45870 | G18: ='KPI 1'!G18 -> 45901 | H18: ='KPI 1'!H18 -> 45931 | I18: ='KPI 1'!I18 -> 45962 | J18: ='KPI 1'!J18 -> 45992 | K18: ='KPI 1'!K18 -> 46023 | L18: ='KPI 1'!L18 -> 46054 | ... P18: ='KPI 1'!P18 -> 46174 | Q18: Total
D19: ='KPI 1'!D19 -> budget2025/26 | E19: =BUDGET2526!D20 -> 210000 | F19: =BUDGET2526!E20 -> 210000 | G19: =BUDGET2526!F20 -> 210000 | H19: =BUDGET2526!G20 -> 210000 | I19: =BUDGET2526!H20 -> 210000 | J19: =BUDGET2526!I20 -> 210000 | K19: =BUDGET2526!J20 -> 210000 | L19: =BUDGET2526!K20 -> 210000 | ... P19: =BUDGET2526!O20 -> 210000 | Q19: =SUM(E19:P19) -> 2520000
D20: ='KPI 1'!D20 -> ACTUAL2025/26 | E20: =ACTUAL2122!D20 -> 48000 | F20: =ACTUAL2122!E20 -> 0 | G20: =ACTUAL2122!F20 -> 0 | H20: =ACTUAL2122!G20 -> 0 | I20: =ACTUAL2122!H20 -> 0 | J20: =ACTUAL2122!I20 -> 0 | K20: =ACTUAL2122!J20 -> 0 | L20: =ACTUAL2122!K20 -> 0 | ... P20: =ACTUAL2122!O20 -> 0 | Q20: =SUM(E20:P20) -> 83000
D21: ='KPI 1'!D21 -> ACTUAL2024/25 | E21: =ACTUAL2021!D19 -> 0 | F21: =ACTUAL2021!E19 -> 0 | G21: =ACTUAL2021!F19 -> 0 | H21: =ACTUAL2021!G19 -> 0 | I21: =ACTUAL2021!H19 -> 0 | J21: =ACTUAL2021!I19 -> 0 | K21: =ACTUAL2021!J19 -> 0 | L21: =ACTUAL2021!K19 -> 0 | ... P21: =ACTUAL2021!O19 -> 0 | Q21: =SUM(E21:P21) -> 0
D22: ='KPI 1'!D22 -> DIFFERENCE | E22: =IF(E20=0,0,E20-E19) -> -162000 | F22: =IF(F20=0,0,F20-F19) -> 0 | G22: =IF(G20=0,0,G20-G19) -> 0 | H22: =IF(H20=0,0,H20-H19) -> 0 | I22: =IF(I20=0,0,I20-I19) -> 0 | J22: =IF(J20=0,0,J20-J19) -> 0 | K22: =IF(K20=0,0,K20-K19) -> 0 | L22: =IF(L20=0,0,L20-L19) -> 0 | ... P22: =IF(P20=0,0,P20-P19) -> 0 | Q22: =SUM(E22:P22) -> -337000
D23: ='KPI 1'!D23 -> %REALISATION | E23: =E21/E19 -> 0 | F23: =F20/F19 -> 0 | G23: =G20/G19 -> 0 | H23: =H20/H19 -> 0 | I23: =I20/I19 -> 0 | J23: =J20/J19 -> 0 | K23: =K20/K19 -> 0 | L23: =L20/L19 -> 0 | M23: =M20/M19 -> 0.16666667 | ... P23: =P20/P19 -> 0
E24: =#REF! -> #REF! | F24: =#REF! -> #REF! | G24: =#REF! -> #REF! | H24: =#REF! -> #REF! | I24: =#REF! -> #REF! | J24: =#REF! -> #REF! | K24: =#REF! -> #REF! | L24: =#REF! -> #REF! | ... P24: =#REF! -> #REF!
C25: CUMULATIVE | D25: ='KPI 1'!D25 -> 0 | E25: ='KPI 1'!E25 -> 45839 | F25: ='KPI 1'!F25 -> 45870 | G25: ='KPI 1'!G25 -> 45901 | H25: ='KPI 1'!H25 -> 45931 | I25: ='KPI 1'!I25 -> 45962 | J25: ='KPI 1'!J25 -> 45992 | K25: ='KPI 1'!K25 -> 46023 | ... P25: ='KPI 1'!P25 -> 46174
D26: ='KPI 1'!D26 -> budget2025/26 | E26: =SUM($E19:E19) -> 210000 | F26: =SUM($E19:F19) -> 420000 | G26: =SUM($E19:G19) -> 630000 | H26: =SUM($E19:H19) -> 840000 | I26: =SUM($E19:I19) -> 1050000 | J26: =SUM($E19:J19) -> 1260000 | K26: =SUM($E19:K19) -> 1470000 | L26: =SUM($E19:L19) -> 1680000 | ... P26: =SUM($E19:P19) -> 2520000
D27: ='KPI 1'!D27 -> ACTUAL2025/26 | E27: =SUM($E20:E20) -> 48000 | F27: =SUM($E20:F20) -> 48000 | G27: =SUM($E20:G20) -> 48000 | H27: =SUM($E20:H20) -> 48000 | I27: =SUM($E20:I20) -> 48000 | J27: =SUM($E20:J20) -> 48000 | K27: =SUM($E20:K20) -> 48000 | L27: =SUM($E20:L20) -> 48000 | ... P27: =SUM($E20:P20) -> 83000
D28: ='KPI 1'!D28 -> ACTUAL2024/25 | E28: =SUM($E21:E21) -> 0 | F28: =SUM($E21:F21) -> 0 | G28: =SUM($E21:G21) -> 0 | H28: =SUM($E21:H21) -> 0 | I28: =SUM($E21:I21) -> 0 | J28: =SUM($E21:J21) -> 0 | K28: =SUM($E21:K21) -> 0 | L28: =SUM($E21:L21) -> 0 | ... P28: =SUM($E21:P21) -> 0
D29: ='KPI 1'!D29 -> DIFFERENCE | E29: =SUM($E22:E22) -> -162000 | F29: =SUM($E22:F22) -> -162000 | G29: =SUM($E22:G22) -> -162000 | H29: =SUM($E22:H22) -> -162000 | I29: =SUM($E22:I22) -> -162000 | J29: =SUM($E22:J22) -> -162000 | K29: =SUM($E22:K22) -> -162000 | L29: =SUM($E22:L22) -> -162000 | ... P29: =SUM($E22:P22) -> -337000
D30: ='KPI 1'!D30 -> %REALISATION | E30: =E28/E26 -> 0 | F30: =F27/F26 -> 0.11428571 | G30: =G27/G26 -> 0.076190476 | H30: =H27/H26 -> 0.057142857 | I30: =I27/I26 -> 0.045714286 | J30: =J27/J26 -> 0.038095238 | K30: =K27/K26 -> 0.032653061 | L30: =L27/L26 -> 0.028571429 | M30: =M27/M26 -> 0.043915344 | ... P30: =P27/P26 -> 0.032936508

Sheet KPI y
A1: KPI | B1: =Dashboard!A13 -> 8 | C1: =Dashboard!B13 -> Prepaid kiosk | G1: Actual month: | I1: =INDEX($E$18:$P$18,Actual_month) -> 46082 | L1: Dashboard
A2: Unit | C2: Ksh.
C3: l | J3: Comments
C4: l | R4: actual | S4: =INDEX(E27:P27,Actual_month) -> 708200
C5: l | R5: target | S5: =INDEX(E26:P26,Actual_month) -> 810000
R6: 0.9 | S6: =+S5*R6 -> 729000
J9: Actions
C18: MONTHLY | E18: ='KPI 1'!E18 -> 45839 | F18: ='KPI 1'!F18 -> 45870 | G18: ='KPI 1'!G18 -> 45901 | H18: ='KPI 1'!H18 -> 45931 | I18: ='KPI 1'!I18 -> 45962 | J18: ='KPI 1'!J18 -> 45992 | K18: ='KPI 1'!K18 -> 46023 | L18: ='KPI 1'!L18 -> 46054 | ... P18: ='KPI 1'!P18 -> 46174 | Q18: Total
D19: ='KPI 1'!D19 -> budget2025/26 | E19: =BUDGET2526!D14 -> 90000 | F19: =BUDGET2526!E14 -> 90000 | G19: =BUDGET2526!F14 -> 90000 | H19: =BUDGET2526!G14 -> 90000 | I19: =BUDGET2526!H14 -> 90000 | J19: =BUDGET2526!I14 -> 90000 | K19: =BUDGET2526!J14 -> 90000 | L19: =BUDGET2526!K14 -> 90000 | ... P19: =BUDGET2526!O14 -> 90000 | Q19: =SUM(E19:P19) -> 1080000
D20: ='KPI 1'!D20 -> ACTUAL2025/26 | E20: ='ACTUAL 2526'!E14 -> 78800 | F20: ='ACTUAL 2526'!F14 -> 82100 | G20: ='ACTUAL 2526'!G14 -> 74600 | H20: ='ACTUAL 2526'!H14 -> 84300 | I20: ='ACTUAL 2526'!I14 -> 67100 | J20: ='ACTUAL 2526'!J14 -> 62600 | K20: ='ACTUAL 2526'!K14 -> 116200 | L20: ='ACTUAL 2526'!L14 -> 81000 | ... P20: ='ACTUAL 2526'!P14 -> 0 | Q20: =SUM(E20:P20) -> 708200
D21: ='KPI 1'!D21 -> ACTUAL2024/25 | E21: ='Actual 202425'!E14 -> 77900 | F21: ='Actual 202425'!F14 -> 100000 | G21: ='Actual 202425'!G14 -> 107100 | H21: ='Actual 202425'!H14 -> 99700 | I21: ='Actual 202425'!I14 -> 100900 | J21: ='Actual 202425'!J14 -> 57800 | K21: ='Actual 202425'!K14 -> 124500 | L21: ='Actual 202425'!L14 -> 96800 | ... P21: ='Actual 202425'!P14 -> 124600 | Q21: =SUM(E21:P21) -> 1144400
D22: ='KPI 1'!D22 -> DIFFERENCE | E22: =IF(E20=0,0,E20-E19) -> -11200 | F22: =IF(F20=0,0,F20-F19) -> -7900 | G22: =IF(G20=0,0,G20-G19) -> -15400 | H22: =IF(H20=0,0,H20-H19) -> -5700 | I22: =IF(I20=0,0,I20-I19) -> -22900 | J22: =IF(J20=0,0,J20-J19) -> -27400 | K22: =IF(K20=0,0,K20-K19) -> 26200 | L22: =IF(L20=0,0,L20-L19) -> -9000 | ... P22: =IF(P20=0,0,P20-P19) -> 0 | Q22: =SUM(E22:P22) -> -101800
D23: ='KPI 1'!D23 -> %REALISATION | E23: =E20/E19 -> 0.87555556 | F23: =F20/F19 -> 0.91222222 | G23: =G20/G19 -> 0.82888889 | H23: =H20/H19 -> 0.93666667 | I23: =I20/I19 -> 0.74555556 | J23: =J20/J19 -> 0.69555556 | K23: =K20/K19 -> 1.2911111 | L23: =L20/L19 -> 0.9 | ... P23: =P20/P19 -> 0
C25: CUMULATIVE | D25: ='KPI 1'!D25 -> 0 | E25: ='KPI 1'!E25 -> 45839 | F25: ='KPI 1'!F25 -> 45870 | G25: ='KPI 1'!G25 -> 45901 | H25: ='KPI 1'!H25 -> 45931 | I25: ='KPI 1'!I25 -> 45962 | J25: ='KPI 1'!J25 -> 45992 | K25: ='KPI 1'!K25 -> 46023 | ... P25: ='KPI 1'!P25 -> 46174
D26: ='KPI 1'!D26 -> budget2025/26 | E26: =SUM($E19:E19) -> 90000 | F26: =SUM($E19:F19) -> 180000 | G26: =SUM($E19:G19) -> 270000 | H26: =SUM($E19:H19) -> 360000 | I26: =SUM($E19:I19) -> 450000 | J26: =SUM($E19:J19) -> 540000 | K26: =SUM($E19:K19) -> 630000 | L26: =SUM($E19:L19) -> 720000 | ... P26: =SUM($E19:P19) -> 1080000
D27: ='KPI 1'!D27 -> ACTUAL2025/26 | E27: =SUM($E20:E20) -> 78800 | F27: =SUM($E20:F20) -> 160900 | G27: =SUM($E20:G20) -> 235500 | H27: =SUM($E20:H20) -> 319800 | I27: =SUM($E20:I20) -> 386900 | J27: =SUM($E20:J20) -> 449500 | K27: =SUM($E20:K20) -> 565700 | L27: =SUM($E20:L20) -> 646700 | ... P27: =SUM($E20:P20) -> 708200
D28: ='KPI 1'!D28 -> ACTUAL2024/25 | E28: =SUM($E21:E21) -> 77900 | F28: =SUM($E21:F21) -> 177900 | G28: =SUM($E21:G21) -> 285000 | H28: =SUM($E21:H21) -> 384700 | I28: =SUM($E21:I21) -> 485600 | J28: =SUM($E21:J21) -> 543400 | K28: =SUM($E21:K21) -> 667900 | L28: =SUM($E21:L21) -> 764700 | ... P28: =SUM($E21:P21) -> 1144400
D29: ='KPI 1'!D29 -> DIFFERENCE | E29: =SUM($E22:E22) -> -11200 | F29: =SUM($E22:F22) -> -19100 | G29: =SUM($E22:G22) -> -34500 | H29: =SUM($E22:H22) -> -40200 | I29: =SUM($E22:I22) -> -63100 | J29: =SUM($E22:J22) -> -90500 | K29: =SUM($E22:K22) -> -64300 | L29: =SUM($E22:L22) -> -73300 | ... P29: =SUM($E22:P22) -> -101800
D30: ='KPI 1'!D30 -> %REALISATION | E30: =E27/E26 -> 0.87555556 | F30: =F27/F26 -> 0.89388889 | G30: =G27/G26 -> 0.87222222 | H30: =H27/H26 -> 0.88833333 | I30: =I27/I26 -> 0.85977778 | J30: =J27/J26 -> 0.83240741 | K30: =K27/K26 -> 0.89793651 | L30: =L27/L26 -> 0.89819444 | ... P30: =P27/P26 -> 0.65574074

Sheet KPI w
A1: KPI | B1: =Dashboard!A14 -> 9 | C1: =Dashboard!B14 -> misc income-printing fee,CA,meter replacement fee,meter testing | G1: Actual month: | I1: =INDEX($E$18:$P$18,Actual_month) -> 46082 | L1: Dashboard
A2: Unit | C2: Ksh.
C3: l | J3: Comments
C4: l | R4: actual | S4: =INDEX(E27:P27,Actual_month) -> 2918450
C5: l | R5: target | S5: =INDEX(E26:P26,Actual_month) -> 1008450
R6: 0.9 | S6: =+S5*R6 -> 907605
J9: Actions
C18: MONTHLY | E18: ='KPI 1'!E18 -> 45839 | F18: ='KPI 1'!F18 -> 45870 | G18: ='KPI 1'!G18 -> 45901 | H18: ='KPI 1'!H18 -> 45931 | I18: ='KPI 1'!I18 -> 45962 | J18: ='KPI 1'!J18 -> 45992 | K18: ='KPI 1'!K18 -> 46023 | L18: ='KPI 1'!L18 -> 46054 | ... P18: ='KPI 1'!P18 -> 46174 | Q18: Total
D19: ='KPI 1'!D19 -> budget2025/26 | E19: =BUDGET2526!D15 -> 112050 | F19: =BUDGET2526!E15 -> 112050 | G19: =BUDGET2526!F15 -> 112050 | H19: =BUDGET2526!G15 -> 112050 | I19: =BUDGET2526!H15 -> 112050 | J19: =BUDGET2526!I15 -> 112050 | K19: =BUDGET2526!J15 -> 112050 | L19: =BUDGET2526!K15 -> 112050 | ... P19: =BUDGET2526!O15 -> 112050 | Q19: =SUM(E19:P19) -> 1344600
D20: ='KPI 1'!D20 -> ACTUAL2025/26 | E20: ='ACTUAL 2526'!E15 -> 115100 | F20: ='ACTUAL 2526'!F15 -> 30900 | G20: ='ACTUAL 2526'!G15 -> 49000 | H20: ='ACTUAL 2526'!H15 -> 44200 | I20: ='ACTUAL 2526'!I15 -> 68950 | J20: ='ACTUAL 2526'!J15 -> 21500 | K20: ='ACTUAL 2526'!K15 -> 57700 | L20: ='ACTUAL 2526'!L15 -> 76800 | ... P20: ='ACTUAL 2526'!P15 -> 0 | Q20: =SUM(E20:P20) -> 2918450
D21: ='KPI 1'!D21 -> ACTUAL2024/25 | E21: ='Actual 202425'!E15 -> 75850 | F21: ='Actual 202425'!F15 -> 51400 | G21: ='Actual 202425'!G15 -> 133100 | H21: ='Actual 202425'!H15 -> 165000 | I21: ='Actual 202425'!I15 -> 46900 | J21: ='Actual 202425'!J15 -> 80800 | K21: ='Actual 202425'!K15 -> 147500 | L21: ='Actual 202425'!L15 -> 100950 | ... P21: ='Actual 202425'!P15 -> 90350 | Q21: =ACTUAL2021!P20 -> 0
D22: ='KPI 1'!D22 -> DIFFERENCE | E22: =IF(E20=0,0,E20-E19) -> 3050 | F22: =IF(F20=0,0,F20-F19) -> -81150 | G22: =IF(G20=0,0,G20-G19) -> -63050 | H22: =IF(H20=0,0,H20-H19) -> -67850 | I22: =IF(I20=0,0,I20-I19) -> -43100 | J22: =IF(J20=0,0,J20-J19) -> -90550 | K22: =IF(K20=0,0,K20-K19) -> -54350 | L22: =IF(L20=0,0,L20-L19) -> -35250 | ... P22: =IF(P20=0,0,P20-P19) -> 0 | Q22: =SUM(E22:P22) -> 1910000
D23: ='KPI 1'!D23 -> %REALISATION | E23: =E20/E19 -> 1.02722 | F23: =F20/F19 -> 0.27576975 | G23: =G20/G19 -> 0.43730477 | H23: =H20/H19 -> 0.39446676 | I23: =I20/I19 -> 0.61535029 | J23: =J20/J19 -> 0.19187863 | K23: =K20/K19 -> 0.51494868 | L23: =L20/L19 -> 0.6854083 | ... P23: =P20/P19 -> 0
C25: CUMULATIVE | D25: ='KPI 1'!D25 -> 0 | E25: ='KPI 1'!E25 -> 45839 | F25: ='KPI 1'!F25 -> 45870 | G25: ='KPI 1'!G25 -> 45901 | H25: ='KPI 1'!H25 -> 45931 | I25: ='KPI 1'!I25 -> 45962 | J25: ='KPI 1'!J25 -> 45992 | K25: ='KPI 1'!K25 -> 46023 | ... P25: ='KPI 1'!P25 -> 46174
D26: ='KPI 1'!D26 -> budget2025/26 | E26: =SUM($E19:E19) -> 112050 | F26: =SUM($E19:F19) -> 224100 | G26: =SUM($E19:G19) -> 336150 | H26: =SUM($E19:H19) -> 448200 | I26: =SUM($E19:I19) -> 560250 | J26: =SUM($E19:J19) -> 672300 | K26: =SUM($E19:K19) -> 784350 | L26: =SUM($E19:L19) -> 896400 | ... P26: =SUM($E19:P19) -> 1344600
D27: ='KPI 1'!D27 -> ACTUAL2025/26 | E27: =SUM($E20:E20) -> 115100 | F27: =SUM($E20:F20) -> 146000 | G27: =SUM($E20:G20) -> 195000 | H27: =SUM($E20:H20) -> 239200 | I27: =SUM($E20:I20) -> 308150 | J27: =SUM($E20:J20) -> 329650 | K27: =SUM($E20:K20) -> 387350 | L27: =SUM($E20:L20) -> 464150 | ... P27: =SUM($E20:P20) -> 2918450
D28: ='KPI 1'!D28 -> ACTUAL2024/25 | E28: =SUM($E21:E21) -> 75850 | F28: =SUM($E21:F21) -> 127250 | G28: =SUM($E21:G21) -> 260350 | H28: =SUM($E21:H21) -> 425350 | I28: =SUM($E21:I21) -> 472250 | J28: =SUM($E21:J21) -> 553050 | K28: =SUM($E21:K21) -> 700550 | L28: =SUM($E21:L21) -> 801500 | ... P28: =SUM($E21:P21) -> 1494850
D29: ='KPI 1'!D29 -> DIFFERENCE | E29: =SUM($E22:E22) -> 3050 | F29: =SUM($E22:F22) -> -78100 | G29: =SUM($E22:G22) -> -141150 | H29: =SUM($E22:H22) -> -209000 | I29: =SUM($E22:I22) -> -252100 | J29: =SUM($E22:J22) -> -342650 | K29: =SUM($E22:K22) -> -397000 | L29: =SUM($E22:L22) -> -432250 | ... P29: =SUM($E22:P22) -> 1910000
D30: ='KPI 1'!D30 -> %REALISATION | E30: =E27/E26 -> 1.02722 | F30: =F27/F26 -> 0.65149487 | G30: =G27/G26 -> 0.58009817 | H30: =H27/H26 -> 0.53369032 | I30: =I27/I26 -> 0.55002231 | J30: =J27/J26 -> 0.4903317 | K30: =K27/K26 -> 0.49384841 | L30: =L27/L26 -> 0.5177934 | ... P30: =P27/P26 -> 2.1704968

Sheet KPI z
A1: KPI | B1: =Dashboard!A15 -> 10 | C1: =Dashboard!B15 -> sewer unblocking fee | G1: Actual month: | I1: =INDEX($E$18:$P$18,Actual_month) -> 46082 | L1: Dashboard
A2: Unit | C2: Ksh.
C3: l | J3: Comments
C4: l | R4: actual | S4: =INDEX(E27:P27,Actual_month) -> 45000
C5: l | R5: target | S5: =INDEX(E26:P26,Actual_month) -> 22500
R6: 0.9 | S6: =+S5*R6 -> 20250
J9: Actions
C18: MONTHLY | E18: ='KPI 1'!E18 -> 45839 | F18: ='KPI 1'!F18 -> 45870 | G18: ='KPI 1'!G18 -> 45901 | H18: ='KPI 1'!H18 -> 45931 | I18: ='KPI 1'!I18 -> 45962 | J18: ='KPI 1'!J18 -> 45992 | K18: ='KPI 1'!K18 -> 46023 | L18: ='KPI 1'!L18 -> 46054 | ... P18: ='KPI 1'!P18 -> 46174 | Q18: Total
D19: ='KPI 1'!D19 -> budget2025/26 | E19: =BUDGET2526!D16 -> 2500 | F19: =BUDGET2526!E16 -> 2500 | G19: =BUDGET2526!F16 -> 2500 | H19: =BUDGET2526!G16 -> 2500 | I19: =BUDGET2526!H16 -> 2500 | J19: =BUDGET2526!I16 -> 2500 | K19: =BUDGET2526!J16 -> 2500 | L19: =BUDGET2526!K16 -> 2500 | ... P19: =BUDGET2526!O16 -> 2500 | Q19: =SUM(E19:P19) -> 30000
D20: ='KPI 1'!D20 -> ACTUAL2025/26 | E20: ='ACTUAL 2526'!E16 -> 2500 | F20: ='ACTUAL 2526'!F16 -> 5000 | G20: ='ACTUAL 2526'!G16 -> 5000 | H20: ='ACTUAL 2526'!H16 -> 0 | I20: ='ACTUAL 2526'!I16 -> 0 | J20: ='ACTUAL 2526'!J16 -> 0 | K20: ='ACTUAL 2526'!K16 -> 32500 | L20: ='ACTUAL 2526'!L16 -> 0 | ... P20: ='ACTUAL 2526'!P16 -> 0 | Q20: =SUM(E20:P20) -> 45000
D21: ='KPI 1'!D21 -> ACTUAL2024/25 | E21: ='Actual 202425'!E16 -> 0 | F21: ='Actual 202425'!F16 -> 0 | G21: ='Actual 202425'!G16 -> 0 | H21: ='Actual 202425'!H16 -> 0 | I21: ='Actual 202425'!I16 -> 0 | J21: ='Actual 202425'!J16 -> 2500 | K21: ='Actual 202425'!K16 -> 0 | L21: ='Actual 202425'!L16 -> 0 | ... P21: ='Actual 202425'!P16 -> 0 | Q21: =SUM(E21:P21) -> 5000
D22: ='KPI 1'!D22 -> DIFFERENCE | E22: =IF(E20=0,0,E20-E19) -> 0 | F22: =IF(F20=0,0,F20-F19) -> 2500 | G22: =IF(G20=0,0,G20-G19) -> 2500 | H22: =IF(H20=0,0,H20-H19) -> 0 | I22: =IF(I20=0,0,I20-I19) -> 0 | J22: =IF(J20=0,0,J20-J19) -> 0 | K22: =IF(K20=0,0,K20-K19) -> 30000 | L22: =IF(L20=0,0,L20-L19) -> 0 | ... P22: =IF(P20=0,0,P20-P19) -> 0 | Q22: =SUM(E22:P22) -> 35000
D23: ='KPI 1'!D23 -> %REALISATION | E23: =E20/E19 -> 1 | F23: =F20/F19 -> 2 | G23: =G20/G19 -> 2 | H23: =H20/H19 -> 0 | I23: =I20/I19 -> 0 | J23: =J20/J19 -> 0 | K23: =K20/K19 -> 13 | L23: =L20/L19 -> 0 | ... P23: =P20/P19 -> 0
C25: CUMULATIVE | D25: ='KPI 1'!D25 -> 0 | E25: ='KPI 1'!E25 -> 45839 | F25: ='KPI 1'!F25 -> 45870 | G25: ='KPI 1'!G25 -> 45901 | H25: ='KPI 1'!H25 -> 45931 | I25: ='KPI 1'!I25 -> 45962 | J25: ='KPI 1'!J25 -> 45992 | K25: ='KPI 1'!K25 -> 46023 | ... P25: ='KPI 1'!P25 -> 46174
D26: ='KPI 1'!D26 -> budget2025/26 | E26: =SUM($E19:E19) -> 2500 | F26: =SUM($E19:F19) -> 5000 | G26: =SUM($E19:G19) -> 7500 | H26: =SUM($E19:H19) -> 10000 | I26: =SUM($E19:I19) -> 12500 | J26: =SUM($E19:J19) -> 15000 | K26: =SUM($E19:K19) -> 17500 | L26: =SUM($E19:L19) -> 20000 | ... P26: =SUM($E19:P19) -> 30000
D27: ='KPI 1'!D27 -> ACTUAL2025/26 | E27: =SUM($E20:E20) -> 2500 | F27: =SUM($E20:F20) -> 7500 | G27: =SUM($E20:G20) -> 12500 | H27: =SUM($E20:H20) -> 12500 | I27: =SUM($E20:I20) -> 12500 | J27: =SUM($E20:J20) -> 12500 | K27: =SUM($E20:K20) -> 45000 | L27: =SUM($E20:L20) -> 45000 | ... P27: =SUM($E20:P20) -> 45000
D28: ='KPI 1'!D28 -> ACTUAL2024/25 | E28: =SUM($E21:E21) -> 0 | F28: =SUM($E21:F21) -> 0 | G28: =SUM($E21:G21) -> 0 | H28: =SUM($E21:H21) -> 0 | I28: =SUM($E21:I21) -> 0 | J28: =SUM($E21:J21) -> 2500 | K28: =SUM($E21:K21) -> 2500 | L28: =SUM($E21:L21) -> 2500 | ... P28: =SUM($E21:P21) -> 5000
D29: ='KPI 1'!D29 -> DIFFERENCE | E29: =SUM($E22:E22) -> 0 | F29: =SUM($E22:F22) -> 2500 | G29: =SUM($E22:G22) -> 5000 | H29: =SUM($E22:H22) -> 5000 | I29: =SUM($E22:I22) -> 5000 | J29: =SUM($E22:J22) -> 5000 | K29: =SUM($E22:K22) -> 35000 | L29: =SUM($E22:L22) -> 35000 | ... P29: =SUM($E22:P22) -> 35000
D30: ='KPI 1'!D30 -> %REALISATION | E30: =E27/E26 -> 1 | F30: =F27/F26 -> 1.5 | G30: =G27/G26 -> 1.6666667 | H30: =H27/H26 -> 1.25 | I30: =I27/I26 -> 1 | J30: =J27/J26 -> 0.83333333 | K30: =K27/K26 -> 2.5714286 | L30: =L27/L26 -> 2.25 | ... P30: =P27/P26 -> 1.5

Sheet KPI j
A1: KPI | B1: =Dashboard!A16 -> 11 | C1: =Dashboard!B16 -> penalties (water+sewer) | G1: Actual month: | I1: =INDEX($E$18:$P$18,Actual_month) -> 46082 | L1: Dashboard
A2: Unit | C2: Ksh.
C3: l | J3: Comments
C4: l | R4: actual | S4: =INDEX(E27:P27,Actual_month) -> 865000
C5: l | R5: target | S5: =INDEX(E26:P26,Actual_month) -> 1710009
R6: 0.9 | S6: =+S5*R6 -> 1539008.1
J9: Actions
