Workbook
Name Actual_month: General!$B$3

Sheet Dashboard Production Quality
A1: TECHNICAL DASHBOARD PRODUCTION AND WATER QUALITY
B2: =INDEX('KPI 1a'!E$18:P$18,Actual_month) -> 46054
D3: Monthly | J3: Cumulative | R3: 0.9
C4: Unit | G4: Target | H4: Actual | I4: % real. | M4: Target | N4: Actual | O4: % real.
A5: DASHBOARD - VOLUMES PRODUCED - NON-REVENUE WATER
A6: 1 | B6: DTI PRODUCTION SITE
A7: 1a | B7: Water Volume Abstracted | C7: M3 | D7: l | E7: l | F7: l | G7: =INDEX('KPI 1a'!$E$19:$P$19,Actual_month) -> 43020 | H7: =INDEX('KPI 1a'!E$20:P$20,Actual_month) -> 34037 | I7: =IFERROR(H7/G7,"") -> 0.79119014 | J7: l | K7: l | L7: l | M7: =INDEX('KPI 1a'!$E$26:$P$26,Actual_month) -> 330640 | N7: =INDEX('KPI 1a'!$E$27:$P$27,Actual_month) -> 345878 | O7: =IFERROR(N7/M7,"") -> 1.0460864 | P7: details | Q7: =G7*$R$3 -> 38718 | R7: =M7*$R$3 -> 297576 | S7: H | T7: v
A8: 1b | B8: Water Volume Supplied | C8: M3 | D8: l | E8: l | F8: l | G8: =INDEX('KPI 1b'!$E$19:$P$19,Actual_month) -> 42159.6 | H8: =INDEX('KPI 1b'!E$20:P$20,Actual_month) -> 34037 | I8: =IFERROR(H8/G8,"") -> 0.80733688 | J8: l | K8: l | L8: l | M8: =INDEX('KPI 1b'!$E$26:$P$26,Actual_month) -> 324027.2 | N8: =INDEX('KPI 1b'!$E$27:$P$27,Actual_month) -> 345878 | O8: =IFERROR(N8/M8,"") -> 1.0674351 | P8: details | Q8: =G8*$R$3 -> 37943.64 | R8: =M8*$R$3 -> 291624.48 | S8: H | T8: v
A9: 1c | B9: Power Grid | C9: KWH | D9: l | E9: l | F9: l | G9: =INDEX('KPI 1c'!$E$19:$P$19,Actual_month) -> 50298.261 | H9: =INDEX('KPI 1c'!$E$20:$P$20,Actual_month) -> 48514.887 | I9: =IFERROR(H9/G9,"") -> 0.96454403 | J9: l | K9: l | L9: l | M9: =INDEX('KPI 1c'!$E$26:$P$26,Actual_month) -> 402386.09 | N9: =INDEX('KPI 1c'!E$27:P$27,Actual_month) -> 431553.89 | O9: =IFERROR(N9/M9,"") -> 1.0724871 | P9: details | Q9: =G9/$R$3 -> 55886.957 | R9: =M9/$R$3 -> 447095.65 | S9: L | T9: v
A10: 1d | B10: Power Solar | C10: KWH | D10: l | E10: l | F10: l | G10: =INDEX('KPI 1d'!$E$19:$P$19,Actual_month) -> 15534.791 | H10: =INDEX('KPI 1d'!E$20:P$20,Actual_month) -> 9920 | I10: =IFERROR(H10/G10,"") -> 0.63856667 | J10: l | K10: l | L10: l | M10: =INDEX('KPI 1d'!$E$26:$P$26,Actual_month) -> 124278.33 | N10: =INDEX('KPI 1d'!$E$27:$P$27,Actual_month) -> 96199.16 | O10: =IFERROR(N10/M10,"") -> 0.77406222 | P10: details | Q10: =G10*$R$3 -> 13981.312 | R10: =M10*$R$3 -> 111850.5 | S10: H | T10: v
A11: 1e | B11: Total Power Consumption | C11: KWH | D11: l | E11: l | F11: l | G11: =INDEX('KPI 1e'!$E$19:$P$19,Actual_month) -> 65833.052 | H11: =INDEX('KPI 1e'!E$20:P$20,Actual_month) -> 58434.887 | I11: =IFERROR(H11/G11,"") -> 0.88762233 | J11: l | K11: l | L11: l | M11: =INDEX('KPI 1e'!$E$26:$P$26,Actual_month) -> 526664.42 | N11: =INDEX('KPI 1e'!$E$27:$P$27,Actual_month) -> 527753.05 | O11: =IFERROR(N11/M11,"") -> 1.002067 | P11: details | Q11: =G11*$R$3 -> 59249.747 | R11: =M11*$R$3 -> 473997.98 | S11: H | T11: v
A12: 1f | B12: % Solar | C12: % | D12: l | E12: l | F12: l | G12: =INDEX('KPI 1f'!$E$19:$P$19,Actual_month) -> 0.23597252 | H12: =INDEX('KPI 1f'!E$20:P$20,Actual_month) -> 0.1697616 | I12: =IFERROR(H12/G12,"") -> 0.71941259 | J12: l | K12: l | L12: l | M12: =INDEX('KPI 1f'!$E$26:$P$26,Actual_month) -> 0.23597252 | N12: =INDEX('KPI 1f'!$E$27:$P$27,Actual_month) -> 0.18247408 | O12: =IFERROR(N12/M12,"") -> 0.7732853 | P12: details | Q12: =G12*$R$3 -> 0.21237527 | R12: =M12*$R$3 -> 0.21237527 | S12: H | T12: v
A13: 1g | B13: Power Efficiency | C13: KWH/M3 | D13: l | E13: l | F13: l | G13: =INDEX('KPI 1g'!$E$19:$P$19,Actual_month) -> 1.5302895 | H13: =IFERROR(INDEX('KPI 1g'!E$20:P$20,Actual_month),) -> 1.7168049 | I13: =IFERROR(G13/H13,"") -> 0.89135899 | J13: l | K13: l | L13: l | M13: =INDEX('KPI 1g'!$E$26:$P$26,Actual_month) -> 1.5939116 | N13: =IFERROR(INDEX('KPI 1g'!E$27:P$27,Actual_month),) -> 1.5501161 | O13: =IFERROR(M13/N13,"") -> 1.028253 | P13: details | Q13: =G13/$R$3 -> 1.7003216 | R13: =M13/$R$3 -> 1.7710128 | S13: L | T13: v
A14: 1h | B14: Production Loss | C14: M3 | D14: l | E14: l | F14: l | G14: =INDEX('KPI 1h'!E$19:P$19,Actual_month) -> 860.4 | H14: =INDEX('KPI 1h'!E$20:P$20,Actual_month) -> 1053 | I14: =IFERROR(G14/H14,"") -> 0.81709402 | J14: l | K14: l | L14: l | M14: =INDEX('KPI 1h'!$E$26:$P$26,Actual_month) -> 6612.8 | N14: =INDEX('KPI 1h'!E$27:P$27,Actual_month) -> 17779 | O14: =IFERROR(M14/N14,"") -> 0.37194443 | P14: details | Q14: =G14/$R$3 -> 956 | R14: =M14/$R$3 -> 7347.5556 | S14: L | T14: v
A16: 2 | B16: WATERWORKS PRODUCTION SITE
A17: 2a | B17: Water Volume Abstracted | C17: M3 | D17: l | E17: l | F17: l | G17: =INDEX('KPI 2a'!E$19:P$19,Actual_month) -> 19550 | H17: =INDEX('KPI 2a'!E$20:Q$20,Actual_month) -> 28759 | I17: =IFERROR(H17/G17,"") -> 1.4710486 | J17: l | K17: l | L17: l | M17: =INDEX('KPI 2a'!$E$26:$P$26,Actual_month) -> 155000 | N17: =INDEX('KPI 2a'!$E$27:$P$27,Actual_month) -> 176227 | O17: =IFERROR(N17/M17,"") -> 1.1369484 | P17: details | Q17: =G17*$R$3 -> 17595 | R17: =M17*$R$3 -> 139500 | S17: H | T17: v
A18: 2b | B18: Water Volume Supplied | C18: M3 | D18: l | E18: l | F18: l | G18: =INDEX('KPI 2b'!E$19:P$19,Actual_month) -> 19159 | H18: =INDEX('KPI 2b'!E$20:Q$20,Actual_month) -> 28759 | I18: =IFERROR(H18/G18,"") -> 1.50107 | J18: l | K18: l | L18: l | M18: =INDEX('KPI 2b'!$E$26:$P$26,Actual_month) -> 151900 | N18: =INDEX('KPI 2b'!$E$27:$P$27,Actual_month) -> 176227 | O18: =IFERROR(N18/M18,"") -> 1.1601514 | P18: details | Q18: =G18*$R$3 -> 17243.1 | R18: =M18*$R$3 -> 136710 | S18: H | T18: v
A19: 2c | B19: Power Grid | C19: KWH | D19: l | E19: l | F19: l | G19: =INDEX('KPI 2c'!E$19:P$19,Actual_month) -> 32877.705 | H19: =INDEX('KPI 2c'!E$20:P$20,Actual_month) -> 34188 | I19: =IFERROR(H19/G19,"") -> 1.0398536 | J19: l | K19: l | L19: l | M19: =INDEX('KPI 2c'!$E$26:$P$26,Actual_month) -> 263021.64 | N19: =INDEX('KPI 2c'!$E$27:$P$27,Actual_month) -> 283549 | O19: =IFERROR(N19/M19,"") -> 1.0780444 | P19: details | Q19: =G19/$R$3 -> 36530.783 | R19: =M19/$R$3 -> 292246.27 | S19: L | T19: v
A20: 2d | B20: Power solar | C20: KWH | D20: l | E20: l | F20: l | G20: =INDEX('KPI 2d'!E$19:O$19,Actual_month) -> 10118.458 | H20: =INDEX('KPI 2d'!E$20:P$20,Actual_month) -> 6981 | I20: =IFERROR(H20/G20,"") -> 0.68992723 | J20: l | K20: l | L20: l | M20: =INDEX('KPI 2d'!$E$26:$P$26,Actual_month) -> 80947.667 | N20: =INDEX('KPI 2d'!$E$27:$P$27,Actual_month) -> 95906.92 | O20: =IFERROR(N20/M20,"") -> 1.1848015 | P20: details | Q20: =G20*$R$3 -> 9106.6125 | R20: =M20*$R$3 -> 72852.9 | S20: H | T20: v
A21: 2e | B21: Total Power Consumption | C21: KWH | E21: l | F21: l | G21: =INDEX('KPI 2e'!E$19:P$19,Actual_month) -> 42996.163 | H21: =INDEX('KPI 2e'!E$20:P$20,Actual_month) -> 41169 | I21: =IFERROR(H21/G21,"") -> 0.95750404 | L21: l | M21: =INDEX('KPI 2e'!$E$26:$P$26,Actual_month) -> 343969.31 | N21: =INDEX('KPI 2e'!$E$27:$P$27,Actual_month) -> 379455.92 | O21: =IFERROR(N21/M21,"") -> 1.103168 | P21: details | Q21: =G21*$R$3 -> 38696.547 | R21: =M21*$R$3 -> 309572.38 | S21: H | T21: v
A22: 2f | B22: % Solar | C22: % | D22: l | E22: l | F22: l | G22: =INDEX('KPI 2f'!E$19:P$19,Actual_month) -> 0.23533398 | H22: =INDEX('KPI 2f'!E$20:P$20,Actual_month) -> 0.16956934 | I22: =IFERROR(H22/G22,"") -> 0.7205476 | J22: l | K22: l | L22: l | M22: =INDEX('KPI 2f'!$E$26:$P$26,Actual_month) -> 0.23533398 | N22: =INDEX('KPI 2f'!$E$27:$P$27,Actual_month) -> 0.24979114 | O22: =IFERROR(N22/M22,"") -> 1.0614325 | P22: details | Q22: =G22*$R$3 -> 0.21180058 | R22: =M22*$R$3 -> 0.21180058 | S22: H | T22: v
A23: 2g | B23: Power Efficiency | C23: KWH/M3 | D23: l | E23: l | F23: l | G23: =INDEX('KPI 2g'!E$19:P$19,Actual_month) -> 2.1992922 | H23: =IFERROR(INDEX('KPI 2g'!E$20:P$20,Actual_month),) -> 1.4315171 | I23: =IFERROR(G23/H23,"") -> 1.5363367 | J23: l | K23: l | L23: l | M23: =INDEX('KPI 2g'!$E$26:$P$26,Actual_month) -> 2.2192344 | N23: =IFERROR(INDEX('KPI 2g'!$E$27:$P$27,Actual_month),) -> 2.2106639 | O23: =IFERROR(M23/N23,"") -> 1.0038769 | P23: details | Q23: =G23/$R$3 -> 2.443658 | R23: =M23/$R$3 -> 2.465816 | S23: L | T23: v
A24: 2h | B24: Production Loss | C24: M3 | D24: l | E24: l | F24: l | G24: =INDEX('KPI 2h'!E$19:P$19,Actual_month) -> 391 | H24: =INDEX('KPI 2h'!E$20:P$20,Actual_month) -> 1962 | I24: =IFERROR(G24/H24,"") -> 0.19928644 | J24: l | K24: l | L24: l | M24: =INDEX('KPI 2h'!$E$26:$P$26,Actual_month) -> 3100 | N24: =INDEX('KPI 2h'!$E$27:$P$27,Actual_month) -> 12032.9 | O24: =IFERROR(M24/N24,"") -> 0.25762701 | P24: details | Q24: =G24/$R$3 -> 434.44444 | R24: =M24/$R$3 -> 3444.4444 | S24: L | T24: v
A26: 3 | B26: A.I.C PRODUCTION SITE
A27: 3a | B27: Water Volume Abstracted | C27: M3 | D27: l | E27: l | F27: l | G27: =INDEX('KPI 3a'!E$19:P$19,Actual_month) -> 9220 | H27: =INDEX('KPI 3a'!E$20:P$20,Actual_month) -> 16841 | I27: =IFERROR(H27/G27,"") -> 1.8265727 | J27: l | K27: l | L27: l | M27: =INDEX('KPI 3a'!$E$26:$P$26,Actual_month) -> 68340 | N27: =INDEX('KPI 3a'!$E$27:$P$27,Actual_month) -> 92061 | O27: =IFERROR(N27/M27,"") -> 1.3471027 | P27: details | Q27: =G27*$R$3 -> 8298 | R27: =M27*$R$3 -> 61506 | S27: H | T27: v
A28: 3b | B28: Water Volume Supplied | C28: M3 | G28: =INDEX('KPI 3b'!E$19:P$19,Actual_month) -> 9035.6 | H28: =INDEX('KPI 3b'!E$20:P$20,Actual_month) -> 16763 | I28: =IFERROR(H28/G28,"") -> 1.8552171 | J28: l | K28: l | L28: l | M28: =INDEX('KPI 3b'!$E$26:$P$26,Actual_month) -> 66973.2 | N28: =INDEX('KPI 3b'!$E$27:$P$27,Actual_month) -> 91311 | O28: =IFERROR(N28/M28,"") -> 1.3633961 | P28: details | Q28: =G28*$R$3 -> 8132.04 | R28: =M28*$R$3 -> 60275.88 | S28: H | T28: v
A29: 3c | B29: Power Consumption | C29: KWH | D29: l | E29: l | F29: l | G29: =INDEX('KPI 3c'!E$19:P$19,Actual_month) -> 4699.8333 | H29: =INDEX('KPI 3c'!E$20:P$20,Actual_month) -> 10709.556 | I29: =IFERROR(G29/H29,"") -> 0.43884485 | J29: l | K29: l | L29: l | M29: =INDEX('KPI 3c'!$E$26:$P$26,Actual_month) -> 37598.667 | N29: =INDEX('KPI 3c'!$E$27:$P$27,Actual_month) -> 50629.556 | O29: =IFERROR(M29/N29,"") -> 0.74262289 | P29: details | Q29: =G29/$R$3 -> 5222.037 | R29: =M29/$R$3 -> 41776.296 | S29: L | T29: v
A30: 3d | B30: Power Efficiency | C30: KWH/M3 | D30: l | E30: l | F30: l | G30: =INDEX('KPI 3d'!E$19:P$19,Actual_month) -> 0.50974331 | H30: =INDEX('KPI 3d'!E$20:P$20,Actual_month) -> 0.63592159 | I30: =IFERROR(G30/H30,"") -> 0.80158202 | J30: l | K30: l | L30: l | M30: =INDEX('KPI 3d'!$E$26:$P$26,Actual_month) -> 0.55153731 | N30: =INDEX('KPI 3d'!$E$27:$P$27,Actual_month) -> 0.53925494 | O30: =IFERROR(M30/N30,"") -> 1.0227766 | P30: details | Q30: =G30/$R$3 -> 0.56638146 | R30: =M30/$R$3 -> 0.61281924 | S30: L | T30: v
A31: 3e | B31: Production Loss | C31: M3 | D31: l | E31: l | F31: l | G31: =INDEX('KPI 3e'!E$19:P$19,Actual_month) -> 184.4 | H31: =INDEX('KPI 3e'!E$20:P$20,Actual_month) -> 78 | I31: =IFERROR(G31/H31,"") -> 2.3641026 | J31: l | K31: l | L31: l | M31: =INDEX('KPI 3e'!$E$26:$P$26,Actual_month) -> 1366.8 | N31: =INDEX('KPI 3e'!$E$27:$P$27,Actual_month) -> 750 | O31: =IFERROR(M31/N31,"") -> 1.8224 | P31: details | Q31: =G31/$R$3 -> 204.88889 | R31: =M31/$R$3 -> 1518.6667 | S31: L | T31: v
A33: 4 | B33: KARATI PRODUCTION SITE
A34: 4a | B34: Water Volume Abstracted | C34: M3 | D34: l | E34: l | F34: l | G34: =INDEX('KPI 4a'!E$19:P$19,Actual_month) -> 60680 | H34: =INDEX('KPI 4a'!E$20:P$20,Actual_month) -> 55641 | I34: =IFERROR(H34/G34,"") -> 0.91695781 | J34: l | K34: l | L34: l | M34: =INDEX('KPI 4a'!$E$26:$P$26,Actual_month) -> 483530 | N34: =INDEX('KPI 4a'!$E$27:$P$27,Actual_month) -> 438286.74 | O34: =IFERROR(N34/M34,"") -> 0.90643133 | P34: details | Q34: =G34*$R$3 -> 54612 | R34: =M34*$R$3 -> 435177 | S34: H | T34: v
A35: 4b | B35: Water Volume Supplied | C35: M3 | D35: l | E35: l | F35: l | G35: =INDEX('KPI 4b'!E$19:P$19,Actual_month) -> 53435.444 | H35: =INDEX('KPI 4b'!E$20:P$20,Actual_month) -> 52879 | I35: =IFERROR(H35/G35,"") -> 0.98958662 | J35: l | K35: l | L35: l | M35: =INDEX('KPI 4b'!$E$26:$P$26,Actual_month) -> 449891.85 | N35: =INDEX('KPI 4b'!$E$27:$P$27,Actual_month) -> 410352.7 | O35: =IFERROR(N35/M35,"") -> 0.91211411 | P35: details | Q35: =G35*$R$3 -> 48091.899 | R35: =M35*$R$3 -> 404902.66 | S35: H | T35: v
A36: 4c | B36: Power Grid | C36: KWH | D36: l | E36: l | F36: l | G36: =INDEX('KPI 4c'!E$19:P$19,Actual_month) -> 55514.06 | H36: =INDEX('KPI 4c'!E$20:P$20,Actual_month) -> 41487 | I36: =IFERROR(H36/G36,"") -> 0.74732419 | J36: l | K36: l | L36: l | M36: =INDEX('KPI 4c'!$E$26:$P$26,Actual_month) -> 444112.48 | N36: =INDEX('KPI 4c'!$E$27:$P$27,Actual_month) -> 323923 | O36: =IFERROR(N36/M36,"") -> 0.72937153 | P36: details | Q36: =G36/$R$3 -> 61682.289 | R36: =M36/$R$3 -> 493458.31 | S36: L | T36: v
A37: 4d | B37: Power Solar | C37: KWH | D37: l | E37: l | F37: l | G37: =INDEX('KPI 4d'!E$19:P$19,Actual_month) -> 10113.154 | H37: =INDEX('KPI 4d'!E$20:P$20,Actual_month) -> 36723 | I37: =IFERROR(H37/G37,"") -> 3.6312115 | J37: l | K37: l | L37: l | M37: =INDEX('KPI 4d'!$E$26:$P$26,Actual_month) -> 80905.229 | N37: =INDEX('KPI 4d'!$E$27:$P$27,Actual_month) -> 129122.95 | O37: =IFERROR(N37/M37,"") -> 1.5959778 | P37: details | Q37: =G37*$R$3 -> 9101.8383 | R37: =M37*$R$3 -> 72814.706 | S37: H | T37: v
A38: 4e | B38: Total Power Consumption | C38: KWH | D38: l | E38: l | F38: l | G38: =INDEX('KPI 4e'!E$19:P$19,Actual_month) -> 65627.214 | H38: =INDEX('KPI 4e'!E$20:P$20,Actual_month) -> 78210 | I38: =IFERROR(H38/G38,"") -> 1.1917312 | J38: l | K38: l | L38: l | M38: =INDEX('KPI 4e'!$E$26:$P$26,Actual_month) -> 525017.71 | N38: =INDEX('KPI 4e'!$E$27:$P$27,Actual_month) -> 453045.95 | O38: =IFERROR(N38/M38,"") -> 0.86291556 | P38: details | Q38: =G38*$R$3 -> 59064.492 | R38: =M38*$R$3 -> 472515.94 | S38: H | T38: v
A39: 4f | B39: % Solar | C39: % | D39: l | E39: l | F39: l | G39: =INDEX('KPI 4f'!E$19:P$19,Actual_month) -> 0.1541 | H39: =INDEX('KPI 4f'!E$20:P$20,Actual_month) -> 0.46954354 | I39: =IFERROR(H39/G39,"") -> 3.0470054 | J39: l | K39: l | L39: l | M39: =INDEX('KPI 4f'!$E$26:$P$26,Actual_month) -> 0.1541 | N39: =INDEX('KPI 4f'!$E$27:$P$27,Actual_month) -> 0.27365874 | O39: =IFERROR(N39/M39,"") -> 1.7758517 | P39: details | Q39: =G39*$R$3 -> 0.13869 | R39: =M39*$R$3 -> 0.13869 | S39: H | T39: v
A40: 4g | B40: Power Efficiency | C40: KWH/M3 | D40: l | E40: l | F40: l | G40: =INDEX('KPI 4g'!E$19:P$19,Actual_month) -> 0.11938952 | H40: =INDEX('KPI 4g'!E$20:P$20,Actual_month) -> 1.4056182 | I40: =IFERROR(G40/H40,"") -> 0.084937379 | J40: l | K40: l | L40: l | M40: =INDEX('KPI 4g'!$E$26:$P$26,Actual_month) -> 0.06948763 | N40: =INDEX('KPI 4g'!$E$27:$P$27,Actual_month) -> 1.0281053 | O40: =IFERROR(M40/N40,"") -> 0.067588051 | P40: details | Q40: =G40/$R$3 -> 0.13265502 | R40: =M40/$R$3 -> 0.077208478 | S40: L | T40: v
A41: 4h | B41: Production Loss | C41: M3 | D41: l | E41: l | F41: l | G41: =INDEX('KPI 4h'!E$19:P$19,Actual_month) -> 7244.5562 | H41: =INDEX('KPI 4h'!E$20:P$20,Actual_month) -> 2762 | I41: =IFERROR(G41/H41,"") -> 2.6229385 | J41: l | K41: l | L41: l | M41: =INDEX('KPI 4h'!$E$26:$P$26,Actual_month) -> 33638.153 | N41: =INDEX('KPI 4h'!$E$27:$P$27,Actual_month) -> 27934.037 | O41: =IFERROR(M41/N41,"") -> 1.2041995 | P41: details | Q41: =G41/$R$3 -> 8049.5069 | R41: =M41/$R$3 -> 37375.726 | S41: L | T41: v
A43: 5 | B43: DCK PRODUCTION SITE
A44: 5a | B44: Water Volume Abstracted | C44: M3 | D44: l | E44: l | F44: l | G44: =INDEX('KPI 5a'!E$19:P$19,Actual_month) -> 9600 | H44: =INDEX('KPI 5a'!E$20:P$20,Actual_month) -> 8683 | I44: =IFERROR(H44/G44,"") -> 0.90447917 | J44: l | K44: l | L44: l | M44: =INDEX('KPI 5a'!$E$25:$P$25,Actual_month) -> 62500 | N44: =INDEX('KPI 5a'!$E$26:$P$26,Actual_month) -> 62998 | O44: =IFERROR(N44/M44,"") -> 1.007968 | P44: details | Q44: =G44*$R$3 -> 8640 | R44: =M44*$R$3 -> 56250 | S44: H | T44: v
A45: 5b | B45: Water Volume Supplied | C45: M3 | D45: l | E45: l | F45: l | G45: =INDEX('KPI 5b'!E$19:P$19,Actual_month) -> 9408 | H45: =INDEX('KPI 5b'!E$20:P$20,Actual_month) -> 8239 | I45: =IFERROR(H45/G45,"") -> 0.87574405 | J45: l | K45: l | L45: l | M45: =INDEX('KPI 5b'!$E$25:$P$25,Actual_month) -> 61250 | N45: =INDEX('KPI 5b'!$E$26:$P$26,Actual_month) -> 61108 | O45: =IFERROR(N45/M45,"") -> 0.99768163 | P45: details | Q45: =G45*$R$3 -> 8467.2 | R45: =M45*$R$3 -> 55125 | S45: H | T45: v
A46: 5c | B46: Power Grid | C46: KWH | D46: l | E46: l | F46: l | G46: =INDEX('KPI 5c'!E$19:P$19,Actual_month) -> 9153.0833 | H46: =INDEX('KPI 5c'!E$20:P$20,Actual_month) -> 10436 | I46: =IFERROR(G46/H46,"") -> 0.87706816 | J46: l | K46: l | L46: l | M46: =INDEX('KPI 5c'!$E$26:$P$26,Actual_month) -> 73224.667 | N46: =INDEX('KPI 5c'!$E$20:$P$20,Actual_month) -> 10436 | O46: =IFERROR(M46/N46,"") -> 7.0165453 | P46: details | Q46: =G46/$R$3 -> 10170.093 | R46: =M46/$R$3 -> 81360.741 | S46: L | T46: v
A47: 5d | B47: Power Solar | C47: KWH | D47: l | E47: l | F47: l | G47: =INDEX('KPI 5d'!E$19:P$19,Actual_month) -> 0 | H47: =INDEX('KPI 5d'!E$20:P$20,Actual_month) -> 52.71 | I47: =IFERROR(H47/G47,"") | J47: l | K47: l | L47: l | M47: =INDEX('KPI 5d'!$E$25:$P$25,Actual_month) -> 0 | N47: =INDEX('KPI 5d'!$E$26:$P$26,Actual_month) -> 515.71 | O47: =IFERROR(M47/N47,"") -> 0 | P47: details | Q47: =G47*$R$3 -> 0 | R47: =M47*$R$3 -> 0 | S47: H | T47: v
A48: 5e | B48: Total Power Consumption | C48: KWH | D48: l | E48: l | F48: l | G48: =INDEX('KPI 5e'!E$19:P$19,Actual_month) -> 9153.0833 | H48: =INDEX('KPI 5e'!E$20:P$20,Actual_month) -> 10488.71 | I48: =IFERROR(H48/G48,"") -> 1.145921 | J48: l | K48: l | L48: l | M48: =INDEX('KPI 5e'!$E$25:$P$25,Actual_month) -> 73224.667 | N48: =INDEX('KPI 5e'!$E$26:$P$26,Actual_month) -> 61742.01 | O48: =IFERROR(M48/N48,"") -> 1.185978 | P48: details | Q48: =G48*$R$3 -> 8237.775 | R48: =M48*$R$3 -> 65902.2 | S48: H | T48: v
A49: 5f | B49: % Solar | C49: % | D49: l | E49: l | F49: l | G49: =INDEX('KPI 5f'!E$19:P$19,Actual_month) -> 0 | H49: =INDEX('KPI 5f'!E$20:P$20,Actual_month) -> 0.0050254035 | I49: =IFERROR(H49/G49,"") | J49: l | K49: l | L49: l | M49: =INDEX('KPI 5f'!$E$25:$P$25,Actual_month) -> 0 | N49: =INDEX('KPI 5f'!$E$26:$P$26,Actual_month) -> 0.0093032481 | O49: =IFERROR(N49/M49,"") | P49: details | Q49: =G49*$R$3 -> 0 | R49: =M49*$R$3 -> 0 | S49: H | T49: v
A50: 5g | B50: Power Efficiency | C50: KWH/M3 | D50: l | E50: l | F50: l | G50: =INDEX('KPI 5g'!E$19:P$19,Actual_month) -> 0.95344618 | H50: =INDEX('KPI 5g'!E$20:P$20,Actual_month) -> 1.2079592 | I50: =IFERROR(G50/H50,"") -> 0.78930328 | J50: l | K50: l | L50: l | M50: =INDEX('KPI 5g'!$E$26:$P$26,Actual_month) -> 1.1999023 | N50: =INDEX('KPI 5g'!$E$27:$P$27,Actual_month) -> 1.0430256 | O50: =IFERROR(M50/N50,"") -> 1.1504055 | P50: details | Q50: =G50/$R$3 -> 1.0593846 | R50: =M50/$R$3 -> 1.3332248 | S50: L | T50: v
A51: 5h | B51: Production Loss | C51: M3 | D51: l | E51: l | F51: l | G51: =INDEX('KPI 5h'!E$19:P$19,Actual_month) -> 192 | H51: =INDEX('KPI 5h'!E$20:P$20,Actual_month) -> 444 | I51: =IFERROR(G51/H51,"") -> 0.43243243 | J51: l | K51: l | L51: l | M51: =INDEX('KPI 5h'!$E$26:$P$26,Actual_month) -> 1250 | N51: =INDEX('KPI 5h'!$E$27:$P$27,Actual_month) -> 1890 | O51: =IFERROR(M51/N51,"") -> 0.66137566 | P51: details | Q51: =G51/$R$3 -> 213.33333 | R51: =M51/$R$3 -> 1388.8889 | S51: L | T51: v
A53: 6 | B53: POLICELINE PRODUCTION SITE
A54: 6a | B54: Water Volume Abstracted | C54: M3 | D54: l | E54: l | F54: l | G54: =INDEX('KPI 6a'!E$19:P$19,Actual_month) -> 14715 | H54: =INDEX('KPI 6a'!E$20:P$20,Actual_month) -> 18916 | I54: =IFERROR(H54/G54,"") -> 1.285491 | J54: l | K54: l | L54: l | M54: =INDEX('KPI 6a'!$E$25:$P$25,Actual_month) -> 116360 | N54: =INDEX('KPI 6a'!$E$26:$P$26,Actual_month) -> 171529 | O54: =IFERROR(N54/M54,"") -> 1.4741234 | P54: details | Q54: =G54*$R$3 -> 13243.5 | R54: =M54*$R$3 -> 104724 | S54: H | T54: v
A55: 6b | B55: Water Volume Supplied | C55: M3 | D55: l | E55: l | F55: l | G55: =INDEX('KPI 6b'!E$19:P$19,Actual_month) -> 14420.7 | H55: =INDEX('KPI 6b'!E$20:P$20,Actual_month) -> 18539 | I55: =IFERROR(H55/G55,"") -> 1.2855825 | J55: l | K55: l | L55: l | M55: =INDEX('KPI 6b'!$E$25:$P$25,Actual_month) -> 114032.8 | N55: =INDEX('KPI 6b'!$E$26:$P$26,Actual_month) -> 170396 | O55: =IFERROR(N55/M55,"") -> 1.4942718 | P55: details | Q55: =G55*$R$3 -> 12978.63 | R55: =M55*$R$3 -> 102629.52 | S55: H | T55: v
A56: 6c | B56: Power Grid | C56: KWH | D56: l | E56: l | F56: l | G56: =INDEX('KPI 6c'!E$19:P$19,Actual_month) -> 11029.5 | H56: =INDEX('KPI 6c'!E$20:P$20,Actual_month) -> 9025 | I56: =IFERROR(G56/H56,"") -> 1.2221053 | J56: l | K56: l | L56: l | M56: =INDEX('KPI 6c'!$E$26:$P$26,Actual_month) -> 88236 | N56: =INDEX('KPI 6c'!$E$27:$P$27,Actual_month) -> 90116 | O56: =IFERROR(M56/N56,"") -> 0.979138 | P56: details | Q56: =G56/$R$3 -> 12255 | R56: =M56/$R$3 -> 98040 | S56: L | T56: v
A57: 6d | B57: Power Solar | C57: KWH | D57: l | E57: l | F57: l | G57: =INDEX('KPI 6d'!E$19:P$19,Actual_month) -> 3801.5022 | H57: =INDEX('KPI 6d'!E$20:P$20,Actual_month) -> 3087 | I57: =IFERROR(H57/G57,"") -> 0.81204741 | J57: l | K57: l | L57: l | M57: =INDEX('KPI 6d'!$E$25:$P$25,Actual_month) -> 30412.017 | N57: =INDEX('KPI 6d'!$E$26:$P$26,Actual_month) -> 32689.49 | O57: =IFERROR(N57/M57,"") -> 1.0748873 | P57: details | Q57: =G57*$R$3 -> 3421.352 | R57: =M57*$R$3 -> 27370.816 | S57: H | T57: v
A58: 6e | B58: Total Power Consumption | C58: KWH | D58: l | E58: l | F58: l | G58: =INDEX('KPI 6e'!E$19:P$19,Actual_month) -> 14831.002 | H58: =INDEX('KPI 6e'!E$20:P$20,Actual_month) -> 12112 | I58: =IFERROR(H58/G58,"") -> 0.81666767 | J58: l | K58: l | L58: l | M58: =INDEX('KPI 6e'!$E$25:$P$25,Actual_month) -> 118648.02 | N58: =INDEX('KPI 6e'!$E$26:$P$26,Actual_month) -> 122805.49 | O58: =IFERROR(N58/M58,"") -> 1.0350404 | P58: details | Q58: =G58*$R$3 -> 13347.902 | R58: =M58*$R$3 -> 106783.22 | S58: H | T58: v
A59: 6f | B59: % Solar | C59: % | D59: l | E59: l | F59: l | G59: =INDEX('KPI 6f'!E$19:P$19,Actual_month) -> 0.25632133 | H59: =INDEX('KPI 6f'!E$20:P$20,Actual_month) -> 0.2548712 | I59: =IFERROR(H59/G59,"") -> 0.99434255 | J59: l | K59: l | L59: l | M59: =INDEX('KPI 6f'!$E$25:$P$25,Actual_month) -> 0.25632133 | N59: =INDEX('KPI 6f'!$E$26:$P$26,Actual_month) -> 0.2668662 | O59: =IFERROR(N59/M59,"") -> 1.0411393 | P59: details | Q59: =G59*$R$3 -> 0.23068919 | R59: =M59*$R$3 -> 0.23068919 | S59: H | T59: v
A60: 6g | B60: Power Efficiency | C60: KWH/M3 | D60: l | E60: l | F60: l | G60: =INDEX('KPI 6g'!E$19:P$19,Actual_month) -> 1.0078833 | H60: =INDEX('KPI 6g'!E$20:P$20,Actual_month) -> 0.6403045 | I60: =IFERROR(G60/H60,"") -> 1.5740687 | J60: l | K60: l | L60: l | M60: =INDEX('KPI 6g'!$E$26:$P$26,Actual_month) -> 1.0197189 | N60: =INDEX('KPI 6g'!$E$27:$P$27,Actual_month) -> 0.71933718 | O60: =IFERROR(M60/N60,"") -> 1.4175812 | P60: details | Q60: =G60/$R$3 -> 1.1198703 | R60: =M60/$R$3 -> 1.133021 | S60: L | T60: v
A61: 6h | B61: Production Loss | C61: M3 | D61: l | E61: l | F61: l | G61: =INDEX('KPI 6h'!E$19:P$19,Actual_month) -> 294.3 | H61: =INDEX('KPI 6h'!E$20:P$20,Actual_month) -> 377 | I61: =IFERROR(G61/H61,"") -> 0.7806366 | J61: l | K61: l | L61: l | M61: =INDEX('KPI 6h'!$E$26:$P$26,Actual_month) -> 2327.2 | N61: =INDEX('KPI 6h'!$E$27:$P$27,Actual_month) -> 1133 | O61: =IFERROR(M61/N61,"") -> 2.0540159 | P61: details | Q61: =G61/$R$3 -> 327 | R61: =M61/$R$3 -> 2585.7778 | S61: L | T61: v
A62: 7 | B62: MAI MAHIU PRODUCTION SITE
A63: 7a | B63: Water Volume Abstracted | C63: M3 | D63: l | E63: l | F63: l | G63: =INDEX('KPI 7a'!E$19:P$19,Actual_month) -> 8000 | H63: =INDEX('KPI 7a'!E$20:P$20,Actual_month) -> 8977 | I63: =IFERROR(H63/G63,"") -> 1.122125 | J63: l | K63: l | L63: l | M63: =INDEX('KPI 7a'!$E$26:$P$26,Actual_month) -> 50000 | N63: =INDEX('KPI 7a'!$E$27:$P$27,Actual_month) -> 57513 | O63: =IFERROR(N63/M63,"") -> 1.15026 | P63: details | Q63: =G63*$R$3 -> 7200 | R63: =M63*$R$3 -> 45000 | S63: H | T63: v
A64: 7b | B64: Water Volume Supplied | C64: M3 | D64: l | E64: l | F64: l | G64: =INDEX('KPI 7b'!E$19:P$19,Actual_month) -> 8000 | H64: =INDEX('KPI 7b'!E$20:P$20,Actual_month) -> 8977 | I64: =IFERROR(H64/G64,"") -> 1.122125 | J64: l | K64: l | L64: l | M64: =INDEX('KPI 7b'!$E$25:$P$25,Actual_month) -> 46054 | N64: =INDEX('KPI 7b'!$E$26:$P$26,Actual_month) -> 50000 | O64: =IFERROR(N64/M64,"") -> 1.085682 | P64: details | Q64: =G64*$R$3 -> 7200 | R64: =M64*$R$3 -> 41448.6 | S64: H | T64: v
A65: 7c | B65: Power Consumption | C65: KWH | D65: l | E65: l | F65: l | G65: =INDEX('KPI 7c'!E$19:P$19,Actual_month) -> 4108.8333 | H65: =INDEX('KPI 7c'!E$20:P$20,Actual_month) -> 4703 | I65: =IFERROR(G65/H65,"") -> 0.8736622 | J65: l | K65: l | L65: l | M65: =INDEX('KPI 7c'!$E$26:$P$26,Actual_month) -> 32870.667 | N65: =INDEX('KPI 7c'!$E$27:$P$27,Actual_month) -> 43309 | O65: =IFERROR(M65/N65,"") -> 0.75898004 | P65: details | Q65: =G65/$R$3 -> 4565.3704 | R65: =M65/$R$3 -> 36522.963 | S65: L | T65: v
A66: 7d | B66: Power Efficiency | C66: KWH/M3 | D66: l | E66: l | F66: l | G66: =INDEX('KPI 7d'!E$19:P$19,Actual_month) -> 0.51360417 | H66: =INDEX('KPI 7d'!E$20:P$20,Actual_month) -> 0.5238944 | I66: =IFERROR(G66/H66,"") -> 0.9803582 | J66: l | K66: l | L66: l | M66: =INDEX('KPI 7d'!$E$26:$P$26,Actual_month) -> 0.68090749 | N66: =INDEX('KPI 7d'!$E$20:$P$20,Actual_month) -> 0.5238944 | O66: =IFERROR(M66/N66,"") -> 1.2997037 | P66: details | Q66: =G66/$R$3 -> 0.5706713 | R66: =M66/$R$3 -> 0.75656388 | S66: L | T66: v
A67: 7e | B67: Production Loss | C67: M3 | D67: l | E67: l | F67: l | G67: =INDEX('KPI 7e'!E$19:P$19,Actual_month) -> 1 | H67: =INDEX('KPI 7e'!E$20:P$20,Actual_month) -> 336 | I67: =IFERROR(G67/H67,"") -> 0.0029761905 | J67: l | K67: l | L67: l | M67: =INDEX('KPI 7e'!$E$26:$P$26,Actual_month) -> 3 | N67: =INDEX('KPI 7e'!$E$26:$P$26,Actual_month) -> 3 | O67: =IFERROR(M67/N67,"") -> 1 | P67: details | Q67: =G67/$R$3 -> 1.1111111 | R67: =M67/$R$3 -> 3.3333333 | S67: L | T67: v
A68: 8 | B68: MUCHIRINGIRI PRODUCTION SITE
A69: 8a | B69: Water Volume Abstracted | C69: M3 | D69: l | E69: l | F69: l | G69: =INDEX('KPI 8a'!E$19:P$19,Actual_month) -> 50 | H69: =INDEX('KPI 8a'!E$20:P$20,Actual_month) -> 0 | I69: =IFERROR(H69/G69,"") -> 0 | J69: l | K69: l | L69: l | M69: =INDEX('KPI 8a'!$E$26:$P$26,Actual_month) -> 150 | N69: =INDEX('KPI 8a'!$E$27:$P$27,Actual_month) -> 0 | O69: =IFERROR(N69/M69,"") -> 0 | P69: details | Q69: =G69*$R$3 -> 45 | R69: =M69*$R$3 -> 135 | S69: H | T69: v
A70: 8b | B70: Water Volume Supplied | C70: M3 | D70: l | E70: l | F70: l | G70: =INDEX('KPI 8b'!E$19:P$19,Actual_month) -> 49 | H70: =INDEX('KPI 8b'!E$20:P$20,Actual_month) -> 0 | I70: =IFERROR(H70/G70,"") -> 0 | J70: l | K70: l | L70: l | M70: =INDEX('KPI 8b'!$E$26:$P$26,Actual_month) -> 147 | N70: =INDEX('KPI 8b'!$E$27:$P$27,Actual_month) -> 0 | O70: =IFERROR(N70/M70,"") -> 0 | P70: details | Q70: =G70*$R$3 -> 44.1 | R70: =M70*$R$3 -> 132.3 | S70: H | T70: v
A71: 8c | B71: Power Consumption | C71: KWH | D71: l | E71: l | F71: l | G71: =INDEX('KPI 8c'!E$19:P$19,Actual_month) -> 0 | H71: =INDEX('KPI 8c'!E$20:P$20,Actual_month) -> 0 | I71: =IFERROR(G71/H71,"") | J71: l | K71: l | L71: l | M71: =INDEX('KPI 8c'!$E$26:$P$26,Actual_month) -> 0 | N71: =INDEX('KPI 8c'!$E$26:$P$26,Actual_month) -> 0 | O71: =IFERROR(M71/N71,"") | P71: details | Q71: =G71/$R$3 -> 0 | R71: =M71/$R$3 -> 0 | S71: L | T71: v
A72: 8d | B72: Power Efficiency | C72: KWH/M3 | D72: l | E72: l | F72: l | G72: =INDEX('KPI 8d'!E$19:P$19,Actual_month) -> 0 | H72: =INDEX('KPI 8d'!E$20:P$20,Actual_month) -> 0 | I72: =IFERROR(G72/H72,"") | J72: l | K72: l | L72: l | M72: =INDEX('KPI 8d'!$E$26:$P$26,Actual_month) -> 0 | N72: =INDEX('KPI 8d'!$E$26:$P$26,Actual_month) -> 0 | O72: =IFERROR(M72/N72,"") | P72: details | Q72: =G72/$R$3 -> 0 | R72: =M72/$R$3 -> 0 | S72: L | T72: v
A73: 8e | B73: Production Loss | C73: M3 | D73: l | E73: l | F73: l | G73: =INDEX('KPI 8e'!E$19:P$19,Actual_month) -> 1 | H73: =INDEX('KPI 8e'!E$20:P$20,Actual_month) -> 0 | I73: =IFERROR(G73/H73,"") | J73: l | K73: l | L73: l | M73: =INDEX('KPI 8e'!$E$26:$P$26,Actual_month) -> 3 | N73: =INDEX('KPI 8e'!$E$26:$P$26,Actual_month) -> 3 | O73: =IFERROR(M73/N73,"") -> 1 | P73: details | Q73: =G73/$R$3 -> 1.1111111 | R73: =M73/$R$3 -> 3.3333333 | S73: L | T73: v
A74: 9 | B74: NGONDI
A75: 9a | B75: Water Volume Abstracted | C75: M3 | D75: l | E75: l | F75: l | G75: =INDEX('KPI 9a'!E$19:P$19,Actual_month) -> 750 | H75: =INDEX('KPI 9a'!E$20:P$20,Actual_month) -> 1376 | I75: =IFERROR(H75/G75,"") -> 1.8346667 | J75: l | K75: l | L75: l | M75: =INDEX('KPI 9a'!$E$26:$P$26,Actual_month) -> 4600 | N75: =INDEX('KPI 9a'!$E$27:$P$27,Actual_month) -> 7288 | O75: =IFERROR(N75/M75,"") -> 1.5843478 | P75: details | Q75: =G75*$R$3 -> 675 | R75: =M75*$R$3 -> 4140 | S75: H | T75: v
A76: 9b | B76: Water Volume Supplied | C76: M3 | D76: l | E76: l | F76: l | G76: =INDEX('KPI 9b'!E$19:P$19,Actual_month) -> 750 | H76: =INDEX('KPI 9b'!E$20:P$20,Actual_month) -> 1376 | I76: =IFERROR(H76/G76,"") -> 1.8346667 | J76: l | K76: l | L76: l | M76: =INDEX('KPI 9b'!$E$25:$P$25,Actual_month) -> 46054 | N76: =INDEX('KPI 9b'!$E$26:$P$26,Actual_month) -> 4600 | O76: =IFERROR(N76/M76,"") -> 0.099882746 | P76: details | Q76: =G76*$R$3 -> 675 | R76: =M76*$R$3 -> 41448.6 | S76: H | T76: v
A77: 9c | B77: Power Solar | C77: KWH | D77: l | E77: l | F77: l | G77: =INDEX('KPI 9c'!E$19:P$19,Actual_month) -> 0 | H77: =INDEX('KPI 9c'!E$20:P$20,Actual_month) -> 0 | I77: =IFERROR(G77/H77,"") | J77: l | K77: l | L77: l | M77: =INDEX('KPI 9c'!$E$26:$P$26,Actual_month) -> 0 | N77: =INDEX('KPI 9c'!$E$26:$P$26,Actual_month) -> 0 | O77: =IFERROR(M77/N77,"") | P77: details | Q77: =G77/$R$3 -> 0 | R77: =M77/$R$3 -> 0 | S77: L | T77: v
A78: 9d | B78: Power Efficiency | C78: KWH/M3 | D78: l | E78: l | F78: l | G78: =INDEX('KPI 9d'!E$19:P$19,Actual_month) -> 0 | H78: =INDEX('KPI 9d'!E$20:P$20,Actual_month) -> 0 | I78: =IFERROR(G78/H78,"") | J78: l | K78: l | L78: l | M78: =INDEX('KPI 9d'!$E$26:$P$26,Actual_month) -> 0 | N78: =INDEX('KPI 9d'!$E$26:$P$26,Actual_month) -> 0 | O78: =IFERROR(M78/N78,"") | P78: details | Q78: =G78/$R$3 -> 0 | R78: =M78/$R$3 -> 0 | S78: L | T78: v
A79: 9e | B79: Production Loss | C79: M3 | D79: l | E79: l | F79: l | G79: =INDEX('KPI 9e'!E$19:P$19,Actual_month) -> 15 | H79: =INDEX('KPI 9e'!E$20:P$20,Actual_month) -> 0 | I79: =IFERROR(G79/H79,"") | J79: l | K79: l | L79: l | M79: =INDEX('KPI 9e'!$E$26:$P$26,Actual_month) -> 92 | N79: =INDEX('KPI 9e'!$E$26:$P$26,Actual_month) -> 92 | O79: =IFERROR(M79/N79,"") -> 1 | P79: details | Q79: =G79/$R$3 -> 16.666667 | R79: =M79/$R$3 -> 102.22222 | S79: L | T79: v
A80: 10 | B80: NYONJORO
A81: 10a | B81: Water Volume Abstracted | C81: M3 | D81: l | E81: l | F81: l | G81: =INDEX('KPI 10a'!E$19:P$19,Actual_month) -> 350 | H81: =INDEX('KPI 10a'!E$20:P$20,Actual_month) -> 726 | I81: =IFERROR(H81/G81,"") -> 2.0742857 | J81: l | K81: l | L81: l | M81: =INDEX('KPI 10a'!$E$26:$P$26,Actual_month) -> 2520 | N81: =INDEX('KPI 10a'!$E$27:$P$27,Actual_month) -> 2943 | O81: =IFERROR(N81/M81,"") -> 1.1678571 | P81: details | Q81: =G81*$R$3 -> 315 | R81: =M81*$R$3 -> 2268 | S81: H | T81: v
A82: 10b | B82: Water Volume Suplied | C82: M3 | D82: l | E82: l | F82: l | G82: =INDEX('KPI 10b'!E$19:P$19,Actual_month) -> 343 | H82: =INDEX('KPI 10b'!E$20:P$20,Actual_month) -> 726 | I82: =IFERROR(H82/G82,"") -> 2.1166181 | J82: l | K82: l | L82: l | M82: =INDEX('KPI 10b'!$E$26:$P$26,Actual_month) -> 2469.6 | N82: =INDEX('KPI 10b'!$E$27:$P$27,Actual_month) -> 2943 | O82: =IFERROR(N82/M82,"") -> 1.191691 | P82: details | Q82: =G82*$R$3 -> 308.7 | R82: =M82*$R$3 -> 2222.64 | S82: H | T82: v
A83: 10c | B83: Power Solar | C83: KWH | D83: l | E83: l | F83: l | G83: =INDEX('KPI 10c'!E$19:P$19,Actual_month) -> 0 | H83: =INDEX('KPI 10c'!E$20:P$20,Actual_month) -> 0 | I83: =IFERROR(G83/H83,"") | J83: l | K83: l | L83: l | M83: =INDEX('KPI 10c'!$E$26:$P$26,Actual_month) -> 0 | N83: =INDEX('KPI 10c'!$E$26:$P$26,Actual_month) -> 0 | O83: =IFERROR(M83/N83,"") | P83: details | Q83: =G83/$R$3 -> 0 | R83: =M83/$R$3 -> 0 | S83: L | T83: v
A84: 10d | B84: Power Efficiency | C84: KWH/M3 | D84: l | E84: l | F84: l | G84: =INDEX('KPI 10d'!E$19:P$19,Actual_month) -> 0 | H84: =INDEX('KPI 10d'!E$20:P$20,Actual_month) -> 0 | I84: =IFERROR(G84/H84,"") | J84: l | K84: l | L84: l | M84: =INDEX('KPI 10d'!$E$26:$P$26,Actual_month) -> 0 | N84: =INDEX('KPI 10d'!$E$26:$P$26,Actual_month) -> 0 | O84: =IFERROR(M84/N84,"") | P84: details | Q84: =G84/$R$3 -> 0 | R84: =M84/$R$3 -> 0 | S84: L | T84: v
A85: 10e | B85: Production Loss | C85: M3 | D85: l | E85: l | F85: l | G85: =INDEX('KPI 10e'!E$19:P$19,Actual_month) -> 7 | H85: =INDEX('KPI 10e'!E$20:P$20,Actual_month) -> 0 | I85: =IFERROR(G85/H85,"") | J85: l | K85: l | L85: l | M85: =INDEX('KPI 10e'!$E$26:$P$26,Actual_month) -> 50.4 | N85: =INDEX('KPI 10e'!$E$26:$P$26,Actual_month) -> 50.4 | O85: =IFERROR(M85/N85,"") -> 1 | P85: details | Q85: =G85/$R$3 -> 7.7777778 | R85: =M85/$R$3 -> 56 | S85: L | T85: v
B86: BULK WATER PURCHASE
A87: 6b | B87: Volume Water Imported ( Bulk Purchase) | C87: M3 | D87: l | E87: l | F87: l | G87: =INDEX('KPI 6b2'!E$19:P$19,Actual_month) -> 0 | H87: =INDEX('KPI 6b2'!E$20:P$20,Actual_month) -> 0 | I87: =IFERROR(H87/G87,"") | J87: l | K87: l | L87: l | M87: =INDEX('KPI 6b2'!$E$26:$P$26,Actual_month) -> 0 | N87: =INDEX('KPI 6b2'!$E$27:$P$27,Actual_month) -> 0 | O87: =IFERROR(N87/M87,"") | P87: details | Q87: =G87*$R$3 -> 0 | R87: =M87*$R$3 -> 0 | S87: H | T87: v
A88: 6b1 | B88: Cost Incurred for Purchase | C88: Ksh | D88: l | E88: l | F88: l | G88: =INDEX('KPI 6b1'!E$19:P$19,Actual_month) -> 0 | H88: =INDEX('KPI 6b1'!E$20:P$20,Actual_month) -> 0 | I88: =IFERROR(G88/H88,"") | J88: l | K88: l | L88: l | M88: =INDEX('KPI 6b1'!$E$26:$P$26,Actual_month) -> 0 | N88: =INDEX('KPI 6b1'!$E$27:$P$27,Actual_month) -> 0 | O88: =IFERROR(M88/N88,"") | P88: details | Q88: =G88/$R$3 -> 0 | R88: =M88/$R$3 -> 0 | S88: L | T88: v
A89: 11 | B89: KARATI POLICE POST
A90: 11a | B90: Water Volume Abstracted | C90: M3 | D90: l | E90: l | F90: l | G90: =INDEX('KPI 11a'!E$19:P$19,Actual_month) -> 420 | H90: =INDEX('KPI 11a'!E$20:P$20,Actual_month) -> 694 | I90: =IFERROR(H90/G90,"") -> 1.652381 | J90: l | K90: l | L90: l | M90: =INDEX('KPI 11a'!$E$26:$P$26,Actual_month) -> 2800 | N90: =INDEX('KPI 11a'!$E$27:$P$27,Actual_month) -> 3337 | O90: =IFERROR(N90/M90,"") -> 1.1917857 | P90: details | Q90: =G90*$R$3 -> 378 | R90: =M90*$R$3 -> 2520 | S90: H | T90: v
A91: 11b | B91: Water Volume Supplied | C91: M3 | D91: l | E91: l | F91: l | G91: =INDEX('KPI 11b'!E$19:P$19,Actual_month) -> 411.6 | H91: =INDEX('KPI 11b'!E$20:P$20,Actual_month) -> 694 | I91: =IFERROR(H91/G91,"") -> 1.686103 | J91: l | K91: l | L91: l | M91: =INDEX('KPI 11b'!$E$25:$P$25,Actual_month) -> 46054 | N91: =INDEX('KPI 11b'!$E$26:$P$26,Actual_month) -> 2744 | O91: =IFERROR(N91/M91,"") -> 0.05958223 | P91: details | Q91: =G91*$R$3 -> 370.44 | R91: =M91*$R$3 -> 41448.6 | S91: H | T91: v
A92: 11c | B92: Power Consumption | C92: KWH | D92: l | E92: l | F92: l | G92: =INDEX('KPI 11c'!E$19:P$19,Actual_month) -> 525 | H92: =INDEX('KPI 11c'!E$20:P$20,Actual_month) -> 868 | I92: =IFERROR(G92/H92,"") -> 0.60483871 | J92: l | K92: l | L92: l | M92: =INDEX('KPI 11c'!$E$26:$P$26,Actual_month) -> 4200 | N92: =INDEX('KPI 11c'!$E$20:$P$20,Actual_month) -> 868 | O92: =IFERROR(M92/N92,"") -> 4.8387097 | P92: details | Q92: =G92/$R$3 -> 583.33333 | R92: =M92/$R$3 -> 4666.6667 | S92: L | T92: v
A93: 11d | B93: Power Efficiency | C93: KWH/M3 | D93: l | E93: l | F93: l | G93: =INDEX('KPI 11d'!E$19:P$19,Actual_month) -> 1.25 | H93: =INDEX('KPI 11d'!E$20:P$20,Actual_month) -> 1.2507205 | I93: =IFERROR(G93/H93,"") -> 0.99942396 | J93: l | K93: l | L93: l | M93: =INDEX('KPI 11d'!$E$26:$P$26,Actual_month) -> 1.5265194 | N93: =INDEX('KPI 11d'!$E$20:$P$20,Actual_month) -> 1.2507205 | O93: =IFERROR(M93/N93,"") -> 1.220512 | P93: details | Q93: =G93/$R$3 -> 1.3888889 | R93: =M93/$R$3 -> 1.6961326 | S93: L | T93: v
A94: 11e | B94: Production Loss | C94: M3 | D94: l | E94: l | F94: l | G94: =INDEX('KPI 11e'!E$19:P$19,Actual_month) -> 8.4 | H94: =INDEX('KPI 11e'!E$20:P$20,Actual_month) -> 0 | I94: =IFERROR(G94/H94,"") | J94: l | K94: l | L94: l | M94: =INDEX('KPI 11e'!$E$26:$P$26,Actual_month) -> 56 | N94: =INDEX('KPI 11e'!$E$26:$P$26,Actual_month) -> 56 | O94: =IFERROR(M94/N94,"") -> 1 | P94: details | Q94: =G94/$R$3 -> 9.3333333 | R94: =M94/$R$3 -> 62.222222 | S94: L | T94: v
A95: 12 | B95: NIP
A96: 12a | B96: Water Volume Abstracted | C96: M3 | D96: l | E96: l | F96: l | G96: =INDEX('KPI 12a'!E$19:P$19,Actual_month) -> 73000 | H96: =INDEX('KPI 12a'!E$20:P$20,Actual_month) -> 61627 | I96: =IFERROR(H96/G96,"") -> 0.84420548 | J96: l | K96: l | L96: l | M96: =INDEX('KPI 12a'!$E$26:$P$26,Actual_month) -> 547000 | N96: =INDEX('KPI 12a'!$E$27:$P$27,Actual_month) -> 542234 | O96: =IFERROR(N96/M96,"") -> 0.99128702 | P96: details | Q96: =G96*$R$3 -> 65700 | R96: =M96*$R$3 -> 492300 | S96: H | T96: v
A97: 12b | B97: Water Volume Supplied | C97: M3 | D97: l | E97: l | F97: l | G97: =INDEX('KPI 12b'!E$19:P$19,Actual_month) -> 73000 | H97: =INDEX('KPI 12b'!E$20:P$20,Actual_month) -> 61627 | I97: =IFERROR(H97/G97,"") -> 0.84420548 | J97: l | K97: l | L97: l | M97: =INDEX('KPI 12b'!$E$25:$P$25,Actual_month) -> 46054 | N97: =INDEX('KPI 12b'!$E$26:$P$26,Actual_month) -> 547000 | O97: =IFERROR(N97/M97,"") -> 11.877361 | P97: details | Q97: =G97*$R$3 -> 65700 | R97: =M97*$R$3 -> 41448.6 | S97: H | T97: v
A98: 12c | B98: Power Consumption | C98: KWH | D98: l | E98: l | F98: l | G98: =INDEX('KPI 12c'!E$19:P$19,Actual_month) -> 57804.667 | H98: =INDEX('KPI 12c'!E$20:P$20,Actual_month) -> 78692 | I98: =IFERROR(G98/H98,"") -> 0.73456853 | J98: l | K98: l | L98: l | M98: =INDEX('KPI 12c'!$E$26:$P$26,Actual_month) -> 462437.33 | N98: =INDEX('KPI 12c'!$E$20:$P$20,Actual_month) -> 78692 | O98: =IFERROR(M98/N98,"") -> 5.8765482 | P98: details | Q98: =G98/$R$3 -> 64227.407 | R98: =M98/$R$3 -> 513819.26 | S98: L | T98: v
A99: 12d | B99: Power Efficiency | C99: KWH/M3 | D99: l | E99: l | F99: l | G99: =INDEX('KPI 12d'!E$19:P$19,Actual_month) -> 0.79184475 | H99: =INDEX('KPI 12d'!E$20:P$20,Actual_month) -> 1.2769078 | I99: =IFERROR(G99/H99,"") -> 0.62012678 | J99: l | K99: l | L99: l | M99: =INDEX('KPI 12d'!$E$26:$P$26,Actual_month) -> 0.84715628 | N99: =INDEX('KPI 12d'!$E$20:$P$20,Actual_month) -> 1.2769078 | O99: =IFERROR(M99/N99,"") -> 0.66344356 | P99: details | Q99: =G99/$R$3 -> 0.8798275 | R99: =M99/$R$3 -> 0.94128476 | S99: L | T99: v
A100: 12e | B100: Production Loss | C100: M3 | D100: l | E100: l | F100: l | G100: =INDEX('KPI 12e'!E$19:P$19,Actual_month) -> 1460 | H100: =INDEX('KPI 12e'!E$20:P$20,Actual_month) -> 1679 | I100: =IFERROR(G100/H100,"") -> 0.86956522 | J100: l | K100: l | L100: l | M100: =INDEX('KPI 12e'!$E$26:$P$26,Actual_month) -> 10940 | N100: =INDEX('KPI 12e'!$E$26:$P$26,Actual_month) -> 10940 | O100: =IFERROR(M100/N100,"") -> 1 | P100: details | Q100: =G100/$R$3 -> 1622.2222 | R100: =M100/$R$3 -> 12155.556 | S100: L | T100: v
A101: 13 | B101: IHINDU
A102: 13a | B102: Water Volume Abstracted | C102: M3 | D102: l | E102: l | F102: l | G102: =INDEX('KPI 13a'!E$19:P$19,Actual_month) -> 2100 | H102: =INDEX('KPI 13a'!E$20:P$20,Actual_month) -> 471 | I102: =IFERROR(H102/G102,"") -> 0.22428571 | J102: l | K102: l | L102: l | M102: =INDEX('KPI 13a'!$E$26:$P$26,Actual_month) -> 14000 | N102: =INDEX('KPI 13a'!$E$27:$P$27,Actual_month) -> 5187 | O102: =IFERROR(N102/M102,"") -> 0.3705 | P102: details | Q102: =G102*$R$3 -> 1890 | R102: =M102*$R$3 -> 12600 | S102: H | T102: v
A103: 13b | B103: Water Volume Supplied | C103: M3 | D103: l | E103: l | F103: l | G103: =INDEX('KPI 12b'!E$19:P$19,Actual_month) -> 73000 | H103: =INDEX('KPI 12b'!E$20:P$20,Actual_month) -> 61627 | I103: =IFERROR(H103/G103,"") -> 0.84420548 | J103: l | K103: l | L103: l | M103: =INDEX('KPI 12b'!$E$25:$P$25,Actual_month) -> 46054 | N103: =INDEX('KPI 12b'!$E$26:$P$26,Actual_month) -> 547000 | O103: =IFERROR(N103/M103,"") -> 11.877361 | P103: details | Q103: =G103*$R$3 -> 65700 | R103: =M103*$R$3 -> 41448.6 | S103: H | T103: v
A104: 13c | B104: Power Consumption | C104: KWH | D104: l | E104: l | G104: =INDEX('KPI 13c'!E$19:P$19,Actual_month) -> 2250 | H104: =INDEX('KPI 13c'!E$20:P$20,Actual_month) -> 258 | I104: =IFERROR(H104/G104,"") -> 0.11466667 | J104: l | K104: l | M104: =INDEX('KPI 13c'!$E$26:$P$26,Actual_month) -> 18000 | N104: =INDEX('KPI 13c'!$E$27:$P$27,Actual_month) -> 6948 | O104: =IFERROR(N104/M104,"") -> 0.386 | P104: details | Q104: =G104/$R$3 -> 2500 | R104: =M104/$R$3 -> 20000 | S104: L | T104: v
A105: 13d | B105: Power Efficiency | C105: KWH/M3 | D105: l | E105: l | G105: =INDEX('KPI 13d'!E$19:P$19,Actual_month) -> 1.0714286 | H105: =INDEX('KPI 13d'!E$26:P$26,Actual_month) -> 1.3084452 | I105: =IFERROR(H105/G105,"") -> 1.2212155 | J105: l | K105: l | M105: =INDEX('KPI 13d'!$E$26:$P$26,Actual_month) -> 1.3084452 | N105: =INDEX('KPI 13d'!$E$26:$P$26,Actual_month) -> 1.3084452 | O105: =IFERROR(N105/M105,"") -> 1 | P105: details | Q105: =G105/$R$3 -> 1.1904762 | R105: =M105/$R$3 -> 1.453828 | S105: L | T105: v
...

Sheet Budget2526
B1: ='Dashboard Production Quality'!B1 -> 0 | C1: ='Dashboard Production Quality'!C1 -> 0 | E1: 13.4
B2: ='Dashboard Production Quality'!B2 -> 46054 | C2: ='Dashboard Production Quality'!C2 -> 0 | E2: 0.02
B3: ='Dashboard Production Quality'!B3 -> 0 | C3: ='Dashboard Production Quality'!C3 -> 0
A4: ='Dashboard Production Quality'!A4 -> 0 | C4: ='Dashboard Production Quality'!C4 -> Unit | E4: jul | F4: aug | G4: sep | H4: oct | I4: nov | J4: dec | K4: jan | L4: feb | M4: mar | N4: apr | O4: may | P4: jun
A5: ='Dashboard Production Quality'!A5 -> DASHBOARD - VOLUMES PRODUCED - NON-REVENUE WATER | B5: ='Dashboard Production Quality'!B5 -> 0 | C5: ='Dashboard Production Quality'!C5 -> 0
A6: ='Dashboard Production Quality'!A7 -> 1a | B6: ='Dashboard Production Quality'!B6 -> DTI PRODUCTION SITE | C6: ='Dashboard Production Quality'!C6 -> 0
A7: ='Dashboard Production Quality'!A7 -> 1a | B7: ='Dashboard Production Quality'!B7 -> Water Volume Abstracted | C7: ='Dashboard Production Quality'!C7 -> M3 | E7: 40000 | F7: 40020 | G7: 40520 | H7: 41020 | I7: 41520 | J7: 42020 | K7: 42520 | L7: 43020 | M7: 43520 | N7: 44020 | O7: 44520 | P7: 45020
A8: ='Dashboard Production Quality'!A8 -> 1b | B8: ='Dashboard Production Quality'!B8 -> Water Volume Supplied | C8: ='Dashboard Production Quality'!C8 -> M3 | E8: =E7-E14 -> 39200 | F8: =F7-F14 -> 39219.6 | G8: =G7-G14 -> 39709.6 | H8: =H7-H14 -> 40199.6 | I8: =I7-I14 -> 40689.6 | J8: =J7-J14 -> 41179.6 | K8: =K7-K14 -> 41669.6 | L8: =L7-L14 -> 42159.6 | ... P8: =P7-P14 -> 44119.6
A9: ='Dashboard Production Quality'!A9 -> 1c | B9: ='Dashboard Production Quality'!B9 -> Power Grid | C9: ='Dashboard Production Quality'!C9 -> KWH | E9: 50298.261 | F9: 50298.261 | G9: 50298.261 | H9: 50298.261 | I9: 50298.261 | J9: 50298.261 | K9: 50298.261 | L9: 50298.261 | M9: 50298.261 | N9: 50298.261 | O9: 50298.261 | P9: 50298.261
A10: ='Dashboard Production Quality'!A10 -> 1d | B10: ='Dashboard Production Quality'!B10 -> Power Solar | C10: ='Dashboard Production Quality'!C10 -> KWH | E10: 15534.791 | F10: 15534.791 | G10: 15534.791 | H10: 15534.791 | I10: 15534.791 | J10: 15534.791 | K10: 15534.791 | L10: 15534.791 | M10: 15534.791 | N10: 15534.791 | O10: 15534.791 | P10: 15534.791
A11: ='Dashboard Production Quality'!A11 -> 1e | B11: ='Dashboard Production Quality'!B11 -> Total Power Consumption | C11: ='Dashboard Production Quality'!C11 -> KWH | E11: =E10+E9 -> 65833.052 | F11: =F10+F9 -> 65833.052 | G11: =G10+G9 -> 65833.052 | H11: =H10+H9 -> 65833.052 | I11: =I10+I9 -> 65833.052 | J11: =J10+J9 -> 65833.052 | K11: =K10+K9 -> 65833.052 | L11: =L10+L9 -> 65833.052 | ... P11: =P10+P9 -> 65833.052
A12: ='Dashboard Production Quality'!A12 -> 1f | B12: ='Dashboard Production Quality'!B12 -> % Solar | C12: ='Dashboard Production Quality'!C12 -> % | E12: =E10/E11 -> 0.23597252 | F12: =F10/F11 -> 0.23597252 | G12: =G10/G11 -> 0.23597252 | H12: =H10/H11 -> 0.23597252 | I12: =I10/I11 -> 0.23597252 | J12: =J10/J11 -> 0.23597252 | K12: =K10/K11 -> 0.23597252 | L12: =L10/L11 -> 0.23597252 | ... P12: =P10/P11 -> 0.23597252
A13: ='Dashboard Production Quality'!A13 -> 1g | B13: ='Dashboard Production Quality'!B13 -> Power Efficiency | C13: ='Dashboard Production Quality'!C13 -> KWH/M3 | E13: =E11/E7 -> 1.6458263 | F13: =F11/F7 -> 1.6450038 | G13: =G11/G7 -> 1.6247051 | H13: =H11/H7 -> 1.6049013 | I13: =I11/I7 -> 1.5855745 | J13: =J11/J7 -> 1.5667076 | K13: =K11/K7 -> 1.5482844 | L13: =L11/L7 -> 1.5302895 | ... P13: =P11/P7 -> 1.4623068
A14: ='Dashboard Production Quality'!A14 -> 1h | B14: ='Dashboard Production Quality'!B14 -> Production Loss | C14: ='Dashboard Production Quality'!C14 -> M3 | E14: =$E$2*E7 -> 800 | F14: =$E$2*F7 -> 800.4 | G14: =$E$2*G7 -> 810.4 | H14: =$E$2*H7 -> 820.4 | I14: =$E$2*I7 -> 830.4 | J14: =$E$2*J7 -> 840.4 | K14: =$E$2*K7 -> 850.4 | L14: =$E$2*L7 -> 860.4 | ... P14: =$E$2*P7 -> 900.4
A15: ='Dashboard Production Quality'!A16 -> 2 | B15: ='Dashboard Production Quality'!B16 -> WATERWORKS PRODUCTION SITE | C15: ='Dashboard Production Quality'!C16 -> 0
A16: ='Dashboard Production Quality'!A17 -> 2a | B16: ='Dashboard Production Quality'!B17 -> Water Volume Abstracted | C16: ='Dashboard Production Quality'!C17 -> M3 | E16: 19200 | F16: 19250 | G16: 19300 | H16: 19350 | I16: 19400 | J16: 19450 | K16: 19500 | L16: 19550 | M16: 19600 | N16: 19650 | O16: 19700 | P16: 19750
A17: ='Dashboard Production Quality'!A18 -> 2b | B17: ='Dashboard Production Quality'!B18 -> Water Volume Supplied | C17: ='Dashboard Production Quality'!C18 -> M3 | E17: =E16-E23 -> 18816 | F17: =F16-F23 -> 18865 | G17: =G16-G23 -> 18914 | H17: =H16-H23 -> 18963 | I17: =I16-I23 -> 19012 | J17: =J16-J23 -> 19061 | K17: =K16-K23 -> 19110 | L17: =L16-L23 -> 19159 | ... P17: =P16-P23 -> 19355
A18: ='Dashboard Production Quality'!A19 -> 2c | B18: ='Dashboard Production Quality'!B19 -> Power Grid | C18: ='Dashboard Production Quality'!C19 -> KWH | E18: 32877.705 | F18: 32877.705 | G18: 32877.705 | H18: 32877.705 | I18: 32877.705 | J18: 32877.705 | K18: 32877.705 | L18: 32877.705 | M18: 32877.705 | N18: 32877.705 | O18: 32877.705 | P18: 32877.705
A19: ='Dashboard Production Quality'!A20 -> 2d | B19: ='Dashboard Production Quality'!B20 -> Power solar | C19: ='Dashboard Production Quality'!C20 -> KWH | E19: 10118.458 | F19: 10118.458 | G19: 10118.458 | H19: 10118.458 | I19: 10118.458 | J19: 10118.458 | K19: 10118.458 | L19: 10118.458 | M19: 10118.458 | N19: 10118.458 | O19: 10118.458 | P19: 10118.458
A20: ='Dashboard Production Quality'!A21 -> 2e | B20: ='Dashboard Production Quality'!B21 -> Total Power Consumption | C20: ='Dashboard Production Quality'!C21 -> KWH | E20: =E18+E19 -> 42996.163 | F20: =F18+F19 -> 42996.163 | G20: =G18+G19 -> 42996.163 | H20: =H18+H19 -> 42996.163 | I20: =I18+I19 -> 42996.163 | J20: =J18+J19 -> 42996.163 | K20: =K18+K19 -> 42996.163 | L20: =L18+L19 -> 42996.163 | ... P20: =P18+P19 -> 42996.163
A21: ='Dashboard Production Quality'!A22 -> 2f | B21: ='Dashboard Production Quality'!B22 -> % Solar | C21: ='Dashboard Production Quality'!C22 -> % | E21: =E19/E20 -> 0.23533398 | F21: =F19/F20 -> 0.23533398 | G21: =G19/G20 -> 0.23533398 | H21: =H19/H20 -> 0.23533398 | I21: =I19/I20 -> 0.23533398 | J21: =J19/J20 -> 0.23533398 | K21: =K19/K20 -> 0.23533398 | L21: =L19/L20 -> 0.23533398 | ... P21: =P19/P20 -> 0.23533398
A22: ='Dashboard Production Quality'!A23 -> 2g | B22: ='Dashboard Production Quality'!B23 -> Power Efficiency | C22: ='Dashboard Production Quality'!C23 -> KWH/M3 | E22: =E20/E16 -> 2.2393835 | F22: =F20/F16 -> 2.2335669 | G22: =G20/G16 -> 2.2277805 | H22: =H20/H16 -> 2.2220239 | I22: =I20/I16 -> 2.2162971 | J22: =J20/J16 -> 2.2105997 | K22: =K20/K16 -> 2.2049315 | L22: =L20/L16 -> 2.1992922 | ... P22: =P20/P16 -> 2.1770209
A23: ='Dashboard Production Quality'!A24 -> 2h | B23: ='Dashboard Production Quality'!B24 -> Production Loss | C23: ='Dashboard Production Quality'!C24 -> M3 | E23: =$E$2*E16 -> 384 | F23: =$E$2*F16 -> 385 | G23: =$E$2*G16 -> 386 | H23: =$E$2*H16 -> 387 | I23: =$E$2*I16 -> 388 | J23: =$E$2*J16 -> 389 | K23: =$E$2*K16 -> 390 | L23: =$E$2*L16 -> 391 | ... P23: =$E$2*P16 -> 395
A24: ='Dashboard Production Quality'!A26 -> 3 | B24: ='Dashboard Production Quality'!B26 -> A.I.C PRODUCTION SITE | C24: ='Dashboard Production Quality'!C26 -> 0
A25: ='Dashboard Production Quality'!A27 -> 3a | B25: ='Dashboard Production Quality'!B27 -> Water Volume Abstracted | C25: ='Dashboard Production Quality'!C27 -> M3 | E25: 8000 | F25: 8020 | G25: 8220 | H25: 8420 | I25: 8620 | J25: 8820 | K25: 9020 | L25: 9220 | M25: 9420 | N25: 9620 | O25: 9820 | P25: 10020
A26: ='Dashboard Production Quality'!A28 -> 3b | B26: ='Dashboard Production Quality'!B28 -> Water Volume Supplied | C26: ='Dashboard Production Quality'!C28 -> M3 | E26: =E25-E29 -> 7840 | F26: =F25-F29 -> 7859.6 | G26: =G25-G29 -> 8055.6 | H26: =H25-H29 -> 8251.6 | I26: =I25-I29 -> 8447.6 | J26: =J25-J29 -> 8643.6 | K26: =K25-K29 -> 8839.6 | L26: =L25-L29 -> 9035.6 | ... P26: =P25-P29 -> 9819.6
A27: ='Dashboard Production Quality'!A29 -> 3c | B27: ='Dashboard Production Quality'!B29 -> Power Consumption | C27: ='Dashboard Production Quality'!C29 -> KWH | E27: 4699.8333 | F27: 4699.8333 | G27: 4699.8333 | H27: 4699.8333 | I27: 4699.8333 | J27: 4699.8333 | K27: 4699.8333 | L27: 4699.8333 | M27: 4699.8333 | N27: 4699.8333 | O27: 4699.8333 | P27: 4699.8333
A28: ='Dashboard Production Quality'!A30 -> 3d | B28: ='Dashboard Production Quality'!B30 -> Power Efficiency | C28: ='Dashboard Production Quality'!C30 -> KWH/M3 | E28: =E27/E25 -> 0.58747917 | F28: =F27/F25 -> 0.58601413 | G28: =G27/G25 -> 0.57175588 | H28: =H27/H25 -> 0.55817498 | I28: =I27/I25 -> 0.54522428 | J28: =J27/J25 -> 0.53286092 | K28: =K27/K25 -> 0.52104582 | L28: =L27/L25 -> 0.50974331 | ... P28: =P27/P25 -> 0.46904524
A29: ='Dashboard Production Quality'!A31 -> 3e | B29: ='Dashboard Production Quality'!B31 -> Production Loss | C29: ='Dashboard Production Quality'!C31 -> M3 | E29: =E25*$E$2 -> 160 | F29: =F25*$E$2 -> 160.4 | G29: =G25*$E$2 -> 164.4 | H29: =H25*$E$2 -> 168.4 | I29: =I25*$E$2 -> 172.4 | J29: =J25*$E$2 -> 176.4 | K29: =K25*$E$2 -> 180.4 | L29: =L25*$E$2 -> 184.4 | ... P29: =P25*$E$2 -> 200.4
A30: ='Dashboard Production Quality'!A33 -> 4 | B30: ='Dashboard Production Quality'!B33 -> KARATI PRODUCTION SITE | C30: ='Dashboard Production Quality'!C33 -> 0
A31: ='Dashboard Production Quality'!A34 -> 4a | B31: ='Dashboard Production Quality'!B34 -> Water Volume Abstracted | C31: ='Dashboard Production Quality'!C34 -> M3 | E31: 60240 | F31: 60260 | G31: 60330 | H31: 60400 | I31: 60470 | J31: 60540 | K31: 60610 | L31: 60680 | M31: 60750 | N31: 60820 | O31: 60890 | P31: 60960
A32: ='Dashboard Production Quality'!A35 -> 4b | B32: ='Dashboard Production Quality'!B35 -> Water Volume Supplied | C32: ='Dashboard Production Quality'!C35 -> M3 | E32: =E31-E38 -> 58540.269 | F32: =F31-F38 -> 58357.137 | G32: =G31-G38 -> 57571.797 | H32: =H31-H38 -> 56911.728 | I32: =I31-I38 -> 56001.527 | J32: =J31-J38 -> 54832.721 | K32: =K31-K38 -> 54241.225 | L32: =L31-L38 -> 53435.444 | ... P32: =P31-P38 -> 49221.375
A33: ='Dashboard Production Quality'!A36 -> 4c | B33: ='Dashboard Production Quality'!B36 -> Power Grid | C33: ='Dashboard Production Quality'!C36 -> KWH | E33: 55514.06 | F33: 55514.06 | G33: 55514.06 | H33: 55514.06 | I33: 55514.06 | J33: 55514.06 | K33: 55514.06 | L33: 55514.06 | M33: 55514.06 | N33: 55514.06 | O33: 55514.06 | P33: 55514.06
A34: ='Dashboard Production Quality'!A37 -> 4d | B34: ='Dashboard Production Quality'!B37 -> Power Solar | C34: ='Dashboard Production Quality'!C37 -> KWH | E34: 10113.154 | F34: 10113.154 | G34: 10113.154 | H34: 10113.154 | I34: 10113.154 | J34: 10113.154 | K34: 10113.154 | L34: 10113.154 | M34: 10113.154 | N34: 10113.154 | O34: 10113.154 | P34: 10113.154
A35: ='Dashboard Production Quality'!A38 -> 4e | B35: ='Dashboard Production Quality'!B38 -> Total Power Consumption | C35: ='Dashboard Production Quality'!C38 -> KWH | E35: =E33+E34 -> 65627.214 | F35: =F33+F34 -> 65627.214 | G35: =G33+G34 -> 65627.214 | H35: =H33+H34 -> 65627.214 | I35: =I33+I34 -> 65627.214 | J35: =J33+J34 -> 65627.214 | K35: =K33+K34 -> 65627.214 | L35: =L33+L34 -> 65627.214 | ... P35: =P33+P34 -> 65627.214
A36: ='Dashboard Production Quality'!A39 -> 4f | B36: ='Dashboard Production Quality'!B39 -> % Solar | C36: ='Dashboard Production Quality'!C39 -> % | E36: =E34/E35 -> 0.1541 | F36: =F34/F35 -> 0.1541 | G36: =G34/G35 -> 0.1541 | H36: =H34/H35 -> 0.1541 | I36: =I34/I35 -> 0.1541 | J36: =J34/J35 -> 0.1541 | K36: =K34/K35 -> 0.1541 | L36: =L34/L35 -> 0.1541 | ... P36: =P34/P35 -> 0.1541
A37: ='Dashboard Production Quality'!A40 -> 4g | B37: ='Dashboard Production Quality'!B40 -> Power Efficiency | C37: ='Dashboard Production Quality'!C40 -> KWH/M3 | E37: =E38/E31 -> 0.028215984 | F37: =F38/F31 -> 0.031577553 | G37: =G38/G31 -> 0.045718599 | H37: =H38/H31 -> 0.057752851 | I37: =I38/I31 -> 0.073895702 | J37: =J38/J31 -> 0.094272866 | K37: =K38/K31 -> 0.10507796 | L37: =L38/L31 -> 0.11938952 | ... P37: =P38/P31 -> 0.19256275
A38: ='Dashboard Production Quality'!A41 -> 4h | B38: ='Dashboard Production Quality'!B41 -> Production Loss | C38: ='Dashboard Production Quality'!C41 -> M3 | E38: 1699.7309 | F38: 1902.8633 | G38: 2758.2031 | H38: 3488.2722 | I38: 4468.4731 | J38: 5707.2793 | K38: 6368.7754 | L38: 7244.5562 | M38: 8444.0638 | N38: 9336.4382 | O38: 10258.719 | P38: 11738.625
A39: ='Dashboard Production Quality'!A43 -> 5 | B39: ='Dashboard Production Quality'!B43 -> DCK PRODUCTION SITE | C39: ='Dashboard Production Quality'!C43 -> 0
A40: ='Dashboard Production Quality'!A44 -> 5a | B40: ='Dashboard Production Quality'!B44 -> Water Volume Abstracted | C40: ='Dashboard Production Quality'!C44 -> M3 | E40: 6000 | F40: 6500 | G40: 7000 | H40: 7600 | I40: 8100 | J40: 8600 | K40: 9100 | L40: 9600 | M40: 10100 | N40: 10600 | O40: 11100 | P40: 11600
A41: ='Dashboard Production Quality'!A45 -> 5b | B41: ='Dashboard Production Quality'!B45 -> Water Volume Supplied | C41: ='Dashboard Production Quality'!C45 -> M3 | E41: =E40-E47 -> 5880 | F41: =F40-F47 -> 6370 | G41: =G40-G47 -> 6860 | H41: =H40-H47 -> 7448 | I41: =I40-I47 -> 7938 | J41: =J40-J47 -> 8428 | K41: =K40-K47 -> 8918 | L41: =L40-L47 -> 9408 | ... P41: =P40-P47 -> 11368
A42: ='Dashboard Production Quality'!A46 -> 5c | B42: ='Dashboard Production Quality'!B46 -> Power Grid | C42: ='Dashboard Production Quality'!C46 -> KWH | E42: 9153.0833 | F42: 9153.0833 | G42: 9153.0833 | H42: 9153.0833 | I42: 9153.0833 | J42: 9153.0833 | K42: 9153.0833 | L42: 9153.0833 | M42: 9153.0833 | N42: 9153.0833 | O42: 9153.0833 | P42: 9153.0833
A43: ='Dashboard Production Quality'!A47 -> 5d | B43: ='Dashboard Production Quality'!B47 -> Power Solar | C43: ='Dashboard Production Quality'!C47 -> KWH
A44: ='Dashboard Production Quality'!A48 -> 5e | B44: ='Dashboard Production Quality'!B48 -> Total Power Consumption | C44: ='Dashboard Production Quality'!C48 -> KWH | E44: =E42+E43 -> 9153.0833 | F44: =F42+F43 -> 9153.0833 | G44: =G42+G43 -> 9153.0833 | H44: =H42+H43 -> 9153.0833 | I44: =I42+I43 -> 9153.0833 | J44: =J42+J43 -> 9153.0833 | K44: =K42+K43 -> 9153.0833 | L44: =L42+L43 -> 9153.0833 | ... P44: =P42+P43 -> 9153.0833
A45: ='Dashboard Production Quality'!A49 -> 5f | B45: ='Dashboard Production Quality'!B49 -> % Solar | C45: ='Dashboard Production Quality'!C49 -> % | E45: =E43/E44 -> 0 | F45: =F43/F44 -> 0 | G45: =G43/G44 -> 0 | H45: =H43/H44 -> 0 | I45: =I43/I44 -> 0 | J45: =J43/J44 -> 0 | K45: =K43/K44 -> 0 | L45: =L43/L44 -> 0 | ... P45: =P43/P44 -> 0
A46: ='Dashboard Production Quality'!A50 -> 5g | B46: Power Efficieny | C46: ='Dashboard Production Quality'!C50 -> KWH/M3 | E46: =E44/E40 -> 1.5255139 | F46: =F44/F40 -> 1.4081667 | G46: =G44/G40 -> 1.3075833 | H46: =H44/H40 -> 1.2043531 | I46: =I44/I40 -> 1.1300103 | J46: =J44/J40 -> 1.064312 | K46: =K44/K40 -> 1.0058333 | L46: =L44/L40 -> 0.95344618 | ... P46: =P44/P40 -> 0.78905891
A47: ='Dashboard Production Quality'!A51 -> 5h | B47: ='Dashboard Production Quality'!B51 -> Production Loss | C47: ='Dashboard Production Quality'!C51 -> M3 | E47: =$E$2*E40 -> 120 | F47: =$E$2*F40 -> 130 | G47: =$E$2*G40 -> 140 | H47: =$E$2*H40 -> 152 | I47: =$E$2*I40 -> 162 | J47: =$E$2*J40 -> 172 | K47: =$E$2*K40 -> 182 | L47: =$E$2*L40 -> 192 | ... P47: =$E$2*P40 -> 232
A48: ='Dashboard Production Quality'!A53 -> 6 | B48: ='Dashboard Production Quality'!B53 -> POLICELINE PRODUCTION SITE | C48: ='Dashboard Production Quality'!C53 -> 0
A49: ='Dashboard Production Quality'!A54 -> 6a | B49: ='Dashboard Production Quality'!B54 -> Water Volume Abstracted | C49: ='Dashboard Production Quality'!C54 -> M3 | E49: 14405 | F49: 14415 | G49: 14465 | H49: 14515 | I49: 14565 | J49: 14615 | K49: 14665 | L49: 14715 | M49: 14765 | N49: 14815 | O49: 14865 | P49: 14915
A50: ='Dashboard Production Quality'!A55 -> 6b | B50: ='Dashboard Production Quality'!B55 -> Water Volume Supplied | C50: ='Dashboard Production Quality'!C55 -> M3 | E50: =E49-E56 -> 14116.9 | F50: =F49-F56 -> 14126.7 | G50: =G49-G56 -> 14175.7 | H50: =H49-H56 -> 14224.7 | I50: =I49-I56 -> 14273.7 | J50: =J49-J56 -> 14322.7 | K50: =K49-K56 -> 14371.7 | L50: =L49-L56 -> 14420.7 | ... P50: =P49-P56 -> 14616.7
A51: ='Dashboard Production Quality'!A56 -> 6c | B51: ='Dashboard Production Quality'!B56 -> Power Grid | C51: ='Dashboard Production Quality'!C56 -> KWH | E51: 11029.5 | F51: 11029.5 | G51: 11029.5 | H51: 11029.5 | I51: 11029.5 | J51: 11029.5 | K51: 11029.5 | L51: 11029.5 | M51: 11029.5 | N51: 11029.5 | O51: 11029.5 | P51: 11029.5
A52: ='Dashboard Production Quality'!A57 -> 6d | B52: ='Dashboard Production Quality'!B57 -> Power Solar | C52: ='Dashboard Production Quality'!C57 -> KWH | E52: 3801.5022 | F52: 3801.5022 | G52: 3801.5022 | H52: 3801.5022 | I52: 3801.5022 | J52: 3801.5022 | K52: 3801.5022 | L52: 3801.5022 | M52: 3801.5022 | N52: 3801.5022 | O52: 3801.5022 | P52: 3801.5022
A53: ='Dashboard Production Quality'!A58 -> 6e | B53: ='Dashboard Production Quality'!B58 -> Total Power Consumption | C53: ='Dashboard Production Quality'!C58 -> KWH | E53: =E51+E52 -> 14831.002 | F53: =F51+F52 -> 14831.002 | G53: =G51+G52 -> 14831.002 | H53: =H51+H52 -> 14831.002 | I53: =I51+I52 -> 14831.002 | J53: =J51+J52 -> 14831.002 | K53: =K51+K52 -> 14831.002 | L53: =L51+L52 -> 14831.002 | ... P53: =P51+P52 -> 14831.002
A54: ='Dashboard Production Quality'!A59 -> 6f | B54: % Solar | C54: ='Dashboard Production Quality'!C59 -> % | E54: =E52/E53 -> 0.25632133 | F54: =F52/F53 -> 0.25632133 | G54: =G52/G53 -> 0.25632133 | H54: =H52/H53 -> 0.25632133 | I54: =I52/I53 -> 0.25632133 | J54: =J52/J53 -> 0.25632133 | K54: =K52/K53 -> 0.25632133 | L54: =L52/L53 -> 0.25632133 | ... P54: =P52/P53 -> 0.25632133
A55: ='Dashboard Production Quality'!A60 -> 6g | B55: ='Dashboard Production Quality'!B60 -> Power Efficiency | C55: ='Dashboard Production Quality'!C60 -> KWH/M3 | E55: =E53/E49 -> 1.0295732 | F55: =F53/F49 -> 1.028859 | G55: =G53/G49 -> 1.0253026 | H55: =H53/H49 -> 1.0217707 | I55: =I53/I49 -> 1.0182631 | J55: =J53/J49 -> 1.0147795 | K55: =K53/K49 -> 1.0113196 | L55: =L53/L49 -> 1.0078833 | ... P55: =P53/P49 -> 0.99436823
A56: ='Dashboard Production Quality'!A61 -> 6h | B56: ='Dashboard Production Quality'!B61 -> Production Loss | C56: ='Dashboard Production Quality'!C61 -> M3 | E56: =E49*$E$2 -> 288.1 | F56: =F49*$E$2 -> 288.3 | G56: =G49*$E$2 -> 289.3 | H56: =H49*$E$2 -> 290.3 | I56: =I49*$E$2 -> 291.3 | J56: =J49*$E$2 -> 292.3 | K56: =K49*$E$2 -> 293.3 | L56: =L49*$E$2 -> 294.3 | ... P56: =P49*$E$2 -> 298.3
A57: ='Dashboard Production Quality'!A62 -> 7 | B57: ='Dashboard Production Quality'!B62 -> MAI MAHIU PRODUCTION SITE | C57: ='Dashboard Production Quality'!C62 -> 0
A58: ='Dashboard Production Quality'!A63 -> 7a | B58: ='Dashboard Production Quality'!B63 -> Water Volume Abstracted | C58: ='Dashboard Production Quality'!C63 -> M3 | E58: 4500 | F58: 5000 | G58: 5500 | H58: 6000 | I58: 6500 | J58: 7000 | K58: 7500 | L58: 8000 | M58: 8500 | N58: 9000 | O58: 9500 | P58: 10000
A59: ='Dashboard Production Quality'!A64 -> 7b | B59: ='Dashboard Production Quality'!B64 -> Water Volume Supplied | C59: ='Dashboard Production Quality'!C64 -> M3 | E59: =E58-E62 -> 4410 | F59: =F58-F62 -> 4900 | G59: =G58-G62 -> 5390 | H59: =H58-H62 -> 5880 | I59: =I58-I62 -> 6370 | J59: =J58-J62 -> 6860 | K59: =K58-K62 -> 7350 | L59: =L58-L62 -> 7840 | ... P59: =P58-P62 -> 9800
A60: ='Dashboard Production Quality'!A65 -> 7c | B60: ='Dashboard Production Quality'!B65 -> Power Consumption | C60: ='Dashboard Production Quality'!C65 -> KWH | E60: 4108.8333 | F60: 4108.8333 | G60: 4108.8333 | H60: 4108.8333 | I60: 4108.8333 | J60: 4108.8333 | K60: 4108.8333 | L60: 4108.8333 | M60: 4108.8333 | N60: 4108.8333 | O60: 4108.8333 | P60: 4108.8333
A61: ='Dashboard Production Quality'!A66 -> 7d | B61: ='Dashboard Production Quality'!B66 -> Power Efficiency | C61: ='Dashboard Production Quality'!C66 -> KWH/M3 | E61: =E60/E58 -> 0.91307407 | F61: =F60/F58 -> 0.82176667 | G61: =G60/G58 -> 0.74706061 | H61: =H60/H58 -> 0.68480556 | I61: =I60/I58 -> 0.63212821 | J61: =J60/J58 -> 0.58697619 | K61: =K60/K58 -> 0.54784444 | L61: =L60/L58 -> 0.51360417 | ... P61: =P60/P58 -> 0.41088333
A62: ='Dashboard Production Quality'!A67 -> 7e | B62: ='Dashboard Production Quality'!B67 -> Production Loss | C62: ='Dashboard Production Quality'!C67 -> M3 | E62: =$E$2*E58 -> 90 | F62: =$E$2*F58 -> 100 | G62: =$E$2*G58 -> 110 | H62: =$E$2*H58 -> 120 | I62: =$E$2*I58 -> 130 | J62: =$E$2*J58 -> 140 | K62: =$E$2*K58 -> 150 | L62: =$E$2*L58 -> 160 | ... P62: =$E$2*P58 -> 200
A63: ='Dashboard Production Quality'!A68 -> 8 | B63: ='Dashboard Production Quality'!B68 -> MUCHIRINGIRI PRODUCTION SITE | C63: ='Dashboard Production Quality'!C68 -> 0
A64: ='Dashboard Production Quality'!A69 -> 8a | B64: ='Dashboard Production Quality'!B69 -> Water Volume Abstracted | C64: ='Dashboard Production Quality'!C69 -> M3 | E64: 0 | F64: 0 | G64: 0 | H64: 0 | I64: 0 | J64: 50 | K64: 50 | L64: 50 | M64: 50 | N64: 50 | O64: 50 | P64: 50
A65: ='Dashboard Production Quality'!A70 -> 8b | B65: ='Dashboard Production Quality'!B70 -> Water Volume Supplied | C65: ='Dashboard Production Quality'!C70 -> M3 | E65: =E64-E68 -> 0 | F65: =F64-F68 -> 0 | G65: =G64-G68 -> 0 | H65: =H64-H68 -> 0 | I65: =I64-I68 -> 0 | J65: =J64-J68 -> 49 | K65: =K64-K68 -> 49 | L65: =L64-L68 -> 49 | ... P65: =P64-P68 -> 49
A66: ='Dashboard Production Quality'!A71 -> 8c | B66: ='Dashboard Production Quality'!B71 -> Power Consumption | C66: ='Dashboard Production Quality'!C71 -> KWH
A67: ='Dashboard Production Quality'!A72 -> 8d | B67: ='Dashboard Production Quality'!B72 -> Power Efficiency | C67: ='Dashboard Production Quality'!C72 -> KWH/M3 | E67: =E66/E64 -> #DIV/0! | F67: =IFERROR(F66/F64,0) -> 0 | G67: =IFERROR(G66/G64,0) -> 0 | H67: =IFERROR(H66/H64,0) -> 0 | I67: =IFERROR(I66/I64,0) -> 0 | J67: =IFERROR(J66/J64,0) -> 0 | K67: =IFERROR(K66/K64,0) -> 0 | L67: =IFERROR(L66/L64,0) -> 0 | M67: =IFERROR(M66/M64,0) -> 0 | ... P67: =IFERROR(P66/P64,0) -> 0
A68: ='Dashboard Production Quality'!A73 -> 8e | B68: ='Dashboard Production Quality'!B73 -> Production Loss | C68: ='Dashboard Production Quality'!C73 -> M3 | E68: =$E$2*E64 -> 0 | F68: =$E$2*F64 -> 0 | G68: =$E$2*G64 -> 0 | H68: =$E$2*H64 -> 0 | I68: =$E$2*I64 -> 0 | J68: =$E$2*J64 -> 1 | K68: =$E$2*K64 -> 1 | L68: =$E$2*L64 -> 1 | ... P68: =$E$2*P64 -> 1
A69: ='Dashboard Production Quality'!A74 -> 9 | B69: ='Dashboard Production Quality'!B74 -> NGONDI | C69: ='Dashboard Production Quality'!C74 -> 0
A70: ='Dashboard Production Quality'!A75 -> 9a | B70: ='Dashboard Production Quality'!B75 -> Water Volume Abstracted | C70: ='Dashboard Production Quality'!C75 -> M3 | E70: 400 | F70: 450 | G70: 500 | H70: 550 | I70: 600 | J70: 650 | K70: 700 | L70: 750 | M70: 800 | N70: 850 | O70: 900 | P70: 950
A71: ='Dashboard Production Quality'!A76 -> 9b | B71: ='Dashboard Production Quality'!B76 -> Water Volume Supplied | C71: ='Dashboard Production Quality'!C76 -> M3 | E71: =E70-E74 -> 392 | F71: =F70-F74 -> 441 | G71: =G70-G74 -> 490 | H71: =H70-H74 -> 539 | I71: =I70-I74 -> 588 | J71: =J70-J74 -> 637 | K71: =K70-K74 -> 686 | L71: =L70-L74 -> 735 | ... P71: =P70-P74 -> 931
A72: ='Dashboard Production Quality'!A77 -> 9c | B72: ='Dashboard Production Quality'!B77 -> Power Solar | C72: ='Dashboard Production Quality'!C77 -> KWH
A73: ='Dashboard Production Quality'!A78 -> 9d | B73: ='Dashboard Production Quality'!B78 -> Power Efficiency | C73: ='Dashboard Production Quality'!C78 -> KWH/M3 | E73: =E72/E70 -> 0 | F73: =F72/F70 -> 0 | G73: =G72/G70 -> 0 | H73: =H72/H70 -> 0 | I73: =I72/I70 -> 0 | J73: =J72/J70 -> 0 | K73: =K72/K70 -> 0 | L73: =L72/L70 -> 0 | ... P73: =P72/P70 -> 0
A74: ='Dashboard Production Quality'!A79 -> 9e | B74: ='Dashboard Production Quality'!B79 -> Production Loss | C74: ='Dashboard Production Quality'!C79 -> M3 | E74: =$E$2*E70 -> 8 | F74: =$E$2*F70 -> 9 | G74: =$E$2*G70 -> 10 | H74: =$E$2*H70 -> 11 | I74: =$E$2*I70 -> 12 | J74: =$E$2*J70 -> 13 | K74: =$E$2*K70 -> 14 | L74: =$E$2*L70 -> 15 | ... P74: =$E$2*P70 -> 19
A75: ='Dashboard Production Quality'!A80 -> 10 | B75: ='Dashboard Production Quality'!B80 -> NYONJORO | C75: ='Dashboard Production Quality'!C80 -> 0
A76: ='Dashboard Production Quality'!A81 -> 10a | B76: ='Dashboard Production Quality'!B81 -> Water Volume Abstracted | C76: ='Dashboard Production Quality'!C81 -> M3 | E76: 280 | F76: 290 | G76: 300 | H76: 310 | I76: 320 | J76: 330 | K76: 340 | L76: 350 | M76: 360 | N76: 370 | O76: 380 | P76: 390
A77: ='Dashboard Production Quality'!A82 -> 10b | B77: ='Dashboard Production Quality'!B82 -> Water Volume Suplied | C77: ='Dashboard Production Quality'!C82 -> M3 | E77: =E76-E80 -> 274.4 | F77: =F76-F80 -> 284.2 | G77: =G76-G80 -> 294 | H77: =H76-H80 -> 303.8 | I77: =I76-I80 -> 313.6 | J77: =J76-J80 -> 323.4 | K77: =K76-K80 -> 333.2 | L77: =L76-L80 -> 343 | ... P77: =P76-P80 -> 382.2
A78: ='Dashboard Production Quality'!A83 -> 10c | B78: ='Dashboard Production Quality'!B83 -> Power Solar | C78: ='Dashboard Production Quality'!C83 -> KWH
A79: ='Dashboard Production Quality'!A84 -> 10d | B79: ='Dashboard Production Quality'!B84 -> Power Efficiency | C79: ='Dashboard Production Quality'!C84 -> KWH/M3 | E79: =E78/E76 -> 0 | F79: =F78/F76 -> 0 | G79: =G78/G76 -> 0 | H79: =H78/H76 -> 0 | I79: =I78/I76 -> 0 | J79: =J78/J76 -> 0 | K79: =K78/K76 -> 0 | L79: =L78/L76 -> 0 | ... P79: =P78/P76 -> 0
A80: ='Dashboard Production Quality'!A85 -> 10e | B80: ='Dashboard Production Quality'!B85 -> Production Loss | C80: ='Dashboard Production Quality'!C85 -> M3 | E80: =E76*$E$2 -> 5.6 | F80: =F76*$E$2 -> 5.8 | G80: =G76*$E$2 -> 6 | H80: =H76*$E$2 -> 6.2 | I80: =I76*$E$2 -> 6.4 | J80: =J76*$E$2 -> 6.6 | K80: =K76*$E$2 -> 6.8 | L80: =L76*$E$2 -> 7 | ... P80: =P76*$E$2 -> 7.8
A81: ='Dashboard Production Quality'!A89 -> 11 | B81: ='Dashboard Production Quality'!B89 -> KARATI POLICE POST | C81: ='Dashboard Production Quality'!C89 -> 0
A82: ='Dashboard Production Quality'!A90 -> 11a | B82: ='Dashboard Production Quality'!B90 -> Water Volume Abstracted | C82: ='Dashboard Production Quality'!C90 -> M3 | E82: 280 | F82: 300 | G82: 320 | H82: 340 | I82: 360 | J82: 380 | K82: 400 | L82: 420 | M82: 440 | N82: 460 | O82: 480 | P82: 500
A83: ='Dashboard Production Quality'!A91 -> 11b | B83: ='Dashboard Production Quality'!B91 -> Water Volume Supplied | C83: ='Dashboard Production Quality'!C91 -> M3 | E83: =E82-E86 -> 274.4 | F83: =F82-F86 -> 294 | G83: =G82-G86 -> 313.6 | H83: =H82-H86 -> 333.2 | I83: =I82-I86 -> 352.8 | J83: =J82-J86 -> 372.4 | K83: =K82-K86 -> 392 | L83: =L82-L86 -> 411.6 | ... P83: =P82-P86 -> 490
A84: ='Dashboard Production Quality'!A92 -> 11c | B84: ='Dashboard Production Quality'!B92 -> Power Consumption | C84: ='Dashboard Production Quality'!C92 -> KWH | E84: 525 | F84: 525 | G84: 525 | H84: 525 | I84: 525 | J84: 525 | K84: 525 | L84: 525 | M84: 525 | N84: 525 | O84: 525 | P84: 525
A85: ='Dashboard Production Quality'!A93 -> 11d | B85: ='Dashboard Production Quality'!B93 -> Power Efficiency | C85: ='Dashboard Production Quality'!C93 -> KWH/M3 | E85: =E84/E82 -> 1.875 | F85: =F84/F82 -> 1.75 | G85: =G84/G82 -> 1.640625 | H85: =H84/H82 -> 1.5441176 | I85: =I84/I82 -> 1.4583333 | J85: =J84/J82 -> 1.3815789 | K85: =K84/K82 -> 1.3125 | L85: =L84/L82 -> 1.25 | ... P85: =P84/P82 -> 1.05
A86: ='Dashboard Production Quality'!A94 -> 11e | B86: ='Dashboard Production Quality'!B94 -> Production Loss | C86: ='Dashboard Production Quality'!C94 -> M3 | E86: =E82*$E$2 -> 5.6 | F86: =F82*$E$2 -> 6 | G86: =G82*$E$2 -> 6.4 | H86: =H82*$E$2 -> 6.8 | I86: =I82*$E$2 -> 7.2 | J86: =J82*$E$2 -> 7.6 | K86: =K82*$E$2 -> 8 | L86: =L82*$E$2 -> 8.4 | ... P86: =P82*$E$2 -> 10
A87: ='Dashboard Production Quality'!A95 -> 12 | B87: ='Dashboard Production Quality'!B95 -> NIP | C87: ='Dashboard Production Quality'!C95 -> 0
A88: ='Dashboard Production Quality'!A96 -> 12a | B88: ='Dashboard Production Quality'!B96 -> Water Volume Abstracted | C88: ='Dashboard Production Quality'!C96 -> M3 | E88: 65000 | F88: 65000 | G88: 65000 | H88: 67000 | I88: 69000 | J88: 71000 | K88: 72000 | L88: 73000 | M88: 74000 | N88: 74000 | O88: 74000 | P88: 74500
A89: ='Dashboard Production Quality'!A97 -> 12b | B89: ='Dashboard Production Quality'!B97 -> Water Volume Supplied | C89: ='Dashboard Production Quality'!C97 -> M3 | E89: =E88-E92 -> 63700 | F89: =F88-F92 -> 63700 | G89: =G88-G92 -> 63700 | H89: =H88-H92 -> 65660 | I89: =I88-I92 -> 67620 | J89: =J88-J92 -> 69580 | K89: =K88-K92 -> 70560 | L89: =L88-L92 -> 71540 | ... P89: =P88-P92 -> 73010
A90: ='Dashboard Production Quality'!A98 -> 12c | B90: ='Dashboard Production Quality'!B98 -> Power Consumption | C90: ='Dashboard Production Quality'!C98 -> KWH | E90: 57804.667 | F90: 57804.667 | G90: 57804.667 | H90: 57804.667 | I90: 57804.667 | J90: 57804.667 | K90: 57804.667 | L90: 57804.667 | M90: 57804.667 | N90: 57804.667 | O90: 57804.667 | P90: 57804.667
A91: ='Dashboard Production Quality'!A99 -> 12d | B91: ='Dashboard Production Quality'!B99 -> Power Efficiency | C91: ='Dashboard Production Quality'!C99 -> KWH/M3 | E91: =E90/E88 -> 0.88930256 | F91: =F90/F88 -> 0.88930256 | G91: =G90/G88 -> 0.88930256 | H91: =H90/H88 -> 0.86275622 | I91: =I90/I88 -> 0.83774879 | J91: =J90/J88 -> 0.81415023 | K91: =K90/K88 -> 0.80284259 | L91: =L90/L88 -> 0.79184475 | ... P91: =P90/P88 -> 0.77590157
A92: ='Dashboard Production Quality'!A100 -> 12e | B92: ='Dashboard Production Quality'!B100 -> Production Loss | C92: ='Dashboard Production Quality'!C100 -> M3 | E92: =E88*$E$2 -> 1300 | F92: =F88*$E$2 -> 1300 | G92: =G88*$E$2 -> 1300 | H92: =H88*$E$2 -> 1340 | I92: =I88*$E$2 -> 1380 | J92: =J88*$E$2 -> 1420 | K92: =K88*$E$2 -> 1440 | L92: =L88*$E$2 -> 1460 | ... P92: =P88*$E$2 -> 1490
B93: ='Dashboard Production Quality'!B101 -> IHINDU | C93: ='Dashboard Production Quality'!C101 -> 0
A94: ='Dashboard Production Quality'!A102 -> 13a | B94: ='Dashboard Production Quality'!B102 -> Water Volume Abstracted | C94: ='Dashboard Production Quality'!C102 -> M3 | E94: 1400 | F94: 1500 | G94: 1600 | H94: 1700 | I94: 1800 | J94: 1900 | K94: 2000 | L94: 2100 | M94: 2200 | N94: 2300 | O94: 2400 | P94: 2500
A95: ='Dashboard Production Quality'!A103 -> 13b | B95: ='Dashboard Production Quality'!B103 -> Water Volume Supplied | C95: ='Dashboard Production Quality'!C103 -> M3 | E95: =E94-E98 -> 1372 | F95: =F94-F98 -> 1470 | G95: =G94-G98 -> 1568 | H95: =H94-H98 -> 1666 | I95: =I94-I98 -> 1764 | J95: =J94-J98 -> 1862 | K95: =K94-K98 -> 1960 | L95: =L94-L98 -> 2058 | ... P95: =P94-P98 -> 2450
A96: ='Dashboard Production Quality'!A104 -> 13c | B96: ='Dashboard Production Quality'!B104 -> Power Consumption | C96: ='Dashboard Production Quality'!C104 -> KWH | E96: 2250 | F96: 2250 | G96: 2250 | H96: 2250 | I96: 2250 | J96: 2250 | K96: 2250 | L96: 2250 | M96: 2250 | N96: 2250 | O96: 2250 | P96: 2250
A97: ='Dashboard Production Quality'!A105 -> 13d | B97: ='Dashboard Production Quality'!B105 -> Power Efficiency | C97: ='Dashboard Production Quality'!C105 -> KWH/M3 | E97: =E96/E94 -> 1.6071429 | F97: =F96/F94 -> 1.5 | G97: =G96/G94 -> 1.40625 | H97: =H96/H94 -> 1.3235294 | I97: =I96/I94 -> 1.25 | J97: =J96/J94 -> 1.1842105 | K97: =K96/K94 -> 1.125 | L97: =L96/L94 -> 1.0714286 | ... P97: =P96/P94 -> 0.9
A98: ='Dashboard Production Quality'!A106 -> 13e | B98: ='Dashboard Production Quality'!B106 -> Production Loss | C98: ='Dashboard Production Quality'!C106 -> M3 | E98: =E94*$E$2 -> 28 | F98: =F94*$E$2 -> 30 | G98: =G94*$E$2 -> 32 | H98: =H94*$E$2 -> 34 | I98: =I94*$E$2 -> 36 | J98: =J94*$E$2 -> 38 | K98: =K94*$E$2 -> 40 | L98: =L94*$E$2 -> 42 | ... P98: =P94*$E$2 -> 50
A99: ='Dashboard Production Quality'!A107 -> 14 | B99: ='Dashboard Production Quality'!B107 -> MANERA | C99: ='Dashboard Production Quality'!C107 -> 0
A100: ='Dashboard Production Quality'!A108 -> 14a | B100: ='Dashboard Production Quality'!B108 -> Water Volume Abstracted | C100: ='Dashboard Production Quality'!C108 -> M3
...

Sheet ACTUAL 2526
B1: ='Dashboard Production Quality'!B1 -> 0 | C1: ='Dashboard Production Quality'!C1 -> 0
C2: ='Dashboard Production Quality'!C2 -> 0
B3: ='Dashboard Production Quality'!B3 -> 0 | C3: ='Dashboard Production Quality'!C3 -> 0
A4: ='Dashboard Production Quality'!A4 -> 0 | C4: ='Dashboard Production Quality'!C4 -> Unit | D4: jul | E4: aug | F4: sep | G4: oct | H4: nov | I4: dec | J4: jan | K4: feb | L4: mar | M4: apr | N4: may | O4: jun
A5: ='Dashboard Production Quality'!A5 -> DASHBOARD - VOLUMES PRODUCED - NON-REVENUE WATER | B5: ='Dashboard Production Quality'!B5 -> 0 | C5: ='Dashboard Production Quality'!C5 -> 0
A6: ='Dashboard Production Quality'!A6 -> 1 | B6: ='Dashboard Production Quality'!B6 -> DTI PRODUCTION SITE | C6: ='Dashboard Production Quality'!C6 -> 0
A7: ='Dashboard Production Quality'!A7 -> 1a | B7: ='Dashboard Production Quality'!B7 -> Water Volume Abstracted | C7: ='Dashboard Production Quality'!C7 -> M3 | D7: 45093 | E7: 50272 | F7: 38210 | G7: 45521 | H7: 38240 | I7: 37291 | J7: 57214 | K7: 34037
A8: ='Dashboard Production Quality'!A8 -> 1b | B8: ='Dashboard Production Quality'!B8 -> Water Volume Supplied | C8: ='Dashboard Production Quality'!C8 -> M3 | D8: =D7-D14 -> 44015 | E8: =E7-E14 -> 47210 | F8: =F7-F14 -> 35022 | G8: =G7-G14 -> 42660 | H8: =H7-H14 -> 35997 | I8: =I7-I14 -> 35997 | J8: =J7-J14 -> 54214 | K8: =K7-K14 -> 32984 | ... O8: =O7-O14 -> 0
A9: ='Dashboard Production Quality'!A9 -> 1c | B9: ='Dashboard Production Quality'!B9 -> Power Grid | C9: ='Dashboard Production Quality'!C9 -> KWH | D9: 54776 | E9: 55447 | F9: 56659 | G9: 56802 | H9: 42378 | I9: 53153 | J9: 63824 | K9: 48514.887
A10: ='Dashboard Production Quality'!A10 -> 1d | B10: ='Dashboard Production Quality'!B10 -> Power Solar | C10: ='Dashboard Production Quality'!C10 -> KWH | D10: 12533.16 | E10: 8129 | F10: 9469 | G10: 10170 | H10: 14386 | I10: 15791 | J10: 15801 | K10: 9920
A11: ='Dashboard Production Quality'!A11 -> 1e | B11: ='Dashboard Production Quality'!B11 -> Total Power Consumption | C11: ='Dashboard Production Quality'!C11 -> KWH | D11: =D9+D10 -> 67309.16 | E11: =E9+E10 -> 63576 | F11: =F9+F10 -> 66128 | G11: =G9+G10 -> 66972 | H11: =H9+H10 -> 56764 | I11: =I9+I10 -> 68944 | J11: =J9+J10 -> 79625 | K11: =K9+K10 -> 58434.887 | ... O11: =O9+O10 -> 0
A12: ='Dashboard Production Quality'!A12 -> 1f | B12: ='Dashboard Production Quality'!B12 -> % Solar | C12: ='Dashboard Production Quality'!C12 -> % | D12: =D10/D11 -> 0.18620289 | E12: =E10/E11 -> 0.12786272 | F12: =F10/F11 -> 0.14319199 | G12: =G10/G11 -> 0.15185451 | H12: =H10/H11 -> 0.25343528 | I12: =I10/I11 -> 0.22904096 | J12: =J10/J11 -> 0.1984427 | K12: =K10/K11 -> 0.1697616 | ... O12: =O10/O11 -> #DIV/0!
A13: ='Dashboard Production Quality'!A13 -> 1g | B13: ='Dashboard Production Quality'!B13 -> Power Efficiency | C13: ='Dashboard Production Quality'!C13 -> KWH/M3 | D13: =D11/D7 -> 1.4926743 | E13: =E11/E7 -> 1.2646404 | F13: =F11/F7 -> 1.7306464 | G13: =G11/G7 -> 1.4712331 | H13: =H11/H7 -> 1.4844142 | I13: =I11/I7 -> 1.8488107 | J13: =J11/J7 -> 1.3917048 | K13: =K11/K7 -> 1.7168049 | ... O13: =O11/O7 -> #DIV/0!
A14: ='Dashboard Production Quality'!A14 -> 1h | B14: ='Dashboard Production Quality'!B14 -> Production Loss | C14: ='Dashboard Production Quality'!C14 -> M3 | D14: 1078 | E14: 3062 | F14: 3188 | G14: 2861 | H14: 2243 | I14: 1294 | J14: 3000 | K14: 1053
A15: ='Dashboard Production Quality'!A16 -> 2 | B15: ='Dashboard Production Quality'!B16 -> WATERWORKS PRODUCTION SITE | C15: ='Dashboard Production Quality'!C16 -> 0
A16: ='Dashboard Production Quality'!A17 -> 2a | B16: ='Dashboard Production Quality'!B17 -> Water Volume Abstracted | C16: ='Dashboard Production Quality'!C17 -> M3 | D16: 19269 | E16: 21454 | F16: 20216 | G16: 24029 | H16: 18217 | I16: 17440 | J16: 26843 | K16: 28759
A17: ='Dashboard Production Quality'!A18 -> 2b | B17: ='Dashboard Production Quality'!B18 -> Water Volume Supplied | C17: ='Dashboard Production Quality'!C18 -> M3 | D17: =D16-D23 -> 17644 | E17: =E16-E23 -> 19463 | F17: =F16-F23 -> 19420.1 | G17: =G16-G23 -> 23533 | H17: =H16-H23 -> 16578 | I17: =I16-I23 -> 16578 | J17: =J16-J23 -> 24181 | K17: =K16-K23 -> 26797 | ... O17: =O16-O23 -> 0
