Workbook
Name Actual_month: General!$B$3

Sheet Dashboard
A1: SALES & CC DASHBOARD
B2: =INDEX('KPI 1'!$E18:$P18,Actual_month) -> 46054
D3: Monthly | J3: Cumulative | R3: 0.9
C4: Unit | G4: Target | H4: Actual | I4: % real. | M4: Target | N4: Actual | O4: % real.
A5: NEW CONNECTIONS WATER | Q5: monthly | R5: cumluative
A6: 1 | B6: CBD - NEW WATER | C6: No. | D6: l | E6: l | F6: l | G6: =IFERROR(INDEX('KPI 1'!E$19:P$19,Actual_month),) -> 1 | H6: =IFERROR(INDEX('KPI 1'!$E$20:$P$20,Actual_month),) -> 0 | I6: =IFERROR(H6/G6,"") -> 0 | J6: l | K6: l | L6: l | M6: =IFERROR(INDEX('KPI 1'!$E$26:$P$26,Actual_month),) -> 8 | N6: =IFERROR(INDEX('KPI 1'!$E$27:$P$27,Actual_month),) -> 2 | O6: =IFERROR(N6/M6,"") -> 0.25 | P6: details | Q6: =G6*$R$3 -> 0.9 | R6: =M6*$R$3 -> 7.2 | S6: H | T6: v
A7: 2 | B7: CCCR- NEW WATER | C7: No. | D7: l | E7: l | F7: l | G7: =IFERROR(INDEX('KPI 2'!E$19:P$19,Actual_month),) -> 10 | H7: =IFERROR(INDEX('KPI 2'!$E$20:$P$20,Actual_month),) -> 3 | I7: =IFERROR(H7/G7,"") -> 0.3 | J7: l | K7: l | L7: l | M7: =IFERROR(INDEX('KPI 2'!$E$26:$P$26,Actual_month),) -> 79 | N7: =IFERROR(INDEX('KPI 2'!$E$27:$P$27,Actual_month),) -> 20 | O7: =IFERROR(N7/M7,"") -> 0.25316456 | P7: details | Q7: =G7*$R$3 -> 9 | R7: =M7*$R$3 -> 71.1 | S7: H | T7: v
A8: 3 | B8: KABATI- NEW WATER | C8: No. | D8: l | E8: l | F8: l | G8: =IFERROR(INDEX('KPI 3'!E$19:P$19,Actual_month),) -> 4 | H8: =IFERROR(INDEX('KPI 3'!$E$20:$P$20,Actual_month),) -> 0 | I8: =IFERROR(H8/G8,"") -> 0 | J8: l | K8: l | L8: l | M8: =IFERROR(INDEX('KPI 3'!$E$26:$P$26,Actual_month),) -> 32 | N8: =IFERROR(INDEX('KPI 3'!$E$27:$P$27,Actual_month),) -> 10 | O8: =IFERROR(N8/M8,"") -> 0.3125 | P8: details | Q8: =G8*$R$3 -> 3.6 | R8: =M8*$R$3 -> 28.8 | S8: H | T8: v
A9: 4 | B9: SITE- NEW WATER | C9: No. | D9: l | E9: l | F9: l | G9: =IFERROR(INDEX('KPI 4'!E$19:P$19,Actual_month),) -> 1 | H9: =IFERROR(INDEX('KPI 4'!$E$20:$P$20,Actual_month),) -> 0 | I9: =IFERROR(H9/G9,"") -> 0 | J9: l | K9: l | L9: l | M9: =IFERROR(INDEX('KPI 4'!$E$26:$P$26,Actual_month),) -> 8 | N9: =IFERROR(INDEX('KPI 4'!$E$27:$P$27,Actual_month),) -> 7 | O9: =IFERROR(N9/M9,"") -> 0.875 | P9: details | Q9: =G9*$R$3 -> 0.9 | R9: =M9*$R$3 -> 7.2 | S9: H | T9: v
A10: 5 | B10: KIHOTO- NEW WATER | C10: No. | D10: l | E10: l | F10: l | G10: =IFERROR(INDEX('KPI 5'!E$19:P$19,Actual_month),) -> 1 | H10: =IFERROR(INDEX('KPI 5'!$E$20:$P$20,Actual_month),) -> 1 | I10: =IFERROR(H10/G10,"") -> 1 | J10: l | K10: l | L10: l | M10: =IFERROR(INDEX('KPI 5'!$E$26:$P$26,Actual_month),) -> 8 | N10: =IFERROR(INDEX('KPI 5'!$E$27:$P$27,Actual_month),) -> 3 | O10: =IFERROR(N10/M10,"") -> 0.375 | P10: details | Q10: =G10*$R$3 -> 0.9 | R10: =M10*$R$3 -> 7.2 | S10: H | T10: v
A11: 6 | B11: LAKEVIEW- NEW WATER | C11: No. | D11: l | E11: l | F11: l | G11: =IFERROR(INDEX('KPI 10'!E$19:P$19,Actual_month),) -> 2 | H11: =IFERROR(INDEX('KPI 10'!$E$20:$P$20,Actual_month),) -> 0 | I11: =IFERROR(H11/G11,"") -> 0 | J11: l | K11: l | L11: l | M11: =IFERROR(INDEX('KPI 10'!$E$26:$P$26,Actual_month),) -> 16 | N11: =IFERROR(INDEX('KPI 10'!$E$27:$P$27,Actual_month),) -> 14 | O11: =IFERROR(N11/M11,"") -> 0.875 | P11: details | Q11: =G11*$R$3 -> 1.8 | R11: =M11*$R$3 -> 14.4 | S11: H | T11: v
A12: 7 | B12: HOPEWELL- NEW WATER | C12: No. | D12: l | E12: l | F12: l | G12: =IFERROR(INDEX('KPI 10A'!E$19:P$19,Actual_month),) -> 2 | H12: =IFERROR(INDEX('KPI 10A'!$E$20:$P$20,Actual_month),) -> 3 | I12: =IFERROR(H12/G12,"") -> 1.5 | J12: l | K12: l | L12: l | M12: =IFERROR(INDEX('KPI 10A'!$E$26:$P$26,Actual_month),) -> 16 | N12: =IFERROR(INDEX('KPI 10A'!$E$27:$P$27,Actual_month),) -> 53 | O12: =IFERROR(N12/M12,"") -> 3.3125 | P12: details | Q12: =G12*$R$3 -> 1.8 | R12: =M12*$R$3 -> 14.4 | S12: H | T12: v
B13: TOTAL NEW WATER CONNECTIONS CENTRAL REGION | C13: No. | D13: l | E13: l | F13: l | G13: =IFERROR(INDEX('KPI 6'!E$19:P$19,Actual_month),) -> 21 | H13: =IFERROR(INDEX('KPI 6'!$E$20:$P$20,Actual_month),) -> 7 | I13: =IFERROR(H13/G13,"") -> 0.33333333 | J13: l | K13: l | L13: l | M13: =IFERROR(INDEX('KPI 6'!$E$26:$P$26,Actual_month),) -> 167 | N13: =IFERROR(INDEX('KPI 6'!$E$27:$P$27,Actual_month),) -> 109 | O13: =IFERROR(N13/M13,"") -> 0.65269461 | P13: details | Q13: =G13*$R$3 -> 18.9 | R13: =M13*$R$3 -> 150.3 | S13: H | T13: v
A14: 1 | B14: HELLSGATE- NEW WATER | C14: No. | D14: l | E14: l | F14: l | G14: =IFERROR(INDEX('KPI 7'!E$19:P$19,Actual_month),) -> 45 | H14: =IFERROR(INDEX('KPI 7'!$E$20:$P$20,Actual_month),) -> 14 | I14: =IFERROR(H14/G14,"") -> 0.31111111 | J14: l | K14: l | L14: l | M14: =IFERROR(INDEX('KPI 7'!$E$26:$P$26,Actual_month),) -> 276 | N14: =IFERROR(INDEX('KPI 7'!$E$27:$P$27,Actual_month),) -> 147 | O14: =IFERROR(N14/M14,"") -> 0.5326087 | P14: details | Q14: =G14*$R$3 -> 40.5 | R14: =M14*$R$3 -> 248.4 | S14: H | T14: v
A15: 2 | B15: KAMERE- NEW WATER | C15: No. | D15: l | E15: l | F15: l | G15: =IFERROR(INDEX('KPI 8'!E$19:P$19,Actual_month),) -> 11 | H15: =IFERROR(INDEX('KPI 8'!$E$20:$P$20,Actual_month),) -> 14 | I15: =IFERROR(H15/G15,"") -> 1.2727273 | J15: l | K15: l | L15: l | M15: =IFERROR(INDEX('KPI 8'!$E$26:$P$26,Actual_month),) -> 68 | N15: =IFERROR(INDEX('KPI 8'!$E$27:$P$27,Actual_month),) -> 147 | O15: =IFERROR(N15/M15,"") -> 2.1617647 | P15: details | Q15: =G15*$R$3 -> 9.9 | R15: =M15*$R$3 -> 61.2 | S15: H | T15: v
A16: 3 | B16: MAI-MAHIU- NEW WATER | C16: No. | D16: l | E16: l | F16: l | G16: =IFERROR(INDEX('KPI 11'!E$19:P$19,Actual_month),) -> 61 | H16: =IFERROR(INDEX('KPI 11'!$E$20:$P$20,Actual_month),) -> 33 | I16: =IFERROR(H16/G16,"") -> 0.54098361 | J16: l | K16: l | L16: l | M16: =IFERROR(INDEX('KPI 11'!$E$26:$P$26,Actual_month),) -> 478 | N16: =IFERROR(INDEX('KPI 11'!$E$27:$P$27,Actual_month),) -> 384 | O16: =IFERROR(N16/M16,"") -> 0.80334728 | P16: details | Q16: =G16*$R$3 -> 54.9 | R16: =M16*$R$3 -> 430.2 | S16: H | T16: v
A17: 4 | B17: LONGONOT- NEW WATER | C17: No. | D17: l | E17: l | F17: l | G17: =IFERROR(INDEX('KPI 11B'!E$19:P$19,Actual_month),) -> 10 | H17: =IFERROR(INDEX('KPI 11B'!$E$20:$P$20,Actual_month),) -> 2 | I17: =IFERROR(H17/G17,"") -> 0.2 | J17: l | K17: l | L17: l | M17: =IFERROR(INDEX('KPI 11B'!$E$26:$P$26,Actual_month),) -> 80 | N17: =IFERROR(INDEX('KPI 11B'!$E$27:$P$27,Actual_month),) -> 71 | O17: =IFERROR(N17/M17,"") -> 0.8875 | P17: details | Q17: =G17*$R$3 -> 9 | R17: =M17*$R$3 -> 72 | S17: H | T17: v
B18: TOTAL NEW WATER CONNECTION SOUTHERN REGION | C18: No. | D18: l | E18: l | F18: l | G18: =IFERROR(INDEX('KPI 12'!E$19:P$19,Actual_month),) -> 127 | H18: =IFERROR(INDEX('KPI 12'!$E$20:$P$20,Actual_month),) -> 51 | I18: =IFERROR(H18/G18,"") -> 0.4015748 | J18: l | K18: l | L18: l | M18: =IFERROR(INDEX('KPI 12'!$E$26:$P$26,Actual_month),) -> 902 | N18: =IFERROR(INDEX('KPI 12'!$E$27:$P$27,Actual_month),) -> 646 | O18: =IFERROR(N18/M18,"") -> 0.71618625 | P18: details | Q18: =G18*$R$3 -> 114.3 | R18: =M18*$R$3 -> 811.8 | S18: H | T18: v
A19: EASTERN REGION | Q19: monthly | R19: cumluative
A20: 1 | B20: KAYOLE- NEW WATER | C20: No. | D20: l | E20: l | F20: l | G20: =IFERROR(INDEX('KPI 9'!E$19:P$19,Actual_month),) -> 23 | H20: =IFERROR(INDEX('KPI 9'!$E$20:$P$20,Actual_month),) -> 17 | I20: =IFERROR(H20/G20,"") -> 0.73913043 | J20: l | K20: l | L20: l | M20: =IFERROR(INDEX('KPI 9'!$E$26:$P$26,Actual_month),) -> 184 | N20: =IFERROR(INDEX('KPI 9'!$E$27:$P$27,Actual_month),) -> 270 | O20: =IFERROR(N20/M20,"") -> 1.4673913 | P20: details | Q20: =G20*$R$3 -> 20.7 | R20: =M20*$R$3 -> 165.6 | S20: H | T20: v
A21: 2 | B21: IHINDU- NEW WATER | C21: No. | D21: l | E21: l | F21: l | G21: =IFERROR(INDEX('KPI 9B'!E$19:P$19,Actual_month),) -> 18 | H21: =IFERROR(INDEX('KPI 9B'!$E$20:$P$20,Actual_month),) -> 0 | I21: =IFERROR(H21/G21,"") -> 0 | J21: l | K21: l | L21: l | M21: =IFERROR(INDEX('KPI 9B'!$E$26:$P$26,Actual_month),) -> 229 | N21: =IFERROR(INDEX('KPI 9B'!$E$27:$P$27,Actual_month),) -> 4 | O21: =IFERROR(N21/M21,"") -> 0.017467249 | P21: details | Q21: =G21*$R$3 -> 16.2 | R21: =M21*$R$3 -> 206.1 | S21: H | T21: v
B22: TOTAL NEW W CONNECTION EASTERN REGION | C22: No. | D22: l | E22: l | F22: l | G22: =IFERROR(INDEX('KPI 12B'!E$19:P$19,Actual_month),) -> 41 | H22: =IFERROR(INDEX('KPI 12B'!$E$20:$P$20,Actual_month),) -> 17 | I22: =IFERROR(H22/G22,"") -> 0.41463415 | J22: l | K22: l | L22: l | M22: =IFERROR(INDEX('KPI 12B'!$E$26:$P$26,Actual_month),) -> 413 | N22: =IFERROR(INDEX('KPI 12B'!$E$27:$P$27,Actual_month),) -> 274 | O22: =IFERROR(N22/M22,"") -> 0.66343826 | P22: details | Q22: =G22*$R$3 -> 36.9 | R22: =M22*$R$3 -> 371.7 | S22: H | T22: v
A23: NEW CONNECTIONS SEWER | Q23: monthly | R23: cumluative
A24: 1 | B24: CBD- NEW SEWER | C24: No. | D24: l | E24: l | F24: l | G24: =IFERROR(INDEX('KPI 13'!E$19:P$19,Actual_month),) -> 1 | H24: =IFERROR(INDEX('KPI 13'!$E$20:$P$20,Actual_month),) -> 0 | I24: =IFERROR(H24/G24,"") -> 0 | J24: l | K24: l | L24: l | M24: =IFERROR(INDEX('KPI 13'!$E$26:$P$26,Actual_month),) -> 8 | N24: =IFERROR(INDEX('KPI 13'!$E$27:$P$27,Actual_month),) -> 0 | O24: =IFERROR(N24/M24,"") -> 0 | P24: details | Q24: =G24*$R$3 -> 0.9 | R24: =M24*$R$3 -> 7.2 | S24: H | T24: v
A25: 2 | B25: CCCR- NEW SEWER | C25: No. | D25: l | E25: l | F25: l | G25: =IFERROR(INDEX('KPI 14'!E$19:P$19,Actual_month),) -> 7 | H25: =IFERROR(INDEX('KPI 14'!$E$20:$P$20,Actual_month),) -> 2 | I25: =IFERROR(H25/G25,"") -> 0.28571429 | J25: l | K25: l | L25: l | M25: =IFERROR(INDEX('KPI 14'!$E$26:$P$26,Actual_month),) -> 56 | N25: =IFERROR(INDEX('KPI 14'!$E$27:$P$27,Actual_month),) -> 5 | O25: =IFERROR(N25/M25,"") -> 0.089285714 | P25: details | Q25: =G25*$R$3 -> 6.3 | R25: =M25*$R$3 -> 50.4 | S25: H | T25: v
A26: 3 | B26: KABATI- NEW SEWER | C26: No. | D26: l | E26: l | F26: l | G26: =IFERROR(INDEX('KPI 15'!E$19:P$19,Actual_month),) -> 3 | H26: =IFERROR(INDEX('KPI 15'!$E$20:$P$20,Actual_month),) -> 1 | I26: =IFERROR(H26/G26,"") -> 0.33333333 | J26: l | K26: l | L26: l | M26: =IFERROR(INDEX('KPI 15'!$E$26:$P$26,Actual_month),) -> 25 | N26: =IFERROR(INDEX('KPI 15'!$E$27:$P$27,Actual_month),) -> 6 | O26: =IFERROR(N26/M26,"") -> 0.24 | P26: details | Q26: =G26*$R$3 -> 2.7 | R26: =M26*$R$3 -> 22.5 | S26: H | T26: v
A27: 4 | B27: SITE- NEW SEWER | C27: No. | D27: l | E27: l | F27: l | G27: =IFERROR(INDEX('KPI 16'!E$19:P$19,Actual_month),) -> 1 | H27: =IFERROR(INDEX('KPI 16'!$E$20:$P$20,Actual_month),) -> 0 | I27: =IFERROR(H27/G27,"") -> 0 | J27: l | K27: l | L27: l | M27: =IFERROR(INDEX('KPI 16'!$E$26:$P$26,Actual_month),) -> 8 | N27: =IFERROR(INDEX('KPI 16'!$E$27:$P$27,Actual_month),) -> 1 | O27: =IFERROR(N27/M27,"") -> 0.125 | P27: details | Q27: =G27*$R$3 -> 0.9 | R27: =M27*$R$3 -> 7.2 | S27: H | T27: v
A28: 5 | B28: KIHOTO- NEW SEWER | C28: No. | D28: l | E28: l | F28: l | G28: =IFERROR(INDEX('KPI 17'!E$19:P$19,Actual_month),) -> 0 | H28: =IFERROR(INDEX('KPI 17'!$E$20:$P$20,Actual_month),) -> 0 | I28: =IFERROR(H28/G28,"") | J28: l | K28: l | L28: l | M28: =IFERROR(INDEX('KPI 17'!$E$26:$P$26,Actual_month),) -> 0 | N28: =IFERROR(INDEX('KPI 17'!$E$27:$P$27,Actual_month),) -> 0 | O28: =IFERROR(N28/M28,"") | P28: details | Q28: =G28*$R$3 -> 0 | R28: =M28*$R$3 -> 0 | S28: H | T28: v
A29: 6 | B29: LAKEVIEW- NEW SEWER | C29: No. | D29: l | E29: l | F29: l | G29: =IFERROR(INDEX('KPI 22'!E$19:P$19,Actual_month),) -> 1 | H29: =IFERROR(INDEX('KPI 22'!$E$20:$P$20,Actual_month),) -> 0 | I29: =IFERROR(H29/G29,"") -> 0 | J29: l | K29: l | L29: l | M29: =IFERROR(INDEX('KPI 22'!$E$26:$P$26,Actual_month),) -> 8 | N29: =IFERROR(INDEX('KPI 22'!$E$27:$P$27,Actual_month),) -> 3 | O29: =IFERROR(N29/M29,"") -> 0.375 | P29: details | Q29: =G29*$R$3 -> 0.9 | R29: =M29*$R$3 -> 7.2 | S29: H | T29: v
A30: 7 | B30: HOPEWELL- NEW SEWER | C30: No. | D30: l | E30: l | F30: l | G30: =IFERROR(INDEX('KPI 22A'!E$19:P$19,Actual_month),) -> 0 | H30: =IFERROR(INDEX('KPI 22A'!$E$20:$P$20,Actual_month),) -> 0 | I30: =IFERROR(H30/G30,"") | J30: l | K30: l | L30: l | M30: =IFERROR(INDEX('KPI 22A'!$E$26:$P$26,Actual_month),) -> 0 | N30: =IFERROR(INDEX('KPI 22A'!$E$27:$P$27,Actual_month),) -> 0 | O30: =IFERROR(N30/M30,"") | P30: details | Q30: =G30*$R$3 -> 0 | R30: =M30*$R$3 -> 0 | S30: H | T30: v
B31: TOTAL NEW SEWER CONNECTIONS CENTRAL REGION | C31: No. | D31: l | E31: l | F31: l | G31: =IFERROR(INDEX('KPI 18'!E$19:P$19,Actual_month),) -> 13 | H31: =IFERROR(INDEX('KPI 18'!$E$20:$P$20,Actual_month),) -> 3 | I31: =IFERROR(H31/G31,"") -> 0.23076923 | J31: l | K31: l | L31: l | M31: =IFERROR(INDEX('KPI 18'!$E$26:$P$26,Actual_month),) -> 105 | N31: =IFERROR(INDEX('KPI 18'!$E$27:$P$27,Actual_month),) -> 15 | O31: =IFERROR(N31/M31,"") -> 0.14285714 | P31: details | Q31: =G31*$R$3 -> 11.7 | R31: =M31*$R$3 -> 94.5 | S31: H | T31: v
A32: 1 | B32: HELLSGATE- NEW SEWER | C32: No. | D32: l | E32: l | F32: l | G32: =IFERROR(INDEX('KPI 19'!E$19:P$19,Actual_month),) -> 0 | H32: =IFERROR(INDEX('KPI 19'!$E$20:$P$20,Actual_month),) -> 0 | I32: =IFERROR(H32/G32,"") | J32: l | K32: l | L32: l | M32: =IFERROR(INDEX('KPI 19'!$E$26:$P$26,Actual_month),) -> 0 | N32: =IFERROR(INDEX('KPI 19'!$E$27:$P$27,Actual_month),) -> 0 | O32: =IFERROR(N32/M32,"") | P32: details | Q32: =G32*$R$3 -> 0 | R32: =M32*$R$3 -> 0 | S32: H | T32: v
A33: 2 | B33: KAMERE- NEW SEWER | C33: No. | D33: l | E33: l | F33: l | G33: =IFERROR(INDEX('KPI 20'!E$19:P$19,Actual_month),) -> 0 | H33: =IFERROR(INDEX('KPI 20'!$E$20:$P$20,Actual_month),) -> 0 | I33: =IFERROR(H33/G33,"") | J33: l | K33: l | L33: l | M33: =IFERROR(INDEX('KPI 20'!$E$26:$P$26,Actual_month),) -> 0 | N33: =IFERROR(INDEX('KPI 20'!$E$27:$P$27,Actual_month),) -> 0 | O33: =IFERROR(N33/M33,"") | P33: details | Q33: =G33*$R$3 -> 0 | R33: =M33*$R$3 -> 0 | S33: H | T33: v
A34: 3 | B34: MAI-MAHIU- NEW SEWER | C34: No. | D34: l | E34: l | F34: l | G34: =IFERROR(INDEX('KPI 23'!E$19:P$19,Actual_month),) -> 0 | H34: =IFERROR(INDEX('KPI 23'!$E$20:$P$20,Actual_month),) -> 0 | I34: =IFERROR(H34/G34,"") | J34: l | K34: l | L34: l | M34: =IFERROR(INDEX('KPI 23'!$E$26:$P$26,Actual_month),) -> 0 | N34: =IFERROR(INDEX('KPI 23'!$E$27:$P$27,Actual_month),) -> 0 | O34: =IFERROR(N34/M34,"") | P34: details | Q34: =G34*$R$3 -> 0 | R34: =M34*$R$3 -> 0 | S34: H | T34: v
B35: TOTAL NEW S CONNECTION SOUTHERN REGION | C35: No. | D35: l | E35: l | F35: l | G35: =IFERROR(INDEX('KPI 24'!E$19:P$19,Actual_month),) -> 0 | H35: =IFERROR(INDEX('KPI 24'!$E$20:$P$20,Actual_month),) -> 0 | I35: =IFERROR(H35/G35,"") | J35: l | K35: l | L35: l | M35: =IFERROR(INDEX('KPI 24'!$E$26:$P$26,Actual_month),) -> 0 | N35: =IFERROR(INDEX('KPI 24'!$E$27:$P$27,Actual_month),) -> 0 | O35: =IFERROR(N35/M35,"") | P35: details | Q35: =G35*$R$3 -> 0 | R35: =M35*$R$3 -> 0 | S35: H | T35: v
A36: EASTERN REGION | Q36: monthly | R36: cumluative
A37: 1 | B37: KAYOLE- NEW SEWER | C37: No. | D37: l | E37: l | F37: l | G37: =IFERROR(INDEX('KPI 21'!E$19:P$19,Actual_month),) -> 1 | H37: =IFERROR(INDEX('KPI 21'!$E$20:$P$20,Actual_month),) -> 2 | I37: =IFERROR(H37/G37,"") -> 2 | J37: l | K37: l | L37: l | M37: =IFERROR(INDEX('KPI 21'!$E$26:$P$26,Actual_month),) -> 8 | N37: =IFERROR(INDEX('KPI 21'!$E$27:$P$27,Actual_month),) -> 10 | O37: =IFERROR(N37/M37,"") -> 1.25 | P37: details | Q37: =G37*$R$3 -> 0.9 | R37: =M37*$R$3 -> 7.2 | S37: H | T37: v
A38: TOTAL CONNECTIONS-WATER | Q38: monthly | R38: cumluative
A39: 1 | B39: CBD- WATER | C39: No. | D39: l | E39: l | F39: l | G39: =IFERROR(INDEX('KPI 25'!E$19:P$19,Actual_month),) -> 798 | H39: =IFERROR(INDEX('KPI 25'!$E$20:$P$20,Actual_month),) -> 792 | I39: =IFERROR(H39/G39,"") -> 0.9924812 | J39: l | K39: l | L39: l | M39: =IFERROR(INDEX('KPI 25'!$E$26:$P$26,Actual_month),) -> 798 | N39: =IFERROR(INDEX('KPI 25'!$E$27:$P$27,Actual_month),) -> 792 | O39: =IFERROR(N39/M39,"") -> 0.9924812 | P39: details | Q39: =G39*$R$3 -> 718.2 | R39: =M39*$R$3 -> 718.2 | S39: H | T39: v
A40: 2 | B40: CCCR- WATER | C40: No. | D40: l | E40: l | F40: l | G40: =IFERROR(INDEX('KPI 26'!E$19:P$19,Actual_month),) -> 959 | H40: =IFERROR(INDEX('KPI 26'!$E$20:$P$20,Actual_month),) -> 898 | I40: =IFERROR(H40/G40,"") -> 0.93639208 | J40: l | K40: l | L40: l | M40: =IFERROR(INDEX('KPI 26'!$E$26:$P$26,Actual_month),) -> 959 | N40: =IFERROR(INDEX('KPI 26'!$E$27:$P$27,Actual_month),) -> 898 | O40: =IFERROR(N40/M40,"") -> 0.93639208 | P40: details | Q40: =G40*$R$3 -> 863.1 | R40: =M40*$R$3 -> 863.1 | S40: H | T40: v
A41: 3 | B41: KABATI- WATER | C41: No. | D41: l | E41: l | F41: l | G41: =IFERROR(INDEX('KPI 27'!E$19:P$19,Actual_month),) -> 985 | H41: =IFERROR(INDEX('KPI 27'!$E$20:$P$20,Actual_month),) -> 959 | I41: =IFERROR(H41/G41,"") -> 0.97360406 | J41: l | K41: l | L41: l | M41: =IFERROR(INDEX('KPI 27'!$E$26:$P$26,Actual_month),) -> 985 | N41: =IFERROR(INDEX('KPI 27'!$E$27:$P$27,Actual_month),) -> 959 | O41: =IFERROR(N41/M41,"") -> 0.97360406 | P41: details | Q41: =G41*$R$3 -> 886.5 | R41: =M41*$R$3 -> 886.5 | S41: H | T41: v
A42: 4 | B42: SITE- WATER | C42: No. | D42: l | E42: l | F42: l | G42: =IFERROR(INDEX('KPI 28'!E$19:P$19,Actual_month),) -> 947 | H42: =IFERROR(INDEX('KPI 28'!$E$20:$P$20,Actual_month),) -> 944 | I42: =IFERROR(H42/G42,"") -> 0.9968321 | J42: l | K42: l | L42: l | M42: =IFERROR(INDEX('KPI 28'!$E$26:$P$26,Actual_month),) -> 947 | N42: =IFERROR(INDEX('KPI 28'!$E$27:$P$27,Actual_month),) -> 944 | O42: =IFERROR(N42/M42,"") -> 0.9968321 | P42: details | Q42: =G42*$R$3 -> 852.3 | R42: =M42*$R$3 -> 852.3 | S42: H | T42: v
A43: 5 | B43: KIHOTO- WATER | C43: No. | D43: l | E43: l | F43: l | G43: =IFERROR(INDEX('KPI 29'!E$19:P$19,Actual_month),) -> 227 | H43: =IFERROR(INDEX('KPI 29'!$E$20:$P$20,Actual_month),) -> 222 | I43: =IFERROR(H43/G43,"") -> 0.97797357 | J43: l | K43: l | L43: l | M43: =IFERROR(INDEX('KPI 29'!$E$26:$P$26,Actual_month),) -> 227 | N43: =IFERROR(INDEX('KPI 29'!$E$27:$P$27,Actual_month),) -> 222 | O43: =IFERROR(N43/M43,"") -> 0.97797357 | P43: details | Q43: =G43*$R$3 -> 204.3 | R43: =M43*$R$3 -> 204.3 | S43: H | T43: v
A44: 6 | B44: LAKEVIEW- WATER | C44: No. | D44: l | E44: l | F44: l | G44: =IFERROR(INDEX('KPI 34'!E$19:P$19,Actual_month),) -> 1168 | H44: =IFERROR(INDEX('KPI 34'!$E$20:$P$20,Actual_month),) -> 1168 | I44: =IFERROR(H44/G44,"") -> 1 | J44: l | K44: l | L44: l | M44: =IFERROR(INDEX('KPI 34'!$E$26:$P$26,Actual_month),) -> 1168 | N44: =IFERROR(INDEX('KPI 34'!$E$27:$P$27,Actual_month),) -> 1168 | O44: =IFERROR(N44/M44,"") -> 1 | P44: details | Q44: =G44*$R$3 -> 1051.2 | R44: =M44*$R$3 -> 1051.2 | S44: H | T44: v
A45: 7 | B45: HOPEWELL- WATER | C45: No. | D45: l | E45: l | F45: l | G45: =IFERROR(INDEX('KPI 34A'!E$19:P$19,Actual_month),) -> 381 | H45: =IFERROR(INDEX('KPI 34A'!$E$20:$P$20,Actual_month),) -> 418 | I45: =IFERROR(H45/G45,"") -> 1.0971129 | J45: l | K45: l | L45: l | M45: =IFERROR(INDEX('KPI 34A'!$E$26:$P$26,Actual_month),) -> 381 | N45: =IFERROR(INDEX('KPI 34A'!$E$27:$P$27,Actual_month),) -> 418 | O45: =IFERROR(N45/M45,"") -> 1.0971129 | P45: details | Q45: =G45*$R$3 -> 342.9 | R45: =M45*$R$3 -> 342.9 | S45: H | T45: v
B46: TOTALWATER CONNECTION CENTRAL REGION | C46: No. | D46: l | E46: l | F46: l | G46: =IFERROR(INDEX('KPI 30'!E$19:P$19,Actual_month),) -> 5465 | H46: =IFERROR(INDEX('KPI 30'!$E$20:$P$20,Actual_month),) -> 5401 | I46: =IFERROR(H46/G46,"") -> 0.98828911 | J46: l | K46: l | L46: l | M46: =IFERROR(INDEX('KPI 30'!$E$26:$P$26,Actual_month),) -> 5465 | N46: =IFERROR(INDEX('KPI 30'!$E$27:$P$27,Actual_month),) -> 5401 | O46: =IFERROR(N46/M46,"") -> 0.98828911 | P46: details | Q46: =G46*$R$3 -> 4918.5 | R46: =M46*$R$3 -> 4918.5 | S46: H | T46: v
A47: 1 | B47: HELLSGATE- WATER | C47: No. | D47: l | E47: l | F47: l | G47: =IFERROR(INDEX('KPI 31'!E$19:P$19,Actual_month),) -> 2111 | H47: =IFERROR(INDEX('KPI 31'!$E$20:$P$20,Actual_month),) -> 1975 | I47: =IFERROR(H47/G47,"") -> 0.93557556 | J47: l | K47: l | L47: l | M47: =IFERROR(INDEX('KPI 31'!$E$26:$P$26,Actual_month),) -> 2111 | N47: =IFERROR(INDEX('KPI 31'!$E$27:$P$27,Actual_month),) -> 1975 | O47: =IFERROR(N47/M47,"") -> 0.93557556 | P47: details | Q47: =G47*$R$3 -> 1899.9 | R47: =M47*$R$3 -> 1899.9 | S47: H | T47: v
A48: 2 | B48: KAMERE- WATER | C48: No. | D48: l | E48: l | F48: l | G48: =IFERROR(INDEX('KPI 32'!E$19:P$19,Actual_month),) -> 433 | H48: =IFERROR(INDEX('KPI 32'!$E$20:$P$20,Actual_month),) -> 407 | I48: =IFERROR(H48/G48,"") -> 0.93995381 | J48: l | K48: l | L48: l | M48: =IFERROR(INDEX('KPI 32'!$E$26:$P$26,Actual_month),) -> 433 | N48: =IFERROR(INDEX('KPI 32'!$E$27:$P$27,Actual_month),) -> 407 | O48: =IFERROR(N48/M48,"") -> 0.93995381 | P48: details | Q48: =G48*$R$3 -> 389.7 | R48: =M48*$R$3 -> 389.7 | S48: H | T48: v
A49: 3 | B49: MAI-MAHIU- WATER | C49: No. | D49: l | E49: l | F49: l | G49: =IFERROR(INDEX('KPI 35'!E$19:P$19,Actual_month),) -> 1624 | H49: =IFERROR(INDEX('KPI 35'!$E$20:$P$20,Actual_month),) -> 1509 | I49: =IFERROR(H49/G49,"") -> 0.92918719 | J49: l | K49: l | L49: l | M49: =IFERROR(INDEX('KPI 35'!$E$26:$P$26,Actual_month),) -> 1624 | N49: =IFERROR(INDEX('KPI 35'!$E$27:$P$27,Actual_month),) -> 1509 | O49: =IFERROR(N49/M49,"") -> 0.92918719 | P49: details | Q49: =G49*$R$3 -> 1461.6 | R49: =M49*$R$3 -> 1461.6 | S49: H | T49: v
A50: 4 | B50: LONGONOT- WATER | C50: No. | D50: l | E50: l | F50: l | G50: =IFERROR(INDEX('KPI 35B'!E$19:P$19,Actual_month),) -> 698 | H50: =IFERROR(INDEX('KPI 35B'!$E$20:$P$20,Actual_month),) -> 696 | I50: =IFERROR(H50/G50,"") -> 0.99713467 | J50: l | K50: l | L50: l | M50: =IFERROR(INDEX('KPI 35B'!$E$26:$P$26,Actual_month),) -> 698 | N50: =IFERROR(INDEX('KPI 35B'!$E$27:$P$27,Actual_month),) -> 696 | O50: =IFERROR(N50/M50,"") -> 0.99713467 | P50: details | Q50: =G50*$R$3 -> 628.2 | R50: =M50*$R$3 -> 628.2 | S50: H | T50: v
B51: TOTAL WATER CONNECTION SOUTHERN REGION | C51: No. | D51: l | E51: l | F51: l | G51: =IFERROR(INDEX('KPI 36'!E$19:P$19,Actual_month),) -> 4866 | H51: =IFERROR(INDEX('KPI 36'!$E$20:$P$20,Actual_month),) -> 4587 | I51: =IFERROR(H51/G51,"") -> 0.94266338 | J51: l | K51: l | L51: l | M51: =IFERROR(INDEX('KPI 36'!$E$26:$P$26,Actual_month),) -> 4866 | N51: =IFERROR(INDEX('KPI 36'!$E$27:$P$27,Actual_month),) -> 4587 | O51: =IFERROR(N51/M51,"") -> 0.94266338 | P51: details | Q51: =G51*$R$3 -> 4379.4 | R51: =M51*$R$3 -> 4379.4 | S51: H | T51: v
A52: EASTERN REGION | Q52: monthly | R52: cumluative
A53: 1 | B53: KAYOLE-WATER | C53: No. | D53: l | E53: l | F53: l | G53: =IFERROR(INDEX('KPI 33'!E$19:P$19,Actual_month),) -> 3047 | H53: =IFERROR(INDEX('KPI 33'!$E$20:$P$20,Actual_month),) -> 3131 | I53: =IFERROR(H53/G53,"") -> 1.0275681 | J53: l | K53: l | L53: l | M53: =IFERROR(INDEX('KPI 33'!$E$26:$P$26,Actual_month),) -> 3047 | N53: =IFERROR(INDEX('KPI 33'!$E$27:$P$27,Actual_month),) -> 3131 | O53: =IFERROR(N53/M53,"") -> 1.0275681 | P53: details | Q53: =G53*$R$3 -> 2742.3 | R53: =M53*$R$3 -> 2742.3 | S53: H | T53: v
A54: 2 | B54: IHINDU-WATER | C54: No. | D54: l | E54: l | F54: l | G54: =IFERROR(INDEX('KPI 33B'!E$19:P$19,Actual_month),) -> 285 | H54: =IFERROR(INDEX('KPI 33B'!$E$20:$P$20,Actual_month),) -> 60 | I54: =IFERROR(H54/G54,"") -> 0.21052632 | J54: l | K54: l | L54: l | M54: =IFERROR(INDEX('KPI 33B'!$E$26:$P$26,Actual_month),) -> 285 | N54: =IFERROR(INDEX('KPI 33B'!$E$27:$P$27,Actual_month),) -> 60 | O54: =IFERROR(N54/M54,"") -> 0.21052632 | P54: details | Q54: =G54*$R$3 -> 256.5 | R54: =M54*$R$3 -> 256.5 | S54: H | T54: v
B55: TOTAL WATER CONNECTION EASTERN REGION | C55: No. | D55: l | E55: l | F55: l | G55: =IFERROR(INDEX('KPI 36B'!E$19:P$19,Actual_month),) -> 3332 | H55: =IFERROR(INDEX('KPI 36B'!$E$20:$P$20,Actual_month),) -> 3191 | I55: =IFERROR(H55/G55,"") -> 0.95768307 | J55: l | K55: l | L55: l | M55: =IFERROR(INDEX('KPI 36B'!$E$26:$P$26,Actual_month),) -> 3332 | N55: =IFERROR(INDEX('KPI 36B'!$E$27:$P$27,Actual_month),) -> 3191 | O55: =IFERROR(N55/M55,"") -> 0.95768307 | P55: details | Q55: =G55*$R$3 -> 2998.8 | R55: =M55*$R$3 -> 2998.8 | S55: H | T55: v
A56: TOTAL CONNECTIONS-SEWER | Q56: monthly | R56: cumluative
A57: 1 | B57: CBD- SEWER | C57: No. | D57: l | E57: l | F57: l | G57: =IFERROR(INDEX('KPI 37'!E$19:P$19,Actual_month),) -> 488 | H57: =IFERROR(INDEX('KPI 37'!$E$20:$P$20,Actual_month),) -> 482 | I57: =IFERROR(H57/G57,"") -> 0.98770492 | J57: l | K57: l | L57: l | M57: =IFERROR(INDEX('KPI 37'!$E$26:$P$26,Actual_month),) -> 488 | N57: =IFERROR(INDEX('KPI 37'!$E$27:$P$27,Actual_month),) -> 482 | O57: =IFERROR(N57/M57,"") -> 0.98770492 | P57: details | Q57: =G57*$R$3 -> 439.2 | R57: =M57*$R$3 -> 439.2 | S57: H | T57: v
A58: 2 | B58: CCCR-SEWER | C58: No. | D58: l | E58: l | F58: l | G58: =IFERROR(INDEX('KPI 38'!E$19:P$19,Actual_month),) -> 509 | H58: =IFERROR(INDEX('KPI 38'!$E$20:$P$20,Actual_month),) -> 456 | I58: =IFERROR(H58/G58,"") -> 0.89587426 | J58: l | K58: l | L58: l | M58: =IFERROR(INDEX('KPI 38'!$E$26:$P$26,Actual_month),) -> 509 | N58: =IFERROR(INDEX('KPI 38'!$E$27:$P$27,Actual_month),) -> 456 | O58: =IFERROR(N58/M58,"") -> 0.89587426 | P58: details | Q58: =G58*$R$3 -> 458.1 | R58: =M58*$R$3 -> 458.1 | S58: H | T58: v
A59: 3 | B59: KABATI-SEWER | C59: No. | D59: l | E59: l | F59: l | G59: =IFERROR(INDEX('KPI 39'!E$19:P$19,Actual_month),) -> 407 | H59: =IFERROR(INDEX('KPI 39'!$E$20:$P$20,Actual_month),) -> 384 | I59: =IFERROR(H59/G59,"") -> 0.94348894 | J59: l | K59: l | L59: l | M59: =IFERROR(INDEX('KPI 39'!$E$26:$P$26,Actual_month),) -> 407 | N59: =IFERROR(INDEX('KPI 39'!$E$27:$P$27,Actual_month),) -> 384 | O59: =IFERROR(N59/M59,"") -> 0.94348894 | P59: details | Q59: =G59*$R$3 -> 366.3 | R59: =M59*$R$3 -> 366.3 | S59: H | T59: v
A60: 4 | B60: SITE- SEWER | C60: No. | D60: l | E60: l | F60: l | G60: =IFERROR(INDEX('KPI 40'!E$19:P$19,Actual_month),) -> 613 | H60: =IFERROR(INDEX('KPI 40'!$E$20:$P$20,Actual_month),) -> 604 | I60: =IFERROR(H60/G60,"") -> 0.98531811 | J60: l | K60: l | L60: l | M60: =IFERROR(INDEX('KPI 40'!$E$26:$P$26,Actual_month),) -> 613 | N60: =IFERROR(INDEX('KPI 40'!$E$27:$P$27,Actual_month),) -> 604 | O60: =IFERROR(N60/M60,"") -> 0.98531811 | P60: details | Q60: =G60*$R$3 -> 551.7 | R60: =M60*$R$3 -> 551.7 | S60: H | T60: v
A61: 5 | B61: KIHOTO- SEWER | C61: No. | D61: l | E61: l | F61: l | G61: =IFERROR(INDEX('KPI 41'!E$19:P$19,Actual_month),) -> 0 | H61: =IFERROR(INDEX('KPI 41'!$E$20:$P$20,Actual_month),) -> 0 | I61: =IFERROR(H61/G61,"") | J61: l | K61: l | L61: l | M61: =IFERROR(INDEX('KPI 41'!$E$26:$P$26,Actual_month),) -> 0 | N61: =IFERROR(INDEX('KPI 41'!$E$27:$P$27,Actual_month),) -> 0 | O61: =IFERROR(N61/M61,"") | P61: details | Q61: =G61*$R$3 -> 0 | R61: =M61*$R$3 -> 0 | S61: H | T61: v
A62: 6 | B62: LAKEVIEW- SEWER | C62: No. | D62: l | E62: l | F62: l | G62: =IFERROR(INDEX('KPI 46'!E$19:P$19,Actual_month),) -> 188 | H62: =IFERROR(INDEX('KPI 46'!$E$20:$P$20,Actual_month),) -> 184 | I62: =IFERROR(H62/G62,"") -> 0.9787234 | J62: l | K62: l | L62: l | M62: =IFERROR(INDEX('KPI 46'!$E$26:$P$26,Actual_month),) -> 188 | N62: =IFERROR(INDEX('KPI 46'!$E$27:$P$27,Actual_month),) -> 184 | O62: =IFERROR(N62/M62,"") -> 0.9787234 | P62: details | Q62: =G62*$R$3 -> 169.2 | R62: =M62*$R$3 -> 169.2 | S62: H | T62: v
A63: 7 | B63: HOPEWELL- SEWER | C63: No. | D63: l | E63: l | F63: l | G63: =IFERROR(INDEX('KPI 46A'!E$19:P$19,Actual_month),) -> 2 | H63: =IFERROR(INDEX('KPI 46A'!$E$20:$P$20,Actual_month),) -> 2 | I63: =IFERROR(H63/G63,"") -> 1 | J63: l | K63: l | L63: l | M63: =IFERROR(INDEX('KPI 46A'!$E$26:$P$26,Actual_month),) -> 2 | N63: =IFERROR(INDEX('KPI 46A'!$E$27:$P$27,Actual_month),) -> 2 | O63: =IFERROR(N63/M63,"") -> 1 | P63: details | Q63: =G63*$R$3 -> 1.8 | R63: =M63*$R$3 -> 1.8 | S63: H | T63: v
B64: TOTAL SEWER CONNECTION CENTRAL REGION | C64: No. | D64: l | E64: l | F64: l | G64: =IFERROR(INDEX('KPI 42'!E$19:P$19,Actual_month),) -> 2207 | H64: =IFERROR(INDEX('KPI 42'!$E$20:$P$20,Actual_month),) -> 2112 | I64: =IFERROR(H64/G64,"") -> 0.95695514 | J64: l | K64: l | L64: l | M64: =IFERROR(INDEX('KPI 42'!$E$26:$P$26,Actual_month),) -> 2207 | N64: =IFERROR(INDEX('KPI 42'!$E$27:$P$27,Actual_month),) -> 2112 | O64: =IFERROR(N64/M64,"") -> 0.95695514 | P64: details | Q64: =G64*$R$3 -> 1986.3 | R64: =M64*$R$3 -> 1986.3 | S64: H | T64: v
A65: SOUTHERN REGION | Q65: monthly | R65: cumluative
A66: 1 | B66: HELLSGATE-SEWER | C66: No. | D66: l | E66: l | F66: l | G66: =IFERROR(INDEX('KPI 43'!E$19:P$19,Actual_month),) -> 0 | H66: =IFERROR(INDEX('KPI 43'!$E$20:$P$20,Actual_month),) -> 0 | I66: =IFERROR(H66/G66,"") | J66: l | K66: l | L66: l | M66: =IFERROR(INDEX('KPI 43'!$E$26:$P$26,Actual_month),) -> 0 | N66: =IFERROR(INDEX('KPI 43'!$E$27:$P$27,Actual_month),) -> 0 | O66: =IFERROR(N66/M66,"") | P66: details | Q66: =G66*$R$3 -> 0 | R66: =M66*$R$3 -> 0 | S66: H | T66: v
A67: 2 | B67: KAMERE- SEWER | C67: No. | D67: l | E67: l | F67: l | G67: =IFERROR(INDEX('KPI 44'!E$19:P$19,Actual_month),) -> 0 | H67: =IFERROR(INDEX('KPI 44'!$E$20:$P$20,Actual_month),) -> 0 | I67: =IFERROR(H67/G67,"") | J67: l | K67: l | L67: l | M67: =IFERROR(INDEX('KPI 44'!$E$26:$P$26,Actual_month),) -> 0 | N67: =IFERROR(INDEX('KPI 44'!$E$27:$P$27,Actual_month),) -> 0 | O67: =IFERROR(N67/M67,"") | P67: details | Q67: =G67*$R$3 -> 0 | R67: =M67*$R$3 -> 0 | S67: H | T67: v
A68: 3 | B68: MAI-MAHIU-SEWER | C68: No. | D68: l | E68: l | F68: l | G68: =IFERROR(INDEX('KPI 47'!E$19:P$19,Actual_month),) -> 0 | H68: =IFERROR(INDEX('KPI 47'!$E$20:$P$20,Actual_month),) -> 0 | I68: =IFERROR(H68/G68,"") | J68: l | K68: l | L68: l | M68: =IFERROR(INDEX('KPI 47'!$E$26:$P$26,Actual_month),) -> 0 | N68: =IFERROR(INDEX('KPI 47'!$E$27:$P$27,Actual_month),) -> 0 | O68: =IFERROR(N68/M68,"") | P68: details | Q68: =G68*$R$3 -> 0 | R68: =M68*$R$3 -> 0 | S68: H | T68: v
B69: TOTAL SEWER CONNECTION SOUTHERNREGION | C69: No. | D69: l | E69: l | F69: l | G69: =IFERROR(INDEX('KPI 48'!E$19:P$19,Actual_month),) -> 0 | H69: =IFERROR(INDEX('KPI 48'!$E$20:$P$20,Actual_month),) -> 0 | I69: =IFERROR(H69/G69,"") | J69: l | K69: l | L69: l | M69: =IFERROR(INDEX('KPI 48'!$E$26:$P$26,Actual_month),) -> 0 | N69: =IFERROR(INDEX('KPI 48'!$E$27:$P$27,Actual_month),) -> 0 | O69: =IFERROR(N69/M69,"") | P69: details | Q69: =G69*$R$3 -> 0 | R69: =M69*$R$3 -> 0 | S69: H | T69: v
A70: EASTERN REGION | Q70: monthly | R70: cumluative
A71: 1 | B71: KAYOLE-SEWER | C71: No. | D71: l | E71: l | F71: l | G71: =IFERROR(INDEX('KPI 45'!E$19:P$19,Actual_month),) -> 60 | H71: =IFERROR(INDEX('KPI 45'!$E$20:$P$20,Actual_month),) -> 64 | I71: =IFERROR(H71/G71,"") -> 1.0666667 | J71: l | K71: l | L71: l | M71: =IFERROR(INDEX('KPI 45'!$E$26:$P$26,Actual_month),) -> 60 | N71: =IFERROR(INDEX('KPI 45'!$E$27:$P$27,Actual_month),) -> 64 | O71: =IFERROR(N71/M71,"") -> 1.0666667 | P71: details | Q71: =G71*$R$3 -> 54 | R71: =M71*$R$3 -> 54 | S71: H | T71: v
A72: TOTAL ACTIVE CONNECTIONS-WATER | Q72: monthly | R72: cumluative
A73: 1 | B73: CBD- ACTIVE WATER | C73: No. | D73: l | E73: l | F73: l | G73: =IFERROR(INDEX('KPI 49'!E$19:P$19,Actual_month),) -> 604 | H73: =IFERROR(INDEX('KPI 49'!$E$20:$P$20,Actual_month),) -> 600 | I73: =IFERROR(H73/G73,"") -> 0.99337748 | J73: l | K73: l | L73: l | M73: =IFERROR(INDEX('KPI 49'!$E$26:$P$26,Actual_month),) -> 604 | N73: =IFERROR(INDEX('KPI 49'!$E$27:$P$27,Actual_month),) -> 600 | O73: =IFERROR(N73/M73,"") -> 0.99337748 | P73: details | Q73: =G73*$R$3 -> 543.6 | R73: =M73*$R$3 -> 543.6 | S73: H | T73: v
A74: 2 | B74: CCCR- ACTIVE WATER | C74: No. | D74: l | E74: l | F74: l | G74: =IFERROR(INDEX('KPI 50'!E$19:P$19,Actual_month),) -> 779 | H74: =IFERROR(INDEX('KPI 50'!$E$20:$P$20,Actual_month),) -> 716 | I74: =IFERROR(H74/G74,"") -> 0.91912709 | J74: l | K74: l | L74: l | M74: =IFERROR(INDEX('KPI 50'!$E$26:$P$26,Actual_month),) -> 779 | N74: =IFERROR(INDEX('KPI 50'!$E$27:$P$27,Actual_month),) -> 716 | O74: =IFERROR(N74/M74,"") -> 0.91912709 | P74: details | Q74: =G74*$R$3 -> 701.1 | R74: =M74*$R$3 -> 701.1 | S74: H | T74: v
A75: 3 | B75: KABATI- ACTIVE WATER | C75: No. | D75: l | E75: l | F75: l | G75: =IFERROR(INDEX('KPI 51'!E$19:P$19,Actual_month),) -> 894 | H75: =IFERROR(INDEX('KPI 51'!$E$20:$P$20,Actual_month),) -> 870 | I75: =IFERROR(H75/G75,"") -> 0.97315436 | J75: l | K75: l | L75: l | M75: =IFERROR(INDEX('KPI 51'!$E$26:$P$26,Actual_month),) -> 894 | N75: =IFERROR(INDEX('KPI 51'!$E$27:$P$27,Actual_month),) -> 870 | O75: =IFERROR(N75/M75,"") -> 0.97315436 | P75: details | Q75: =G75*$R$3 -> 804.6 | R75: =M75*$R$3 -> 804.6 | S75: H | T75: v
A76: 4 | B76: SITE- ACTIVE WATER | C76: No. | D76: l | E76: l | F76: l | G76: =IFERROR(INDEX('KPI 52'!E$19:P$19,Actual_month),) -> 844 | H76: =IFERROR(INDEX('KPI 52'!$E$20:$P$20,Actual_month),) -> 842 | I76: =IFERROR(H76/G76,"") -> 0.99763033 | J76: l | K76: l | L76: l | M76: =IFERROR(INDEX('KPI 52'!$E$26:$P$26,Actual_month),) -> 844 | N76: =IFERROR(INDEX('KPI 52'!$E$27:$P$27,Actual_month),) -> 842 | O76: =IFERROR(N76/M76,"") -> 0.99763033 | P76: details | Q76: =G76*$R$3 -> 759.6 | R76: =M76*$R$3 -> 759.6 | S76: H | T76: v
A77: 5 | B77: KIHOTO-ACTIVE WATER | C77: No. | D77: l | E77: l | F77: l | G77: =IFERROR(INDEX('KPI 53'!E$19:P$19,Actual_month),) -> 183 | H77: =IFERROR(INDEX('KPI 53'!$E$20:$P$20,Actual_month),) -> 176 | I77: =IFERROR(H77/G77,"") -> 0.96174863 | J77: l | K77: l | L77: l | M77: =IFERROR(INDEX('KPI 53'!$E$26:$P$26,Actual_month),) -> 183 | N77: =IFERROR(INDEX('KPI 53'!$E$27:$P$27,Actual_month),) -> 176 | O77: =IFERROR(N77/M77,"") -> 0.96174863 | P77: details | Q77: =G77*$R$3 -> 164.7 | R77: =M77*$R$3 -> 164.7 | S77: H | T77: v
A78: 6 | B78: LAKEVIEW- ACTIVE WATER | C78: No. | D78: l | E78: l | F78: l | G78: =IFERROR(INDEX('KPI 58'!E$19:P$19,Actual_month),) -> 997 | H78: =IFERROR(INDEX('KPI 58'!$E$20:$P$20,Actual_month),) -> 1000 | I78: =IFERROR(H78/G78,"") -> 1.003009 | J78: l | K78: l | L78: l | M78: =IFERROR(INDEX('KPI 58'!$E$26:$P$26,Actual_month),) -> 997 | N78: =IFERROR(INDEX('KPI 58'!$E$27:$P$27,Actual_month),) -> 1000 | O78: =IFERROR(N78/M78,"") -> 1.003009 | P78: details | Q78: =G78*$R$3 -> 897.3 | R78: =M78*$R$3 -> 897.3 | S78: H | T78: v
A79: 7 | B79: HOPEWELL- ACTIVE WATER | C79: No. | D79: l | E79: l | F79: l | G79: =IFERROR(INDEX('KPI 58A'!E$19:P$19,Actual_month),) -> 311 | H79: =IFERROR(INDEX('KPI 58A'!$E$20:$P$20,Actual_month),) -> 343 | I79: =IFERROR(H79/G79,"") -> 1.1028939 | J79: l | K79: l | L79: l | M79: =IFERROR(INDEX('KPI 58A'!$E$26:$P$26,Actual_month),) -> 311 | N79: =IFERROR(INDEX('KPI 58A'!$E$27:$P$27,Actual_month),) -> 343 | O79: =IFERROR(N79/M79,"") -> 1.1028939 | P79: details | Q79: =G79*$R$3 -> 279.9 | R79: =M79*$R$3 -> 279.9 | S79: H | T79: v
B80: TOTAL ACTIVE WATER CONNECTION CENTRAL REGION | C80: No. | D80: l | E80: l | F80: l | G80: =IFERROR(INDEX('KPI 54'!E$19:P$19,Actual_month),) -> 4612 | H80: =IFERROR(INDEX('KPI 54'!$E$20:$P$20,Actual_month),) -> 4547 | I80: =IFERROR(H80/G80,"") -> 0.98590633 | J80: l | K80: l | L80: l | M80: =IFERROR(INDEX('KPI 54'!$E$26:$P$26,Actual_month),) -> 4612 | N80: =IFERROR(INDEX('KPI 54'!$E$27:$P$27,Actual_month),) -> 4547 | O80: =IFERROR(N80/M80,"") -> 0.98590633 | P80: details | Q80: =G80*$R$3 -> 4150.8 | R80: =M80*$R$3 -> 4150.8 | S80: H | T80: v
A81: 1 | B81: HELLSGATE- ACTIVE WATER | C81: No. | D81: l | E81: l | F81: l | G81: =IFERROR(INDEX('KPI 55'!E$19:P$19,Actual_month),) -> 1859 | H81: =IFERROR(INDEX('KPI 55'!$E$20:$P$20,Actual_month),) -> 1719 | I81: =IFERROR(H81/G81,"") -> 0.92469069 | J81: l | K81: l | L81: l | M81: =IFERROR(INDEX('KPI 55'!$E$26:$P$26,Actual_month),) -> 1859 | N81: =IFERROR(INDEX('KPI 55'!$E$27:$P$27,Actual_month),) -> 1719 | O81: =IFERROR(N81/M81,"") -> 0.92469069 | P81: details | Q81: =G81*$R$3 -> 1673.1 | R81: =M81*$R$3 -> 1673.1 | S81: H | T81: v
A82: 2 | B82: KAMERE- ACTIVE WATER | C82: No. | D82: l | E82: l | F82: l | G82: =IFERROR(INDEX('KPI 56'!E$19:P$19,Actual_month),) -> 332 | H82: =IFERROR(INDEX('KPI 56'!$E$20:$P$20,Actual_month),) -> 296 | I82: =IFERROR(H82/G82,"") -> 0.89156627 | J82: l | K82: l | L82: l | M82: =IFERROR(INDEX('KPI 56'!$E$26:$P$26,Actual_month),) -> 332 | N82: =IFERROR(INDEX('KPI 56'!$E$27:$P$27,Actual_month),) -> 296 | O82: =IFERROR(N82/M82,"") -> 0.89156627 | P82: details | Q82: =G82*$R$3 -> 298.8 | R82: =M82*$R$3 -> 298.8 | S82: H | T82: v
A83: 3 | B83: MAI-MAHIU- ACTIVE WATER | C83: No. | D83: l | E83: l | F83: l | G83: =IFERROR(INDEX('KPI 59'!E$19:P$19,Actual_month),) -> 1159 | H83: =IFERROR(INDEX('KPI 59'!$E$20:$P$20,Actual_month),) -> 985 | I83: =IFERROR(H83/G83,"") -> 0.84987058 | J83: l | K83: l | L83: l | M83: =IFERROR(INDEX('KPI 59'!$E$26:$P$26,Actual_month),) -> 1159 | N83: =IFERROR(INDEX('KPI 59'!$E$27:$P$27,Actual_month),) -> 985 | O83: =IFERROR(N83/M83,"") -> 0.84987058 | P83: details | Q83: =G83*$R$3 -> 1043.1 | R83: =M83*$R$3 -> 1043.1 | S83: H | T83: v
A84: 4 | B84: LONGONOT- ACTIVE WATER | C84: No. | D84: l | E84: l | F84: l | G84: =IFERROR(INDEX('KPI 59B'!E$19:P$19,Actual_month),) -> 599 | H84: =IFERROR(INDEX('KPI 59B'!$E$20:$P$20,Actual_month),) -> 605 | I84: =IFERROR(H84/G84,"") -> 1.0100167 | J84: l | K84: l | L84: l | M84: =IFERROR(INDEX('KPI 59B'!$E$26:$P$26,Actual_month),) -> 599 | N84: =IFERROR(INDEX('KPI 59B'!$E$27:$P$27,Actual_month),) -> 605 | O84: =IFERROR(N84/M84,"") -> 1.0100167 | P84: details | Q84: =G84*$R$3 -> 539.1 | R84: =M84*$R$3 -> 539.1 | S84: H | T84: v
B85: TOTAL ACTIVE WATER CONNECTION SOUTHERN REGION | C85: No. | D85: l | E85: l | F85: l | G85: =IFERROR(INDEX('KPI 60'!E$19:P$19,Actual_month),) -> 3949 | H85: =IFERROR(INDEX('KPI 60'!$E$20:$P$20,Actual_month),) -> 3605 | I85: =IFERROR(H85/G85,"") -> 0.91288934 | J85: l | K85: l | L85: l | M85: =IFERROR(INDEX('KPI 60'!$E$26:$P$26,Actual_month),) -> 3949 | N85: =IFERROR(INDEX('KPI 60'!$E$27:$P$27,Actual_month),) -> 3605 | O85: =IFERROR(N85/M85,"") -> 0.91288934 | P85: details | Q85: =G85*$R$3 -> 3554.1 | R85: =M85*$R$3 -> 3554.1 | S85: H | T85: v
A86: EASTERN REGION | Q86: monthly | R86: cumluative
A87: 1 | B87: KAYOLE- ACTIVE WATER | C87: No. | D87: l | E87: l | F87: l | G87: =IFERROR(INDEX('KPI 57'!E$19:P$19,Actual_month),) -> 2886 | H87: =IFERROR(INDEX('KPI 57'!$E$20:$P$20,Actual_month),) -> 2926 | I87: =IFERROR(H87/G87,"") -> 1.01386 | J87: l | K87: l | L87: l | M87: =IFERROR(INDEX('KPI 57'!$E$26:$P$26,Actual_month),) -> 2886 | N87: =IFERROR(INDEX('KPI 57'!$E$27:$P$27,Actual_month),) -> 2926 | O87: =IFERROR(N87/M87,"") -> 1.01386 | P87: details | Q87: =G87*$R$3 -> 2597.4 | R87: =M87*$R$3 -> 2597.4 | S87: H | T87: v
A88: 2 | B88: IHINDU- ACTIVE WATER | C88: No. | D88: l | E88: l | F88: l | G88: =IFERROR(INDEX('KPI 57B'!E$19:P$19,Actual_month),) -> 242 | H88: =IFERROR(INDEX('KPI 57B'!$E$20:$P$20,Actual_month),) -> 17 | I88: =IFERROR(H88/G88,"") -> 0.070247934 | J88: l | K88: l | L88: l | M88: =IFERROR(INDEX('KPI 57B'!$E$26:$P$26,Actual_month),) -> 242 | N88: =IFERROR(INDEX('KPI 57B'!$E$27:$P$27,Actual_month),) -> 17 | O88: =IFERROR(N88/M88,"") -> 0.070247934 | P88: details | Q88: =G88*$R$3 -> 217.8 | R88: =M88*$R$3 -> 217.8 | S88: H | T88: v
B89: TOTAL ACTIVE WATER CONNECTION EASTERN REGION | C89: No. | D89: l | E89: l | F89: l | G89: =IFERROR(INDEX('KPI 60B'!E$19:P$19,Actual_month),) -> 3128 | H89: =IFERROR(INDEX('KPI 60B'!$E$20:$P$20,Actual_month),) -> 2943 | I89: =IFERROR(H89/G89,"") -> 0.94085678 | J89: l | K89: l | L89: l | M89: =IFERROR(INDEX('KPI 60B'!$E$26:$P$26,Actual_month),) -> 3128 | N89: =IFERROR(INDEX('KPI 60B'!$E$27:$P$27,Actual_month),) -> 2943 | O89: =IFERROR(N89/M89,"") -> 0.94085678 | P89: details | Q89: =G89*$R$3 -> 2815.2 | R89: =M89*$R$3 -> 2815.2 | S89: H | T89: v
A90: TOTAL ACTIVE CONNECTIONS-SEWER | Q90: monthly | R90: cumluative
A91: 1 | B91: CBD- ACTIVE SEWER | C91: No. | D91: l | E91: l | F91: l | G91: =IFERROR(INDEX('KPI 61'!E$19:P$19,Actual_month),) -> 396 | H91: =IFERROR(INDEX('KPI 61'!$E$20:$P$20,Actual_month),) -> 389 | I91: =IFERROR(H91/G91,"") -> 0.98232323 | J91: l | K91: l | L91: l | M91: =IFERROR(INDEX('KPI 61'!$E$26:$P$26,Actual_month),) -> 396 | N91: =IFERROR(INDEX('KPI 61'!$E$27:$P$27,Actual_month),) -> 389 | O91: =IFERROR(N91/M91,"") -> 0.98232323 | P91: details | Q91: =G91*$R$3 -> 356.4 | R91: =M91*$R$3 -> 356.4 | S91: H | T91: v
A92: 2 | B92: CCCR- ACTIVE SEWER | C92: No. | D92: l | E92: l | F92: l | G92: =IFERROR(INDEX('KPI 62'!E$19:P$19,Actual_month),) -> 447 | H92: =IFERROR(INDEX('KPI 62'!$E$20:$P$20,Actual_month),) -> 392 | I92: =IFERROR(H92/G92,"") -> 0.87695749 | J92: l | K92: l | L92: l | M92: =IFERROR(INDEX('KPI 62'!$E$26:$P$26,Actual_month),) -> 447 | N92: =IFERROR(INDEX('KPI 62'!$E$27:$P$27,Actual_month),) -> 392 | O92: =IFERROR(N92/M92,"") -> 0.87695749 | P92: details | Q92: =G92*$R$3 -> 402.3 | R92: =M92*$R$3 -> 402.3 | S92: H | T92: v
A93: 3 | B93: KABATI- ACTIVE SEWER | C93: No. | D93: l | E93: l | F93: l | G93: =IFERROR(INDEX('KPI 63'!E$19:P$19,Actual_month),) -> 353 | H93: =IFERROR(INDEX('KPI 63'!$E$20:$P$20,Actual_month),) -> 330 | I93: =IFERROR(H93/G93,"") -> 0.93484419 | J93: l | K93: l | L93: l | M93: =IFERROR(INDEX('KPI 63'!$E$26:$P$26,Actual_month),) -> 353 | N93: =IFERROR(INDEX('KPI 63'!$E$27:$P$27,Actual_month),) -> 330 | O93: =IFERROR(N93/M93,"") -> 0.93484419 | P93: details | Q93: =G93*$R$3 -> 317.7 | R93: =M93*$R$3 -> 317.7 | S93: H | T93: v
A94: 4 | B94: SITE- ACTIVE SEWER | C94: No. | D94: l | E94: l | F94: l | G94: =IFERROR(INDEX('KPI 64'!E$19:P$19,Actual_month),) -> 527 | H94: =IFERROR(INDEX('KPI 64'!$E$20:$P$20,Actual_month),) -> 518 | I94: =IFERROR(H94/G94,"") -> 0.9829222 | J94: l | K94: l | L94: l | M94: =IFERROR(INDEX('KPI 64'!$E$26:$P$26,Actual_month),) -> 527 | N94: =IFERROR(INDEX('KPI 64'!$E$27:$P$27,Actual_month),) -> 518 | O94: =IFERROR(N94/M94,"") -> 0.9829222 | P94: details | Q94: =G94*$R$3 -> 474.3 | R94: =M94*$R$3 -> 474.3 | S94: H | T94: v
A95: 5 | B95: KIHOTO- ACTIVE SEWER | C95: No. | D95: l | E95: l | F95: l | G95: =IFERROR(INDEX('KPI 65'!E$19:P$19,Actual_month),) -> 0 | H95: =IFERROR(INDEX('KPI 65'!$E$20:$P$20,Actual_month),) -> 0 | I95: =IFERROR(H95/G95,"") | J95: l | K95: l | L95: l | M95: =IFERROR(INDEX('KPI 65'!$E$26:$P$26,Actual_month),) -> 0 | N95: =IFERROR(INDEX('KPI 65'!$E$27:$P$27,Actual_month),) -> 0 | O95: =IFERROR(N95/M95,"") | P95: details | Q95: =G95*$R$3 -> 0 | R95: =M95*$R$3 -> 0 | S95: H | T95: v
A96: 6 | B96: LAKEVIEW- ACTIVE SEWER | C96: No. | D96: l | E96: l | F96: l | G96: =IFERROR(INDEX('KPI 70'!E$19:P$19,Actual_month),) -> 163 | H96: =IFERROR(INDEX('KPI 70'!$E$20:$P$20,Actual_month),) -> 159 | I96: =IFERROR(H96/G96,"") -> 0.97546012 | J96: l | K96: l | L96: l | M96: =IFERROR(INDEX('KPI 70'!$E$26:$P$26,Actual_month),) -> 163 | N96: =IFERROR(INDEX('KPI 70'!$E$27:$P$27,Actual_month),) -> 159 | O96: =IFERROR(N96/M96,"") -> 0.97546012 | P96: details | Q96: =G96*$R$3 -> 146.7 | R96: =M96*$R$3 -> 146.7 | S96: H | T96: v
A97: 7 | B97: HOPEWELL- ACTIVE SEWER | C97: No. | D97: l | E97: l | F97: l | G97: =IFERROR(INDEX('KPI 70A'!E$19:P$19,Actual_month),) -> 2 | H97: =IFERROR(INDEX('KPI 70A'!$E$20:$P$20,Actual_month),) -> 2 | I97: =IFERROR(H97/G97,"") -> 1 | J97: l | K97: l | L97: l | M97: =IFERROR(INDEX('KPI 70A'!$E$26:$P$26,Actual_month),) -> 2 | N97: =IFERROR(INDEX('KPI 70A'!$E$27:$P$27,Actual_month),) -> 2 | O97: =IFERROR(N97/M97,"") -> 1 | P97: details | Q97: =G97*$R$3 -> 1.8 | R97: =M97*$R$3 -> 1.8 | S97: H | T97: v
B98: TOTAL ACTIVE SEWER CONNECTION CENTRAL REGION | C98: No. | D98: l | E98: l | F98: l | G98: =IFERROR(INDEX('KPI 66'!E$19:P$19,Actual_month),) -> 1888 | H98: =IFERROR(INDEX('KPI 66'!$E$20:$P$20,Actual_month),) -> 1790 | I98: =IFERROR(H98/G98,"") -> 0.94809322 | J98: l | K98: l | L98: l | M98: =IFERROR(INDEX('KPI 66'!$E$26:$P$26,Actual_month),) -> 1888 | N98: =IFERROR(INDEX('KPI 66'!$E$27:$P$27,Actual_month),) -> 1790 | O98: =IFERROR(N98/M98,"") -> 0.94809322 | P98: details | Q98: =G98*$R$3 -> 1699.2 | R98: =M98*$R$3 -> 1699.2 | S98: H | T98: v
A99: 1 | B99: HELLSGATE- ACTIVE SEWER | C99: No. | D99: l | E99: l | F99: l | G99: =IFERROR(INDEX('KPI 67'!E$19:P$19,Actual_month),) -> 0 | H99: =IFERROR(INDEX('KPI 67'!$E$20:$P$20,Actual_month),) -> 0 | I99: =IFERROR(H99/G99,"") | J99: l | K99: l | L99: l | M99: =IFERROR(INDEX('KPI 67'!$E$26:$P$26,Actual_month),) -> 0 | N99: =IFERROR(INDEX('KPI 67'!$E$27:$P$27,Actual_month),) -> 0 | O99: =IFERROR(N99/M99,"") | P99: details | Q99: =G99*$R$3 -> 0 | R99: =M99*$R$3 -> 0 | S99: H | T99: v
A100: 2 | B100: KAMERE- ACTIVE SEWER | C100: No. | D100: l | E100: l | F100: l | G100: =IFERROR(INDEX('KPI 68'!E$19:P$19,Actual_month),) -> 0 | H100: =IFERROR(INDEX('KPI 68'!$E$20:$P$20,Actual_month),) -> 0 | I100: =IFERROR(H100/G100,"") | J100: l | K100: l | L100: l | M100: =IFERROR(INDEX('KPI 68'!$E$26:$P$26,Actual_month),) -> 0 | N100: =IFERROR(INDEX('KPI 68'!$E$27:$P$27,Actual_month),) -> 0 | O100: =IFERROR(N100/M100,"") | P100: details | Q100: =G100*$R$3 -> 0 | R100: =M100*$R$3 -> 0 | S100: H | T100: v
...

Sheet budget 2025-26
A1: =Dashboard!A1 -> SALES & CC DASHBOARD
E2: 12 | F2: 48
B4: MONTH | C4: UNIT | D4: JUL | E4: AUG | F4: SEP | G4: OCT | H4: NOV | I4: DEC | J4: JAN | K4: FEB | L4: MAR | M4: APR | N4: MAY | O4: JUN
A5: =Dashboard!A5 -> NEW CONNECTIONS WATER
A6: =Dashboard!A6 -> 1 | B6: =Dashboard!B6 -> CBD - NEW WATER | C6: =Dashboard!C6 -> No. | D6: 1 | E6: 1 | F6: 1 | G6: 1 | H6: 1 | I6: 1 | J6: 1 | K6: 1 | L6: 1 | M6: 1 | N6: 1 | O6: 1
A7: =Dashboard!A7 -> 2 | B7: =Dashboard!B7 -> CCCR- NEW WATER | C7: =Dashboard!C7 -> No. | D7: 9 | E7: 10 | F7: 10 | G7: 10 | H7: 10 | I7: 10 | J7: 10 | K7: 10 | L7: 10 | M7: 10 | N7: 10 | O7: 10
A8: =Dashboard!A8 -> 3 | B8: =Dashboard!B8 -> KABATI- NEW WATER | C8: =Dashboard!C8 -> No. | D8: 4 | E8: 4 | F8: 4 | G8: 4 | H8: 4 | I8: 4 | J8: 4 | K8: 4 | L8: 4 | M8: 4 | N8: 4 | O8: 4
A9: =Dashboard!A9 -> 4 | B9: =Dashboard!B9 -> SITE- NEW WATER | C9: =Dashboard!C9 -> No. | D9: 1 | E9: 1 | F9: 1 | G9: 1 | H9: 1 | I9: 1 | J9: 1 | K9: 1 | L9: 1 | M9: 1 | N9: 1 | O9: 1
A10: =Dashboard!A10 -> 5 | B10: =Dashboard!B10 -> KIHOTO- NEW WATER | C10: =Dashboard!C10 -> No. | D10: 1 | E10: 1 | F10: 1 | G10: 1 | H10: 1 | I10: 1 | J10: 1 | K10: 1 | L10: 1 | M10: 1 | N10: 1 | O10: 1
A11: =Dashboard!A11 -> 6 | B11: =Dashboard!B11 -> LAKEVIEW- NEW WATER | C11: =Dashboard!C11 -> No. | D11: 2 | E11: 2 | F11: 2 | G11: 2 | H11: 2 | I11: 2 | J11: 2 | K11: 2 | L11: 2 | M11: 2 | N11: 2 | O11: 2
A12: =Dashboard!A12 -> 7 | B12: =Dashboard!B12 -> HOPEWELL- NEW WATER | C12: =Dashboard!C12 -> No. | D12: 2 | E12: 2 | F12: 2 | G12: 2 | H12: 2 | I12: 2 | J12: 2 | K12: 2 | L12: 2 | M12: 2 | N12: 2 | O12: 2
A13: =Dashboard!A13 -> 0 | B13: =Dashboard!B13 -> TOTAL NEW WATER CONNECTIONS CENTRAL REGION | C13: =Dashboard!C13 -> No. | D13: =SUM(D6:D12) -> 20 | E13: =SUM(E6:E12) -> 21 | F13: =SUM(F6:F12) -> 21 | G13: =SUM(G6:G12) -> 21 | H13: =SUM(H6:H12) -> 21 | I13: =SUM(I6:I12) -> 21 | J13: =SUM(J6:J12) -> 21 | K13: =SUM(K6:K12) -> 21 | ... O13: =SUM(O6:O12) -> 21
A14: =Dashboard!A14 -> 1 | B14: =Dashboard!B14 -> HELLSGATE- NEW WATER | C14: =Dashboard!C14 -> No. | D14: 8 | E14: 8 | F14: 20 | G14: 50 | H14: 50 | I14: 50 | J14: 45 | K14: 45 | L14: 35 | M14: 30 | N14: 30 | O14: 28
A15: =Dashboard!A15 -> 2 | B15: =Dashboard!B15 -> KAMERE- NEW WATER | C15: =Dashboard!C15 -> No. | D15: 1 | E15: 1 | F15: 1 | G15: 21 | H15: 11 | I15: 11 | J15: 11 | K15: 11 | L15: 11 | M15: 11 | N15: 11 | O15: 11
A16: =Dashboard!A16 -> 3 | B16: =Dashboard!B16 -> MAI-MAHIU- NEW WATER | C16: =Dashboard!C16 -> No. | D16: 51 | E16: 51 | F16: 46 | G16: 71 | H16: 71 | I16: 66 | J16: 61 | K16: 61 | L16: 56 | M16: 46 | N16: 46 | O16: 46
A17: =Dashboard!A17 -> 4 | B17: =Dashboard!B17 -> LONGONOT- NEW WATER | C17: =Dashboard!C17 -> No. | D17: 10 | E17: 10 | F17: 10 | G17: 10 | H17: 10 | I17: 10 | J17: 10 | K17: 10 | L17: 10 | M17: 10 | N17: 10 | O17: 10
A18: =Dashboard!A18 -> 0 | B18: =Dashboard!B18 -> TOTAL NEW WATER CONNECTION SOUTHERN REGION | C18: =Dashboard!C18 -> No. | D18: =SUM(D14:D17) -> 70 | E18: =SUM(E14:E17) -> 70 | F18: =SUM(F14:F17) -> 77 | G18: =SUM(G14:G17) -> 152 | H18: =SUM(H14:H17) -> 142 | I18: =SUM(I14:I17) -> 137 | J18: =SUM(J14:J17) -> 127 | K18: =SUM(K14:K17) -> 127 | ... O18: =SUM(O14:O17) -> 95
A19: =Dashboard!A20 -> 1 | B19: =Dashboard!B20 -> KAYOLE- NEW WATER | C19: =Dashboard!C20 -> No. | D19: 38 | E19: 18 | F19: 18 | G19: 18 | H19: 18 | I19: 18 | J19: 33 | K19: 23 | L19: 23 | M19: 18 | N19: 18 | O19: 18
A20: =Dashboard!A21 -> 2 | B20: =Dashboard!B21 -> IHINDU- NEW WATER | C20: =Dashboard!C21 -> No. | D20: 38 | E20: 38 | F20: 33 | G20: 28 | H20: 28 | I20: 23 | J20: 23 | K20: 18 | L20: 18 | M20: 18 | N20: 18 | O20: 18
B21: =Dashboard!B22 -> TOTAL NEW W CONNECTION EASTERN REGION | C21: =Dashboard!C22 -> No. | D21: =D19+D20 -> 76 | E21: =E19+E20 -> 56 | F21: =F19+F20 -> 51 | G21: =G19+G20 -> 46 | H21: =H19+H20 -> 46 | I21: =I19+I20 -> 41 | J21: =J19+J20 -> 56 | K21: =K19+K20 -> 41 | ... O21: =O19+O20 -> 36
A22: =Dashboard!A23 -> NEW CONNECTIONS SEWER
A23: =Dashboard!A24 -> 1 | B23: =Dashboard!B24 -> CBD- NEW SEWER | C23: =Dashboard!C24 -> No. | D23: 1 | E23: 1 | F23: 1 | G23: 1 | H23: 1 | I23: 1 | J23: 1 | K23: 1 | L23: 1 | M23: 1 | N23: 1 | O23: 1
A24: =Dashboard!A25 -> 2 | B24: =Dashboard!B25 -> CCCR- NEW SEWER | C24: =Dashboard!C25 -> No. | D24: 7 | E24: 7 | F24: 7 | G24: 7 | H24: 7 | I24: 7 | J24: 7 | K24: 7 | L24: 7 | M24: 7 | N24: 7 | O24: 7
A25: =Dashboard!A26 -> 3 | B25: =Dashboard!B26 -> KABATI- NEW SEWER | C25: =Dashboard!C26 -> No. | D25: 4 | E25: 3 | F25: 3 | G25: 3 | H25: 3 | I25: 3 | J25: 3 | K25: 3 | L25: 3 | M25: 3 | N25: 3 | O25: 3
A26: =Dashboard!A27 -> 4 | B26: =Dashboard!B27 -> SITE- NEW SEWER | C26: =Dashboard!C27 -> No. | D26: 1 | E26: 1 | F26: 1 | G26: 1 | H26: 1 | I26: 1 | J26: 1 | K26: 1 | L26: 1 | M26: 1 | N26: 1 | O26: 1
A27: =Dashboard!A28 -> 5 | B27: =Dashboard!B28 -> KIHOTO- NEW SEWER | C27: =Dashboard!C28 -> No.
A28: =Dashboard!A29 -> 6 | B28: =Dashboard!B29 -> LAKEVIEW- NEW SEWER | C28: =Dashboard!C29 -> No. | D28: 1 | E28: 1 | F28: 1 | G28: 1 | H28: 1 | I28: 1 | J28: 1 | K28: 1 | L28: 1 | M28: 1 | N28: 1 | O28: 1
A29: =Dashboard!A30 -> 7 | B29: =Dashboard!B30 -> HOPEWELL- NEW SEWER | C29: =Dashboard!C30 -> No.
A30: =Dashboard!A31 -> 0 | B30: =Dashboard!B31 -> TOTAL NEW SEWER CONNECTIONS CENTRAL REGION | C30: =Dashboard!C31 -> No. | D30: =SUM(D23:D29) -> 14 | E30: =SUM(E23:E29) -> 13 | F30: =SUM(F23:F29) -> 13 | G30: =SUM(G23:G29) -> 13 | H30: =SUM(H23:H29) -> 13 | I30: =SUM(I23:I29) -> 13 | J30: =SUM(J23:J29) -> 13 | K30: =SUM(K23:K29) -> 13 | ... O30: =SUM(O23:O29) -> 13
A31: =Dashboard!A32 -> 1 | B31: =Dashboard!B32 -> HELLSGATE- NEW SEWER | C31: =Dashboard!C32 -> No. | D31: 0 | E31: 0 | F31: 0 | G31: 0 | H31: 0 | I31: 0 | J31: 0 | K31: 0 | L31: 0 | M31: 0 | N31: 0 | O31: 0
A32: =Dashboard!A33 -> 2 | B32: =Dashboard!B33 -> KAMERE- NEW SEWER | C32: =Dashboard!C33 -> No. | D32: 0 | E32: 0 | F32: 0 | G32: 0 | H32: 0 | I32: 0 | J32: 0 | K32: 0 | L32: 0 | M32: 0 | N32: 0 | O32: 0
A33: =Dashboard!A34 -> 3 | B33: =Dashboard!B34 -> MAI-MAHIU- NEW SEWER | C33: =Dashboard!C34 -> No. | D33: 0 | E33: 0 | F33: 0 | G33: 0 | H33: 0 | I33: 0 | J33: 0 | K33: 0 | L33: 0 | M33: 0 | N33: 0 | O33: 0
A34: =Dashboard!A35 -> 0 | B34: =Dashboard!B35 -> TOTAL NEW S CONNECTION SOUTHERN REGION | C34: =Dashboard!C35 -> No. | D34: =SUM(D31:D33) -> 0 | E34: =SUM(E31:E33) -> 0 | F34: =SUM(F31:F33) -> 0 | G34: =SUM(G31:G33) -> 0 | H34: =SUM(H31:H33) -> 0 | I34: =SUM(I31:I33) -> 0 | J34: =SUM(J31:J33) -> 0 | K34: =SUM(K31:K33) -> 0 | ... O34: =SUM(O31:O33) -> 0
A35: =Dashboard!A37 -> 1 | B35: =Dashboard!B37 -> KAYOLE- NEW SEWER | C35: =Dashboard!C37 -> No. | D35: 1 | E35: 1 | F35: 1 | G35: 1 | H35: 1 | I35: 1 | J35: 1 | K35: 1 | L35: 1 | M35: 1 | N35: 1 | O35: 1
A36: =Dashboard!A38 -> TOTAL CONNECTIONS-WATER
A37: =Dashboard!A39 -> 1 | B37: =Dashboard!B39 -> CBD- WATER | C37: =Dashboard!C39 -> No. | D37: ='Input Actual2024-25'!P37+'budget 2025-26'!D6 -> 791 | E37: =D37+E6 -> 792 | F37: =E37+F6 -> 793 | G37: =F37+G6 -> 794 | H37: =G37+H6 -> 795 | I37: =H37+I6 -> 796 | J37: =I37+J6 -> 797 | K37: =J37+K6 -> 798 | L37: =K37+L6 -> 799 | ... O37: =N37+O6 -> 802
A38: =Dashboard!A40 -> 2 | B38: =Dashboard!B40 -> CCCR- WATER | C38: =Dashboard!C40 -> No. | D38: ='Input Actual2024-25'!P38+'budget 2025-26'!D7 -> 889 | E38: =D38+E7 -> 899 | F38: =E38+F7 -> 909 | G38: =F38+G7 -> 919 | H38: =G38+H7 -> 929 | I38: =H38+I7 -> 939 | J38: =I38+J7 -> 949 | K38: =J38+K7 -> 959 | L38: =K38+L7 -> 969 | ... O38: =N38+O7 -> 999
A39: =Dashboard!A41 -> 3 | B39: =Dashboard!B41 -> KABATI- WATER | C39: =Dashboard!C41 -> No. | D39: ='Input Actual2024-25'!P39+'budget 2025-26'!D8 -> 957 | E39: =D39+E8 -> 961 | F39: =E39+F8 -> 965 | G39: =F39+G8 -> 969 | H39: =G39+H8 -> 973 | I39: =H39+I8 -> 977 | J39: =I39+J8 -> 981 | K39: =J39+K8 -> 985 | L39: =K39+L8 -> 989 | ... O39: =N39+O8 -> 1001
A40: =Dashboard!A42 -> 4 | B40: =Dashboard!B42 -> SITE- WATER | C40: =Dashboard!C42 -> No. | D40: ='Input Actual2024-25'!P40+'budget 2025-26'!D9 -> 940 | E40: =D40+E9 -> 941 | F40: =E40+F9 -> 942 | G40: =F40+G9 -> 943 | H40: =G40+H9 -> 944 | I40: =H40+I9 -> 945 | J40: =I40+J9 -> 946 | K40: =J40+K9 -> 947 | L40: =K40+L9 -> 948 | ... O40: =N40+O9 -> 951
A41: =Dashboard!A43 -> 5 | B41: =Dashboard!B43 -> KIHOTO- WATER | C41: =Dashboard!C43 -> No. | D41: ='Input Actual2024-25'!P41+'budget 2025-26'!D10 -> 220 | E41: =D41+E10 -> 221 | F41: =E41+F10 -> 222 | G41: =F41+G10 -> 223 | H41: =G41+H10 -> 224 | I41: =H41+I10 -> 225 | J41: =I41+J10 -> 226 | K41: =J41+K10 -> 227 | L41: =K41+L10 -> 228 | ... O41: =N41+O10 -> 231
A42: =Dashboard!A44 -> 6 | B42: =Dashboard!B44 -> LAKEVIEW- WATER | C42: =Dashboard!C44 -> No. | D42: ='Input Actual2024-25'!P42+'budget 2025-26'!D11 -> 1154 | E42: =D42+E11 -> 1156 | F42: =E42+F11 -> 1158 | G42: =F42+G11 -> 1160 | H42: =G42+H11 -> 1162 | I42: =H42+I11 -> 1164 | J42: =I42+J11 -> 1166 | K42: =J42+K11 -> 1168 | L42: =K42+L11 -> 1170 | ... O42: =N42+O11 -> 1176
A43: =Dashboard!A45 -> 7 | B43: =Dashboard!B45 -> HOPEWELL- WATER | C43: =Dashboard!C45 -> No. | D43: ='Input Actual2024-25'!P43+'budget 2025-26'!D12 -> 367 | E43: =D43+E12 -> 369 | F43: =E43+F12 -> 371 | G43: =F43+G12 -> 373 | H43: =G43+H12 -> 375 | I43: =H43+I12 -> 377 | J43: =I43+J12 -> 379 | K43: =J43+K12 -> 381 | L43: =K43+L12 -> 383 | ... O43: =N43+O12 -> 389
A44: =Dashboard!A46 -> 0 | B44: =Dashboard!B46 -> TOTALWATER CONNECTION CENTRAL REGION | C44: =Dashboard!C46 -> No. | D44: =SUM(D37:D43) -> 5318 | E44: =SUM(E37:E43) -> 5339 | F44: =SUM(F37:F43) -> 5360 | G44: =SUM(G37:G43) -> 5381 | H44: =SUM(H37:H43) -> 5402 | I44: =SUM(I37:I43) -> 5423 | J44: =SUM(J37:J43) -> 5444 | K44: =SUM(K37:K43) -> 5465 | ... O44: =SUM(O37:O43) -> 5549
A45: =Dashboard!A47 -> 1 | B45: =Dashboard!B47 -> HELLSGATE- WATER | C45: =Dashboard!C47 -> No. | D45: ='Input Actual2024-25'!P45+D14 -> 1843 | E45: =D45+E14 -> 1851 | F45: =E45+F14 -> 1871 | G45: =F45+G14 -> 1921 | H45: =G45+H14 -> 1971 | I45: =H45+I14 -> 2021 | J45: =I45+J14 -> 2066 | K45: =J45+K14 -> 2111 | L45: =K45+L14 -> 2146 | ... O45: =N45+O14 -> 2234
A46: =Dashboard!A48 -> 2 | B46: =Dashboard!B48 -> KAMERE- WATER | C46: =Dashboard!C48 -> No. | D46: ='Input Actual2024-25'!P46+D15 -> 366 | E46: =D46+E15 -> 367 | F46: =E46+F15 -> 368 | G46: =F46+G15 -> 389 | H46: =G46+H15 -> 400 | I46: =H46+I15 -> 411 | J46: =I46+J15 -> 422 | K46: =J46+K15 -> 433 | L46: =K46+L15 -> 444 | ... O46: =N46+O15 -> 477
A47: =Dashboard!A49 -> 3 | B47: =Dashboard!B49 -> MAI-MAHIU- WATER | C47: =Dashboard!C49 -> No. | D47: ='Input Actual2024-25'!P47+D16 -> 1197 | E47: =D47+E16 -> 1248 | F47: =E47+F16 -> 1294 | G47: =F47+G16 -> 1365 | H47: =G47+H16 -> 1436 | I47: =H47+I16 -> 1502 | J47: =I47+J16 -> 1563 | K47: =J47+K16 -> 1624 | L47: =K47+L16 -> 1680 | ... O47: =N47+O16 -> 1818
A48: =Dashboard!A50 -> 4 | B48: =Dashboard!B50 -> LONGONOT- WATER | C48: =Dashboard!C50 -> No. | D48: ='Input Actual2024-25'!P48+D17 -> 628 | E48: =D48+E17 -> 638 | F48: =E48+F17 -> 648 | G48: =F48+G17 -> 658 | H48: =G48+H17 -> 668 | I48: =H48+I17 -> 678 | J48: =I48+J17 -> 688 | K48: =J48+K17 -> 698 | L48: =K48+L17 -> 708 | ... O48: =N48+O17 -> 738
A49: =Dashboard!A51 -> 0 | B49: =Dashboard!B51 -> TOTAL WATER CONNECTION SOUTHERN REGION | C49: =Dashboard!C51 -> No. | D49: =SUM(D45:D48) -> 4034 | E49: =SUM(E45:E48) -> 4104 | F49: =SUM(F45:F48) -> 4181 | G49: =SUM(G45:G48) -> 4333 | H49: =SUM(H45:H48) -> 4475 | I49: =SUM(I45:I48) -> 4612 | J49: =SUM(J45:J48) -> 4739 | K49: =SUM(K45:K48) -> 4866 | ... O49: =SUM(O45:O48) -> 5267
A50: =Dashboard!A53 -> 1 | B50: =Dashboard!B53 -> KAYOLE-WATER | C50: =Dashboard!C53 -> No. | D50: =2863+D19 -> 2901 | E50: =D50+E19 -> 2919 | F50: =E50+F19 -> 2937 | G50: =F50+G19 -> 2955 | H50: =G50+H19 -> 2973 | I50: =H50+I19 -> 2991 | J50: =I50+J19 -> 3024 | K50: =J50+K19 -> 3047 | L50: =K50+L19 -> 3070 | ... O50: =N50+O19 -> 3124
A51: =Dashboard!A54 -> 2 | B51: =Dashboard!B54 -> IHINDU-WATER | C51: =Dashboard!C54 -> No. | D51: =56+D20 -> 94 | E51: =D51+E20 -> 132 | F51: =E51+F20 -> 165 | G51: =F51+G20 -> 193 | H51: =G51+H20 -> 221 | I51: =H51+I20 -> 244 | J51: =I51+J20 -> 267 | K51: =J51+K20 -> 285 | L51: =K51+L20 -> 303 | ... O51: =N51+O20 -> 357
A52: =Dashboard!A55 -> 0 | B52: =Dashboard!B55 -> TOTAL WATER CONNECTION EASTERN REGION | C52: =Dashboard!C55 -> No. | D52: =D50+D51 -> 2995 | E52: =E50+E51 -> 3051 | F52: =F50+F51 -> 3102 | G52: =G50+G51 -> 3148 | H52: =H50+H51 -> 3194 | I52: =I50+I51 -> 3235 | J52: =J50+J51 -> 3291 | K52: =K50+K51 -> 3332 | ... O52: =O50+O51 -> 3481
A53: =Dashboard!A56 -> TOTAL CONNECTIONS-SEWER
A54: =Dashboard!A57 -> 1 | B54: =Dashboard!B57 -> CBD- SEWER | C54: =Dashboard!C57 -> No. | D54: ='Input Actual2024-25'!P52+D23 -> 481 | E54: =D54+E23 -> 482 | F54: =E54+F23 -> 483 | G54: =F54+G23 -> 484 | H54: =G54+H23 -> 485 | I54: =H54+I23 -> 486 | J54: =I54+J23 -> 487 | K54: =J54+K23 -> 488 | L54: =K54+L23 -> 489 | ... O54: =N54+O23 -> 492
A55: =Dashboard!A58 -> 2 | B55: =Dashboard!B58 -> CCCR-SEWER | C55: =Dashboard!C58 -> No. | D55: ='Input Actual2024-25'!P53+D24 -> 460 | E55: =D55+E24 -> 467 | F55: =E55+F24 -> 474 | G55: =F55+G24 -> 481 | H55: =G55+H24 -> 488 | I55: =H55+I24 -> 495 | J55: =I55+J24 -> 502 | K55: =J55+K24 -> 509 | L55: =K55+L24 -> 516 | ... O55: =N55+O24 -> 537
A56: =Dashboard!A59 -> 3 | B56: =Dashboard!B59 -> KABATI-SEWER | C56: =Dashboard!C59 -> No. | D56: ='Input Actual2024-25'!P54+D25 -> 386 | E56: =D56+E25 -> 389 | F56: =E56+F25 -> 392 | G56: =F56+G25 -> 395 | H56: =G56+H25 -> 398 | I56: =H56+I25 -> 401 | J56: =I56+J25 -> 404 | K56: =J56+K25 -> 407 | L56: =K56+L25 -> 410 | ... O56: =N56+O25 -> 419
A57: =Dashboard!A60 -> 4 | B57: =Dashboard!B60 -> SITE- SEWER | C57: =Dashboard!C60 -> No. | D57: ='Input Actual2024-25'!P55+D26 -> 606 | E57: =D57+E26 -> 607 | F57: =E57+F26 -> 608 | G57: =F57+G26 -> 609 | H57: =G57+H26 -> 610 | I57: =H57+I26 -> 611 | J57: =I57+J26 -> 612 | K57: =J57+K26 -> 613 | L57: =K57+L26 -> 614 | ... O57: =N57+O26 -> 617
A58: =Dashboard!A61 -> 5 | B58: =Dashboard!B61 -> KIHOTO- SEWER | C58: =Dashboard!C61 -> No. | D58: ='Input Actual2024-25'!P56+D27 -> 0 | E58: =D58+E27 -> 0 | F58: =E58+F27 -> 0 | G58: =F58+G27 -> 0 | H58: =G58+H27 -> 0 | I58: =H58+I27 -> 0 | J58: =I58+J27 -> 0 | K58: =J58+K27 -> 0 | L58: =K58+L27 -> 0 | ... O58: =N58+O27 -> 0
A59: =Dashboard!A62 -> 6 | B59: =Dashboard!B62 -> LAKEVIEW- SEWER | C59: =Dashboard!C62 -> No. | D59: ='Input Actual2024-25'!P57+D28 -> 181 | E59: =D59+E28 -> 182 | F59: =E59+F28 -> 183 | G59: =F59+G28 -> 184 | H59: =G59+H28 -> 185 | I59: =H59+I28 -> 186 | J59: =I59+J28 -> 187 | K59: =J59+K28 -> 188 | L59: =K59+L28 -> 189 | ... O59: =N59+O28 -> 192
A60: =Dashboard!A63 -> 7 | B60: =Dashboard!B63 -> HOPEWELL- SEWER | C60: =Dashboard!C63 -> No. | D60: ='Input Actual2024-25'!P58+D29 -> 2 | E60: =D60+E29 -> 2 | F60: =E60+F29 -> 2 | G60: =F60+G29 -> 2 | H60: =G60+H29 -> 2 | I60: =H60+I29 -> 2 | J60: =I60+J29 -> 2 | K60: =J60+K29 -> 2 | L60: =K60+L29 -> 2 | ... O60: =N60+O29 -> 2
A61: =Dashboard!A64 -> 0 | B61: =Dashboard!B64 -> TOTAL SEWER CONNECTION CENTRAL REGION | C61: =Dashboard!C64 -> No. | D61: =SUM(D54:D60) -> 2116 | E61: =SUM(E54:E60) -> 2129 | F61: =SUM(F54:F60) -> 2142 | G61: =SUM(G54:G60) -> 2155 | H61: =SUM(H54:H60) -> 2168 | I61: =SUM(I54:I60) -> 2181 | J61: =SUM(J54:J60) -> 2194 | K61: =SUM(K54:K60) -> 2207 | ... O61: =SUM(O54:O60) -> 2259
A62: =Dashboard!A66 -> 1 | B62: =Dashboard!B66 -> HELLSGATE-SEWER | C62: =Dashboard!C66 -> No. | D62: ='Input Actual2024-25'!E60+'budget 2025-26'!D31 -> 0 | E62: =D62+E31 -> 0 | F62: =E62+F31 -> 0 | G62: =F62+G31 -> 0 | H62: =G62+H31 -> 0 | I62: =H62+I31 -> 0 | J62: =I62+J31 -> 0 | K62: =J62+K31 -> 0 | L62: =K62+L31 -> 0 | ... O62: =N62+O31 -> 0
A63: =Dashboard!A67 -> 2 | B63: =Dashboard!B67 -> KAMERE- SEWER | C63: =Dashboard!C67 -> No. | D63: ='Input Actual2024-25'!E61+'budget 2025-26'!D32 -> 0 | E63: =D63+E32 -> 0 | F63: =E63+F32 -> 0 | G63: =F63+G32 -> 0 | H63: =G63+H32 -> 0 | I63: =H63+I32 -> 0 | J63: =I63+J32 -> 0 | K63: =J63+K32 -> 0 | L63: =K63+L32 -> 0 | ... O63: =N63+O32 -> 0
A64: =Dashboard!A68 -> 3 | B64: =Dashboard!B68 -> MAI-MAHIU-SEWER | C64: =Dashboard!C68 -> No. | D64: ='Input Actual2024-25'!E62+'budget 2025-26'!D33 -> 0 | E64: =D64+E33 -> 0 | F64: =E64+F33 -> 0 | G64: =F64+G33 -> 0 | H64: =G64+H33 -> 0 | I64: =H64+I33 -> 0 | J64: =I64+J33 -> 0 | K64: =J64+K33 -> 0 | L64: =K64+L33 -> 0 | ... O64: =N64+O33 -> 0
A65: =Dashboard!A69 -> 0 | B65: =Dashboard!B69 -> TOTAL SEWER CONNECTION SOUTHERNREGION | C65: =Dashboard!C69 -> No. | D65: =SUM(D62:D64) -> 0 | E65: =SUM(E62:E64) -> 0 | F65: =SUM(F62:F64) -> 0 | G65: =SUM(G62:G64) -> 0 | H65: =SUM(H62:H64) -> 0 | I65: =SUM(I62:I64) -> 0 | J65: =SUM(J62:J64) -> 0 | K65: =SUM(K62:K64) -> 0 | ... O65: =SUM(O62:O64) -> 0
A66: =Dashboard!A71 -> 1 | B66: =Dashboard!B71 -> KAYOLE-SEWER | C66: =Dashboard!C71 -> No. | D66: ='Input Actual2024-25'!P64+'budget 2025-26'!D35 -> 53 | E66: =D66+E35 -> 54 | F66: =E66+F35 -> 55 | G66: =F66+G35 -> 56 | H66: =G66+H35 -> 57 | I66: =H66+I35 -> 58 | J66: =I66+J35 -> 59 | K66: =J66+K35 -> 60 | L66: =K66+L35 -> 61 | ... O66: =N66+O35 -> 64 | Q66: 7
A67: =Dashboard!A72 -> TOTAL ACTIVE CONNECTIONS-WATER
A68: =Dashboard!A73 -> 1 | B68: =Dashboard!B73 -> CBD- ACTIVE WATER | C68: =Dashboard!C73 -> No. | D68: ='Input Actual2024-25'!P66+'budget 2025-26'!D6 -> 597 | E68: =D68+E6 -> 598 | F68: =E68+F6 -> 599 | G68: =F68+G6 -> 600 | H68: =G68+H6 -> 601 | I68: =H68+I6 -> 602 | J68: =I68+J6 -> 603 | K68: =J68+K6 -> 604 | L68: =K68+L6 -> 605 | ... O68: =N68+O6 -> 608
A69: =Dashboard!A74 -> 2 | B69: =Dashboard!B74 -> CCCR- ACTIVE WATER | C69: =Dashboard!C74 -> No. | D69: ='Input Actual2024-25'!P67+'budget 2025-26'!D7 -> 709 | E69: =D69+E7 -> 719 | F69: =E69+F7 -> 729 | G69: =F69+G7 -> 739 | H69: =G69+H7 -> 749 | I69: =H69+I7 -> 759 | J69: =I69+J7 -> 769 | K69: =J69+K7 -> 779 | L69: =K69+L7 -> 789 | ... O69: =N69+O7 -> 819
A70: =Dashboard!A75 -> 3 | B70: =Dashboard!B75 -> KABATI- ACTIVE WATER | C70: =Dashboard!C75 -> No. | D70: ='Input Actual2024-25'!P68+'budget 2025-26'!D8 -> 866 | E70: =D70+E8 -> 870 | F70: =E70+F8 -> 874 | G70: =F70+G8 -> 878 | H70: =G70+H8 -> 882 | I70: =H70+I8 -> 886 | J70: =I70+J8 -> 890 | K70: =J70+K8 -> 894 | L70: =K70+L8 -> 898 | ... O70: =N70+O8 -> 910
A71: =Dashboard!A76 -> 4 | B71: =Dashboard!B76 -> SITE- ACTIVE WATER | C71: =Dashboard!C76 -> No. | D71: ='Input Actual2024-25'!P69+'budget 2025-26'!D9 -> 837 | E71: =D71+E9 -> 838 | F71: =E71+F9 -> 839 | G71: =F71+G9 -> 840 | H71: =G71+H9 -> 841 | I71: =H71+I9 -> 842 | J71: =I71+J9 -> 843 | K71: =J71+K9 -> 844 | L71: =K71+L9 -> 845 | ... O71: =N71+O9 -> 848
A72: =Dashboard!A77 -> 5 | B72: =Dashboard!B77 -> KIHOTO-ACTIVE WATER | C72: =Dashboard!C77 -> No. | D72: ='Input Actual2024-25'!P70+'budget 2025-26'!D10 -> 176 | E72: =D72+E10 -> 177 | F72: =E72+F10 -> 178 | G72: =F72+G10 -> 179 | H72: =G72+H10 -> 180 | I72: =H72+I10 -> 181 | J72: =I72+J10 -> 182 | K72: =J72+K10 -> 183 | L72: =K72+L10 -> 184 | ... O72: =N72+O10 -> 187
A73: =Dashboard!A78 -> 6 | B73: =Dashboard!B78 -> LAKEVIEW- ACTIVE WATER | C73: =Dashboard!C78 -> No. | D73: ='Input Actual2024-25'!P71+'budget 2025-26'!D11 -> 983 | E73: =D73+E11 -> 985 | F73: =E73+F11 -> 987 | G73: =F73+G11 -> 989 | H73: =G73+H11 -> 991 | I73: =H73+I11 -> 993 | J73: =I73+J11 -> 995 | K73: =J73+K11 -> 997 | L73: =K73+L11 -> 999 | ... O73: =N73+O11 -> 1005
A74: =Dashboard!A79 -> 7 | B74: =Dashboard!B79 -> HOPEWELL- ACTIVE WATER | C74: =Dashboard!C79 -> No. | D74: ='Input Actual2024-25'!P72+'budget 2025-26'!D12 -> 297 | E74: =D74+E12 -> 299 | F74: =E74+F12 -> 301 | G74: =F74+G12 -> 303 | H74: =G74+H12 -> 305 | I74: =H74+I12 -> 307 | J74: =I74+J12 -> 309 | K74: =J74+K12 -> 311 | L74: =K74+L12 -> 313 | ... O74: =N74+O12 -> 319
A75: =Dashboard!A80 -> 0 | B75: =Dashboard!B80 -> TOTAL ACTIVE WATER CONNECTION CENTRAL REGION | C75: =Dashboard!C80 -> No. | D75: =SUM(D68:D74) -> 4465 | E75: =SUM(E68:E74) -> 4486 | F75: =SUM(F68:F74) -> 4507 | G75: =SUM(G68:G74) -> 4528 | H75: =SUM(H68:H74) -> 4549 | I75: =SUM(I68:I74) -> 4570 | J75: =SUM(J68:J74) -> 4591 | K75: =SUM(K68:K74) -> 4612 | ... O75: =SUM(O68:O74) -> 4696
A76: =Dashboard!A81 -> 1 | B76: =Dashboard!B81 -> HELLSGATE- ACTIVE WATER | C76: =Dashboard!C81 -> No. | D76: ='Input Actual2024-25'!P74+'budget 2025-26'!D14 -> 1591 | E76: =D76+E14 -> 1599 | F76: =E76+F14 -> 1619 | G76: =F76+G14 -> 1669 | H76: =G76+H14 -> 1719 | I76: =H76+I14 -> 1769 | J76: =I76+J14 -> 1814 | K76: =J76+K14 -> 1859 | L76: =K76+L14 -> 1894 | ... O76: =N76+O14 -> 1982
A77: =Dashboard!A82 -> 2 | B77: =Dashboard!B82 -> KAMERE- ACTIVE WATER | C77: =Dashboard!C82 -> No. | D77: ='Input Actual2024-25'!P75+'budget 2025-26'!D15 -> 265 | E77: =D77+E15 -> 266 | F77: =E77+F15 -> 267 | G77: =F77+G15 -> 288 | H77: =G77+H15 -> 299 | I77: =H77+I15 -> 310 | J77: =I77+J15 -> 321 | K77: =J77+K15 -> 332 | L77: =K77+L15 -> 343 | ... O77: =N77+O15 -> 376
A78: =Dashboard!A83 -> 3 | B78: =Dashboard!B83 -> MAI-MAHIU- ACTIVE WATER | C78: =Dashboard!C83 -> No. | D78: ='Input Actual2024-25'!P76+'budget 2025-26'!D16 -> 732 | E78: =D78+E16 -> 783 | F78: =E78+F16 -> 829 | G78: =F78+G16 -> 900 | H78: =G78+H16 -> 971 | I78: =H78+I16 -> 1037 | J78: =I78+J16 -> 1098 | K78: =J78+K16 -> 1159 | L78: =K78+L16 -> 1215 | ... O78: =N78+O16 -> 1353
A79: =Dashboard!A84 -> 4 | B79: =Dashboard!B84 -> LONGONOT- ACTIVE WATER | C79: =Dashboard!C84 -> No. | D79: ='Input Actual2024-25'!P77+'budget 2025-26'!D17 -> 529 | E79: =D79+E17 -> 539 | F79: =E79+F17 -> 549 | G79: =F79+G17 -> 559 | H79: =G79+H17 -> 569 | I79: =H79+I17 -> 579 | J79: =I79+J17 -> 589 | K79: =J79+K17 -> 599 | L79: =K79+L17 -> 609 | ... O79: =N79+O17 -> 639
A80: =Dashboard!A85 -> 0 | B80: =Dashboard!B85 -> TOTAL ACTIVE WATER CONNECTION SOUTHERN REGION | C80: =Dashboard!C85 -> No. | D80: =SUM(D76:D79) -> 3117 | E80: =SUM(E76:E79) -> 3187 | F80: =SUM(F76:F79) -> 3264 | G80: =SUM(G76:G79) -> 3416 | H80: =SUM(H76:H79) -> 3558 | I80: =SUM(I76:I79) -> 3695 | J80: =SUM(J76:J79) -> 3822 | K80: =SUM(K76:K79) -> 3949 | ... O80: =SUM(O76:O79) -> 4350
A81: =Dashboard!A87 -> 1 | B81: =Dashboard!B87 -> KAYOLE- ACTIVE WATER | C81: =Dashboard!C87 -> No. | D81: =2702+D19 -> 2740 | E81: =D81+E19 -> 2758 | F81: =E81+F19 -> 2776 | G81: =F81+G19 -> 2794 | H81: =G81+H19 -> 2812 | I81: =H81+I19 -> 2830 | J81: =I81+J19 -> 2863 | K81: =J81+K19 -> 2886 | L81: =K81+L19 -> 2909 | ... O81: =N81+O19 -> 2963
A82: =Dashboard!A88 -> 2 | B82: =Dashboard!B88 -> IHINDU- ACTIVE WATER | C82: =Dashboard!C88 -> No. | D82: =13+D20 -> 51 | E82: =D82+E20 -> 89 | F82: =E82+F20 -> 122 | G82: =F82+G20 -> 150 | H82: =G82+H20 -> 178 | I82: =H82+I20 -> 201 | J82: =I82+J20 -> 224 | K82: =J82+K20 -> 242 | L82: =K82+L20 -> 260 | ... O82: =N82+O20 -> 314
A83: =Dashboard!A89 -> 0 | B83: =Dashboard!B89 -> TOTAL ACTIVE WATER CONNECTION EASTERN REGION | C83: =Dashboard!C89 -> No. | D83: =D81+D82 -> 2791 | E83: =E81+E82 -> 2847 | F83: =F81+F82 -> 2898 | G83: =G81+G82 -> 2944 | H83: =H81+H82 -> 2990 | I83: =I81+I82 -> 3031 | J83: =J81+J82 -> 3087 | K83: =K81+K82 -> 3128 | ... O83: =O81+O82 -> 3277
A84: =Dashboard!A90 -> TOTAL ACTIVE CONNECTIONS-SEWER
A85: =Dashboard!A91 -> 1 | B85: =Dashboard!B91 -> CBD- ACTIVE SEWER | C85: =Dashboard!C91 -> No. | D85: ='Input Actual2024-25'!P81+'budget 2025-26'!D23 -> 389 | E85: =D85+E23 -> 390 | F85: =E85+F23 -> 391 | G85: =F85+G23 -> 392 | H85: =G85+H23 -> 393 | I85: =H85+I23 -> 394 | J85: =I85+J23 -> 395 | K85: =J85+K23 -> 396 | L85: =K85+L23 -> 397 | ... O85: =N85+O23 -> 400
A86: =Dashboard!A92 -> 2 | B86: =Dashboard!B92 -> CCCR- ACTIVE SEWER | C86: =Dashboard!C92 -> No. | D86: ='Input Actual2024-25'!P82+'budget 2025-26'!D24 -> 398 | E86: =D86+E24 -> 405 | F86: =E86+F24 -> 412 | G86: =F86+G24 -> 419 | H86: =G86+H24 -> 426 | I86: =H86+I24 -> 433 | J86: =I86+J24 -> 440 | K86: =J86+K24 -> 447 | L86: =K86+L24 -> 454 | ... O86: =N86+O24 -> 475
A87: =Dashboard!A93 -> 3 | B87: =Dashboard!B93 -> KABATI- ACTIVE SEWER | C87: =Dashboard!C93 -> No. | D87: ='Input Actual2024-25'!P83+'budget 2025-26'!D25 -> 332 | E87: =D87+E25 -> 335 | F87: =E87+F25 -> 338 | G87: =F87+G25 -> 341 | H87: =G87+H25 -> 344 | I87: =H87+I25 -> 347 | J87: =I87+J25 -> 350 | K87: =J87+K25 -> 353 | L87: =K87+L25 -> 356 | ... O87: =N87+O25 -> 365
A88: =Dashboard!A94 -> 4 | B88: =Dashboard!B94 -> SITE- ACTIVE SEWER | C88: =Dashboard!C94 -> No. | D88: ='Input Actual2024-25'!P84+'budget 2025-26'!D26 -> 520 | E88: =D88+E26 -> 521 | F88: =E88+F26 -> 522 | G88: =F88+G26 -> 523 | H88: =G88+H26 -> 524 | I88: =H88+I26 -> 525 | J88: =I88+J26 -> 526 | K88: =J88+K26 -> 527 | L88: =K88+L26 -> 528 | ... O88: =N88+O26 -> 531
A89: =Dashboard!A95 -> 5 | B89: =Dashboard!B95 -> KIHOTO- ACTIVE SEWER | C89: =Dashboard!C95 -> No. | D89: ='Input Actual2024-25'!P85+'budget 2025-26'!D27 -> 0 | E89: =D89+E27 -> 0 | F89: =E89+F27 -> 0 | G89: =F89+G27 -> 0 | H89: =G89+H27 -> 0 | I89: =H89+I27 -> 0 | J89: =I89+J27 -> 0 | K89: =J89+K27 -> 0 | L89: =K89+L27 -> 0 | ... O89: =N89+O27 -> 0
A90: =Dashboard!A96 -> 6 | B90: =Dashboard!B96 -> LAKEVIEW- ACTIVE SEWER | C90: =Dashboard!C96 -> No. | D90: ='Input Actual2024-25'!P86+'budget 2025-26'!D28 -> 156 | E90: =D90+E28 -> 157 | F90: =E90+F28 -> 158 | G90: =F90+G28 -> 159 | H90: =G90+H28 -> 160 | I90: =H90+I28 -> 161 | J90: =I90+J28 -> 162 | K90: =J90+K28 -> 163 | L90: =K90+L28 -> 164 | ... O90: =N90+O28 -> 167
A91: =Dashboard!A97 -> 7 | B91: =Dashboard!B97 -> HOPEWELL- ACTIVE SEWER | C91: =Dashboard!C97 -> No. | D91: ='Input Actual2024-25'!P87+'budget 2025-26'!D29 -> 2 | E91: =D91+E29 -> 2 | F91: =E91+F29 -> 2 | G91: =F91+G29 -> 2 | H91: =G91+H29 -> 2 | I91: =H91+I29 -> 2 | J91: =I91+J29 -> 2 | K91: =J91+K29 -> 2 | L91: =K91+L29 -> 2 | ... O91: =N91+O29 -> 2
A92: =Dashboard!A98 -> 0 | B92: =Dashboard!B98 -> TOTAL ACTIVE SEWER CONNECTION CENTRAL REGION | C92: =Dashboard!C98 -> No. | D92: =SUM(D85:D91) -> 1797 | E92: =SUM(E85:E91) -> 1810 | F92: =SUM(F85:F91) -> 1823 | G92: =SUM(G85:G91) -> 1836 | H92: =SUM(H85:H91) -> 1849 | I92: =SUM(I85:I91) -> 1862 | J92: =SUM(J85:J91) -> 1875 | K92: =SUM(K85:K91) -> 1888 | ... O92: =SUM(O85:O91) -> 1940
A93: =Dashboard!A99 -> 1 | B93: =Dashboard!B99 -> HELLSGATE- ACTIVE SEWER | C93: =Dashboard!C99 -> No. | D93: ='Input Actual2024-25'!P89+'budget 2025-26'!D31 -> 0 | E93: =D93+E31 -> 0 | F93: =E93+F31 -> 0 | G93: =F93+G31 -> 0 | H93: =G93+H31 -> 0 | I93: =H93+I31 -> 0 | J93: =I93+J31 -> 0 | K93: =J93+K31 -> 0 | L93: =K93+L31 -> 0 | ... O93: =N93+O31 -> 0
A94: =Dashboard!A100 -> 2 | B94: =Dashboard!B100 -> KAMERE- ACTIVE SEWER | C94: =Dashboard!C100 -> No. | D94: ='Input Actual2024-25'!P90+'budget 2025-26'!D32 -> 0 | E94: =D94+E32 -> 0 | F94: =E94+F32 -> 0 | G94: =F94+G32 -> 0 | H94: =G94+H32 -> 0 | I94: =H94+I32 -> 0 | J94: =I94+J32 -> 0 | K94: =J94+K32 -> 0 | L94: =K94+L32 -> 0 | ... O94: =N94+O32 -> 0
A95: =Dashboard!A101 -> 3 | B95: =Dashboard!B101 -> MAI-MAHIU- ACTIVE SEWER | C95: =Dashboard!C101 -> No. | D95: ='Input Actual2024-25'!P91+'budget 2025-26'!D33 -> 0 | E95: =D95+E33 -> 0 | F95: =E95+F33 -> 0 | G95: =F95+G33 -> 0 | H95: =G95+H33 -> 0 | I95: =H95+I33 -> 0 | J95: =I95+J33 -> 0 | K95: =J95+K33 -> 0 | L95: =K95+L33 -> 0 | ... O95: =N95+O33 -> 0
A96: =Dashboard!A102 -> 0 | B96: =Dashboard!B102 -> TOTAL ACTIVE SEWER CONNECTION SOUTHERN REGION | C96: =Dashboard!C102 -> No. | D96: =SUM(D93:D95) -> 0 | E96: =SUM(E93:E95) -> 0 | F96: =SUM(F93:F95) -> 0 | G96: =SUM(G93:G95) -> 0 | H96: =SUM(H93:H95) -> 0 | I96: =SUM(I93:I95) -> 0 | J96: =SUM(J93:J95) -> 0 | K96: =SUM(K93:K95) -> 0 | ... O96: =SUM(O93:O95) -> 0
A97: =Dashboard!A104 -> 1 | B97: =Dashboard!B104 -> KAYOLE- ACTIVE SEWER | C97: =Dashboard!C104 -> No. | D97: ='Input Actual2024-25'!P93+'budget 2025-26'!D35 -> 51 | E97: =D97+E35 -> 52 | F97: =E97+F35 -> 53 | G97: =F97+G35 -> 54 | H97: =G97+H35 -> 55 | I97: =H97+I35 -> 56 | J97: =I97+J35 -> 57 | K97: =J97+K35 -> 58 | L97: =K97+L35 -> 59 | ... O97: =N97+O35 -> 62
A98: =Dashboard!A105 -> SUMMARY CONNECTIONS
A99: =Dashboard!A106 -> 1 | B99: =Dashboard!B106 -> TOTAL WATER CONNECTIONS | C99: =Dashboard!C106 -> No. | D99: =D44+D49+D52 -> 12347 | E99: =E44+E49+E52 -> 12494 | F99: =F44+F49+F52 -> 12643 | G99: =G44+G49+G52 -> 12862 | H99: =H44+H49+H52 -> 13071 | I99: =I44+I49+I52 -> 13270 | J99: =J44+J49+J52 -> 13474 | K99: =K44+K49+K52 -> 13663 | ... O99: =O44+O49+O52 -> 14297
A100: =Dashboard!A107 -> 2 | B100: =Dashboard!B107 -> TOTAL SEWER CONNECTIONS | C100: =Dashboard!C107 -> No. | D100: =D65+D61+D66 -> 2169 | E100: =E65+E61+E66 -> 2183 | F100: =F65+F61+F66 -> 2197 | G100: =G65+G61+G66 -> 2211 | H100: =H65+H61+H66 -> 2225 | I100: =I65+I61+I66 -> 2239 | J100: =J65+J61+J66 -> 2253 | K100: =K65+K61+K66 -> 2267 | ... O100: =O65+O61+O66 -> 2323
A101: =Dashboard!A108 -> 3 | B101: =Dashboard!B108 -> TOTAL ACTIVE WATER CONNECTIONS | C101: =Dashboard!C108 -> No. | D101: =D75+D80+D83 -> 10373 | E101: =E75+E80+E83 -> 10520 | F101: =F75+F80+F83 -> 10669 | G101: =G75+G80+G83 -> 10888 | H101: =H75+H80+H83 -> 11097 | I101: =I75+I80+I83 -> 11296 | J101: =J75+J80+J83 -> 11500 | K101: =K75+K80+K83 -> 11689 | ... O101: =O75+O80+O83 -> 12323
...

Sheet Input Actual2025-26
A1: =Dashboard!A1 -> SALES & CC DASHBOARD | E1: =E13+E18+E19 -> 136 | G1: =G13+G18+G19 -> 129 | H1: =H13+H18+H19 -> 149 | I1: =I13+I18+I19 -> 96 | J1: =J13+J18+J19 -> 134
E2: =E31+E35+E36 -> 0 | G2: =G31+G35+G36 -> 4 | H2: =H31+H35+H36 -> 3 | I2: =I31+I35+I36 -> 5 | J2: =J31+J35+J36 -> 0
B4: MONTH | C4: UNIT | E4: JUL | F4: AUG | G4: SEP | H4: OCT | I4: NOV | J4: DEC | K4: JAN | L4: FEB | M4: MAR | N4: APR | O4: MAY | P4: JUN
A5: =Dashboard!A5 -> NEW CONNECTIONS WATER
A6: =Dashboard!A6 -> 1 | B6: =Dashboard!B6 -> CBD - NEW WATER | C6: =Dashboard!C6 -> No. | D6: 8 | E6: 0 | F6: 0 | G6: 0 | H6: 1 | I6: 0 | J6: 0 | K6: 1 | L6: 0
A7: =Dashboard!A7 -> 2 | B7: =Dashboard!B7 -> CCCR- NEW WATER | C7: =Dashboard!C7 -> No. | D7: 14 | E7: 0 | F7: 3 | G7: 2 | H7: 2 | I7: 3 | J7: 2 | K7: 5 | L7: 3
A8: =Dashboard!A8 -> 3 | B8: =Dashboard!B8 -> KABATI- NEW WATER | C8: =Dashboard!C8 -> No. | D8: 4 | E8: 0 | F8: 0 | G8: 5 | H8: 1 | I8: 2 | J8: 0 | K8: 2 | L8: 0
A9: =Dashboard!A9 -> 4 | B9: =Dashboard!B9 -> SITE- NEW WATER | C9: =Dashboard!C9 -> No. | D9: 2 | E9: 0 | F9: 2 | G9: 0 | H9: 3 | I9: 0 | J9: 0 | K9: 2 | L9: 0
A10: =Dashboard!A10 -> 5 | B10: =Dashboard!B10 -> KIHOTO- NEW WATER | C10: =Dashboard!C10 -> No. | D10: 5 | E10: 2 | F10: 0 | G10: 0 | H10: 0 | I10: 0 | J10: 0 | K10: 0 | L10: 1
A11: =Dashboard!A11 -> 6 | B11: =Dashboard!B11 -> LAKEVIEW- NEW WATER | C11: =Dashboard!C11 -> No. | D11: 7 | E11: 2 | F11: 8 | G11: 0 | H11: 2 | I11: 0 | J11: 0 | K11: 2 | L11: 0
A12: =Dashboard!A12 -> 7 | B12: =Dashboard!B12 -> HOPEWELL- NEW WATER | C12: =Dashboard!C12 -> No. | D12: =Dashboard!D12 -> l | E12: 1 | F12: 0 | G12: 0 | H12: 14 | I12: 1 | J12: 12 | K12: 22 | L12: 3
A13: =Dashboard!A13 -> 0 | B13: =Dashboard!B13 -> TOTAL NEW WATER CONNECTIONS CENTRAL REGION | C13: =Dashboard!C13 -> No. | D13: 40 | E13: =SUM(E6:E12) -> 5 | F13: =SUM(F6:F12) -> 13 | G13: =SUM(G6:G12) -> 7 | H13: =SUM(H6:H12) -> 23 | I13: =SUM(I6:I12) -> 6 | J13: =SUM(J6:J12) -> 14 | K13: =SUM(K6:K12) -> 34 | L13: =SUM(L6:L12) -> 7 | ... P13: =SUM(P6:P12) -> 0
A14: =Dashboard!A14 -> 1 | B14: =Dashboard!B14 -> HELLSGATE- NEW WATER | C14: =Dashboard!C14 -> No. | D14: 24 | E14: 37 | F14: 18 | G14: 13 | H14: 11 | I14: 10 | J14: 10 | K14: 34 | L14: 14
A15: =Dashboard!A15 -> 2 | B15: =Dashboard!B15 -> KAMERE- NEW WATER | C15: =Dashboard!C15 -> No. | D15: 0 | E15: 0 | F15: 4 | G15: 14 | H15: 1 | I15: 15 | J15: 4 | K15: 4 | L15: 2
A16: =Dashboard!A16 -> 3 | B16: =Dashboard!B16 -> MAI-MAHIU- NEW WATER | C16: =Dashboard!C16 -> No. | D16: 24 | E16: 66 | F16: 59 | G16: 29 | H16: 73 | I16: 27 | J16: 66 | K16: 31 | L16: 33
A17: =Dashboard!A17 -> 4 | B17: =Dashboard!B17 -> LONGONOT- NEW WATER | C17: =Dashboard!C17 -> No. | D17: 24 | E17: 11 | F17: 20 | G17: 11 | H17: 11 | I17: 8 | J17: 2 | K17: 6 | L17: 2
A18: =Dashboard!A18 -> 0 | B18: =Dashboard!B18 -> TOTAL NEW WATER CONNECTION SOUTHERN REGION | C18: =Dashboard!C18 -> No. | D18: 48 | E18: =SUM(E14:E17) -> 114 | F18: =SUM(F14:F17) -> 101 | G18: =SUM(G14:G17) -> 67 | H18: =SUM(H14:H17) -> 96 | I18: =SUM(I14:I17) -> 60 | J18: =SUM(J14:J17) -> 82 | K18: =SUM(K14:K17) -> 75 | L18: =SUM(L14:L17) -> 51 | ... P18: =SUM(P14:P17) -> 0
A19: =Dashboard!A20 -> 1 | B19: =Dashboard!B20 -> KAYOLE- NEW WATER | C19: =Dashboard!C20 -> No. | D19: 25 | E19: 17 | F19: 40 | G19: 55 | H19: 30 | I19: 30 | J19: 38 | K19: 43 | L19: 17
A20: =Dashboard!A21 -> 2 | B20: =Dashboard!B21 -> IHINDU- NEW WATER | C20: =Dashboard!C21 -> No. | D20: =Dashboard!D21 -> l | E20: 1 | F20: 0 | G20: 1 | H20: 0 | I20: 0 | J20: 0 | K20: 2 | L20: 0
A21: =Dashboard!A22 -> 0 | B21: =Dashboard!B22 -> TOTAL NEW W CONNECTION EASTERN REGION | C21: =Dashboard!C22 -> No. | E21: =E20+E19 -> 18 | F21: =F20+F19 -> 40 | G21: =G20+G19 -> 56 | H21: =H20+H19 -> 30 | I21: =I20+I19 -> 30 | J21: =J20+J19 -> 38 | K21: =K20+K19 -> 45 | L21: =L20+L19 -> 17 | ... P21: =P20+P19 -> 0
B22: TOTAL NEW CONNECTIONS WATER | E22: =E21+E18+E13 -> 137 | F22: =F21+F18+F13 -> 154 | G22: =G21+G18+G13 -> 130 | H22: =H21+H18+H13 -> 149 | I22: =I21+I18+I13 -> 96 | J22: =J21+J18+J13 -> 134 | K22: =K21+K18+K13 -> 154 | L22: =L21+L18+L13 -> 75 | ... P22: =P21+P18+P13 -> 0
A23: =Dashboard!A23 -> NEW CONNECTIONS SEWER
A24: =Dashboard!A24 -> 1 | B24: =Dashboard!B24 -> CBD- NEW SEWER | C24: =Dashboard!C24 -> No. | D24: 0 | E24: 0 | F24: 0 | G24: 0 | H24: 0 | I24: 0 | J24: 0 | K24: 0 | L24: 0
A25: =Dashboard!A25 -> 2 | B25: =Dashboard!B25 -> CCCR- NEW SEWER | C25: =Dashboard!C25 -> No. | D25: 0 | E25: 0 | F25: 0 | G25: 0 | H25: 1 | I25: 1 | J25: 0 | K25: 1 | L25: 2
A26: =Dashboard!A26 -> 3 | B26: =Dashboard!B26 -> KABATI- NEW SEWER | C26: =Dashboard!C26 -> No. | D26: 0 | E26: 0 | F26: 1 | G26: 1 | H26: 0 | I26: 1 | J26: 0 | K26: 2 | L26: 1
A27: =Dashboard!A27 -> 4 | B27: =Dashboard!B27 -> SITE- NEW SEWER | C27: =Dashboard!C27 -> No. | D27: 0 | E27: 0 | F27: 0 | G27: 1 | H27: 0 | I27: 0 | J27: 0 | K27: 0 | L27: 0
A28: =Dashboard!A28 -> 5 | B28: =Dashboard!B28 -> KIHOTO- NEW SEWER | C28: =Dashboard!C28 -> No. | D28: 0 | E28: 0 | F28: 0 | G28: 0 | H28: 0 | I28: 0 | J28: 0 | K28: 0 | L28: 0
A29: =Dashboard!A29 -> 6 | B29: =Dashboard!B29 -> LAKEVIEW- NEW SEWER | C29: =Dashboard!C29 -> No. | D29: 2 | E29: 0 | F29: 1 | G29: 0 | H29: 1 | I29: 0 | J29: 0 | K29: 1 | L29: 0
A30: =Dashboard!A30 -> 7 | B30: =Dashboard!B30 -> HOPEWELL- NEW SEWER | C30: =Dashboard!C30 -> No. | D30: 2 | E30: 0 | F30: 0 | G30: 0 | H30: 0 | I30: 0 | J30: 0 | K30: 0 | L30: 0
A31: =Dashboard!A31 -> 0 | B31: =Dashboard!B31 -> TOTAL NEW SEWER CONNECTIONS CENTRAL REGION | C31: =Dashboard!C31 -> No. | D31: 2 | E31: =SUM(E24:E30) -> 0 | F31: =SUM(F24:F30) -> 2 | G31: =SUM(G24:G30) -> 2 | H31: =SUM(H24:H30) -> 2 | I31: =SUM(I24:I30) -> 2 | J31: =SUM(J24:J30) -> 0 | K31: =SUM(K24:K30) -> 4 | L31: =SUM(L24:L30) -> 3 | ... P31: =SUM(P24:P30) -> 0
A32: =Dashboard!A32 -> 1 | B32: =Dashboard!B32 -> HELLSGATE- NEW SEWER | C32: =Dashboard!C32 -> No. | E32: 0 | F32: =F64-E64 -> 0 | G32: =G64-F64 -> 0 | H32: =H64-G64 -> 0 | I32: =I64-H64 -> 0 | J32: =J64-I64 -> 0 | K32: =K64-J64 -> 0 | L32: =L64-K64 -> 0 | M32: =M64-L64 -> 0 | ... P32: =P64-O64 -> 0
A33: =Dashboard!A33 -> 2 | B33: =Dashboard!B33 -> KAMERE- NEW SEWER | C33: =Dashboard!C33 -> No. | E33: 0 | F33: =F65-E65 -> 0 | G33: =G65-F65 -> 0 | H33: =H65-G65 -> 0 | I33: =I65-H65 -> 0 | J33: =J65-I65 -> 0 | K33: =K65-J65 -> 0 | L33: =L65-K65 -> 0 | M33: =M65-L65 -> 0 | ... P33: =P65-O65 -> 0
A34: =Dashboard!A34 -> 3 | B34: =Dashboard!B34 -> MAI-MAHIU- NEW SEWER | C34: =Dashboard!C34 -> No. | E34: 0 | F34: =F66-E66 -> 0 | G34: =G66-F66 -> 0 | H34: =H66-G66 -> 0 | I34: =I66-H66 -> 0 | J34: =J66-I66 -> 0 | K34: =K66-J66 -> 0 | L34: =L66-K66 -> 0 | M34: =M66-L66 -> 0 | ... P34: =P66-O66 -> 0
A35: =Dashboard!A35 -> 0 | B35: =Dashboard!B35 -> TOTAL NEW S CONNECTION SOUTHERN REGION | C35: =Dashboard!C35 -> No. | D35: 0 | E35: =SUM(E32:E34) -> 0 | F35: =SUM(F32:F34) -> 0 | G35: =SUM(G32:G34) -> 0 | H35: =SUM(H32:H34) -> 0 | I35: =SUM(I32:I34) -> 0 | J35: =SUM(J32:J34) -> 0 | K35: =SUM(K32:K34) -> 0 | L35: =SUM(L32:L34) -> 0 | ... P35: =SUM(P32:P34) -> 0
A36: =Dashboard!A37 -> 1 | B36: =Dashboard!B37 -> KAYOLE- NEW SEWER | C36: =Dashboard!C37 -> No. | D36: 6 | E36: 0 | F36: 2 | G36: 2 | H36: 1 | I36: 3 | J36: 0 | K36: 0 | L36: 2
B37: TOTAL NEW CONNECTIONS -SEWER | D37: 8 | E37: =E36+E31 -> 0 | F37: =F36+F31 -> 4 | G37: =G36+G31 -> 4 | H37: =H36+H31 -> 3 | I37: =I36+I31 -> 5 | J37: =J36+J31 -> 0 | K37: =K36+K31 -> 4 | L37: =L36+L31 -> 5 | ... P37: =P36+P31 -> 0
A38: =Dashboard!A38 -> TOTAL CONNECTIONS-WATER
A39: =Dashboard!A39 -> 1 | B39: =Dashboard!B39 -> CBD- WATER | C39: =Dashboard!C39 -> No. | D39: 773 | E39: 790 | F39: 791 | G39: 791 | H39: 793 | I39: 793 | J39: 793 | K39: 792 | L39: 792
A40: =Dashboard!A40 -> 2 | B40: =Dashboard!B40 -> CCCR- WATER | C40: =Dashboard!C40 -> No. | D40: 779 | E40: 880 | F40: 883 | G40: 885 | H40: 886 | I40: 889 | J40: 890 | K40: 895 | L40: 898
A41: =Dashboard!A41 -> 3 | B41: =Dashboard!B41 -> KABATI- WATER | C41: =Dashboard!C41 -> No. | D41: 908 | E41: 953 | F41: 952 | G41: 956 | H41: 956 | I41: 957 | J41: 957 | K41: 959 | L41: 959
A42: =Dashboard!A42 -> 4 | B42: =Dashboard!B42 -> SITE- WATER | C42: =Dashboard!C42 -> No. | D42: 921 | E42: 939 | F42: 940 | G42: 940 | H42: 943 | I42: 943 | J42: 942 | K42: 944 | L42: 944
A43: =Dashboard!A43 -> 5 | B43: =Dashboard!B43 -> KIHOTO- WATER | C43: =Dashboard!C43 -> No. | D43: 207 | E43: 221 | F43: 221 | G43: 221 | H43: 221 | I43: 221 | J43: 221 | K43: 221 | L43: 222
A44: =Dashboard!A44 -> 6 | B44: =Dashboard!B44 -> LAKEVIEW- WATER | C44: =Dashboard!C44 -> No. | D44: 1413 | E44: 1154 | F44: 1162 | G44: 1163 | H44: 1165 | I44: 1166 | J44: 1166 | K44: 1168 | L44: 1168
A45: =Dashboard!A45 -> 7 | B45: =Dashboard!B45 -> HOPEWELL- WATER | C45: =Dashboard!C45 -> No. | D45: 1413 | E45: 366 | F45: 366 | G45: 366 | H45: 380 | I45: 381 | J45: 393 | K45: 415 | L45: 418
A46: =Dashboard!A46 -> 0 | B46: =Dashboard!B46 -> TOTALWATER CONNECTION CENTRAL REGION | C46: =Dashboard!C46 -> No. | D46: 5001 | E46: =SUM(E39:E45) -> 5303 | F46: =SUM(F39:F45) -> 5315 | G46: =SUM(G39:G45) -> 5322 | H46: =SUM(H39:H45) -> 5344 | I46: =SUM(I39:I45) -> 5350 | J46: =SUM(J39:J45) -> 5362 | K46: =SUM(K39:K45) -> 5394 | L46: =SUM(L39:L45) -> 5401 | ... P46: =SUM(P39:P45) -> 0
A47: =Dashboard!A47 -> 1 | B47: =Dashboard!B47 -> HELLSGATE- WATER | C47: =Dashboard!C47 -> No. | D47: 1607 | E47: 1872 | F47: 1889 | G47: 1901 | H47: 1910 | I47: 1919 | J47: 1929 | K47: 1962 | L47: 1975
A48: =Dashboard!A48 -> 2 | B48: =Dashboard!B48 -> KAMERE- WATER | C48: =Dashboard!C48 -> No. | D48: 343 | E48: 365 | F48: 368 | G48: 382 | H48: 382 | I48: 397 | J48: 401 | K48: 405 | L48: 407
A49: =Dashboard!A49 -> 3 | B49: =Dashboard!B49 -> MAI-MAHIU- WATER | C49: =Dashboard!C49 -> No. | D49: 1194 | E49: 1211 | F49: 1265 | G49: 1292 | H49: 1361 | I49: 1387 | J49: 1447 | K49: 1477 | L49: 1509
A50: =Dashboard!A50 -> 4 | B50: =Dashboard!B50 -> LONGONOT- WATER | C50: =Dashboard!C50 -> No. | D50: =Dashboard!D50 -> l | E50: 629 | F50: 653 | G50: 665 | H50: 676 | I50: 684 | J50: 686 | K50: 693 | L50: 696
A51: =Dashboard!A51 -> 0 | B51: =Dashboard!B51 -> TOTAL WATER CONNECTION SOUTHERN REGION | C51: =Dashboard!C51 -> No. | D51: 3144 | E51: =SUM(E47:E50) -> 4077 | F51: =SUM(F47:F50) -> 4175 | G51: =SUM(G47:G50) -> 4240 | H51: =SUM(H47:H50) -> 4329 | I51: =SUM(I47:I50) -> 4387 | J51: =SUM(J47:J50) -> 4463 | K51: =SUM(K47:K50) -> 4537 | L51: =SUM(L47:L50) -> 4587 | ... P51: =SUM(P47:P50) -> 0
A52: =Dashboard!A53 -> 1 | B52: =Dashboard!B53 -> KAYOLE-WATER | C52: =Dashboard!C53 -> No. | D52: 2457 | E52: 2880 | F52: 2920 | G52: 2975 | H52: 3005 | I52: 3035 | J52: 3073 | K52: 3115 | L52: 3131
A53: =Dashboard!A54 -> 2 | B53: =Dashboard!B54 -> IHINDU-WATER | C53: =Dashboard!C54 -> No. | D53: =Dashboard!D54 -> l | E53: 57 | F53: 57 | G53: 58 | H53: 58 | I53: 58 | J53: 58 | K53: 60 | L53: 60
A54: =Dashboard!A55 -> 0 | B54: =Dashboard!B55 -> TOTAL WATER CONNECTION EASTERN REGION | C54: =Dashboard!C55 -> No. | D54: =Dashboard!D55 -> l | E54: =E52+E53 -> 2937 | F54: =F52+F53 -> 2977 | G54: =G52+G53 -> 3033 | H54: =H52+H53 -> 3063 | I54: =I52+I53 -> 3093 | J54: =J52+J53 -> 3131 | K54: =K52+K53 -> 3175 | L54: =L52+L53 -> 3191 | ... P54: =P52+P53 -> 0
A55: =Dashboard!A56 -> TOTAL CONNECTIONS-SEWER
A56: =Dashboard!A57 -> 1 | B56: =Dashboard!B57 -> CBD- SEWER | C56: =Dashboard!C57 -> No. | D56: 439 | E56: 480 | F56: 481 | G56: 482 | H56: 481 | I56: 481 | J56: 482 | K56: 482 | L56: 482
A57: =Dashboard!A58 -> 2 | B57: =Dashboard!B58 -> CCCR-SEWER | C57: =Dashboard!C58 -> No. | D57: 358 | E57: 453 | F57: 456 | G57: 456 | H57: 456 | I57: 457 | J57: 457 | K57: 456 | L57: 456
A58: =Dashboard!A59 -> 3 | B58: =Dashboard!B59 -> KABATI-SEWER | C58: =Dashboard!C59 -> No. | D58: 326 | E58: 382 | F58: 384 | G58: 383 | H58: 383 | I58: 382 | J58: 382 | K58: 384 | L58: 384
A59: =Dashboard!A60 -> 4 | B59: =Dashboard!B60 -> SITE- SEWER | C59: =Dashboard!C60 -> No. | D59: 530 | E59: 604 | F59: 604 | G59: 604 | H59: 604 | I59: 604 | J59: 603 | K59: 604 | L59: 604
A60: =Dashboard!A61 -> 5 | B60: =Dashboard!B61 -> KIHOTO- SEWER | C60: =Dashboard!C61 -> No. | D60: 0 | E60: 0 | F60: 0 | G60: 0 | H60: 0 | I60: 0 | J60: 0 | K60: 0 | L60: 0
A61: =Dashboard!A62 -> 6 | B61: =Dashboard!B62 -> LAKEVIEW- SEWER | C61: =Dashboard!C62 -> No. | D61: 166 | E61: 180 | F61: 180 | G61: 180 | H61: 179 | I61: 180 | J61: 183 | K61: 184 | L61: 184
A62: =Dashboard!A63 -> 7 | B62: =Dashboard!B63 -> HOPEWELL- SEWER | C62: =Dashboard!C63 -> No. | D62: 166 | E62: 2 | F62: 2 | G62: 2 | H62: 2 | I62: 2 | J62: 2 | K62: 2 | L62: 2
A63: =Dashboard!A64 -> 0 | B63: =Dashboard!B64 -> TOTAL SEWER CONNECTION CENTRAL REGION | C63: =Dashboard!C64 -> No. | D63: 1819 | E63: =SUM(E56:E62) -> 2101 | F63: =SUM(F56:F62) -> 2107 | G63: =SUM(G56:G62) -> 2107 | H63: =SUM(H56:H62) -> 2105 | I63: =SUM(I56:I62) -> 2106 | J63: =SUM(J56:J62) -> 2109 | K63: =SUM(K56:K62) -> 2112 | L63: =SUM(L56:L62) -> 2112 | ... P63: =SUM(P56:P62) -> 0
A64: =Dashboard!A66 -> 1 | B64: =Dashboard!B66 -> HELLSGATE-SEWER | C64: =Dashboard!C66 -> No. | D64: 0 | E64: 0 | F64: 0 | G64: 0 | H64: 0 | I64: 0 | J64: 0 | K64: 0 | L64: 0 | M64: 0 | N64: 0 | O64: 0 | P64: 0
A65: =Dashboard!A67 -> 2 | B65: =Dashboard!B67 -> KAMERE- SEWER | C65: =Dashboard!C67 -> No. | D65: 0 | E65: 0 | F65: 0 | G65: 0 | H65: 0 | I65: 0 | J65: 0 | K65: 0 | L65: 0 | M65: 0 | N65: 0 | O65: 0 | P65: 0
A66: =Dashboard!A68 -> 3 | B66: =Dashboard!B68 -> MAI-MAHIU-SEWER | C66: =Dashboard!C68 -> No. | D66: 0 | E66: 0 | F66: 0 | G66: 0 | H66: 0 | I66: 0 | J66: 0 | K66: 0 | L66: 0 | M66: 0 | N66: 0 | O66: 0 | P66: 0
A67: =Dashboard!A69 -> 0 | B67: =Dashboard!B69 -> TOTAL SEWER CONNECTION SOUTHERNREGION | C67: =Dashboard!C69 -> No. | D67: 0 | E67: =SUM(E64:E66) -> 0 | F67: =SUM(F64:F66) -> 0 | G67: =SUM(G64:G66) -> 0 | H67: =SUM(H64:H66) -> 0 | I67: =SUM(I64:I66) -> 0 | J67: =SUM(J64:J66) -> 0 | K67: =SUM(K64:K66) -> 0 | L67: =SUM(L64:L66) -> 0 | ... P67: =SUM(P64:P66) -> 0
A68: =Dashboard!A71 -> 1 | B68: =Dashboard!B71 -> KAYOLE-SEWER | C68: =Dashboard!C71 -> No. | D68: 21 | E68: 52 | F68: 54 | G68: 56 | H68: 56 | I68: 57 | J68: 61 | K68: 63 | L68: 64
A69: =Dashboard!A72 -> TOTAL ACTIVE CONNECTIONS-WATER
A70: =Dashboard!A73 -> 1 | B70: =Dashboard!B73 -> CBD- ACTIVE WATER | C70: =Dashboard!C73 -> No. | D70: 583 | E70: 595 | F70: 596 | G70: 596 | H70: 598 | I70: 598 | J70: 599 | K70: 598 | L70: 600
A71: =Dashboard!A74 -> 2 | B71: =Dashboard!B74 -> CCCR- ACTIVE WATER | C71: =Dashboard!C74 -> No. | D71: 593 | E71: 700 | F71: 702 | G71: 705 | H71: 705 | I71: 710 | J71: 709 | K71: 709 | L71: 716
A72: =Dashboard!A75 -> 3 | B72: =Dashboard!B75 -> KABATI- ACTIVE WATER | C72: =Dashboard!C75 -> No. | D72: 811 | E72: 864 | F72: 864 | G72: 868 | H72: 868 | I72: 868 | J72: 868 | K72: 868 | L72: 870
A73: =Dashboard!A76 -> 4 | B73: =Dashboard!B76 -> SITE- ACTIVE WATER | C73: =Dashboard!C76 -> No. | D73: 811 | E73: 836 | F73: 836 | G73: 837 | H73: 840 | I73: 840 | J73: 840 | K73: 840 | L73: 842
A74: =Dashboard!A77 -> 5 | B74: =Dashboard!B77 -> KIHOTO-ACTIVE WATER | C74: =Dashboard!C77 -> No. | D74: 157 | E74: 176 | F74: 176 | G74: 176 | H74: 176 | I74: 176 | J74: 176 | K74: 176 | L74: 176
A75: =Dashboard!A78 -> 6 | B75: =Dashboard!B78 -> LAKEVIEW- ACTIVE WATER | C75: =Dashboard!C78 -> No. | D75: 1180 | E75: 984 | F75: 990 | G75: 993 | H75: 993 | I75: 996 | J75: 997 | K75: 999 | L75: 1000
A76: =Dashboard!A79 -> 7 | B76: =Dashboard!B79 -> HOPEWELL- ACTIVE WATER | C76: =Dashboard!C79 -> No. | D76: =Dashboard!D79 -> l | E76: 295 | F76: 297 | G76: 298 | H76: 299 | I76: 300 | J76: 302 | K76: 339 | L76: 343
A77: =Dashboard!A80 -> 0 | B77: =Dashboard!B80 -> TOTAL ACTIVE WATER CONNECTION CENTRAL REGION | C77: =Dashboard!C80 -> No. | D77: 4135 | E77: =SUM(E70:E76) -> 4450 | F77: =SUM(F70:F76) -> 4461 | G77: =SUM(G70:G76) -> 4473 | H77: =SUM(H70:H76) -> 4479 | I77: =SUM(I70:I76) -> 4488 | J77: =SUM(J70:J76) -> 4491 | K77: =SUM(K70:K76) -> 4529 | L77: =SUM(L70:L76) -> 4547 | ... P77: =SUM(P70:P76) -> 0
A78: =Dashboard!A81 -> 1 | B78: =Dashboard!B81 -> HELLSGATE- ACTIVE WATER | C78: =Dashboard!C81 -> No. | D78: 1390 | E78: 1600 | F78: 1622 | G78: 1633 | H78: 1658 | I78: 1670 | J78: 1683 | K78: 1696 | L78: 1719
A79: =Dashboard!A82 -> 2 | B79: =Dashboard!B82 -> KAMERE- ACTIVE WATER | C79: =Dashboard!C82 -> No. | D79: 243 | E79: 264 | F79: 267 | G79: 269 | H79: 269 | I79: 271 | J79: 286 | K79: 292 | L79: 296
A80: =Dashboard!A83 -> 3 | B80: =Dashboard!B83 -> MAI-MAHIU- ACTIVE WATER | C80: =Dashboard!C83 -> No. | D80: 682 | E80: 735 | F80: 755 | G80: 798 | H80: 843 | I80: 874 | J80: 928 | K80: 955 | L80: 985
A81: =Dashboard!A84 -> 4 | B81: =Dashboard!B84 -> LONGONOT- ACTIVE WATER | C81: =Dashboard!C84 -> No. | D81: 682 | E81: 530 | F81: 546 | G81: 564 | H81: 577 | I81: 589 | J81: 594 | K81: 599 | L81: 605
A82: =Dashboard!A85 -> 0 | B82: =Dashboard!B85 -> TOTAL ACTIVE WATER CONNECTION SOUTHERN REGION | C82: =Dashboard!C85 -> No. | D82: 2315 | E82: =SUM(E78:E81) -> 3129 | F82: =SUM(F78:F81) -> 3190 | G82: =SUM(G78:G81) -> 3264 | H82: =SUM(H78:H81) -> 3347 | I82: =SUM(I78:I81) -> 3404 | J82: =SUM(J78:J81) -> 3491 | K82: =SUM(K78:K81) -> 3542 | L82: =SUM(L78:L81) -> 3605 | ... P82: =SUM(P78:P81) -> 0
A83: =Dashboard!A87 -> 1 | B83: =Dashboard!B87 -> KAYOLE- ACTIVE WATER | C83: =Dashboard!C87 -> No. | D83: 2294 | E83: 2715 | F83: 2750 | G83: 2794 | H83: 2818 | I83: 2835 | J83: 2865 | K83: 2894 | L83: 2926
A84: =Dashboard!A88 -> 2 | B84: =Dashboard!B88 -> IHINDU- ACTIVE WATER | C84: =Dashboard!C88 -> No. | D84: =Dashboard!D88 -> l | E84: 13 | F84: 16 | G84: 16 | H84: 16 | I84: 16 | J84: 16 | K84: 17 | L84: 17
A85: =Dashboard!A89 -> 0 | B85: =Dashboard!B89 -> TOTAL ACTIVE WATER CONNECTION EASTERN REGION | C85: =Dashboard!C89 -> No. | D85: =Dashboard!D89 -> l | E85: =E83+E84 -> 2728 | F85: =F83+F84 -> 2766 | G85: =G83+G84 -> 2810 | H85: =H83+H84 -> 2834 | I85: =I83+I84 -> 2851 | J85: =J83+J84 -> 2881 | K85: =K83+K84 -> 2911 | L85: =L83+L84 -> 2943 | ... P85: =P83+P84 -> 0
A86: =Dashboard!A90 -> TOTAL ACTIVE CONNECTIONS-SEWER
A87: =Dashboard!A90 -> TOTAL ACTIVE CONNECTIONS-SEWER
A88: =Dashboard!A91 -> 1 | B88: =Dashboard!B91 -> CBD- ACTIVE SEWER | C88: =Dashboard!C91 -> No. | D88: 352 | E88: 387 | F88: 388 | G88: 389 | H88: 388 | I88: 388 | J88: 389 | K88: 389 | L88: 389
A89: =Dashboard!A92 -> 2 | B89: =Dashboard!B92 -> CCCR- ACTIVE SEWER | C89: =Dashboard!C92 -> No. | D89: 297 | E89: 390 | F89: 392 | G89: 392 | H89: 391 | I89: 392 | J89: 392 | K89: 392 | L89: 392
A90: =Dashboard!A93 -> 3 | B90: =Dashboard!B93 -> KABATI- ACTIVE SEWER | C90: =Dashboard!C93 -> No. | D90: 272 | E90: 328 | F90: 330 | G90: 329 | H90: 329 | I90: 328 | J90: 328 | K90: 330 | L90: 330
A91: =Dashboard!A94 -> 4 | B91: =Dashboard!B94 -> SITE- ACTIVE SEWER | C91: =Dashboard!C94 -> No. | D91: 441 | E91: 518 | F91: 518 | G91: 518 | H91: 517 | I91: 517 | J91: 517 | K91: 518 | L91: 518
A92: =Dashboard!A95 -> 5 | B92: =Dashboard!B95 -> KIHOTO- ACTIVE SEWER | C92: =Dashboard!C95 -> No. | D92: 0 | E92: 0 | F92: 0 | G92: 0 | H92: 0 | I92: 0 | J92: 0 | K92: 0 | L92: 0
A93: =Dashboard!A96 -> 6 | B93: =Dashboard!B96 -> LAKEVIEW- ACTIVE SEWER | C93: =Dashboard!C96 -> No. | D93: 138 | E93: 155 | F93: 155 | G93: 155 | H93: 154 | I93: 155 | J93: 158 | K93: 159 | L93: 159
A94: =Dashboard!A97 -> 7 | B94: =Dashboard!B97 -> HOPEWELL- ACTIVE SEWER | C94: =Dashboard!C97 -> No. | D94: =Dashboard!D97 -> l | E94: 2 | F94: 2 | G94: 2 | H94: 2 | I94: 2 | J94: 2 | K94: 2 | L94: 2
A95: =Dashboard!A98 -> 0 | B95: =Dashboard!B98 -> TOTAL ACTIVE SEWER CONNECTION CENTRAL REGION | C95: =Dashboard!C98 -> No. | D95: 1500 | E95: =SUM(E88:E94) -> 1780 | F95: =SUM(F88:F94) -> 1785 | G95: =SUM(G88:G94) -> 1785 | H95: =SUM(H88:H94) -> 1781 | I95: =SUM(I88:I94) -> 1782 | J95: =SUM(J88:J94) -> 1786 | K95: =SUM(K88:K94) -> 1790 | L95: =SUM(L88:L94) -> 1790 | ... P95: =SUM(P88:P94) -> 0
A96: =Dashboard!A99 -> 1 | B96: =Dashboard!B99 -> HELLSGATE- ACTIVE SEWER | C96: =Dashboard!C99 -> No. | E96: 0 | F96: 0 | G96: 0 | H96: 0 | I96: 0 | J96: 0 | K96: 0 | L96: 0 | M96: 0 | N96: 0 | O96: 0 | P96: 0
A97: =Dashboard!A100 -> 2 | B97: =Dashboard!B100 -> KAMERE- ACTIVE SEWER | C97: =Dashboard!C100 -> No. | E97: 0 | F97: 0 | G97: 0 | H97: 0 | I97: 0 | J97: 0 | K97: 0 | L97: 0 | M97: 0 | N97: 0 | O97: 0 | P97: 0
A98: =Dashboard!A101 -> 3 | B98: =Dashboard!B101 -> MAI-MAHIU- ACTIVE SEWER | C98: =Dashboard!C101 -> No. | E98: 0 | F98: 0 | G98: 0 | H98: 0 | I98: 0 | J98: 0 | K98: 0 | L98: 0 | M98: 0 | N98: 0 | O98: 0 | P98: 0
A99: =Dashboard!A102 -> 0 | B99: =Dashboard!B102 -> TOTAL ACTIVE SEWER CONNECTION SOUTHERN REGION | C99: =Dashboard!C102 -> No. | D99: 0 | E99: =SUM(E96:E98) -> 0 | F99: =SUM(F96:F98) -> 0 | G99: =SUM(G96:G98) -> 0 | H99: =SUM(H96:H98) -> 0 | I99: =SUM(I96:I98) -> 0 | J99: =SUM(J96:J98) -> 0 | K99: =SUM(K96:K98) -> 0 | L99: =SUM(L96:L98) -> 0 | ... P99: =SUM(P96:P98) -> 0
A100: =Dashboard!A104 -> 1 | B100: =Dashboard!B104 -> KAYOLE- ACTIVE SEWER | C100: =Dashboard!C104 -> No. | D100: 20 | E100: 50 | F100: 52 | G100: 54 | H100: 54 | I100: 54 | J100: 59 | K100: 61 | L100: 61
A101: =Dashboard!A105 -> SUMMARY CONNECTIONS | E101: =E65+E60+E66 -> 0 | G101: =G65+G60+G66 -> 0 | H101: =H65+H60+H66 -> 0 | I101: =I65+I60+I66 -> 0 | J101: =J65+J60+J66 -> 0 | K101: =K65+K60+K66 -> 0 | L101: =L65+L60+L66 -> 0 | M101: =M65+M60+M66 -> 0 | N101: =N65+N60+N66 -> 0 | ... P101: =P65+P60+P66 -> 0
...

Sheet Input Actual2024-25
A1: =Dashboard!A1 -> SALES & CC DASHBOARD | E1: =E13+E18+E19 -> 78 | G1: =G13+G18+G19 -> 26 | H1: =H13+H18+H19 -> 10 | I1: =I13+I18+I19 -> 39 | J1: =J13+J18+J19 -> 56
E2: =E29+E33+E34 -> 3 | G2: =G29+G33+G34 -> 3 | H2: =H29+H33+H34 -> 2 | I2: =I29+I33+I34 -> 0 | J2: =J29+J33+J34 -> 4
B4: MONTH | C4: UNIT | E4: JUL | F4: AUG | G4: SEP | H4: OCT | I4: NOV | J4: DEC | K4: JAN | L4: FEB | M4: MAR | N4: APR | O4: MAY | P4: JUN
A5: =Dashboard!A5 -> NEW CONNECTIONS WATER
A6: =Dashboard!A6 -> 1 | B6: =Dashboard!B6 -> CBD - NEW WATER | C6: =Dashboard!C6 -> No. | D6: 8 | E6: 1 | F6: 1 | G6: 2 | H6: 0 | I6: 0 | J6: 0 | K6: 0 | L6: 0 | M6: 0 | N6: 1 | O6: 2 | P6: 2
A7: =Dashboard!A7 -> 2 | B7: =Dashboard!B7 -> CCCR- NEW WATER | C7: =Dashboard!C7 -> No. | D7: 14 | E7: 6 | F7: 1 | G7: 3 | H7: 0 | I7: 0 | J7: 0 | K7: 7 | L7: 2 | M7: 1 | N7: 3 | O7: 2 | P7: 4
A8: =Dashboard!A8 -> 3 | B8: =Dashboard!B8 -> KABATI- NEW WATER | C8: =Dashboard!C8 -> No. | D8: 4 | E8: 1 | F8: 4 | G8: 5 | H8: 0 | I8: 3 | J8: 0 | K8: 1 | L8: 4 | M8: 0 | N8: 2 | O8: 2 | P8: 0
A9: =Dashboard!A9 -> 4 | B9: =Dashboard!B9 -> SITE- NEW WATER | C9: =Dashboard!C9 -> No. | D9: 2 | E9: 1 | F9: 0 | G9: 0 | H9: 0 | I9: 0 | J9: 0 | K9: 1 | L9: 0 | M9: 0 | N9: 0 | O9: 0 | P9: 2
A10: =Dashboard!A10 -> 5 | B10: =Dashboard!B10 -> KIHOTO- NEW WATER | C10: =Dashboard!C10 -> No. | D10: 5 | E10: 0 | F10: 0 | G10: 0 | H10: 0 | I10: 0 | J10: 0 | K10: 1 | L10: 0 | M10: 0 | N10: 0 | O10: 0 | P10: 1
A11: =Dashboard!A11 -> 6 | B11: =Dashboard!B11 -> LAKEVIEW- NEW WATER | C11: =Dashboard!C11 -> No. | D11: 7 | E11: 7 | F11: 5 | G11: 0 | H11: 2 | I11: 0 | J11: 0 | K11: 2 | L11: 4 | M11: 2 | N11: 1 | O11: 2 | P11: 1
A12: =Dashboard!A12 -> 7 | B12: =Dashboard!B12 -> HOPEWELL- NEW WATER | C12: =Dashboard!C12 -> No. | D12: =Dashboard!D12 -> l | E12: 0 | F12: 0 | G12: 0 | H12: 0 | I12: 0 | J12: 0 | K12: 4 | L12: 0 | M12: 2 | N12: 0 | O12: 1 | P12: 2
A13: =Dashboard!A13 -> 0 | B13: =Dashboard!B13 -> TOTAL NEW WATER CONNECTIONS CENTRAL REGION | C13: =Dashboard!C13 -> No. | D13: 40 | E13: =SUM(E6:E12) -> 16 | F13: =SUM(F6:F12) -> 11 | G13: =SUM(G6:G12) -> 10 | H13: =SUM(H6:H12) -> 2 | I13: =SUM(I6:I12) -> 3 | J13: =SUM(J6:J12) -> 0 | K13: =SUM(K6:K12) -> 16 | L13: =SUM(L6:L12) -> 10 | ... P13: =SUM(P6:P12) -> 12
A14: =Dashboard!A14 -> 1 | B14: =Dashboard!B14 -> HELLSGATE- NEW WATER | C14: =Dashboard!C14 -> No. | D14: 24 | E14: 13 | F14: 8 | G14: -1 | H14: 0 | I14: 1 | J14: 1 | K14: 13 | L14: 12 | M14: 16 | N14: 16 | O14: 17 | P14: 16
A15: =Dashboard!A15 -> 2 | B15: =Dashboard!B15 -> KAMERE- NEW WATER | C15: =Dashboard!C15 -> No. | D15: 0 | E15: 4 | F15: 1 | G15: 0 | H15: 0 | I15: 0 | J15: 1 | K15: 1 | L15: 4 | M15: 0 | N15: 1 | O15: 1 | P15: 0
A16: =Dashboard!A16 -> 3 | B16: =Dashboard!B16 -> MAI-MAHIU- NEW WATER | C16: =Dashboard!C16 -> No. | D16: 24 | E16: 14 | F16: 22 | G16: 12 | H16: 2 | I16: 13 | J16: 53 | K16: 87 | L16: 17 | M16: 16 | N16: 75 | O16: 11 | P16: 24
A17: =Dashboard!A17 -> 4 | B17: =Dashboard!B17 -> LONGONOT- NEW WATER | C17: =Dashboard!C17 -> No. | D17: 24 | E17: 0 | F17: 0 | G17: 3 | H17: 0 | I17: 0 | J17: 1 | K17: 5 | L17: 6 | M17: 6 | N17: 5 | O17: 9 | P17: 10
A18: =Dashboard!A18 -> 0 | B18: =Dashboard!B18 -> TOTAL NEW WATER CONNECTION SOUTHERN REGION | C18: =Dashboard!C18 -> No. | D18: 48 | E18: =SUM(E14:E17) -> 31 | F18: =SUM(F14:F17) -> 31 | G18: =SUM(G14:G17) -> 14 | H18: =SUM(H14:H17) -> 2 | I18: =SUM(I14:I17) -> 14 | J18: =SUM(J14:J17) -> 56 | K18: =SUM(K14:K17) -> 106 | L18: =SUM(L14:L17) -> 39 | ... P18: =SUM(P14:P17) -> 50
A19: =Dashboard!A20 -> 1 | B19: =Dashboard!B20 -> KAYOLE- NEW WATER | C19: =Dashboard!C20 -> No. | D19: 25 | E19: 31 | F19: 9 | G19: 2 | H19: 6 | I19: 22 | J19: 0 | K19: 7 | L19: 37 | M19: 47 | N19: 55 | O19: 12 | P19: 25
B20: TOTAL NEW CONNECTIONS WATER | D20: 113 | E20: =E19+E18+E13 -> 78 | F20: =F19+F18+F13 -> 51 | G20: =G19+G18+G13 -> 26 | H20: =H19+H18+H13 -> 10 | I20: =I19+I18+I13 -> 39 | J20: =J19+J18+J13 -> 56 | K20: =K19+K18+K13 -> 129 | L20: =L19+L18+L13 -> 86 | ... P20: =P19+P18+P13 -> 87
A21: =Dashboard!A23 -> NEW CONNECTIONS SEWER
A22: =Dashboard!A24 -> 1 | B22: =Dashboard!B24 -> CBD- NEW SEWER | C22: =Dashboard!C24 -> No. | D22: 0 | E22: 0 | F22: 1 | G22: 0 | H22: 0 | I22: 0 | J22: 1 | K22: 1 | L22: 0 | M22: 0 | N22: 0 | O22: 0 | P22: 1
A23: =Dashboard!A25 -> 2 | B23: =Dashboard!B25 -> CCCR- NEW SEWER | C23: =Dashboard!C25 -> No. | D23: 0 | E23: 1 | F23: 2 | G23: -2 | H23: 0 | I23: 0 | J23: 0 | K23: 0 | L23: 0 | M23: 1 | N23: 1 | O23: 0 | P23: 0
A24: =Dashboard!A26 -> 3 | B24: =Dashboard!B26 -> KABATI- NEW SEWER | C24: =Dashboard!C26 -> No. | D24: 0 | E24: 0 | F24: 4 | G24: 0 | H24: 0 | I24: 0 | J24: 2 | K24: 0 | L24: 2 | M24: 0 | N24: 1 | O24: 0 | P24: 1
A25: =Dashboard!A27 -> 4 | B25: =Dashboard!B27 -> SITE- NEW SEWER | C25: =Dashboard!C27 -> No. | D25: 0 | E25: 1 | F25: 3 | G25: 1 | H25: 0 | I25: 0 | J25: 0 | K25: 0 | L25: 1 | M25: 0 | N25: 0 | O25: 0 | P25: 0
A26: =Dashboard!A28 -> 5 | B26: =Dashboard!B28 -> KIHOTO- NEW SEWER | C26: =Dashboard!C28 -> No. | D26: 0 | E26: 0 | F26: 0 | G26: 0 | H26: 0 | I26: 0 | J26: 0 | K26: 0 | L26: 0 | M26: 0 | N26: 0 | O26: 0 | P26: 0
A27: =Dashboard!A29 -> 6 | B27: =Dashboard!B29 -> LAKEVIEW- NEW SEWER | C27: =Dashboard!C29 -> No. | D27: 2 | E27: 0 | F27: 0 | G27: 2 | H27: 1 | I27: 0 | J27: 0 | K27: 0 | L27: 1 | M27: 1 | N27: 0 | O27: 0 | P27: 0
A28: =Dashboard!A30 -> 7 | B28: =Dashboard!B30 -> HOPEWELL- NEW SEWER | C28: =Dashboard!C30 -> No. | D28: 2 | E28: 0 | F28: 0 | G28: 0 | H28: 0 | I28: 0 | J28: 0 | K28: 0 | L28: 0 | M28: 0 | N28: 0 | O28: 0 | P28: 0
A29: =Dashboard!A31 -> 0 | B29: =Dashboard!B31 -> TOTAL NEW SEWER CONNECTIONS CENTRAL REGION | C29: =Dashboard!C31 -> No. | D29: 2 | E29: =SUM(E22:E28) -> 2 | F29: =SUM(F22:F28) -> 10 | G29: =SUM(G22:G28) -> 1 | H29: =SUM(H22:H28) -> 1 | I29: =SUM(I22:I28) -> 0 | J29: =SUM(J22:J28) -> 3 | K29: =SUM(K22:K28) -> 1 | L29: =SUM(L22:L28) -> 4 | ... P29: =SUM(P22:P28) -> 2
A30: =Dashboard!A32 -> 1 | B30: =Dashboard!B32 -> HELLSGATE- NEW SEWER | C30: =Dashboard!C32 -> No. | E30: 0 | F30: =F60-E60 -> 0 | G30: =G60-F60 -> 0 | H30: =H60-G60 -> 0 | I30: =I60-H60 -> 0 | J30: =J60-I60 -> 0 | K30: =K60-J60 -> 0 | L30: =L60-K60 -> 0 | M30: =M60-L60 -> 0 | ... P30: =P60-O60 -> 0
A31: =Dashboard!A33 -> 2 | B31: =Dashboard!B33 -> KAMERE- NEW SEWER | C31: =Dashboard!C33 -> No. | E31: 0 | F31: =F61-E61 -> 0 | G31: =G61-F61 -> 0 | H31: =H61-G61 -> 0 | I31: =I61-H61 -> 0 | J31: =J61-I61 -> 0 | K31: =K61-J61 -> 0 | L31: =L61-K61 -> 0 | M31: =M61-L61 -> 0 | ... P31: =P61-O61 -> 0
A32: =Dashboard!A34 -> 3 | B32: =Dashboard!B34 -> MAI-MAHIU- NEW SEWER | C32: =Dashboard!C34 -> No. | E32: 0 | F32: =F62-E62 -> 0 | G32: =G62-F62 -> 0 | H32: =H62-G62 -> 0 | I32: =I62-H62 -> 0 | J32: =J62-I62 -> 0 | K32: =K62-J62 -> 0 | L32: =L62-K62 -> 0 | M32: =M62-L62 -> 0 | ... P32: =P62-O62 -> 0
A33: =Dashboard!A35 -> 0 | B33: =Dashboard!B35 -> TOTAL NEW S CONNECTION SOUTHERN REGION | C33: =Dashboard!C35 -> No. | D33: 0 | E33: =SUM(E30:E32) -> 0 | F33: =SUM(F30:F32) -> 0 | G33: =SUM(G30:G32) -> 0 | H33: =SUM(H30:H32) -> 0 | I33: =SUM(I30:I32) -> 0 | J33: =SUM(J30:J32) -> 0 | K33: =SUM(K30:K32) -> 0 | L33: =SUM(L30:L32) -> 0 | ... P33: =SUM(P30:P32) -> 0
A34: =Dashboard!A37 -> 1 | B34: =Dashboard!B37 -> KAYOLE- NEW SEWER | C34: =Dashboard!C37 -> No. | D34: 6 | E34: 1 | F34: 0 | G34: 2 | H34: 1 | I34: 0 | J34: 1 | K34: 0 | L34: 2 | M34: 2 | N34: 1 | O34: 0 | P34: 1
B35: TOTAL NEW CONNECTIONS -SEWER | D35: 8 | E35: =E34+E29 -> 3 | F35: =F34+F29 -> 10 | G35: =G34+G29 -> 3 | H35: =H34+H29 -> 2 | I35: =I34+I29 -> 0 | J35: =J34+J29 -> 4 | K35: =K34+K29 -> 1 | L35: =L34+L29 -> 6 | ... P35: =P34+P29 -> 3
A36: =Dashboard!A38 -> TOTAL CONNECTIONS-WATER
A37: =Dashboard!A39 -> 1 | B37: =Dashboard!B39 -> CBD- WATER | C37: =Dashboard!C39 -> No. | D37: 773 | E37: 782 | F37: 783 | G37: 785 | H37: 786 | I37: 785 | J37: 786 | K37: 785 | L37: 785 | M37: 785 | N37: 786 | O37: 788 | P37: 790
A38: =Dashboard!A40 -> 2 | B38: =Dashboard!B40 -> CCCR- WATER | C38: =Dashboard!C40 -> No. | D38: 779 | E38: 857 | F38: 858 | G38: 861 | H38: 859 | I38: 861 | J38: 861 | K38: 869 | L38: 872 | M38: 873 | N38: 875 | O38: 876 | P38: 880
A39: =Dashboard!A41 -> 3 | B39: =Dashboard!B41 -> KABATI- WATER | C39: =Dashboard!C41 -> No. | D39: 908 | E39: 935 | F39: 939 | G39: 944 | H39: 944 | I39: 946 | J39: 945 | K39: 946 | L39: 950 | M39: 950 | N39: 951 | O39: 953 | P39: 953
A40: =Dashboard!A42 -> 4 | B40: =Dashboard!B42 -> SITE- WATER | C40: =Dashboard!C42 -> No. | D40: 921 | E40: 935 | F40: 935 | G40: 935 | H40: 935 | I40: 935 | J40: 935 | K40: 936 | L40: 937 | M40: 937 | N40: 937 | O40: 937 | P40: 939
A41: =Dashboard!A43 -> 5 | B41: =Dashboard!B43 -> KIHOTO- WATER | C41: =Dashboard!C43 -> No. | D41: 207 | E41: 217 | F41: 217 | G41: 217 | H41: 217 | I41: 217 | J41: 217 | K41: 218 | L41: 218 | M41: 218 | N41: 218 | O41: 218 | P41: 219
A42: =Dashboard!A44 -> 6 | B42: =Dashboard!B44 -> LAKEVIEW- WATER | C42: =Dashboard!C44 -> No. | D42: 1413 | E42: =1491-E43 -> 1226 | F42: 1231 | G42: 1138 | H42: 1139 | I42: 1140 | J42: 1141 | K42: 1143 | L42: 1147 | M42: 1148 | N42: 1149 | O42: 1151 | P42: 1152
A43: =Dashboard!A45 -> 7 | B43: =Dashboard!B45 -> HOPEWELL- WATER | C43: =Dashboard!C45 -> No. | D43: 1413 | E43: 265 | F43: 265 | G43: 358 | H43: 358 | I43: 358 | J43: 358 | K43: 361 | L43: 359 | M43: 361 | N43: 361 | O43: 363 | P43: 365
A44: =Dashboard!A46 -> 0 | B44: =Dashboard!B46 -> TOTALWATER CONNECTION CENTRAL REGION | C44: =Dashboard!C46 -> No. | D44: 5001 | E44: =SUM(E37:E43) -> 5217 | F44: =SUM(F37:F43) -> 5228 | G44: =SUM(G37:G43) -> 5238 | H44: =SUM(H37:H43) -> 5238 | I44: =SUM(I37:I43) -> 5242 | J44: =SUM(J37:J43) -> 5243 | K44: =SUM(K37:K43) -> 5258 | L44: =SUM(L37:L43) -> 5268 | ... P44: =SUM(P37:P43) -> 5298
A45: =Dashboard!A47 -> 1 | B45: =Dashboard!B47 -> HELLSGATE- WATER | C45: =Dashboard!C47 -> No. | D45: 1607 | E45: 1740 | F45: 1748 | G45: 1747 | H45: 1748 | I45: 1749 | J45: 1749 | K45: 1762 | L45: 1774 | M45: 1789 | N45: 1804 | O45: 1821 | P45: 1835
A46: =Dashboard!A48 -> 2 | B46: =Dashboard!B48 -> KAMERE- WATER | C46: =Dashboard!C48 -> No. | D46: 343 | E46: 356 | F46: 357 | G46: 357 | H46: 358 | I46: 358 | J46: 359 | K46: 360 | L46: 364 | M46: 364 | N46: 364 | O46: 365 | P46: 365
A47: =Dashboard!A49 -> 3 | B47: =Dashboard!B49 -> MAI-MAHIU- WATER | C47: =Dashboard!C49 -> No. | D47: 1194 | E47: 834 | F47: 856 | G47: 868 | H47: 869 | I47: 880 | J47: 933 | K47: 1019 | L47: 1032 | M47: 1044 | N47: 1118 | O47: 1123 | P47: 1146
A48: =Dashboard!A50 -> 4 | B48: =Dashboard!B50 -> LONGONOT- WATER | C48: =Dashboard!C50 -> No. | D48: =Dashboard!D50 -> l | E48: 562 | F48: 562 | G48: 565 | H48: 565 | I48: 568 | J48: 567 | K48: 572 | L48: 579 | M48: 588 | N48: 593 | O48: 608 | P48: 618
A49: =Dashboard!A51 -> 0 | B49: =Dashboard!B51 -> TOTAL WATER CONNECTION SOUTHERN REGION | C49: =Dashboard!C51 -> No. | D49: 3144 | E49: =SUM(E45:E48) -> 3492 | F49: =SUM(F45:F48) -> 3523 | G49: =SUM(G45:G48) -> 3537 | H49: =SUM(H45:H48) -> 3540 | I49: =SUM(I45:I48) -> 3555 | J49: =SUM(J45:J48) -> 3608 | K49: =SUM(K45:K48) -> 3713 | L49: =SUM(L45:L48) -> 3749 | ... P49: =SUM(P45:P48) -> 3964
A50: =Dashboard!A53 -> 1 | B50: =Dashboard!B53 -> KAYOLE-WATER | C50: =Dashboard!C53 -> No. | D50: 2457 | E50: 2701 | F50: 2710 | G50: 2712 | H50: 2716 | I50: 2737 | J50: 2737 | K50: 2743 | L50: 2779 | M50: 2827 | N50: 2882 | O50: 2894 | P50: 2919
A51: =Dashboard!A56 -> TOTAL CONNECTIONS-SEWER
A52: =Dashboard!A57 -> 1 | B52: =Dashboard!B57 -> CBD- SEWER | C52: =Dashboard!C57 -> No. | D52: 439 | E52: 476 | F52: 477 | G52: 477 | H52: 477 | I52: 477 | J52: 478 | K52: 478 | L52: 478 | M52: 479 | N52: 479 | O52: 480 | P52: 480
A53: =Dashboard!A58 -> 2 | B53: =Dashboard!B58 -> CCCR-SEWER | C53: =Dashboard!C58 -> No. | D53: 358 | E53: 447 | F53: 449 | G53: 447 | H53: 447 | I53: 446 | J53: 446 | K53: 446 | L53: 451 | M53: 454 | N53: 454 | O53: 453 | P53: 453
A54: =Dashboard!A59 -> 3 | B54: =Dashboard!B59 -> KABATI-SEWER | C54: =Dashboard!C59 -> No. | D54: 326 | E54: 362 | F54: 366 | G54: 366 | H54: 366 | I54: 374 | J54: 374 | K54: 377 | L54: 379 | M54: 382 | N54: 383 | O54: 382 | P54: 382
A55: =Dashboard!A60 -> 4 | B55: =Dashboard!B60 -> SITE- SEWER | C55: =Dashboard!C60 -> No. | D55: 530 | E55: 591 | F55: 594 | G55: 595 | H55: 595 | I55: 595 | J55: 595 | K55: 600 | L55: 603 | M55: 603 | N55: 604 | O55: 604 | P55: 605
A56: =Dashboard!A61 -> 5 | B56: =Dashboard!B61 -> KIHOTO- SEWER | C56: =Dashboard!C61 -> No. | D56: 0 | E56: 0 | F56: 0 | G56: 0 | H56: 0 | I56: 0 | J56: 0 | K56: =J56-I56 -> 0 | L56: 0 | M56: 0 | N56: 0 | O56: 0 | P56: 0
A57: =Dashboard!A62 -> 6 | B57: =Dashboard!B62 -> LAKEVIEW- SEWER | C57: =Dashboard!C62 -> No. | D57: 166 | E57: 184 | F57: 177 | G57: 179 | H57: 179 | I57: 179 | J57: 178 | K57: 178 | L57: 178 | M57: 180 | N57: 180 | O57: 180 | P57: 180
A58: =Dashboard!A63 -> 7 | B58: =Dashboard!B63 -> HOPEWELL- SEWER | C58: =Dashboard!C63 -> No. | D58: 166 | E58: 0 | F58: 7 | G58: 7 | H58: 7 | I58: 7 | J58: 7 | K58: 7 | L58: 2 | M58: 2 | N58: 2 | O58: 2 | P58: 2
A59: =Dashboard!A64 -> 0 | B59: =Dashboard!B64 -> TOTAL SEWER CONNECTION CENTRAL REGION | C59: =Dashboard!C64 -> No. | D59: 1819 | E59: =SUM(E52:E58) -> 2060 | F59: =SUM(F52:F58) -> 2070 | G59: =SUM(G52:G58) -> 2071 | H59: =SUM(H52:H58) -> 2071 | I59: =SUM(I52:I58) -> 2078 | J59: =SUM(J52:J58) -> 2078 | K59: =SUM(K52:K58) -> 2086 | L59: =SUM(L52:L58) -> 2091 | ... P59: =SUM(P52:P58) -> 2102
A60: =Dashboard!A66 -> 1 | B60: =Dashboard!B66 -> HELLSGATE-SEWER | C60: =Dashboard!C66 -> No. | D60: 0 | E60: 0 | F60: 0 | G60: 0 | H60: 0 | I60: 0 | J60: 0 | K60: 0 | L60: 0 | M60: 0 | N60: 0 | O60: 0 | P60: 0
A61: =Dashboard!A67 -> 2 | B61: =Dashboard!B67 -> KAMERE- SEWER | C61: =Dashboard!C67 -> No. | D61: 0 | E61: 0 | F61: 0 | G61: 0 | H61: 0 | I61: 0 | J61: 0 | K61: 0 | L61: 0 | M61: 0 | N61: 0 | O61: 0 | P61: 0
A62: =Dashboard!A68 -> 3 | B62: =Dashboard!B68 -> MAI-MAHIU-SEWER | C62: =Dashboard!C68 -> No. | D62: 0 | E62: 0 | F62: 0 | G62: 0 | H62: 0 | I62: 0 | J62: 0 | K62: 0 | L62: 0 | M62: 0 | N62: 0 | O62: 0 | P62: 0
A63: =Dashboard!A69 -> 0 | B63: =Dashboard!B69 -> TOTAL SEWER CONNECTION SOUTHERNREGION | C63: =Dashboard!C69 -> No. | D63: 0 | E63: =SUM(E60:E62) -> 0 | F63: =SUM(F60:F62) -> 0 | G63: =SUM(G60:G62) -> 0 | H63: =SUM(H60:H62) -> 0 | I63: =SUM(I60:I62) -> 0 | J63: =SUM(J60:J62) -> 0 | K63: =SUM(K60:K62) -> 0 | L63: =SUM(L60:L62) -> 0 | ... P63: =SUM(P60:P62) -> 0
A64: =Dashboard!A71 -> 1 | B64: =Dashboard!B71 -> KAYOLE-SEWER | C64: =Dashboard!C71 -> No. | D64: 21 | E64: 44 | F64: 44 | G64: 46 | H64: 47 | I64: 47 | J64: 47 | K64: 47 | L64: 50 | M64: 52 | N64: 52 | O64: 52 | P64: 52
A65: =Dashboard!A72 -> TOTAL ACTIVE CONNECTIONS-WATER
A66: =Dashboard!A73 -> 1 | B66: =Dashboard!B73 -> CBD- ACTIVE WATER | C66: =Dashboard!C73 -> No. | D66: 583 | E66: 596 | F66: 598 | G66: 599 | H66: 600 | I66: 598 | J66: 598 | K66: 598 | L66: 599 | M66: 598 | N66: 598 | O66: 597 | P66: 596
A67: =Dashboard!A74 -> 2 | B67: =Dashboard!B74 -> CCCR- ACTIVE WATER | C67: =Dashboard!C74 -> No. | D67: 593 | E67: 676 | F67: 676 | G67: 681 | H67: 680 | I67: 683 | J67: 683 | K67: 687 | L67: 692 | M67: 697 | N67: 697 | O67: 696 | P67: 700
A68: =Dashboard!A75 -> 3 | B68: =Dashboard!B75 -> KABATI- ACTIVE WATER | C68: =Dashboard!C75 -> No. | D68: 811 | E68: 844 | F68: 847 | G68: 851 | H68: 851 | I68: 853 | J68: 852 | K68: 852 | L68: 856 | M68: 859 | N68: 860 | O68: 862 | P68: 862
A69: =Dashboard!A76 -> 4 | B69: =Dashboard!B76 -> SITE- ACTIVE WATER | C69: =Dashboard!C76 -> No. | D69: 811 | E69: 830 | F69: 830 | G69: 831 | H69: 831 | I69: 831 | J69: 831 | K69: 831 | L69: 833 | M69: 834 | N69: 834 | O69: 834 | P69: 836
A70: =Dashboard!A77 -> 5 | B70: =Dashboard!B77 -> KIHOTO-ACTIVE WATER | C70: =Dashboard!C77 -> No. | D70: 157 | E70: 171 | F70: 172 | G70: 173 | H70: 172 | I70: 172 | J70: 172 | K70: 172 | L70: 172 | M70: 173 | N70: 173 | O70: 173 | P70: 175
A71: =Dashboard!A78 -> 6 | B71: =Dashboard!B78 -> LAKEVIEW- ACTIVE WATER | C71: =Dashboard!C78 -> No. | D71: 1180 | E71: =1250-E72 -> 1032 | F71: 1034 | G71: 966 | H71: 969 | I71: 970 | J71: 971 | K71: 972 | L71: 977 | M71: 978 | N71: 981 | O71: 980 | P71: 981
A72: =Dashboard!A79 -> 7 | B72: =Dashboard!B79 -> HOPEWELL- ACTIVE WATER | C72: =Dashboard!C79 -> No. | D72: =Dashboard!D79 -> l | E72: 218 | F72: 218 | G72: 287 | H72: 287 | I72: 288 | J72: 288 | K72: 289 | L72: 289 | M72: 292 | N72: 294 | O72: 295 | P72: 295
A73: =Dashboard!A80 -> 0 | B73: =Dashboard!B80 -> TOTAL ACTIVE WATER CONNECTION CENTRAL REGION | C73: =Dashboard!C80 -> No. | D73: 4135 | E73: =SUM(E66:E72) -> 4367 | F73: =SUM(F66:F72) -> 4375 | G73: =SUM(G66:G72) -> 4388 | H73: =SUM(H66:H72) -> 4390 | I73: =SUM(I66:I72) -> 4395 | J73: =SUM(J66:J72) -> 4395 | K73: =SUM(K66:K72) -> 4401 | L73: =SUM(L66:L72) -> 4418 | ... P73: =SUM(P66:P72) -> 4445
A74: =Dashboard!A81 -> 1 | B74: =Dashboard!B81 -> HELLSGATE- ACTIVE WATER | C74: =Dashboard!C81 -> No. | D74: 1390 | E74: 1522 | F74: 1530 | G74: 1532 | H74: 1533 | I74: 1535 | J74: 1536 | K74: 1538 | L74: 1554 | M74: 1559 | N74: 1567 | O74: 1580 | P74: 1583
A75: =Dashboard!A82 -> 2 | B75: =Dashboard!B82 -> KAMERE- ACTIVE WATER | C75: =Dashboard!C82 -> No. | D75: 243 | E75: 252 | F75: 254 | G75: 254 | H75: 255 | I75: 255 | J75: 255 | K75: 256 | L75: 256 | M75: 259 | N75: 260 | O75: 263 | P75: 264
A76: =Dashboard!A83 -> 3 | B76: =Dashboard!B83 -> MAI-MAHIU- ACTIVE WATER | C76: =Dashboard!C83 -> No. | D76: 682 | E76: 459 | F76: 466 | G76: 487 | H76: 489 | I76: 517 | J76: 550 | K76: 555 | L76: 593 | M76: 613 | N76: 641 | O76: 658 | P76: 681
A77: =Dashboard!A84 -> 4 | B77: =Dashboard!B84 -> LONGONOT- ACTIVE WATER | C77: =Dashboard!C84 -> No. | D77: 682 | E77: 475 | F77: 474 | G77: 477 | H77: 478 | I77: 485 | J77: 483 | K77: 483 | L77: 489 | M77: 499 | N77: 501 | O77: 514 | P77: 519
A78: =Dashboard!A85 -> 0 | B78: =Dashboard!B85 -> TOTAL ACTIVE WATER CONNECTION SOUTHERN REGION | C78: =Dashboard!C85 -> No. | D78: 2315 | E78: =SUM(E74:E77) -> 2708 | F78: =SUM(F74:F77) -> 2724 | G78: =SUM(G74:G77) -> 2750 | H78: =SUM(H74:H77) -> 2755 | I78: =SUM(I74:I77) -> 2792 | J78: =SUM(J74:J77) -> 2824 | K78: =SUM(K74:K77) -> 2832 | L78: =SUM(L74:L77) -> 2892 | ... P78: =SUM(P74:P77) -> 3047
A79: =Dashboard!A87 -> 1 | B79: =Dashboard!B87 -> KAYOLE- ACTIVE WATER | C79: =Dashboard!C87 -> No. | D79: 2294 | E79: 2545 | F79: 2557 | G79: 2564 | H79: 2564 | I79: 2569 | J79: 2569 | K79: 2571 | L79: 2590 | M79: 2608 | N79: 2647 | O79: 2686 | P79: 2703
A80: =Dashboard!A90 -> TOTAL ACTIVE CONNECTIONS-SEWER
A81: =Dashboard!A91 -> 1 | B81: =Dashboard!B91 -> CBD- ACTIVE SEWER | C81: =Dashboard!C91 -> No. | D81: 352 | E81: 389 | F81: 390 | G81: 389 | H81: 389 | I81: 389 | J81: 389 | K81: 388 | L81: 388 | M81: 387 | N81: 387 | O81: 388 | P81: 388
A82: =Dashboard!A92 -> 2 | B82: =Dashboard!B92 -> CCCR- ACTIVE SEWER | C82: =Dashboard!C92 -> No. | D82: 297 | E82: 386 | F82: 387 | G82: 386 | H82: 386 | I82: 385 | J82: 385 | K82: 385 | L82: 390 | M82: 393 | N82: 393 | O82: 391 | P82: 391
A83: =Dashboard!A93 -> 3 | B83: =Dashboard!B93 -> KABATI- ACTIVE SEWER | C83: =Dashboard!C93 -> No. | D83: 272 | E83: 307 | F83: 311 | G83: 311 | H83: 311 | I83: 319 | J83: 319 | K83: 322 | L83: 324 | M83: 327 | N83: 329 | O83: 328 | P83: 328
A84: =Dashboard!A94 -> 4 | B84: =Dashboard!B94 -> SITE- ACTIVE SEWER | C84: =Dashboard!C94 -> No. | D84: 441 | E84: 505 | F84: 508 | G84: 508 | H84: 508 | I84: 508 | J84: 508 | K84: 513 | L84: 516 | M84: 517 | N84: 518 | O84: 518 | P84: 519
A85: =Dashboard!A95 -> 5 | B85: =Dashboard!B95 -> KIHOTO- ACTIVE SEWER | C85: =Dashboard!C95 -> No. | D85: 0 | E85: 0 | F85: 0 | G85: 0 | H85: 0 | I85: 0 | J85: 0 | K85: 0 | L85: 0 | M85: 0 | N85: 0 | O85: 0 | P85: 0
A86: =Dashboard!A96 -> 6 | B86: =Dashboard!B96 -> LAKEVIEW- ACTIVE SEWER | C86: =Dashboard!C96 -> No. | D86: 138 | E86: 158 | F86: 152 | G86: 154 | H86: 154 | I86: 154 | J86: 153 | K86: 153 | L86: 153 | M86: 155 | N86: 156 | O86: 155 | P86: 155
A87: =Dashboard!A97 -> 7 | B87: =Dashboard!B97 -> HOPEWELL- ACTIVE SEWER | C87: =Dashboard!C97 -> No. | D87: =Dashboard!D97 -> l | E87: 0 | F87: 6 | G87: 6 | H87: 6 | I87: 6 | J87: 6 | K87: 6 | L87: 2 | M87: 2 | N87: 2 | O87: 2 | P87: 2
A88: =Dashboard!A98 -> 0 | B88: =Dashboard!B98 -> TOTAL ACTIVE SEWER CONNECTION CENTRAL REGION | C88: =Dashboard!C98 -> No. | D88: 1500 | E88: =SUM(E81:E87) -> 1745 | F88: =SUM(F81:F87) -> 1754 | G88: =SUM(G81:G87) -> 1754 | H88: =SUM(H81:H87) -> 1754 | I88: =SUM(I81:I87) -> 1761 | J88: =SUM(J81:J87) -> 1760 | K88: =SUM(K81:K87) -> 1767 | L88: =SUM(L81:L87) -> 1773 | ... P88: =SUM(P81:P87) -> 1783
A89: =Dashboard!A99 -> 1 | B89: =Dashboard!B99 -> HELLSGATE- ACTIVE SEWER | C89: =Dashboard!C99 -> No. | E89: 0 | F89: 0 | G89: 0 | H89: 0 | I89: 0 | J89: 0 | K89: 0 | L89: 0 | M89: 0 | N89: 0 | O89: 0 | P89: 0
A90: =Dashboard!A100 -> 2 | B90: =Dashboard!B100 -> KAMERE- ACTIVE SEWER | C90: =Dashboard!C100 -> No. | E90: 0 | F90: 0 | G90: 0 | H90: 0 | I90: 0 | J90: 0 | K90: 0 | L90: 0 | M90: 0 | N90: 0 | O90: 0 | P90: 0
A91: =Dashboard!A101 -> 3 | B91: =Dashboard!B101 -> MAI-MAHIU- ACTIVE SEWER | C91: =Dashboard!C101 -> No. | E91: 0 | F91: 0 | G91: 0 | H91: 0 | I91: 0 | J91: 0 | K91: 0 | L91: 0 | M91: 0 | N91: 0 | O91: 0 | P91: 0
A92: =Dashboard!A102 -> 0 | B92: =Dashboard!B102 -> TOTAL ACTIVE SEWER CONNECTION SOUTHERN REGION | C92: =Dashboard!C102 -> No. | D92: 0 | E92: =SUM(E89:E91) -> 0 | F92: =SUM(F89:F91) -> 0 | G92: =SUM(G89:G91) -> 0 | H92: =SUM(H89:H91) -> 0 | I92: =SUM(I89:I91) -> 0 | J92: =SUM(J89:J91) -> 0 | K92: =SUM(K89:K91) -> 0 | L92: =SUM(L89:L91) -> 0 | ... P92: =SUM(P89:P91) -> 0
A93: =Dashboard!A104 -> 1 | B93: =Dashboard!B104 -> KAYOLE- ACTIVE SEWER | C93: =Dashboard!C104 -> No. | D93: 20 | E93: 43 | F93: 43 | G93: 44 | H93: 45 | I93: 45 | J93: 45 | K93: 45 | L93: 48 | M93: 50 | N93: 50 | O93: 50 | P93: 50
A94: =Dashboard!A105 -> SUMMARY CONNECTIONS | E94: =E61+E56+E62 -> 0 | G94: =G61+G56+G62 -> 0 | H94: =H61+H56+H62 -> 0 | I94: =I61+I56+I62 -> 0 | J94: =J61+J56+J62 -> 0 | K94: =K61+K56+K62 -> 0 | L94: =L61+L56+L62 -> 0 | M94: =M61+M56+M62 -> 0 | N94: =N61+N56+N62 -> 0 | ... P94: =P61+P56+P62 -> 0
A95: =Dashboard!A106 -> 1 | B95: =Dashboard!B106 -> TOTAL WATER CONNECTIONS | C95: =Dashboard!C106 -> No. | D95: 10602 | E95: =E50+E49+E44 -> 11410 | F95: =F50+F49+F44 -> 11461 | G95: =G50+G49+G44 -> 11487 | H95: =H50+H49+H44 -> 11494 | I95: =I50+I49+I44 -> 11534 | J95: =J50+J49+J44 -> 11588 | K95: =K50+K49+K44 -> 11714 | L95: =L50+L49+L44 -> 11796 | ... P95: =P50+P49+P44 -> 12181
A96: =Dashboard!A107 -> 2 | B96: =Dashboard!B107 -> TOTAL SEWER CONNECTIONS | C96: =Dashboard!C107 -> No. | D96: 1840 | E96: =E64+E59+E63 -> 2104 | F96: =F64+F59+F63 -> 2114 | G96: =G64+G59+G63 -> 2117 | H96: =H64+H59+H63 -> 2118 | I96: =I64+I59+I63 -> 2125 | J96: =J64+J59+J63 -> 2125 | K96: =K64+K59+K63 -> 2133 | L96: =L64+L59+L63 -> 2141 | ... P96: =P64+P59+P63 -> 2154
A97: =Dashboard!A108 -> 3 | B97: =Dashboard!B108 -> TOTAL ACTIVE WATER CONNECTIONS | C97: =Dashboard!C108 -> No. | D97: 8744 | E97: =E79+E78+E73 -> 9620 | F97: =F79+F78+F73 -> 9656 | G97: =G79+G78+G73 -> 9702 | H97: =H79+H78+H73 -> 9709 | I97: =I79+I78+I73 -> 9756 | J97: =J79+J78+J73 -> 9788 | K97: =K79+K78+K73 -> 9804 | L97: =L79+L78+L73 -> 9900 | ... P97: =P79+P78+P73 -> 10195
A98: =Dashboard!A109 -> 4 | B98: =Dashboard!B109 -> TOTAL SEWER ACTIVE CONNECTIONS | C98: =Dashboard!C109 -> No. | D98: 1520 | E98: =E88+E92+E93 -> 1788 | F98: =F88+F92+F93 -> 1797 | G98: =G88+G92+G93 -> 1798 | H98: =H88+H92+H93 -> 1799 | I98: =I88+I92+I93 -> 1806 | J98: =J88+J92+J93 -> 1805 | K98: =K88+K92+K93 -> 1812 | L98: =L88+L92+L93 -> 1821 | ... P98: =P88+P92+P93 -> 1833
A99: =Dashboard!A110 -> x | B99: =Dashboard!B110 -> TOTAL NEW CONNECTION WATER | C99: =Dashboard!C110 -> No. | E99: =E13+E18+E19 -> 78 | F99: =F13+F18+F19 -> 51 | G99: =G13+G18+G19 -> 26 | H99: =H13+H18+H19 -> 10 | I99: =I13+I18+I19 -> 39 | J99: =J13+J18+J19 -> 56 | K99: =K13+K18+K19 -> 129 | L99: =L13+L18+L19 -> 86 | ... P99: =P13+P18+P19 -> 87
A100: =Dashboard!A111 -> y | B100: =Dashboard!B111 -> TOTAL NEW CONNECTIONS SEWER | C100: =Dashboard!C111 -> No. | E100: =E35 -> 3 | F100: =F35 -> 10 | G100: =G35 -> 3 | H100: =H35 -> 2 | I100: =I35 -> 0 | J100: =J35 -> 4 | K100: =K35 -> 1 | L100: =L35 -> 6 | ... P100: =P35 -> 3
A101: =Dashboard!A112 -> 5 | B101: =Dashboard!B112 -> % ACTIVE CONNECTIONS | C101: =Dashboard!C112 -> No. | D101: 0.82494776 | E101: =SUM(E97:E98)/SUM(E95:E96) -> 0.84416161 | F101: =SUM(F97:F98)/SUM(F95:F96) -> 0.84368324 | G101: =SUM(G97:G98)/SUM(G95:G96) -> 0.84533961 | H101: =SUM(H97:H98)/SUM(H95:H96) -> 0.8454305 | I101: =SUM(I97:I98)/SUM(I95:I96) -> 0.84647485 | J101: =SUM(J97:J98)/SUM(J95:J96) -> 0.84540217 | K101: =SUM(K97:K98)/SUM(K95:K96) -> 0.83888207 | L101: =SUM(L97:L98)/SUM(L95:L96) -> 0.84099878 | ... P101: =SUM(P97:P98)/SUM(P95:P96) -> 0.83906522
...

Sheet MARKETING PLAN
B1: MARKETING PLAN (QUARTERLY)
A2: In order to fully implement both the marketing and the sales plan, the section needs more staff
A3: AREA | B3: TARGET | C3: STRATEGY | D3: BUDGET | E3: TIMELINE | F3: LEVEL OF IMPLEMENTATION | G3: REMARKS
A4: Ihindu Marketing and target | B4: 300 | C4: · Door to door marketing, | E4: July-September 2024 | F4: 0 | G4: Pending project completion
C5: · Conduct water clinic. | D5: 29250 | F5: 0
C6: · Follow up with customers via phone | D6: Airtime -1,000 | F6: 0
C7: · Social marketer | D7: 200 per connection | F7: 0
C8: · Use of communication materials | F8: 0
C9: · Use of point man | F9: 1
A10: Kayole Sewer Marketing | B10: 400 | C10: · Door to door marketing | E10: July-September 2024 | F10: 0
C11: · Call customers on phone for follow up (customers with water connection | D11: Airtime -1,000 | F11: 0
C12: · PHO enforcement on customers reluctant to apply | F12: 1
C13: · Use of communication materials | F13: 0
C14: · Social marketer | D14: 200 per connection | F14: 0
C15: · Hold water clinic in the target areas | D15: 29250 | F15: 1
A16: Ngondi | B16: 300 | C16: · Door to door marketing | E16: July-September 2024 | F16: 0
C17: · Hold water clinic | D17: Water clinic-29,250 | F17: 0 | G17: Pending phase 2 clinics
C18: · Use of point man | F18: 1
C19: · Social marketer | D19: 200 per connection | F19: 0
C20: · Use of communication materials | F20: 0
C21: · Follow up with customers via phone | D21: Airtime -1,000 | F21: 0
C22: · Hold a community meeting | D22: Refreshments-50*100=5,000 | F22: 0
D23: Hiring of hall- 5,000 | F23: 0.5
A24: Karima, Rare and Kamucira | B24: 400 | C24: · Door to door marketing | E24: July-August 2024 | F24: 0.5
C25: · Use of communication materials | F25: 0
C26: · Hold water clinic | D26: Water clinic-29,250 | F26: 0 | G26: Pending phase 2 clinics
C27: · Follow up by calling customers | D27: Airtime -1,000 | F27: 0.8
C28: · Social marketers | D28: 200 per connection | F28: 1
C29: · Use of point man | F29: 0.5
A30: Kedong (Wachira line) | B30: 100 | C30: · Use of point man | E30: 45474 | F30: 0
C31: · Follow up by calling customers | D31: Airtime -1,000 | F31: 0
A32: Rwanyaga | B32: 150 | C32: · Hold a community meeting | D32: Refreshments-50*100=5,000 | E32: August - September 2024 | F32: 0
D33: Hiring of hall- 5,000 | F33: 0
C34: · Social marketers | D34: 200 per connection | F34: 0
C35: · Use of communication materials | F35: 0
C36: · Follow up with customers on pending payment and NAWC | D36: Airtime -1,000 | F36: 0
A37: Kabati sewer connection | B37: 100 | C37: · Hold a community meeting | D37: Refreshments-50*100=5,000 | E37: 45474 | F37: 0.333
D38: Hiring of hall- 5,000 | F38: 0
C39: · Social marketers | D39: 200 per connection | F39: 0
C40: · Use of communication materials | F40: 1
A41: Kinungi | B41: 100 | C41: · Hold a community meeting | D41: Refreshments-50*100=5,000 | E41: 45536 | F41: 0
D42: Hiring of hall- 5,000 | F42: 0
C43: · Door to door marketing | F43: 0
C44: · Hold water clinic | D44: Water clinic-29,250 | F44: 0 | G44: Pending phase 2 clinics
C45: · Social marketers | D45: 200 per connection | F45: 0
C46: · Use of communication materials | F46: 0
C47: · Use of Point man | F47: 0
A48: Canaan | B48: 100 | C48: · Hold a community meeting | D48: Refreshments-50*100=5000 | E48: August - September 2024 | F48: 0
D49: Hiring of hall- 5,000 | F49: 0
C50: · Use of communication materials | F50: 0
C51: · Door to door marketing | F51: 0
C52: · Hold water clinic | D52: 29250 | F52: 0 | G52: Pending phase 2 clinics
C53: · Social marketer | D53: 300 per connection | F53: 1
A54: Kambi | B54: 300 | C54: · Door to door marketing | E54: August - September 2024 | F54: 0
C55: · Hold water clinic | D55: 29250 | F55: 0 | G55: Pending phase 2 clinics
C56: · Follow up with customers on calls | D56: Airtime-1,000 | F56: 0
C57: · Social marketer | D57: 300 per connection | F57: 1
C58: · Use of communication materials | F58: 0

Sheet SALES PLAN
C1: Duration/Time required to complete a task/step and activity in days | D1: 45474 | H1: 45505 | L1: 45536 | P1: 45566 | T1: 45597 | X1: 45627 | AB1: 45658 | AF1: 45689 | AJ1: 45717 | AN1: 45748 | AR1: 45778 | AV1: 45809 | BA1: person Responsible | BB1: External support needed
B2: SALES SECTION | D2: W1 | E2: W2 | F2: W3 | G2: W4 | H2: W1 | I2: W2 | J2: W3 | K2: W4 | L2: W1 | M2: W2 | N2: W3 | O2: W4 | P2: W1 | Q2: W2 | R2: W3 | S2: W4 | T2: W1 | U2: W2 | V2: W3 | W2: W4 | X2: W1 | Y2: W2 | Z2: W3 | AA2: W4 | AB2: W1 | AC2: W2 | AD2: W3 | AE2: W4 | AF2: W1 | AG2: W2 | AH2: W3 | AI2: W4 | AJ2: W1 | AK2: W2 | AL2: W3 | AM2: W4 | AN2: W1 | AO2: W2 | AP2: W3 | AQ2: W4 | AR2: W1 | AS2: W2 | AT2: W3 | AU2: W4 | AV2: W1 | AW2: W2 | AX2: W3 | AY2: W4 | AZ2: Annual Targets
B3: ACTIVITIES
B4: INCREASE SALES | C4: =SUM(C5:C123) -> 8537 | BA4: SALES S.
B5: INCREASE SALES IN EASTERN REGION
B6: Water Extensions: Laketown(Bridge), Jumbo Estate, Solomon extension, Signture lane 2 & 7 | C6: Assessment done | BA6: Sales Supervisor
B7: Designing and Development of BoQs | C7: =5*4 -> 20 | BA7: Projects
B8: Approval for Extensions | C8: =5*4 -> 20 | BA8: DSM | BB8: 535000
B9: Implementation | C9: =5*4 -> 20 | BA9: Zonal Officer
B10: Customer registration & connection | C10: 180 | AZ10: 107 | BA10: Sales Supervisor | BB10: 50000
B11: Analysis of the inactive accounts | C11: (156)19.67% | BA11: Sales Supervisor
B13: Increase in sewer connections | C13: =12*22 -> 264 | BA13: Sales Supervisor | BB13: 50000
B15: INCREASE SALES IN SOUTHERN REGION
B16: Extensions: Dam1, Transit 1, 2 & 3, Silvester, Kedon( Kwa-Ngombe), Sanctuary,Part Island, Shalom & Musaka, Ngondi | C16: Assesment done | BA16: Sales Supervisor
B17: Designing and Development of BoQs | C17: 20 | BA17: Projects Engineer
B18: Approval for Extensions | C18: =5*4 -> 20 | BA18: DSM | BB18: 2642625
B19: Implementation | C19: =5*6 -> 30 | BA19: Zonal Officer
B20: Customer registration & connection | C20: 180 | AZ20: 200 | BA20: Sales Supervisor(Social Marketer) | BB20: 50000
B21: Analysis of the inactive accounts | C21: (793)22.76% | BA21: Sales Supervisor
B23: Increase water connections in Maai-Mahiu WFL | C23: =22*12 -> 264 | AZ23: 320 | BA23: Sales Supervisor
B25: INCREASE SALES IN CENTRAL REGION
B26: Extensions: Kihoto-Line 1 ,2, 7 & 8 Ziwa Drive,Catholic,Maziwa,Mulika Mwizi, and =ndegwa lane; Manera 1,2& 3, Banda line 1 and : ; Prison extension | C26: Assessment Done | BA26: Sales Supervisor
B27: Designing and Development of BoQs | C27: 10 | BA27: Projects Engineer
B28: Approval for Extensions | C28: 10 | BA28: DSM | BB28: 2225000
B29: Implementation | C29: =5*4 -> 20 | BA29: Zonal Officer
B30: Customer registration & connection | C30: 150 | AZ30: 445 | BA30: Sales Supervisor(Social Marketer) | BB30: 50000
B31: Analysis of the inactive accounts | C31: (1,160)15.98% | BA31: Sales Supervisor
B33: Increase in sewer connections | C33: =12*22 -> 264 | BA33: Sales Supervisor | BB33: 50000
B35: NEW PROJECT AREAS
B36: KINUNGI
B37: Community meeting | C37: 1 | BA37: SSS
B38: prioritization of extension | C38: =5*4 -> 20 | BA38: SSS
B39: Implementation | C39: =5*8 -> 40 | BA39: Zonal Officer
B40: Registration | C40: =10*22 -> 220 | AZ40: 300 | BA40: Sales Supervisor(Social Marketer) | BB40: 60000
B41: Customer connection | C41: =10*22 -> 220 | BA41: Zonal Officer
B43: GOVERNOR
B44: Commnity meeting | C44: 1 | BA44: Sales Supervisor(Social Marketer)
B45: prioritization of extension | C45: =5*3 -> 15 | BA45: SSS | BB45: 1000000
B46: Implementation | C46: =5*4 -> 20 | BA46: Zonal Officer
B47: Registration | C47: =11*22 -> 242 | BA47: Sales Supervisor(Social Marketer) | BB47: 60000
B48: Customer connection | C48: =11*22 -> 242 | AZ48: 400 | BA48: Zonal Officer
B50: MAI MAHIU | BA50: County funding
B51: Baseline Assessment | C51: =5*3 -> 15 | BA51: Sales Supervisor
B52: Community meeting | C52: 2 | BA52: SSS | BB52: 30000
B53: implementation | C53: 5 | BA53: TM | BB53: project funded
B54: Registration | C54: =11*22 -> 242 | BA54: Sales Supervisor(Social Marketer) | BB54: 50000
B55: Customer connection | C55: =11*22 -> 242 | AZ55: 150 | BA55: Zonal Officer
B57: KABATI SEWER
B58: Baseline Assessment | C58: done | BA58: Project funded
B59: Community meeting | C59: 2 | BA59: wsup
B60: implementation | C60: 120 | BA60: WSUP/TM
B61: Registration | C61: 300 | BA61: SSS | BB61: 50000
B62: Customer connection | C62: 300 | BA62: Sales Supervisor
B64: SUBERICO SEWER
B65: Baseline Assessment | C65: 10 | BA65: SSS
B66: Community meeting | C66: 1 | BA66: Sales supervisor
B67: implementation | C67: =5*22 -> 110 | BA67: TM
B68: Registration | C68: =6*22 -> 132 | BA68: SSS
B69: Customer connection | C69: =6*22 -> 132 | AZ69: 50 | BA69: Sales supervisor
B72: CUSTOMER ENGAGEMENT | C72: =SUM(C73:C99) -> 1581 | BA72: CUSTOMER CARE S.
B73: COMPLAINTS MANAGEMENT
B74: Complaint booking | C74: 365 | BA74: Customer Care Assistants | BB74: 0
B75: Complaint Follow Up for Resolution | C75: 365 | AZ75: 0.8 | BA75: Customer Care Assistants | BB75: 0
B76: New Connection processing & approval | C76: 365 | BA76: Customer Care Assistants | BB76: 0
B77: Adjustment Preparation | C77: 365 | BA77: Customer Care supervisor | BB77: 0
B78: Adjustment | C78: 52 | BA78: Finance | BB78: 0
B80: CUSTOMER SERVICE WEEK
B81: Communication to Customers | C81: 2 | BA81: Sales Supervisor | BB81: 10000
B82: Office decoration | C82: 1 | BA82: Sales Supervisor | BB82: 5000
B83: Rewarding loyal customers - NAIVAWASco notebook | C83: 2 | BA83: SSS | BB83: 20000
B84: Cake Cutting | C84: 1 | BA84: DSM | BB84: 8000
B86: WATER CLINIC
B87: Development of communication materials | C87: 20 | BA87: Sales Supervisor | BB87: 500000
B88: Water Clinics - CBD/CCCR | C88: 5
B89: Water Clinics - Lakeview/Guestinn | C89: 4
B90: Water Clinics - Kabati/Site | C90: 5
B91: Water Clinics - Longonot | C91: 5
B92: Water Clinics-Hellsgate | C92: 5 | BA92: Sales Supervisor | BB92: 20000
B93: Open Clinics-KAYOLE | C93: 5 | BA93: Sales Supervisor | BB93: 20000
B94: Water Clinics-MAI-MAHIU | C94: 5 | BA94: Sales Supervisor | BB94: 20000
B95: Water Clinics-Ngondi | C95: 2 | BA95: Sales Supervisor | BB95: 20000
B96: Water Clinics-Hopewell | C96: 1 | BA96: Sales Supervisor | BB96: 20000
B97: Water Clinics-Kihoto | C97: 2 | BA97: Sales Supervisor | BB97: 20000
B98: Water Clinics-Ihindu | C98: 2 | BA98: Sales Supervisor | BB98: 20000
B99: Open Clinic-KINUNGI | C99: 2 | BA99: Sales Supervisor | BB99: 20000
B102: METER READING | C102: =SUM(C103:C104) -> 156 | BA102: METER READING S.
B103: EASTERN REGION MR | C103: =6*12 -> 72 | BA103: Meter readers
B104: SOUTHERN REGION MR | C104: =7*12 -> 84 | BA104: Meter readers
B105: CENTRAL REGION MR | C105: =15*12 -> 180
B106: Meter Reading Approval | C106: 365 | BA106: SCCS & BA
B107: Addition of a Meter Reader | C107: 365 | BA107: DSM | BB107: =(1*25000*11)+(1*6*25000) -> 425000
B108: CAPACITY BUILDING
B109: Customer Care Section
B110: Customer service | C110: 5 | BA110: HRO/WSUP | BB110: 50000
B111: Refresher on Procedures | C111: 4 | BA111: SCCS | BB111: 2000
B112: Effective communication. | C112: 4 | BA112: HRO/WSUP | BB112: 50000
B113: Customer engagement and campaign management. | C113: 6 | BA113: HRO/WSUP | BB113: 50000
B114: How to handle difficult customers. | C114: 2 | BA114: HRO/WSUP | BB114: 50000
B115: The cost of poor customer service. | C115: 4 | BA115: HRO/WSUP | BB115: 50000
B116: Telephone Etiquette & Call Centre Training | C116: 4 | BA116: HRO/WSUP | BB116: 50000
...

Sheet actual 2022-23
A1: =Dashboard!A1 -> SALES & CC DASHBOARD | D1: =D12+D16+D17 -> 44 | E1: =E12+E16+E17 -> 115 | F1: =F12+F16+F17 -> 155 | G1: =G12+G16+G17 -> 78 | H1: =H12+H16+H17 -> 80 | I1: =I12+I16+I17 -> 45
D2: =D26+D30+D31 -> 11 | E2: =E26+E30+E31 -> 2 | F2: =F26+F30+F31 -> 4 | G2: =G26+G30+G31 -> 16 | H2: =H26+H30+H31 -> 4 | I2: =I26+I30+I31 -> 5
B4: MONTH | C4: UNIT | D4: JUL | E4: AUG | F4: SEP | G4: OCT | H4: NOV | I4: DEC | J4: JAN | K4: FEB | L4: MAR | M4: APR | N4: MAY | O4: JUN
A5: =Dashboard!A5 -> NEW CONNECTIONS WATER
A6: =Dashboard!A6 -> 1 | B6: =Dashboard!B6 -> CBD - NEW WATER | C6: =Dashboard!C6 -> No. | D6: =D34-'actual 2021-22'!O32 -> 0 | E6: =E34-D34 -> 0 | F6: =F34-E34 -> 5 | G6: 0 | H6: =H34-G34 -> 3 | I6: =I34-H34 -> 1 | J6: =J34-I34 -> 2 | K6: =K34-J34 -> 3 | L6: =L34-K34 -> 4 | M6: 2 | N6: 3 | O6: 8
A7: =Dashboard!A7 -> 2 | B7: =Dashboard!B7 -> CCCR- NEW WATER | C7: =Dashboard!C7 -> No. | D7: =D35-'actual 2021-22'!O33 -> 4 | E7: =E35-D35 -> 6 | F7: =F35-E35 -> 8 | G7: =G35-F35 -> 15 | H7: =H35-G35 -> 5 | I7: =I35-H35 -> 1 | J7: =J35-I35 -> 6 | K7: =K35-J35 -> 5 | L7: =L35-K35 -> 6 | M7: 1 | N7: 0 | O7: 14
A8: =Dashboard!A8 -> 3 | B8: =Dashboard!B8 -> KABATI- NEW WATER | C8: =Dashboard!C8 -> No. | D8: =D36-'actual 2021-22'!O34 -> 4 | E8: =E36-D36 -> 10 | F8: =F36-E36 -> 4 | G8: 0 | H8: =H36-G36 -> 2 | I8: =I36-H36 -> 8 | J8: =J36-I36 -> 10 | K8: =K36-J36 -> 5 | L8: =L36-K36 -> 8 | M8: 4 | N8: 4 | O8: 4
A9: =Dashboard!A9 -> 4 | B9: =Dashboard!B9 -> SITE- NEW WATER | C9: =Dashboard!C9 -> No. | D9: =D37-'actual 2021-22'!O35 -> 4 | E9: =E37-D37 -> 3 | F9: =F37-E37 -> 1 | G9: =G37-F37 -> 0 | H9: =H37-G37 -> 1 | I9: =I37-H37 -> 0 | J9: =J37-I37 -> 1 | K9: =K37-J37 -> 3 | L9: =L37-K37 -> 2 | M9: 5 | N9: 3 | O9: 2
A10: =Dashboard!A10 -> 5 | B10: =Dashboard!B10 -> KIHOTO- NEW WATER | C10: =Dashboard!C10 -> No. | D10: =D38-'actual 2021-22'!O36 -> 3 | E10: =E38-D38 -> 2 | F10: =F38-E38 -> 0 | G10: =G38-F38 -> 0 | H10: =H38-G38 -> 3 | I10: =I38-H38 -> 2 | J10: =J38-I38 -> 1 | K10: =K38-J38 -> 0 | L10: =L38-K38 -> 0 | M10: 2 | N10: 0 | O10: 5
A11: =Dashboard!A11 -> 6 | B11: =Dashboard!B11 -> LAKEVIEW- NEW WATER | C11: =Dashboard!C11 -> No. | D11: =D39-'actual 2021-22'!O41 -> 2 | E11: =E39-D39 -> 6 | F11: =F39-E39 -> 2 | G11: 3 | H11: =H39-G39 -> 7 | I11: =I39-H39 -> 7 | J11: =J39-I39 -> 6 | K11: =K39-J39 -> 9 | L11: =L39-K39 -> 10 | M11: 4 | N11: 1 | O11: 7
A12: =Dashboard!A13 -> 0 | B12: =Dashboard!B13 -> TOTAL NEW WATER CONNECTIONS CENTRAL REGION | C12: =Dashboard!C13 -> No. | D12: =SUM(D6:D11) -> 17 | E12: =SUM(E6:E11) -> 27 | F12: =SUM(F6:F11) -> 20 | G12: =SUM(G6:G11) -> 18 | H12: =SUM(H6:H11) -> 21 | I12: =SUM(I6:I11) -> 19 | J12: =SUM(J6:J11) -> 26 | K12: =SUM(K6:K11) -> 25 | ... O12: =SUM(O6:O11) -> 40
A13: =Dashboard!A14 -> 1 | B13: =Dashboard!B14 -> HELLSGATE- NEW WATER | C13: =Dashboard!C14 -> No. | D13: =D41-'actual 2021-22'!O38 -> 6 | E13: =E41-D41 -> 22 | F13: =F41-E41 -> 13 | G13: =G41-F41 -> 29 | H13: =H41-G41 -> 16 | I13: =I41-H41 -> 12 | J13: =J41-I41 -> 10 | K13: =K41-J41 -> 31 | L13: =L41-K41 -> 29 | M13: 19 | N13: 19 | O13: 24
A14: =Dashboard!A15 -> 2 | B14: =Dashboard!B15 -> KAMERE- NEW WATER | C14: =Dashboard!C15 -> No. | D14: =D42-'actual 2021-22'!O39 -> 0 | E14: =E42-D42 -> 3 | F14: =F42-E42 -> 0 | G14: =G42-F42 -> 1 | H14: =H42-G42 -> 2 | I14: =I42-H42 -> 0 | J14: =J42-I42 -> 1 | K14: =K42-J42 -> 1 | L14: =L42-K42 -> 1 | M14: 1 | N14: 0 | O14: 0
A15: =Dashboard!A16 -> 3 | B15: =Dashboard!B16 -> MAI-MAHIU- NEW WATER | C15: =Dashboard!C16 -> No. | D15: =D43-'actual 2021-22'!O42 -> 8 | E15: =E43-D43 -> 31 | F15: =F43-E43 -> 110 | G15: =G43-F43 -> 14 | H15: =H43-G43 -> 27 | I15: =I43-H43 -> 5 | J15: =J43-I43 -> 19 | K15: =K43-J43 -> 81 | L15: =L43-K43 -> 114 | M15: 52 | N15: 22 | O15: 24
A16: =Dashboard!A18 -> 0 | B16: =Dashboard!B18 -> TOTAL NEW WATER CONNECTION SOUTHERN REGION | C16: =Dashboard!C18 -> No. | D16: =SUM(D13:D15) -> 14 | E16: =SUM(E13:E15) -> 56 | F16: =SUM(F13:F15) -> 123 | G16: =SUM(G13:G15) -> 44 | H16: =SUM(H13:H15) -> 45 | I16: =SUM(I13:I15) -> 17 | J16: =SUM(J13:J15) -> 30 | K16: =SUM(K13:K15) -> 113 | ... O16: =SUM(O13:O15) -> 48
A17: =Dashboard!A20 -> 1 | B17: =Dashboard!B20 -> KAYOLE- NEW WATER | C17: =Dashboard!C20 -> No. | D17: =D45-'actual 2021-22'!O40 -> 13 | E17: =E45-D45 -> 32 | F17: =F45-E45 -> 12 | G17: =G45-F45 -> 16 | H17: =H45-G45 -> 14 | I17: =I45-H45 -> 9 | J17: =J45-I45 -> 29 | K17: =K45-J45 -> 25 | L17: =L45-K45 -> 57 | M17: 25 | N17: 20 | O17: 25
B18: TOTAL NEW CONNECTIONS WATER | D18: =D17+D16+D12 -> 44 | E18: =E17+E16+E12 -> 115 | F18: =F17+F16+F12 -> 155 | G18: =G17+G16+G12 -> 78 | H18: =H17+H16+H12 -> 80 | I18: =I17+I16+I12 -> 45 | J18: =J17+J16+J12 -> 85 | K18: =K17+K16+K12 -> 163 | ... O18: =O17+O16+O12 -> 113
A19: =Dashboard!A23 -> NEW CONNECTIONS SEWER
A20: =Dashboard!A24 -> 1 | B20: =Dashboard!B24 -> CBD- NEW SEWER | C20: =Dashboard!C24 -> No. | D20: =D47-'actual 2021-22'!O45 -> 1 | E20: =E47-D47 -> 1 | F20: =F47-E47 -> 1 | G20: =G47-F47 -> 2 | H20: =H47-G47 -> 0 | I20: =I47-H47 -> 1 | J20: =J47-I47 -> 0 | K20: =K47-J47 -> 2 | L20: =L47-K47 -> 0 | M20: 1 | N20: 3 | O20: 0
A21: =Dashboard!A25 -> 2 | B21: =Dashboard!B25 -> CCCR- NEW SEWER | C21: =Dashboard!C25 -> No. | D21: =D48-'actual 2021-22'!O46 -> 0 | E21: =E48-D48 -> 0 | F21: =F48-E48 -> 0 | G21: =G48-F48 -> 6 | H21: =H48-G48 -> 0 | I21: =I48-H48 -> 0 | J21: =J48-I48 -> 0 | K21: =K48-J48 -> 0 | L21: =L48-K48 -> 0 | M21: 2 | N21: 0 | O21: 0
A22: =Dashboard!A26 -> 3 | B22: =Dashboard!B26 -> KABATI- NEW SEWER | C22: =Dashboard!C26 -> No. | D22: =D49-'actual 2021-22'!O47 -> 0 | E22: =E49-D49 -> 1 | F22: =F49-E49 -> 2 | G22: =G49-F49 -> 3 | H22: =H49-G49 -> 0 | I22: =I49-H49 -> 0 | J22: =J49-I49 -> 0 | K22: =K49-J49 -> 0 | L22: =L49-K49 -> 2 | M22: 1 | N22: 3 | O22: 0
A23: =Dashboard!A27 -> 4 | B23: =Dashboard!B27 -> SITE- NEW SEWER | C23: =Dashboard!C27 -> No. | D23: =D50-'actual 2021-22'!O48 -> 0 | E23: =E50-D50 -> 0 | F23: =F50-E50 -> 0 | G23: =G50-F50 -> 2 | H23: =H50-G50 -> 2 | I23: =I50-H50 -> 3 | J23: =J50-I50 -> 1 | K23: =K50-J50 -> 6 | L23: =L50-K50 -> 0 | M23: 3 | N23: 1 | O23: 0
A24: =Dashboard!A28 -> 5 | B24: =Dashboard!B28 -> KIHOTO- NEW SEWER | C24: =Dashboard!C28 -> No. | D24: =D51-'actual 2021-22'!O49 -> 0 | E24: =E51-D51 -> 0 | F24: =F51-E51 -> 0 | G24: =G51-F51 -> 0 | H24: =H51-G51 -> 0 | I24: =I51-H51 -> 0 | J24: =J51-I51 -> 0 | K24: =K51-J51 -> 0 | L24: =L51-K51 -> 0 | M24: 0 | N24: 0 | O24: 0
A25: =Dashboard!A29 -> 6 | B25: =Dashboard!B29 -> LAKEVIEW- NEW SEWER | C25: =Dashboard!C29 -> No. | D25: =D52-'actual 2021-22'!O54 -> 1 | E25: =E52-D52 -> 0 | F25: 0 | G25: 1 | H25: 2 | I25: =I52-H52 -> 1 | J25: =J52-I52 -> 0 | K25: =K52-J52 -> 3 | L25: =L52-K52 -> 0 | M25: 1 | N25: 3 | O25: 2
A26: =Dashboard!A31 -> 0 | B26: =Dashboard!B31 -> TOTAL NEW SEWER CONNECTIONS CENTRAL REGION | C26: =Dashboard!C31 -> No. | D26: =SUM(D20:D25) -> 2 | E26: =SUM(E20:E25) -> 2 | F26: =SUM(F20:F25) -> 3 | G26: =SUM(G20:G25) -> 14 | H26: =SUM(H20:H25) -> 4 | I26: =SUM(I20:I25) -> 5 | J26: =SUM(J20:J25) -> 1 | K26: =SUM(K20:K25) -> 11 | ... O26: =SUM(O20:O25) -> 2
A27: =Dashboard!A32 -> 1 | B27: =Dashboard!B32 -> HELLSGATE- NEW SEWER | C27: =Dashboard!C32 -> No. | D27: =D54-'actual 2021-22'!O51 -> 0 | E27: =E54-D54 -> 0 | F27: =F54-E54 -> 0 | G27: =G54-F54 -> 0 | H27: =H54-G54 -> 0 | I27: =I54-H54 -> 0 | J27: =J54-I54 -> 0 | K27: =K54-J54 -> 0 | L27: =L54-K54 -> 0 | M27: 0 | N27: 0
A28: =Dashboard!A33 -> 2 | B28: =Dashboard!B33 -> KAMERE- NEW SEWER | C28: =Dashboard!C33 -> No. | D28: =D55-'actual 2021-22'!O52 -> 0 | E28: =E55-D55 -> 0 | F28: =F55-E55 -> 0 | G28: =G55-F55 -> 0 | H28: =H55-G55 -> 0 | I28: =I55-H55 -> 0 | J28: =J55-I55 -> 0 | K28: =K55-J55 -> 0 | L28: =L55-K55 -> 0 | M28: 0 | N28: 0
A29: =Dashboard!A34 -> 3 | B29: =Dashboard!B34 -> MAI-MAHIU- NEW SEWER | C29: =Dashboard!C34 -> No. | D29: =D56-'actual 2021-22'!O55 -> 0 | E29: =E56-D56 -> 0 | F29: =F56-E56 -> 0 | G29: =G56-F56 -> 0 | H29: =H56-G56 -> 0 | I29: =I56-H56 -> 0 | J29: =J56-I56 -> 0 | K29: =K56-J56 -> 0 | L29: =L56-K56 -> 0 | M29: 0 | N29: 0
A30: =Dashboard!A35 -> 0 | B30: =Dashboard!B35 -> TOTAL NEW S CONNECTION SOUTHERN REGION | C30: =Dashboard!C35 -> No. | D30: =SUM(D27:D29) -> 0 | E30: =SUM(E27:E29) -> 0 | F30: =SUM(F27:F29) -> 0 | G30: =SUM(G27:G29) -> 0 | H30: =SUM(H27:H29) -> 0 | I30: =SUM(I27:I29) -> 0 | J30: =SUM(J27:J29) -> 0 | K30: =SUM(K27:K29) -> 0 | ... O30: =SUM(O27:O29) -> 0
A31: =Dashboard!A37 -> 1 | B31: =Dashboard!B37 -> KAYOLE- NEW SEWER | C31: =Dashboard!C37 -> No. | D31: =D58-'actual 2021-22'!O53 -> 9 | E31: =E58-D58 -> 0 | F31: =F58-E58 -> 1 | G31: =G58-F58 -> 2 | H31: =H58-G58 -> 0 | I31: =I58-H58 -> 0 | J31: =J58-I58 -> 0 | K31: 0 | L31: 0 | M31: 0 | N31: 6 | O31: 6
B32: TOTAL NEW CONNECTIONS -SEWER | D32: =D31+D30+D26 -> 11 | E32: =E31+E30+E26 -> 2 | F32: =F31+F30+F26 -> 4 | G32: =G31+G30+G26 -> 16 | H32: =H31+H30+H26 -> 4 | I32: =I31+I30+I26 -> 5 | J32: =J31+J30+J26 -> 1 | K32: =K31+K30+K26 -> 11 | ... O32: =O31+O30+O26 -> 8
A33: =Dashboard!A38 -> TOTAL CONNECTIONS-WATER
A34: =Dashboard!A39 -> 1 | B34: =Dashboard!B39 -> CBD- WATER | C34: =Dashboard!C39 -> No. | D34: 756 | E34: 756 | F34: 761 | G34: 757 | H34: 760 | I34: 761 | J34: 763 | K34: 766 | L34: 770 | M34: 771 | N34: 774 | O34: 773
A35: =Dashboard!A40 -> 2 | B35: =Dashboard!B40 -> CCCR- WATER | C35: =Dashboard!C40 -> No. | D35: 713 | E35: 719 | F35: 727 | G35: 742 | H35: 747 | I35: 748 | J35: 754 | K35: 759 | L35: 765 | M35: 766 | N35: 765 | O35: 779
A36: =Dashboard!A41 -> 3 | B36: =Dashboard!B41 -> KABATI- WATER | C36: =Dashboard!C41 -> No. | D36: 850 | E36: 860 | F36: 864 | G36: 863 | H36: 865 | I36: 873 | J36: 883 | K36: 888 | L36: 896 | M36: 900 | N36: 904 | O36: 908
A37: =Dashboard!A42 -> 4 | B37: =Dashboard!B42 -> SITE- WATER | C37: =Dashboard!C42 -> No. | D37: 900 | E37: 903 | F37: 904 | G37: 904 | H37: 905 | I37: 905 | J37: 906 | K37: 909 | L37: 911 | M37: 916 | N37: 919 | O37: 921
A38: =Dashboard!A43 -> 5 | B38: =Dashboard!B43 -> KIHOTO- WATER | C38: =Dashboard!C43 -> No. | D38: 192 | E38: 194 | F38: 194 | G38: 194 | H38: 197 | I38: 199 | J38: 200 | K38: 200 | L38: 200 | M38: 202 | N38: 202 | O38: 207
A39: =Dashboard!A44 -> 6 | B39: =Dashboard!B44 -> LAKEVIEW- WATER | C39: =Dashboard!C44 -> No. | D39: 1345 | E39: 1351 | F39: 1353 | G39: 1361 | H39: 1368 | I39: 1375 | J39: 1381 | K39: 1390 | L39: 1400 | M39: 1404 | N39: 1406 | O39: 1413
A40: =Dashboard!A46 -> 0 | B40: =Dashboard!B46 -> TOTALWATER CONNECTION CENTRAL REGION | C40: =Dashboard!C46 -> No. | D40: =SUM(D34:D39) -> 4756 | E40: =SUM(E34:E39) -> 4783 | F40: =SUM(F34:F39) -> 4803 | G40: =SUM(G34:G39) -> 4821 | H40: =SUM(H34:H39) -> 4842 | I40: =SUM(I34:I39) -> 4861 | J40: =SUM(J34:J39) -> 4887 | K40: =SUM(K34:K39) -> 4912 | ... O40: =SUM(O34:O39) -> 5001
A41: =Dashboard!A47 -> 1 | B41: =Dashboard!B47 -> HELLSGATE- WATER | C41: =Dashboard!C47 -> No. | D41: 1384 | E41: 1406 | F41: 1419 | G41: 1448 | H41: 1464 | I41: 1476 | J41: 1486 | K41: 1517 | L41: 1546 | M41: 1564 | N41: 1583 | O41: 1607
A42: =Dashboard!A48 -> 2 | B42: =Dashboard!B48 -> KAMERE- WATER | C42: =Dashboard!C48 -> No. | D42: 333 | E42: 336 | F42: 336 | G42: 337 | H42: 339 | I42: 339 | J42: 340 | K42: 341 | L42: 342 | M42: 343 | N42: 343 | O42: 343
A43: =Dashboard!A49 -> 3 | B43: =Dashboard!B49 -> MAI-MAHIU- WATER | C43: =Dashboard!C49 -> No. | D43: 695 | E43: 726 | F43: 836 | G43: 850 | H43: 877 | I43: 882 | J43: 901 | K43: 982 | L43: 1096 | M43: 1148 | N43: 1170 | O43: 1194
A44: =Dashboard!A51 -> 0 | B44: =Dashboard!B51 -> TOTAL WATER CONNECTION SOUTHERN REGION | C44: =Dashboard!C51 -> No. | D44: =SUM(D41:D43) -> 2412 | E44: =SUM(E41:E43) -> 2468 | F44: =SUM(F41:F43) -> 2591 | G44: =SUM(G41:G43) -> 2635 | H44: =SUM(H41:H43) -> 2680 | I44: =SUM(I41:I43) -> 2697 | J44: =SUM(J41:J43) -> 2727 | K44: =SUM(K41:K43) -> 2840 | ... O44: =SUM(O41:O43) -> 3144
A45: =Dashboard!A53 -> 1 | B45: =Dashboard!B53 -> KAYOLE-WATER | C45: =Dashboard!C53 -> No. | D45: 2193 | E45: 2225 | F45: 2237 | G45: 2253 | H45: 2267 | I45: 2276 | J45: 2305 | K45: 2330 | L45: 2387 | M45: 2413 | N45: 2432 | O45: 2457
A46: =Dashboard!A56 -> TOTAL CONNECTIONS-SEWER
A47: =Dashboard!A57 -> 1 | B47: =Dashboard!B57 -> CBD- SEWER | C47: =Dashboard!C57 -> No. | D47: 429 | E47: 430 | F47: 431 | G47: 433 | H47: 433 | I47: 434 | J47: 434 | K47: 436 | L47: 436 | M47: 437 | N47: 440 | O47: 439
A48: =Dashboard!A58 -> 2 | B48: =Dashboard!B58 -> CCCR-SEWER | C48: =Dashboard!C58 -> No. | D48: 351 | E48: 351 | F48: 351 | G48: 357 | H48: 357 | I48: 357 | J48: 357 | K48: 357 | L48: 357 | M48: 359 | N48: 358 | O48: 358
A49: =Dashboard!A59 -> 3 | B49: =Dashboard!B59 -> KABATI-SEWER | C49: =Dashboard!C59 -> No. | D49: 313 | E49: 314 | F49: 316 | G49: 319 | H49: 319 | I49: 319 | J49: 319 | K49: 319 | L49: 321 | M49: 323 | N49: 326 | O49: 326
A50: =Dashboard!A60 -> 4 | B50: =Dashboard!B60 -> SITE- SEWER | C50: =Dashboard!C60 -> No. | D50: 512 | E50: 512 | F50: 512 | G50: 514 | H50: 516 | I50: 519 | J50: 520 | K50: 526 | L50: 526 | M50: 529 | N50: 530 | O50: 530
A51: =Dashboard!A61 -> 5 | B51: =Dashboard!B61 -> KIHOTO- SEWER | C51: =Dashboard!C61 -> No. | D51: 0 | E51: 0 | F51: 0 | G51: 0 | H51: 0 | I51: 0 | J51: 0 | K51: 0 | L51: 0 | M51: 0 | N51: 0 | O51: 0
A52: =Dashboard!A62 -> 6 | B52: =Dashboard!B62 -> LAKEVIEW- SEWER | C52: =Dashboard!C62 -> No. | D52: 152 | E52: 152 | F52: 151 | G52: 155 | H52: 155 | I52: 156 | J52: 156 | K52: 159 | L52: 159 | M52: 160 | N52: 164 | O52: 166
A53: =Dashboard!A64 -> 0 | B53: =Dashboard!B64 -> TOTAL SEWER CONNECTION CENTRAL REGION | C53: =Dashboard!C64 -> No. | D53: =SUM(D47:D52) -> 1757 | E53: =SUM(E47:E52) -> 1759 | F53: =SUM(F47:F52) -> 1761 | G53: =SUM(G47:G52) -> 1778 | H53: =SUM(H47:H52) -> 1780 | I53: =SUM(I47:I52) -> 1785 | J53: =SUM(J47:J52) -> 1786 | K53: =SUM(K47:K52) -> 1797 | ... O53: =SUM(O47:O52) -> 1819
A54: =Dashboard!A66 -> 1 | B54: =Dashboard!B66 -> HELLSGATE-SEWER | C54: =Dashboard!C66 -> No. | D54: 0 | E54: 0 | F54: 0 | G54: 0 | H54: 0 | I54: 0 | J54: 0 | K54: 0 | L54: 0 | M54: 0 | N54: 0 | O54: 0
A55: =Dashboard!A67 -> 2 | B55: =Dashboard!B67 -> KAMERE- SEWER | C55: =Dashboard!C67 -> No. | D55: 0 | E55: 0 | F55: 0 | G55: 0 | H55: 0 | I55: 0 | J55: 0 | K55: 0 | L55: 0 | M55: 0 | N55: 0 | O55: 0
A56: =Dashboard!A68 -> 3 | B56: =Dashboard!B68 -> MAI-MAHIU-SEWER | C56: =Dashboard!C68 -> No. | D56: 0 | E56: 0 | F56: 0 | G56: 0 | H56: 0 | I56: 0 | J56: 0 | K56: 0 | L56: 0 | M56: 0 | N56: 0 | O56: 0
A57: =Dashboard!A69 -> 0 | B57: =Dashboard!B69 -> TOTAL SEWER CONNECTION SOUTHERNREGION | C57: =Dashboard!C69 -> No. | D57: =SUM(D54:D56) -> 0 | E57: =SUM(E54:E56) -> 0 | F57: =SUM(F54:F56) -> 0 | G57: =SUM(G54:G56) -> 0 | H57: =SUM(H54:H56) -> 0 | I57: =SUM(I54:I56) -> 0 | J57: =SUM(J54:J56) -> 0 | K57: =SUM(K54:K56) -> 0 | ... O57: =SUM(O54:O56) -> 0
A58: =Dashboard!A71 -> 1 | B58: =Dashboard!B71 -> KAYOLE-SEWER | C58: =Dashboard!C71 -> No. | D58: 77 | E58: 77 | F58: 78 | G58: 80 | H58: 80 | I58: 80 | J58: 80 | K58: 79 | L58: 9 | M58: 9 | N58: 15 | O58: 21
A59: =Dashboard!A72 -> TOTAL ACTIVE CONNECTIONS-WATER
A60: =Dashboard!A73 -> 1 | B60: =Dashboard!B73 -> CBD- ACTIVE WATER | C60: =Dashboard!C73 -> No. | D60: 577 | E60: 577 | F60: 579 | G60: 574 | H60: 574 | I60: 577 | J60: 582 | K60: 586 | L60: 587 | M60: 590 | N60: 592 | O60: 583
A61: =Dashboard!A74 -> 2 | B61: =Dashboard!B74 -> CCCR- ACTIVE WATER | C61: =Dashboard!C74 -> No. | D61: 544 | E61: 544 | F61: 551 | G61: 561 | H61: 570 | I61: 572 | J61: 577 | K61: 582 | L61: 587 | M61: 588 | N61: 588 | O61: 593
A62: =Dashboard!A75 -> 3 | B62: =Dashboard!B75 -> KABATI- ACTIVE WATER | C62: =Dashboard!C75 -> No. | D62: 761 | E62: 771 | F62: 775 | G62: 773 | H62: 776 | I62: 781 | J62: 783 | K62: 791 | L62: 800 | M62: 805 | N62: 805 | O62: 811
A63: =Dashboard!A76 -> 4 | B63: =Dashboard!B76 -> SITE- ACTIVE WATER | C63: =Dashboard!C76 -> No. | D63: 788 | E63: 793 | F63: 795 | G63: 794 | H63: 794 | I63: 794 | J63: 794 | K63: 794 | L63: 800 | M63: 802 | N63: 808 | O63: 811
A64: =Dashboard!A77 -> 5 | B64: =Dashboard!B77 -> KIHOTO-ACTIVE WATER | C64: =Dashboard!C77 -> No. | D64: 147 | E64: 147 | F64: 150 | G64: 151 | H64: 150 | I64: 152 | J64: 152 | K64: 155 | L64: 155 | M64: 155 | N64: 156 | O64: 157
A65: =Dashboard!A78 -> 6 | B65: =Dashboard!B78 -> LAKEVIEW- ACTIVE WATER | C65: =Dashboard!C78 -> No. | D65: 1075 | E65: 1096 | F65: 1106 | G65: 1123 | H65: 1129 | I65: 1138 | J65: 1147 | K65: 1150 | L65: 1164 | M65: 1167 | N65: 1171 | O65: 1180
A66: =Dashboard!A80 -> 0 | B66: =Dashboard!B80 -> TOTAL ACTIVE WATER CONNECTION CENTRAL REGION | C66: =Dashboard!C80 -> No. | D66: =SUM(D60:D65) -> 3892 | E66: =SUM(E60:E65) -> 3928 | F66: =SUM(F60:F65) -> 3956 | G66: =SUM(G60:G65) -> 3976 | H66: =SUM(H60:H65) -> 3993 | I66: =SUM(I60:I65) -> 4014 | J66: =SUM(J60:J65) -> 4035 | K66: =SUM(K60:K65) -> 4058 | ... O66: =SUM(O60:O65) -> 4135
A67: =Dashboard!A81 -> 1 | B67: =Dashboard!B81 -> HELLSGATE- ACTIVE WATER | C67: =Dashboard!C81 -> No. | D67: 1169 | E67: 1191 | F67: 1203 | G67: 1236 | H67: 1247 | I67: 1257 | J67: 1275 | K67: 1297 | L67: 1317 | M67: 1343 | N67: 1362 | O67: 1390
A68: =Dashboard!A82 -> 2 | B68: =Dashboard!B82 -> KAMERE- ACTIVE WATER | C68: =Dashboard!C82 -> No. | D68: 236 | E68: 236 | F68: 236 | G68: 237 | H68: 238 | I68: 238 | J68: 239 | K68: 239 | L68: 240 | M68: 240 | N68: 243 | O68: 243
A69: =Dashboard!A83 -> 3 | B69: =Dashboard!B83 -> MAI-MAHIU- ACTIVE WATER | C69: =Dashboard!C83 -> No. | D69: 257 | E69: 419 | F69: 444 | G69: 519 | H69: 551 | I69: 561 | J69: 592 | K69: 606 | L69: 634 | M69: 642 | N69: 662 | O69: 682
A70: =Dashboard!A85 -> 0 | B70: =Dashboard!B85 -> TOTAL ACTIVE WATER CONNECTION SOUTHERN REGION | C70: =Dashboard!C85 -> No. | D70: =SUM(D67:D69) -> 1662 | E70: =SUM(E67:E69) -> 1846 | F70: =SUM(F67:F69) -> 1883 | G70: =SUM(G67:G69) -> 1992 | H70: =SUM(H67:H69) -> 2036 | I70: =SUM(I67:I69) -> 2056 | J70: =SUM(J67:J69) -> 2106 | K70: =SUM(K67:K69) -> 2142 | ... O70: =SUM(O67:O69) -> 2315
A71: =Dashboard!A87 -> 1 | B71: =Dashboard!B87 -> KAYOLE- ACTIVE WATER | C71: =Dashboard!C87 -> No. | D71: 2044 | E71: 2071 | F71: 2089 | G71: 2113 | H71: 2122 | I71: 2135 | J71: 2157 | K71: 2182 | L71: 2225 | M71: 2245 | N71: 2263 | O71: 2294
A72: =Dashboard!A90 -> TOTAL ACTIVE CONNECTIONS-SEWER
A73: =Dashboard!A91 -> 1 | B73: =Dashboard!B91 -> CBD- ACTIVE SEWER | C73: =Dashboard!C91 -> No. | D73: 374 | E73: 376 | F73: 377 | G73: 379 | H73: 377 | I73: 378 | J73: 378 | K73: 358 | L73: 358 | M73: 359 | N73: 363 | O73: 352
A74: =Dashboard!A92 -> 2 | B74: =Dashboard!B92 -> CCCR- ACTIVE SEWER | C74: =Dashboard!C92 -> No. | D74: 312 | E74: 312 | F74: 312 | G74: 318 | H74: 318 | I74: 318 | J74: 318 | K74: 297 | L74: 296 | M74: 298 | N74: 297 | O74: 297
A75: =Dashboard!A93 -> 3 | B75: =Dashboard!B93 -> KABATI- ACTIVE SEWER | C75: =Dashboard!C93 -> No. | D75: 293 | E75: 293 | F75: 295 | G75: 299 | H75: 299 | I75: 299 | J75: 299 | K75: 368 | L75: 268 | M75: 269 | N75: 272 | O75: 272
A76: =Dashboard!A94 -> 4 | B76: =Dashboard!B94 -> SITE- ACTIVE SEWER | C76: =Dashboard!C94 -> No. | D76: 453 | E76: 454 | F76: 455 | G76: 456 | H76: 458 | I76: 460 | J76: 461 | K76: 437 | L76: 437 | M76: 440 | N76: 441 | O76: 441
A77: =Dashboard!A95 -> 5 | B77: =Dashboard!B95 -> KIHOTO- ACTIVE SEWER | C77: =Dashboard!C95 -> No. | D77: 0 | E77: 0 | F77: 0 | G77: 0 | H77: 0 | I77: 0 | J77: 0 | K77: 0 | L77: 0 | M77: 0 | N77: 0 | O77: 0
A78: =Dashboard!A96 -> 6 | B78: =Dashboard!B96 -> LAKEVIEW- ACTIVE SEWER | C78: =Dashboard!C96 -> No. | D78: 125 | E78: 125 | F78: 124 | G78: 128 | H78: 127 | I78: 128 | J78: 128 | K78: 131 | L78: 131 | M78: 132 | N78: 136 | O78: 138
A79: =Dashboard!A98 -> 0 | B79: =Dashboard!B98 -> TOTAL ACTIVE SEWER CONNECTION CENTRAL REGION | C79: =Dashboard!C98 -> No. | D79: =SUM(D73:D78) -> 1557 | E79: =SUM(E73:E78) -> 1560 | F79: =SUM(F73:F78) -> 1563 | G79: =SUM(G73:G78) -> 1580 | H79: =SUM(H73:H78) -> 1579 | I79: =SUM(I73:I78) -> 1583 | J79: =SUM(J73:J78) -> 1584 | K79: =SUM(K73:K78) -> 1591 | ... O79: =SUM(O73:O78) -> 1500
A80: =Dashboard!A99 -> 1 | B80: =Dashboard!B99 -> HELLSGATE- ACTIVE SEWER | C80: =Dashboard!C99 -> No. | D80: 0 | E80: 0 | F80: 0 | G80: 0 | H80: 0 | I80: 0 | J80: 0 | K80: 0 | L80: 0 | M80: 0 | N80: 0
A81: =Dashboard!A100 -> 2 | B81: =Dashboard!B100 -> KAMERE- ACTIVE SEWER | C81: =Dashboard!C100 -> No. | D81: 0 | E81: 0 | F81: 0 | G81: 0 | H81: 0 | I81: 0 | J81: 0 | K81: 0 | L81: 0 | M81: 0 | N81: 0
A82: =Dashboard!A101 -> 3 | B82: =Dashboard!B101 -> MAI-MAHIU- ACTIVE SEWER | C82: =Dashboard!C101 -> No. | D82: 0 | E82: 0 | F82: 0 | G82: 0 | H82: 0 | I82: 0 | J82: 0 | K82: 0 | L82: 0 | M82: 0 | N82: 0
A83: =Dashboard!A102 -> 0 | B83: =Dashboard!B102 -> TOTAL ACTIVE SEWER CONNECTION SOUTHERN REGION | C83: =Dashboard!C102 -> No. | D83: =SUM(D80:D82) -> 0 | E83: =SUM(E80:E82) -> 0 | F83: =SUM(F80:F82) -> 0 | G83: =SUM(G80:G82) -> 0 | H83: =SUM(H80:H82) -> 0 | I83: =SUM(I80:I82) -> 0 | J83: =SUM(J80:J82) -> 0 | K83: =SUM(K80:K82) -> 0 | ... O83: =SUM(O80:O82) -> 0
A84: =Dashboard!A104 -> 1 | B84: =Dashboard!B104 -> KAYOLE- ACTIVE SEWER | C84: =Dashboard!C104 -> No. | D84: 77 | E84: 77 | F84: 78 | G84: 80 | H84: 80 | I84: 80 | J84: 80 | K84: 78 | L84: 8 | M84: 8 | N84: 14 | O84: 20
A85: =Dashboard!A105 -> SUMMARY CONNECTIONS
A86: =Dashboard!A106 -> 1 | B86: =Dashboard!B106 -> TOTAL WATER CONNECTIONS | C86: =Dashboard!C106 -> No. | D86: =D40+D44+D45 -> 9361 | E86: =E40+E44+E45 -> 9476 | F86: =F40+F44+F45 -> 9631 | G86: =G40+G44+G45 -> 9709 | H86: =H40+H44+H45 -> 9789 | I86: =I40+I44+I45 -> 9834 | J86: =J40+J44+J45 -> 9919 | K86: =K40+K44+K45 -> 10082 | ... O86: =O40+O44+O45 -> 10602
A87: =Dashboard!A107 -> 2 | B87: =Dashboard!B107 -> TOTAL SEWER CONNECTIONS | C87: =Dashboard!C107 -> No. | D87: =D57+D53+D58 -> 1834 | E87: =E57+E53+E58 -> 1836 | F87: =F57+F53+F58 -> 1839 | G87: =G57+G53+G58 -> 1858 | H87: =H57+H53+H58 -> 1860 | I87: =I57+I53+I58 -> 1865 | J87: =J57+J53+J58 -> 1866 | K87: =K57+K53+K58 -> 1876 | ... O87: =O57+O53+O58 -> 1840
A88: =Dashboard!A108 -> 3 | B88: =Dashboard!B108 -> TOTAL ACTIVE WATER CONNECTIONS | C88: =Dashboard!C108 -> No. | D88: =D66+D70+D71 -> 7598 | E88: =E66+E70+E71 -> 7845 | F88: =F66+F70+F71 -> 7928 | G88: =G66+G70+G71 -> 8081 | H88: =H66+H70+H71 -> 8151 | I88: =I66+I70+I71 -> 8205 | J88: =J66+J70+J71 -> 8298 | K88: =K66+K70+K71 -> 8382 | ... O88: =O66+O70+O71 -> 8744
A89: =Dashboard!A109 -> 4 | B89: =Dashboard!B109 -> TOTAL SEWER ACTIVE CONNECTIONS | C89: =Dashboard!C109 -> No. | D89: =D79+D83+D84 -> 1634 | E89: =E79+E83+E84 -> 1637 | F89: =F79+F83+F84 -> 1641 | G89: =G79+G83+G84 -> 1660 | H89: =H79+H83+H84 -> 1659 | I89: =I79+I83+I84 -> 1663 | J89: =J79+J83+J84 -> 1664 | K89: =K79+K83+K84 -> 1669 | ... O89: =O79+O83+O84 -> 1520
A90: =Dashboard!A112 -> 5 | B90: =Dashboard!B112 -> % ACTIVE CONNECTIONS | C90: =Dashboard!C112 -> No. | D90: =SUM(D88:D89)/SUM(D86:D87) -> 0.82465386 | E90: =SUM(E88:E89)/SUM(E86:E87) -> 0.83822489 | F90: =SUM(F88:F89)/SUM(F86:F87) -> 0.8342633 | G90: =SUM(G88:G89)/SUM(G86:G87) -> 0.84213711 | H90: =SUM(H88:H89)/SUM(H86:H87) -> 0.84213237 | I90: =SUM(I88:I89)/SUM(I86:I87) -> 0.8434909 | J90: =SUM(J88:J89)/SUM(J86:J87) -> 0.84531184 | K90: =SUM(K88:K89)/SUM(K86:K87) -> 0.84052517 | ... O90: =SUM(O88:O89)/SUM(O86:O87) -> 0.82494776
A91: =Dashboard!A113 -> TOTAL BILLING IN M3 - WATER
A92: =Dashboard!A114 -> 1 | B92: =Dashboard!B114 -> CBD - WATER(M3) | C92: =Dashboard!C114 -> M3 | D92: 16276 | E92: 15745 | F92: 14642 | G92: 10926 | H92: 16241 | I92: 14596 | J92: 13738 | K92: 16338 | L92: 16947 | M92: 13863 | N92: 14764 | O92: 15453
A93: =Dashboard!A115 -> 2 | B93: =Dashboard!B115 -> CCCR - WATER(M3) | C93: =Dashboard!C115 -> M3 | D93: 26014 | E93: 25915 | F93: 22957 | G93: 15606 | H93: 18594 | I93: 22016 | J93: 22166 | K93: 22610 | L93: 23154 | M93: 22838 | N93: 21463 | O93: 21858
A94: =Dashboard!A116 -> 3 | B94: =Dashboard!B116 -> KABATI - WATER(M3) | C94: =Dashboard!C116 -> M3 | D94: 12529 | E94: 13190 | F94: 10507 | G94: 13004 | H94: 7682 | I94: 12092 | J94: 10940 | K94: 13438 | L94: 13760 | M94: 11740 | N94: 9964 | O94: 11468
A95: =Dashboard!A117 -> 4 | B95: =Dashboard!B117 -> SITE - WATER(M3) | C95: =Dashboard!C117 -> M3 | D95: 10322 | E95: 10117 | F95: 9026 | G95: 10000 | H95: 7869 | I95: 9280 | J95: 10263 | K95: 11014 | L95: 10702 | M95: 10235 | N95: 9134 | O95: 9404
A96: =Dashboard!A118 -> 5 | B96: =Dashboard!B118 -> KIHOTO - WATER(M3) | C96: =Dashboard!C118 -> M3 | D96: 2772 | E96: 2080 | F96: 1347 | G96: 1141 | H96: 1693 | I96: 1590 | J96: 2369 | K96: 2241 | L96: 2236 | M96: 1444 | N96: 1437 | O96: 1692
A97: =Dashboard!A119 -> 6 | B97: =Dashboard!B119 -> LAKEVIEW - WATER(M3) | C97: =Dashboard!C119 -> M3 | D97: 23194 | E97: 25400 | F97: 32758 | G97: 20259 | H97: 19822 | I97: 21110 | J97: 23140 | K97: 25593 | L97: 27005 | M97: 24587 | N97: 16817 | O97: 21299
A98: =Dashboard!A121 -> 0 | B98: =Dashboard!B121 -> TOTAL - WATER(M3) CENTRAL REGION | C98: =Dashboard!C121 -> M3 | D98: =SUM(D92:D97) -> 91107 | E98: =SUM(E92:E97) -> 92447 | F98: =SUM(F92:F97) -> 91237 | G98: =SUM(G92:G97) -> 70936 | H98: =SUM(H92:H97) -> 71901 | I98: =SUM(I92:I97) -> 80684 | J98: =SUM(J92:J97) -> 82616 | K98: =SUM(K92:K97) -> 91234 | ... O98: =SUM(O92:O97) -> 81174
A99: =Dashboard!A122 -> 1 | B99: =Dashboard!B122 -> HELLSGATE - WATER(M3) | C99: =Dashboard!C122 -> M3 | D99: 20752 | E99: 21521 | F99: 18968 | G99: 18382 | H99: 19743 | I99: 17301 | J99: 20591 | K99: 22250 | L99: 24784 | M99: 22577 | N99: 14170 | O99: 22076
A100: =Dashboard!A123 -> 2 | B100: =Dashboard!B123 -> KAMERE - WATER(M3) | C100: =Dashboard!C123 -> M3 | D100: 6689 | E100: 7168 | F100: 6829 | G100: 6369 | H100: 6247 | I100: 5706 | J100: 5916 | K100: 6958 | L100: 6756 | M100: 6326 | N100: 4365 | O100: 5937
A101: =Dashboard!A124 -> 3 | B101: =Dashboard!B124 -> MAI-MAHIU - WATER(M3) | C101: =Dashboard!C124 -> M3 | D101: 3010 | E101: 4054 | F101: 6482 | G101: 5612 | H101: 4918 | I101: 6474 | J101: 6589 | K101: 8073 | L101: 9560 | M101: 7050 | N101: 3034 | O101: 5452
...

Sheet Sheet1

Sheet actual 2021-22
A1: =Dashboard!A1 -> SALES & CC DASHBOARD | J1: =J11+J17 -> 51 | K1: =K11+K17 -> 99 | L1: =L11+L17 -> 161 | M1: =M11+M17 -> 103 | N1: =N11+N17 -> 52 | O1: =O11+O17 -> 113
J2: =J24+J30 -> 1 | K2: =K24+K30 -> 1 | L2: =L24+L30 -> 73 | M2: =M24+M30 -> 14 | N2: =N24+N30 -> 1 | O2: =O24+O30 -> 0
B4: MONTH | C4: UNIT | D4: JUL | E4: AUG | F4: SEP | G4: OCT | H4: NOV | I4: DEC | J4: JAN | K4: FEB | L4: MAR | M4: APR | N4: MAY | O4: JUN
A5: =Dashboard!A5 -> NEW CONNECTIONS WATER
A6: =Dashboard!A6 -> 1 | B6: =Dashboard!B6 -> CBD - NEW WATER | C6: =Dashboard!C6 -> No. | D6: 2 | E6: 2 | F6: 5 | G6: 0 | H6: 3 | I6: 2 | J6: 0 | K6: 3 | L6: 5 | M6: 0 | N6: 2 | O6: 2
A7: =Dashboard!A7 -> 2 | B7: =Dashboard!B7 -> CCCR- NEW WATER | C7: =Dashboard!C7 -> No. | D7: 4 | E7: 6 | F7: 4 | G7: 6 | H7: 2 | I7: 12 | J7: 2 | K7: 28 | L7: 3 | M7: 0 | N7: 3 | O7: 2
A8: =Dashboard!A8 -> 3 | B8: =Dashboard!B8 -> KABATI- NEW WATER | C8: =Dashboard!C8 -> No. | D8: 16 | E8: 3 | F8: 3 | G8: 9 | H8: 4 | I8: 30 | J8: 0 | K8: 3 | L8: 2 | M8: 5 | N8: 4 | O8: 5
A9: =Dashboard!A9 -> 4 | B9: =Dashboard!B9 -> SITE- NEW WATER | C9: =Dashboard!C9 -> No. | D9: 6 | E9: 12 | F9: 9 | G9: 3 | H9: 5 | I9: 11 | J9: 3 | K9: 3 | L9: 3 | M9: 3 | N9: 2 | O9: 3
A10: =Dashboard!A10 -> 5 | B10: =Dashboard!B10 -> KIHOTO- NEW WATER | C10: =Dashboard!C10 -> No. | D10: 2 | E10: 1 | F10: 2 | G10: 2 | H10: 0 | I10: 5 | J10: 0 | K10: 0 | L10: 3 | M10: 2 | N10: 3 | O10: 0
A11: =Dashboard!A13 -> 0 | B11: =Dashboard!B13 -> TOTAL NEW WATER CONNECTIONS CENTRAL REGION | C11: =Dashboard!C13 -> No. | D11: 30 | E11: 24 | F11: 23 | G11: 20 | H11: 14 | I11: 60 | J11: 5 | K11: 37 | L11: 16 | M11: 10 | N11: 14 | O11: 12
A12: =Dashboard!A14 -> 1 | B12: =Dashboard!B14 -> HELLSGATE- NEW WATER | C12: =Dashboard!C14 -> No. | D12: ` | E12: 37 | F12: 55 | G12: 66 | H12: 34 | I12: 29 | J12: 20 | K12: 18 | L12: 42 | M12: 13 | N12: 13 | O12: 26
A13: =Dashboard!A15 -> 2 | B13: =Dashboard!B15 -> KAMERE- NEW WATER | C13: =Dashboard!C15 -> No. | D13: 1 | E13: 3 | F13: 1 | G13: 1 | H13: 1 | I13: 0 | J13: 0 | K13: 1 | L13: 1 | M13: 0 | N13: 2 | O13: 0
A14: =Dashboard!A20 -> 1 | B14: =Dashboard!B20 -> KAYOLE- NEW WATER | C14: =Dashboard!C20 -> No. | D14: 24 | E14: 20 | F14: 19 | G14: 20 | H14: 23 | I14: 25 | J14: 15 | K14: 16 | L14: 84 | M14: 17 | N14: 11 | O14: 37
A15: =Dashboard!A11 -> 6 | B15: =Dashboard!B11 -> LAKEVIEW- NEW WATER | C15: =Dashboard!C11 -> No. | D15: 4 | E15: 6 | F15: 10 | G15: 18 | H15: 54 | I15: 34 | J15: 5 | K15: 8 | L15: 12 | M15: 37 | N15: 4 | O15: 4
A16: =Dashboard!A16 -> 3 | B16: =Dashboard!B16 -> MAI-MAHIU- NEW WATER | C16: =Dashboard!C16 -> No. | D16: 22 | E16: 24 | F16: 57 | G16: 192 | H16: 58 | I16: 87 | J16: 6 | K16: 19 | L16: 6 | M16: 26 | N16: 8 | O16: 34
A17: =Dashboard!A18 -> 0 | B17: =Dashboard!B18 -> TOTAL NEW WATER CONNECTION SOUTHERN REGION | C17: =Dashboard!C18 -> No. | D17: 51 | E17: 90 | F17: 142 | G17: 297 | H17: 170 | I17: 175 | J17: 46 | K17: 62 | L17: 145 | M17: 93 | N17: 38 | O17: 101
A18: =Dashboard!A23 -> NEW CONNECTIONS SEWER
A19: =Dashboard!A24 -> 1 | B19: =Dashboard!B24 -> CBD- NEW SEWER | C19: =Dashboard!C24 -> No. | D19: 2 | E19: 2 | F19: 0 | G19: 0 | H19: 4 | I19: 0 | J19: 0 | K19: 0 | L19: 2 | M19: 0 | N19: 0 | O19: 0
A20: =Dashboard!A25 -> 2 | B20: =Dashboard!B25 -> CCCR- NEW SEWER | C20: =Dashboard!C25 -> No. | D20: 0 | E20: 2 | F20: 0 | G20: 1 | H20: 2 | I20: 0 | J20: 0 | K20: 0 | L20: 2 | M20: 9 | N20: 0 | O20: 0
A21: =Dashboard!A26 -> 3 | B21: =Dashboard!B26 -> KABATI- NEW SEWER | C21: =Dashboard!C26 -> No. | D21: 1 | E21: 1 | F21: 0 | G21: 0 | H21: 4 | I21: 0 | J21: 1 | K21: 0 | L21: 2 | M21: 0 | N21: 1 | O21: 0
A22: =Dashboard!A27 -> 4 | B22: =Dashboard!B27 -> SITE- NEW SEWER | C22: =Dashboard!C27 -> No. | D22: 0 | E22: 0 | F22: 0 | G22: 0 | H22: 2 | I22: 1 | J22: 0 | K22: 0 | L22: 0 | M22: 2 | N22: 0 | O22: 0
A23: =Dashboard!A28 -> 5 | B23: =Dashboard!B28 -> KIHOTO- NEW SEWER | C23: =Dashboard!C28 -> No. | D23: 0 | E23: 0 | F23: 0 | G23: 0 | H23: 0 | I23: 0 | J23: 0 | K23: 0 | L23: 0 | M23: 0 | N23: 0 | O23: 0
A24: =Dashboard!A31 -> 0 | B24: =Dashboard!B31 -> TOTAL NEW SEWER CONNECTIONS CENTRAL REGION | C24: =Dashboard!C31 -> No. | D24: 3 | E24: 5 | F24: 0 | G24: 1 | H24: 12 | I24: 1 | J24: 1 | K24: 0 | L24: 6 | M24: 11 | N24: 1 | O24: 0
A25: =Dashboard!A32 -> 1 | B25: =Dashboard!B32 -> HELLSGATE- NEW SEWER | C25: =Dashboard!C32 -> No. | D25: 0 | E25: 0 | F25: 0 | G25: 0 | H25: 0 | I25: 0 | J25: 0 | K25: 0 | L25: 0 | M25: 0 | N25: 0 | O25: 0
A26: =Dashboard!A33 -> 2 | B26: =Dashboard!B33 -> KAMERE- NEW SEWER | C26: =Dashboard!C33 -> No. | D26: 0 | E26: 0 | F26: 0 | G26: 0 | H26: 0 | I26: 0 | J26: 0 | K26: 0 | L26: 0 | M26: 0 | N26: 0 | O26: 0
A27: =Dashboard!A37 -> 1 | B27: =Dashboard!B37 -> KAYOLE- NEW SEWER | C27: =Dashboard!C37 -> No. | D27: 0 | E27: 0 | F27: 0 | G27: 2 | H27: 0 | I27: 0 | J27: 0 | K27: 0 | L27: 63 | M27: 3 | N27: 0 | O27: 0
A28: =Dashboard!A29 -> 6 | B28: =Dashboard!B29 -> LAKEVIEW- NEW SEWER | C28: =Dashboard!C29 -> No. | D28: 1 | E28: 1 | F28: 0 | G28: 4 | H28: 2 | I28: 1 | J28: 0 | K28: 1 | L28: 4 | M28: 0 | N28: 0 | O28: 0
A29: =Dashboard!A34 -> 3 | B29: =Dashboard!B34 -> MAI-MAHIU- NEW SEWER | C29: =Dashboard!C34 -> No. | D29: 0 | E29: 0 | F29: 0 | G29: 0 | H29: 0 | I29: 0 | J29: 0 | K29: 0 | L29: 0 | M29: 0 | N29: 0 | O29: 0
A30: =Dashboard!A35 -> 0 | B30: =Dashboard!B35 -> TOTAL NEW S CONNECTION SOUTHERN REGION | C30: =Dashboard!C35 -> No. | D30: 1 | E30: 1 | F30: 0 | G30: 6 | H30: 2 | I30: 1 | J30: 0 | K30: 1 | L30: 67 | M30: 3 | N30: 0 | O30: 0
A31: =Dashboard!A38 -> TOTAL CONNECTIONS-WATER
A32: =Dashboard!A39 -> 1 | B32: =Dashboard!B39 -> CBD- WATER | C32: =Dashboard!C39 -> No. | D32: 734 | E32: 733 | F32: 738 | G32: 743 | H32: 746 | I32: 748 | J32: 748 | K32: 751 | L32: 756 | M32: 752 | N32: 754 | O32: 756
A33: =Dashboard!A40 -> 2 | B33: =Dashboard!B40 -> CCCR- WATER | C33: =Dashboard!C40 -> No. | D33: 669 | E33: 672 | F33: 676 | G33: 682 | H33: 684 | I33: 696 | J33: 698 | K33: 726 | L33: 729 | M33: 704 | N33: 707 | O33: 709
A34: =Dashboard!A41 -> 3 | B34: =Dashboard!B41 -> KABATI- WATER | C34: =Dashboard!C41 -> No. | D34: 787 | E34: 789 | F34: 792 | G34: 793 | H34: 800 | I34: 830 | J34: 827 | K34: 830 | L34: 832 | M34: 837 | N34: 841 | O34: 846
A35: =Dashboard!A42 -> 4 | B35: =Dashboard!B42 -> SITE- WATER | C35: =Dashboard!C42 -> No. | D35: 838 | E35: 848 | F35: 857 | G35: 860 | H35: 865 | I35: 876 | J35: 882 | K35: 885 | L35: 888 | M35: 891 | N35: 893 | O35: 896
A36: =Dashboard!A43 -> 5 | B36: =Dashboard!B43 -> KIHOTO- WATER | C36: =Dashboard!C43 -> No. | D36: 171 | E36: 172 | F36: 174 | G36: 176 | H36: 176 | I36: 181 | J36: 181 | K36: 181 | L36: 184 | M36: 186 | N36: 189 | O36: 189
A37: =Dashboard!A46 -> 0 | B37: =Dashboard!B46 -> TOTALWATER CONNECTION CENTRAL REGION | C37: =Dashboard!C46 -> No. | D37: 3199 | E37: 3214 | F37: 3237 | G37: 3254 | H37: 3271 | I37: 3331 | J37: 3336 | K37: 3373 | L37: 3389 | M37: 3370 | N37: 3384 | O37: 3396
A38: =Dashboard!A47 -> 1 | B38: =Dashboard!B47 -> HELLSGATE- WATER | C38: =Dashboard!C47 -> No. | D38: 1026 | E38: 1062 | F38: 1117 | G38: 1183 | H38: 1217 | I38: 1246 | J38: 1266 | K38: 1284 | L38: 1326 | M38: 1339 | N38: 1352 | O38: 1378
A39: =Dashboard!A48 -> 2 | B39: =Dashboard!B48 -> KAMERE- WATER | C39: =Dashboard!C48 -> No. | D39: 323 | E39: 326 | F39: 327 | G39: 328 | H39: 329 | I39: 329 | J39: 329 | K39: 330 | L39: 331 | M39: 331 | N39: 333 | O39: 333
A40: =Dashboard!A53 -> 1 | B40: =Dashboard!B53 -> KAYOLE-WATER | C40: =Dashboard!C53 -> No. | D40: 1891 | E40: 1913 | F40: 1932 | G40: 1952 | H40: 1975 | I40: 2000 | J40: 2015 | K40: 2031 | L40: 2115 | M40: 2132 | N40: 2143 | O40: 2180
A41: =Dashboard!A44 -> 6 | B41: =Dashboard!B44 -> LAKEVIEW- WATER | C41: =Dashboard!C44 -> No. | D41: 1148 | E41: 1157 | F41: 1167 | G41: 1185 | H41: 1239 | I41: 1273 | J41: 1278 | K41: 1286 | L41: 1298 | M41: 1335 | N41: 1339 | O41: 1343
A42: =Dashboard!A49 -> 3 | B42: =Dashboard!B49 -> MAI-MAHIU- WATER | C42: =Dashboard!C49 -> No. | D42: 170 | E42: 194 | F42: 251 | G42: 443 | H42: 501 | I42: 588 | J42: 594 | K42: 613 | L42: 619 | M42: 645 | N42: 653 | O42: 687
A43: =Dashboard!A51 -> 0 | B43: =Dashboard!B51 -> TOTAL WATER CONNECTION SOUTHERN REGION | C43: =Dashboard!C51 -> No. | D43: 4558 | E43: 4652 | F43: 4794 | G43: 5091 | H43: 5261 | I43: 5436 | J43: 5482 | K43: 5544 | L43: 5689 | M43: 5782 | N43: 5820 | O43: 5921
A44: =Dashboard!A56 -> TOTAL CONNECTIONS-SEWER
A45: =Dashboard!A57 -> 1 | B45: =Dashboard!B57 -> CBD- SEWER | C45: =Dashboard!C57 -> No. | D45: 421 | E45: 423 | F45: 423 | G45: 423 | H45: 427 | I45: 427 | J45: 427 | K45: 427 | L45: 429 | M45: 428 | N45: 428 | O45: 428
A46: =Dashboard!A58 -> 2 | B46: =Dashboard!B58 -> CCCR-SEWER | C46: =Dashboard!C58 -> No. | D46: 338 | E46: 339 | F46: 338 | G46: 339 | H46: 341 | I46: 341 | J46: 341 | K46: 340 | L46: 342 | M46: 351 | N46: 351 | O46: 351
A47: =Dashboard!A59 -> 3 | B47: =Dashboard!B59 -> KABATI-SEWER | C47: =Dashboard!C59 -> No. | D47: 293 | E47: 296 | F47: 296 | G47: 305 | H47: 309 | I47: 309 | J47: 310 | K47: 310 | L47: 312 | M47: 312 | N47: 313 | O47: 313
A48: =Dashboard!A60 -> 4 | B48: =Dashboard!B60 -> SITE- SEWER | C48: =Dashboard!C60 -> No. | D48: 510 | E48: 510 | F48: 509 | G48: 508 | H48: 510 | I48: 511 | J48: 511 | K48: 510 | L48: 510 | M48: 512 | N48: 512 | O48: 512
A49: =Dashboard!A61 -> 5 | B49: =Dashboard!B61 -> KIHOTO- SEWER | C49: =Dashboard!C61 -> No. | D49: 0 | E49: 0 | F49: 0 | G49: 0 | H49: 0 | I49: 0 | J49: 0 | K49: 0 | L49: 0 | M49: 0 | N49: 0 | O49: 0
A50: =Dashboard!A64 -> 0 | B50: =Dashboard!B64 -> TOTAL SEWER CONNECTION CENTRAL REGION | C50: =Dashboard!C64 -> No. | D50: 1562 | E50: 1568 | F50: 1566 | G50: 1575 | H50: 1587 | I50: 1588 | J50: 1589 | K50: 1587 | L50: 1593 | M50: 1603 | N50: 1604 | O50: 1604
A51: =Dashboard!A66 -> 1 | B51: =Dashboard!B66 -> HELLSGATE-SEWER | C51: =Dashboard!C66 -> No. | D51: 0 | E51: 0 | F51: 0 | G51: 0 | H51: 0 | I51: 0 | J51: 0 | K51: 0 | L51: 0 | M51: 0 | N51: 0 | O51: 0
A52: =Dashboard!A67 -> 2 | B52: =Dashboard!B67 -> KAMERE- SEWER | C52: =Dashboard!C67 -> No. | D52: 0 | E52: 0 | F52: 0 | G52: 0 | H52: 0 | I52: 0 | J52: 0 | K52: 0 | L52: 0 | M52: 0 | N52: 0 | O52: 0
A53: =Dashboard!A71 -> 1 | B53: =Dashboard!B71 -> KAYOLE-SEWER | C53: =Dashboard!C71 -> No. | D53: 0 | E53: 0 | F53: 0 | G53: 2 | H53: 2 | I53: 2 | J53: 2 | K53: 2 | L53: 65 | M53: 68 | N53: 68 | O53: 68
A54: =Dashboard!A62 -> 6 | B54: =Dashboard!B62 -> LAKEVIEW- SEWER | C54: =Dashboard!C62 -> No. | D54: 142 | E54: 144 | F54: 144 | G54: 148 | H54: 150 | I54: 149 | J54: 149 | K54: 150 | L54: 154 | M54: 151 | N54: 151 | O54: 151
A55: =Dashboard!A68 -> 3 | B55: =Dashboard!B68 -> MAI-MAHIU-SEWER | C55: =Dashboard!C68 -> No. | D55: 0 | E55: 0 | F55: 0 | G55: 0 | H55: 0 | I55: 0 | J55: 0 | K55: 0 | L55: 0 | M55: 0 | N55: 0 | O55: 0
A56: =Dashboard!A69 -> 0 | B56: =Dashboard!B69 -> TOTAL SEWER CONNECTION SOUTHERNREGION | C56: =Dashboard!C69 -> No. | D56: 142 | E56: 144 | F56: 144 | G56: 150 | H56: 152 | I56: 151 | J56: 151 | K56: 152 | L56: 219 | M56: 219 | N56: 219 | O56: 219
A57: =Dashboard!A72 -> TOTAL ACTIVE CONNECTIONS-WATER
A58: =Dashboard!A73 -> 1 | B58: =Dashboard!B73 -> CBD- ACTIVE WATER | C58: =Dashboard!C73 -> No. | D58: 560 | E58: 558 | F58: 556 | G58: 562 | H58: 568 | I58: 568 | J58: 569 | K58: 570 | L58: 574 | M58: 574 | N58: 575 | O58: 576
A59: =Dashboard!A74 -> 2 | B59: =Dashboard!B74 -> CCCR- ACTIVE WATER | C59: =Dashboard!C74 -> No. | D59: 490 | E59: 503 | F59: 506 | G59: 510 | H59: 517 | I59: 523 | J59: 526 | K59: 530 | L59: 534 | M59: 537 | N59: 540 | O59: 543
A60: =Dashboard!A75 -> 3 | B60: =Dashboard!B75 -> KABATI- ACTIVE WATER | C60: =Dashboard!C75 -> No. | D60: 689 | E60: 701 | F60: 704 | G60: 703 | H60: 708 | I60: 714 | J60: 732 | K60: 741 | L60: 743 | M60: 750 | N60: 754 | O60: 758
A61: =Dashboard!A76 -> 4 | B61: =Dashboard!B76 -> SITE- ACTIVE WATER | C61: =Dashboard!C76 -> No. | D61: 729 | E61: 736 | F61: 745 | G61: 753 | H61: 757 | I61: 759 | J61: 771 | K61: 775 | L61: 777 | M61: 782 | N61: 784 | O61: 786
A62: =Dashboard!A77 -> 5 | B62: =Dashboard!B77 -> KIHOTO-ACTIVE WATER | C62: =Dashboard!C77 -> No. | D62: 126 | E62: 127 | F62: 128 | G62: 131 | H62: 131 | I62: 132 | J62: 134 | K62: 135 | L62: 135 | M62: 140 | N62: 143 | O62: 143
A63: =Dashboard!A80 -> 0 | B63: =Dashboard!B80 -> TOTAL ACTIVE WATER CONNECTION CENTRAL REGION | C63: =Dashboard!C80 -> No. | D63: 2594 | E63: 2625 | F63: 2639 | G63: 2659 | H63: 2681 | I63: 2696 | J63: 2732 | K63: 2751 | L63: 2763 | M63: 2783 | N63: 2796 | O63: 2806
A64: =Dashboard!A81 -> 1 | B64: =Dashboard!B81 -> HELLSGATE- ACTIVE WATER | C64: =Dashboard!C81 -> No. | D64: 811 | E64: 842 | F64: 876 | G64: 930 | H64: 967 | I64: 995 | J64: 1027 | K64: 1065 | L64: 1088 | M64: 1137 | N64: 1146 | O64: 1158
A65: =Dashboard!A82 -> 2 | B65: =Dashboard!B82 -> KAMERE- ACTIVE WATER | C65: =Dashboard!C82 -> No. | D65: 228 | E65: 230 | F65: 231 | G65: 231 | H65: 231 | I65: 231 | J65: 231 | K65: 232 | L65: 233 | M65: 234 | N65: 236 | O65: 236
A66: =Dashboard!A87 -> 1 | B66: =Dashboard!B87 -> KAYOLE- ACTIVE WATER | C66: =Dashboard!C87 -> No. | D66: 1743 | E66: 1761 | F66: 1780 | G66: 1798 | H66: 1825 | I66: 1841 | J66: 1866 | K66: 1882 | L66: 1944 | M66: 1990 | N66: 2001 | O66: 2028
A67: =Dashboard!A78 -> 6 | B67: =Dashboard!B78 -> LAKEVIEW- ACTIVE WATER | C67: =Dashboard!C78 -> No. | D67: 969 | E67: 978 | F67: 957 | G67: 964 | H67: 981 | I67: 991 | J67: 998 | K67: 1007 | L67: 1040 | M67: 1066 | N67: 1068 | O67: 1069
A68: =Dashboard!A83 -> 3 | B68: =Dashboard!B83 -> MAI-MAHIU- ACTIVE WATER | C68: =Dashboard!C83 -> No. | D68: 72 | E68: 76 | F68: 94 | G68: 101 | H68: 130 | I68: 154 | J68: 178 | K68: 188 | L68: 197 | M68: 231 | N68: 235 | O68: 242
A69: =Dashboard!A85 -> 0 | B69: =Dashboard!B85 -> TOTAL ACTIVE WATER CONNECTION SOUTHERN REGION | C69: =Dashboard!C85 -> No. | D69: 3823 | E69: 3887 | F69: 3938 | G69: 4024 | H69: 4134 | I69: 4212 | J69: 4300 | K69: 4374 | L69: 4502 | M69: 4658 | N69: 4686 | O69: 4733
A70: =Dashboard!A90 -> TOTAL ACTIVE CONNECTIONS-SEWER
A71: =Dashboard!A91 -> 1 | B71: =Dashboard!B91 -> CBD- ACTIVE SEWER | C71: =Dashboard!C91 -> No. | D71: 372 | E71: 373 | F71: 373 | G71: 373 | H71: 375 | I71: 375 | J71: 375 | K71: 375 | L71: 374 | M71: 374 | N71: 374 | O71: 373
A72: =Dashboard!A92 -> 2 | B72: =Dashboard!B92 -> CCCR- ACTIVE SEWER | C72: =Dashboard!C92 -> No. | D72: 297 | E72: 300 | F72: 297 | G72: 300 | H72: 300 | I72: 301 | J72: 301 | K72: 299 | L72: 301 | M72: 310 | N72: 310 | O72: 311
A73: =Dashboard!A93 -> 3 | B73: =Dashboard!B93 -> KABATI- ACTIVE SEWER | C73: =Dashboard!C93 -> No. | D73: 270 | E73: 274 | F73: 275 | G73: 283 | H73: 284 | I73: 285 | J73: 288 | K73: 289 | L73: 291 | M73: 291 | N73: 292 | O73: 292
A74: =Dashboard!A94 -> 4 | B74: =Dashboard!B94 -> SITE- ACTIVE SEWER | C74: =Dashboard!C94 -> No. | D74: 451 | E74: 453 | F74: 452 | G74: 450 | H74: 453 | I74: 452 | J74: 453 | K74: 452 | L74: 452 | M74: 454 | N74: 454 | O74: 453
A75: =Dashboard!A95 -> 5 | B75: =Dashboard!B95 -> KIHOTO- ACTIVE SEWER | C75: =Dashboard!C95 -> No. | D75: 0 | E75: 0 | F75: 0 | G75: 0 | H75: 0 | I75: 0 | J75: 0 | K75: 0 | L75: 0 | M75: 0 | N75: 0 | O75: 0
A76: =Dashboard!A98 -> 0 | B76: =Dashboard!B98 -> TOTAL ACTIVE SEWER CONNECTION CENTRAL REGION | C76: =Dashboard!C98 -> No. | D76: 1390 | E76: 1400 | F76: 1397 | G76: 1406 | H76: 1412 | I76: 1413 | J76: 1417 | K76: 1415 | L76: 1418 | M76: 1429 | N76: 1430 | O76: 1429
A77: =Dashboard!A99 -> 1 | B77: =Dashboard!B99 -> HELLSGATE- ACTIVE SEWER | C77: =Dashboard!C99 -> No. | D77: 0 | E77: 0 | F77: 0 | G77: 0 | H77: 0 | I77: 0 | J77: 0 | K77: 0 | L77: 0 | M77: 0 | N77: 0 | O77: 0
A78: =Dashboard!A100 -> 2 | B78: =Dashboard!B100 -> KAMERE- ACTIVE SEWER | C78: =Dashboard!C100 -> No. | D78: 0 | E78: 0 | F78: 0 | G78: 0 | H78: 0 | I78: 0 | J78: 0 | K78: 0 | L78: 0 | M78: 0 | N78: 0 | O78: 0
A79: =Dashboard!A104 -> 1 | B79: =Dashboard!B104 -> KAYOLE- ACTIVE SEWER | C79: =Dashboard!C104 -> No. | D79: 0 | E79: 0 | F79: 0 | G79: 1 | H79: 1 | I79: 1 | J79: 1 | K79: 1 | L79: 47 | M79: 68 | N79: 68 | O79: 68
A80: =Dashboard!A96 -> 6 | B80: =Dashboard!B96 -> LAKEVIEW- ACTIVE SEWER | C80: =Dashboard!C96 -> No. | D80: 113 | E80: 116 | F80: 114 | G80: 118 | H80: 122 | I80: 122 | J80: 121 | K80: 123 | L80: 125 | M80: 124 | N80: 124 | O80: 124
A81: =Dashboard!A101 -> 3 | B81: =Dashboard!B101 -> MAI-MAHIU- ACTIVE SEWER | C81: =Dashboard!C101 -> No. | D81: 0 | E81: 0 | F81: 0 | G81: 0 | H81: 0 | I81: 0 | J81: 0 | K81: 0 | L81: 0 | M81: 0 | N81: 0 | O81: 0
A82: =Dashboard!A102 -> 0 | B82: =Dashboard!B102 -> TOTAL ACTIVE SEWER CONNECTION SOUTHERN REGION | C82: =Dashboard!C102 -> No. | D82: 113 | E82: 116 | F82: 114 | G82: 119 | H82: 123 | I82: 123 | J82: 122 | K82: 124 | L82: 172 | M82: 192 | N82: 192 | O82: 192
A83: =Dashboard!A105 -> SUMMARY CONNECTIONS
A84: =Dashboard!A106 -> 1 | B84: =Dashboard!B106 -> TOTAL WATER CONNECTIONS | C84: =Dashboard!C106 -> No. | D84: 7757 | E84: 7866 | F84: 8031 | G84: 8345 | H84: 8532 | I84: 8767 | J84: 8818 | K84: 8917 | L84: 9078 | M84: 9152 | N84: 9204 | O84: 9317
A85: =Dashboard!A107 -> 2 | B85: =Dashboard!B107 -> TOTAL SEWER CONNECTIONS | C85: =Dashboard!C107 -> No. | D85: 1704 | E85: 1712 | F85: 1710 | G85: 1725 | H85: 1739 | I85: 1739 | J85: 1740 | K85: 1739 | L85: 1812 | M85: 1822 | N85: 1823 | O85: 1823
A86: =Dashboard!A108 -> 3 | B86: =Dashboard!B108 -> TOTAL ACTIVE WATER CONNECTIONS | C86: =Dashboard!C108 -> No. | D86: 6417 | E86: 6512 | F86: 6577 | G86: 6683 | H86: 6815 | I86: 6908 | J86: 7032 | K86: 7125 | L86: 7265 | M86: 7441 | N86: 7482 | O86: 7539
A87: =Dashboard!A109 -> 4 | B87: =Dashboard!B109 -> TOTAL SEWER ACTIVE CONNECTIONS | C87: =Dashboard!C109 -> No. | D87: 1503 | E87: 1516 | F87: 1511 | G87: 1525 | H87: 1535 | I87: 1536 | J87: 1539 | K87: 1539 | L87: 1590 | M87: 1621 | N87: 1622 | O87: 1621
A88: =Dashboard!A112 -> 5 | B88: =Dashboard!B112 -> % ACTIVE CONNECTIONS | C88: =Dashboard!C112 -> No. | D88: 0.83712081 | E88: 0.83817081 | F88: 0.8303049 | G88: 0.81509434 | H88: 0.81296855 | I88: 0.8037312 | J88: 0.81180148 | K88: 0.81306306 | L88: 0.81313131 | M88: 0.82577 | N88: 0.82560987 | O88: 0.82226212
A89: =Dashboard!A113 -> TOTAL BILLING IN M3 - WATER
A90: =Dashboard!A114 -> 1 | B90: =Dashboard!B114 -> CBD - WATER(M3) | C90: =Dashboard!C114 -> M3 | D90: 14570 | E90: 12703 | F90: 14042 | G90: 14935 | H90: 13880 | I90: 13632 | J90: 12993 | K90: 16261 | L90: 13989 | M90: 15297 | N90: 13743 | O90: 15808
A91: =Dashboard!A115 -> 2 | B91: =Dashboard!B115 -> CCCR - WATER(M3) | C91: =Dashboard!C115 -> M3 | D91: 21194 | E91: 20639 | F91: 23153 | G91: 22430 | H91: 26502 | I91: 28276 | J91: 27957 | K91: 30971 | L91: 26244 | M91: 25791 | N91: 21206 | O91: 14455
A92: =Dashboard!A116 -> 3 | B92: =Dashboard!B116 -> KABATI - WATER(M3) | C92: =Dashboard!C116 -> M3 | D92: 11902 | E92: 11649 | F92: 11670 | G92: 11430 | H92: 11627 | I92: 9817 | J92: 11168 | K92: 11595 | L92: 9144 | M92: 11551 | N92: 11007 | O92: 12306
A93: =Dashboard!A117 -> 4 | B93: =Dashboard!B117 -> SITE - WATER(M3) | C93: =Dashboard!C117 -> M3 | D93: 10380 | E93: 10384 | F93: 9824 | G93: 9575 | H93: 9820 | I93: 8786 | J93: 10525 | K93: 10497 | L93: 10543 | M93: 9624 | N93: 10549 | O93: 10453
A94: =Dashboard!A118 -> 5 | B94: =Dashboard!B118 -> KIHOTO - WATER(M3) | C94: =Dashboard!C118 -> M3 | D94: 1694 | E94: 1250 | F94: 1780 | G94: 1549 | H94: 1676 | I94: 1491 | J94: 1848 | K94: 1558 | L94: 1422 | M94: 1627 | N94: 1047 | O94: 1497
A95: =Dashboard!A121 -> 0 | B95: =Dashboard!B121 -> TOTAL - WATER(M3) CENTRAL REGION | C95: =Dashboard!C121 -> M3 | D95: 59740 | E95: 56625 | F95: 60469 | G95: 59919 | H95: 63505 | I95: 62002 | J95: 64491 | K95: 70882 | L95: 61342 | M95: 63890 | N95: 57552 | O95: 54519
A96: =Dashboard!A122 -> 1 | B96: =Dashboard!B122 -> HELLSGATE - WATER(M3) | C96: =Dashboard!C122 -> M3 | D96: 15499 | E96: 15491 | F96: 15957 | G96: 17272 | H96: 16979 | I96: 16972 | J96: 20812 | K96: 18533 | L96: 17119 | M96: 23651 | N96: 16398 | O96: 17921
A97: =Dashboard!A123 -> 2 | B97: =Dashboard!B123 -> KAMERE - WATER(M3) | C97: =Dashboard!C123 -> M3 | D97: 3826 | E97: 5784 | F97: 5973 | G97: 6283 | H97: 6051 | I97: 5901 | J97: 6534 | K97: 6121 | L97: 4679 | M97: 6665 | N97: 5651 | O97: 5352
A98: =Dashboard!A128 -> 1 | B98: =Dashboard!B128 -> KAYOLE - WATER(M3) | C98: =Dashboard!C128 -> M3 | D98: 19638 | E98: 18845 | F98: 16366 | G98: 20028 | H98: 17507 | I98: 17716 | J98: 20471 | K98: 18921 | L98: 18590 | M98: 23996 | N98: 18450 | O98: 17776
A99: =Dashboard!A119 -> 6 | B99: =Dashboard!B119 -> LAKEVIEW - WATER(M3) | C99: =Dashboard!C119 -> M3 | D99: 21080 | E99: 23926 | F99: 22037 | G99: 21522 | H99: 19960 | I99: 18923 | J99: 22230 | K99: 21621 | L99: 18992 | M99: 23353 | N99: 18377 | O99: 19259
A100: =Dashboard!A124 -> 3 | B100: =Dashboard!B124 -> MAI-MAHIU - WATER(M3) | C100: =Dashboard!C124 -> M3 | D100: 483 | E100: 757 | F100: 1812 | G100: 1248 | H100: 1499 | I100: 1237 | J100: 2594 | K100: 1783 | L100: 1985 | M100: 3030 | N100: 1560 | O100: 1997
A101: =Dashboard!A126 -> 0 | B101: =Dashboard!B126 -> TOTAL WATER(M3) SOUTHERN REGION | C101: =Dashboard!C126 -> M3 | D101: 60526 | E101: 64803 | F101: 62145 | G101: 66353 | H101: 61996 | I101: 60749 | J101: 72641 | K101: 66979 | L101: 61365 | M101: 80695 | N101: 60436 | O101: 62305
...

Sheet KPI 1
A1: KPI | B1: =Dashboard!A6 -> 1 | C1: =Dashboard!B6 -> CBD - NEW WATER | G1: Actual month: | I1: =INDEX($E$18:$P$18,Actual_month) -> 46054 | L1: Dashboard
A2: Unit | C2: Ksh.
C3: l | J3: Comments
C4: l | R4: actual | S4: =INDEX(E27:P27,Actual_month) -> 2
C5: l | R5: target | S5: =INDEX(E26:P26,Actual_month) -> 8
R6: 0.9 | S6: =+S5*R6 -> 7.2
J9: Actions
C18: MONTHLY | E18: 45839 | F18: 45870 | G18: 45901 | H18: 45931 | I18: 45962 | J18: 45992 | K18: 46023 | L18: 46054 | M18: 46082 | N18: 46113 | O18: 46143 | P18: 46174 | Q18: Total
D19: Budget 2025-26 | E19: ='budget 2025-26'!D6 -> 1 | F19: ='budget 2025-26'!E6 -> 1 | G19: ='budget 2025-26'!F6 -> 1 | H19: ='budget 2025-26'!G6 -> 1 | I19: ='budget 2025-26'!H6 -> 1 | J19: ='budget 2025-26'!I6 -> 1 | K19: ='budget 2025-26'!J6 -> 1 | L19: ='budget 2025-26'!K6 -> 1 | ... P19: ='budget 2025-26'!O6 -> 1 | Q19: =SUM(E19:P19) -> 12
D20: Actual 2025-26 | E20: ='Input Actual2025-26'!E6 -> 0 | F20: ='Input Actual2025-26'!F6 -> 0 | G20: ='Input Actual2025-26'!G6 -> 0 | H20: ='Input Actual2025-26'!H6 -> 1 | I20: ='Input Actual2025-26'!I6 -> 0 | J20: ='Input Actual2025-26'!J6 -> 0 | K20: ='Input Actual2025-26'!K6 -> 1 | L20: ='Input Actual2025-26'!L6 -> 0 | ... P20: ='Input Actual2025-26'!P6 -> 0 | Q20: =SUM(E20:P20) -> 2
D21: Actual 2024-25 | E21: ='Input Actual2024-25'!E6 -> 1 | F21: ='Input Actual2024-25'!F6 -> 1 | G21: ='Input Actual2024-25'!G6 -> 2 | H21: ='Input Actual2024-25'!H6 -> 0 | I21: ='Input Actual2024-25'!I6 -> 0 | J21: ='Input Actual2024-25'!J6 -> 0 | K21: ='Input Actual2024-25'!K6 -> 0 | L21: ='Input Actual2024-25'!L6 -> 0 | ... Q21: ='Input Actual2024-25'!Q6 -> 0
D22: Difference | E22: =IF(E20=0,0,E20-E19) -> 0 | F22: =IF(F20=0,0,F20-F19) -> 0 | G22: =IF(G20=0,0,G20-G19) -> 0 | H22: =IF(H20=0,0,H20-H19) -> 0 | I22: =IF(I20=0,0,I20-I19) -> 0 | J22: =IF(J20=0,0,J20-J19) -> 0 | K22: =IF(K20=0,0,K20-K19) -> 0 | L22: =IF(L20=0,0,L20-L19) -> 0 | ... P22: =IF(P20=0,0,P20-P19) -> 0 | Q22: =SUM(E22:P22) -> 0
D23: Realisation | E23: =E21/E19 -> 1 | F23: =F20/F19 -> 0 | G23: =G20/G19 -> 0 | H23: =H20/H19 -> 1 | I23: =I20/I19 -> 0 | J23: =J20/J19 -> 0 | K23: =K20/K19 -> 1 | L23: =L20/L19 -> 0 | M23: =M20/M19 -> 0 | ... P23: =P20/P19 -> 0
C25: CUMULATIVE | E25: =E18 -> 45839 | F25: =F18 -> 45870 | G25: =G18 -> 45901 | H25: =H18 -> 45931 | I25: =I18 -> 45962 | J25: =J18 -> 45992 | K25: =K18 -> 46023 | L25: =L18 -> 46054 | ... P25: =P18 -> 46174
D26: =D19 -> Budget 2025-26 | E26: =SUM($E19:E19) -> 1 | F26: =SUM($E19:F19) -> 2 | G26: =SUM($E19:G19) -> 3 | H26: =SUM($E19:H19) -> 4 | I26: =SUM($E19:I19) -> 5 | J26: =SUM($E19:J19) -> 6 | K26: =SUM($E19:K19) -> 7 | L26: =SUM($E19:L19) -> 8 | ... P26: =SUM($E19:P19) -> 12
D27: =D20 -> Actual 2025-26 | E27: =SUM($E20:E20) -> 0 | F27: =SUM($E20:F20) -> 0 | G27: =SUM($E20:G20) -> 0 | H27: =SUM($E20:H20) -> 1 | I27: =SUM($E20:I20) -> 1 | J27: =SUM($E20:J20) -> 1 | K27: =SUM($E20:K20) -> 2 | L27: =SUM($E20:L20) -> 2 | ... P27: =SUM($E20:P20) -> 2
D28: =D21 -> Actual 2024-25 | E28: =SUM($E21:E21) -> 1 | F28: =SUM($E21:F21) -> 2 | G28: =SUM($E21:G21) -> 4 | H28: =SUM($E21:H21) -> 4 | I28: =SUM($E21:I21) -> 4 | J28: =SUM($E21:J21) -> 4 | K28: =SUM($E21:K21) -> 4 | L28: =SUM($E21:L21) -> 4 | ... P28: =SUM($E21:P21) -> 9
D29: =D22 -> Difference | E29: =SUM($E22:E22) -> 0 | F29: =SUM($E22:F22) -> 0 | G29: =SUM($E22:G22) -> 0 | H29: =SUM($E22:H22) -> 0 | I29: =SUM($E22:I22) -> 0 | J29: =SUM($E22:J22) -> 0 | K29: =SUM($E22:K22) -> 0 | L29: =SUM($E22:L22) -> 0 | ... P29: =SUM($E22:P22) -> 0
D30: =D23 -> Realisation | E30: =E28/E26 -> 1 | F30: =F27/F26 -> 0 | G30: =G27/G26 -> 0 | H30: =H27/H26 -> 0.25 | I30: =I27/I26 -> 0.2 | J30: =J27/J26 -> 0.16666667 | K30: =K27/K26 -> 0.28571429 | L30: =L27/L26 -> 0.25 | M30: =M27/M26 -> 0.22222222 | ... P30: =P27/P26 -> 0.16666667

Sheet KPI 2
A1: KPI | B1: =Dashboard!A7 -> 2 | C1: =Dashboard!B7 -> CCCR- NEW WATER | G1: Actual month: | I1: =INDEX($E$18:$P$18,Actual_month) -> 46054 | L1: Dashboard
A2: Unit | C2: Ksh.
C3: l | J3: Comments
C4: l | R4: actual | S4: =INDEX(E27:P27,Actual_month) -> 20
C5: l | R5: target | S5: =INDEX(E26:P26,Actual_month) -> 79
R6: 0.9 | S6: =+S5*R6 -> 71.1
J9: Actions
C18: MONTHLY | E18: ='KPI 1'!E18 -> 45839 | F18: ='KPI 1'!F18 -> 45870 | G18: ='KPI 1'!G18 -> 45901 | H18: ='KPI 1'!H18 -> 45931 | I18: ='KPI 1'!I18 -> 45962 | J18: ='KPI 1'!J18 -> 45992 | K18: ='KPI 1'!K18 -> 46023 | L18: ='KPI 1'!L18 -> 46054 | ... P18: ='KPI 1'!P18 -> 46174 | Q18: Total
D19: ='KPI 1'!D19 -> Budget 2025-26 | E19: ='budget 2025-26'!D7 -> 9 | F19: ='budget 2025-26'!E7 -> 10 | G19: ='budget 2025-26'!F7 -> 10 | H19: ='budget 2025-26'!G7 -> 10 | I19: ='budget 2025-26'!H7 -> 10 | J19: ='budget 2025-26'!I7 -> 10 | K19: ='budget 2025-26'!J7 -> 10 | L19: ='budget 2025-26'!K7 -> 10 | ... P19: ='budget 2025-26'!O7 -> 10 | Q19: =SUM(E19:P19) -> 119
D20: ='KPI 1'!D20 -> Actual 2025-26 | E20: ='Input Actual2025-26'!E7 -> 0 | F20: ='Input Actual2025-26'!F7 -> 3 | G20: ='Input Actual2025-26'!G7 -> 2 | H20: ='Input Actual2025-26'!H7 -> 2 | I20: ='Input Actual2025-26'!I7 -> 3 | J20: ='Input Actual2025-26'!J7 -> 2 | K20: ='Input Actual2025-26'!K7 -> 5 | L20: ='Input Actual2025-26'!L7 -> 3 | ... P20: ='Input Actual2025-26'!P7 -> 0 | Q20: =SUM(E20:P20) -> 20
D21: Actual 2024-25 | E21: ='Input Actual2024-25'!E7 -> 6 | F21: ='Input Actual2024-25'!F7 -> 1 | G21: ='Input Actual2024-25'!G7 -> 3 | H21: ='Input Actual2024-25'!H7 -> 0 | I21: ='Input Actual2024-25'!I7 -> 0 | J21: ='Input Actual2024-25'!J7 -> 0 | K21: ='Input Actual2024-25'!K7 -> 7 | L21: ='Input Actual2024-25'!L7 -> 2 | ... P21: ='Input Actual2024-25'!P7 -> 4 | Q21: =SUM(E21:P21) -> 29
D22: Difference | E22: =IF(E20=0,0,E20-E19) -> 0 | F22: =IF(F20=0,0,F20-F19) -> -7 | G22: =IF(G20=0,0,G20-G19) -> -8 | H22: =IF(H20=0,0,H20-H19) -> -8 | I22: =IF(I20=0,0,I20-I19) -> -7 | J22: =IF(J20=0,0,J20-J19) -> -8 | K22: =IF(K20=0,0,K20-K19) -> -5 | L22: =IF(L20=0,0,L20-L19) -> -7 | ... P22: =IF(P20=0,0,P20-P19) -> 0 | Q22: =SUM(E22:P22) -> -50
D23: Realisation | E23: =E21/E19 -> 0.66666667 | F23: =F20/F19 -> 0.3 | G23: =G20/G19 -> 0.2 | H23: =H20/H19 -> 0.2 | I23: =I20/I19 -> 0.3 | J23: =J20/J19 -> 0.2 | K23: =K20/K19 -> 0.5 | L23: =L20/L19 -> 0.3 | M23: =M20/M19 -> 0 | ... P23: =P20/P19 -> 0
C25: CUMULATIVE | E25: =E18 -> 45839 | F25: =F18 -> 45870 | G25: =G18 -> 45901 | H25: =H18 -> 45931 | I25: =I18 -> 45962 | J25: =J18 -> 45992 | K25: =K18 -> 46023 | L25: =L18 -> 46054 | ... P25: =P18 -> 46174
D26: =D19 -> Budget 2025-26 | E26: =SUM($E19:E19) -> 9 | F26: =SUM($E19:F19) -> 19 | G26: =SUM($E19:G19) -> 29 | H26: =SUM($E19:H19) -> 39 | I26: =SUM($E19:I19) -> 49 | J26: =SUM($E19:J19) -> 59 | K26: =SUM($E19:K19) -> 69 | L26: =SUM($E19:L19) -> 79 | ... P26: =SUM($E19:P19) -> 119
D27: =D20 -> Actual 2025-26 | E27: =SUM($E20:E20) -> 0 | F27: =SUM($E20:F20) -> 3 | G27: =SUM($E20:G20) -> 5 | H27: =SUM($E20:H20) -> 7 | I27: =SUM($E20:I20) -> 10 | J27: =SUM($E20:J20) -> 12 | K27: =SUM($E20:K20) -> 17 | L27: =SUM($E20:L20) -> 20 | ... P27: =SUM($E20:P20) -> 20
D28: =D21 -> Actual 2024-25 | E28: =SUM($E21:E21) -> 6 | F28: =SUM($E21:F21) -> 7 | G28: =SUM($E21:G21) -> 10 | H28: =SUM($E21:H21) -> 10 | I28: =SUM($E21:I21) -> 10 | J28: =SUM($E21:J21) -> 10 | K28: =SUM($E21:K21) -> 17 | L28: =SUM($E21:L21) -> 19 | ... P28: =SUM($E21:P21) -> 29
D29: =D22 -> Difference | E29: =SUM($E22:E22) -> 0 | F29: =SUM($E22:F22) -> -7 | G29: =SUM($E22:G22) -> -15 | H29: =SUM($E22:H22) -> -23 | I29: =SUM($E22:I22) -> -30 | J29: =SUM($E22:J22) -> -38 | K29: =SUM($E22:K22) -> -43 | L29: =SUM($E22:L22) -> -50 | ... P29: =SUM($E22:P22) -> -50
D30: =D23 -> Realisation | E30: =E28/E26 -> 0.66666667 | F30: =F27/F26 -> 0.15789474 | G30: =G27/G26 -> 0.17241379 | H30: =H27/H26 -> 0.17948718 | I30: =I27/I26 -> 0.20408163 | J30: =J27/J26 -> 0.20338983 | K30: =K27/K26 -> 0.24637681 | L30: =L27/L26 -> 0.25316456 | M30: =M27/M26 -> 0.2247191 | ... P30: =P27/P26 -> 0.16806723

Sheet KPI 3A
A1: KPI | B1: =Dashboard!A8 -> 3 | C1: =Dashboard!B186 -> TOTAL WATER & SEWER SALES | G1: Actual month: | I1: =INDEX($E$18:$P$18,Actual_month) -> 46054 | L1: Dashboard
A2: Unit | C2: Ksh.
C3: l | J3: Comments
C4: l | R4: actual | S4: =INDEX(E27:P27,Actual_month) -> 2.0779297e+08
C5: l | R5: target | S5: =INDEX(E26:P26,Actual_month) -> 1.8343922e+08
R6: 0.9 | S6: =+S5*R6 -> 1.650953e+08
J9: Actions
C18: MONTHLY | E18: 45839 | F18: 45870 | G18: 45901 | H18: 45931 | I18: 45962 | J18: 45992 | K18: 46023 | L18: 46054 | M18: 46082 | N18: 46113 | O18: 46143 | P18: 46174 | Q18: Total
D19: Budget 2025-26 | E19: ='budget 2025-26'!D175 -> 22014752 | F19: ='budget 2025-26'!E175 -> 22256147 | G19: ='budget 2025-26'!F175 -> 22500783 | H19: ='budget 2025-26'!G175 -> 22794018 | I19: ='budget 2025-26'!H175 -> 23071053 | J19: ='budget 2025-26'!I175 -> 23331889 | K19: ='budget 2025-26'!J175 -> 23608924 | L19: ='budget 2025-26'!K175 -> 23861659 | ... P19: ='budget 2025-26'!O175 -> 24723561 | Q19: =SUM(E19:P19) -> 2.8106977e+08
D20: Actual 2025-26 | E20: ='Input Actual2025-26'!E178 -> 24092391 | F20: ='Input Actual2025-26'!F178 -> 28116426 | G20: ='Input Actual2025-26'!G178 -> 24118066 | H20: ='Input Actual2025-26'!H178 -> 27515501 | I20: ='Input Actual2025-26'!I178 -> 22379914 | J20: ='Input Actual2025-26'!J178 -> 21346714 | K20: ='Input Actual2025-26'!K178 -> 32566214 | L20: ='Input Actual2025-26'!L178 -> 27657741 | ... P20: ='Input Actual2025-26'!P178 -> 0 | Q20: =SUM(E20:P20) -> 2.0779297e+08
D21: Actual 2024-25 | E21: ='Input Actual2024-25'!E165 -> 15292420 | F21: ='Input Actual2024-25'!F165 -> 18966349 | G21: ='Input Actual2024-25'!G165 -> 17301727 | H21: ='Input Actual2024-25'!H165 -> 17045652 | I21: ='Input Actual2024-25'!I165 -> 18658038 | J21: ='Input Actual2024-25'!J165 -> 12741782 | K21: ='Input Actual2024-25'!K165 -> 20192574 | L21: ='Input Actual2024-25'!L165 -> 17727809 | ... P21: ='Input Actual2024-25'!P165 -> 27123524 | Q21: =SUM(E21:P21) -> 2.2928061e+08
D22: Difference | E22: =IF(E20=0,0,E20-E19) -> 2077639.1 | F22: =IF(F20=0,0,F20-F19) -> 5860278.8 | G22: =IF(G20=0,0,G20-G19) -> 1617283.5 | H22: =IF(H20=0,0,H20-H19) -> 4721483.1 | I22: =IF(I20=0,0,I20-I19) -> -691139.7 | J22: =IF(J20=0,0,J20-J19) -> -1985174.7 | K22: =IF(K20=0,0,K20-K19) -> 8957289.6 | L22: =IF(L20=0,0,L20-L19) -> 3796081.8 | ... P22: =IF(P20=0,0,P20-P19) -> 0 | Q22: =SUM(E22:P22) -> 24353742
D23: Realisation | E23: =E21/E19 -> 0.69464423 | F23: =F20/F19 -> 1.2633106 | G23: =G20/G19 -> 1.0718768 | H23: =H20/H19 -> 1.2071369 | I23: =I20/I19 -> 0.97004299 | J23: =J20/J19 -> 0.91491581 | K23: =K20/K19 -> 1.3794027 | L23: =L20/L19 -> 1.1590871 | M23: =M20/M19 -> 0 | ... P23: =P20/P19 -> 0
C25: CUMULATIVE | E25: =E18 -> 45839 | F25: =F18 -> 45870 | G25: =G18 -> 45901 | H25: =H18 -> 45931 | I25: =I18 -> 45962 | J25: =J18 -> 45992 | K25: =K18 -> 46023 | L25: =L18 -> 46054 | ... P25: =P18 -> 46174
D26: =D19 -> Budget 2025-26 | E26: =SUM($E19:E19) -> 22014752 | F26: =SUM($E19:F19) -> 44270899 | G26: =SUM($E19:G19) -> 66771682 | H26: =SUM($E19:H19) -> 89565699 | I26: =SUM($E19:I19) -> 1.1263675e+08 | J26: =SUM($E19:J19) -> 1.3596864e+08 | K26: =SUM($E19:K19) -> 1.5957757e+08 | L26: =SUM($E19:L19) -> 1.8343922e+08 | ... P26: =SUM($E19:P19) -> 2.8106977e+08
D27: =D20 -> Actual 2025-26 | E27: =SUM($E20:E20) -> 24092391 | F27: =SUM($E20:F20) -> 52208817 | G27: =SUM($E20:G20) -> 76326883 | H27: =SUM($E20:H20) -> 103842384 | I27: =SUM($E20:I20) -> 1.262223e+08 | J27: =SUM($E20:J20) -> 1.4756901e+08 | K27: =SUM($E20:K20) -> 1.8013522e+08 | L27: =SUM($E20:L20) -> 2.0779297e+08 | ... P27: =SUM($E20:P20) -> 2.0779297e+08
D28: =D21 -> Actual 2024-25 | E28: =SUM($E21:E21) -> 15292420 | F28: =SUM($E21:F21) -> 34258770 | G28: =SUM($E21:G21) -> 51560496 | H28: =SUM($E21:H21) -> 68606148 | I28: =SUM($E21:I21) -> 87264185 | J28: =SUM($E21:J21) -> 1.0000597e+08 | K28: =SUM($E21:K21) -> 1.2019854e+08 | L28: =SUM($E21:L21) -> 1.3792635e+08 | ... P28: =SUM($E21:P21) -> 2.2928061e+08
D29: =D22 -> Difference | E29: =SUM($E22:E22) -> 2077639.1 | F29: =SUM($E22:F22) -> 7937917.9 | G29: =SUM($E22:G22) -> 9555201.4 | H29: =SUM($E22:H22) -> 14276685 | I29: =SUM($E22:I22) -> 13585545 | J29: =SUM($E22:J22) -> 11600370 | K29: =SUM($E22:K22) -> 20557660 | L29: =SUM($E22:L22) -> 24353742 | ... P29: =SUM($E22:P22) -> 24353742
D30: =D23 -> Realisation | E30: =E28/E26 -> 0.69464423 | F30: =F27/F26 -> 1.1793033 | G30: =G27/G26 -> 1.1431026 | H30: =H27/H26 -> 1.159399 | I30: =I27/I26 -> 1.1206138 | J30: =J27/J26 -> 1.0853165 | K30: =K27/K26 -> 1.1288255 | L30: =L27/L26 -> 1.1327619 | M30: =M27/M26 -> 1.0012704 | ... P30: =P27/P26 -> 0.73929317

Sheet KPI 3
A1: KPI | B1: =Dashboard!A8 -> 3 | C1: =Dashboard!B8 -> KABATI- NEW WATER | G1: Actual month: | I1: =INDEX($E$18:$P$18,Actual_month) -> 46054 | L1: Dashboard
A2: Unit | C2: Ksh.
C3: l | J3: Comments
C4: l | R4: actual | S4: =INDEX(E27:P27,Actual_month) -> 10
C5: l | R5: target | S5: =INDEX(E26:P26,Actual_month) -> 32
R6: 0.9 | S6: =+S5*R6 -> 28.8
J9: Actions
C18: MONTHLY | E18: 45839 | F18: 45870 | G18: 45901 | H18: 45931 | I18: 45962 | J18: 45992 | K18: 46023 | L18: 46054 | M18: 46082 | N18: 46113 | O18: 46143 | P18: 46174 | Q18: Total
D19: Budget 2025-26 | E19: ='budget 2025-26'!D8 -> 4 | F19: ='budget 2025-26'!E8 -> 4 | G19: ='budget 2025-26'!F8 -> 4 | H19: ='budget 2025-26'!G8 -> 4 | I19: ='budget 2025-26'!H8 -> 4 | J19: ='budget 2025-26'!I8 -> 4 | K19: ='budget 2025-26'!J8 -> 4 | L19: ='budget 2025-26'!K8 -> 4 | ... P19: ='budget 2025-26'!O8 -> 4 | Q19: =SUM(E19:P19) -> 48
D20: Actual 2025-26 | E20: ='Input Actual2025-26'!E8 -> 0 | F20: ='Input Actual2025-26'!F8 -> 0 | G20: ='Input Actual2025-26'!G8 -> 5 | H20: ='Input Actual2025-26'!H8 -> 1 | I20: ='Input Actual2025-26'!I8 -> 2 | J20: ='Input Actual2025-26'!J8 -> 0 | K20: ='Input Actual2025-26'!K8 -> 2 | L20: ='Input Actual2025-26'!L8 -> 0 | ... P20: ='Input Actual2025-26'!P8 -> 0 | Q20: =SUM(E20:P20) -> 10
D21: Actual 2024-25 | E21: ='Input Actual2024-25'!E8 -> 1 | F21: ='Input Actual2024-25'!F8 -> 4 | G21: ='Input Actual2024-25'!G8 -> 5 | H21: ='Input Actual2024-25'!H8 -> 0 | I21: ='Input Actual2024-25'!I8 -> 3 | J21: ='Input Actual2024-25'!J8 -> 0 | K21: ='Input Actual2024-25'!K8 -> 1 | L21: ='Input Actual2024-25'!L8 -> 4 | ... P21: ='Input Actual2024-25'!P8 -> 0 | Q21: =SUM(E21:P21) -> 22
D22: Difference | E22: =IF(E20=0,0,E20-E19) -> 0 | F22: =IF(F20=0,0,F20-F19) -> 0 | G22: =IF(G20=0,0,G20-G19) -> 1 | H22: =IF(H20=0,0,H20-H19) -> -3 | I22: =IF(I20=0,0,I20-I19) -> -2 | J22: =IF(J20=0,0,J20-J19) -> 0 | K22: =IF(K20=0,0,K20-K19) -> -2 | L22: =IF(L20=0,0,L20-L19) -> 0 | ... P22: =IF(P20=0,0,P20-P19) -> 0 | Q22: =SUM(E22:P22) -> -6
D23: Realisation | E23: =E21/E19 -> 0.25 | F23: =F20/F19 -> 0 | G23: =G20/G19 -> 1.25 | H23: =H20/H19 -> 0.25 | I23: =I20/I19 -> 0.5 | J23: =J20/J19 -> 0 | K23: =K20/K19 -> 0.5 | L23: =L20/L19 -> 0 | M23: =M20/M19 -> 0 | ... P23: =P20/P19 -> 0
C25: CUMULATIVE | E25: =E18 -> 45839 | F25: =F18 -> 45870 | G25: =G18 -> 45901 | H25: =H18 -> 45931 | I25: =I18 -> 45962 | J25: =J18 -> 45992 | K25: =K18 -> 46023 | L25: =L18 -> 46054 | ... P25: =P18 -> 46174
D26: =D19 -> Budget 2025-26 | E26: =SUM($E19:E19) -> 4 | F26: =SUM($E19:F19) -> 8 | G26: =SUM($E19:G19) -> 12 | H26: =SUM($E19:H19) -> 16 | I26: =SUM($E19:I19) -> 20 | J26: =SUM($E19:J19) -> 24 | K26: =SUM($E19:K19) -> 28 | L26: =SUM($E19:L19) -> 32 | ... P26: =SUM($E19:P19) -> 48
D27: =D20 -> Actual 2025-26 | E27: =SUM($E20:E20) -> 0 | F27: =SUM($E20:F20) -> 0 | G27: =SUM($E20:G20) -> 5 | H27: =SUM($E20:H20) -> 6 | I27: =SUM($E20:I20) -> 8 | J27: =SUM($E20:J20) -> 8 | K27: =SUM($E20:K20) -> 10 | L27: =SUM($E20:L20) -> 10 | ... P27: =SUM($E20:P20) -> 10
D28: =D21 -> Actual 2024-25 | E28: =SUM($E21:E21) -> 1 | F28: =SUM($E21:F21) -> 5 | G28: =SUM($E21:G21) -> 10 | H28: =SUM($E21:H21) -> 10 | I28: =SUM($E21:I21) -> 13 | J28: =SUM($E21:J21) -> 13 | K28: =SUM($E21:K21) -> 14 | L28: =SUM($E21:L21) -> 18 | ... P28: =SUM($E21:P21) -> 22
D29: =D22 -> Difference | E29: =SUM($E22:E22) -> 0 | F29: =SUM($E22:F22) -> 0 | G29: =SUM($E22:G22) -> 1 | H29: =SUM($E22:H22) -> -2 | I29: =SUM($E22:I22) -> -4 | J29: =SUM($E22:J22) -> -4 | K29: =SUM($E22:K22) -> -6 | L29: =SUM($E22:L22) -> -6 | ... P29: =SUM($E22:P22) -> -6
D30: =D23 -> Realisation | E30: =E28/E26 -> 0.25 | F30: =F27/F26 -> 0 | G30: =G27/G26 -> 0.41666667 | H30: =H27/H26 -> 0.375 | I30: =I27/I26 -> 0.4 | J30: =J27/J26 -> 0.33333333 | K30: =K27/K26 -> 0.35714286 | L30: =L27/L26 -> 0.3125 | M30: =M27/M26 -> 0.27777778 | ... P30: =P27/P26 -> 0.20833333

Sheet KPI 4
A1: KPI | B1: =Dashboard!A9 -> 4 | C1: =Dashboard!B9 -> SITE- NEW WATER | G1: Actual month: | I1: =INDEX($E$18:$P$18,Actual_month) -> 46054 | L1: Dashboard
A2: Unit | C2: Ksh.
C3: l | J3: Comments
C4: l | R4: actual | S4: =INDEX(E27:P27,Actual_month) -> 7
C5: l | R5: target | S5: =INDEX(E26:P26,Actual_month) -> 8
R6: 0.9 | S6: =+S5*R6 -> 7.2
J9: Actions
C18: MONTHLY | E18: ='KPI 1'!E18 -> 45839 | F18: ='KPI 1'!F18 -> 45870 | G18: ='KPI 1'!G18 -> 45901 | H18: ='KPI 1'!H18 -> 45931 | I18: ='KPI 1'!I18 -> 45962 | J18: ='KPI 1'!J18 -> 45992 | K18: ='KPI 1'!K18 -> 46023 | L18: ='KPI 1'!L18 -> 46054 | ... P18: ='KPI 1'!P18 -> 46174 | Q18: Total
D19: ='KPI 1'!D19 -> Budget 2025-26 | E19: ='budget 2025-26'!D9 -> 1 | F19: ='budget 2025-26'!E9 -> 1 | G19: ='budget 2025-26'!F9 -> 1 | H19: ='budget 2025-26'!G9 -> 1 | I19: ='budget 2025-26'!H9 -> 1 | J19: ='budget 2025-26'!I9 -> 1 | K19: ='budget 2025-26'!J9 -> 1 | L19: ='budget 2025-26'!K9 -> 1 | ... P19: ='budget 2025-26'!O9 -> 1 | Q19: =SUM(E19:P19) -> 12
D20: ='KPI 1'!D20 -> Actual 2025-26 | E20: ='Input Actual2025-26'!E9 -> 0 | F20: ='Input Actual2025-26'!F9 -> 2 | G20: ='Input Actual2025-26'!G9 -> 0 | H20: ='Input Actual2025-26'!H9 -> 3 | I20: ='Input Actual2025-26'!I9 -> 0 | J20: ='Input Actual2025-26'!J9 -> 0 | K20: ='Input Actual2025-26'!K9 -> 2 | L20: ='Input Actual2025-26'!L9 -> 0 | ... P20: ='Input Actual2025-26'!P9 -> 0 | Q20: =SUM(E20:P20) -> 7
D21: Actual 2024-25 | E21: ='Input Actual2024-25'!E9 -> 1 | F21: ='Input Actual2024-25'!F9 -> 0 | G21: ='Input Actual2024-25'!G9 -> 0 | H21: ='Input Actual2024-25'!H9 -> 0 | I21: ='Input Actual2024-25'!I9 -> 0 | J21: ='Input Actual2024-25'!J9 -> 0 | K21: ='Input Actual2024-25'!K9 -> 1 | L21: ='Input Actual2024-25'!L9 -> 0 | ... P21: ='Input Actual2024-25'!P9 -> 2 | Q21: =SUM(E21:P21) -> 4
D22: Difference | E22: =IF(E20=0,0,E20-E19) -> 0 | F22: =IF(F20=0,0,F20-F19) -> 1 | G22: =IF(G20=0,0,G20-G19) -> 0 | H22: =IF(H20=0,0,H20-H19) -> 2 | I22: =IF(I20=0,0,I20-I19) -> 0 | J22: =IF(J20=0,0,J20-J19) -> 0 | K22: =IF(K20=0,0,K20-K19) -> 1 | L22: =IF(L20=0,0,L20-L19) -> 0 | ... P22: =IF(P20=0,0,P20-P19) -> 0 | Q22: =SUM(E22:P22) -> 4
D23: Realisation | E23: =E21/E19 -> 1 | F23: =F20/F19 -> 2 | G23: =G20/G19 -> 0 | H23: =H20/H19 -> 3 | I23: =I20/I19 -> 0 | J23: =J20/J19 -> 0 | K23: =K20/K19 -> 2 | L23: =L20/L19 -> 0 | M23: =M20/M19 -> 0 | ... P23: =P20/P19 -> 0
C25: CUMULATIVE | E25: =E18 -> 45839 | F25: =F18 -> 45870 | G25: =G18 -> 45901 | H25: =H18 -> 45931 | I25: =I18 -> 45962 | J25: =J18 -> 45992 | K25: =K18 -> 46023 | L25: =L18 -> 46054 | ... P25: =P18 -> 46174
D26: =D19 -> Budget 2025-26 | E26: =SUM($E19:E19) -> 1 | F26: =SUM($E19:F19) -> 2 | G26: =SUM($E19:G19) -> 3 | H26: =SUM($E19:H19) -> 4 | I26: =SUM($E19:I19) -> 5 | J26: =SUM($E19:J19) -> 6 | K26: =SUM($E19:K19) -> 7 | L26: =SUM($E19:L19) -> 8 | ... P26: =SUM($E19:P19) -> 12
D27: =D20 -> Actual 2025-26 | E27: =SUM($E20:E20) -> 0 | F27: =SUM($E20:F20) -> 2 | G27: =SUM($E20:G20) -> 2 | H27: =SUM($E20:H20) -> 5 | I27: =SUM($E20:I20) -> 5 | J27: =SUM($E20:J20) -> 5 | K27: =SUM($E20:K20) -> 7 | L27: =SUM($E20:L20) -> 7 | ... P27: =SUM($E20:P20) -> 7
D28: =D21 -> Actual 2024-25 | E28: =SUM($E21:E21) -> 1 | F28: =SUM($E21:F21) -> 1 | G28: =SUM($E21:G21) -> 1 | H28: =SUM($E21:H21) -> 1 | I28: =SUM($E21:I21) -> 1 | J28: =SUM($E21:J21) -> 1 | K28: =SUM($E21:K21) -> 2 | L28: =SUM($E21:L21) -> 2 | ... P28: =SUM($E21:P21) -> 4
D29: =D22 -> Difference | E29: =SUM($E22:E22) -> 0 | F29: =SUM($E22:F22) -> 1 | G29: =SUM($E22:G22) -> 1 | H29: =SUM($E22:H22) -> 3 | I29: =SUM($E22:I22) -> 3 | J29: =SUM($E22:J22) -> 3 | K29: =SUM($E22:K22) -> 4 | L29: =SUM($E22:L22) -> 4 | ... P29: =SUM($E22:P22) -> 4
D30: =D23 -> Realisation | E30: =E28/E26 -> 1 | F30: =F27/F26 -> 1 | G30: =G27/G26 -> 0.66666667 | H30: =H27/H26 -> 1.25 | I30: =I27/I26 -> 1 | J30: =J27/J26 -> 0.83333333 | K30: =K27/K26 -> 1 | L30: =L27/L26 -> 0.875 | M30: =M27/M26 -> 0.77777778 | ... P30: =P27/P26 -> 0.58333333

Sheet KPI 5
A1: KPI | B1: =Dashboard!A10 -> 5 | C1: =Dashboard!B10 -> KIHOTO- NEW WATER | G1: Actual month: | I1: =INDEX($E$18:$P$18,Actual_month) -> 46054 | L1: Dashboard
A2: Unit | C2: Ksh.
C3: l | J3: Comments
C4: l | R4: actual | S4: =INDEX(E27:P27,Actual_month) -> 3
C5: l | R5: target | S5: =INDEX(E26:P26,Actual_month) -> 8
R6: 0.9 | S6: =+S5*R6 -> 7.2
J9: Actions
C18: MONTHLY | E18: ='KPI 1'!E18 -> 45839 | F18: ='KPI 1'!F18 -> 45870 | G18: ='KPI 1'!G18 -> 45901 | H18: ='KPI 1'!H18 -> 45931 | I18: ='KPI 1'!I18 -> 45962 | J18: ='KPI 1'!J18 -> 45992 | K18: ='KPI 1'!K18 -> 46023 | L18: ='KPI 1'!L18 -> 46054 | ... P18: ='KPI 1'!P18 -> 46174 | Q18: Total
